Workbook

Sheet For WH
A1: SKU | B1: ASIN | C1: FNSKU | D1: Item # | E1: Total EA (Transfer to WH06) | F1: Sellable Unit/Set/box to ship | G1: Box to pull | H1: Case to pull | I1: Sets per Box/Case | J1: Label | K1: Packing Instructions | L1: Supplies | M1: UoM | N1: BOX | O1: CASE | P1: Recommended Replenishment Qty | Q1: Current WH Inventory
D2: =VLOOKUP(Table1[[#This Row],[SKU]],Data1!A:B,2,0) -> #N/A | E2: =Table1[[#This Row],[UoM]]*Table1[[#This Row],[Recommended Replenishment Qty]] -> #N/A | F2: =Table1[[#This Row],[Total EA (Transfer to WH06)]]/Table1[[#This Row],[UoM]] -> #N/A | G2: =Table1[[#This Row],[Total EA (Transfer to WH06)]]/Table1[[#This Row],[BOX]] -> #N/A | H2: =Table1[[#This Row],[Total EA (Transfer to WH06)]]/Table1[[#This Row],[CASE]] -> #N/A | I2: =Table1[[#This Row],[Sellable Unit/Set/box to ship]]/Table1[[#This Row],[Case to pull]] -> #N/A | J2: =IF(ISNUMBER(SEARCH("FNSKU",K2)),"Labeling","") | K2: =VLOOKUP(Table1[[#This Row],[SKU]],Instruction!A:F,6,0) -> #N/A | L2: =VLOOKUP(Table1[[#This Row],[ASIN]],'[1]2024'!$A:$AB,28,0) -> #N/A | M2: =VLOOKUP(Table1[[#This Row],[SKU]],Data1!A:C,3,0) -> #N/A | N2: =VLOOKUP(Table1[[#This Row],[Item '#]],Data2!A:D,4,0) -> #N/A | O2: =VLOOKUP(Table1[[#This Row],[Item '#]],Data2!A:D,3,0) -> #N/A | P2: =VLOOKUP(Table1[[#This Row],[Item '#]],[2]Sheet1!$B:$D,3,0) -> #N/A | Q2: =[8]!Table1[[#This Row],[Current WH Inventory]]=VLOOKUP(Table1[[#This Row],[Item '#]],[2]Sheet1!$B:$D,3,0) -> #REF!
D3: =VLOOKUP(Table1[[#This Row],[SKU]],Data1!A:B,2,0) -> #N/A | E3: =Table1[[#This Row],[UoM]]*Table1[[#This Row],[Recommended Replenishment Qty]] -> #N/A | F3: =Table1[[#This Row],[Total EA (Transfer to WH06)]]/Table1[[#This Row],[UoM]] -> #N/A | G3: =Table1[[#This Row],[Total EA (Transfer to WH06)]]/Table1[[#This Row],[BOX]] -> #N/A | H3: =Table1[[#This Row],[Total EA (Transfer to WH06)]]/Table1[[#This Row],[CASE]] -> #N/A | I3: =Table1[[#This Row],[Sellable Unit/Set/box to ship]]/Table1[[#This Row],[Case to pull]] -> #N/A | J3: =IF(ISNUMBER(SEARCH("FNSKU",K3)),"Labeling","") | K3: =VLOOKUP(Table1[[#This Row],[SKU]],Instruction!A:F,6,0) -> #N/A | L3: =VLOOKUP(Table1[[#This Row],[ASIN]],'[1]2024'!$A:$AB,28,0) -> #N/A | M3: =VLOOKUP(Table1[[#This Row],[SKU]],Data1!A:C,3,0) -> #N/A | N3: =VLOOKUP(Table1[[#This Row],[Item '#]],Data2!A:D,4,0) -> #N/A | O3: =VLOOKUP(Table1[[#This Row],[Item '#]],Data2!A:D,3,0) -> #N/A | P3: =VLOOKUP(Table1[[#This Row],[Item '#]],[2]Sheet1!$B:$D,3,0) -> #N/A | Q3: =[8]!Table1[[#This Row],[Current WH Inventory]]=VLOOKUP(Table1[[#This Row],[Item '#]],[2]Sheet1!$B:$D,3,0) -> #REF!
D4: =VLOOKUP(Table1[[#This Row],[SKU]],Data1!A:B,2,0) -> #N/A | E4: =Table1[[#This Row],[UoM]]*Table1[[#This Row],[Recommended Replenishment Qty]] -> #N/A | F4: =Table1[[#This Row],[Total EA (Transfer to WH06)]]/Table1[[#This Row],[UoM]] -> #N/A | G4: =Table1[[#This Row],[Total EA (Transfer to WH06)]]/Table1[[#This Row],[BOX]] -> #N/A | H4: =Table1[[#This Row],[Total EA (Transfer to WH06)]]/Table1[[#This Row],[CASE]] -> #N/A | I4: =Table1[[#This Row],[Sellable Unit/Set/box to ship]]/Table1[[#This Row],[Case to pull]] -> #N/A | J4: =IF(ISNUMBER(SEARCH("FNSKU",K4)),"Labeling","") | K4: =VLOOKUP(Table1[[#This Row],[SKU]],Instruction!A:F,6,0) -> #N/A | L4: =VLOOKUP(Table1[[#This Row],[ASIN]],'[1]2024'!$A:$AB,28,0) -> #N/A | M4: =VLOOKUP(Table1[[#This Row],[SKU]],Data1!A:C,3,0) -> #N/A | N4: =VLOOKUP(Table1[[#This Row],[Item '#]],Data2!A:D,4,0) -> #N/A | O4: =VLOOKUP(Table1[[#This Row],[Item '#]],Data2!A:D,3,0) -> #N/A | P4: =VLOOKUP(Table1[[#This Row],[Item '#]],[2]Sheet1!$B:$D,3,0) -> #N/A | Q4: =[8]!Table1[[#This Row],[Current WH Inventory]]=VLOOKUP(Table1[[#This Row],[Item '#]],[2]Sheet1!$B:$D,3,0) -> #REF!
D5: =VLOOKUP(Table1[[#This Row],[SKU]],Data1!A:B,2,0) -> #N/A | E5: =Table1[[#This Row],[UoM]]*Table1[[#This Row],[Recommended Replenishment Qty]] -> #N/A | F5: =Table1[[#This Row],[Total EA (Transfer to WH06)]]/Table1[[#This Row],[UoM]] -> #N/A | G5: =Table1[[#This Row],[Total EA (Transfer to WH06)]]/Table1[[#This Row],[BOX]] -> #N/A | H5: =Table1[[#This Row],[Total EA (Transfer to WH06)]]/Table1[[#This Row],[CASE]] -> #N/A | I5: =Table1[[#This Row],[Sellable Unit/Set/box to ship]]/Table1[[#This Row],[Case to pull]] -> #N/A | J5: =IF(ISNUMBER(SEARCH("FNSKU",K5)),"Labeling","") | K5: =VLOOKUP(Table1[[#This Row],[SKU]],Instruction!A:F,6,0) -> #N/A | L5: =VLOOKUP(Table1[[#This Row],[ASIN]],'[1]2024'!$A:$AB,28,0) -> #N/A | M5: =VLOOKUP(Table1[[#This Row],[SKU]],Data1!A:C,3,0) -> #N/A | N5: =VLOOKUP(Table1[[#This Row],[Item '#]],Data2!A:D,4,0) -> #N/A | O5: =VLOOKUP(Table1[[#This Row],[Item '#]],Data2!A:D,3,0) -> #N/A | P5: =VLOOKUP(Table1[[#This Row],[Item '#]],[2]Sheet1!$B:$D,3,0) -> #N/A | Q5: =[8]!Table1[[#This Row],[Current WH Inventory]]=VLOOKUP(Table1[[#This Row],[Item '#]],[2]Sheet1!$B:$D,3,0) -> #REF!
D6: =VLOOKUP(Table1[[#This Row],[SKU]],Data1!A:B,2,0) -> #N/A | E6: =Table1[[#This Row],[UoM]]*Table1[[#This Row],[Recommended Replenishment Qty]] -> #N/A | F6: =Table1[[#This Row],[Total EA (Transfer to WH06)]]/Table1[[#This Row],[UoM]] -> #N/A | G6: =Table1[[#This Row],[Total EA (Transfer to WH06)]]/Table1[[#This Row],[BOX]] -> #N/A | H6: =Table1[[#This Row],[Total EA (Transfer to WH06)]]/Table1[[#This Row],[CASE]] -> #N/A | I6: =Table1[[#This Row],[Sellable Unit/Set/box to ship]]/Table1[[#This Row],[Case to pull]] -> #N/A | J6: =IF(ISNUMBER(SEARCH("FNSKU",K6)),"Labeling","") | K6: =VLOOKUP(Table1[[#This Row],[SKU]],Instruction!A:F,6,0) -> #N/A | L6: =VLOOKUP(Table1[[#This Row],[ASIN]],'[1]2024'!$A:$AB,28,0) -> #N/A | M6: =VLOOKUP(Table1[[#This Row],[SKU]],Data1!A:C,3,0) -> #N/A | N6: =VLOOKUP(Table1[[#This Row],[Item '#]],Data2!A:D,4,0) -> #N/A | O6: =VLOOKUP(Table1[[#This Row],[Item '#]],Data2!A:D,3,0) -> #N/A | P6: =VLOOKUP(Table1[[#This Row],[Item '#]],[2]Sheet1!$B:$D,3,0) -> #N/A | Q6: =[8]!Table1[[#This Row],[Current WH Inventory]]=VLOOKUP(Table1[[#This Row],[Item '#]],[2]Sheet1!$B:$D,3,0) -> #REF!
D7: =VLOOKUP(Table1[[#This Row],[SKU]],Data1!A:B,2,0) -> #N/A | E7: =Table1[[#This Row],[UoM]]*Table1[[#This Row],[Recommended Replenishment Qty]] -> #N/A | F7: =Table1[[#This Row],[Total EA (Transfer to WH06)]]/Table1[[#This Row],[UoM]] -> #N/A | G7: =Table1[[#This Row],[Total EA (Transfer to WH06)]]/Table1[[#This Row],[BOX]] -> #N/A | H7: =Table1[[#This Row],[Total EA (Transfer to WH06)]]/Table1[[#This Row],[CASE]] -> #N/A | I7: =Table1[[#This Row],[Sellable Unit/Set/box to ship]]/Table1[[#This Row],[Case to pull]] -> #N/A | J7: =IF(ISNUMBER(SEARCH("FNSKU",K7)),"Labeling","") | K7: =VLOOKUP(Table1[[#This Row],[SKU]],Instruction!A:F,6,0) -> #N/A | L7: =VLOOKUP(Table1[[#This Row],[ASIN]],'[1]2024'!$A:$AB,28,0) -> #N/A | M7: =VLOOKUP(Table1[[#This Row],[SKU]],Data1!A:C,3,0) -> #N/A | N7: =VLOOKUP(Table1[[#This Row],[Item '#]],Data2!A:D,4,0) -> #N/A | O7: =VLOOKUP(Table1[[#This Row],[Item '#]],Data2!A:D,3,0) -> #N/A | P7: =VLOOKUP(Table1[[#This Row],[Item '#]],[2]Sheet1!$B:$D,3,0) -> #N/A | Q7: =[8]!Table1[[#This Row],[Current WH Inventory]]=VLOOKUP(Table1[[#This Row],[Item '#]],[2]Sheet1!$B:$D,3,0) -> #REF!
D8: =VLOOKUP(Table1[[#This Row],[SKU]],Data1!A:B,2,0) -> #N/A | E8: =Table1[[#This Row],[UoM]]*Table1[[#This Row],[Recommended Replenishment Qty]] -> #N/A | F8: =Table1[[#This Row],[Total EA (Transfer to WH06)]]/Table1[[#This Row],[UoM]] -> #N/A | G8: =Table1[[#This Row],[Total EA (Transfer to WH06)]]/Table1[[#This Row],[BOX]] -> #N/A | H8: =Table1[[#This Row],[Total EA (Transfer to WH06)]]/Table1[[#This Row],[CASE]] -> #N/A | I8: =Table1[[#This Row],[Sellable Unit/Set/box to ship]]/Table1[[#This Row],[Case to pull]] -> #N/A | J8: =IF(ISNUMBER(SEARCH("FNSKU",K8)),"Labeling","") | K8: =VLOOKUP(Table1[[#This Row],[SKU]],Instruction!A:F,6,0) -> #N/A | L8: =VLOOKUP(Table1[[#This Row],[ASIN]],'[1]2024'!$A:$AB,28,0) -> #N/A | M8: =VLOOKUP(Table1[[#This Row],[SKU]],Data1!A:C,3,0) -> #N/A | N8: =VLOOKUP(Table1[[#This Row],[Item '#]],Data2!A:D,4,0) -> #N/A | O8: =VLOOKUP(Table1[[#This Row],[Item '#]],Data2!A:D,3,0) -> #N/A | P8: =VLOOKUP(Table1[[#This Row],[Item '#]],[2]Sheet1!$B:$D,3,0) -> #N/A | Q8: =[8]!Table1[[#This Row],[Current WH Inventory]]=VLOOKUP(Table1[[#This Row],[Item '#]],[2]Sheet1!$B:$D,3,0) -> #REF!
D9: =VLOOKUP(Table1[[#This Row],[SKU]],Data1!A:B,2,0) -> #N/A | E9: =Table1[[#This Row],[UoM]]*Table1[[#This Row],[Recommended Replenishment Qty]] -> #N/A | F9: =Table1[[#This Row],[Total EA (Transfer to WH06)]]/Table1[[#This Row],[UoM]] -> #N/A | G9: =Table1[[#This Row],[Total EA (Transfer to WH06)]]/Table1[[#This Row],[BOX]] -> #N/A | H9: =Table1[[#This Row],[Total EA (Transfer to WH06)]]/Table1[[#This Row],[CASE]] -> #N/A | I9: =Table1[[#This Row],[Sellable Unit/Set/box to ship]]/Table1[[#This Row],[Case to pull]] -> #N/A | J9: =IF(ISNUMBER(SEARCH("FNSKU",K9)),"Labeling","") | K9: =VLOOKUP(Table1[[#This Row],[SKU]],Instruction!A:F,6,0) -> #N/A | L9: =VLOOKUP(Table1[[#This Row],[ASIN]],'[1]2024'!$A:$AB,28,0) -> #N/A | M9: =VLOOKUP(Table1[[#This Row],[SKU]],Data1!A:C,3,0) -> #N/A | N9: =VLOOKUP(Table1[[#This Row],[Item '#]],Data2!A:D,4,0) -> #N/A | O9: =VLOOKUP(Table1[[#This Row],[Item '#]],Data2!A:D,3,0) -> #N/A | P9: =VLOOKUP(Table1[[#This Row],[Item '#]],[2]Sheet1!$B:$D,3,0) -> #N/A | Q9: =[8]!Table1[[#This Row],[Current WH Inventory]]=VLOOKUP(Table1[[#This Row],[Item '#]],[2]Sheet1!$B:$D,3,0) -> #REF!
D10: =VLOOKUP(Table1[[#This Row],[SKU]],Data1!A:B,2,0) -> #N/A | E10: =Table1[[#This Row],[UoM]]*Table1[[#This Row],[Recommended Replenishment Qty]] -> #N/A | F10: =Table1[[#This Row],[Total EA (Transfer to WH06)]]/Table1[[#This Row],[UoM]] -> #N/A | G10: =Table1[[#This Row],[Total EA (Transfer to WH06)]]/Table1[[#This Row],[BOX]] -> #N/A | H10: =Table1[[#This Row],[Total EA (Transfer to WH06)]]/Table1[[#This Row],[CASE]] -> #N/A | I10: =Table1[[#This Row],[Sellable Unit/Set/box to ship]]/Table1[[#This Row],[Case to pull]] -> #N/A | J10: =IF(ISNUMBER(SEARCH("FNSKU",K10)),"Labeling","") | K10: =VLOOKUP(Table1[[#This Row],[SKU]],Instruction!A:F,6,0) -> #N/A | L10: =VLOOKUP(Table1[[#This Row],[ASIN]],'[1]2024'!$A:$AB,28,0) -> #N/A | M10: =VLOOKUP(Table1[[#This Row],[SKU]],Data1!A:C,3,0) -> #N/A | N10: =VLOOKUP(Table1[[#This Row],[Item '#]],Data2!A:D,4,0) -> #N/A | O10: =VLOOKUP(Table1[[#This Row],[Item '#]],Data2!A:D,3,0) -> #N/A | P10: =VLOOKUP(Table1[[#This Row],[Item '#]],[2]Sheet1!$B:$D,3,0) -> #N/A | Q10: =[8]!Table1[[#This Row],[Current WH Inventory]]=VLOOKUP(Table1[[#This Row],[Item '#]],[2]Sheet1!$B:$D,3,0) -> #REF!
D11: =VLOOKUP(Table1[[#This Row],[SKU]],Data1!A:B,2,0) -> #N/A | E11: =Table1[[#This Row],[UoM]]*Table1[[#This Row],[Recommended Replenishment Qty]] -> #N/A | F11: =Table1[[#This Row],[Total EA (Transfer to WH06)]]/Table1[[#This Row],[UoM]] -> #N/A | G11: =Table1[[#This Row],[Total EA (Transfer to WH06)]]/Table1[[#This Row],[BOX]] -> #N/A | H11: =Table1[[#This Row],[Total EA (Transfer to WH06)]]/Table1[[#This Row],[CASE]] -> #N/A | I11: =Table1[[#This Row],[Sellable Unit/Set/box to ship]]/Table1[[#This Row],[Case to pull]] -> #N/A | J11: =IF(ISNUMBER(SEARCH("FNSKU",K11)),"Labeling","") | K11: =VLOOKUP(Table1[[#This Row],[SKU]],Instruction!A:F,6,0) -> #N/A | L11: =VLOOKUP(Table1[[#This Row],[ASIN]],'[1]2024'!$A:$AB,28,0) -> #N/A | M11: =VLOOKUP(Table1[[#This Row],[SKU]],Data1!A:C,3,0) -> #N/A | N11: =VLOOKUP(Table1[[#This Row],[Item '#]],Data2!A:D,4,0) -> #N/A | O11: =VLOOKUP(Table1[[#This Row],[Item '#]],Data2!A:D,3,0) -> #N/A | P11: =VLOOKUP(Table1[[#This Row],[Item '#]],[2]Sheet1!$B:$D,3,0) -> #N/A | Q11: =[8]!Table1[[#This Row],[Current WH Inventory]]=VLOOKUP(Table1[[#This Row],[Item '#]],[2]Sheet1!$B:$D,3,0) -> #REF!
D12: =VLOOKUP(Table1[[#This Row],[SKU]],Data1!A:B,2,0) -> #N/A | E12: =Table1[[#This Row],[UoM]]*Table1[[#This Row],[Recommended Replenishment Qty]] -> #N/A | F12: =Table1[[#This Row],[Total EA (Transfer to WH06)]]/Table1[[#This Row],[UoM]] -> #N/A | G12: =Table1[[#This Row],[Total EA (Transfer to WH06)]]/Table1[[#This Row],[BOX]] -> #N/A | H12: =Table1[[#This Row],[Total EA (Transfer to WH06)]]/Table1[[#This Row],[CASE]] -> #N/A | I12: =Table1[[#This Row],[Sellable Unit/Set/box to ship]]/Table1[[#This Row],[Box to pull]] -> #N/A | J12: =IF(ISNUMBER(SEARCH("FNSKU",K12)),"Labeling","") | K12: =VLOOKUP(Table1[[#This Row],[SKU]],Instruction!A:F,6,0) -> #N/A | L12: =VLOOKUP(Table1[[#This Row],[ASIN]],'[1]2024'!$A:$AB,28,0) -> #N/A | M12: =VLOOKUP(Table1[[#This Row],[SKU]],Data1!A:C,3,0) -> #N/A | N12: =VLOOKUP(Table1[[#This Row],[Item '#]],Data2!A:D,4,0) -> #N/A | O12: =VLOOKUP(Table1[[#This Row],[Item '#]],Data2!A:D,3,0) -> #N/A | P12: =VLOOKUP(Table1[[#This Row],[Item '#]],[2]Sheet1!$B:$D,3,0) -> #N/A | Q12: =[8]!Table1[[#This Row],[Current WH Inventory]]=VLOOKUP(Table1[[#This Row],[Item '#]],[2]Sheet1!$B:$D,3,0) -> #REF!
D13: =VLOOKUP(Table1[[#This Row],[SKU]],Data1!A:B,2,0) -> #N/A | E13: =Table1[[#This Row],[UoM]]*Table1[[#This Row],[Recommended Replenishment Qty]] -> #N/A | F13: =Table1[[#This Row],[Total EA (Transfer to WH06)]]/Table1[[#This Row],[UoM]] -> #N/A | G13: =Table1[[#This Row],[Total EA (Transfer to WH06)]]/Table1[[#This Row],[BOX]] -> #N/A | H13: =Table1[[#This Row],[Total EA (Transfer to WH06)]]/Table1[[#This Row],[CASE]] -> #N/A | I13: =Table1[[#This Row],[Sellable Unit/Set/box to ship]]/Table1[[#This Row],[Box to pull]] -> #N/A | J13: =IF(ISNUMBER(SEARCH("FNSKU",K13)),"Labeling","") | K13: =VLOOKUP(Table1[[#This Row],[SKU]],Instruction!A:F,6,0) -> #N/A | L13: =VLOOKUP(Table1[[#This Row],[ASIN]],'[1]2024'!$A:$AB,28,0) -> #N/A | M13: =VLOOKUP(Table1[[#This Row],[SKU]],Data1!A:C,3,0) -> #N/A | N13: =VLOOKUP(Table1[[#This Row],[Item '#]],Data2!A:D,4,0) -> #N/A | O13: =VLOOKUP(Table1[[#This Row],[Item '#]],Data2!A:D,3,0) -> #N/A | P13: =VLOOKUP(Table1[[#This Row],[Item '#]],[2]Sheet1!$B:$D,3,0) -> #N/A | Q13: =[8]!Table1[[#This Row],[Current WH Inventory]]=VLOOKUP(Table1[[#This Row],[Item '#]],[2]Sheet1!$B:$D,3,0) -> #REF!
D14: =VLOOKUP(Table1[[#This Row],[SKU]],Data1!A:B,2,0) -> #N/A | E14: =Table1[[#This Row],[UoM]]*Table1[[#This Row],[Recommended Replenishment Qty]] -> #N/A | F14: =Table1[[#This Row],[Total EA (Transfer to WH06)]]/Table1[[#This Row],[UoM]] -> #N/A | G14: =Table1[[#This Row],[Total EA (Transfer to WH06)]]/Table1[[#This Row],[BOX]] -> #N/A | H14: =Table1[[#This Row],[Total EA (Transfer to WH06)]]/Table1[[#This Row],[CASE]] -> #N/A | I14: =Table1[[#This Row],[Sellable Unit/Set/box to ship]]/Table1[[#This Row],[Case to pull]] -> #N/A | J14: =IF(ISNUMBER(SEARCH("FNSKU",K14)),"Labeling","") | K14: =VLOOKUP(Table1[[#This Row],[SKU]],Instruction!A:F,6,0) -> #N/A | L14: =VLOOKUP(Table1[[#This Row],[ASIN]],'[1]2024'!$A:$AB,28,0) -> #N/A | M14: =VLOOKUP(Table1[[#This Row],[SKU]],Data1!A:C,3,0) -> #N/A | N14: =VLOOKUP(Table1[[#This Row],[Item '#]],Data2!A:D,4,0) -> #N/A | O14: =VLOOKUP(Table1[[#This Row],[Item '#]],Data2!A:D,3,0) -> #N/A | P14: =VLOOKUP(Table1[[#This Row],[Item '#]],[2]Sheet1!$B:$D,3,0) -> #N/A | Q14: =[8]!Table1[[#This Row],[Current WH Inventory]]=VLOOKUP(Table1[[#This Row],[Item '#]],[2]Sheet1!$B:$D,3,0) -> #REF!
D15: =VLOOKUP(Table1[[#This Row],[SKU]],Data1!A:B,2,0) -> #N/A | E15: =Table1[[#This Row],[UoM]]*Table1[[#This Row],[Recommended Replenishment Qty]] -> #N/A | F15: =Table1[[#This Row],[Total EA (Transfer to WH06)]]/Table1[[#This Row],[UoM]] -> #N/A | G15: =Table1[[#This Row],[Total EA (Transfer to WH06)]]/Table1[[#This Row],[BOX]] -> #N/A | H15: =Table1[[#This Row],[Total EA (Transfer to WH06)]]/Table1[[#This Row],[CASE]] -> #N/A | I15: =Table1[[#This Row],[Sellable Unit/Set/box to ship]]/Table1[[#This Row],[Case to pull]] -> #N/A | J15: =IF(ISNUMBER(SEARCH("FNSKU",K15)),"Labeling","") | K15: =VLOOKUP(Table1[[#This Row],[SKU]],Instruction!A:F,6,0) -> #N/A | L15: =VLOOKUP(Table1[[#This Row],[ASIN]],'[1]2024'!$A:$AB,28,0) -> #N/A | M15: =VLOOKUP(Table1[[#This Row],[SKU]],Data1!A:C,3,0) -> #N/A | N15: =VLOOKUP(Table1[[#This Row],[Item '#]],Data2!A:D,4,0) -> #N/A | O15: =VLOOKUP(Table1[[#This Row],[Item '#]],Data2!A:D,3,0) -> #N/A | P15: =VLOOKUP(Table1[[#This Row],[Item '#]],[2]Sheet1!$B:$D,3,0) -> #N/A | Q15: =[8]!Table1[[#This Row],[Current WH Inventory]]=VLOOKUP(Table1[[#This Row],[Item '#]],[2]Sheet1!$B:$D,3,0) -> #REF!
D16: =VLOOKUP(Table1[[#This Row],[SKU]],Data1!A:B,2,0) -> #N/A | E16: =Table1[[#This Row],[UoM]]*Table1[[#This Row],[Recommended Replenishment Qty]] -> #N/A | F16: =Table1[[#This Row],[Total EA (Transfer to WH06)]]/Table1[[#This Row],[UoM]] -> #N/A | G16: =Table1[[#This Row],[Total EA (Transfer to WH06)]]/Table1[[#This Row],[BOX]] -> #N/A | H16: =Table1[[#This Row],[Total EA (Transfer to WH06)]]/Table1[[#This Row],[CASE]] -> #N/A | I16: =Table1[[#This Row],[Sellable Unit/Set/box to ship]]/Table1[[#This Row],[Case to pull]] -> #N/A | J16: =IF(ISNUMBER(SEARCH("FNSKU",K16)),"Labeling","") | K16: =VLOOKUP(Table1[[#This Row],[SKU]],Instruction!A:F,6,0) -> #N/A | L16: =VLOOKUP(Table1[[#This Row],[ASIN]],'[1]2024'!$A:$AB,28,0) -> #N/A | M16: =VLOOKUP(Table1[[#This Row],[SKU]],Data1!A:C,3,0) -> #N/A | N16: =VLOOKUP(Table1[[#This Row],[Item '#]],Data2!A:D,4,0) -> #N/A | O16: =VLOOKUP(Table1[[#This Row],[Item '#]],Data2!A:D,3,0) -> #N/A | P16: =VLOOKUP(Table1[[#This Row],[Item '#]],[2]Sheet1!$B:$D,3,0) -> #N/A | Q16: =[8]!Table1[[#This Row],[Current WH Inventory]]=VLOOKUP(Table1[[#This Row],[Item '#]],[2]Sheet1!$B:$D,3,0) -> #REF!
D17: =VLOOKUP(Table1[[#This Row],[SKU]],Data1!A:B,2,0) -> #N/A | E17: =Table1[[#This Row],[UoM]]*Table1[[#This Row],[Recommended Replenishment Qty]] -> #N/A | F17: =Table1[[#This Row],[Total EA (Transfer to WH06)]]/Table1[[#This Row],[UoM]] -> #N/A | G17: =Table1[[#This Row],[Total EA (Transfer to WH06)]]/Table1[[#This Row],[BOX]] -> #N/A | H17: =Table1[[#This Row],[Total EA (Transfer to WH06)]]/Table1[[#This Row],[CASE]] -> #N/A | I17: =Table1[[#This Row],[Sellable Unit/Set/box to ship]]/Table1[[#This Row],[Case to pull]] -> #N/A | J17: =IF(ISNUMBER(SEARCH("FNSKU",K17)),"Labeling","") | K17: =VLOOKUP(Table1[[#This Row],[SKU]],Instruction!A:F,6,0) -> #N/A | L17: =VLOOKUP(Table1[[#This Row],[ASIN]],'[1]2024'!$A:$AB,28,0) -> #N/A | M17: =VLOOKUP(Table1[[#This Row],[SKU]],Data1!A:C,3,0) -> #N/A | N17: =VLOOKUP(Table1[[#This Row],[Item '#]],Data2!A:D,4,0) -> #N/A | O17: =VLOOKUP(Table1[[#This Row],[Item '#]],Data2!A:D,3,0) -> #N/A | P17: =VLOOKUP(Table1[[#This Row],[Item '#]],[2]Sheet1!$B:$D,3,0) -> #N/A | Q17: =[8]!Table1[[#This Row],[Current WH Inventory]]=VLOOKUP(Table1[[#This Row],[Item '#]],[2]Sheet1!$B:$D,3,0) -> #REF!
D18: =VLOOKUP(Table1[[#This Row],[SKU]],Data1!A:B,2,0) -> #N/A | E18: =Table1[[#This Row],[UoM]]*Table1[[#This Row],[Recommended Replenishment Qty]] -> #N/A | F18: =Table1[[#This Row],[Total EA (Transfer to WH06)]]/Table1[[#This Row],[UoM]] -> #N/A | G18: =Table1[[#This Row],[Total EA (Transfer to WH06)]]/Table1[[#This Row],[BOX]] -> #N/A | H18: =Table1[[#This Row],[Total EA (Transfer to WH06)]]/Table1[[#This Row],[CASE]] -> #N/A | I18: =Table1[[#This Row],[Sellable Unit/Set/box to ship]]/Table1[[#This Row],[Case to pull]] -> #N/A | J18: =IF(ISNUMBER(SEARCH("FNSKU",K18)),"Labeling","") | K18: =VLOOKUP(Table1[[#This Row],[SKU]],Instruction!A:F,6,0) -> #N/A | L18: =VLOOKUP(Table1[[#This Row],[ASIN]],'[1]2024'!$A:$AB,28,0) -> #N/A | M18: =VLOOKUP(Table1[[#This Row],[SKU]],Data1!A:C,3,0) -> #N/A | N18: =VLOOKUP(Table1[[#This Row],[Item '#]],Data2!A:D,4,0) -> #N/A | O18: =VLOOKUP(Table1[[#This Row],[Item '#]],Data2!A:D,3,0) -> #N/A | P18: =VLOOKUP(Table1[[#This Row],[Item '#]],[2]Sheet1!$B:$D,3,0) -> #N/A | Q18: =[8]!Table1[[#This Row],[Current WH Inventory]]=VLOOKUP(Table1[[#This Row],[Item '#]],[2]Sheet1!$B:$D,3,0) -> #REF!
D19: =VLOOKUP(Table1[[#This Row],[SKU]],Data1!A:B,2,0) -> #N/A | E19: =Table1[[#This Row],[UoM]]*Table1[[#This Row],[Recommended Replenishment Qty]] -> #N/A | F19: =Table1[[#This Row],[Total EA (Transfer to WH06)]]/Table1[[#This Row],[UoM]] -> #N/A | G19: =Table1[[#This Row],[Total EA (Transfer to WH06)]]/Table1[[#This Row],[BOX]] -> #N/A | H19: =Table1[[#This Row],[Total EA (Transfer to WH06)]]/Table1[[#This Row],[CASE]] -> #N/A | I19: =Table1[[#This Row],[Sellable Unit/Set/box to ship]]/Table1[[#This Row],[Case to pull]] -> #N/A | J19: =IF(ISNUMBER(SEARCH("FNSKU",K19)),"Labeling","") | K19: =VLOOKUP(Table1[[#This Row],[SKU]],Instruction!A:F,6,0) -> #N/A | L19: =VLOOKUP(Table1[[#This Row],[ASIN]],'[1]2024'!$A:$AB,28,0) -> #N/A | M19: =VLOOKUP(Table1[[#This Row],[SKU]],Data1!A:C,3,0) -> #N/A | N19: =VLOOKUP(Table1[[#This Row],[Item '#]],Data2!A:D,4,0) -> #N/A | O19: =VLOOKUP(Table1[[#This Row],[Item '#]],Data2!A:D,3,0) -> #N/A | P19: =VLOOKUP(Table1[[#This Row],[Item '#]],[2]Sheet1!$B:$D,3,0) -> #N/A | Q19: =[8]!Table1[[#This Row],[Current WH Inventory]]=VLOOKUP(Table1[[#This Row],[Item '#]],[2]Sheet1!$B:$D,3,0) -> #REF!
D20: =VLOOKUP(Table1[[#This Row],[SKU]],Data1!A:B,2,0) -> #N/A | E20: =Table1[[#This Row],[UoM]]*Table1[[#This Row],[Recommended Replenishment Qty]] -> #N/A | F20: =Table1[[#This Row],[Total EA (Transfer to WH06)]]/Table1[[#This Row],[UoM]] -> #N/A | G20: =Table1[[#This Row],[Total EA (Transfer to WH06)]]/Table1[[#This Row],[BOX]] -> #N/A | H20: =Table1[[#This Row],[Total EA (Transfer to WH06)]]/Table1[[#This Row],[CASE]] -> #N/A | I20: =Table1[[#This Row],[Sellable Unit/Set/box to ship]]/Table1[[#This Row],[Case to pull]] -> #N/A | J20: =IF(ISNUMBER(SEARCH("FNSKU",K20)),"Labeling","") | K20: =VLOOKUP(Table1[[#This Row],[SKU]],Instruction!A:F,6,0) -> #N/A | L20: =VLOOKUP(Table1[[#This Row],[ASIN]],'[1]2024'!$A:$AB,28,0) -> #N/A | M20: =VLOOKUP(Table1[[#This Row],[SKU]],Data1!A:C,3,0) -> #N/A | N20: =VLOOKUP(Table1[[#This Row],[Item '#]],Data2!A:D,4,0) -> #N/A | O20: =VLOOKUP(Table1[[#This Row],[Item '#]],Data2!A:D,3,0) -> #N/A | P20: =VLOOKUP(Table1[[#This Row],[Item '#]],[2]Sheet1!$B:$D,3,0) -> #N/A | Q20: =[8]!Table1[[#This Row],[Current WH Inventory]]=VLOOKUP(Table1[[#This Row],[Item '#]],[2]Sheet1!$B:$D,3,0) -> #REF!
D21: =VLOOKUP(Table1[[#This Row],[SKU]],Data1!A:B,2,0) -> #N/A | E21: =Table1[[#This Row],[UoM]]*Table1[[#This Row],[Recommended Replenishment Qty]] -> #N/A | F21: =Table1[[#This Row],[Total EA (Transfer to WH06)]]/Table1[[#This Row],[UoM]] -> #N/A | G21: =Table1[[#This Row],[Total EA (Transfer to WH06)]]/Table1[[#This Row],[BOX]] -> #N/A | H21: =Table1[[#This Row],[Total EA (Transfer to WH06)]]/Table1[[#This Row],[CASE]] -> #N/A | I21: =Table1[[#This Row],[Sellable Unit/Set/box to ship]]/Table1[[#This Row],[Case to pull]] -> #N/A | J21: =IF(ISNUMBER(SEARCH("FNSKU",K21)),"Labeling","") | K21: =VLOOKUP(Table1[[#This Row],[SKU]],Instruction!A:F,6,0) -> #N/A | L21: =VLOOKUP(Table1[[#This Row],[ASIN]],'[1]2024'!$A:$AB,28,0) -> #N/A | M21: =VLOOKUP(Table1[[#This Row],[SKU]],Data1!A:C,3,0) -> #N/A | N21: =VLOOKUP(Table1[[#This Row],[Item '#]],Data2!A:D,4,0) -> #N/A | O21: =VLOOKUP(Table1[[#This Row],[Item '#]],Data2!A:D,3,0) -> #N/A | P21: =VLOOKUP(Table1[[#This Row],[Item '#]],[2]Sheet1!$B:$D,3,0) -> #N/A | Q21: =[8]!Table1[[#This Row],[Current WH Inventory]]=VLOOKUP(Table1[[#This Row],[Item '#]],[2]Sheet1!$B:$D,3,0) -> #REF!
D22: =VLOOKUP(Table1[[#This Row],[SKU]],Data1!A:B,2,0) -> #N/A | E22: =Table1[[#This Row],[UoM]]*Table1[[#This Row],[Recommended Replenishment Qty]] -> #N/A | F22: =Table1[[#This Row],[Total EA (Transfer to WH06)]]/Table1[[#This Row],[UoM]] -> #N/A | G22: =Table1[[#This Row],[Total EA (Transfer to WH06)]]/Table1[[#This Row],[BOX]] -> #N/A | H22: =Table1[[#This Row],[Total EA (Transfer to WH06)]]/Table1[[#This Row],[CASE]] -> #N/A | I22: =Table1[[#This Row],[Sellable Unit/Set/box to ship]]/Table1[[#This Row],[Case to pull]] -> #N/A | J22: =IF(ISNUMBER(SEARCH("FNSKU",K22)),"Labeling","") | K22: =VLOOKUP(Table1[[#This Row],[SKU]],Instruction!A:F,6,0) -> #N/A | L22: =VLOOKUP(Table1[[#This Row],[ASIN]],'[1]2024'!$A:$AB,28,0) -> #N/A | M22: =VLOOKUP(Table1[[#This Row],[SKU]],Data1!A:C,3,0) -> #N/A | N22: =VLOOKUP(Table1[[#This Row],[Item '#]],Data2!A:D,4,0) -> #N/A | O22: =VLOOKUP(Table1[[#This Row],[Item '#]],Data2!A:D,3,0) -> #N/A | P22: =VLOOKUP(Table1[[#This Row],[Item '#]],[2]Sheet1!$B:$D,3,0) -> #N/A | Q22: =[8]!Table1[[#This Row],[Current WH Inventory]]=VLOOKUP(Table1[[#This Row],[Item '#]],[2]Sheet1!$B:$D,3,0) -> #REF!
D23: =VLOOKUP(Table1[[#This Row],[SKU]],Data1!A:B,2,0) -> #N/A | E23: =Table1[[#This Row],[UoM]]*Table1[[#This Row],[Recommended Replenishment Qty]] -> #N/A | F23: =Table1[[#This Row],[Total EA (Transfer to WH06)]]/Table1[[#This Row],[UoM]] -> #N/A | G23: =Table1[[#This Row],[Total EA (Transfer to WH06)]]/Table1[[#This Row],[BOX]] -> #N/A | H23: =Table1[[#This Row],[Total EA (Transfer to WH06)]]/Table1[[#This Row],[CASE]] -> #N/A | I23: =Table1[[#This Row],[Sellable Unit/Set/box to ship]]/Table1[[#This Row],[Case to pull]] -> #N/A | J23: =IF(ISNUMBER(SEARCH("FNSKU",K23)),"Labeling","") | K23: =VLOOKUP(Table1[[#This Row],[SKU]],Instruction!A:F,6,0) -> #N/A | L23: =VLOOKUP(Table1[[#This Row],[ASIN]],'[1]2024'!$A:$AB,28,0) -> #N/A | M23: =VLOOKUP(Table1[[#This Row],[SKU]],Data1!A:C,3,0) -> #N/A | N23: =VLOOKUP(Table1[[#This Row],[Item '#]],Data2!A:D,4,0) -> #N/A | O23: =VLOOKUP(Table1[[#This Row],[Item '#]],Data2!A:D,3,0) -> #N/A | P23: =VLOOKUP(Table1[[#This Row],[Item '#]],[2]Sheet1!$B:$D,3,0) -> #N/A | Q23: =[8]!Table1[[#This Row],[Current WH Inventory]]=VLOOKUP(Table1[[#This Row],[Item '#]],[2]Sheet1!$B:$D,3,0) -> #REF!
D24: =VLOOKUP(Table1[[#This Row],[SKU]],Data1!A:B,2,0) -> #N/A | E24: =Table1[[#This Row],[UoM]]*Table1[[#This Row],[Recommended Replenishment Qty]] -> #N/A | F24: =Table1[[#This Row],[Total EA (Transfer to WH06)]]/Table1[[#This Row],[UoM]] -> #N/A | G24: =Table1[[#This Row],[Total EA (Transfer to WH06)]]/Table1[[#This Row],[BOX]] -> #N/A | H24: =Table1[[#This Row],[Total EA (Transfer to WH06)]]/Table1[[#This Row],[CASE]] -> #N/A | I24: =Table1[[#This Row],[Sellable Unit/Set/box to ship]]/Table1[[#This Row],[Case to pull]] -> #N/A | J24: =IF(ISNUMBER(SEARCH("FNSKU",K24)),"Labeling","") | K24: =VLOOKUP(Table1[[#This Row],[SKU]],Instruction!A:F,6,0) -> #N/A | L24: =VLOOKUP(Table1[[#This Row],[ASIN]],'[1]2024'!$A:$AB,28,0) -> #N/A | M24: =VLOOKUP(Table1[[#This Row],[SKU]],Data1!A:C,3,0) -> #N/A | N24: =VLOOKUP(Table1[[#This Row],[Item '#]],Data2!A:D,4,0) -> #N/A | O24: =VLOOKUP(Table1[[#This Row],[Item '#]],Data2!A:D,3,0) -> #N/A | P24: =VLOOKUP(Table1[[#This Row],[Item '#]],[2]Sheet1!$B:$D,3,0) -> #N/A | Q24: =[8]!Table1[[#This Row],[Current WH Inventory]]=VLOOKUP(Table1[[#This Row],[Item '#]],[2]Sheet1!$B:$D,3,0) -> #REF!
D25: =VLOOKUP(Table1[[#This Row],[SKU]],Data1!A:B,2,0) -> #N/A | E25: =Table1[[#This Row],[UoM]]*Table1[[#This Row],[Recommended Replenishment Qty]] -> #N/A | F25: =Table1[[#This Row],[Total EA (Transfer to WH06)]]/Table1[[#This Row],[UoM]] -> #N/A | G25: =Table1[[#This Row],[Total EA (Transfer to WH06)]]/Table1[[#This Row],[BOX]] -> #N/A | H25: =Table1[[#This Row],[Total EA (Transfer to WH06)]]/Table1[[#This Row],[CASE]] -> #N/A | I25: =Table1[[#This Row],[Sellable Unit/Set/box to ship]]/Table1[[#This Row],[Case to pull]] -> #N/A | J25: =IF(ISNUMBER(SEARCH("FNSKU",K25)),"Labeling","") | K25: =VLOOKUP(Table1[[#This Row],[SKU]],Instruction!A:F,6,0) -> #N/A | L25: =VLOOKUP(Table1[[#This Row],[ASIN]],'[1]2024'!$A:$AB,28,0) -> #N/A | M25: =VLOOKUP(Table1[[#This Row],[SKU]],Data1!A:C,3,0) -> #N/A | N25: =VLOOKUP(Table1[[#This Row],[Item '#]],Data2!A:D,4,0) -> #N/A | O25: =VLOOKUP(Table1[[#This Row],[Item '#]],Data2!A:D,3,0) -> #N/A | P25: =VLOOKUP(Table1[[#This Row],[Item '#]],[2]Sheet1!$B:$D,3,0) -> #N/A | Q25: =[8]!Table1[[#This Row],[Current WH Inventory]]=VLOOKUP(Table1[[#This Row],[Item '#]],[2]Sheet1!$B:$D,3,0) -> #REF!
... D33: =VLOOKUP(Table1[[#This Row],[SKU]],Data1!A:B,2,0) -> #N/A | E33: =Table1[[#This Row],[UoM]]*Table1[[#This Row],[Recommended Replenishment Qty]] -> #N/A | F33: =Table1[[#This Row],[Total EA (Transfer to WH06)]]/Table1[[#This Row],[UoM]] -> #N/A | G33: =Table1[[#This Row],[Total EA (Transfer to WH06)]]/Table1[[#This Row],[BOX]] -> #N/A | H33: =Table1[[#This Row],[Total EA (Transfer to WH06)]]/Table1[[#This Row],[CASE]] -> #N/A | I33: =Table1[[#This Row],[Sellable Unit/Set/box to ship]]/Table1[[#This Row],[Case to pull]] -> #N/A | J33: =IF(ISNUMBER(SEARCH("FNSKU",K33)),"Labeling","") | K33: =VLOOKUP(Table1[[#This Row],[SKU]],Instruction!A:F,6,0) -> #N/A | L33: =VLOOKUP(Table1[[#This Row],[ASIN]],'[1]2024'!$A:$AB,28,0) -> #N/A | M33: =VLOOKUP(Table1[[#This Row],[SKU]],Data1!A:C,3,0) -> #N/A | N33: =VLOOKUP(Table1[[#This Row],[Item '#]],Data2!A:D,4,0) -> #N/A | O33: =VLOOKUP(Table1[[#This Row],[Item '#]],Data2!A:D,3,0) -> #N/A | P33: =VLOOKUP(Table1[[#This Row],[Item '#]],[2]Sheet1!$B:$D,3,0) -> #N/A | Q33: =[8]!Table1[[#This Row],[Current WH Inventory]]=VLOOKUP(Table1[[#This Row],[Item '#]],[2]Sheet1!$B:$D,3,0) -> #REF!
D34: =VLOOKUP(Table1[[#This Row],[SKU]],Data1!A:B,2,0) -> #N/A | E34: =Table1[[#This Row],[UoM]]*Table1[[#This Row],[Recommended Replenishment Qty]] -> #N/A | F34: =Table1[[#This Row],[Total EA (Transfer to WH06)]]/Table1[[#This Row],[UoM]] -> #N/A | G34: =Table1[[#This Row],[Total EA (Transfer to WH06)]]/Table1[[#This Row],[BOX]] -> #N/A | H34: =Table1[[#This Row],[Total EA (Transfer to WH06)]]/Table1[[#This Row],[CASE]] -> #N/A | I34: =Table1[[#This Row],[Sellable Unit/Set/box to ship]]/Table1[[#This Row],[Box to pull]] -> #N/A | J34: =IF(ISNUMBER(SEARCH("FNSKU",K34)),"Labeling","") | K34: =VLOOKUP(Table1[[#This Row],[SKU]],Instruction!A:F,6,0) -> #N/A | L34: =VLOOKUP(Table1[[#This Row],[ASIN]],'[1]2024'!$A:$AB,28,0) -> #N/A | M34: =VLOOKUP(Table1[[#This Row],[SKU]],Data1!A:C,3,0) -> #N/A | N34: =VLOOKUP(Table1[[#This Row],[Item '#]],Data2!A:D,4,0) -> #N/A | O34: =VLOOKUP(Table1[[#This Row],[Item '#]],Data2!A:D,3,0) -> #N/A | P34: =VLOOKUP(Table1[[#This Row],[Item '#]],[2]Sheet1!$B:$D,3,0) -> #N/A | Q34: =[8]!Table1[[#This Row],[Current WH Inventory]]=VLOOKUP(Table1[[#This Row],[Item '#]],[2]Sheet1!$B:$D,3,0) -> #REF!
D35: =VLOOKUP(Table1[[#This Row],[SKU]],Data1!A:B,2,0) -> #N/A | E35: =Table1[[#This Row],[UoM]]*Table1[[#This Row],[Recommended Replenishment Qty]] -> #N/A | F35: =Table1[[#This Row],[Total EA (Transfer to WH06)]]/Table1[[#This Row],[UoM]] -> #N/A | G35: =Table1[[#This Row],[Total EA (Transfer to WH06)]]/Table1[[#This Row],[BOX]] -> #N/A | H35: =Table1[[#This Row],[Total EA (Transfer to WH06)]]/Table1[[#This Row],[CASE]] -> #N/A | I35: =Table1[[#This Row],[Sellable Unit/Set/box to ship]]/Table1[[#This Row],[Box to pull]] -> #N/A | J35: =IF(ISNUMBER(SEARCH("FNSKU",K35)),"Labeling","") | K35: =VLOOKUP(Table1[[#This Row],[SKU]],Instruction!A:F,6,0) -> #N/A | L35: =VLOOKUP(Table1[[#This Row],[ASIN]],'[1]2024'!$A:$AB,28,0) -> #N/A | M35: =VLOOKUP(Table1[[#This Row],[SKU]],Data1!A:C,3,0) -> #N/A | N35: =VLOOKUP(Table1[[#This Row],[Item '#]],Data2!A:D,4,0) -> #N/A | O35: =VLOOKUP(Table1[[#This Row],[Item '#]],Data2!A:D,3,0) -> #N/A | P35: =VLOOKUP(Table1[[#This Row],[Item '#]],[2]Sheet1!$B:$D,3,0) -> #N/A | Q35: =[8]!Table1[[#This Row],[Current WH Inventory]]=VLOOKUP(Table1[[#This Row],[Item '#]],[2]Sheet1!$B:$D,3,0) -> #REF!
D36: =VLOOKUP(Table1[[#This Row],[SKU]],Data1!A:B,2,0) -> #N/A | E36: =Table1[[#This Row],[UoM]]*Table1[[#This Row],[Recommended Replenishment Qty]] -> #N/A | F36: =Table1[[#This Row],[Total EA (Transfer to WH06)]]/Table1[[#This Row],[UoM]] -> #N/A | G36: =Table1[[#This Row],[Total EA (Transfer to WH06)]]/Table1[[#This Row],[BOX]] -> #N/A | H36: =Table1[[#This Row],[Total EA (Transfer to WH06)]]/Table1[[#This Row],[CASE]] -> #N/A | I36: =Table1[[#This Row],[Sellable Unit/Set/box to ship]]/Table1[[#This Row],[Case to pull]] -> #N/A | J36: =IF(ISNUMBER(SEARCH("FNSKU",K36)),"Labeling","") | K36: =VLOOKUP(Table1[[#This Row],[SKU]],Instruction!A:F,6,0) -> #N/A | L36: =VLOOKUP(Table1[[#This Row],[ASIN]],'[1]2024'!$A:$AB,28,0) -> #N/A | M36: =VLOOKUP(Table1[[#This Row],[SKU]],Data1!A:C,3,0) -> #N/A | N36: =VLOOKUP(Table1[[#This Row],[Item '#]],Data2!A:D,4,0) -> #N/A | O36: =VLOOKUP(Table1[[#This Row],[Item '#]],Data2!A:D,3,0) -> #N/A | P36: =VLOOKUP(Table1[[#This Row],[Item '#]],[2]Sheet1!$B:$D,3,0) -> #N/A | Q36: =[8]!Table1[[#This Row],[Current WH Inventory]]=VLOOKUP(Table1[[#This Row],[Item '#]],[2]Sheet1!$B:$D,3,0) -> #REF!
D37: =VLOOKUP(Table1[[#This Row],[SKU]],Data1!A:B,2,0) -> #N/A | E37: =Table1[[#This Row],[UoM]]*Table1[[#This Row],[Recommended Replenishment Qty]] -> #N/A | F37: =Table1[[#This Row],[Total EA (Transfer to WH06)]]/Table1[[#This Row],[UoM]] -> #N/A | G37: =Table1[[#This Row],[Total EA (Transfer to WH06)]]/Table1[[#This Row],[BOX]] -> #N/A | H37: =Table1[[#This Row],[Total EA (Transfer to WH06)]]/Table1[[#This Row],[CASE]] -> #N/A | I37: =Table1[[#This Row],[Sellable Unit/Set/box to ship]]/Table1[[#This Row],[Box to pull]] -> #N/A | J37: =IF(ISNUMBER(SEARCH("FNSKU",K37)),"Labeling","") | K37: =VLOOKUP(Table1[[#This Row],[SKU]],Instruction!A:F,6,0) -> #N/A | L37: =VLOOKUP(Table1[[#This Row],[ASIN]],'[1]2024'!$A:$AB,28,0) -> #N/A | M37: =VLOOKUP(Table1[[#This Row],[SKU]],Data1!A:C,3,0) -> #N/A | N37: =VLOOKUP(Table1[[#This Row],[Item '#]],Data2!A:D,4,0) -> #N/A | O37: =VLOOKUP(Table1[[#This Row],[Item '#]],Data2!A:D,3,0) -> #N/A | P37: =VLOOKUP(Table1[[#This Row],[Item '#]],[2]Sheet1!$B:$D,3,0) -> #N/A | Q37: =[8]!Table1[[#This Row],[Current WH Inventory]]=VLOOKUP(Table1[[#This Row],[Item '#]],[2]Sheet1!$B:$D,3,0) -> #REF!
D38: =VLOOKUP(Table1[[#This Row],[SKU]],Data1!A:B,2,0) -> #N/A | E38: =Table1[[#This Row],[UoM]]*Table1[[#This Row],[Recommended Replenishment Qty]] -> #N/A | F38: =Table1[[#This Row],[Total EA (Transfer to WH06)]]/Table1[[#This Row],[UoM]] -> #N/A | G38: =Table1[[#This Row],[Total EA (Transfer to WH06)]]/Table1[[#This Row],[BOX]] -> #N/A | H38: =Table1[[#This Row],[Total EA (Transfer to WH06)]]/Table1[[#This Row],[CASE]] -> #N/A | I38: =Table1[[#This Row],[Sellable Unit/Set/box to ship]]/Table1[[#This Row],[Box to pull]] -> #N/A | J38: =IF(ISNUMBER(SEARCH("FNSKU",K38)),"Labeling","") | K38: =VLOOKUP(Table1[[#This Row],[SKU]],Instruction!A:F,6,0) -> #N/A | L38: =VLOOKUP(Table1[[#This Row],[ASIN]],'[1]2024'!$A:$AB,28,0) -> #N/A | M38: =VLOOKUP(Table1[[#This Row],[SKU]],Data1!A:C,3,0) -> #N/A | N38: =VLOOKUP(Table1[[#This Row],[Item '#]],Data2!A:D,4,0) -> #N/A | O38: =VLOOKUP(Table1[[#This Row],[Item '#]],Data2!A:D,3,0) -> #N/A | P38: =VLOOKUP(Table1[[#This Row],[Item '#]],[2]Sheet1!$B:$D,3,0) -> #N/A | Q38: =[8]!Table1[[#This Row],[Current WH Inventory]]=VLOOKUP(Table1[[#This Row],[Item '#]],[2]Sheet1!$B:$D,3,0) -> #REF!
D39: =VLOOKUP(Table1[[#This Row],[SKU]],Data1!A:B,2,0) -> #N/A | E39: =Table1[[#This Row],[UoM]]*Table1[[#This Row],[Recommended Replenishment Qty]] -> #N/A | F39: =Table1[[#This Row],[Total EA (Transfer to WH06)]]/Table1[[#This Row],[UoM]] -> #N/A | G39: =Table1[[#This Row],[Total EA (Transfer to WH06)]]/Table1[[#This Row],[BOX]] -> #N/A | H39: =Table1[[#This Row],[Total EA (Transfer to WH06)]]/Table1[[#This Row],[CASE]] -> #N/A | I39: =Table1[[#This Row],[Sellable Unit/Set/box to ship]]/Table1[[#This Row],[Case to pull]] -> #N/A | J39: =IF(ISNUMBER(SEARCH("FNSKU",K39)),"Labeling","") | K39: =VLOOKUP(Table1[[#This Row],[SKU]],Instruction!A:F,6,0) -> #N/A | L39: =VLOOKUP(Table1[[#This Row],[ASIN]],'[1]2024'!$A:$AB,28,0) -> #N/A | M39: =VLOOKUP(Table1[[#This Row],[SKU]],Data1!A:C,3,0) -> #N/A | N39: =VLOOKUP(Table1[[#This Row],[Item '#]],Data2!A:D,4,0) -> #N/A | O39: =VLOOKUP(Table1[[#This Row],[Item '#]],Data2!A:D,3,0) -> #N/A | P39: =VLOOKUP(Table1[[#This Row],[Item '#]],[2]Sheet1!$B:$D,3,0) -> #N/A | Q39: =[8]!Table1[[#This Row],[Current WH Inventory]]=VLOOKUP(Table1[[#This Row],[Item '#]],[2]Sheet1!$B:$D,3,0) -> #REF!
D40: =VLOOKUP(Table1[[#This Row],[SKU]],Data1!A:B,2,0) -> #N/A | E40: =Table1[[#This Row],[UoM]]*Table1[[#This Row],[Recommended Replenishment Qty]] -> #N/A | F40: =Table1[[#This Row],[Total EA (Transfer to WH06)]]/Table1[[#This Row],[UoM]] -> #N/A | G40: =Table1[[#This Row],[Total EA (Transfer to WH06)]]/Table1[[#This Row],[BOX]] -> #N/A | H40: =Table1[[#This Row],[Total EA (Transfer to WH06)]]/Table1[[#This Row],[CASE]] -> #N/A | I40: =Table1[[#This Row],[Sellable Unit/Set/box to ship]]/Table1[[#This Row],[Case to pull]] -> #N/A | J40: =IF(ISNUMBER(SEARCH("FNSKU",K40)),"Labeling","") | K40: =VLOOKUP(Table1[[#This Row],[SKU]],Instruction!A:F,6,0) -> #N/A | L40: =VLOOKUP(Table1[[#This Row],[ASIN]],'[1]2024'!$A:$AB,28,0) -> #N/A | M40: =VLOOKUP(Table1[[#This Row],[SKU]],Data1!A:C,3,0) -> #N/A | N40: =VLOOKUP(Table1[[#This Row],[Item '#]],Data2!A:D,4,0) -> #N/A | O40: =VLOOKUP(Table1[[#This Row],[Item '#]],Data2!A:D,3,0) -> #N/A | P40: =VLOOKUP(Table1[[#This Row],[Item '#]],[2]Sheet1!$B:$D,3,0) -> #N/A | Q40: =[8]!Table1[[#This Row],[Current WH Inventory]]=VLOOKUP(Table1[[#This Row],[Item '#]],[2]Sheet1!$B:$D,3,0) -> #REF!
D41: =VLOOKUP(Table1[[#This Row],[SKU]],Data1!A:B,2,0) -> #N/A | E41: =Table1[[#This Row],[UoM]]*Table1[[#This Row],[Recommended Replenishment Qty]] -> #N/A | F41: =Table1[[#This Row],[Total EA (Transfer to WH06)]]/Table1[[#This Row],[UoM]] -> #N/A | G41: =Table1[[#This Row],[Total EA (Transfer to WH06)]]/Table1[[#This Row],[BOX]] -> #N/A | H41: =Table1[[#This Row],[Total EA (Transfer to WH06)]]/Table1[[#This Row],[CASE]] -> #N/A | I41: =Table1[[#This Row],[Sellable Unit/Set/box to ship]]/Table1[[#This Row],[Case to pull]] -> #N/A | J41: =IF(ISNUMBER(SEARCH("FNSKU",K41)),"Labeling","") | K41: =VLOOKUP(Table1[[#This Row],[SKU]],Instruction!A:F,6,0) -> #N/A | L41: =VLOOKUP(Table1[[#This Row],[ASIN]],'[1]2024'!$A:$AB,28,0) -> #N/A | M41: =VLOOKUP(Table1[[#This Row],[SKU]],Data1!A:C,3,0) -> #N/A | N41: =VLOOKUP(Table1[[#This Row],[Item '#]],Data2!A:D,4,0) -> #N/A | O41: =VLOOKUP(Table1[[#This Row],[Item '#]],Data2!A:D,3,0) -> #N/A | P41: =VLOOKUP(Table1[[#This Row],[Item '#]],[2]Sheet1!$B:$D,3,0) -> #N/A | Q41: =[8]!Table1[[#This Row],[Current WH Inventory]]=VLOOKUP(Table1[[#This Row],[Item '#]],[2]Sheet1!$B:$D,3,0) -> #REF!
D42: =VLOOKUP(Table1[[#This Row],[SKU]],Data1!A:B,2,0) -> #N/A | E42: =Table1[[#This Row],[UoM]]*Table1[[#This Row],[Recommended Replenishment Qty]] -> #N/A | F42: =Table1[[#This Row],[Total EA (Transfer to WH06)]]/Table1[[#This Row],[UoM]] -> #N/A | G42: =Table1[[#This Row],[Total EA (Transfer to WH06)]]/Table1[[#This Row],[BOX]] -> #N/A | H42: =Table1[[#This Row],[Total EA (Transfer to WH06)]]/Table1[[#This Row],[CASE]] -> #N/A | I42: =Table1[[#This Row],[Sellable Unit/Set/box to ship]]/Table1[[#This Row],[Case to pull]] -> #N/A | J42: =IF(ISNUMBER(SEARCH("FNSKU",K42)),"Labeling","") | K42: =VLOOKUP(Table1[[#This Row],[SKU]],Instruction!A:F,6,0) -> #N/A | L42: =VLOOKUP(Table1[[#This Row],[ASIN]],'[1]2024'!$A:$AB,28,0) -> #N/A | M42: =VLOOKUP(Table1[[#This Row],[SKU]],Data1!A:C,3,0) -> #N/A | N42: =VLOOKUP(Table1[[#This Row],[Item '#]],Data2!A:D,4,0) -> #N/A | O42: =VLOOKUP(Table1[[#This Row],[Item '#]],Data2!A:D,3,0) -> #N/A | P42: =VLOOKUP(Table1[[#This Row],[Item '#]],[2]Sheet1!$B:$D,3,0) -> #N/A | Q42: =[8]!Table1[[#This Row],[Current WH Inventory]]=VLOOKUP(Table1[[#This Row],[Item '#]],[2]Sheet1!$B:$D,3,0) -> #REF!
D43: =VLOOKUP(Table1[[#This Row],[SKU]],Data1!A:B,2,0) -> #N/A | E43: =Table1[[#This Row],[UoM]]*Table1[[#This Row],[Recommended Replenishment Qty]] -> #N/A | F43: =Table1[[#This Row],[Total EA (Transfer to WH06)]]/Table1[[#This Row],[UoM]] -> #N/A | G43: =Table1[[#This Row],[Total EA (Transfer to WH06)]]/Table1[[#This Row],[BOX]] -> #N/A | H43: =Table1[[#This Row],[Total EA (Transfer to WH06)]]/Table1[[#This Row],[CASE]] -> #N/A | I43: =Table1[[#This Row],[Sellable Unit/Set/box to ship]]/Table1[[#This Row],[Case to pull]] -> #N/A | J43: =IF(ISNUMBER(SEARCH("FNSKU",K43)),"Labeling","") | K43: =VLOOKUP(Table1[[#This Row],[SKU]],Instruction!A:F,6,0) -> #N/A | L43: =VLOOKUP(Table1[[#This Row],[ASIN]],'[1]2024'!$A:$AB,28,0) -> #N/A | M43: =VLOOKUP(Table1[[#This Row],[SKU]],Data1!A:C,3,0) -> #N/A | N43: =VLOOKUP(Table1[[#This Row],[Item '#]],Data2!A:D,4,0) -> #N/A | O43: =VLOOKUP(Table1[[#This Row],[Item '#]],Data2!A:D,3,0) -> #N/A | P43: =VLOOKUP(Table1[[#This Row],[Item '#]],[2]Sheet1!$B:$D,3,0) -> #N/A | Q43: =[8]!Table1[[#This Row],[Current WH Inventory]]=VLOOKUP(Table1[[#This Row],[Item '#]],[2]Sheet1!$B:$D,3,0) -> #REF!
D44: =VLOOKUP(Table1[[#This Row],[SKU]],Data1!A:B,2,0) -> #N/A | E44: =Table1[[#This Row],[UoM]]*Table1[[#This Row],[Recommended Replenishment Qty]] -> #N/A | F44: =Table1[[#This Row],[Total EA (Transfer to WH06)]]/Table1[[#This Row],[UoM]] -> #N/A | G44: =Table1[[#This Row],[Total EA (Transfer to WH06)]]/Table1[[#This Row],[BOX]] -> #N/A | H44: =Table1[[#This Row],[Total EA (Transfer to WH06)]]/Table1[[#This Row],[CASE]] -> #N/A | I44: =Table1[[#This Row],[Sellable Unit/Set/box to ship]]/Table1[[#This Row],[Case to pull]] -> #N/A | J44: =IF(ISNUMBER(SEARCH("FNSKU",K44)),"Labeling","") | K44: =VLOOKUP(Table1[[#This Row],[SKU]],Instruction!A:F,6,0) -> #N/A | L44: =VLOOKUP(Table1[[#This Row],[ASIN]],'[1]2024'!$A:$AB,28,0) -> #N/A | M44: =VLOOKUP(Table1[[#This Row],[SKU]],Data1!A:C,3,0) -> #N/A | N44: =VLOOKUP(Table1[[#This Row],[Item '#]],Data2!A:D,4,0) -> #N/A | O44: =VLOOKUP(Table1[[#This Row],[Item '#]],Data2!A:D,3,0) -> #N/A | P44: =VLOOKUP(Table1[[#This Row],[Item '#]],[2]Sheet1!$B:$D,3,0) -> #N/A | Q44: =[8]!Table1[[#This Row],[Current WH Inventory]]=VLOOKUP(Table1[[#This Row],[Item '#]],[2]Sheet1!$B:$D,3,0) -> #REF!
D45: =VLOOKUP(Table1[[#This Row],[SKU]],Data1!A:B,2,0) -> #N/A | E45: =Table1[[#This Row],[UoM]]*Table1[[#This Row],[Recommended Replenishment Qty]] -> #N/A | F45: =Table1[[#This Row],[Total EA (Transfer to WH06)]]/Table1[[#This Row],[UoM]] -> #N/A | G45: =Table1[[#This Row],[Total EA (Transfer to WH06)]]/Table1[[#This Row],[BOX]] -> #N/A | H45: =Table1[[#This Row],[Total EA (Transfer to WH06)]]/Table1[[#This Row],[CASE]] -> #N/A | I45: =Table1[[#This Row],[Sellable Unit/Set/box to ship]]/Table1[[#This Row],[Case to pull]] -> #N/A | J45: =IF(ISNUMBER(SEARCH("FNSKU",K45)),"Labeling","") | K45: =VLOOKUP(Table1[[#This Row],[SKU]],Instruction!A:F,6,0) -> #N/A | L45: =VLOOKUP(Table1[[#This Row],[ASIN]],'[1]2024'!$A:$AB,28,0) -> #N/A | M45: =VLOOKUP(Table1[[#This Row],[SKU]],Data1!A:C,3,0) -> #N/A | N45: =VLOOKUP(Table1[[#This Row],[Item '#]],Data2!A:D,4,0) -> #N/A | O45: =VLOOKUP(Table1[[#This Row],[Item '#]],Data2!A:D,3,0) -> #N/A | P45: =VLOOKUP(Table1[[#This Row],[Item '#]],[2]Sheet1!$B:$D,3,0) -> #N/A | Q45: =[8]!Table1[[#This Row],[Current WH Inventory]]=VLOOKUP(Table1[[#This Row],[Item '#]],[2]Sheet1!$B:$D,3,0) -> #REF!
D46: =VLOOKUP(Table1[[#This Row],[SKU]],Data1!A:B,2,0) -> #N/A | E46: =Table1[[#This Row],[UoM]]*Table1[[#This Row],[Recommended Replenishment Qty]] -> #N/A | F46: =Table1[[#This Row],[Total EA (Transfer to WH06)]]/Table1[[#This Row],[UoM]] -> #N/A | G46: =Table1[[#This Row],[Total EA (Transfer to WH06)]]/Table1[[#This Row],[BOX]] -> #N/A | H46: =Table1[[#This Row],[Total EA (Transfer to WH06)]]/Table1[[#This Row],[CASE]] -> #N/A | I46: =Table1[[#This Row],[Sellable Unit/Set/box to ship]]/Table1[[#This Row],[Case to pull]] -> #N/A | J46: =IF(ISNUMBER(SEARCH("FNSKU",K46)),"Labeling","") | K46: =VLOOKUP(Table1[[#This Row],[SKU]],Instruction!A:F,6,0) -> #N/A | L46: =VLOOKUP(Table1[[#This Row],[ASIN]],'[1]2024'!$A:$AB,28,0) -> #N/A | M46: =VLOOKUP(Table1[[#This Row],[SKU]],Data1!A:C,3,0) -> #N/A | N46: =VLOOKUP(Table1[[#This Row],[Item '#]],Data2!A:D,4,0) -> #N/A | O46: =VLOOKUP(Table1[[#This Row],[Item '#]],Data2!A:D,3,0) -> #N/A | P46: =VLOOKUP(Table1[[#This Row],[Item '#]],[2]Sheet1!$B:$D,3,0) -> #N/A | Q46: =[8]!Table1[[#This Row],[Current WH Inventory]]=VLOOKUP(Table1[[#This Row],[Item '#]],[2]Sheet1!$B:$D,3,0) -> #REF!
D47: =VLOOKUP(Table1[[#This Row],[SKU]],Data1!A:B,2,0) -> #N/A | E47: =Table1[[#This Row],[UoM]]*Table1[[#This Row],[Recommended Replenishment Qty]] -> #N/A | F47: =Table1[[#This Row],[Total EA (Transfer to WH06)]]/Table1[[#This Row],[UoM]] -> #N/A | G47: =Table1[[#This Row],[Total EA (Transfer to WH06)]]/Table1[[#This Row],[BOX]] -> #N/A | H47: =Table1[[#This Row],[Total EA (Transfer to WH06)]]/Table1[[#This Row],[CASE]] -> #N/A | I47: =Table1[[#This Row],[Sellable Unit/Set/box to ship]]/Table1[[#This Row],[Box to pull]] -> #N/A | J47: =IF(ISNUMBER(SEARCH("FNSKU",K47)),"Labeling","") | K47: =VLOOKUP(Table1[[#This Row],[SKU]],Instruction!A:F,6,0) -> #N/A | L47: =VLOOKUP(Table1[[#This Row],[ASIN]],'[1]2024'!$A:$AB,28,0) -> #N/A | M47: =VLOOKUP(Table1[[#This Row],[SKU]],Data1!A:C,3,0) -> #N/A | N47: =VLOOKUP(Table1[[#This Row],[Item '#]],Data2!A:D,4,0) -> #N/A | O47: =VLOOKUP(Table1[[#This Row],[Item '#]],Data2!A:D,3,0) -> #N/A | P47: =VLOOKUP(Table1[[#This Row],[Item '#]],[2]Sheet1!$B:$D,3,0) -> #N/A | Q47: =[8]!Table1[[#This Row],[Current WH Inventory]]=VLOOKUP(Table1[[#This Row],[Item '#]],[2]Sheet1!$B:$D,3,0) -> #REF!
D48: =VLOOKUP(Table1[[#This Row],[SKU]],Data1!A:B,2,0) -> #N/A | E48: =Table1[[#This Row],[UoM]]*Table1[[#This Row],[Recommended Replenishment Qty]] -> #N/A | F48: =Table1[[#This Row],[Total EA (Transfer to WH06)]]/Table1[[#This Row],[UoM]] -> #N/A | G48: =Table1[[#This Row],[Total EA (Transfer to WH06)]]/Table1[[#This Row],[BOX]] -> #N/A | H48: =Table1[[#This Row],[Total EA (Transfer to WH06)]]/Table1[[#This Row],[CASE]] -> #N/A | I48: =Table1[[#This Row],[Sellable Unit/Set/box to ship]]/Table1[[#This Row],[Case to pull]] -> #N/A | J48: =IF(ISNUMBER(SEARCH("FNSKU",K48)),"Labeling","") | K48: =VLOOKUP(Table1[[#This Row],[SKU]],Instruction!A:F,6,0) -> #N/A | L48: =VLOOKUP(Table1[[#This Row],[ASIN]],'[1]2024'!$A:$AB,28,0) -> #N/A | M48: =VLOOKUP(Table1[[#This Row],[SKU]],Data1!A:C,3,0) -> #N/A | N48: =VLOOKUP(Table1[[#This Row],[Item '#]],Data2!A:D,4,0) -> #N/A | O48: =VLOOKUP(Table1[[#This Row],[Item '#]],Data2!A:D,3,0) -> #N/A | P48: =VLOOKUP(Table1[[#This Row],[Item '#]],[2]Sheet1!$B:$D,3,0) -> #N/A | Q48: =[8]!Table1[[#This Row],[Current WH Inventory]]=VLOOKUP(Table1[[#This Row],[Item '#]],[2]Sheet1!$B:$D,3,0) -> #REF!
D49: =VLOOKUP(Table1[[#This Row],[SKU]],Data1!A:B,2,0) -> #N/A | E49: =Table1[[#This Row],[UoM]]*Table1[[#This Row],[Recommended Replenishment Qty]] -> #N/A | F49: =Table1[[#This Row],[Total EA (Transfer to WH06)]]/Table1[[#This Row],[UoM]] -> #N/A | G49: =Table1[[#This Row],[Total EA (Transfer to WH06)]]/Table1[[#This Row],[BOX]] -> #N/A | H49: =Table1[[#This Row],[Total EA (Transfer to WH06)]]/Table1[[#This Row],[CASE]] -> #N/A | I49: =Table1[[#This Row],[Sellable Unit/Set/box to ship]]/Table1[[#This Row],[Case to pull]] -> #N/A | J49: =IF(ISNUMBER(SEARCH("FNSKU",K49)),"Labeling","") | K49: =VLOOKUP(Table1[[#This Row],[SKU]],Instruction!A:F,6,0) -> #N/A | L49: =VLOOKUP(Table1[[#This Row],[ASIN]],'[1]2024'!$A:$AB,28,0) -> #N/A | M49: =VLOOKUP(Table1[[#This Row],[SKU]],Data1!A:C,3,0) -> #N/A | N49: =VLOOKUP(Table1[[#This Row],[Item '#]],Data2!A:D,4,0) -> #N/A | O49: =VLOOKUP(Table1[[#This Row],[Item '#]],Data2!A:D,3,0) -> #N/A | P49: =VLOOKUP(Table1[[#This Row],[Item '#]],[2]Sheet1!$B:$D,3,0) -> #N/A | Q49: =[8]!Table1[[#This Row],[Current WH Inventory]]=VLOOKUP(Table1[[#This Row],[Item '#]],[2]Sheet1!$B:$D,3,0) -> #REF!
D50: =VLOOKUP(Table1[[#This Row],[SKU]],Data1!A:B,2,0) -> #N/A | E50: =Table1[[#This Row],[UoM]]*Table1[[#This Row],[Recommended Replenishment Qty]] -> #N/A | F50: =Table1[[#This Row],[Total EA (Transfer to WH06)]]/Table1[[#This Row],[UoM]] -> #N/A | G50: =Table1[[#This Row],[Total EA (Transfer to WH06)]]/Table1[[#This Row],[BOX]] -> #N/A | H50: =Table1[[#This Row],[Total EA (Transfer to WH06)]]/Table1[[#This Row],[CASE]] -> #N/A | I50: =Table1[[#This Row],[Sellable Unit/Set/box to ship]]/Table1[[#This Row],[Case to pull]] -> #N/A | J50: =IF(ISNUMBER(SEARCH("FNSKU",K50)),"Labeling","") | K50: =VLOOKUP(Table1[[#This Row],[SKU]],Instruction!A:F,6,0) -> #N/A | L50: =VLOOKUP(Table1[[#This Row],[ASIN]],'[1]2024'!$A:$AB,28,0) -> #N/A | M50: =VLOOKUP(Table1[[#This Row],[SKU]],Data1!A:C,3,0) -> #N/A | N50: =VLOOKUP(Table1[[#This Row],[Item '#]],Data2!A:D,4,0) -> #N/A | O50: =VLOOKUP(Table1[[#This Row],[Item '#]],Data2!A:D,3,0) -> #N/A | P50: =VLOOKUP(Table1[[#This Row],[Item '#]],[2]Sheet1!$B:$D,3,0) -> #N/A | Q50: =[8]!Table1[[#This Row],[Current WH Inventory]]=VLOOKUP(Table1[[#This Row],[Item '#]],[2]Sheet1!$B:$D,3,0) -> #REF!
D51: =VLOOKUP(Table1[[#This Row],[SKU]],Data1!A:B,2,0) -> #N/A | E51: =Table1[[#This Row],[UoM]]*Table1[[#This Row],[Recommended Replenishment Qty]] -> #N/A | F51: =Table1[[#This Row],[Total EA (Transfer to WH06)]]/Table1[[#This Row],[UoM]] -> #N/A | G51: =Table1[[#This Row],[Total EA (Transfer to WH06)]]/Table1[[#This Row],[BOX]] -> #N/A | H51: =Table1[[#This Row],[Total EA (Transfer to WH06)]]/Table1[[#This Row],[CASE]] -> #N/A | I51: =Table1[[#This Row],[Sellable Unit/Set/box to ship]]/Table1[[#This Row],[Box to pull]] -> #N/A | J51: =IF(ISNUMBER(SEARCH("FNSKU",K51)),"Labeling","") | K51: =VLOOKUP(Table1[[#This Row],[SKU]],Instruction!A:F,6,0) -> #N/A | L51: =VLOOKUP(Table1[[#This Row],[ASIN]],'[1]2024'!$A:$AB,28,0) -> #N/A | M51: =VLOOKUP(Table1[[#This Row],[SKU]],Data1!A:C,3,0) -> #N/A | N51: =VLOOKUP(Table1[[#This Row],[Item '#]],Data2!A:D,4,0) -> #N/A | O51: =VLOOKUP(Table1[[#This Row],[Item '#]],Data2!A:D,3,0) -> #N/A | P51: =VLOOKUP(Table1[[#This Row],[Item '#]],[2]Sheet1!$B:$D,3,0) -> #N/A | Q51: =[8]!Table1[[#This Row],[Current WH Inventory]]=VLOOKUP(Table1[[#This Row],[Item '#]],[2]Sheet1!$B:$D,3,0) -> #REF!
D52: =VLOOKUP(Table1[[#This Row],[SKU]],Data1!A:B,2,0) -> #N/A | E52: =Table1[[#This Row],[UoM]]*Table1[[#This Row],[Recommended Replenishment Qty]] -> #N/A | F52: =Table1[[#This Row],[Total EA (Transfer to WH06)]]/Table1[[#This Row],[UoM]] -> #N/A | G52: =Table1[[#This Row],[Total EA (Transfer to WH06)]]/Table1[[#This Row],[BOX]] -> #N/A | H52: =Table1[[#This Row],[Total EA (Transfer to WH06)]]/Table1[[#This Row],[CASE]] -> #N/A | I52: =Table1[[#This Row],[Sellable Unit/Set/box to ship]]/Table1[[#This Row],[Case to pull]] -> #N/A | J52: =IF(ISNUMBER(SEARCH("FNSKU",K52)),"Labeling","") | K52: =VLOOKUP(Table1[[#This Row],[SKU]],Instruction!A:F,6,0) -> #N/A | L52: =VLOOKUP(Table1[[#This Row],[ASIN]],'[1]2024'!$A:$AB,28,0) -> #N/A | M52: =VLOOKUP(Table1[[#This Row],[SKU]],Data1!A:C,3,0) -> #N/A | N52: =VLOOKUP(Table1[[#This Row],[Item '#]],Data2!A:D,4,0) -> #N/A | O52: =VLOOKUP(Table1[[#This Row],[Item '#]],Data2!A:D,3,0) -> #N/A | P52: =VLOOKUP(Table1[[#This Row],[Item '#]],[2]Sheet1!$B:$D,3,0) -> #N/A | Q52: =[8]!Table1[[#This Row],[Current WH Inventory]]=VLOOKUP(Table1[[#This Row],[Item '#]],[2]Sheet1!$B:$D,3,0) -> #REF!
D53: =VLOOKUP(Table1[[#This Row],[SKU]],Data1!A:B,2,0) -> #N/A | E53: =Table1[[#This Row],[UoM]]*Table1[[#This Row],[Recommended Replenishment Qty]] -> #N/A | F53: =Table1[[#This Row],[Total EA (Transfer to WH06)]]/Table1[[#This Row],[UoM]] -> #N/A | G53: =Table1[[#This Row],[Total EA (Transfer to WH06)]]/Table1[[#This Row],[BOX]] -> #N/A | H53: =Table1[[#This Row],[Total EA (Transfer to WH06)]]/Table1[[#This Row],[CASE]] -> #N/A | I53: =Table1[[#This Row],[Sellable Unit/Set/box to ship]]/Table1[[#This Row],[Box to pull]] -> #N/A | J53: =IF(ISNUMBER(SEARCH("FNSKU",K53)),"Labeling","") | K53: =VLOOKUP(Table1[[#This Row],[SKU]],Instruction!A:F,6,0) -> #N/A | L53: =VLOOKUP(Table1[[#This Row],[ASIN]],'[1]2024'!$A:$AB,28,0) -> #N/A | M53: =VLOOKUP(Table1[[#This Row],[SKU]],Data1!A:C,3,0) -> #N/A | N53: =VLOOKUP(Table1[[#This Row],[Item '#]],Data2!A:D,4,0) -> #N/A | O53: =VLOOKUP(Table1[[#This Row],[Item '#]],Data2!A:D,3,0) -> #N/A | P53: =VLOOKUP(Table1[[#This Row],[Item '#]],[2]Sheet1!$B:$D,3,0) -> #N/A | Q53: =[8]!Table1[[#This Row],[Current WH Inventory]]=VLOOKUP(Table1[[#This Row],[Item '#]],[2]Sheet1!$B:$D,3,0) -> #REF!
D54: =VLOOKUP(Table1[[#This Row],[SKU]],Data1!A:B,2,0) -> #N/A | E54: =Table1[[#This Row],[UoM]]*Table1[[#This Row],[Recommended Replenishment Qty]] -> #N/A | F54: =Table1[[#This Row],[Total EA (Transfer to WH06)]]/Table1[[#This Row],[UoM]] -> #N/A | G54: =Table1[[#This Row],[Total EA (Transfer to WH06)]]/Table1[[#This Row],[BOX]] -> #N/A | H54: =Table1[[#This Row],[Total EA (Transfer to WH06)]]/Table1[[#This Row],[CASE]] -> #N/A | I54: =Table1[[#This Row],[Sellable Unit/Set/box to ship]]/Table1[[#This Row],[Box to pull]] -> #N/A | J54: =IF(ISNUMBER(SEARCH("FNSKU",K54)),"Labeling","") | K54: =VLOOKUP(Table1[[#This Row],[SKU]],Instruction!A:F,6,0) -> #N/A | L54: =VLOOKUP(Table1[[#This Row],[ASIN]],'[1]2024'!$A:$AB,28,0) -> #N/A | M54: =VLOOKUP(Table1[[#This Row],[SKU]],Data1!A:C,3,0) -> #N/A | N54: =VLOOKUP(Table1[[#This Row],[Item '#]],Data2!A:D,4,0) -> #N/A | O54: =VLOOKUP(Table1[[#This Row],[Item '#]],Data2!A:D,3,0) -> #N/A | P54: =VLOOKUP(Table1[[#This Row],[Item '#]],[2]Sheet1!$B:$D,3,0) -> #N/A | Q54: =[8]!Table1[[#This Row],[Current WH Inventory]]=VLOOKUP(Table1[[#This Row],[Item '#]],[2]Sheet1!$B:$D,3,0) -> #REF!
D55: =VLOOKUP(Table1[[#This Row],[SKU]],Data1!A:B,2,0) -> #N/A | E55: =Table1[[#This Row],[UoM]]*Table1[[#This Row],[Recommended Replenishment Qty]] -> #N/A | F55: =Table1[[#This Row],[Total EA (Transfer to WH06)]]/Table1[[#This Row],[UoM]] -> #N/A | G55: =Table1[[#This Row],[Total EA (Transfer to WH06)]]/Table1[[#This Row],[BOX]] -> #N/A | H55: =Table1[[#This Row],[Total EA (Transfer to WH06)]]/Table1[[#This Row],[CASE]] -> #N/A | I55: =Table1[[#This Row],[Sellable Unit/Set/box to ship]]/Table1[[#This Row],[Box to pull]] -> #N/A | J55: =IF(ISNUMBER(SEARCH("FNSKU",K55)),"Labeling","") | K55: =VLOOKUP(Table1[[#This Row],[SKU]],Instruction!A:F,6,0) -> #N/A | L55: =VLOOKUP(Table1[[#This Row],[ASIN]],'[1]2024'!$A:$AB,28,0) -> #N/A | M55: =VLOOKUP(Table1[[#This Row],[SKU]],Data1!A:C,3,0) -> #N/A | N55: =VLOOKUP(Table1[[#This Row],[Item '#]],Data2!A:D,4,0) -> #N/A | O55: =VLOOKUP(Table1[[#This Row],[Item '#]],Data2!A:D,3,0) -> #N/A | P55: =VLOOKUP(Table1[[#This Row],[Item '#]],[2]Sheet1!$B:$D,3,0) -> #N/A | Q55: =[8]!Table1[[#This Row],[Current WH Inventory]]=VLOOKUP(Table1[[#This Row],[Item '#]],[2]Sheet1!$B:$D,3,0) -> #REF!
D56: =VLOOKUP(Table1[[#This Row],[SKU]],Data1!A:B,2,0) -> #N/A | E56: =Table1[[#This Row],[UoM]]*Table1[[#This Row],[Recommended Replenishment Qty]] -> #N/A | F56: =Table1[[#This Row],[Total EA (Transfer to WH06)]]/Table1[[#This Row],[UoM]] -> #N/A | G56: =Table1[[#This Row],[Total EA (Transfer to WH06)]]/Table1[[#This Row],[BOX]] -> #N/A | H56: =Table1[[#This Row],[Total EA (Transfer to WH06)]]/Table1[[#This Row],[CASE]] -> #N/A | I56: =Table1[[#This Row],[Sellable Unit/Set/box to ship]]/Table1[[#This Row],[Case to pull]] -> #N/A | J56: =IF(ISNUMBER(SEARCH("FNSKU",K56)),"Labeling","") | K56: =VLOOKUP(Table1[[#This Row],[SKU]],Instruction!A:F,6,0) -> #N/A | L56: =VLOOKUP(Table1[[#This Row],[ASIN]],'[1]2024'!$A:$AB,28,0) -> #N/A | M56: =VLOOKUP(Table1[[#This Row],[SKU]],Data1!A:C,3,0) -> #N/A | N56: =VLOOKUP(Table1[[#This Row],[Item '#]],Data2!A:D,4,0) -> #N/A | O56: =VLOOKUP(Table1[[#This Row],[Item '#]],Data2!A:D,3,0) -> #N/A | P56: =VLOOKUP(Table1[[#This Row],[Item '#]],[2]Sheet1!$B:$D,3,0) -> #N/A | Q56: =[8]!Table1[[#This Row],[Current WH Inventory]]=VLOOKUP(Table1[[#This Row],[Item '#]],[2]Sheet1!$B:$D,3,0) -> #REF!
D57: =VLOOKUP(Table1[[#This Row],[SKU]],Data1!A:B,2,0) -> #N/A | E57: =Table1[[#This Row],[UoM]]*Table1[[#This Row],[Recommended Replenishment Qty]] -> #N/A | F57: =Table1[[#This Row],[Total EA (Transfer to WH06)]]/Table1[[#This Row],[UoM]] -> #N/A | G57: =Table1[[#This Row],[Total EA (Transfer to WH06)]]/Table1[[#This Row],[BOX]] -> #N/A | H57: =Table1[[#This Row],[Total EA (Transfer to WH06)]]/Table1[[#This Row],[CASE]] -> #N/A | I57: =Table1[[#This Row],[Sellable Unit/Set/box to ship]]/Table1[[#This Row],[Case to pull]] -> #N/A | J57: =IF(ISNUMBER(SEARCH("FNSKU",K57)),"Labeling","") | K57: =VLOOKUP(Table1[[#This Row],[SKU]],Instruction!A:F,6,0) -> #N/A | L57: =VLOOKUP(Table1[[#This Row],[ASIN]],'[1]2024'!$A:$AB,28,0) -> #N/A | M57: =VLOOKUP(Table1[[#This Row],[SKU]],Data1!A:C,3,0) -> #N/A | N57: =VLOOKUP(Table1[[#This Row],[Item '#]],Data2!A:D,4,0) -> #N/A | O57: =VLOOKUP(Table1[[#This Row],[Item '#]],Data2!A:D,3,0) -> #N/A | P57: =VLOOKUP(Table1[[#This Row],[Item '#]],[2]Sheet1!$B:$D,3,0) -> #N/A | Q57: =[8]!Table1[[#This Row],[Current WH Inventory]]=VLOOKUP(Table1[[#This Row],[Item '#]],[2]Sheet1!$B:$D,3,0) -> #REF!
D58: =VLOOKUP(Table1[[#This Row],[SKU]],Data1!A:B,2,0) -> #N/A | E58: =Table1[[#This Row],[UoM]]*Table1[[#This Row],[Recommended Replenishment Qty]] -> #N/A | F58: =Table1[[#This Row],[Total EA (Transfer to WH06)]]/Table1[[#This Row],[UoM]] -> #N/A | G58: =Table1[[#This Row],[Total EA (Transfer to WH06)]]/Table1[[#This Row],[BOX]] -> #N/A | H58: =Table1[[#This Row],[Total EA (Transfer to WH06)]]/Table1[[#This Row],[CASE]] -> #N/A | I58: =Table1[[#This Row],[Sellable Unit/Set/box to ship]]/Table1[[#This Row],[Box to pull]] -> #N/A | J58: =IF(ISNUMBER(SEARCH("FNSKU",K58)),"Labeling","") | K58: =VLOOKUP(Table1[[#This Row],[SKU]],Instruction!A:F,6,0) -> #N/A | L58: =VLOOKUP(Table1[[#This Row],[ASIN]],'[1]2024'!$A:$AB,28,0) -> #N/A | M58: =VLOOKUP(Table1[[#This Row],[SKU]],Data1!A:C,3,0) -> #N/A | N58: =VLOOKUP(Table1[[#This Row],[Item '#]],Data2!A:D,4,0) -> #N/A | O58: =VLOOKUP(Table1[[#This Row],[Item '#]],Data2!A:D,3,0) -> #N/A | P58: =VLOOKUP(Table1[[#This Row],[Item '#]],[2]Sheet1!$B:$D,3,0) -> #N/A | Q58: =[8]!Table1[[#This Row],[Current WH Inventory]]=VLOOKUP(Table1[[#This Row],[Item '#]],[2]Sheet1!$B:$D,3,0) -> #REF!
D59: =VLOOKUP(Table1[[#This Row],[SKU]],Data1!A:B,2,0) -> #N/A | E59: =Table1[[#This Row],[UoM]]*Table1[[#This Row],[Recommended Replenishment Qty]] -> #N/A | F59: =Table1[[#This Row],[Total EA (Transfer to WH06)]]/Table1[[#This Row],[UoM]] -> #N/A | G59: =Table1[[#This Row],[Total EA (Transfer to WH06)]]/Table1[[#This Row],[BOX]] -> #N/A | H59: =Table1[[#This Row],[Total EA (Transfer to WH06)]]/Table1[[#This Row],[CASE]] -> #N/A | I59: =Table1[[#This Row],[Sellable Unit/Set/box to ship]]/Table1[[#This Row],[Box to pull]] -> #N/A | J59: =IF(ISNUMBER(SEARCH("FNSKU",K59)),"Labeling","") | K59: =VLOOKUP(Table1[[#This Row],[SKU]],Instruction!A:F,6,0) -> #N/A | L59: =VLOOKUP(Table1[[#This Row],[ASIN]],'[1]2024'!$A:$AB,28,0) -> #N/A | M59: =VLOOKUP(Table1[[#This Row],[SKU]],Data1!A:C,3,0) -> #N/A | N59: =VLOOKUP(Table1[[#This Row],[Item '#]],Data2!A:D,4,0) -> #N/A | O59: =VLOOKUP(Table1[[#This Row],[Item '#]],Data2!A:D,3,0) -> #N/A | P59: =VLOOKUP(Table1[[#This Row],[Item '#]],[2]Sheet1!$B:$D,3,0) -> #N/A | Q59: =[8]!Table1[[#This Row],[Current WH Inventory]]=VLOOKUP(Table1[[#This Row],[Item '#]],[2]Sheet1!$B:$D,3,0) -> #REF!
D60: =VLOOKUP(Table1[[#This Row],[SKU]],Data1!A:B,2,0) -> #N/A | E60: =Table1[[#This Row],[UoM]]*Table1[[#This Row],[Recommended Replenishment Qty]] -> #N/A | F60: =Table1[[#This Row],[Total EA (Transfer to WH06)]]/Table1[[#This Row],[UoM]] -> #N/A | G60: =Table1[[#This Row],[Total EA (Transfer to WH06)]]/Table1[[#This Row],[BOX]] -> #N/A | H60: =Table1[[#This Row],[Total EA (Transfer to WH06)]]/Table1[[#This Row],[CASE]] -> #N/A | I60: =Table1[[#This Row],[Sellable Unit/Set/box to ship]]/Table1[[#This Row],[Box to pull]] -> #N/A | J60: =IF(ISNUMBER(SEARCH("FNSKU",K60)),"Labeling","") | K60: =VLOOKUP(Table1[[#This Row],[SKU]],Instruction!A:F,6,0) -> #N/A | L60: =VLOOKUP(Table1[[#This Row],[ASIN]],'[1]2024'!$A:$AB,28,0) -> #N/A | M60: =VLOOKUP(Table1[[#This Row],[SKU]],Data1!A:C,3,0) -> #N/A | N60: =VLOOKUP(Table1[[#This Row],[Item '#]],Data2!A:D,4,0) -> #N/A | O60: =VLOOKUP(Table1[[#This Row],[Item '#]],Data2!A:D,3,0) -> #N/A | P60: =VLOOKUP(Table1[[#This Row],[Item '#]],[2]Sheet1!$B:$D,3,0) -> #N/A | Q60: =[8]!Table1[[#This Row],[Current WH Inventory]]=VLOOKUP(Table1[[#This Row],[Item '#]],[2]Sheet1!$B:$D,3,0) -> #REF!
D61: =VLOOKUP(Table1[[#This Row],[SKU]],Data1!A:B,2,0) -> #N/A | E61: =Table1[[#This Row],[UoM]]*Table1[[#This Row],[Recommended Replenishment Qty]] -> #N/A | F61: =Table1[[#This Row],[Total EA (Transfer to WH06)]]/Table1[[#This Row],[UoM]] -> #N/A | G61: =Table1[[#This Row],[Total EA (Transfer to WH06)]]/Table1[[#This Row],[BOX]] -> #N/A | H61: =Table1[[#This Row],[Total EA (Transfer to WH06)]]/Table1[[#This Row],[CASE]] -> #N/A | I61: =Table1[[#This Row],[Sellable Unit/Set/box to ship]]/Table1[[#This Row],[Case to pull]] -> #N/A | J61: =IF(ISNUMBER(SEARCH("FNSKU",K61)),"Labeling","") | K61: =VLOOKUP(Table1[[#This Row],[SKU]],Instruction!A:F,6,0) -> #N/A | L61: =VLOOKUP(Table1[[#This Row],[ASIN]],'[1]2024'!$A:$AB,28,0) -> #N/A | M61: =VLOOKUP(Table1[[#This Row],[SKU]],Data1!A:C,3,0) -> #N/A | N61: =VLOOKUP(Table1[[#This Row],[Item '#]],Data2!A:D,4,0) -> #N/A | O61: =VLOOKUP(Table1[[#This Row],[Item '#]],Data2!A:D,3,0) -> #N/A | P61: =VLOOKUP(Table1[[#This Row],[Item '#]],[2]Sheet1!$B:$D,3,0) -> #N/A | Q61: =[8]!Table1[[#This Row],[Current WH Inventory]]=VLOOKUP(Table1[[#This Row],[Item '#]],[2]Sheet1!$B:$D,3,0) -> #REF!
D62: =VLOOKUP(Table1[[#This Row],[SKU]],Data1!A:B,2,0) -> #N/A | E62: =Table1[[#This Row],[UoM]]*Table1[[#This Row],[Recommended Replenishment Qty]] -> #N/A | F62: =Table1[[#This Row],[Total EA (Transfer to WH06)]]/Table1[[#This Row],[UoM]] -> #N/A | G62: =Table1[[#This Row],[Total EA (Transfer to WH06)]]/Table1[[#This Row],[BOX]] -> #N/A | H62: =Table1[[#This Row],[Total EA (Transfer to WH06)]]/Table1[[#This Row],[CASE]] -> #N/A | I62: =Table1[[#This Row],[Sellable Unit/Set/box to ship]]/Table1[[#This Row],[Box to pull]] -> #N/A | J62: =IF(ISNUMBER(SEARCH("FNSKU",K62)),"Labeling","") | K62: =VLOOKUP(Table1[[#This Row],[SKU]],Instruction!A:F,6,0) -> #N/A | L62: =VLOOKUP(Table1[[#This Row],[ASIN]],'[1]2024'!$A:$AB,28,0) -> #N/A | M62: =VLOOKUP(Table1[[#This Row],[SKU]],Data1!A:C,3,0) -> #N/A | N62: =VLOOKUP(Table1[[#This Row],[Item '#]],Data2!A:D,4,0) -> #N/A | O62: =VLOOKUP(Table1[[#This Row],[Item '#]],Data2!A:D,3,0) -> #N/A | P62: =VLOOKUP(Table1[[#This Row],[Item '#]],[2]Sheet1!$B:$D,3,0) -> #N/A | Q62: =[8]!Table1[[#This Row],[Current WH Inventory]]=VLOOKUP(Table1[[#This Row],[Item '#]],[2]Sheet1!$B:$D,3,0) -> #REF!
D63: =VLOOKUP(Table1[[#This Row],[SKU]],Data1!A:B,2,0) -> #N/A | E63: =Table1[[#This Row],[UoM]]*Table1[[#This Row],[Recommended Replenishment Qty]] -> #N/A | F63: =Table1[[#This Row],[Total EA (Transfer to WH06)]]/Table1[[#This Row],[UoM]] -> #N/A | G63: =Table1[[#This Row],[Total EA (Transfer to WH06)]]/Table1[[#This Row],[BOX]] -> #N/A | H63: =Table1[[#This Row],[Total EA (Transfer to WH06)]]/Table1[[#This Row],[CASE]] -> #N/A | I63: =Table1[[#This Row],[Sellable Unit/Set/box to ship]]/Table1[[#This Row],[Box to pull]] -> #N/A | J63: =IF(ISNUMBER(SEARCH("FNSKU",K63)),"Labeling","") | K63: =VLOOKUP(Table1[[#This Row],[SKU]],Instruction!A:F,6,0) -> #N/A | L63: =VLOOKUP(Table1[[#This Row],[ASIN]],'[1]2024'!$A:$AB,28,0) -> #N/A | M63: =VLOOKUP(Table1[[#This Row],[SKU]],Data1!A:C,3,0) -> #N/A | N63: =VLOOKUP(Table1[[#This Row],[Item '#]],Data2!A:D,4,0) -> #N/A | O63: =VLOOKUP(Table1[[#This Row],[Item '#]],Data2!A:D,3,0) -> #N/A | P63: =VLOOKUP(Table1[[#This Row],[Item '#]],[2]Sheet1!$B:$D,3,0) -> #N/A | Q63: =[8]!Table1[[#This Row],[Current WH Inventory]]=VLOOKUP(Table1[[#This Row],[Item '#]],[2]Sheet1!$B:$D,3,0) -> #REF!
D64: =VLOOKUP(Table1[[#This Row],[SKU]],Data1!A:B,2,0) -> #N/A | E64: =Table1[[#This Row],[UoM]]*Table1[[#This Row],[Recommended Replenishment Qty]] -> #N/A | F64: =Table1[[#This Row],[Total EA (Transfer to WH06)]]/Table1[[#This Row],[UoM]] -> #N/A | G64: =Table1[[#This Row],[Total EA (Transfer to WH06)]]/Table1[[#This Row],[BOX]] -> #N/A | H64: =Table1[[#This Row],[Total EA (Transfer to WH06)]]/Table1[[#This Row],[CASE]] -> #N/A | I64: =Table1[[#This Row],[Sellable Unit/Set/box to ship]]/Table1[[#This Row],[Box to pull]] -> #N/A | J64: =IF(ISNUMBER(SEARCH("FNSKU",K64)),"Labeling","") | K64: =VLOOKUP(Table1[[#This Row],[SKU]],Instruction!A:F,6,0) -> #N/A | L64: =VLOOKUP(Table1[[#This Row],[ASIN]],'[1]2024'!$A:$AB,28,0) -> #N/A | M64: =VLOOKUP(Table1[[#This Row],[SKU]],Data1!A:C,3,0) -> #N/A | N64: =VLOOKUP(Table1[[#This Row],[Item '#]],Data2!A:D,4,0) -> #N/A | O64: =VLOOKUP(Table1[[#This Row],[Item '#]],Data2!A:D,3,0) -> #N/A | P64: =VLOOKUP(Table1[[#This Row],[Item '#]],[2]Sheet1!$B:$D,3,0) -> #N/A | Q64: =[8]!Table1[[#This Row],[Current WH Inventory]]=VLOOKUP(Table1[[#This Row],[Item '#]],[2]Sheet1!$B:$D,3,0) -> #REF!
D65: =VLOOKUP(Table1[[#This Row],[SKU]],Data1!A:B,2,0) -> #N/A | E65: =Table1[[#This Row],[UoM]]*Table1[[#This Row],[Recommended Replenishment Qty]] -> #N/A | F65: =Table1[[#This Row],[Total EA (Transfer to WH06)]]/Table1[[#This Row],[UoM]] -> #N/A | G65: =Table1[[#This Row],[Total EA (Transfer to WH06)]]/Table1[[#This Row],[BOX]] -> #N/A | H65: =Table1[[#This Row],[Total EA (Transfer to WH06)]]/Table1[[#This Row],[CASE]] -> #N/A | I65: =Table1[[#This Row],[Sellable Unit/Set/box to ship]]/Table1[[#This Row],[Box to pull]] -> #N/A | J65: =IF(ISNUMBER(SEARCH("FNSKU",K65)),"Labeling","") | K65: =VLOOKUP(Table1[[#This Row],[SKU]],Instruction!A:F,6,0) -> #N/A | L65: =VLOOKUP(Table1[[#This Row],[ASIN]],'[1]2024'!$A:$AB,28,0) -> #N/A | M65: =VLOOKUP(Table1[[#This Row],[SKU]],Data1!A:C,3,0) -> #N/A | N65: =VLOOKUP(Table1[[#This Row],[Item '#]],Data2!A:D,4,0) -> #N/A | O65: =VLOOKUP(Table1[[#This Row],[Item '#]],Data2!A:D,3,0) -> #N/A | P65: =VLOOKUP(Table1[[#This Row],[Item '#]],[2]Sheet1!$B:$D,3,0) -> #N/A | Q65: =[8]!Table1[[#This Row],[Current WH Inventory]]=VLOOKUP(Table1[[#This Row],[Item '#]],[2]Sheet1!$B:$D,3,0) -> #REF!
D66: =VLOOKUP(Table1[[#This Row],[SKU]],Data1!A:B,2,0) -> #N/A | E66: =Table1[[#This Row],[UoM]]*Table1[[#This Row],[Recommended Replenishment Qty]] -> #N/A | F66: =Table1[[#This Row],[Total EA (Transfer to WH06)]]/Table1[[#This Row],[UoM]] -> #N/A | G66: =Table1[[#This Row],[Total EA (Transfer to WH06)]]/Table1[[#This Row],[BOX]] -> #N/A | H66: =Table1[[#This Row],[Total EA (Transfer to WH06)]]/Table1[[#This Row],[CASE]] -> #N/A | I66: =Table1[[#This Row],[Sellable Unit/Set/box to ship]]/Table1[[#This Row],[Box to pull]] -> #N/A | J66: =IF(ISNUMBER(SEARCH("FNSKU",K66)),"Labeling","") | K66: =VLOOKUP(Table1[[#This Row],[SKU]],Instruction!A:F,6,0) -> #N/A | L66: =VLOOKUP(Table1[[#This Row],[ASIN]],'[1]2024'!$A:$AB,28,0) -> #N/A | M66: =VLOOKUP(Table1[[#This Row],[SKU]],Data1!A:C,3,0) -> #N/A | N66: =VLOOKUP(Table1[[#This Row],[Item '#]],Data2!A:D,4,0) -> #N/A | O66: =VLOOKUP(Table1[[#This Row],[Item '#]],Data2!A:D,3,0) -> #N/A | P66: =VLOOKUP(Table1[[#This Row],[Item '#]],[2]Sheet1!$B:$D,3,0) -> #N/A | Q66: =[8]!Table1[[#This Row],[Current WH Inventory]]=VLOOKUP(Table1[[#This Row],[Item '#]],[2]Sheet1!$B:$D,3,0) -> #REF!
D67: =VLOOKUP(Table1[[#This Row],[SKU]],Data1!A:B,2,0) -> #N/A | E67: =Table1[[#This Row],[UoM]]*Table1[[#This Row],[Recommended Replenishment Qty]] -> #N/A | F67: =Table1[[#This Row],[Total EA (Transfer to WH06)]]/Table1[[#This Row],[UoM]] -> #N/A | G67: =Table1[[#This Row],[Total EA (Transfer to WH06)]]/Table1[[#This Row],[BOX]] -> #N/A | H67: =Table1[[#This Row],[Total EA (Transfer to WH06)]]/Table1[[#This Row],[CASE]] -> #N/A | I67: =Table1[[#This Row],[Sellable Unit/Set/box to ship]]/Table1[[#This Row],[Box to pull]] -> #N/A | J67: =IF(ISNUMBER(SEARCH("FNSKU",K67)),"Labeling","") | K67: =VLOOKUP(Table1[[#This Row],[SKU]],Instruction!A:F,6,0) -> #N/A | L67: =VLOOKUP(Table1[[#This Row],[ASIN]],'[1]2024'!$A:$AB,28,0) -> #N/A | M67: =VLOOKUP(Table1[[#This Row],[SKU]],Data1!A:C,3,0) -> #N/A | N67: =VLOOKUP(Table1[[#This Row],[Item '#]],Data2!A:D,4,0) -> #N/A | O67: =VLOOKUP(Table1[[#This Row],[Item '#]],Data2!A:D,3,0) -> #N/A | P67: =VLOOKUP(Table1[[#This Row],[Item '#]],[2]Sheet1!$B:$D,3,0) -> #N/A | Q67: =[8]!Table1[[#This Row],[Current WH Inventory]]=VLOOKUP(Table1[[#This Row],[Item '#]],[2]Sheet1!$B:$D,3,0) -> #REF!
D68: =VLOOKUP(Table1[[#This Row],[SKU]],Data1!A:B,2,0) -> #N/A | E68: =Table1[[#This Row],[UoM]]*Table1[[#This Row],[Recommended Replenishment Qty]] -> #N/A | F68: =Table1[[#This Row],[Total EA (Transfer to WH06)]]/Table1[[#This Row],[UoM]] -> #N/A | G68: =Table1[[#This Row],[Total EA (Transfer to WH06)]]/Table1[[#This Row],[BOX]] -> #N/A | H68: =Table1[[#This Row],[Total EA (Transfer to WH06)]]/Table1[[#This Row],[CASE]] -> #N/A | I68: =Table1[[#This Row],[Sellable Unit/Set/box to ship]]/Table1[[#This Row],[Box to pull]] -> #N/A | J68: =IF(ISNUMBER(SEARCH("FNSKU",K68)),"Labeling","") | K68: =VLOOKUP(Table1[[#This Row],[SKU]],Instruction!A:F,6,0) -> #N/A | L68: =VLOOKUP(Table1[[#This Row],[ASIN]],'[1]2024'!$A:$AB,28,0) -> #N/A | M68: =VLOOKUP(Table1[[#This Row],[SKU]],Data1!A:C,3,0) -> #N/A | N68: =VLOOKUP(Table1[[#This Row],[Item '#]],Data2!A:D,4,0) -> #N/A | O68: =VLOOKUP(Table1[[#This Row],[Item '#]],Data2!A:D,3,0) -> #N/A | P68: =VLOOKUP(Table1[[#This Row],[Item '#]],[2]Sheet1!$B:$D,3,0) -> #N/A | Q68: =[8]!Table1[[#This Row],[Current WH Inventory]]=VLOOKUP(Table1[[#This Row],[Item '#]],[2]Sheet1!$B:$D,3,0) -> #REF!
D69: =VLOOKUP(Table1[[#This Row],[SKU]],Data1!A:B,2,0) -> #N/A | E69: =Table1[[#This Row],[UoM]]*Table1[[#This Row],[Recommended Replenishment Qty]] -> #N/A | F69: =Table1[[#This Row],[Total EA (Transfer to WH06)]]/Table1[[#This Row],[UoM]] -> #N/A | G69: =Table1[[#This Row],[Total EA (Transfer to WH06)]]/Table1[[#This Row],[BOX]] -> #N/A | H69: =Table1[[#This Row],[Total EA (Transfer to WH06)]]/Table1[[#This Row],[CASE]] -> #N/A | I69: =Table1[[#This Row],[Sellable Unit/Set/box to ship]]/Table1[[#This Row],[Case to pull]] -> #N/A | J69: =IF(ISNUMBER(SEARCH("FNSKU",K69)),"Labeling","") | K69: =VLOOKUP(Table1[[#This Row],[SKU]],Instruction!A:F,6,0) -> #N/A | L69: =VLOOKUP(Table1[[#This Row],[ASIN]],'[1]2024'!$A:$AB,28,0) -> #N/A | M69: =VLOOKUP(Table1[[#This Row],[SKU]],Data1!A:C,3,0) -> #N/A | N69: =VLOOKUP(Table1[[#This Row],[Item '#]],Data2!A:D,4,0) -> #N/A | O69: =VLOOKUP(Table1[[#This Row],[Item '#]],Data2!A:D,3,0) -> #N/A | P69: =VLOOKUP(Table1[[#This Row],[Item '#]],[2]Sheet1!$B:$D,3,0) -> #N/A | Q69: =[8]!Table1[[#This Row],[Current WH Inventory]]=VLOOKUP(Table1[[#This Row],[Item '#]],[2]Sheet1!$B:$D,3,0) -> #REF!
D70: =VLOOKUP(Table1[[#This Row],[SKU]],Data1!A:B,2,0) -> #N/A | E70: =Table1[[#This Row],[UoM]]*Table1[[#This Row],[Recommended Replenishment Qty]] -> #N/A | F70: =Table1[[#This Row],[Total EA (Transfer to WH06)]]/Table1[[#This Row],[UoM]] -> #N/A | G70: =Table1[[#This Row],[Total EA (Transfer to WH06)]]/Table1[[#This Row],[BOX]] -> #N/A | H70: =Table1[[#This Row],[Total EA (Transfer to WH06)]]/Table1[[#This Row],[CASE]] -> #N/A | I70: =Table1[[#This Row],[Sellable Unit/Set/box to ship]]/Table1[[#This Row],[Case to pull]] -> #N/A | J70: =IF(ISNUMBER(SEARCH("FNSKU",K70)),"Labeling","") | K70: =VLOOKUP(Table1[[#This Row],[SKU]],Instruction!A:F,6,0) -> #N/A | L70: =VLOOKUP(Table1[[#This Row],[ASIN]],'[1]2024'!$A:$AB,28,0) -> #N/A | M70: =VLOOKUP(Table1[[#This Row],[SKU]],Data1!A:C,3,0) -> #N/A | N70: =VLOOKUP(Table1[[#This Row],[Item '#]],Data2!A:D,4,0) -> #N/A | O70: =VLOOKUP(Table1[[#This Row],[Item '#]],Data2!A:D,3,0) -> #N/A | P70: =VLOOKUP(Table1[[#This Row],[Item '#]],[2]Sheet1!$B:$D,3,0) -> #N/A | Q70: =[8]!Table1[[#This Row],[Current WH Inventory]]=VLOOKUP(Table1[[#This Row],[Item '#]],[2]Sheet1!$B:$D,3,0) -> #REF!
D71: =VLOOKUP(Table1[[#This Row],[SKU]],Data1!A:B,2,0) -> #N/A | E71: =Table1[[#This Row],[UoM]]*Table1[[#This Row],[Recommended Replenishment Qty]] -> #N/A | F71: =Table1[[#This Row],[Total EA (Transfer to WH06)]]/Table1[[#This Row],[UoM]] -> #N/A | G71: =Table1[[#This Row],[Total EA (Transfer to WH06)]]/Table1[[#This Row],[BOX]] -> #N/A | H71: =Table1[[#This Row],[Total EA (Transfer to WH06)]]/Table1[[#This Row],[CASE]] -> #N/A | I71: =Table1[[#This Row],[Sellable Unit/Set/box to ship]]/Table1[[#This Row],[Box to pull]] -> #N/A | J71: =IF(ISNUMBER(SEARCH("FNSKU",K71)),"Labeling","") | K71: =VLOOKUP(Table1[[#This Row],[SKU]],Instruction!A:F,6,0) -> #N/A | L71: =VLOOKUP(Table1[[#This Row],[ASIN]],'[1]2024'!$A:$AB,28,0) -> #N/A | M71: =VLOOKUP(Table1[[#This Row],[SKU]],Data1!A:C,3,0) -> #N/A | N71: =VLOOKUP(Table1[[#This Row],[Item '#]],Data2!A:D,4,0) -> #N/A | O71: =VLOOKUP(Table1[[#This Row],[Item '#]],Data2!A:D,3,0) -> #N/A | P71: =VLOOKUP(Table1[[#This Row],[Item '#]],[2]Sheet1!$B:$D,3,0) -> #N/A | Q71: =[8]!Table1[[#This Row],[Current WH Inventory]]=VLOOKUP(Table1[[#This Row],[Item '#]],[2]Sheet1!$B:$D,3,0) -> #REF!
D72: =VLOOKUP(Table1[[#This Row],[SKU]],Data1!A:B,2,0) -> #N/A | E72: =Table1[[#This Row],[UoM]]*Table1[[#This Row],[Recommended Replenishment Qty]] -> #N/A | F72: =Table1[[#This Row],[Total EA (Transfer to WH06)]]/Table1[[#This Row],[UoM]] -> #N/A | G72: =Table1[[#This Row],[Total EA (Transfer to WH06)]]/Table1[[#This Row],[BOX]] -> #N/A | H72: =Table1[[#This Row],[Total EA (Transfer to WH06)]]/Table1[[#This Row],[CASE]] -> #N/A | I72: =Table1[[#This Row],[Sellable Unit/Set/box to ship]]/Table1[[#This Row],[Case to pull]] -> #N/A | J72: =IF(ISNUMBER(SEARCH("FNSKU",K72)),"Labeling","") | K72: =VLOOKUP(Table1[[#This Row],[SKU]],Instruction!A:F,6,0) -> #N/A | L72: =VLOOKUP(Table1[[#This Row],[ASIN]],'[1]2024'!$A:$AB,28,0) -> #N/A | M72: =VLOOKUP(Table1[[#This Row],[SKU]],Data1!A:C,3,0) -> #N/A | N72: =VLOOKUP(Table1[[#This Row],[Item '#]],Data2!A:D,4,0) -> #N/A | O72: =VLOOKUP(Table1[[#This Row],[Item '#]],Data2!A:D,3,0) -> #N/A | P72: =VLOOKUP(Table1[[#This Row],[Item '#]],[2]Sheet1!$B:$D,3,0) -> #N/A | Q72: =[8]!Table1[[#This Row],[Current WH Inventory]]=VLOOKUP(Table1[[#This Row],[Item '#]],[2]Sheet1!$B:$D,3,0) -> #REF!
D73: =VLOOKUP(Table1[[#This Row],[SKU]],Data1!A:B,2,0) -> #N/A | E73: =Table1[[#This Row],[UoM]]*Table1[[#This Row],[Recommended Replenishment Qty]] -> #N/A | F73: =Table1[[#This Row],[Total EA (Transfer to WH06)]]/Table1[[#This Row],[UoM]] -> #N/A | G73: =Table1[[#This Row],[Total EA (Transfer to WH06)]]/Table1[[#This Row],[BOX]] -> #N/A | H73: =Table1[[#This Row],[Total EA (Transfer to WH06)]]/Table1[[#This Row],[CASE]] -> #N/A | I73: =Table1[[#This Row],[Sellable Unit/Set/box to ship]]/Table1[[#This Row],[Case to pull]] -> #N/A | J73: =IF(ISNUMBER(SEARCH("FNSKU",K73)),"Labeling","") | K73: =VLOOKUP(Table1[[#This Row],[SKU]],Instruction!A:F,6,0) -> #N/A | L73: =VLOOKUP(Table1[[#This Row],[ASIN]],'[1]2024'!$A:$AB,28,0) -> #N/A | M73: =VLOOKUP(Table1[[#This Row],[SKU]],Data1!A:C,3,0) -> #N/A | N73: =VLOOKUP(Table1[[#This Row],[Item '#]],Data2!A:D,4,0) -> #N/A | O73: =VLOOKUP(Table1[[#This Row],[Item '#]],Data2!A:D,3,0) -> #N/A | P73: =VLOOKUP(Table1[[#This Row],[Item '#]],[2]Sheet1!$B:$D,3,0) -> #N/A | Q73: =[8]!Table1[[#This Row],[Current WH Inventory]]=VLOOKUP(Table1[[#This Row],[Item '#]],[2]Sheet1!$B:$D,3,0) -> #REF!
D74: =VLOOKUP(Table1[[#This Row],[SKU]],Data1!A:B,2,0) -> #N/A | E74: =Table1[[#This Row],[UoM]]*Table1[[#This Row],[Recommended Replenishment Qty]] -> #N/A | F74: =Table1[[#This Row],[Total EA (Transfer to WH06)]]/Table1[[#This Row],[UoM]] -> #N/A | G74: =Table1[[#This Row],[Total EA (Transfer to WH06)]]/Table1[[#This Row],[BOX]] -> #N/A | H74: =Table1[[#This Row],[Total EA (Transfer to WH06)]]/Table1[[#This Row],[CASE]] -> #N/A | I74: =Table1[[#This Row],[Sellable Unit/Set/box to ship]]/Table1[[#This Row],[Case to pull]] -> #N/A | J74: =IF(ISNUMBER(SEARCH("FNSKU",K74)),"Labeling","") | K74: =VLOOKUP(Table1[[#This Row],[SKU]],Instruction!A:F,6,0) -> #N/A | L74: =VLOOKUP(Table1[[#This Row],[ASIN]],'[1]2024'!$A:$AB,28,0) -> #N/A | M74: =VLOOKUP(Table1[[#This Row],[SKU]],Data1!A:C,3,0) -> #N/A | N74: =VLOOKUP(Table1[[#This Row],[Item '#]],Data2!A:D,4,0) -> #N/A | O74: =VLOOKUP(Table1[[#This Row],[Item '#]],Data2!A:D,3,0) -> #N/A | P74: =VLOOKUP(Table1[[#This Row],[Item '#]],[2]Sheet1!$B:$D,3,0) -> #N/A | Q74: =[8]!Table1[[#This Row],[Current WH Inventory]]=VLOOKUP(Table1[[#This Row],[Item '#]],[2]Sheet1!$B:$D,3,0) -> #REF!
D75: =VLOOKUP(Table1[[#This Row],[SKU]],Data1!A:B,2,0) -> #N/A | E75: =Table1[[#This Row],[UoM]]*Table1[[#This Row],[Recommended Replenishment Qty]] -> #N/A | F75: =Table1[[#This Row],[Total EA (Transfer to WH06)]]/Table1[[#This Row],[UoM]] -> #N/A | G75: =Table1[[#This Row],[Total EA (Transfer to WH06)]]/Table1[[#This Row],[BOX]] -> #N/A | H75: =Table1[[#This Row],[Total EA (Transfer to WH06)]]/Table1[[#This Row],[CASE]] -> #N/A | I75: =Table1[[#This Row],[Sellable Unit/Set/box to ship]]/Table1[[#This Row],[Case to pull]] -> #N/A | J75: =IF(ISNUMBER(SEARCH("FNSKU",K75)),"Labeling","") | K75: =VLOOKUP(Table1[[#This Row],[SKU]],Instruction!A:F,6,0) -> #N/A | L75: =VLOOKUP(Table1[[#This Row],[ASIN]],'[1]2024'!$A:$AB,28,0) -> #N/A | M75: =VLOOKUP(Table1[[#This Row],[SKU]],Data1!A:C,3,0) -> #N/A | N75: =VLOOKUP(Table1[[#This Row],[Item '#]],Data2!A:D,4,0) -> #N/A | O75: =VLOOKUP(Table1[[#This Row],[Item '#]],Data2!A:D,3,0) -> #N/A | P75: =VLOOKUP(Table1[[#This Row],[Item '#]],[2]Sheet1!$B:$D,3,0) -> #N/A | Q75: =[8]!Table1[[#This Row],[Current WH Inventory]]=VLOOKUP(Table1[[#This Row],[Item '#]],[2]Sheet1!$B:$D,3,0) -> #REF!
D76: =VLOOKUP(Table1[[#This Row],[SKU]],Data1!A:B,2,0) -> #N/A | E76: =Table1[[#This Row],[UoM]]*Table1[[#This Row],[Recommended Replenishment Qty]] -> #N/A | F76: =Table1[[#This Row],[Total EA (Transfer to WH06)]]/Table1[[#This Row],[UoM]] -> #N/A | G76: =Table1[[#This Row],[Total EA (Transfer to WH06)]]/Table1[[#This Row],[BOX]] -> #N/A | H76: =Table1[[#This Row],[Total EA (Transfer to WH06)]]/Table1[[#This Row],[CASE]] -> #N/A | I76: =Table1[[#This Row],[Sellable Unit/Set/box to ship]]/Table1[[#This Row],[Case to pull]] -> #N/A | J76: =IF(ISNUMBER(SEARCH("FNSKU",K76)),"Labeling","") | K76: =VLOOKUP(Table1[[#This Row],[SKU]],Instruction!A:F,6,0) -> #N/A | L76: =VLOOKUP(Table1[[#This Row],[ASIN]],'[1]2024'!$A:$AB,28,0) -> #N/A | M76: =VLOOKUP(Table1[[#This Row],[SKU]],Data1!A:C,3,0) -> #N/A | N76: =VLOOKUP(Table1[[#This Row],[Item '#]],Data2!A:D,4,0) -> #N/A | O76: =VLOOKUP(Table1[[#This Row],[Item '#]],Data2!A:D,3,0) -> #N/A | P76: =VLOOKUP(Table1[[#This Row],[Item '#]],[2]Sheet1!$B:$D,3,0) -> #N/A | Q76: =[8]!Table1[[#This Row],[Current WH Inventory]]=VLOOKUP(Table1[[#This Row],[Item '#]],[2]Sheet1!$B:$D,3,0) -> #REF!
D77: =VLOOKUP(Table1[[#This Row],[SKU]],Data1!A:B,2,0) -> #N/A | E77: =Table1[[#This Row],[UoM]]*Table1[[#This Row],[Recommended Replenishment Qty]] -> #N/A | F77: =Table1[[#This Row],[Total EA (Transfer to WH06)]]/Table1[[#This Row],[UoM]] -> #N/A | G77: =Table1[[#This Row],[Total EA (Transfer to WH06)]]/Table1[[#This Row],[BOX]] -> #N/A | H77: =Table1[[#This Row],[Total EA (Transfer to WH06)]]/Table1[[#This Row],[CASE]] -> #N/A | I77: =Table1[[#This Row],[Sellable Unit/Set/box to ship]]/Table1[[#This Row],[Case to pull]] -> #N/A | J77: =IF(ISNUMBER(SEARCH("FNSKU",K77)),"Labeling","") | K77: =VLOOKUP(Table1[[#This Row],[SKU]],Instruction!A:F,6,0) -> #N/A | L77: =VLOOKUP(Table1[[#This Row],[ASIN]],'[1]2024'!$A:$AB,28,0) -> #N/A | M77: =VLOOKUP(Table1[[#This Row],[SKU]],Data1!A:C,3,0) -> #N/A | N77: =VLOOKUP(Table1[[#This Row],[Item '#]],Data2!A:D,4,0) -> #N/A | O77: =VLOOKUP(Table1[[#This Row],[Item '#]],Data2!A:D,3,0) -> #N/A | P77: =VLOOKUP(Table1[[#This Row],[Item '#]],[2]Sheet1!$B:$D,3,0) -> #N/A | Q77: =[8]!Table1[[#This Row],[Current WH Inventory]]=VLOOKUP(Table1[[#This Row],[Item '#]],[2]Sheet1!$B:$D,3,0) -> #REF!
D78: =VLOOKUP(Table1[[#This Row],[SKU]],Data1!A:B,2,0) -> #N/A | E78: =Table1[[#This Row],[UoM]]*Table1[[#This Row],[Recommended Replenishment Qty]] -> #N/A | F78: =Table1[[#This Row],[Total EA (Transfer to WH06)]]/Table1[[#This Row],[UoM]] -> #N/A | G78: =Table1[[#This Row],[Total EA (Transfer to WH06)]]/Table1[[#This Row],[BOX]] -> #N/A | H78: =Table1[[#This Row],[Total EA (Transfer to WH06)]]/Table1[[#This Row],[CASE]] -> #N/A | I78: =Table1[[#This Row],[Sellable Unit/Set/box to ship]]/Table1[[#This Row],[Case to pull]] -> #N/A | J78: =IF(ISNUMBER(SEARCH("FNSKU",K78)),"Labeling","") | K78: =VLOOKUP(Table1[[#This Row],[SKU]],Instruction!A:F,6,0) -> #N/A | L78: =VLOOKUP(Table1[[#This Row],[ASIN]],'[1]2024'!$A:$AB,28,0) -> #N/A | M78: =VLOOKUP(Table1[[#This Row],[SKU]],Data1!A:C,3,0) -> #N/A | N78: =VLOOKUP(Table1[[#This Row],[Item '#]],Data2!A:D,4,0) -> #N/A | O78: =VLOOKUP(Table1[[#This Row],[Item '#]],Data2!A:D,3,0) -> #N/A | P78: =VLOOKUP(Table1[[#This Row],[Item '#]],[2]Sheet1!$B:$D,3,0) -> #N/A | Q78: =[8]!Table1[[#This Row],[Current WH Inventory]]=VLOOKUP(Table1[[#This Row],[Item '#]],[2]Sheet1!$B:$D,3,0) -> #REF!
D79: =VLOOKUP(Table1[[#This Row],[SKU]],Data1!A:B,2,0) -> #N/A | E79: =Table1[[#This Row],[UoM]]*Table1[[#This Row],[Recommended Replenishment Qty]] -> #N/A | F79: =Table1[[#This Row],[Total EA (Transfer to WH06)]]/Table1[[#This Row],[UoM]] -> #N/A | G79: =Table1[[#This Row],[Total EA (Transfer to WH06)]]/Table1[[#This Row],[BOX]] -> #N/A | H79: =Table1[[#This Row],[Total EA (Transfer to WH06)]]/Table1[[#This Row],[CASE]] -> #N/A | I79: =Table1[[#This Row],[Sellable Unit/Set/box to ship]]/Table1[[#This Row],[Case to pull]] -> #N/A | J79: =IF(ISNUMBER(SEARCH("FNSKU",K79)),"Labeling","") | K79: =VLOOKUP(Table1[[#This Row],[SKU]],Instruction!A:F,6,0) -> #N/A | L79: =VLOOKUP(Table1[[#This Row],[ASIN]],'[1]2024'!$A:$AB,28,0) -> #N/A | M79: =VLOOKUP(Table1[[#This Row],[SKU]],Data1!A:C,3,0) -> #N/A | N79: =VLOOKUP(Table1[[#This Row],[Item '#]],Data2!A:D,4,0) -> #N/A | O79: =VLOOKUP(Table1[[#This Row],[Item '#]],Data2!A:D,3,0) -> #N/A | P79: =VLOOKUP(Table1[[#This Row],[Item '#]],[2]Sheet1!$B:$D,3,0) -> #N/A | Q79: =[8]!Table1[[#This Row],[Current WH Inventory]]=VLOOKUP(Table1[[#This Row],[Item '#]],[2]Sheet1!$B:$D,3,0) -> #REF!
D80: =VLOOKUP(Table1[[#This Row],[SKU]],Data1!A:B,2,0) -> #N/A | E80: =Table1[[#This Row],[UoM]]*Table1[[#This Row],[Recommended Replenishment Qty]] -> #N/A | F80: =Table1[[#This Row],[Total EA (Transfer to WH06)]]/Table1[[#This Row],[UoM]] -> #N/A | G80: =Table1[[#This Row],[Total EA (Transfer to WH06)]]/Table1[[#This Row],[BOX]] -> #N/A | H80: =Table1[[#This Row],[Total EA (Transfer to WH06)]]/Table1[[#This Row],[CASE]] -> #N/A | I80: =Table1[[#This Row],[Sellable Unit/Set/box to ship]]/Table1[[#This Row],[Case to pull]] -> #N/A | J80: =IF(ISNUMBER(SEARCH("FNSKU",K80)),"Labeling","") | K80: =VLOOKUP(Table1[[#This Row],[SKU]],Instruction!A:F,6,0) -> #N/A | L80: =VLOOKUP(Table1[[#This Row],[ASIN]],'[1]2024'!$A:$AB,28,0) -> #N/A | M80: =VLOOKUP(Table1[[#This Row],[SKU]],Data1!A:C,3,0) -> #N/A | N80: =VLOOKUP(Table1[[#This Row],[Item '#]],Data2!A:D,4,0) -> #N/A | O80: =VLOOKUP(Table1[[#This Row],[Item '#]],Data2!A:D,3,0) -> #N/A | P80: =VLOOKUP(Table1[[#This Row],[Item '#]],[2]Sheet1!$B:$D,3,0) -> #N/A | Q80: =[8]!Table1[[#This Row],[Current WH Inventory]]=VLOOKUP(Table1[[#This Row],[Item '#]],[2]Sheet1!$B:$D,3,0) -> #REF!
D81: =VLOOKUP(Table1[[#This Row],[SKU]],Data1!A:B,2,0) -> #N/A | E81: =Table1[[#This Row],[UoM]]*Table1[[#This Row],[Recommended Replenishment Qty]] -> #N/A | F81: =Table1[[#This Row],[Total EA (Transfer to WH06)]]/Table1[[#This Row],[UoM]] -> #N/A | G81: =Table1[[#This Row],[Total EA (Transfer to WH06)]]/Table1[[#This Row],[BOX]] -> #N/A | H81: =Table1[[#This Row],[Total EA (Transfer to WH06)]]/Table1[[#This Row],[CASE]] -> #N/A | I81: =Table1[[#This Row],[Sellable Unit/Set/box to ship]]/Table1[[#This Row],[Case to pull]] -> #N/A | J81: =IF(ISNUMBER(SEARCH("FNSKU",K81)),"Labeling","") | K81: =VLOOKUP(Table1[[#This Row],[SKU]],Instruction!A:F,6,0) -> #N/A | L81: =VLOOKUP(Table1[[#This Row],[ASIN]],'[1]2024'!$A:$AB,28,0) -> #N/A | M81: =VLOOKUP(Table1[[#This Row],[SKU]],Data1!A:C,3,0) -> #N/A | N81: =VLOOKUP(Table1[[#This Row],[Item '#]],Data2!A:D,4,0) -> #N/A | O81: =VLOOKUP(Table1[[#This Row],[Item '#]],Data2!A:D,3,0) -> #N/A | P81: =VLOOKUP(Table1[[#This Row],[Item '#]],[2]Sheet1!$B:$D,3,0) -> #N/A | Q81: =[8]!Table1[[#This Row],[Current WH Inventory]]=VLOOKUP(Table1[[#This Row],[Item '#]],[2]Sheet1!$B:$D,3,0) -> #REF!
D82: =VLOOKUP(Table1[[#This Row],[SKU]],Data1!A:B,2,0) -> #N/A | E82: =Table1[[#This Row],[UoM]]*Table1[[#This Row],[Recommended Replenishment Qty]] -> #N/A | F82: =Table1[[#This Row],[Total EA (Transfer to WH06)]]/Table1[[#This Row],[UoM]] -> #N/A | G82: =Table1[[#This Row],[Total EA (Transfer to WH06)]]/Table1[[#This Row],[BOX]] -> #N/A | H82: =Table1[[#This Row],[Total EA (Transfer to WH06)]]/Table1[[#This Row],[CASE]] -> #N/A | I82: =Table1[[#This Row],[Sellable Unit/Set/box to ship]]/Table1[[#This Row],[Case to pull]] -> #N/A | J82: =IF(ISNUMBER(SEARCH("FNSKU",K82)),"Labeling","") | K82: =VLOOKUP(Table1[[#This Row],[SKU]],Instruction!A:F,6,0) -> #N/A | L82: =VLOOKUP(Table1[[#This Row],[ASIN]],'[1]2024'!$A:$AB,28,0) -> #N/A | M82: =VLOOKUP(Table1[[#This Row],[SKU]],Data1!A:C,3,0) -> #N/A | N82: =VLOOKUP(Table1[[#This Row],[Item '#]],Data2!A:D,4,0) -> #N/A | O82: =VLOOKUP(Table1[[#This Row],[Item '#]],Data2!A:D,3,0) -> #N/A | P82: =VLOOKUP(Table1[[#This Row],[Item '#]],[2]Sheet1!$B:$D,3,0) -> #N/A | Q82: =[8]!Table1[[#This Row],[Current WH Inventory]]=VLOOKUP(Table1[[#This Row],[Item '#]],[2]Sheet1!$B:$D,3,0) -> #REF!
D83: =VLOOKUP(Table1[[#This Row],[SKU]],Data1!A:B,2,0) -> #N/A | E83: =Table1[[#This Row],[UoM]]*Table1[[#This Row],[Recommended Replenishment Qty]] -> #N/A | F83: =Table1[[#This Row],[Total EA (Transfer to WH06)]]/Table1[[#This Row],[UoM]] -> #N/A | G83: =Table1[[#This Row],[Total EA (Transfer to WH06)]]/Table1[[#This Row],[BOX]] -> #N/A | H83: =Table1[[#This Row],[Total EA (Transfer to WH06)]]/Table1[[#This Row],[CASE]] -> #N/A | I83: =Table1[[#This Row],[Sellable Unit/Set/box to ship]]/Table1[[#This Row],[Case to pull]] -> #N/A | J83: =IF(ISNUMBER(SEARCH("FNSKU",K83)),"Labeling","") | K83: =VLOOKUP(Table1[[#This Row],[SKU]],Instruction!A:F,6,0) -> #N/A | L83: =VLOOKUP(Table1[[#This Row],[ASIN]],'[1]2024'!$A:$AB,28,0) -> #N/A | M83: =VLOOKUP(Table1[[#This Row],[SKU]],Data1!A:C,3,0) -> #N/A | N83: =VLOOKUP(Table1[[#This Row],[Item '#]],Data2!A:D,4,0) -> #N/A | O83: =VLOOKUP(Table1[[#This Row],[Item '#]],Data2!A:D,3,0) -> #N/A | P83: =VLOOKUP(Table1[[#This Row],[Item '#]],[2]Sheet1!$B:$D,3,0) -> #N/A | Q83: =[8]!Table1[[#This Row],[Current WH Inventory]]=VLOOKUP(Table1[[#This Row],[Item '#]],[2]Sheet1!$B:$D,3,0) -> #REF!
... D105: =VLOOKUP(Table1[[#This Row],[SKU]],Data1!A:B,2,0) -> #N/A | E105: =Table1[[#This Row],[UoM]]*Table1[[#This Row],[Recommended Replenishment Qty]] -> #N/A | F105: =Table1[[#This Row],[Total EA (Transfer to WH06)]]/Table1[[#This Row],[UoM]] -> #N/A | G105: =Table1[[#This Row],[Total EA (Transfer to WH06)]]/Table1[[#This Row],[BOX]] -> #N/A | H105: =Table1[[#This Row],[Total EA (Transfer to WH06)]]/Table1[[#This Row],[CASE]] -> #N/A | I105: =Table1[[#This Row],[Sellable Unit/Set/box to ship]]/Table1[[#This Row],[Case to pull]] -> #N/A | J105: =IF(ISNUMBER(SEARCH("FNSKU",K105)),"Labeling","") | K105: =VLOOKUP(Table1[[#This Row],[SKU]],Instruction!A:F,6,0) -> #N/A | L105: =VLOOKUP(Table1[[#This Row],[ASIN]],'[1]2024'!$A:$AB,28,0) -> #N/A | M105: =VLOOKUP(Table1[[#This Row],[SKU]],Data1!A:C,3,0) -> #N/A | N105: =VLOOKUP(Table1[[#This Row],[Item '#]],Data2!A:D,4,0) -> #N/A | O105: =VLOOKUP(Table1[[#This Row],[Item '#]],Data2!A:D,3,0) -> #N/A | P105: =VLOOKUP(Table1[[#This Row],[Item '#]],[2]Sheet1!$B:$D,3,0) -> #N/A | Q105: =[8]!Table1[[#This Row],[Current WH Inventory]]=VLOOKUP(Table1[[#This Row],[Item '#]],[2]Sheet1!$B:$D,3,0) -> #REF!
E106: =SUM(Table1[Total EA (Transfer to WH06)]) -> #N/A | F106: =SUM(Table1[Sellable Unit/Set/box to ship]) -> #N/A | G106: =SUM(Table1[Box to pull]) -> #N/A | H106: =SUM(Table1[Case to pull]) -> #N/A

Sheet SO
F1: ATTENTION: AWD removal | G1: Qty | H1: Used
B2: Item# | C2: BOX | D2: CASE | F2: 5027-CASE | G2: 10 | H2: 1
B3: 203 | C3: 1
B4: 534 | C4: 1
B5: 713 | C5: 1
B6: 2012 | C6: 1
B7: 2225 | C7: 1
B8: 609 | C8: 2
B9: 767 | C9: 2
B10: 1293 | C10: 2
B11: 2204 | C11: 2
B12: 2043 | C12: 3
B13: 5074 | C13: 3
B14: S-2 | C14: 4
B15: 837 | C15: 5
B16: 508 | D16: 1
B17: 530 | D17: 1
B18: 569 | D18: 1
B19: 1286 | D19: 1
B20: 2405 | D20: 1
B21: 4151 | D21: 1
B22: 5053 | D22: 1
B23: 5087 | D23: 1
B24: 5173 | D24: 1
B25: 6303 | D25: 1
B26: 533 | D26: 2
B27: 608 | D27: 2
... B46: 4122 | D46: 4
B47: 942-A | D47: 4
B48: 560 | D48: 5
B49: 609 | D49: 5
B50: 5027 | D50: 5
B51: 5043 | D51: 5
B52: 4576436 | D52: 5
B53: 3459-A | D53: 5
B54: 532 | D54: 6
B55: 39200 | D55: 6
B56: 3451 | D56: 8
B57: 3191 | D57: 9
B58: 3467 | D58: 9
B59: 847 | D59: 10
B60: 5066 | D60: 10
B61: 41166 | D61: 10
B62: 3163 | D62: 12
B63: 3167 | D63: 17
B64: 582 | D64: 20

Sheet Sheet1
A1: Workflow name | B1: wf9547a679-894d-4f41-afc0-a2dbe4aa3f05
A2: Shipment ID | B2: STAR-VKFAPNKKS6S4A
A3: Shipment name | B3: To be assigned
A4: Ship to | B4: NORTH EAST, MD
A5: Boxes | B5: 241
A6: SKUs | B6: 72
A7: Units | B7: 4352
A9: Case packed (241 boxes)
A10: SKU | B10: Title | C10: ASIN | D10: FNSKU | E10: Case pack template name | F10: Condition | G10: Who preps units? | H10: Who labels units? | I10: Prep type | J10: Box weight (lb) | K10: Box length (inch) | L10: Box width (inch) | M10: Box height (inch) | N10: Units per box | O10: Total boxes | P10: Total units | Q10: Box ID
A11: FBA_533-BOX | B11: BAZIC Subtraction Flash Cards, Numbers Math Flashcards Game at School Home, Problem Solving (36/Pack), 24-Packs | C11: B07XQLGMSV | D11: X0044RLXAR | E11: Case (3 boxes) | F11: New | G11: By seller | H11: By seller | I11: No prep needed | J11: 16.4 | K11: 7 | L11: 12 | M11: 11 | N11: 3 | O11: 2 | P11: 6 | Q11: To be assigned
A12: FBA_508-EACH | B12: BAZIC Composition Book Wide Ruled 100 Sheet Black Marble Notebook, Writing Journal Comp Lined Notebooks for School, 1-Pack | C12: B001E75OY0 | D12: B001E75OY0 | E12: ASDN_DEFAULT_CONFIG | F12: New | G12: By seller | H12: - | I12: No prep needed | J12: 31.8 | K12: 15.5 | L12: 10 | M12: 8.5 | N12: 48 | O12: 1 | P12: 48 | Q12: To be assigned
A13: FBA_3107-BOX | B13: BAZIC Binder Dividers w/ 10 Color Tabs 8. 5" x 11", 11 Hole Punch Plastic Index Divider with Tab for 3 Ring Binders, (10/Pack), 24-Packs | C13: B07XQJZL28 | D13: X0045A6VWX | E13: Case (6 boxes) | F13: New | G13: By seller | H13: By seller | I13: No prep needed | J13: 37.6 | K13: 10 | L13: 15 | M13: 13 | N13: 6 | O13: 2 | P13: 12 | Q13: To be assigned
A14: FBA_942-A-EA-BL | B14: BAZIC Desktop Tape Dispenser w/Tape Refill 3/4" x 250", 1" Core Weighted Non-Skid Base, Sharpe Blade Tapes Holder, Blue Color, 1-Pack | C14: B0CV2WM9FJ | D14: X0044KCA65 | E14: Case (12) | F14: New | G14: By seller | H14: By seller | I14: No prep needed | J14: 20 | K14: 8 | L14: 12 | M14: 11 | N14: 12 | O14: 1 | P14: 12 | Q14: To be assigned
A15: FBA_3191-CASE | B15: BAZIC 3 Ring Binder 1" Economy View Binders Organizer - Blue, Round Ring, Hold 175 Sheets Paper, for School Office Home, 12-Count | C15: B07QF5ZS6P | D15: X003SBSJJN | E15: 1 Case | F15: New | G15: By seller | H15: By seller | I15: No prep needed | J15: 8.64 | K15: 6 | L15: 13.25 | M15: 12.25 | N15: 1 | O15: 9 | P15: 9 | Q15: To be assigned
A16: FBA_3467-EACH | B16: BAZIC Glitter Glue Tube Classic Color, Non-Toxic Washable Glitter Glue for Slime Paints DIY Art Crafts Party (120ml/Pack), 1-Pack | C16: B01HDJMKBM | D16: B01HDJMKBM | E16: Case (72) | F16: New | G16: By seller | H16: - | I16: No prep needed | J16: 30.58 | K16: 12 | L16: 13.5 | M16: 13.25 | N16: 72 | O16: 4 | P16: 288 | Q16: To be assigned
A17: FBA_3167-SET4 | B17: BAZIC 3 Ring Binder 1" Economy View Binders Organizer - Pastel Color, Round Ring, Hold 175 Sheets Paper, for School Office Home, 4-Count | C17: B08LP2FGJM | D17: X003BVZHKJ | E17: Case Pack (10 Sets) | F17: New | G17: - | H17: By seller | I17: No prep needed | J17: 28 | K17: 13 | L17: 19 | M17: 13 | N17: 10 | O17: 10 | P17: 100 | Q17: To be assigned
A18: FBA_609-PACK4 | B18: BAZIC Staples Standard (26/6) Metallic Color 3000/Pack, Stapler Refill Standard Size Staple, Assorted Colors, 4-Packs | C18: B09C2QNFTV | D18: X0044RLX89 | E18: Case (18) | F18: New | G18: By seller | H18: By seller | I18: No prep needed | J18: 17.08 | K18: 5 | L18: 14 | M18: 8 | N18: 18 | O18: 3 | P18: 54 | Q18: To be assigned
A19: FBA_5414-PACK3 | B19: BAZIC Poster Board Glitter Color 11" X 14", Sparkling Frame Colored Poster Board Paper for Christmas Wedding Birthday Craft Project (5/Pack), 3-Packs | C19: B08FZR2GLR | D19: X00468H3EJ | E19: ASDN_DEFAULT_CONFIG | F19: New | G19: By seller | H19: By seller | I19: No prep needed | J19: 19 | K19: 16 | L19: 15 | M19: 6 | N19: 16 | O19: 2 | P19: 32 | Q19: To be assigned
A20: FBA_4577036-SET2 | B20: Disney Princess Coloring Book 2 Titles, Fun Game Workbook for Learning Drawing Coloring, Gift for Kids Toddler Activity at Classroom Home, 80 Pages, 2-Pack | C20: B0897CBHTZ | D20: X004BHUY9L | E20: Case (18 Sets) | F20: New | G20: - | H20: By seller | I20: No prep needed | J20: 10.6 | K20: 4 | L20: 16 | M20: 11 | N20: 18 | O20: 2 | P20: 36 | Q20: To be assigned
A21: FBA_5043-PACK2 | B21: BAZIC Sketch Pad 50 Sheet 6" X 8", Top Bound Spiral Sketchbook Drawing Pads, Sketching Paper Coloring Book for Artist School, 2-Pack | C21: B08DFJW6V4 | D21: X0040DSNM1 | E21: Case (24) | F21: New | G21: By seller | H21: By seller | I21: No prep needed | J21: 22 | K21: 9.75 | L21: 12.75 | M21: 10 | N21: 24 | O21: 3 | P21: 72 | Q21: To be assigned
A22: FBA_2405-EACH | B22: BAZIC White Chalk, Standard Size Blackboard Chalkboard Chalks, Great Game Activity for Kids, Art Teacher Office School Home (24/Pack), 1-Pack | C22: B003BUK0UG | D22: B003BUK0UG | E22: ASDN_DEFAULT_CONFIG | F22: New | G22: By seller | H22: - | I22: No prep needed | J22: 15 | K22: 8 | L22: 6 | M22: 4 | N22: 24 | O22: 1 | P22: 24 | Q22: To be assigned
... A82: FBA_560-PACK6 | B82: BAZIC Writing Pad 100 Sheets 6" X 9", Lined Ruled Memo Writing Notebook, Easy Tear Note Paper for Office School Home, 6-Pack [unknown_binding] | C82: B08FBQM8VF | D82: X003SFDOWB | E82: ASDN_DEFAULT_CONFIG | F82: New | G82: By seller | H82: By seller | I82: No prep needed | J82: 30 | K82: 12 | L82: 13 | M82: 16 | N82: 8 | O82: 5 | P82: 40 | Q82: To be assigned

Sheet AWD Return
A1: SKU | B1: Item | C1: Qty (EA)
A2: 5027-EACH | B2: 5027 | C2: 480
A3: 560-EACH | B3: 560 | C3: =263-96 -> 167
A4: 3001-EACH | B4: 3001 | C4: 24

Sheet For WH Single
A1: SKU | B1: ASIN | C1: FNSKU | D1: Item | E1: Total EA (Transfer to WH06) | F1: Sellable Unit/Set/box to ship | G1: Box 1 units | H1: Box 2 units | I1: Label | J1: Packing Instructions | K1: Supplies | L1: UoM | M1: -- | N1: --2 | O1: Recommended Replenishment Qty | P1: Current WH Inventory
A2: 4403-SET6 | B2: B0BRNSWP12 | C2: X0043V3DCZ | D2: =VLOOKUP(A2,Data1!A:B,2,0) -> 4403 | E2: =L2*O2 -> 12 | F2: =O2 -> 2 | G2: 2 | I2: Labeling | J2: =VLOOKUP(A2,Instruction!A:F,7,0) -> #REF! | L2: =VLOOKUP(A2,Data1!A:C,3,0) -> 6 | O2: 2 | P2: =VLOOKUP(D2,[3]Sheet1!$B:$D,3,0) -> 10343
A3: 4400-SET2 | B3: B07SFT7P7X | C3: X0043UN7EF | D3: =VLOOKUP(A3,Data1!A:B,2,0) -> 4400 | E3: =L3*O3 -> 8 | F3: =O3 -> 4 | G3: 4 | I3: Labeling | J3: =VLOOKUP(A3,Instruction!A:F,7,0) -> #REF! | L3: =VLOOKUP(A3,Data1!A:C,3,0) -> 2 | O3: 4 | P3: =VLOOKUP(D3,[3]Sheet1!$B:$D,3,0) -> 28720
A4: 17036-EACH | B4: B0CQ66C7RL | C4: X0043UNGZ5 | D4: =VLOOKUP(A4,Data1!A:B,2,0) -> 17036 | E4: =L4*O4 -> 6 | F4: =O4 -> 6 | G4: 6 | I4: Labeling | J4: =VLOOKUP(A4,Instruction!A:F,7,0) -> #REF! | L4: =VLOOKUP(A4,Data1!A:C,3,0) -> 1 | O4: 6 | P4: =VLOOKUP(D4,[3]Sheet1!$B:$D,3,0) -> 19554
A5: 709-EACH | B5: B0CGW5J3SV | C5: X0043V3OBP | D5: =VLOOKUP(A5,Data1!A:B,2,0) -> 709 | E5: =L5*O5 -> 6 | F5: =O5 -> 6 | G5: 6 | I5: Labeling | J5: =VLOOKUP(A5,Instruction!A:F,7,0) -> #REF! | L5: =VLOOKUP(A5,Data1!A:C,3,0) -> 1 | O5: 6 | P5: =VLOOKUP(D5,[3]Sheet1!$B:$D,3,0) -> 2396
A6: 17035-EACH | B6: B0CQ67CVM7 | C6: X0043UZRXT | D6: =VLOOKUP(A6,Data1!A:B,2,0) -> 17035 | E6: =L6*O6 -> 6 | F6: =O6 -> 6 | G6: 6 | I6: Labeling | J6: =VLOOKUP(A6,Instruction!A:F,7,0) -> #REF! | L6: =VLOOKUP(A6,Data1!A:C,3,0) -> 1 | O6: 6 | P6: =VLOOKUP(D6,[3]Sheet1!$B:$D,3,0) -> 33166
A7: 914-EACH | B7: B07SKF1B25 | C7: X00446K72N | D7: =VLOOKUP(A7,Data1!A:B,2,0) -> 914 | E7: =L7*O7 -> 4 | F7: =O7 -> 4 | H7: 4 | I7: Labeling | J7: =VLOOKUP(A7,Instruction!A:F,7,0) -> #REF! | L7: =VLOOKUP(A7,Data1!A:C,3,0) -> 1 | O7: 4 | P7: =VLOOKUP(D7,[3]Sheet1!$B:$D,3,0) -> 32063
A8: 905-EACH | B8: B07SKD994F | C8: X0043UN5TH | D8: =VLOOKUP(A8,Data1!A:B,2,0) -> 905 | E8: =L8*O8 -> 4 | F8: =O8 -> 4 | H8: 4 | I8: Labeling | J8: =VLOOKUP(A8,Instruction!A:F,7,0) -> #REF! | L8: =VLOOKUP(A8,Data1!A:C,3,0) -> 1 | O8: 4 | P8: =VLOOKUP(D8,[3]Sheet1!$B:$D,3,0) -> 86003
A9: 1215-EACH | B9: B0CJMRSK5J | C9: X0043UN4H5 | D9: =VLOOKUP(A9,Data1!A:B,2,0) -> 1215 | E9: =L9*O9 -> 6 | F9: =O9 -> 6 | H9: 6 | I9: Labeling | J9: =VLOOKUP(A9,Instruction!A:F,7,0) -> #REF! | L9: =VLOOKUP(A9,Data1!A:C,3,0) -> 1 | O9: 6 | P9: =VLOOKUP(D9,[3]Sheet1!$B:$D,3,0) -> 10438
A10: 1227-EACH | B10: B08WPW8T92 | C10: X0043V3IBL | D10: =VLOOKUP(A10,Data1!A:B,2,0) -> 1227 | E10: =L10*O10 -> 6 | F10: =O10 -> 6 | H10: 6 | I10: Labeling | J10: =VLOOKUP(A10,Instruction!A:F,7,0) -> #REF! | L10: =VLOOKUP(A10,Data1!A:C,3,0) -> 1 | O10: 6 | P10: =VLOOKUP(D10,[3]Sheet1!$B:$D,3,0) -> 4391
A11: 992-EACH | B11: B08R6JJP2L | C11: X0043V3CT9 | D11: =VLOOKUP(A11,Data1!A:B,2,0) -> 992 | E11: =L11*O11 -> 4 | F11: =O11 -> 4 | H11: 4 | I11: Labeling | J11: =VLOOKUP(A11,Instruction!A:F,7,0) -> #REF! | L11: =VLOOKUP(A11,Data1!A:C,3,0) -> 1 | O11: 4 | P11: =VLOOKUP(D11,[3]Sheet1!$B:$D,3,0) -> 3003
A12: 6041-EACH | B12: B072LP49MC | C12: B072LP49MC | D12: =VLOOKUP(A12,Data1!A:B,2,0) -> 6041 | E12: =L12*O12 -> 4 | F12: =O12 -> 4 | G12: 4 | J12: =VLOOKUP(A12,Instruction!A:F,7,0) -> #REF! | L12: =VLOOKUP(A12,Data1!A:C,3,0) -> 1 | O12: 4 | P12: =VLOOKUP(D12,[3]Sheet1!$B:$D,3,0) -> 4235
A13: 2561-EACH | B13: B09QD62R6R | C13: B09QD62R6R | D13: =VLOOKUP(A13,Data1!A:B,2,0) -> 2561 | E13: =L13*O13 -> 6 | F13: =O13 -> 6 | G13: 6 | J13: =VLOOKUP(A13,Instruction!A:F,7,0) -> #REF! | L13: =VLOOKUP(A13,Data1!A:C,3,0) -> 1 | O13: 6 | P13: =VLOOKUP(D13,[3]Sheet1!$B:$D,3,0) -> 30774
A14: 768-EACH | B14: B005KQ9316 | C14: B005KQ9316 | D14: =VLOOKUP(A14,Data1!A:B,2,0) -> 768 | E14: =L14*O14 -> 4 | F14: =O14 -> 4 | G14: 4 | J14: =VLOOKUP(A14,Instruction!A:F,7,0) -> #REF! | L14: =VLOOKUP(A14,Data1!A:C,3,0) -> 1 | O14: 4 | P14: =VLOOKUP(D14,[3]Sheet1!$B:$D,3,0) -> 22194
A15: 1277-EACH | B15: B0B9P3TD4K | C15: B0B9P3TD4K | D15: =VLOOKUP(A15,Data1!A:B,2,0) -> 1277 | E15: =L15*O15 -> 6 | F15: =O15 -> 6 | G15: 6 | J15: =VLOOKUP(A15,Instruction!A:F,7,0) -> #REF! | L15: =VLOOKUP(A15,Data1!A:C,3,0) -> 1 | O15: 6 | P15: =VLOOKUP(D15,[3]Sheet1!$B:$D,3,0) -> 10417
A16: 120-EACH | B16: B003BS9G44 | C16: B003BS9G44 | D16: =VLOOKUP(A16,Data1!A:B,2,0) -> 120 | E16: =L16*O16 -> 6 | F16: =O16 -> 6 | H16: 6 | J16: =VLOOKUP(A16,Instruction!A:F,7,0) -> #REF! | L16: =VLOOKUP(A16,Data1!A:C,3,0) -> 1 | O16: 6 | P16: =VLOOKUP(D16,[3]Sheet1!$B:$D,3,0) -> 22529
A17: 3301-EACH | B17: B0CPRBHWH9 | C17: B0CPRBHWH9 | D17: =VLOOKUP(A17,Data1!A:B,2,0) -> 3301 | E17: =L17*O17 -> 4 | F17: =O17 -> 4 | H17: 4 | J17: =VLOOKUP(A17,Instruction!A:F,7,0) -> #REF! | L17: =VLOOKUP(A17,Data1!A:C,3,0) -> 1 | O17: 4 | P17: =VLOOKUP(D17,[3]Sheet1!$B:$D,3,0) -> 281
A18: 715-EACH | B18: B07S6D1VMB | C18: B07S6D1VMB | D18: =VLOOKUP(A18,Data1!A:B,2,0) -> 715 | E18: =L18*O18 -> 3 | F18: =O18 -> 3 | H18: 3 | J18: =VLOOKUP(A18,Instruction!A:F,7,0) -> #REF! | L18: =VLOOKUP(A18,Data1!A:C,3,0) -> 1 | O18: 3 | P18: =VLOOKUP(D18,[3]Sheet1!$B:$D,3,0) -> 1789
A19: 3300-EACH | B19: B0CPRPLLFH | C19: B0CPRPLLFH | D19: =VLOOKUP(A19,Data1!A:B,2,0) -> 3300 | E19: =L19*O19 -> 4 | F19: =O19 -> 4 | H19: 4 | J19: =VLOOKUP(A19,Instruction!A:F,7,0) -> #REF! | L19: =VLOOKUP(A19,Data1!A:C,3,0) -> 1 | O19: 4 | P19: =VLOOKUP(D19,[3]Sheet1!$B:$D,3,0) -> 832

Sheet AWD
A1: SKU | B1: ASIN | C1: FNSKU | D1: Item # | E1: Total EA (Transfer to WH06) | F1: Sellable Unit/Set/box to ship | G1: Box to pull | H1: Case to pull | I1: Sets per Box/Case | J1: Label | K1: Packing Instructions | L1: AWD Special | M1: Supplies | N1: UoM | O1: BOX | P1: CASE | Q1: Recommended Replenishment Qty | R1: Current WH Inventory
A2: 4147-EACH | B2: B07Q8SQSQF | C2: X003SBSJBL | D2: =VLOOKUP(Table13[[#This Row],[SKU]],Data1!A:B,2,0) -> 4147 | E2: =Table13[[#This Row],[UoM]]*Table13[[#This Row],[Recommended Replenishment Qty]] -> 156 | F2: =Table13[[#This Row],[Total EA (Transfer to WH06)]]/Table13[[#This Row],[UoM]] -> 156 | H2: =Table13[[#This Row],[Total EA (Transfer to WH06)]]/Table13[[#This Row],[CASE]] -> 13 | I2: =Table13[[#This Row],[Sellable Unit/Set/box to ship]]/Table13[[#This Row],[Case to pull]] -> 12 | J2: =IF(ISNUMBER(SEARCH("FNSKU",K2)),"Labeling","") -> Labeling | K2: =VLOOKUP(Table13[[#This Row],[SKU]],Instruction!A:F,6,0) -> • Use FNSKU to label each item (cover barcode). Apply outer box/case label accordingly to match item# (Cover all existing barcodes on the box/case) | L2: =VLOOKUP(Table13[[#This Row],[SKU]],Instruction!A:G,7,0) -> 0 | M2: =VLOOKUP(Table13[[#This Row],[ASIN]],'[1]2024'!$A:$AB,28,0) -> No Supplies | N2: =VLOOKUP(Table13[[#This Row],[SKU]],Data1!A:C,3,0) -> 1 | O2: =VLOOKUP(Table13[[#This Row],[Item '#]],Data2!A:D,4,0) -> 0 | P2: =VLOOKUP(Table13[[#This Row],[Item '#]],Data2!A:D,3,0) -> 12 | Q2: 156 | R2: =VLOOKUP(Table13[[#This Row],[Item '#]],[2]Sheet1!$B:$D,3,0) -> 5414
A3: 2306-EACH-1 | B3: B008ZHNN68 | C3: B008ZHNN68 | D3: =VLOOKUP(Table13[[#This Row],[SKU]],Data1!A:B,2,0) -> 2306 | E3: =Table13[[#This Row],[UoM]]*Table13[[#This Row],[Recommended Replenishment Qty]] -> 1440 | F3: =Table13[[#This Row],[Total EA (Transfer to WH06)]]/Table13[[#This Row],[UoM]] -> 1440 | H3: =Table13[[#This Row],[Total EA (Transfer to WH06)]]/Table13[[#This Row],[CASE]] -> 10 | I3: =Table13[[#This Row],[Sellable Unit/Set/box to ship]]/Table13[[#This Row],[Case to pull]] -> 144 | J3: =IF(ISNUMBER(SEARCH("FNSKU",K3)),"Labeling","") | K3: =VLOOKUP(Table13[[#This Row],[SKU]],Instruction!A:F,6,0) -> Cover inner box barcode. Apply outer case label accordingly to match item# (Cover barcodes on the case) | L3: =VLOOKUP(Table13[[#This Row],[SKU]],Instruction!A:G,7,0) -> 0 | M3: =VLOOKUP(Table13[[#This Row],[ASIN]],'[1]2024'!$A:$AB,28,0) -> No Supplies | N3: =VLOOKUP(Table13[[#This Row],[SKU]],Data1!A:C,3,0) -> 1 | O3: =VLOOKUP(Table13[[#This Row],[Item '#]],Data2!A:D,4,0) -> 24 | P3: =VLOOKUP(Table13[[#This Row],[Item '#]],Data2!A:D,3,0) -> 144 | Q3: 1440 | R3: =VLOOKUP(Table13[[#This Row],[Item '#]],[2]Sheet1!$B:$D,3,0) -> 10915
A4: 6810-EACH | B4: B09DK3BKGB | C4: B09DK3BKGB | D4: =VLOOKUP(Table13[[#This Row],[SKU]],Data1!A:B,2,0) -> 6810 | E4: =Table13[[#This Row],[UoM]]*Table13[[#This Row],[Recommended Replenishment Qty]] -> 144 | F4: =Table13[[#This Row],[Total EA (Transfer to WH06)]]/Table13[[#This Row],[UoM]] -> 144 | H4: =Table13[[#This Row],[Total EA (Transfer to WH06)]]/Table13[[#This Row],[CASE]] -> 1 | I4: =Table13[[#This Row],[Sellable Unit/Set/box to ship]]/Table13[[#This Row],[Case to pull]] -> 144 | J4: =IF(ISNUMBER(SEARCH("FNSKU",K4)),"Labeling","") | K4: =VLOOKUP(Table13[[#This Row],[SKU]],Instruction!A:F,6,0) -> Apply outer box/case label accordingly to match item# (Cover all existing barcodes on the box/case) | L4: =VLOOKUP(Table13[[#This Row],[SKU]],Instruction!A:G,7,0) -> 0 | M4: =VLOOKUP(Table13[[#This Row],[ASIN]],'[1]2024'!$A:$AB,28,0) -> No Supplies | N4: =VLOOKUP(Table13[[#This Row],[SKU]],Data1!A:C,3,0) -> 1 | O4: =VLOOKUP(Table13[[#This Row],[Item '#]],Data2!A:D,4,0) -> 24 | P4: =VLOOKUP(Table13[[#This Row],[Item '#]],Data2!A:D,3,0) -> 144 | Q4: 144 | R4: =VLOOKUP(Table13[[#This Row],[Item '#]],[2]Sheet1!$B:$D,3,0) -> 21300
A5: 5027-EACH-1 | B5: B00KO8DHVC | C5: X004HP06TF | D5: =VLOOKUP(Table13[[#This Row],[SKU]],Data1!A:B,2,0) -> 5027 | E5: =Table13[[#This Row],[UoM]]*Table13[[#This Row],[Recommended Replenishment Qty]] -> 480 | F5: =Table13[[#This Row],[Total EA (Transfer to WH06)]]/Table13[[#This Row],[UoM]] -> 480 | H5: =Table13[[#This Row],[Total EA (Transfer to WH06)]]/Table13[[#This Row],[CASE]] -> 10 | I5: =Table13[[#This Row],[Sellable Unit/Set/box to ship]]/Table13[[#This Row],[Case to pull]] -> 48 | J5: =IF(ISNUMBER(SEARCH("FNSKU",K5)),"Labeling","") -> Labeling | K5: =VLOOKUP(Table13[[#This Row],[SKU]],Instruction!A:F,6,0) -> • Use FNSKU to label each item (cover barcode). Apply outer case label accordingly to match item# (Cover all existing barcodes on the case) | L5: =VLOOKUP(Table13[[#This Row],[SKU]],Instruction!A:G,7,0) -> 0 | M5: =VLOOKUP(Table13[[#This Row],[ASIN]],'[1]2024'!$A:$AB,28,0) -> No Supplies | N5: =VLOOKUP(Table13[[#This Row],[SKU]],Data1!A:C,3,0) -> 1 | O5: =VLOOKUP(Table13[[#This Row],[Item '#]],Data2!A:D,4,0) -> 0 | P5: =VLOOKUP(Table13[[#This Row],[Item '#]],Data2!A:D,3,0) -> 48 | Q5: 480 | R5: =VLOOKUP(Table13[[#This Row],[Item '#]],[2]Sheet1!$B:$D,3,0) -> 4665
A6: 2205-EACH | B6: B003BNZVHK | C6: B003BNZVHK | D6: =VLOOKUP(Table13[[#This Row],[SKU]],Data1!A:B,2,0) -> 2205 | E6: =Table13[[#This Row],[UoM]]*Table13[[#This Row],[Recommended Replenishment Qty]] -> 216 | F6: =Table13[[#This Row],[Total EA (Transfer to WH06)]]/Table13[[#This Row],[UoM]] -> 216 | H6: =Table13[[#This Row],[Total EA (Transfer to WH06)]]/Table13[[#This Row],[CASE]] -> 3 | I6: =Table13[[#This Row],[Sellable Unit/Set/box to ship]]/Table13[[#This Row],[Case to pull]] -> 72 | J6: =IF(ISNUMBER(SEARCH("FNSKU",K6)),"Labeling","") | K6: =VLOOKUP(Table13[[#This Row],[SKU]],Instruction!A:F,6,0) -> Apply outer box/case label accordingly to match item# (Cover all existing barcodes on the box/case) | L6: =VLOOKUP(Table13[[#This Row],[SKU]],Instruction!A:G,7,0) -> 0 | M6: =VLOOKUP(Table13[[#This Row],[ASIN]],'[1]2024'!$A:$AB,28,0) -> No Supplies | N6: =VLOOKUP(Table13[[#This Row],[SKU]],Data1!A:C,3,0) -> 1 | O6: =VLOOKUP(Table13[[#This Row],[Item '#]],Data2!A:D,4,0) -> 24 | P6: =VLOOKUP(Table13[[#This Row],[Item '#]],Data2!A:D,3,0) -> 72 | Q6: 216 | R6: =VLOOKUP(Table13[[#This Row],[Item '#]],[2]Sheet1!$B:$D,3,0) -> 15609
A7: 4105-EACH | B7: B07Q712K7L | C7: X003SC97JN | D7: =VLOOKUP(Table13[[#This Row],[SKU]],Data1!A:B,2,0) -> 4105 | E7: =Table13[[#This Row],[UoM]]*Table13[[#This Row],[Recommended Replenishment Qty]] -> 396 | F7: =Table13[[#This Row],[Total EA (Transfer to WH06)]]/Table13[[#This Row],[UoM]] -> 396 | H7: =Table13[[#This Row],[Total EA (Transfer to WH06)]]/Table13[[#This Row],[CASE]] -> 33 | I7: =Table13[[#This Row],[Sellable Unit/Set/box to ship]]/Table13[[#This Row],[Case to pull]] -> 12 | J7: =IF(ISNUMBER(SEARCH("FNSKU",K7)),"Labeling","") -> Labeling | K7: =VLOOKUP(Table13[[#This Row],[SKU]],Instruction!A:F,6,0) -> • Use FNSKU to label each item (cover barcode). Apply outer box/case label accordingly to match item# (Cover all existing barcodes on the box/case) | L7: =VLOOKUP(Table13[[#This Row],[SKU]],Instruction!A:G,7,0) -> 0 | M7: =VLOOKUP(Table13[[#This Row],[ASIN]],'[1]2024'!$A:$AB,28,0) -> No Supplies | N7: =VLOOKUP(Table13[[#This Row],[SKU]],Data1!A:C,3,0) -> 1 | O7: =VLOOKUP(Table13[[#This Row],[Item '#]],Data2!A:D,4,0) -> 0 | P7: =VLOOKUP(Table13[[#This Row],[Item '#]],Data2!A:D,3,0) -> 12 | Q7: 396 | R7: =VLOOKUP(Table13[[#This Row],[Item '#]],[2]Sheet1!$B:$D,3,0) -> 5443
A8: 2007-EACH | B8: B003BSF7ZG | C8: B003BSF7ZG | D8: =VLOOKUP(Table13[[#This Row],[SKU]],Data1!A:B,2,0) -> 2007 | E8: =Table13[[#This Row],[UoM]]*Table13[[#This Row],[Recommended Replenishment Qty]] -> 72 | F8: =Table13[[#This Row],[Total EA (Transfer to WH06)]]/Table13[[#This Row],[UoM]] -> 72 | G8: =Table13[[#This Row],[Total EA (Transfer to WH06)]]/Table13[[#This Row],[BOX]] -> 3 | I8: =Table13[[#This Row],[Sellable Unit/Set/box to ship]]/Table13[[#This Row],[Box to pull]] -> 24 | J8: =IF(ISNUMBER(SEARCH("FNSKU",K8)),"Labeling","") | K8: =VLOOKUP(Table13[[#This Row],[SKU]],Instruction!A:F,6,0) -> Apply outer box/case label accordingly to match item# (Cover all existing barcodes on the box/case) | L8: =VLOOKUP(Table13[[#This Row],[SKU]],Instruction!A:G,7,0) -> 0 | M8: =VLOOKUP(Table13[[#This Row],[ASIN]],'[1]2024'!$A:$AB,28,0) -> No Supplies | N8: =VLOOKUP(Table13[[#This Row],[SKU]],Data1!A:C,3,0) -> 1 | O8: =VLOOKUP(Table13[[#This Row],[Item '#]],Data2!A:D,4,0) -> 24 | P8: =VLOOKUP(Table13[[#This Row],[Item '#]],Data2!A:D,3,0) -> 144 | Q8: 72 | R8: =VLOOKUP(Table13[[#This Row],[Item '#]],[2]Sheet1!$B:$D,3,0) -> 6536
A9: 306-EACH | B9: B003BMX6SC | C9: B003BMX6SC | D9: =VLOOKUP(Table13[[#This Row],[SKU]],Data1!A:B,2,0) -> 306 | E9: =Table13[[#This Row],[UoM]]*Table13[[#This Row],[Recommended Replenishment Qty]] -> 720 | F9: =Table13[[#This Row],[Total EA (Transfer to WH06)]]/Table13[[#This Row],[UoM]] -> 720 | H9: =Table13[[#This Row],[Total EA (Transfer to WH06)]]/Table13[[#This Row],[CASE]] -> 5 | I9: =Table13[[#This Row],[Sellable Unit/Set/box to ship]]/Table13[[#This Row],[Case to pull]] -> 144 | J9: =IF(ISNUMBER(SEARCH("FNSKU",K9)),"Labeling","") | K9: =VLOOKUP(Table13[[#This Row],[SKU]],Instruction!A:F,6,0) -> Apply outer box/case label accordingly to match item# (Cover all existing barcodes on box and case) | L9: =VLOOKUP(Table13[[#This Row],[SKU]],Instruction!A:G,7,0) -> 0 | M9: =VLOOKUP(Table13[[#This Row],[ASIN]],'[1]2024'!$A:$AB,28,0) -> No Supplies | N9: =VLOOKUP(Table13[[#This Row],[SKU]],Data1!A:C,3,0) -> 1 | O9: =VLOOKUP(Table13[[#This Row],[Item '#]],Data2!A:D,4,0) -> 24 | P9: =VLOOKUP(Table13[[#This Row],[Item '#]],Data2!A:D,3,0) -> 144 | Q9: 720 | R9: =VLOOKUP(Table13[[#This Row],[Item '#]],[2]Sheet1!$B:$D,3,0) -> 30413
A10: 713-EACH | B10: B07S6D27NC | C10: X003SFVDQ5 | D10: =VLOOKUP(Table13[[#This Row],[SKU]],Data1!A:B,2,0) -> 713 | E10: =Table13[[#This Row],[UoM]]*Table13[[#This Row],[Recommended Replenishment Qty]] -> 72 | F10: =Table13[[#This Row],[Total EA (Transfer to WH06)]]/Table13[[#This Row],[UoM]] -> 72 | G10: =Table13[[#This Row],[Total EA (Transfer to WH06)]]/Table13[[#This Row],[BOX]] -> 3 | I10: =Table13[[#This Row],[Sellable Unit/Set/box to ship]]/Table13[[#This Row],[Box to pull]] -> 24 | J10: =IF(ISNUMBER(SEARCH("FNSKU",K10)),"Labeling","") -> Labeling | K10: =VLOOKUP(Table13[[#This Row],[SKU]],Instruction!A:F,6,0) -> • Use FNSKU to label each item (cover barcode). Apply outer case label accordingly to match item# (Cover all existing barcodes on the case) | L10: =VLOOKUP(Table13[[#This Row],[SKU]],Instruction!A:G,7,0) -> 0 | M10: =VLOOKUP(Table13[[#This Row],[ASIN]],'[1]2024'!$A:$AB,28,0) -> No Supplies | N10: =VLOOKUP(Table13[[#This Row],[SKU]],Data1!A:C,3,0) -> 1 | O10: =VLOOKUP(Table13[[#This Row],[Item '#]],Data2!A:D,4,0) -> 24 | P10: =VLOOKUP(Table13[[#This Row],[Item '#]],Data2!A:D,3,0) -> 144 | Q10: 72 | R10: =VLOOKUP(Table13[[#This Row],[Item '#]],[2]Sheet1!$B:$D,3,0) -> 21954
A11: 5012-EACH | B11: B002NLIS7G | C11: B002NLIS7G | D11: =VLOOKUP(Table13[[#This Row],[SKU]],Data1!A:B,2,0) -> 5012 | E11: =Table13[[#This Row],[UoM]]*Table13[[#This Row],[Recommended Replenishment Qty]] -> 250 | F11: =Table13[[#This Row],[Total EA (Transfer to WH06)]]/Table13[[#This Row],[UoM]] -> 250 | H11: =Table13[[#This Row],[Total EA (Transfer to WH06)]]/Table13[[#This Row],[CASE]] -> 5 | I11: =Table13[[#This Row],[Sellable Unit/Set/box to ship]]/Table13[[#This Row],[Case to pull]] -> 50 | J11: =IF(ISNUMBER(SEARCH("FNSKU",K11)),"Labeling","") | K11: =VLOOKUP(Table13[[#This Row],[SKU]],Instruction!A:F,6,0) -> Apply outer box/case label accordingly to match item# (Cover all existing barcodes on the box/case) | L11: =VLOOKUP(Table13[[#This Row],[SKU]],Instruction!A:G,7,0) -> 0 | M11: =VLOOKUP(Table13[[#This Row],[ASIN]],'[1]2024'!$A:$AB,28,0) -> No Supplies | N11: =VLOOKUP(Table13[[#This Row],[SKU]],Data1!A:C,3,0) -> 1 | O11: =VLOOKUP(Table13[[#This Row],[Item '#]],Data2!A:D,4,0) -> 0 | P11: =VLOOKUP(Table13[[#This Row],[Item '#]],Data2!A:D,3,0) -> 50 | Q11: 250 | R11: =VLOOKUP(Table13[[#This Row],[Item '#]],[2]Sheet1!$B:$D,3,0) -> 12082
A12: 3107-EACH | B12: B07S4GZW7L | C12: X003BBR0T5 | D12: =VLOOKUP(Table13[[#This Row],[SKU]],Data1!A:B,2,0) -> 3107 | E12: =Table13[[#This Row],[UoM]]*Table13[[#This Row],[Recommended Replenishment Qty]] -> 1008 | F12: =Table13[[#This Row],[Total EA (Transfer to WH06)]]/Table13[[#This Row],[UoM]] -> 1008 | H12: =Table13[[#This Row],[Total EA (Transfer to WH06)]]/Table13[[#This Row],[CASE]] -> 7 | I12: =Table13[[#This Row],[Sellable Unit/Set/box to ship]]/Table13[[#This Row],[Case to pull]] -> 144 | J12: =IF(ISNUMBER(SEARCH("FNSKU",K12)),"Labeling","") -> Labeling | K12: =VLOOKUP(Table13[[#This Row],[SKU]],Instruction!A:F,6,0) -> • Use FNSKU to label each item (cover barcode). Apply outer box/case label accordingly to match item# (Cover all existing barcodes on the box/case) | L12: =VLOOKUP(Table13[[#This Row],[SKU]],Instruction!A:G,7,0) -> 0 | M12: =VLOOKUP(Table13[[#This Row],[ASIN]],'[1]2024'!$A:$AB,28,0) -> No Supplies | N12: =VLOOKUP(Table13[[#This Row],[SKU]],Data1!A:C,3,0) -> 1 | O12: =VLOOKUP(Table13[[#This Row],[Item '#]],Data2!A:D,4,0) -> 24 | P12: =VLOOKUP(Table13[[#This Row],[Item '#]],Data2!A:D,3,0) -> 144 | Q12: 1008 | R12: =VLOOKUP(Table13[[#This Row],[Item '#]],[2]Sheet1!$B:$D,3,0) -> 27669
A13: 716-EACH | B13: B003BLQH7A | C13: B003BLQH7A | D13: =VLOOKUP(Table13[[#This Row],[SKU]],Data1!A:B,2,0) -> 716 | E13: =Table13[[#This Row],[UoM]]*Table13[[#This Row],[Recommended Replenishment Qty]] -> 288 | F13: =Table13[[#This Row],[Total EA (Transfer to WH06)]]/Table13[[#This Row],[UoM]] -> 288 | H13: =Table13[[#This Row],[Total EA (Transfer to WH06)]]/Table13[[#This Row],[CASE]] -> 2 | I13: =Table13[[#This Row],[Sellable Unit/Set/box to ship]]/Table13[[#This Row],[Case to pull]] -> 144 | J13: =IF(ISNUMBER(SEARCH("FNSKU",K13)),"Labeling","") -> Labeling | K13: =VLOOKUP(Table13[[#This Row],[SKU]],Instruction!A:F,6,0) -> • Use FNSKU to label each item (cover barcode). Apply outer box/case label accordingly to match item# (Cover all existing barcodes on the box/case) | L13: =VLOOKUP(Table13[[#This Row],[SKU]],Instruction!A:G,7,0) -> 0 | M13: =VLOOKUP(Table13[[#This Row],[ASIN]],'[1]2024'!$A:$AB,28,0) -> No Supplies | N13: =VLOOKUP(Table13[[#This Row],[SKU]],Data1!A:C,3,0) -> 1 | O13: =VLOOKUP(Table13[[#This Row],[Item '#]],Data2!A:D,4,0) -> 24 | P13: =VLOOKUP(Table13[[#This Row],[Item '#]],Data2!A:D,3,0) -> 144 | Q13: 288 | R13: =VLOOKUP(Table13[[#This Row],[Item '#]],[2]Sheet1!$B:$D,3,0) -> 58281
A14: 4126-EACH | B14: B07Q4RD2W3 | C14: X003SC1YAX | D14: =VLOOKUP(Table13[[#This Row],[SKU]],Data1!A:B,2,0) -> 4126 | E14: =Table13[[#This Row],[UoM]]*Table13[[#This Row],[Recommended Replenishment Qty]] -> 372 | F14: =Table13[[#This Row],[Total EA (Transfer to WH06)]]/Table13[[#This Row],[UoM]] -> 372 | H14: =Table13[[#This Row],[Total EA (Transfer to WH06)]]/Table13[[#This Row],[CASE]] -> 31 | I14: =Table13[[#This Row],[Sellable Unit/Set/box to ship]]/Table13[[#This Row],[Case to pull]] -> 12 | J14: =IF(ISNUMBER(SEARCH("FNSKU",K14)),"Labeling","") -> Labeling | K14: =VLOOKUP(Table13[[#This Row],[SKU]],Instruction!A:F,6,0) -> • Use FNSKU to label each item (cover barcode). Apply outer box/case label accordingly to match item# (Cover all existing barcodes on the box/case) | L14: =VLOOKUP(Table13[[#This Row],[SKU]],Instruction!A:G,7,0) -> 0 | M14: =VLOOKUP(Table13[[#This Row],[ASIN]],'[1]2024'!$A:$AB,28,0) -> No Supplies | N14: =VLOOKUP(Table13[[#This Row],[SKU]],Data1!A:C,3,0) -> 1 | O14: =VLOOKUP(Table13[[#This Row],[Item '#]],Data2!A:D,4,0) -> 0 | P14: =VLOOKUP(Table13[[#This Row],[Item '#]],Data2!A:D,3,0) -> 12 | Q14: 372 | R14: =VLOOKUP(Table13[[#This Row],[Item '#]],[2]Sheet1!$B:$D,3,0) -> 10832
A15: 4140-EACH | B15: B07Q84V32B | C15: X003Y7CZSH | D15: =VLOOKUP(Table13[[#This Row],[SKU]],Data1!A:B,2,0) -> 4140 | E15: =Table13[[#This Row],[UoM]]*Table13[[#This Row],[Recommended Replenishment Qty]] -> 96 | F15: =Table13[[#This Row],[Total EA (Transfer to WH06)]]/Table13[[#This Row],[UoM]] -> 96 | H15: =Table13[[#This Row],[Total EA (Transfer to WH06)]]/Table13[[#This Row],[CASE]] -> 8 | I15: =Table13[[#This Row],[Sellable Unit/Set/box to ship]]/Table13[[#This Row],[Case to pull]] -> 12 | J15: =IF(ISNUMBER(SEARCH("FNSKU",K15)),"Labeling","") -> Labeling | K15: =VLOOKUP(Table13[[#This Row],[SKU]],Instruction!A:F,6,0) -> • Use FNSKU to label each item (cover barcode). Apply outer box/case label accordingly to match item# (Cover all existing barcodes on the box/case) | L15: =VLOOKUP(Table13[[#This Row],[SKU]],Instruction!A:G,7,0) -> 0 | M15: =VLOOKUP(Table13[[#This Row],[ASIN]],'[1]2024'!$A:$AB,28,0) -> No Supplies | N15: =VLOOKUP(Table13[[#This Row],[SKU]],Data1!A:C,3,0) -> 1 | O15: =VLOOKUP(Table13[[#This Row],[Item '#]],Data2!A:D,4,0) -> 0 | P15: =VLOOKUP(Table13[[#This Row],[Item '#]],Data2!A:D,3,0) -> 12 | Q15: 96 | R15: =VLOOKUP(Table13[[#This Row],[Item '#]],[2]Sheet1!$B:$D,3,0) -> 1130
A16: 5076-EACH | B16: B015T84GY8 | C16: B015T84GY8 | D16: =VLOOKUP(Table13[[#This Row],[SKU]],Data1!A:B,2,0) -> 5076 | E16: =Table13[[#This Row],[UoM]]*Table13[[#This Row],[Recommended Replenishment Qty]] -> 144 | F16: =Table13[[#This Row],[Total EA (Transfer to WH06)]]/Table13[[#This Row],[UoM]] -> 144 | H16: =Table13[[#This Row],[Total EA (Transfer to WH06)]]/Table13[[#This Row],[CASE]] -> 2 | I16: =Table13[[#This Row],[Sellable Unit/Set/box to ship]]/Table13[[#This Row],[Case to pull]] -> 72 | J16: =IF(ISNUMBER(SEARCH("FNSKU",K16)),"Labeling","") | K16: =VLOOKUP(Table13[[#This Row],[SKU]],Instruction!A:F,6,0) -> Apply outer box/case label accordingly to match item# (Cover all existing barcodes on the box/case) | L16: =VLOOKUP(Table13[[#This Row],[SKU]],Instruction!A:G,7,0) -> 0 | M16: =VLOOKUP(Table13[[#This Row],[ASIN]],'[1]2024'!$A:$AB,28,0) -> No Supplies | N16: =VLOOKUP(Table13[[#This Row],[SKU]],Data1!A:C,3,0) -> 1 | O16: =VLOOKUP(Table13[[#This Row],[Item '#]],Data2!A:D,4,0) -> 24 | P16: =VLOOKUP(Table13[[#This Row],[Item '#]],Data2!A:D,3,0) -> 72 | Q16: 144 | R16: =VLOOKUP(Table13[[#This Row],[Item '#]],[2]Sheet1!$B:$D,3,0) -> 58377
A17: 2232-EACH | B17: B00HZ0A98G | C17: X0044RLTCJ | D17: =VLOOKUP(Table13[[#This Row],[SKU]],Data1!A:B,2,0) -> 2232 | E17: =Table13[[#This Row],[UoM]]*Table13[[#This Row],[Recommended Replenishment Qty]] -> 144 | F17: =Table13[[#This Row],[Total EA (Transfer to WH06)]]/Table13[[#This Row],[UoM]] -> 144 | H17: =Table13[[#This Row],[Total EA (Transfer to WH06)]]/Table13[[#This Row],[CASE]] -> 2 | I17: =Table13[[#This Row],[Sellable Unit/Set/box to ship]]/Table13[[#This Row],[Case to pull]] -> 72 | J17: =IF(ISNUMBER(SEARCH("FNSKU",K17)),"Labeling","") -> Labeling | K17: =VLOOKUP(Table13[[#This Row],[SKU]],Instruction!A:F,6,0) -> • Use FNSKU to label each item (cover barcode). Apply outer case label accordingly to match item# (Cover all existing barcodes on the case) | L17: =VLOOKUP(Table13[[#This Row],[SKU]],Instruction!A:G,7,0) -> 0 | M17: =VLOOKUP(Table13[[#This Row],[ASIN]],'[1]2024'!$A:$AB,28,0) -> No Supplies | N17: =VLOOKUP(Table13[[#This Row],[SKU]],Data1!A:C,3,0) -> 1 | O17: =VLOOKUP(Table13[[#This Row],[Item '#]],Data2!A:D,4,0) -> 24 | P17: =VLOOKUP(Table13[[#This Row],[Item '#]],Data2!A:D,3,0) -> 72 | Q17: 144 | R17: =VLOOKUP(Table13[[#This Row],[Item '#]],[2]Sheet1!$B:$D,3,0) -> 18189
A18: 3142-EACH | B18: B07Q713CKC | C18: X0042TT2C3 | D18: =VLOOKUP(Table13[[#This Row],[SKU]],Data1!A:B,2,0) -> 3142 | E18: =Table13[[#This Row],[UoM]]*Table13[[#This Row],[Recommended Replenishment Qty]] -> 84 | F18: =Table13[[#This Row],[Total EA (Transfer to WH06)]]/Table13[[#This Row],[UoM]] -> 84 | H18: =Table13[[#This Row],[Total EA (Transfer to WH06)]]/Table13[[#This Row],[CASE]] -> 7 | I18: =Table13[[#This Row],[Sellable Unit/Set/box to ship]]/Table13[[#This Row],[Case to pull]] -> 12 | J18: =IF(ISNUMBER(SEARCH("FNSKU",K18)),"Labeling","") -> Labeling | K18: =VLOOKUP(Table13[[#This Row],[SKU]],Instruction!A:F,6,0) -> • Use FNSKU to label each item (cover barcode). Apply outer box/case label accordingly to match item# (Cover all existing barcodes on the box/case) | L18: =VLOOKUP(Table13[[#This Row],[SKU]],Instruction!A:G,7,0) -> 0 | M18: =VLOOKUP(Table13[[#This Row],[ASIN]],'[1]2024'!$A:$AB,28,0) -> No Supplies | N18: =VLOOKUP(Table13[[#This Row],[SKU]],Data1!A:C,3,0) -> 1 | O18: =VLOOKUP(Table13[[#This Row],[Item '#]],Data2!A:D,4,0) -> 0 | P18: =VLOOKUP(Table13[[#This Row],[Item '#]],Data2!A:D,3,0) -> 12 | Q18: 84 | R18: =VLOOKUP(Table13[[#This Row],[Item '#]],[2]Sheet1!$B:$D,3,0) -> 23184
A19: 2209-EACH | B19: B07RQQ2SFV | C19: X0040DP1QH | D19: =VLOOKUP(Table13[[#This Row],[SKU]],Data1!A:B,2,0) -> 2209 | E19: =Table13[[#This Row],[UoM]]*Table13[[#This Row],[Recommended Replenishment Qty]] -> 144 | F19: =Table13[[#This Row],[Total EA (Transfer to WH06)]]/Table13[[#This Row],[UoM]] -> 144 | H19: =Table13[[#This Row],[Total EA (Transfer to WH06)]]/Table13[[#This Row],[CASE]] -> 2 | I19: =Table13[[#This Row],[Sellable Unit/Set/box to ship]]/Table13[[#This Row],[Case to pull]] -> 72 | J19: =IF(ISNUMBER(SEARCH("FNSKU",K19)),"Labeling","") -> Labeling | K19: =VLOOKUP(Table13[[#This Row],[SKU]],Instruction!A:F,6,0) -> • Use FNSKU to label each item (cover barcode). Apply outer case label accordingly to match item# (Cover all existing barcodes on the case) | L19: =VLOOKUP(Table13[[#This Row],[SKU]],Instruction!A:G,7,0) -> 0 | M19: =VLOOKUP(Table13[[#This Row],[ASIN]],'[1]2024'!$A:$AB,28,0) -> No Supplies | N19: =VLOOKUP(Table13[[#This Row],[SKU]],Data1!A:C,3,0) -> 1 | O19: =VLOOKUP(Table13[[#This Row],[Item '#]],Data2!A:D,4,0) -> 24 | P19: =VLOOKUP(Table13[[#This Row],[Item '#]],Data2!A:D,3,0) -> 72 | Q19: 144 | R19: =VLOOKUP(Table13[[#This Row],[Item '#]],[2]Sheet1!$B:$D,3,0) -> 24912
A20: 1286-EACH | B20: B07HY4Z2YL | C20: B07HY4Z2YL | D20: =VLOOKUP(Table13[[#This Row],[SKU]],Data1!A:B,2,0) -> 1286 | E20: =Table13[[#This Row],[UoM]]*Table13[[#This Row],[Recommended Replenishment Qty]] -> 120 | F20: =Table13[[#This Row],[Total EA (Transfer to WH06)]]/Table13[[#This Row],[UoM]] -> 120 | G20: =Table13[[#This Row],[Total EA (Transfer to WH06)]]/Table13[[#This Row],[BOX]] -> 5 | I20: =Table13[[#This Row],[Sellable Unit/Set/box to ship]]/Table13[[#This Row],[Box to pull]] -> 24 | J20: =IF(ISNUMBER(SEARCH("FNSKU",K20)),"Labeling","") | K20: =VLOOKUP(Table13[[#This Row],[SKU]],Instruction!A:F,6,0) -> Apply outer box/case label accordingly to match item# (Cover all existing barcodes on the box/case) | L20: =VLOOKUP(Table13[[#This Row],[SKU]],Instruction!A:G,7,0) -> 0 | M20: =VLOOKUP(Table13[[#This Row],[ASIN]],'[1]2024'!$A:$AB,28,0) -> No Supplies | N20: =VLOOKUP(Table13[[#This Row],[SKU]],Data1!A:C,3,0) -> 1 | O20: =VLOOKUP(Table13[[#This Row],[Item '#]],Data2!A:D,4,0) -> 24 | P20: =VLOOKUP(Table13[[#This Row],[Item '#]],Data2!A:D,3,0) -> 144 | Q20: 120 | R20: =VLOOKUP(Table13[[#This Row],[Item '#]],[2]Sheet1!$B:$D,3,0) -> 9796
A21: 535-EACH | B21: B003BOUX9A | C21: B003BOUX9A | D21: =VLOOKUP(Table13[[#This Row],[SKU]],Data1!A:B,2,0) -> 535 | E21: =Table13[[#This Row],[UoM]]*Table13[[#This Row],[Recommended Replenishment Qty]] -> 144 | F21: =Table13[[#This Row],[Total EA (Transfer to WH06)]]/Table13[[#This Row],[UoM]] -> 144 | H21: =Table13[[#This Row],[Total EA (Transfer to WH06)]]/Table13[[#This Row],[CASE]] -> 2 | I21: =Table13[[#This Row],[Sellable Unit/Set/box to ship]]/Table13[[#This Row],[Case to pull]] -> 72 | J21: =IF(ISNUMBER(SEARCH("FNSKU",K21)),"Labeling","") | K21: =VLOOKUP(Table13[[#This Row],[SKU]],Instruction!A:F,6,0) -> Apply outer case label accordingly to match item# (Cover all existing barcodes on the case) | L21: =VLOOKUP(Table13[[#This Row],[SKU]],Instruction!A:G,7,0) -> 0 | M21: =VLOOKUP(Table13[[#This Row],[ASIN]],'[1]2024'!$A:$AB,28,0) -> No Supplies | N21: =VLOOKUP(Table13[[#This Row],[SKU]],Data1!A:C,3,0) -> 1 | O21: =VLOOKUP(Table13[[#This Row],[Item '#]],Data2!A:D,4,0) -> 24 | P21: =VLOOKUP(Table13[[#This Row],[Item '#]],Data2!A:D,3,0) -> 72 | Q21: 144 | R21: =VLOOKUP(Table13[[#This Row],[Item '#]],[2]Sheet1!$B:$D,3,0) -> 3743
A22: 2024-EACH | B22: B003BS9A54 | C22: B003BS9A54 | D22: =VLOOKUP(Table13[[#This Row],[SKU]],Data1!A:B,2,0) -> 2024 | E22: =Table13[[#This Row],[UoM]]*Table13[[#This Row],[Recommended Replenishment Qty]] -> 96 | F22: =Table13[[#This Row],[Total EA (Transfer to WH06)]]/Table13[[#This Row],[UoM]] -> 96 | G22: =Table13[[#This Row],[Total EA (Transfer to WH06)]]/Table13[[#This Row],[BOX]] -> 4 | I22: =Table13[[#This Row],[Sellable Unit/Set/box to ship]]/Table13[[#This Row],[Box to pull]] -> 24 | J22: =IF(ISNUMBER(SEARCH("FNSKU",K22)),"Labeling","") | K22: =VLOOKUP(Table13[[#This Row],[SKU]],Instruction!A:F,6,0) -> Apply outer box/case label accordingly to match item# (Cover all existing barcodes on the box/case) | L22: =VLOOKUP(Table13[[#This Row],[SKU]],Instruction!A:G,7,0) -> 0 | M22: =VLOOKUP(Table13[[#This Row],[ASIN]],'[1]2024'!$A:$AB,28,0) -> No Supplies | N22: =VLOOKUP(Table13[[#This Row],[SKU]],Data1!A:C,3,0) -> 1 | O22: =VLOOKUP(Table13[[#This Row],[Item '#]],Data2!A:D,4,0) -> 24 | P22: =VLOOKUP(Table13[[#This Row],[Item '#]],Data2!A:D,3,0) -> 144 | Q22: 96 | R22: =VLOOKUP(Table13[[#This Row],[Item '#]],[2]Sheet1!$B:$D,3,0) -> 31413
A23: 3190-EACH | B23: B07Q9PJ727 | C23: X003SBSK1P | D23: =VLOOKUP(Table13[[#This Row],[SKU]],Data1!A:B,2,0) -> 3190 | E23: =Table13[[#This Row],[UoM]]*Table13[[#This Row],[Recommended Replenishment Qty]] -> 564 | F23: =Table13[[#This Row],[Total EA (Transfer to WH06)]]/Table13[[#This Row],[UoM]] -> 564 | H23: =Table13[[#This Row],[Total EA (Transfer to WH06)]]/Table13[[#This Row],[CASE]] -> 47 | I23: =Table13[[#This Row],[Sellable Unit/Set/box to ship]]/Table13[[#This Row],[Case to pull]] -> 12 | J23: =IF(ISNUMBER(SEARCH("FNSKU",K23)),"Labeling","") -> Labeling | K23: =VLOOKUP(Table13[[#This Row],[SKU]],Instruction!A:F,6,0) -> • Use FNSKU to label each item (cover barcode). Apply outer box/case label accordingly to match item# (Cover all existing barcodes on the box/case) | L23: =VLOOKUP(Table13[[#This Row],[SKU]],Instruction!A:G,7,0) -> 0 | M23: =VLOOKUP(Table13[[#This Row],[ASIN]],'[1]2024'!$A:$AB,28,0) -> No Supplies | N23: =VLOOKUP(Table13[[#This Row],[SKU]],Data1!A:C,3,0) -> 1 | O23: =VLOOKUP(Table13[[#This Row],[Item '#]],Data2!A:D,4,0) -> 0 | P23: =VLOOKUP(Table13[[#This Row],[Item '#]],Data2!A:D,3,0) -> 12 | Q23: 564 | R23: =VLOOKUP(Table13[[#This Row],[Item '#]],[2]Sheet1!$B:$D,3,0) -> 3269
A24: 1263-EACH | B24: B07S2ZVL8K | C24: X003TJ47A9 | D24: =VLOOKUP(Table13[[#This Row],[SKU]],Data1!A:B,2,0) -> 1263 | E24: =Table13[[#This Row],[UoM]]*Table13[[#This Row],[Recommended Replenishment Qty]] -> 96 | F24: =Table13[[#This Row],[Total EA (Transfer to WH06)]]/Table13[[#This Row],[UoM]] -> 96 | G24: =Table13[[#This Row],[Total EA (Transfer to WH06)]]/Table13[[#This Row],[BOX]] -> 4 | I24: =Table13[[#This Row],[Sellable Unit/Set/box to ship]]/Table13[[#This Row],[Box to pull]] -> 24 | J24: =IF(ISNUMBER(SEARCH("FNSKU",K24)),"Labeling","") -> Labeling | K24: =VLOOKUP(Table13[[#This Row],[SKU]],Instruction!A:F,6,0) -> • Use FNSKU to label each item (cover barcode). Apply outer box/case label accordingly to match item# (Cover all existing barcodes on the box/case) | L24: =VLOOKUP(Table13[[#This Row],[SKU]],Instruction!A:G,7,0) -> 0 | M24: =VLOOKUP(Table13[[#This Row],[ASIN]],'[1]2024'!$A:$AB,28,0) -> No Supplies | N24: =VLOOKUP(Table13[[#This Row],[SKU]],Data1!A:C,3,0) -> 1 | O24: =VLOOKUP(Table13[[#This Row],[Item '#]],Data2!A:D,4,0) -> 24 | P24: =VLOOKUP(Table13[[#This Row],[Item '#]],Data2!A:D,3,0) -> 144 | Q24: 96 | R24: =VLOOKUP(Table13[[#This Row],[Item '#]],[2]Sheet1!$B:$D,3,0) -> 5784
A25: 4150-EACH | B25: B07Q5VSDJZ | C25: X003Y74FUN | D25: =VLOOKUP(Table13[[#This Row],[SKU]],Data1!A:B,2,0) -> 4150 | E25: =Table13[[#This Row],[UoM]]*Table13[[#This Row],[Recommended Replenishment Qty]] -> 72 | F25: =Table13[[#This Row],[Total EA (Transfer to WH06)]]/Table13[[#This Row],[UoM]] -> 72 | H25: =Table13[[#This Row],[Total EA (Transfer to WH06)]]/Table13[[#This Row],[CASE]] -> 6 | I25: =Table13[[#This Row],[Sellable Unit/Set/box to ship]]/Table13[[#This Row],[Case to pull]] -> 12 | J25: =IF(ISNUMBER(SEARCH("FNSKU",K25)),"Labeling","") -> Labeling | K25: =VLOOKUP(Table13[[#This Row],[SKU]],Instruction!A:F,6,0) -> • Use FNSKU to label each item (cover barcode). Apply outer box/case label accordingly to match item# (Cover all existing barcodes on the box/case) | L25: =VLOOKUP(Table13[[#This Row],[SKU]],Instruction!A:G,7,0) -> 0 | M25: =VLOOKUP(Table13[[#This Row],[ASIN]],'[1]2024'!$A:$AB,28,0) -> No Supplies | N25: =VLOOKUP(Table13[[#This Row],[SKU]],Data1!A:C,3,0) -> 1 | O25: =VLOOKUP(Table13[[#This Row],[Item '#]],Data2!A:D,4,0) -> 0 | P25: =VLOOKUP(Table13[[#This Row],[Item '#]],Data2!A:D,3,0) -> 12 | Q25: 72 | R25: =VLOOKUP(Table13[[#This Row],[Item '#]],[2]Sheet1!$B:$D,3,0) -> 1294
A26: 2315-EACH | B26: B07R289Y78 | C26: X0044R3MJ7 | D26: =VLOOKUP(Table13[[#This Row],[SKU]],Data1!A:B,2,0) -> 2315 | E26: =Table13[[#This Row],[UoM]]*Table13[[#This Row],[Recommended Replenishment Qty]] -> 144 | F26: =Table13[[#This Row],[Total EA (Transfer to WH06)]]/Table13[[#This Row],[UoM]] -> 144 | H26: =Table13[[#This Row],[Total EA (Transfer to WH06)]]/Table13[[#This Row],[CASE]] -> 1 | I26: =Table13[[#This Row],[Sellable Unit/Set/box to ship]]/Table13[[#This Row],[Case to pull]] -> 144 | J26: =IF(ISNUMBER(SEARCH("FNSKU",K26)),"Labeling","") -> Labeling | K26: =VLOOKUP(Table13[[#This Row],[SKU]],Instruction!A:F,6,0) -> • Use FNSKU to label each item (cover barcode). Apply outer box/case label accordingly to match item# (Cover all existing barcodes on the box/case) | L26: =VLOOKUP(Table13[[#This Row],[SKU]],Instruction!A:G,7,0) -> 0 | M26: =VLOOKUP(Table13[[#This Row],[ASIN]],'[1]2024'!$A:$AB,28,0) -> No Supplies | N26: =VLOOKUP(Table13[[#This Row],[SKU]],Data1!A:C,3,0) -> 1 | O26: =VLOOKUP(Table13[[#This Row],[Item '#]],Data2!A:D,4,0) -> 24 | P26: =VLOOKUP(Table13[[#This Row],[Item '#]],Data2!A:D,3,0) -> 144 | Q26: 144 | R26: =VLOOKUP(Table13[[#This Row],[Item '#]],[2]Sheet1!$B:$D,3,0) -> 41742
A27: 1906-EACH | B27: B003BMX3T4 | C27: B003BMX3T4 | D27: =VLOOKUP(Table13[[#This Row],[SKU]],Data1!A:B,2,0) -> 1906 | E27: =Table13[[#This Row],[UoM]]*Table13[[#This Row],[Recommended Replenishment Qty]] -> 96 | F27: =Table13[[#This Row],[Total EA (Transfer to WH06)]]/Table13[[#This Row],[UoM]] -> 96 | G27: =Table13[[#This Row],[Total EA (Transfer to WH06)]]/Table13[[#This Row],[BOX]] -> 4 | I27: =Table13[[#This Row],[Sellable Unit/Set/box to ship]]/Table13[[#This Row],[Box to pull]] -> 24 | J27: =IF(ISNUMBER(SEARCH("FNSKU",K27)),"Labeling","") | K27: =VLOOKUP(Table13[[#This Row],[SKU]],Instruction!A:F,6,0) -> Apply outer box/case label accordingly to match item# (Cover all existing barcodes on the box/case) | L27: =VLOOKUP(Table13[[#This Row],[SKU]],Instruction!A:G,7,0) -> 0 | M27: =VLOOKUP(Table13[[#This Row],[ASIN]],'[1]2024'!$A:$AB,28,0) -> No Supplies | N27: =VLOOKUP(Table13[[#This Row],[SKU]],Data1!A:C,3,0) -> 1 | O27: =VLOOKUP(Table13[[#This Row],[Item '#]],Data2!A:D,4,0) -> 24 | P27: =VLOOKUP(Table13[[#This Row],[Item '#]],Data2!A:D,3,0) -> 144 | Q27: 96 | R27: =VLOOKUP(Table13[[#This Row],[Item '#]],[2]Sheet1!$B:$D,3,0) -> 13635
A28: 203-EACH | B28: B08VCZ11NP | C28: X003Y7AI45 | D28: =VLOOKUP(Table13[[#This Row],[SKU]],Data1!A:B,2,0) -> 203 | E28: =Table13[[#This Row],[UoM]]*Table13[[#This Row],[Recommended Replenishment Qty]] -> 72 | F28: =Table13[[#This Row],[Total EA (Transfer to WH06)]]/Table13[[#This Row],[UoM]] -> 72 | G28: =Table13[[#This Row],[Total EA (Transfer to WH06)]]/Table13[[#This Row],[BOX]] -> 3 | I28: =Table13[[#This Row],[Sellable Unit/Set/box to ship]]/Table13[[#This Row],[Box to pull]] -> 24 | J28: =IF(ISNUMBER(SEARCH("FNSKU",K28)),"Labeling","") -> Labeling | K28: =VLOOKUP(Table13[[#This Row],[SKU]],Instruction!A:F,6,0) -> • Use FNSKU to label each item (cover barcode). Apply outer case label accordingly to match item# (Cover all existing barcodes on the case) | L28: =VLOOKUP(Table13[[#This Row],[SKU]],Instruction!A:G,7,0) -> 0 | M28: =VLOOKUP(Table13[[#This Row],[ASIN]],'[1]2024'!$A:$AB,28,0) -> No Supplies | N28: =VLOOKUP(Table13[[#This Row],[SKU]],Data1!A:C,3,0) -> 1 | O28: =VLOOKUP(Table13[[#This Row],[Item '#]],Data2!A:D,4,0) -> 24 | P28: =VLOOKUP(Table13[[#This Row],[Item '#]],Data2!A:D,3,0) -> 144 | Q28: 72 | R28: =VLOOKUP(Table13[[#This Row],[Item '#]],[2]Sheet1!$B:$D,3,0) -> 16948
A29: 5074-EACH | B29: B00IIN3K5I | C29: B00IIN3K5I | D29: =VLOOKUP(Table13[[#This Row],[SKU]],Data1!A:B,2,0) -> 5074 | E29: =Table13[[#This Row],[UoM]]*Table13[[#This Row],[Recommended Replenishment Qty]] -> 288 | F29: =Table13[[#This Row],[Total EA (Transfer to WH06)]]/Table13[[#This Row],[UoM]] -> 288 | H29: =Table13[[#This Row],[Total EA (Transfer to WH06)]]/Table13[[#This Row],[CASE]] -> 2 | I29: =Table13[[#This Row],[Sellable Unit/Set/box to ship]]/Table13[[#This Row],[Case to pull]] -> 144 | J29: =IF(ISNUMBER(SEARCH("FNSKU",K29)),"Labeling","") | K29: =VLOOKUP(Table13[[#This Row],[SKU]],Instruction!A:F,6,0) -> Apply outer box/case label accordingly to match item# (Cover all existing barcodes on the box/case) | L29: =VLOOKUP(Table13[[#This Row],[SKU]],Instruction!A:G,7,0) -> 0 | M29: =VLOOKUP(Table13[[#This Row],[ASIN]],'[1]2024'!$A:$AB,28,0) -> No Supplies | N29: =VLOOKUP(Table13[[#This Row],[SKU]],Data1!A:C,3,0) -> 1 | O29: =VLOOKUP(Table13[[#This Row],[Item '#]],Data2!A:D,4,0) -> 24 | P29: =VLOOKUP(Table13[[#This Row],[Item '#]],Data2!A:D,3,0) -> 144 | Q29: 288 | R29: =VLOOKUP(Table13[[#This Row],[Item '#]],[2]Sheet1!$B:$D,3,0) -> 52465
A30: 6120-EACH | B30: B09DJVP3DS | C30: B09DJVP3DS | D30: =VLOOKUP(Table13[[#This Row],[SKU]],Data1!A:B,2,0) -> 6120 | E30: =Table13[[#This Row],[UoM]]*Table13[[#This Row],[Recommended Replenishment Qty]] -> 1044 | F30: =Table13[[#This Row],[Total EA (Transfer to WH06)]]/Table13[[#This Row],[UoM]] -> 1044 | H30: =Table13[[#This Row],[Total EA (Transfer to WH06)]]/Table13[[#This Row],[CASE]] -> 29 | I30: =Table13[[#This Row],[Sellable Unit/Set/box to ship]]/Table13[[#This Row],[Case to pull]] -> 36 | J30: =IF(ISNUMBER(SEARCH("FNSKU",K30)),"Labeling","") | K30: =VLOOKUP(Table13[[#This Row],[SKU]],Instruction!A:F,6,0) -> Apply outer box/case label accordingly to match item# (Cover all existing barcodes on the box/case) | L30: =VLOOKUP(Table13[[#This Row],[SKU]],Instruction!A:G,7,0) -> 0 | M30: =VLOOKUP(Table13[[#This Row],[ASIN]],'[1]2024'!$A:$AB,28,0) -> No Supplies | N30: =VLOOKUP(Table13[[#This Row],[SKU]],Data1!A:C,3,0) -> 1 | O30: =VLOOKUP(Table13[[#This Row],[Item '#]],Data2!A:D,4,0) -> 0 | P30: =VLOOKUP(Table13[[#This Row],[Item '#]],Data2!A:D,3,0) -> 36 | Q30: 1044 | R30: =VLOOKUP(Table13[[#This Row],[Item '#]],[2]Sheet1!$B:$D,3,0) -> 9582
A31: 2202-EACH | B31: B003BNZVI4 | C31: B003BNZVI4 | D31: =VLOOKUP(Table13[[#This Row],[SKU]],Data1!A:B,2,0) -> 2202 | E31: =Table13[[#This Row],[UoM]]*Table13[[#This Row],[Recommended Replenishment Qty]] -> 1872 | F31: =Table13[[#This Row],[Total EA (Transfer to WH06)]]/Table13[[#This Row],[UoM]] -> 1872 | H31: =Table13[[#This Row],[Total EA (Transfer to WH06)]]/Table13[[#This Row],[CASE]] -> 13 | I31: =Table13[[#This Row],[Sellable Unit/Set/box to ship]]/Table13[[#This Row],[Case to pull]] -> 144 | J31: =IF(ISNUMBER(SEARCH("FNSKU",K31)),"Labeling","") | K31: =VLOOKUP(Table13[[#This Row],[SKU]],Instruction!A:F,6,0) -> Apply outer box/case label accordingly to match item# (Cover all existing barcodes on the box/case) | L31: =VLOOKUP(Table13[[#This Row],[SKU]],Instruction!A:G,7,0) -> 0 | M31: =VLOOKUP(Table13[[#This Row],[ASIN]],'[1]2024'!$A:$AB,28,0) -> No Supplies | N31: =VLOOKUP(Table13[[#This Row],[SKU]],Data1!A:C,3,0) -> 1 | O31: =VLOOKUP(Table13[[#This Row],[Item '#]],Data2!A:D,4,0) -> 24 | P31: =VLOOKUP(Table13[[#This Row],[Item '#]],Data2!A:D,3,0) -> 144 | Q31: 1872 | R31: =VLOOKUP(Table13[[#This Row],[Item '#]],[2]Sheet1!$B:$D,3,0) -> 21513
A32: 6003-EACH | B32: B002URU9G6 | C32: B002URU9G6 | D32: =VLOOKUP(Table13[[#This Row],[SKU]],Data1!A:B,2,0) -> 6003 | E32: =Table13[[#This Row],[UoM]]*Table13[[#This Row],[Recommended Replenishment Qty]] -> 576 | F32: =Table13[[#This Row],[Total EA (Transfer to WH06)]]/Table13[[#This Row],[UoM]] -> 576 | H32: =Table13[[#This Row],[Total EA (Transfer to WH06)]]/Table13[[#This Row],[CASE]] -> 4 | I32: =Table13[[#This Row],[Sellable Unit/Set/box to ship]]/Table13[[#This Row],[Case to pull]] -> 144 | J32: =IF(ISNUMBER(SEARCH("FNSKU",K32)),"Labeling","") -> Labeling | K32: =VLOOKUP(Table13[[#This Row],[SKU]],Instruction!A:F,6,0) -> • Use FNSKU to label each item (cover barcode). Apply outer box/case label accordingly to match item# (Cover all existing barcodes on the box/case) | L32: =VLOOKUP(Table13[[#This Row],[SKU]],Instruction!A:G,7,0) -> 0 | M32: =VLOOKUP(Table13[[#This Row],[ASIN]],'[1]2024'!$A:$AB,28,0) -> No Supplies | N32: =VLOOKUP(Table13[[#This Row],[SKU]],Data1!A:C,3,0) -> 1 | O32: =VLOOKUP(Table13[[#This Row],[Item '#]],Data2!A:D,4,0) -> 24 | P32: =VLOOKUP(Table13[[#This Row],[Item '#]],Data2!A:D,3,0) -> 144 | Q32: 576 | R32: =VLOOKUP(Table13[[#This Row],[Item '#]],[2]Sheet1!$B:$D,3,0) -> 12401
A33: 847-EACH | B33: B08QRDCTXN | C33: B08QRDCTXN | D33: =VLOOKUP(Table13[[#This Row],[SKU]],Data1!A:B,2,0) -> 847 | E33: =Table13[[#This Row],[UoM]]*Table13[[#This Row],[Recommended Replenishment Qty]] -> 144 | F33: =Table13[[#This Row],[Total EA (Transfer to WH06)]]/Table13[[#This Row],[UoM]] -> 144 | H33: =Table13[[#This Row],[Total EA (Transfer to WH06)]]/Table13[[#This Row],[CASE]] -> 6 | I33: =Table13[[#This Row],[Sellable Unit/Set/box to ship]]/Table13[[#This Row],[Case to pull]] -> 24 | J33: =IF(ISNUMBER(SEARCH("FNSKU",K33)),"Labeling","") | K33: =VLOOKUP(Table13[[#This Row],[SKU]],Instruction!A:F,6,0) -> Apply outer box/case label accordingly to match item# (Cover all existing barcodes on the box/case) | L33: =VLOOKUP(Table13[[#This Row],[SKU]],Instruction!A:G,7,0) -> 0 | M33: =VLOOKUP(Table13[[#This Row],[ASIN]],'[1]2024'!$A:$AB,28,0) -> No Supplies | N33: =VLOOKUP(Table13[[#This Row],[SKU]],Data1!A:C,3,0) -> 1 | O33: =VLOOKUP(Table13[[#This Row],[Item '#]],Data2!A:D,4,0) -> 0 | P33: =VLOOKUP(Table13[[#This Row],[Item '#]],Data2!A:D,3,0) -> 24 | Q33: 144 | R33: =VLOOKUP(Table13[[#This Row],[Item '#]],[2]Sheet1!$B:$D,3,0) -> 20841
A34: 2309-EACH-B | B34: B0C4VY1LR7 | C34: B0C4VY1LR7 | D34: =VLOOKUP(Table13[[#This Row],[SKU]],Data1!A:B,2,0) -> 2309 | E34: =Table13[[#This Row],[UoM]]*Table13[[#This Row],[Recommended Replenishment Qty]] -> 288 | F34: =Table13[[#This Row],[Total EA (Transfer to WH06)]]/Table13[[#This Row],[UoM]] -> 288 | H34: =Table13[[#This Row],[Total EA (Transfer to WH06)]]/Table13[[#This Row],[CASE]] -> 2 | I34: =Table13[[#This Row],[Sellable Unit/Set/box to ship]]/Table13[[#This Row],[Case to pull]] -> 144 | J34: =IF(ISNUMBER(SEARCH("FNSKU",K34)),"Labeling","") | K34: =VLOOKUP(Table13[[#This Row],[SKU]],Instruction!A:F,6,0) -> Apply outer case label accordingly to match item# (Cover all existing barcodes on the case) | L34: =VLOOKUP(Table13[[#This Row],[SKU]],Instruction!A:G,7,0) -> 0 | M34: =VLOOKUP(Table13[[#This Row],[ASIN]],'[1]2024'!$A:$AB,28,0) -> No Supplies | N34: =VLOOKUP(Table13[[#This Row],[SKU]],Data1!A:C,3,0) -> 1 | O34: =VLOOKUP(Table13[[#This Row],[Item '#]],Data2!A:D,4,0) -> 24 | P34: =VLOOKUP(Table13[[#This Row],[Item '#]],Data2!A:D,3,0) -> 144 | Q34: 288 | R34: =VLOOKUP(Table13[[#This Row],[Item '#]],[2]Sheet1!$B:$D,3,0) -> 6630
A35: 508-EACH | B35: B001E75OY0 | C35: B001E75OY0 | D35: =VLOOKUP(Table13[[#This Row],[SKU]],Data1!A:B,2,0) -> 508 | E35: =Table13[[#This Row],[UoM]]*Table13[[#This Row],[Recommended Replenishment Qty]] -> 672 | F35: =Table13[[#This Row],[Total EA (Transfer to WH06)]]/Table13[[#This Row],[UoM]] -> 672 | H35: =Table13[[#This Row],[Total EA (Transfer to WH06)]]/Table13[[#This Row],[CASE]] -> 14 | I35: =Table13[[#This Row],[Sellable Unit/Set/box to ship]]/Table13[[#This Row],[Case to pull]] -> 48 | J35: =IF(ISNUMBER(SEARCH("FNSKU",K35)),"Labeling","") | K35: =VLOOKUP(Table13[[#This Row],[SKU]],Instruction!A:F,6,0) -> Apply outer box/case label accordingly to match item# (Cover all existing barcodes on the box/case) | L35: =VLOOKUP(Table13[[#This Row],[SKU]],Instruction!A:G,7,0) -> 0 | M35: =VLOOKUP(Table13[[#This Row],[ASIN]],'[1]2024'!$A:$AB,28,0) -> No Supplies | N35: =VLOOKUP(Table13[[#This Row],[SKU]],Data1!A:C,3,0) -> 1 | O35: =VLOOKUP(Table13[[#This Row],[Item '#]],Data2!A:D,4,0) -> 0 | P35: =VLOOKUP(Table13[[#This Row],[Item '#]],Data2!A:D,3,0) -> 48 | Q35: 672 | R35: =VLOOKUP(Table13[[#This Row],[Item '#]],[2]Sheet1!$B:$D,3,0) -> 124792
A36: 6110-EACH | B36: B07SC668W8 | C36: X002GASSMF | D36: =VLOOKUP(Table13[[#This Row],[SKU]],Data1!A:B,2,0) -> 6110 | E36: =Table13[[#This Row],[UoM]]*Table13[[#This Row],[Recommended Replenishment Qty]] -> 972 | F36: =Table13[[#This Row],[Total EA (Transfer to WH06)]]/Table13[[#This Row],[UoM]] -> 972 | H36: =Table13[[#This Row],[Total EA (Transfer to WH06)]]/Table13[[#This Row],[CASE]] -> 27 | I36: =Table13[[#This Row],[Sellable Unit/Set/box to ship]]/Table13[[#This Row],[Case to pull]] -> 36 | J36: =IF(ISNUMBER(SEARCH("FNSKU",K36)),"Labeling","") -> Labeling | K36: =VLOOKUP(Table13[[#This Row],[SKU]],Instruction!A:F,6,0) -> • Use FNSKU to label each item (cover barcode). Apply outer box/case label accordingly to match item# (Cover all existing barcodes on the box/case) | L36: =VLOOKUP(Table13[[#This Row],[SKU]],Instruction!A:G,7,0) -> 0 | M36: =VLOOKUP(Table13[[#This Row],[ASIN]],'[1]2024'!$A:$AB,28,0) -> No Supplies | N36: =VLOOKUP(Table13[[#This Row],[SKU]],Data1!A:C,3,0) -> 1 | O36: =VLOOKUP(Table13[[#This Row],[Item '#]],Data2!A:D,4,0) -> 0 | P36: =VLOOKUP(Table13[[#This Row],[Item '#]],Data2!A:D,3,0) -> 36 | Q36: 972 | R36: =VLOOKUP(Table13[[#This Row],[Item '#]],[2]Sheet1!$B:$D,3,0) -> 16524
A37: 6100-EACH | B37: B00GSSDLMM | C37: B00GSSDLMM | D37: =VLOOKUP(Table13[[#This Row],[SKU]],Data1!A:B,2,0) -> 6100 | E37: =Table13[[#This Row],[UoM]]*Table13[[#This Row],[Recommended Replenishment Qty]] -> 1692 | F37: =Table13[[#This Row],[Total EA (Transfer to WH06)]]/Table13[[#This Row],[UoM]] -> 1692 | H37: =Table13[[#This Row],[Total EA (Transfer to WH06)]]/Table13[[#This Row],[CASE]] -> 47 | I37: =Table13[[#This Row],[Sellable Unit/Set/box to ship]]/Table13[[#This Row],[Case to pull]] -> 36 | J37: =IF(ISNUMBER(SEARCH("FNSKU",K37)),"Labeling","") | K37: =VLOOKUP(Table13[[#This Row],[SKU]],Instruction!A:F,6,0) -> Apply outer box/case label accordingly to match item# (Cover all existing barcodes on box and case) | L37: =VLOOKUP(Table13[[#This Row],[SKU]],Instruction!A:G,7,0) -> 0 | M37: =VLOOKUP(Table13[[#This Row],[ASIN]],'[1]2024'!$A:$AB,28,0) -> No Supplies | N37: =VLOOKUP(Table13[[#This Row],[SKU]],Data1!A:C,3,0) -> 1 | O37: =VLOOKUP(Table13[[#This Row],[Item '#]],Data2!A:D,4,0) -> 0 | P37: =VLOOKUP(Table13[[#This Row],[Item '#]],Data2!A:D,3,0) -> 36 | Q37: 1692 | R37: =VLOOKUP(Table13[[#This Row],[Item '#]],[2]Sheet1!$B:$D,3,0) -> 9888
A38: 336-EACH | B38: B003BMX65A | C38: X003TIPAXN | D38: =VLOOKUP(Table13[[#This Row],[SKU]],Data1!A:B,2,0) -> 336 | E38: =Table13[[#This Row],[UoM]]*Table13[[#This Row],[Recommended Replenishment Qty]] -> 1152 | F38: =Table13[[#This Row],[Total EA (Transfer to WH06)]]/Table13[[#This Row],[UoM]] -> 1152 | H38: =Table13[[#This Row],[Total EA (Transfer to WH06)]]/Table13[[#This Row],[CASE]] -> 8 | I38: =Table13[[#This Row],[Sellable Unit/Set/box to ship]]/Table13[[#This Row],[Case to pull]] -> 144 | J38: =IF(ISNUMBER(SEARCH("FNSKU",K38)),"Labeling","") -> Labeling | K38: =VLOOKUP(Table13[[#This Row],[SKU]],Instruction!A:F,6,0) -> • Use FNSKU to label each item (cover barcode). Apply outer box/case label accordingly to match item# (Cover all existing barcodes on the box/case) | L38: =VLOOKUP(Table13[[#This Row],[SKU]],Instruction!A:G,7,0) -> 0 | M38: =VLOOKUP(Table13[[#This Row],[ASIN]],'[1]2024'!$A:$AB,28,0) -> No Supplies | N38: =VLOOKUP(Table13[[#This Row],[SKU]],Data1!A:C,3,0) -> 1 | O38: =VLOOKUP(Table13[[#This Row],[Item '#]],Data2!A:D,4,0) -> 24 | P38: =VLOOKUP(Table13[[#This Row],[Item '#]],Data2!A:D,3,0) -> 144 | Q38: 1152 | R38: =VLOOKUP(Table13[[#This Row],[Item '#]],[2]Sheet1!$B:$D,3,0) -> 42004
A39: 3103-EACH | B39: B003BSFCMY | C39: B003BSFCMY | D39: =VLOOKUP(Table13[[#This Row],[SKU]],Data1!A:B,2,0) -> 3103 | E39: =Table13[[#This Row],[UoM]]*Table13[[#This Row],[Recommended Replenishment Qty]] -> 240 | F39: =Table13[[#This Row],[Total EA (Transfer to WH06)]]/Table13[[#This Row],[UoM]] -> 240 | H39: =Table13[[#This Row],[Total EA (Transfer to WH06)]]/Table13[[#This Row],[CASE]] -> 5 | I39: =Table13[[#This Row],[Sellable Unit/Set/box to ship]]/Table13[[#This Row],[Case to pull]] -> 48 | J39: =IF(ISNUMBER(SEARCH("FNSKU",K39)),"Labeling","") | K39: =VLOOKUP(Table13[[#This Row],[SKU]],Instruction!A:F,6,0) -> Apply outer box/case label accordingly to match item# (Cover all existing barcodes on the box/case) | L39: =VLOOKUP(Table13[[#This Row],[SKU]],Instruction!A:G,7,0) -> 0 | M39: =VLOOKUP(Table13[[#This Row],[ASIN]],'[1]2024'!$A:$AB,28,0) -> No Supplies | N39: =VLOOKUP(Table13[[#This Row],[SKU]],Data1!A:C,3,0) -> 1 | O39: =VLOOKUP(Table13[[#This Row],[Item '#]],Data2!A:D,4,0) -> 0 | P39: =VLOOKUP(Table13[[#This Row],[Item '#]],Data2!A:D,3,0) -> 48 | Q39: 240 | R39: =VLOOKUP(Table13[[#This Row],[Item '#]],[2]Sheet1!$B:$D,3,0) -> 6481
A40: 4398-EACH | B40: B07SFKBQ7F | C40: X003GYE2EX | D40: =VLOOKUP(Table13[[#This Row],[SKU]],Data1!A:B,2,0) -> 4398 | E40: =Table13[[#This Row],[UoM]]*Table13[[#This Row],[Recommended Replenishment Qty]] -> 1008 | F40: =Table13[[#This Row],[Total EA (Transfer to WH06)]]/Table13[[#This Row],[UoM]] -> 1008 | H40: =Table13[[#This Row],[Total EA (Transfer to WH06)]]/Table13[[#This Row],[CASE]] -> 7 | I40: =Table13[[#This Row],[Sellable Unit/Set/box to ship]]/Table13[[#This Row],[Case to pull]] -> 144 | J40: =IF(ISNUMBER(SEARCH("FNSKU",K40)),"Labeling","") -> Labeling | K40: =VLOOKUP(Table13[[#This Row],[SKU]],Instruction!A:F,6,0) -> • Use FNSKU to label each item (cover barcode). Apply outer box/case label accordingly to match item# (Cover all existing barcodes on the box/case) | L40: =VLOOKUP(Table13[[#This Row],[SKU]],Instruction!A:G,7,0) -> 0 | M40: =VLOOKUP(Table13[[#This Row],[ASIN]],'[1]2024'!$A:$AB,28,0) -> No Supplies | N40: =VLOOKUP(Table13[[#This Row],[SKU]],Data1!A:C,3,0) -> 1 | O40: =VLOOKUP(Table13[[#This Row],[Item '#]],Data2!A:D,4,0) -> 24 | P40: =VLOOKUP(Table13[[#This Row],[Item '#]],Data2!A:D,3,0) -> 144 | Q40: 1008 | R40: =VLOOKUP(Table13[[#This Row],[Item '#]],[2]Sheet1!$B:$D,3,0) -> 19292
A41: 2330-EACH | B41: B00TQ5WT4U | C41: B00TQ5WT4U | D41: =VLOOKUP(Table13[[#This Row],[SKU]],Data1!A:B,2,0) -> 2330 | E41: =Table13[[#This Row],[UoM]]*Table13[[#This Row],[Recommended Replenishment Qty]] -> 120 | F41: =Table13[[#This Row],[Total EA (Transfer to WH06)]]/Table13[[#This Row],[UoM]] -> 120 | G41: =Table13[[#This Row],[Total EA (Transfer to WH06)]]/Table13[[#This Row],[BOX]] -> 5 | I41: =Table13[[#This Row],[Sellable Unit/Set/box to ship]]/Table13[[#This Row],[Box to pull]] -> 24 | J41: =IF(ISNUMBER(SEARCH("FNSKU",K41)),"Labeling","") | K41: =VLOOKUP(Table13[[#This Row],[SKU]],Instruction!A:F,6,0) -> Apply outer box/case label accordingly to match item# (Cover all existing barcodes on the box/case) | L41: =VLOOKUP(Table13[[#This Row],[SKU]],Instruction!A:G,7,0) -> 0 | M41: =VLOOKUP(Table13[[#This Row],[ASIN]],'[1]2024'!$A:$AB,28,0) -> No Supplies | N41: =VLOOKUP(Table13[[#This Row],[SKU]],Data1!A:C,3,0) -> 1 | O41: =VLOOKUP(Table13[[#This Row],[Item '#]],Data2!A:D,4,0) -> 24 | P41: =VLOOKUP(Table13[[#This Row],[Item '#]],Data2!A:D,3,0) -> 144 | Q41: 120 | R41: =VLOOKUP(Table13[[#This Row],[Item '#]],[2]Sheet1!$B:$D,3,0) -> 10825
A42: 929-EACH | B42: B00GTJD0V2 | C42: B00GTJD0V2 | D42: =VLOOKUP(Table13[[#This Row],[SKU]],Data1!A:B,2,0) -> 929 | E42: =Table13[[#This Row],[UoM]]*Table13[[#This Row],[Recommended Replenishment Qty]] -> 576 | F42: =Table13[[#This Row],[Total EA (Transfer to WH06)]]/Table13[[#This Row],[UoM]] -> 576 | H42: =Table13[[#This Row],[Total EA (Transfer to WH06)]]/Table13[[#This Row],[CASE]] -> 4 | I42: =Table13[[#This Row],[Sellable Unit/Set/box to ship]]/Table13[[#This Row],[Case to pull]] -> 144 | J42: =IF(ISNUMBER(SEARCH("FNSKU",K42)),"Labeling","") | K42: =VLOOKUP(Table13[[#This Row],[SKU]],Instruction!A:F,6,0) -> Apply outer case label accordingly to match item# (Cover all existing barcodes on the case) | L42: =VLOOKUP(Table13[[#This Row],[SKU]],Instruction!A:G,7,0) -> 0 | M42: =VLOOKUP(Table13[[#This Row],[ASIN]],'[1]2024'!$A:$AB,28,0) -> No Supplies | N42: =VLOOKUP(Table13[[#This Row],[SKU]],Data1!A:C,3,0) -> 1 | O42: =VLOOKUP(Table13[[#This Row],[Item '#]],Data2!A:D,4,0) -> 24 | P42: =VLOOKUP(Table13[[#This Row],[Item '#]],Data2!A:D,3,0) -> 144 | Q42: 576 | R42: =VLOOKUP(Table13[[#This Row],[Item '#]],[2]Sheet1!$B:$D,3,0) -> 40589
A43: 520-EACH | B43: B07S962L7Q | C43: X0044RLTFV | D43: =VLOOKUP(Table13[[#This Row],[SKU]],Data1!A:B,2,0) -> 520 | E43: =Table13[[#This Row],[UoM]]*Table13[[#This Row],[Recommended Replenishment Qty]] -> 432 | F43: =Table13[[#This Row],[Total EA (Transfer to WH06)]]/Table13[[#This Row],[UoM]] -> 432 | H43: =Table13[[#This Row],[Total EA (Transfer to WH06)]]/Table13[[#This Row],[CASE]] -> 12 | I43: =Table13[[#This Row],[Sellable Unit/Set/box to ship]]/Table13[[#This Row],[Case to pull]] -> 36 | J43: =IF(ISNUMBER(SEARCH("FNSKU",K43)),"Labeling","") -> Labeling | K43: =VLOOKUP(Table13[[#This Row],[SKU]],Instruction!A:F,6,0) -> • Use FNSKU to label each item (cover barcode). Apply outer case label accordingly to match item# (Cover all existing barcodes on the case) | L43: =VLOOKUP(Table13[[#This Row],[SKU]],Instruction!A:G,7,0) -> 0 | M43: =VLOOKUP(Table13[[#This Row],[ASIN]],'[1]2024'!$A:$AB,28,0) -> No Supplies | N43: =VLOOKUP(Table13[[#This Row],[SKU]],Data1!A:C,3,0) -> 1 | O43: =VLOOKUP(Table13[[#This Row],[Item '#]],Data2!A:D,4,0) -> 0 | P43: =VLOOKUP(Table13[[#This Row],[Item '#]],Data2!A:D,3,0) -> 36 | Q43: 432 | R43: =VLOOKUP(Table13[[#This Row],[Item '#]],[2]Sheet1!$B:$D,3,0) -> 13893
A44: 1292-EACH | B44: B0B9Q8LBNN | C44: B0B9Q8LBNN | D44: =VLOOKUP(Table13[[#This Row],[SKU]],Data1!A:B,2,0) -> 1292 | E44: =Table13[[#This Row],[UoM]]*Table13[[#This Row],[Recommended Replenishment Qty]] -> 24 | F44: =Table13[[#This Row],[Total EA (Transfer to WH06)]]/Table13[[#This Row],[UoM]] -> 24 | G44: =Table13[[#This Row],[Total EA (Transfer to WH06)]]/Table13[[#This Row],[BOX]] -> 1 | I44: =Table13[[#This Row],[Sellable Unit/Set/box to ship]]/Table13[[#This Row],[Box to pull]] -> 24 | J44: =IF(ISNUMBER(SEARCH("FNSKU",K44)),"Labeling","") | K44: =VLOOKUP(Table13[[#This Row],[SKU]],Instruction!A:F,6,0) -> Apply outer box/case label accordingly to match item# (Cover all existing barcodes on the box/case) | L44: =VLOOKUP(Table13[[#This Row],[SKU]],Instruction!A:G,7,0) -> 0 | M44: =VLOOKUP(Table13[[#This Row],[ASIN]],'[1]2024'!$A:$AB,28,0) -> No Supplies | N44: =VLOOKUP(Table13[[#This Row],[SKU]],Data1!A:C,3,0) -> 1 | O44: =VLOOKUP(Table13[[#This Row],[Item '#]],Data2!A:D,4,0) -> 24 | P44: =VLOOKUP(Table13[[#This Row],[Item '#]],Data2!A:D,3,0) -> 144 | Q44: 24 | R44: =VLOOKUP(Table13[[#This Row],[Item '#]],[2]Sheet1!$B:$D,3,0) -> 17572
A45: 2206-EACH | B45: B07RPR34BJ | C45: X002GAOOB9 | D45: =VLOOKUP(Table13[[#This Row],[SKU]],Data1!A:B,2,0) -> 2206 | E45: =Table13[[#This Row],[UoM]]*Table13[[#This Row],[Recommended Replenishment Qty]] -> 720 | F45: =Table13[[#This Row],[Total EA (Transfer to WH06)]]/Table13[[#This Row],[UoM]] -> 720 | H45: =Table13[[#This Row],[Total EA (Transfer to WH06)]]/Table13[[#This Row],[CASE]] -> 5 | I45: =Table13[[#This Row],[Sellable Unit/Set/box to ship]]/Table13[[#This Row],[Case to pull]] -> 144 | J45: =IF(ISNUMBER(SEARCH("FNSKU",K45)),"Labeling","") -> Labeling | K45: =VLOOKUP(Table13[[#This Row],[SKU]],Instruction!A:F,6,0) -> • Use FNSKU to label each item (cover barcode). Apply outer box/case label accordingly to match item# (Cover all existing barcodes on the box/case) | L45: =VLOOKUP(Table13[[#This Row],[SKU]],Instruction!A:G,7,0) -> 0 | M45: =VLOOKUP(Table13[[#This Row],[ASIN]],'[1]2024'!$A:$AB,28,0) -> No Supplies | N45: =VLOOKUP(Table13[[#This Row],[SKU]],Data1!A:C,3,0) -> 1 | O45: =VLOOKUP(Table13[[#This Row],[Item '#]],Data2!A:D,4,0) -> 24 | P45: =VLOOKUP(Table13[[#This Row],[Item '#]],Data2!A:D,3,0) -> 144 | Q45: 720 | R45: =VLOOKUP(Table13[[#This Row],[Item '#]],[2]Sheet1!$B:$D,3,0) -> 26114
A46: 4124-EACH | B46: B07Q714JRN | C46: B07Q714JRN | D46: =VLOOKUP(Table13[[#This Row],[SKU]],Data1!A:B,2,0) -> 4124 | E46: =Table13[[#This Row],[UoM]]*Table13[[#This Row],[Recommended Replenishment Qty]] -> 132 | F46: =Table13[[#This Row],[Total EA (Transfer to WH06)]]/Table13[[#This Row],[UoM]] -> 132 | H46: =Table13[[#This Row],[Total EA (Transfer to WH06)]]/Table13[[#This Row],[CASE]] -> 11 | I46: =Table13[[#This Row],[Sellable Unit/Set/box to ship]]/Table13[[#This Row],[Case to pull]] -> 12 | J46: =IF(ISNUMBER(SEARCH("FNSKU",K46)),"Labeling","") | K46: =VLOOKUP(Table13[[#This Row],[SKU]],Instruction!A:F,6,0) -> Apply outer box/case label accordingly to match item# (Cover all existing barcodes on the box/case) | L46: =VLOOKUP(Table13[[#This Row],[SKU]],Instruction!A:G,7,0) -> 0 | M46: =VLOOKUP(Table13[[#This Row],[ASIN]],'[1]2024'!$A:$AB,28,0) -> No Supplies | N46: =VLOOKUP(Table13[[#This Row],[SKU]],Data1!A:C,3,0) -> 1 | O46: =VLOOKUP(Table13[[#This Row],[Item '#]],Data2!A:D,4,0) -> 0 | P46: =VLOOKUP(Table13[[#This Row],[Item '#]],Data2!A:D,3,0) -> 12 | Q46: 132 | R46: =VLOOKUP(Table13[[#This Row],[Item '#]],[2]Sheet1!$B:$D,3,0) -> 17484
A47: 3109-EACH | B47: B001GE6ACG | C47: B001GE6ACG | D47: =VLOOKUP(Table13[[#This Row],[SKU]],Data1!A:B,2,0) -> 3109 | E47: =Table13[[#This Row],[UoM]]*Table13[[#This Row],[Recommended Replenishment Qty]] -> 192 | F47: =Table13[[#This Row],[Total EA (Transfer to WH06)]]/Table13[[#This Row],[UoM]] -> 192 | H47: =Table13[[#This Row],[Total EA (Transfer to WH06)]]/Table13[[#This Row],[CASE]] -> 4 | I47: =Table13[[#This Row],[Sellable Unit/Set/box to ship]]/Table13[[#This Row],[Case to pull]] -> 48 | J47: =IF(ISNUMBER(SEARCH("FNSKU",K47)),"Labeling","") | K47: =VLOOKUP(Table13[[#This Row],[SKU]],Instruction!A:F,6,0) -> Apply outer box/case label accordingly to match item# (Cover all existing barcodes on the box/case) | L47: =VLOOKUP(Table13[[#This Row],[SKU]],Instruction!A:G,7,0) -> 0 | M47: =VLOOKUP(Table13[[#This Row],[ASIN]],'[1]2024'!$A:$AB,28,0) -> No Supplies | N47: =VLOOKUP(Table13[[#This Row],[SKU]],Data1!A:C,3,0) -> 1 | O47: =VLOOKUP(Table13[[#This Row],[Item '#]],Data2!A:D,4,0) -> 0 | P47: =VLOOKUP(Table13[[#This Row],[Item '#]],Data2!A:D,3,0) -> 48 | Q47: 192 | R47: =VLOOKUP(Table13[[#This Row],[Item '#]],[2]Sheet1!$B:$D,3,0) -> 60395
A48: 1502-EACH | B48: B002WFI620 | C48: B002WFI620 | D48: =VLOOKUP(Table13[[#This Row],[SKU]],Data1!A:B,2,0) -> 1502 | E48: =Table13[[#This Row],[UoM]]*Table13[[#This Row],[Recommended Replenishment Qty]] -> 1152 | F48: =Table13[[#This Row],[Total EA (Transfer to WH06)]]/Table13[[#This Row],[UoM]] -> 1152 | H48: =Table13[[#This Row],[Total EA (Transfer to WH06)]]/Table13[[#This Row],[CASE]] -> 8 | I48: =Table13[[#This Row],[Sellable Unit/Set/box to ship]]/Table13[[#This Row],[Case to pull]] -> 144 | J48: =IF(ISNUMBER(SEARCH("FNSKU",K48)),"Labeling","") | K48: =VLOOKUP(Table13[[#This Row],[SKU]],Instruction!A:F,6,0) -> Cover inner box barcode. Apply outer case label accordingly to match item# (Cover barcodes on the case) | L48: =VLOOKUP(Table13[[#This Row],[SKU]],Instruction!A:G,7,0) -> 0 | M48: =VLOOKUP(Table13[[#This Row],[ASIN]],'[1]2024'!$A:$AB,28,0) -> No Supplies | N48: =VLOOKUP(Table13[[#This Row],[SKU]],Data1!A:C,3,0) -> 1 | O48: =VLOOKUP(Table13[[#This Row],[Item '#]],Data2!A:D,4,0) -> 24 | P48: =VLOOKUP(Table13[[#This Row],[Item '#]],Data2!A:D,3,0) -> 144 | Q48: 1152 | R48: =VLOOKUP(Table13[[#This Row],[Item '#]],[2]Sheet1!$B:$D,3,0) -> 5465
A49: 6303-EACH | B49: B08P3WZTXG | C49: B08P3WZTXG | D49: =VLOOKUP(Table13[[#This Row],[SKU]],Data1!A:B,2,0) -> 6303 | E49: =Table13[[#This Row],[UoM]]*Table13[[#This Row],[Recommended Replenishment Qty]] -> 72 | F49: =Table13[[#This Row],[Total EA (Transfer to WH06)]]/Table13[[#This Row],[UoM]] -> 72 | G49: =Table13[[#This Row],[Total EA (Transfer to WH06)]]/Table13[[#This Row],[BOX]] -> 3 | I49: =Table13[[#This Row],[Sellable Unit/Set/box to ship]]/Table13[[#This Row],[Box to pull]] -> 24 | J49: =IF(ISNUMBER(SEARCH("FNSKU",K49)),"Labeling","") | K49: =VLOOKUP(Table13[[#This Row],[SKU]],Instruction!A:F,6,0) -> Cover inner box barcode. Apply outer case label accordingly to match item# (Cover barcodes on the case) | L49: =VLOOKUP(Table13[[#This Row],[SKU]],Instruction!A:G,7,0) -> 0 | M49: =VLOOKUP(Table13[[#This Row],[ASIN]],'[1]2024'!$A:$AB,28,0) -> No Supplies | N49: =VLOOKUP(Table13[[#This Row],[SKU]],Data1!A:C,3,0) -> 1 | O49: =VLOOKUP(Table13[[#This Row],[Item '#]],Data2!A:D,4,0) -> 24 | P49: =VLOOKUP(Table13[[#This Row],[Item '#]],Data2!A:D,3,0) -> 144 | Q49: 72 | R49: =VLOOKUP(Table13[[#This Row],[Item '#]],[2]Sheet1!$B:$D,3,0) -> -131
A50: 304-EACH | B50: B0019IO3VY | C50: B0019IO3VY | D50: =VLOOKUP(Table13[[#This Row],[SKU]],Data1!A:B,2,0) -> 304 | E50: =Table13[[#This Row],[UoM]]*Table13[[#This Row],[Recommended Replenishment Qty]] -> 120 | F50: =Table13[[#This Row],[Total EA (Transfer to WH06)]]/Table13[[#This Row],[UoM]] -> 120 | G50: =Table13[[#This Row],[Total EA (Transfer to WH06)]]/Table13[[#This Row],[BOX]] -> 5 | I50: =Table13[[#This Row],[Sellable Unit/Set/box to ship]]/Table13[[#This Row],[Box to pull]] -> 24 | J50: =IF(ISNUMBER(SEARCH("FNSKU",K50)),"Labeling","") | K50: =VLOOKUP(Table13[[#This Row],[SKU]],Instruction!A:F,6,0) -> Apply outer box/case label accordingly to match item# (Cover all existing barcodes on the box/case) | L50: =VLOOKUP(Table13[[#This Row],[SKU]],Instruction!A:G,7,0) -> 0 | M50: =VLOOKUP(Table13[[#This Row],[ASIN]],'[1]2024'!$A:$AB,28,0) -> No Supplies | N50: =VLOOKUP(Table13[[#This Row],[SKU]],Data1!A:C,3,0) -> 1 | O50: =VLOOKUP(Table13[[#This Row],[Item '#]],Data2!A:D,4,0) -> 24 | P50: =VLOOKUP(Table13[[#This Row],[Item '#]],Data2!A:D,3,0) -> 288 | Q50: 120 | R50: =VLOOKUP(Table13[[#This Row],[Item '#]],[2]Sheet1!$B:$D,3,0) -> 24396
A51: 540-EACH | B51: B0BCM2D62W | C51: X003GYFQHF | D51: =VLOOKUP(Table13[[#This Row],[SKU]],Data1!A:B,2,0) -> 540 | E51: =Table13[[#This Row],[UoM]]*Table13[[#This Row],[Recommended Replenishment Qty]] -> 48 | F51: =Table13[[#This Row],[Total EA (Transfer to WH06)]]/Table13[[#This Row],[UoM]] -> 48 | H51: =Table13[[#This Row],[Total EA (Transfer to WH06)]]/Table13[[#This Row],[CASE]] -> 1 | I51: =Table13[[#This Row],[Sellable Unit/Set/box to ship]]/Table13[[#This Row],[Case to pull]] -> 48 | J51: =IF(ISNUMBER(SEARCH("FNSKU",K51)),"Labeling","") -> Labeling | K51: =VLOOKUP(Table13[[#This Row],[SKU]],Instruction!A:F,6,0) -> • Use FNSKU to label each item (cover barcode). Apply outer box/case label accordingly to match item# (Cover all existing barcodes on the box/case) | L51: =VLOOKUP(Table13[[#This Row],[SKU]],Instruction!A:G,7,0) -> 0 | M51: =VLOOKUP(Table13[[#This Row],[ASIN]],'[1]2024'!$A:$AB,28,0) -> No Supplies | N51: =VLOOKUP(Table13[[#This Row],[SKU]],Data1!A:C,3,0) -> 1 | O51: =VLOOKUP(Table13[[#This Row],[Item '#]],Data2!A:D,4,0) -> 0 | P51: =VLOOKUP(Table13[[#This Row],[Item '#]],Data2!A:D,3,0) -> 48 | Q51: 48 | R51: =VLOOKUP(Table13[[#This Row],[Item '#]],[2]Sheet1!$B:$D,3,0) -> 9965
A52: 229-EACH | B52: B003BUJXSQ | C52: B003BUJXSQ | D52: =VLOOKUP(Table13[[#This Row],[SKU]],Data1!A:B,2,0) -> 229 | E52: =Table13[[#This Row],[UoM]]*Table13[[#This Row],[Recommended Replenishment Qty]] -> 144 | F52: =Table13[[#This Row],[Total EA (Transfer to WH06)]]/Table13[[#This Row],[UoM]] -> 144 | H52: =Table13[[#This Row],[Total EA (Transfer to WH06)]]/Table13[[#This Row],[CASE]] -> 1 | I52: =Table13[[#This Row],[Sellable Unit/Set/box to ship]]/Table13[[#This Row],[Case to pull]] -> 144 | J52: =IF(ISNUMBER(SEARCH("FNSKU",K52)),"Labeling","") | K52: =VLOOKUP(Table13[[#This Row],[SKU]],Instruction!A:F,6,0) -> Apply outer box/case label accordingly to match item# (Cover all existing barcodes on the box/case) | L52: =VLOOKUP(Table13[[#This Row],[SKU]],Instruction!A:G,7,0) -> 0 | M52: =VLOOKUP(Table13[[#This Row],[ASIN]],'[1]2024'!$A:$AB,28,0) -> No Supplies | N52: =VLOOKUP(Table13[[#This Row],[SKU]],Data1!A:C,3,0) -> 1 | O52: =VLOOKUP(Table13[[#This Row],[Item '#]],Data2!A:D,4,0) -> 24 | P52: =VLOOKUP(Table13[[#This Row],[Item '#]],Data2!A:D,3,0) -> 144 | Q52: 144 | R52: =VLOOKUP(Table13[[#This Row],[Item '#]],[2]Sheet1!$B:$D,3,0) -> 24750
A53: 834-EACH | B53: B0D7RN1FV3 | C53: B0D7RN1FV3 | D53: =VLOOKUP(Table13[[#This Row],[SKU]],Data1!A:B,2,0) -> 834 | E53: =Table13[[#This Row],[UoM]]*Table13[[#This Row],[Recommended Replenishment Qty]] -> 72 | F53: =Table13[[#This Row],[Total EA (Transfer to WH06)]]/Table13[[#This Row],[UoM]] -> 72 | H53: =Table13[[#This Row],[Total EA (Transfer to WH06)]]/Table13[[#This Row],[CASE]] -> 3 | I53: =Table13[[#This Row],[Sellable Unit/Set/box to ship]]/Table13[[#This Row],[Case to pull]] -> 24 | J53: =IF(ISNUMBER(SEARCH("FNSKU",K53)),"Labeling","") | K53: =VLOOKUP(Table13[[#This Row],[SKU]],Instruction!A:F,6,0) -> Apply outer box/case label accordingly to match item# (Cover all existing barcodes on the box/case) | L53: =VLOOKUP(Table13[[#This Row],[SKU]],Instruction!A:G,7,0) -> 0 | M53: =VLOOKUP(Table13[[#This Row],[ASIN]],'[1]2024'!$A:$AB,28,0) -> #N/A | N53: =VLOOKUP(Table13[[#This Row],[SKU]],Data1!A:C,3,0) -> 1 | O53: =VLOOKUP(Table13[[#This Row],[Item '#]],Data2!A:D,4,0) -> 0 | P53: =VLOOKUP(Table13[[#This Row],[Item '#]],Data2!A:D,3,0) -> 24 | Q53: 72 | R53: =VLOOKUP(Table13[[#This Row],[Item '#]],[2]Sheet1!$B:$D,3,0) -> 17621
A54: 4121-EACH | B54: B07Q713Y6M | C54: X003SBSJAR | D54: =VLOOKUP(Table13[[#This Row],[SKU]],Data1!A:B,2,0) -> 4121 | E54: =Table13[[#This Row],[UoM]]*Table13[[#This Row],[Recommended Replenishment Qty]] -> 276 | F54: =Table13[[#This Row],[Total EA (Transfer to WH06)]]/Table13[[#This Row],[UoM]] -> 276 | H54: =Table13[[#This Row],[Total EA (Transfer to WH06)]]/Table13[[#This Row],[CASE]] -> 23 | I54: =Table13[[#This Row],[Sellable Unit/Set/box to ship]]/Table13[[#This Row],[Case to pull]] -> 12 | J54: =IF(ISNUMBER(SEARCH("FNSKU",K54)),"Labeling","") -> Labeling | K54: =VLOOKUP(Table13[[#This Row],[SKU]],Instruction!A:F,6,0) -> • Use FNSKU to label each item (cover barcode). Apply outer box/case label accordingly to match item# (Cover all existing barcodes on the box/case) | L54: =VLOOKUP(Table13[[#This Row],[SKU]],Instruction!A:G,7,0) -> 0 | M54: =VLOOKUP(Table13[[#This Row],[ASIN]],'[1]2024'!$A:$AB,28,0) -> No Supplies | N54: =VLOOKUP(Table13[[#This Row],[SKU]],Data1!A:C,3,0) -> 1 | O54: =VLOOKUP(Table13[[#This Row],[Item '#]],Data2!A:D,4,0) -> 0 | P54: =VLOOKUP(Table13[[#This Row],[Item '#]],Data2!A:D,3,0) -> 12 | Q54: 276 | R54: =VLOOKUP(Table13[[#This Row],[Item '#]],[2]Sheet1!$B:$D,3,0) -> 4125
A55: 5011-EACH | B55: B001BO40DC | C55: B001BO40DC | D55: =VLOOKUP(Table13[[#This Row],[SKU]],Data1!A:B,2,0) -> 5011 | E55: =Table13[[#This Row],[UoM]]*Table13[[#This Row],[Recommended Replenishment Qty]] -> 300 | F55: =Table13[[#This Row],[Total EA (Transfer to WH06)]]/Table13[[#This Row],[UoM]] -> 300 | H55: =Table13[[#This Row],[Total EA (Transfer to WH06)]]/Table13[[#This Row],[CASE]] -> 6 | I55: =Table13[[#This Row],[Sellable Unit/Set/box to ship]]/Table13[[#This Row],[Case to pull]] -> 50 | J55: =IF(ISNUMBER(SEARCH("FNSKU",K55)),"Labeling","") -> Labeling | K55: =VLOOKUP(Table13[[#This Row],[SKU]],Instruction!A:F,6,0) -> • Use FNSKU to label each item (cover barcode). Apply outer box/case label accordingly to match item# (Cover all existing barcodes on the box/case) | L55: =VLOOKUP(Table13[[#This Row],[SKU]],Instruction!A:G,7,0) -> 0 | M55: =VLOOKUP(Table13[[#This Row],[ASIN]],'[1]2024'!$A:$AB,28,0) -> No Supplies | N55: =VLOOKUP(Table13[[#This Row],[SKU]],Data1!A:C,3,0) -> 1 | O55: =VLOOKUP(Table13[[#This Row],[Item '#]],Data2!A:D,4,0) -> 0 | P55: =VLOOKUP(Table13[[#This Row],[Item '#]],Data2!A:D,3,0) -> 50 | Q55: 300 | R55: =VLOOKUP(Table13[[#This Row],[Item '#]],[2]Sheet1!$B:$D,3,0) -> 13825
A56: 2236-EACH | B56: B08FF6RL8X | C56: B08FF6RL8X | D56: =VLOOKUP(Table13[[#This Row],[SKU]],Data1!A:B,2,0) -> 2236 | E56: =Table13[[#This Row],[UoM]]*Table13[[#This Row],[Recommended Replenishment Qty]] -> 288 | F56: =Table13[[#This Row],[Total EA (Transfer to WH06)]]/Table13[[#This Row],[UoM]] -> 288 | H56: =Table13[[#This Row],[Total EA (Transfer to WH06)]]/Table13[[#This Row],[CASE]] -> 12 | I56: =Table13[[#This Row],[Sellable Unit/Set/box to ship]]/Table13[[#This Row],[Case to pull]] -> 24 | J56: =IF(ISNUMBER(SEARCH("FNSKU",K56)),"Labeling","") | K56: =VLOOKUP(Table13[[#This Row],[SKU]],Instruction!A:F,6,0) -> Apply outer box/case label accordingly to match item# (Cover all existing barcodes on the box/case) | L56: =VLOOKUP(Table13[[#This Row],[SKU]],Instruction!A:G,7,0) -> 0 | M56: =VLOOKUP(Table13[[#This Row],[ASIN]],'[1]2024'!$A:$AB,28,0) -> No Supplies | N56: =VLOOKUP(Table13[[#This Row],[SKU]],Data1!A:C,3,0) -> 1 | O56: =VLOOKUP(Table13[[#This Row],[Item '#]],Data2!A:D,4,0) -> 0 | P56: =VLOOKUP(Table13[[#This Row],[Item '#]],Data2!A:D,3,0) -> 24 | Q56: 288 | R56: =VLOOKUP(Table13[[#This Row],[Item '#]],[2]Sheet1!$B:$D,3,0) -> 10533
A57: 552-EACH | B57: B07T1JYHZC | C57: B07T1JYHZC | D57: =VLOOKUP(Table13[[#This Row],[SKU]],Data1!A:B,2,0) -> 552 | E57: =Table13[[#This Row],[UoM]]*Table13[[#This Row],[Recommended Replenishment Qty]] -> 180 | F57: =Table13[[#This Row],[Total EA (Transfer to WH06)]]/Table13[[#This Row],[UoM]] -> 180 | H57: =Table13[[#This Row],[Total EA (Transfer to WH06)]]/Table13[[#This Row],[CASE]] -> 5 | I57: =Table13[[#This Row],[Sellable Unit/Set/box to ship]]/Table13[[#This Row],[Case to pull]] -> 36 | J57: =IF(ISNUMBER(SEARCH("FNSKU",K57)),"Labeling","") | K57: =VLOOKUP(Table13[[#This Row],[SKU]],Instruction!A:F,6,0) -> Apply outer box/case label accordingly to match item# (Cover all existing barcodes on the box/case) | L57: =VLOOKUP(Table13[[#This Row],[SKU]],Instruction!A:G,7,0) -> 0 | M57: =VLOOKUP(Table13[[#This Row],[ASIN]],'[1]2024'!$A:$AB,28,0) -> No Supplies | N57: =VLOOKUP(Table13[[#This Row],[SKU]],Data1!A:C,3,0) -> 1 | O57: =VLOOKUP(Table13[[#This Row],[Item '#]],Data2!A:D,4,0) -> 0 | P57: =VLOOKUP(Table13[[#This Row],[Item '#]],Data2!A:D,3,0) -> 36 | Q57: 180 | R57: =VLOOKUP(Table13[[#This Row],[Item '#]],[2]Sheet1!$B:$D,3,0) -> 17565
A58: 41166-EACH-1 | B58: B09MDRGNCP | C58: B09MDRGNCP | D58: =VLOOKUP(Table13[[#This Row],[SKU]],Data1!A:B,2,0) -> 41166 | E58: =Table13[[#This Row],[UoM]]*Table13[[#This Row],[Recommended Replenishment Qty]] -> 513 | F58: =Table13[[#This Row],[Total EA (Transfer to WH06)]]/Table13[[#This Row],[UoM]] -> 513 | H58: =Table13[[#This Row],[Total EA (Transfer to WH06)]]/Table13[[#This Row],[CASE]] -> 57 | I58: =Table13[[#This Row],[Sellable Unit/Set/box to ship]]/Table13[[#This Row],[Case to pull]] -> 9 | J58: =IF(ISNUMBER(SEARCH("FNSKU",K58)),"Labeling","") | K58: =VLOOKUP(Table13[[#This Row],[SKU]],Instruction!A:F,6,0) -> • 9 UNITS PER CASE (take out 1 unit from original case) • Apply outer case label accordingly to match item# (Cover all existing barcodes on the case) | L58: =VLOOKUP(Table13[[#This Row],[SKU]],Instruction!A:G,7,0) -> 0 | M58: =VLOOKUP(Table13[[#This Row],[ASIN]],'[1]2024'!$A:$AB,28,0) -> No Supplies | N58: =VLOOKUP(Table13[[#This Row],[SKU]],Data1!A:C,3,0) -> 1 | O58: =VLOOKUP(Table13[[#This Row],[Item '#]],Data2!A:D,4,0) -> 0 | P58: 9 | Q58: 513 | R58: =VLOOKUP(Table13[[#This Row],[Item '#]],[2]Sheet1!$B:$D,3,0) -> 1443
A59: 465-EACH-B | B59: B000BLJEKU | C59: B000BLJEKU | D59: =VLOOKUP(Table13[[#This Row],[SKU]],Data1!A:B,2,0) -> 465 | E59: =Table13[[#This Row],[UoM]]*Table13[[#This Row],[Recommended Replenishment Qty]] -> 336 | F59: =Table13[[#This Row],[Total EA (Transfer to WH06)]]/Table13[[#This Row],[UoM]] -> 336 | H59: =Table13[[#This Row],[Total EA (Transfer to WH06)]]/Table13[[#This Row],[CASE]] -> 7 | I59: =Table13[[#This Row],[Sellable Unit/Set/box to ship]]/Table13[[#This Row],[Case to pull]] -> 48 | J59: =IF(ISNUMBER(SEARCH("FNSKU",K59)),"Labeling","") | K59: =VLOOKUP(Table13[[#This Row],[SKU]],Instruction!A:F,6,0) -> Apply outer box/case label accordingly to match item# (Cover all existing barcodes on the box/case) | L59: =VLOOKUP(Table13[[#This Row],[SKU]],Instruction!A:G,7,0) -> 0 | M59: =VLOOKUP(Table13[[#This Row],[ASIN]],'[1]2024'!$A:$AB,28,0) -> No Supplies | N59: =VLOOKUP(Table13[[#This Row],[SKU]],Data1!A:C,3,0) -> 1 | O59: =VLOOKUP(Table13[[#This Row],[Item '#]],Data2!A:D,4,0) -> 0 | P59: =VLOOKUP(Table13[[#This Row],[Item '#]],Data2!A:D,3,0) -> 48 | Q59: 336 | R59: =VLOOKUP(Table13[[#This Row],[Item '#]],[2]Sheet1!$B:$D,3,0) -> 100008
A60: 5045-EACH | B60: B07S94M6P6 | C60: X003DE6G1X | D60: =VLOOKUP(Table13[[#This Row],[SKU]],Data1!A:B,2,0) -> 5045 | E60: =Table13[[#This Row],[UoM]]*Table13[[#This Row],[Recommended Replenishment Qty]] -> 1008 | F60: =Table13[[#This Row],[Total EA (Transfer to WH06)]]/Table13[[#This Row],[UoM]] -> 1008 | H60: =Table13[[#This Row],[Total EA (Transfer to WH06)]]/Table13[[#This Row],[CASE]] -> 21 | I60: =Table13[[#This Row],[Sellable Unit/Set/box to ship]]/Table13[[#This Row],[Case to pull]] -> 48 | J60: =IF(ISNUMBER(SEARCH("FNSKU",K60)),"Labeling","") -> Labeling | K60: =VLOOKUP(Table13[[#This Row],[SKU]],Instruction!A:F,6,0) -> • Use FNSKU to label each item (cover barcode). Apply outer box/case label accordingly to match item# (Cover all existing barcodes on the box/case) | L60: =VLOOKUP(Table13[[#This Row],[SKU]],Instruction!A:G,7,0) -> 0 | M60: =VLOOKUP(Table13[[#This Row],[ASIN]],'[1]2024'!$A:$AB,28,0) -> No Supplies | N60: =VLOOKUP(Table13[[#This Row],[SKU]],Data1!A:C,3,0) -> 1 | O60: =VLOOKUP(Table13[[#This Row],[Item '#]],Data2!A:D,4,0) -> 0 | P60: =VLOOKUP(Table13[[#This Row],[Item '#]],Data2!A:D,3,0) -> 48 | Q60: 1008 | R60: =VLOOKUP(Table13[[#This Row],[Item '#]],[2]Sheet1!$B:$D,3,0) -> 29
A61: 4104-EACH | B61: B07Q97R8X9 | C61: X003SC1YCL | D61: =VLOOKUP(Table13[[#This Row],[SKU]],Data1!A:B,2,0) -> 4104 | E61: =Table13[[#This Row],[UoM]]*Table13[[#This Row],[Recommended Replenishment Qty]] -> 204 | F61: =Table13[[#This Row],[Total EA (Transfer to WH06)]]/Table13[[#This Row],[UoM]] -> 204 | H61: =Table13[[#This Row],[Total EA (Transfer to WH06)]]/Table13[[#This Row],[CASE]] -> 17 | I61: =Table13[[#This Row],[Sellable Unit/Set/box to ship]]/Table13[[#This Row],[Case to pull]] -> 12 | J61: =IF(ISNUMBER(SEARCH("FNSKU",K61)),"Labeling","") -> Labeling | K61: =VLOOKUP(Table13[[#This Row],[SKU]],Instruction!A:F,6,0) -> • Use FNSKU to label each item (cover barcode). Apply outer box/case label accordingly to match item# (Cover all existing barcodes on the box/case) | L61: =VLOOKUP(Table13[[#This Row],[SKU]],Instruction!A:G,7,0) -> 0 | M61: =VLOOKUP(Table13[[#This Row],[ASIN]],'[1]2024'!$A:$AB,28,0) -> No Supplies | N61: =VLOOKUP(Table13[[#This Row],[SKU]],Data1!A:C,3,0) -> 1 | O61: =VLOOKUP(Table13[[#This Row],[Item '#]],Data2!A:D,4,0) -> 0 | P61: =VLOOKUP(Table13[[#This Row],[Item '#]],Data2!A:D,3,0) -> 12 | Q61: 204 | R61: =VLOOKUP(Table13[[#This Row],[Item '#]],[2]Sheet1!$B:$D,3,0) -> 7109
A62: 4120-EACH | B62: B07Q713R9G | C62: X003SC97MP | D62: =VLOOKUP(Table13[[#This Row],[SKU]],Data1!A:B,2,0) -> 4120 | E62: =Table13[[#This Row],[UoM]]*Table13[[#This Row],[Recommended Replenishment Qty]] -> 120 | F62: =Table13[[#This Row],[Total EA (Transfer to WH06)]]/Table13[[#This Row],[UoM]] -> 120 | H62: =Table13[[#This Row],[Total EA (Transfer to WH06)]]/Table13[[#This Row],[CASE]] -> 10 | I62: =Table13[[#This Row],[Sellable Unit/Set/box to ship]]/Table13[[#This Row],[Case to pull]] -> 12 | J62: =IF(ISNUMBER(SEARCH("FNSKU",K62)),"Labeling","") -> Labeling | K62: =VLOOKUP(Table13[[#This Row],[SKU]],Instruction!A:F,6,0) -> • Use FNSKU to label each item (cover barcode). Apply outer box/case label accordingly to match item# (Cover all existing barcodes on the box/case) | L62: =VLOOKUP(Table13[[#This Row],[SKU]],Instruction!A:G,7,0) -> 0 | M62: =VLOOKUP(Table13[[#This Row],[ASIN]],'[1]2024'!$A:$AB,28,0) -> No Supplies | N62: =VLOOKUP(Table13[[#This Row],[SKU]],Data1!A:C,3,0) -> 1 | O62: =VLOOKUP(Table13[[#This Row],[Item '#]],Data2!A:D,4,0) -> 0 | P62: =VLOOKUP(Table13[[#This Row],[Item '#]],Data2!A:D,3,0) -> 12 | Q62: 120 | R62: =VLOOKUP(Table13[[#This Row],[Item '#]],[2]Sheet1!$B:$D,3,0) -> 3799
A63: 212-EACH | B63: B07RLPFK92 | C63: X003TJ1SWJ | D63: =VLOOKUP(Table13[[#This Row],[SKU]],Data1!A:B,2,0) -> 212 | E63: =Table13[[#This Row],[UoM]]*Table13[[#This Row],[Recommended Replenishment Qty]] -> 720 | F63: =Table13[[#This Row],[Total EA (Transfer to WH06)]]/Table13[[#This Row],[UoM]] -> 720 | H63: =Table13[[#This Row],[Total EA (Transfer to WH06)]]/Table13[[#This Row],[CASE]] -> 5 | I63: =Table13[[#This Row],[Sellable Unit/Set/box to ship]]/Table13[[#This Row],[Case to pull]] -> 144 | J63: =IF(ISNUMBER(SEARCH("FNSKU",K63)),"Labeling","") -> Labeling | K63: =VLOOKUP(Table13[[#This Row],[SKU]],Instruction!A:F,6,0) -> • Use FNSKU to label each item (cover barcode). Apply outer box/case label accordingly to match item# (Cover all existing barcodes on the box/case) | L63: =VLOOKUP(Table13[[#This Row],[SKU]],Instruction!A:G,7,0) -> 0 | M63: =VLOOKUP(Table13[[#This Row],[ASIN]],'[1]2024'!$A:$AB,28,0) -> No Supplies | N63: =VLOOKUP(Table13[[#This Row],[SKU]],Data1!A:C,3,0) -> 1 | O63: =VLOOKUP(Table13[[#This Row],[Item '#]],Data2!A:D,4,0) -> 24 | P63: =VLOOKUP(Table13[[#This Row],[Item '#]],Data2!A:D,3,0) -> 144 | Q63: 720 | R63: =VLOOKUP(Table13[[#This Row],[Item '#]],[2]Sheet1!$B:$D,3,0) -> 12311
A64: 903-EACH | B64: B0018ML7KG | C64: B0018ML7KG | D64: =VLOOKUP(Table13[[#This Row],[SKU]],Data1!A:B,2,0) -> 903 | E64: =Table13[[#This Row],[UoM]]*Table13[[#This Row],[Recommended Replenishment Qty]] -> 48 | F64: =Table13[[#This Row],[Total EA (Transfer to WH06)]]/Table13[[#This Row],[UoM]] -> 48 | G64: =Table13[[#This Row],[Total EA (Transfer to WH06)]]/Table13[[#This Row],[BOX]] -> 2 | I64: =Table13[[#This Row],[Sellable Unit/Set/box to ship]]/Table13[[#This Row],[Box to pull]] -> 24 | J64: =IF(ISNUMBER(SEARCH("FNSKU",K64)),"Labeling","") | K64: =VLOOKUP(Table13[[#This Row],[SKU]],Instruction!A:F,6,0) -> Apply outer box/case label accordingly to match item# (Cover all existing barcodes on the box/case) | L64: =VLOOKUP(Table13[[#This Row],[SKU]],Instruction!A:G,7,0) -> 0 | M64: =VLOOKUP(Table13[[#This Row],[ASIN]],'[1]2024'!$A:$AB,28,0) -> No Supplies | N64: =VLOOKUP(Table13[[#This Row],[SKU]],Data1!A:C,3,0) -> 1 | O64: =VLOOKUP(Table13[[#This Row],[Item '#]],Data2!A:D,4,0) -> 24 | P64: =VLOOKUP(Table13[[#This Row],[Item '#]],Data2!A:D,3,0) -> 144 | Q64: 48 | R64: =VLOOKUP(Table13[[#This Row],[Item '#]],[2]Sheet1!$B:$D,3,0) -> 28076
A65: 3161-EACH | B65: B08FK78Z2B | C65: X003BXWZTX | D65: =VLOOKUP(Table13[[#This Row],[SKU]],Data1!A:B,2,0) -> 3161 | E65: =Table13[[#This Row],[UoM]]*Table13[[#This Row],[Recommended Replenishment Qty]] -> 108 | F65: =Table13[[#This Row],[Total EA (Transfer to WH06)]]/Table13[[#This Row],[UoM]] -> 108 | H65: =Table13[[#This Row],[Total EA (Transfer to WH06)]]/Table13[[#This Row],[CASE]] -> 9 | I65: =Table13[[#This Row],[Sellable Unit/Set/box to ship]]/Table13[[#This Row],[Case to pull]] -> 12 | J65: =IF(ISNUMBER(SEARCH("FNSKU",K65)),"Labeling","") -> Labeling | K65: =VLOOKUP(Table13[[#This Row],[SKU]],Instruction!A:F,6,0) -> • Use FNSKU to label each item (cover barcode). Apply outer box/case label accordingly to match item# (Cover all existing barcodes on the box/case) | L65: =VLOOKUP(Table13[[#This Row],[SKU]],Instruction!A:G,7,0) -> 0 | M65: =VLOOKUP(Table13[[#This Row],[ASIN]],'[1]2024'!$A:$AB,28,0) -> No Supplies | N65: =VLOOKUP(Table13[[#This Row],[SKU]],Data1!A:C,3,0) -> 1 | O65: =VLOOKUP(Table13[[#This Row],[Item '#]],Data2!A:D,4,0) -> 0 | P65: =VLOOKUP(Table13[[#This Row],[Item '#]],Data2!A:D,3,0) -> 12 | Q65: 108 | R65: =VLOOKUP(Table13[[#This Row],[Item '#]],[2]Sheet1!$B:$D,3,0) -> 10878
A66: 465-EACH-1 | B66: B07T766984 | C66: X003T9Y59H | D66: =VLOOKUP(Table13[[#This Row],[SKU]],Data1!A:B,2,0) -> 465 | E66: =Table13[[#This Row],[UoM]]*Table13[[#This Row],[Recommended Replenishment Qty]] -> 144 | F66: =Table13[[#This Row],[Total EA (Transfer to WH06)]]/Table13[[#This Row],[UoM]] -> 144 | H66: =Table13[[#This Row],[Total EA (Transfer to WH06)]]/Table13[[#This Row],[CASE]] -> 3 | I66: =Table13[[#This Row],[Sellable Unit/Set/box to ship]]/Table13[[#This Row],[Case to pull]] -> 48 | J66: =IF(ISNUMBER(SEARCH("FNSKU",K66)),"Labeling","") -> Labeling | K66: =VLOOKUP(Table13[[#This Row],[SKU]],Instruction!A:F,6,0) -> • Use FNSKU to label each item (cover barcode). Apply outer box/case label accordingly to match item# (Cover all existing barcodes on the box/case) | L66: =VLOOKUP(Table13[[#This Row],[SKU]],Instruction!A:G,7,0) -> 0 | M66: =VLOOKUP(Table13[[#This Row],[ASIN]],'[1]2024'!$A:$AB,28,0) -> No Supplies | N66: =VLOOKUP(Table13[[#This Row],[SKU]],Data1!A:C,3,0) -> 1 | O66: =VLOOKUP(Table13[[#This Row],[Item '#]],Data2!A:D,4,0) -> 0 | P66: =VLOOKUP(Table13[[#This Row],[Item '#]],Data2!A:D,3,0) -> 48 | Q66: 144 | R66: =VLOOKUP(Table13[[#This Row],[Item '#]],[2]Sheet1!$B:$D,3,0) -> 100008
A67: 2043-EACH-1 | B67: B00J8IK3YI | C67: X004DMV5X3 | D67: =VLOOKUP(Table13[[#This Row],[SKU]],Data1!A:B,2,0) -> 2043 | E67: =Table13[[#This Row],[UoM]]*Table13[[#This Row],[Recommended Replenishment Qty]] -> 96 | F67: =Table13[[#This Row],[Total EA (Transfer to WH06)]]/Table13[[#This Row],[UoM]] -> 96 | G67: =Table13[[#This Row],[Total EA (Transfer to WH06)]]/Table13[[#This Row],[BOX]] -> 4 | I67: =Table13[[#This Row],[Sellable Unit/Set/box to ship]]/Table13[[#This Row],[Box to pull]] -> 24 | J67: =IF(ISNUMBER(SEARCH("FNSKU",K67)),"Labeling","") -> Labeling | K67: =VLOOKUP(Table13[[#This Row],[SKU]],Instruction!A:F,6,0) -> • Use FNSKU to label each item (cover barcode). Apply outer case label accordingly to match item# (Cover all existing barcodes on the case) | L67: =VLOOKUP(Table13[[#This Row],[SKU]],Instruction!A:G,7,0) -> 0 | M67: =VLOOKUP(Table13[[#This Row],[ASIN]],'[1]2024'!$A:$AB,28,0) -> No Supplies | N67: =VLOOKUP(Table13[[#This Row],[SKU]],Data1!A:C,3,0) -> 1 | O67: =VLOOKUP(Table13[[#This Row],[Item '#]],Data2!A:D,4,0) -> 24 | P67: =VLOOKUP(Table13[[#This Row],[Item '#]],Data2!A:D,3,0) -> 144 | Q67: 96 | R67: =VLOOKUP(Table13[[#This Row],[Item '#]],[2]Sheet1!$B:$D,3,0) -> 29532
A68: 5081-EACH | B68: B094XLGQL9 | C68: X0043UZ5ZJ | D68: =VLOOKUP(Table13[[#This Row],[SKU]],Data1!A:B,2,0) -> 5081 | E68: =Table13[[#This Row],[UoM]]*Table13[[#This Row],[Recommended Replenishment Qty]] -> 96 | F68: =Table13[[#This Row],[Total EA (Transfer to WH06)]]/Table13[[#This Row],[UoM]] -> 96 | H68: =Table13[[#This Row],[Total EA (Transfer to WH06)]]/Table13[[#This Row],[CASE]] -> 8 | I68: =Table13[[#This Row],[Sellable Unit/Set/box to ship]]/Table13[[#This Row],[Case to pull]] -> 12 | J68: =IF(ISNUMBER(SEARCH("FNSKU",K68)),"Labeling","") -> Labeling | K68: =VLOOKUP(Table13[[#This Row],[SKU]],Instruction!A:F,6,0) -> • Use FNSKU to label each item (cover barcode). Apply outer case label accordingly to match item# (Cover all existing barcodes on the case) | L68: =VLOOKUP(Table13[[#This Row],[SKU]],Instruction!A:G,7,0) -> 0 | M68: =VLOOKUP(Table13[[#This Row],[ASIN]],'[1]2024'!$A:$AB,28,0) -> No Supplies | N68: =VLOOKUP(Table13[[#This Row],[SKU]],Data1!A:C,3,0) -> 1 | O68: =VLOOKUP(Table13[[#This Row],[Item '#]],Data2!A:D,4,0) -> 0 | P68: =VLOOKUP(Table13[[#This Row],[Item '#]],Data2!A:D,3,0) -> 12 | Q68: 96 | R68: =VLOOKUP(Table13[[#This Row],[Item '#]],[2]Sheet1!$B:$D,3,0) -> 2043
A69: 4127-EACH | B69: B07Q8XTMXF | C69: X003SC97MF | D69: =VLOOKUP(Table13[[#This Row],[SKU]],Data1!A:B,2,0) -> 4127 | E69: =Table13[[#This Row],[UoM]]*Table13[[#This Row],[Recommended Replenishment Qty]] -> 504 | F69: =Table13[[#This Row],[Total EA (Transfer to WH06)]]/Table13[[#This Row],[UoM]] -> 504 | H69: =Table13[[#This Row],[Total EA (Transfer to WH06)]]/Table13[[#This Row],[CASE]] -> 42 | I69: =Table13[[#This Row],[Sellable Unit/Set/box to ship]]/Table13[[#This Row],[Case to pull]] -> 12 | J69: =IF(ISNUMBER(SEARCH("FNSKU",K69)),"Labeling","") -> Labeling | K69: =VLOOKUP(Table13[[#This Row],[SKU]],Instruction!A:F,6,0) -> • Use FNSKU to label each item (cover barcode). Apply outer box/case label accordingly to match item# (Cover all existing barcodes on the box/case) | L69: =VLOOKUP(Table13[[#This Row],[SKU]],Instruction!A:G,7,0) -> 0 | M69: =VLOOKUP(Table13[[#This Row],[ASIN]],'[1]2024'!$A:$AB,28,0) -> No Supplies | N69: =VLOOKUP(Table13[[#This Row],[SKU]],Data1!A:C,3,0) -> 1 | O69: =VLOOKUP(Table13[[#This Row],[Item '#]],Data2!A:D,4,0) -> 0 | P69: =VLOOKUP(Table13[[#This Row],[Item '#]],Data2!A:D,3,0) -> 12 | Q69: 504 | R69: =VLOOKUP(Table13[[#This Row],[Item '#]],[2]Sheet1!$B:$D,3,0) -> 9701
A70: 609-EACH | B70: B00ESWRD10 | C70: B00ESWRD10 | D70: =VLOOKUP(Table13[[#This Row],[SKU]],Data1!A:B,2,0) -> 609 | E70: =Table13[[#This Row],[UoM]]*Table13[[#This Row],[Recommended Replenishment Qty]] -> 648 | F70: =Table13[[#This Row],[Total EA (Transfer to WH06)]]/Table13[[#This Row],[UoM]] -> 648 | H70: =Table13[[#This Row],[Total EA (Transfer to WH06)]]/Table13[[#This Row],[CASE]] -> 9 | I70: =Table13[[#This Row],[Sellable Unit/Set/box to ship]]/Table13[[#This Row],[Case to pull]] -> 72 | J70: =IF(ISNUMBER(SEARCH("FNSKU",K70)),"Labeling","") | K70: =VLOOKUP(Table13[[#This Row],[SKU]],Instruction!A:F,6,0) -> Apply outer box/case label accordingly to match item# (Cover all existing barcodes on the box/case) | L70: =VLOOKUP(Table13[[#This Row],[SKU]],Instruction!A:G,7,0) -> 0 | M70: =VLOOKUP(Table13[[#This Row],[ASIN]],'[1]2024'!$A:$AB,28,0) -> No Supplies | N70: =VLOOKUP(Table13[[#This Row],[SKU]],Data1!A:C,3,0) -> 1 | O70: =VLOOKUP(Table13[[#This Row],[Item '#]],Data2!A:D,4,0) -> 24 | P70: =VLOOKUP(Table13[[#This Row],[Item '#]],Data2!A:D,3,0) -> 72 | Q70: 648 | R70: =VLOOKUP(Table13[[#This Row],[Item '#]],[2]Sheet1!$B:$D,3,0) -> 43600
A71: 2044-EACH | B71: B075VXY8MQ | C71: B075VXY8MQ | D71: =VLOOKUP(Table13[[#This Row],[SKU]],Data1!A:B,2,0) -> 2044 | E71: =Table13[[#This Row],[UoM]]*Table13[[#This Row],[Recommended Replenishment Qty]] -> 912 | F71: =Table13[[#This Row],[Total EA (Transfer to WH06)]]/Table13[[#This Row],[UoM]] -> 912 | H71: =Table13[[#This Row],[Total EA (Transfer to WH06)]]/Table13[[#This Row],[CASE]] -> 19 | I71: =Table13[[#This Row],[Sellable Unit/Set/box to ship]]/Table13[[#This Row],[Case to pull]] -> 48 | J71: =IF(ISNUMBER(SEARCH("FNSKU",K71)),"Labeling","") | K71: =VLOOKUP(Table13[[#This Row],[SKU]],Instruction!A:F,6,0) -> Apply outer case label accordingly to match item# (Cover all existing barcodes on the case) | L71: =VLOOKUP(Table13[[#This Row],[SKU]],Instruction!A:G,7,0) -> 0 | M71: =VLOOKUP(Table13[[#This Row],[ASIN]],'[1]2024'!$A:$AB,28,0) -> No Supplies | N71: =VLOOKUP(Table13[[#This Row],[SKU]],Data1!A:C,3,0) -> 1 | O71: =VLOOKUP(Table13[[#This Row],[Item '#]],Data2!A:D,4,0) -> 0 | P71: =VLOOKUP(Table13[[#This Row],[Item '#]],Data2!A:D,3,0) -> 48 | Q71: 912 | R71: =VLOOKUP(Table13[[#This Row],[Item '#]],[2]Sheet1!$B:$D,3,0) -> 7255
A72: 5174-EACH | B72: B07TGB6SPM | C72: B07TGB6SPM | D72: =VLOOKUP(Table13[[#This Row],[SKU]],Data1!A:B,2,0) -> 5174 | E72: =Table13[[#This Row],[UoM]]*Table13[[#This Row],[Recommended Replenishment Qty]] -> 24 | F72: =Table13[[#This Row],[Total EA (Transfer to WH06)]]/Table13[[#This Row],[UoM]] -> 24 | G72: =Table13[[#This Row],[Total EA (Transfer to WH06)]]/Table13[[#This Row],[BOX]] -> 1 | I72: =Table13[[#This Row],[Sellable Unit/Set/box to ship]]/Table13[[#This Row],[Box to pull]] -> 24 | J72: =IF(ISNUMBER(SEARCH("FNSKU",K72)),"Labeling","") | K72: =VLOOKUP(Table13[[#This Row],[SKU]],Instruction!A:F,6,0) -> Apply outer case label accordingly to match item# (Cover all existing barcodes on the case) | L72: =VLOOKUP(Table13[[#This Row],[SKU]],Instruction!A:G,7,0) -> 0 | M72: =VLOOKUP(Table13[[#This Row],[ASIN]],'[1]2024'!$A:$AB,28,0) -> No Supplies | N72: =VLOOKUP(Table13[[#This Row],[SKU]],Data1!A:C,3,0) -> 1 | O72: =VLOOKUP(Table13[[#This Row],[Item '#]],Data2!A:D,4,0) -> 24 | P72: =VLOOKUP(Table13[[#This Row],[Item '#]],Data2!A:D,3,0) -> 288 | Q72: 24 | R72: =VLOOKUP(Table13[[#This Row],[Item '#]],[2]Sheet1!$B:$D,3,0) -> 12351
A73: 930-EACH | B73: B003BMWQYC | C73: B003BMWQYC | D73: =VLOOKUP(Table13[[#This Row],[SKU]],Data1!A:B,2,0) -> 930 | E73: =Table13[[#This Row],[UoM]]*Table13[[#This Row],[Recommended Replenishment Qty]] -> 96 | F73: =Table13[[#This Row],[Total EA (Transfer to WH06)]]/Table13[[#This Row],[UoM]] -> 96 | G73: =Table13[[#This Row],[Total EA (Transfer to WH06)]]/Table13[[#This Row],[BOX]] -> 4 | I73: =Table13[[#This Row],[Sellable Unit/Set/box to ship]]/Table13[[#This Row],[Box to pull]] -> 24 | J73: =IF(ISNUMBER(SEARCH("FNSKU",K73)),"Labeling","") | K73: =VLOOKUP(Table13[[#This Row],[SKU]],Instruction!A:F,6,0) -> Apply outer case label accordingly to match item# (Cover all existing barcodes on the case) | L73: =VLOOKUP(Table13[[#This Row],[SKU]],Instruction!A:G,7,0) -> 0 | M73: =VLOOKUP(Table13[[#This Row],[ASIN]],'[1]2024'!$A:$AB,28,0) -> No Supplies | N73: =VLOOKUP(Table13[[#This Row],[SKU]],Data1!A:C,3,0) -> 1 | O73: =VLOOKUP(Table13[[#This Row],[Item '#]],Data2!A:D,4,0) -> 24 | P73: =VLOOKUP(Table13[[#This Row],[Item '#]],Data2!A:D,3,0) -> 144 | Q73: 96 | R73: =VLOOKUP(Table13[[#This Row],[Item '#]],[2]Sheet1!$B:$D,3,0) -> 70908
A74: 565-EACH | B74: B0019IKAES | C74: B0019IKAES | D74: =VLOOKUP(Table13[[#This Row],[SKU]],Data1!A:B,2,0) -> 565 | E74: =Table13[[#This Row],[UoM]]*Table13[[#This Row],[Recommended Replenishment Qty]] -> 36 | F74: =Table13[[#This Row],[Total EA (Transfer to WH06)]]/Table13[[#This Row],[UoM]] -> 36 | H74: =Table13[[#This Row],[Total EA (Transfer to WH06)]]/Table13[[#This Row],[CASE]] -> 1 | I74: =Table13[[#This Row],[Sellable Unit/Set/box to ship]]/Table13[[#This Row],[Case to pull]] -> 36 | J74: =IF(ISNUMBER(SEARCH("FNSKU",K74)),"Labeling","") | K74: =VLOOKUP(Table13[[#This Row],[SKU]],Instruction!A:F,6,0) -> Apply outer box/case label accordingly to match item# (Cover all existing barcodes on the box/case) | L74: =VLOOKUP(Table13[[#This Row],[SKU]],Instruction!A:G,7,0) -> 0 | M74: =VLOOKUP(Table13[[#This Row],[ASIN]],'[1]2024'!$A:$AB,28,0) -> No Supplies | N74: =VLOOKUP(Table13[[#This Row],[SKU]],Data1!A:C,3,0) -> 1 | O74: =VLOOKUP(Table13[[#This Row],[Item '#]],Data2!A:D,4,0) -> 0 | P74: =VLOOKUP(Table13[[#This Row],[Item '#]],Data2!A:D,3,0) -> 36 | Q74: 36 | R74: =VLOOKUP(Table13[[#This Row],[Item '#]],[2]Sheet1!$B:$D,3,0) -> 89026
A75: 3171-EACH | B75: B0BP5Q88DW | C75: X0040DP2BL | D75: =VLOOKUP(Table13[[#This Row],[SKU]],Data1!A:B,2,0) -> 3171 | E75: =Table13[[#This Row],[UoM]]*Table13[[#This Row],[Recommended Replenishment Qty]] -> 192 | F75: =Table13[[#This Row],[Total EA (Transfer to WH06)]]/Table13[[#This Row],[UoM]] -> 192 | H75: =Table13[[#This Row],[Total EA (Transfer to WH06)]]/Table13[[#This Row],[CASE]] -> 16 | I75: =Table13[[#This Row],[Sellable Unit/Set/box to ship]]/Table13[[#This Row],[Case to pull]] -> 12 | J75: =IF(ISNUMBER(SEARCH("FNSKU",K75)),"Labeling","") -> Labeling | K75: =VLOOKUP(Table13[[#This Row],[SKU]],Instruction!A:F,6,0) -> • Use FNSKU to label each item (cover barcode). Apply outer case label accordingly to match item# (Cover all existing barcodes on the case) | L75: =VLOOKUP(Table13[[#This Row],[SKU]],Instruction!A:G,7,0) -> 0 | M75: =VLOOKUP(Table13[[#This Row],[ASIN]],'[1]2024'!$A:$AB,28,0) -> No Supplies | N75: =VLOOKUP(Table13[[#This Row],[SKU]],Data1!A:C,3,0) -> 1 | O75: =VLOOKUP(Table13[[#This Row],[Item '#]],Data2!A:D,4,0) -> 0 | P75: =VLOOKUP(Table13[[#This Row],[Item '#]],Data2!A:D,3,0) -> 12 | Q75: 192 | R75: =VLOOKUP(Table13[[#This Row],[Item '#]],[2]Sheet1!$B:$D,3,0) -> 7417
A76: 761-EACH | B76: B0019IHJIS | C76: B0019IHJIS | D76: =VLOOKUP(Table13[[#This Row],[SKU]],Data1!A:B,2,0) -> 761 | E76: =Table13[[#This Row],[UoM]]*Table13[[#This Row],[Recommended Replenishment Qty]] -> 96 | F76: =Table13[[#This Row],[Total EA (Transfer to WH06)]]/Table13[[#This Row],[UoM]] -> 96 | G76: =Table13[[#This Row],[Total EA (Transfer to WH06)]]/Table13[[#This Row],[BOX]] -> 4 | I76: =Table13[[#This Row],[Sellable Unit/Set/box to ship]]/Table13[[#This Row],[Box to pull]] -> 24 | J76: =IF(ISNUMBER(SEARCH("FNSKU",K76)),"Labeling","") | K76: =VLOOKUP(Table13[[#This Row],[SKU]],Instruction!A:F,6,0) -> Apply outer box/case label accordingly to match item# (Cover all existing barcodes on the box/case) | L76: =VLOOKUP(Table13[[#This Row],[SKU]],Instruction!A:G,7,0) -> 0 | M76: =VLOOKUP(Table13[[#This Row],[ASIN]],'[1]2024'!$A:$AB,28,0) -> No Supplies | N76: =VLOOKUP(Table13[[#This Row],[SKU]],Data1!A:C,3,0) -> 1 | O76: =VLOOKUP(Table13[[#This Row],[Item '#]],Data2!A:D,4,0) -> 24 | P76: =VLOOKUP(Table13[[#This Row],[Item '#]],Data2!A:D,3,0) -> 144 | Q76: 96 | R76: =VLOOKUP(Table13[[#This Row],[Item '#]],[2]Sheet1!$B:$D,3,0) -> 134140
A77: 5087-EACH-1 | B77: B084GC6RYF | C77: X004F8SJVB | D77: =VLOOKUP(Table13[[#This Row],[SKU]],Data1!A:B,2,0) -> 5087 | E77: =Table13[[#This Row],[UoM]]*Table13[[#This Row],[Recommended Replenishment Qty]] -> 432 | F77: =Table13[[#This Row],[Total EA (Transfer to WH06)]]/Table13[[#This Row],[UoM]] -> 432 | H77: =Table13[[#This Row],[Total EA (Transfer to WH06)]]/Table13[[#This Row],[CASE]] -> 9 | I77: =Table13[[#This Row],[Sellable Unit/Set/box to ship]]/Table13[[#This Row],[Case to pull]] -> 48 | J77: =IF(ISNUMBER(SEARCH("FNSKU",K77)),"Labeling","") -> Labeling | K77: =VLOOKUP(Table13[[#This Row],[SKU]],Instruction!A:F,6,0) -> • Use FNSKU to label each item (cover barcode). Apply outer case label accordingly to match item# (Cover all existing barcodes on the case) | L77: =VLOOKUP(Table13[[#This Row],[SKU]],Instruction!A:G,7,0) -> 0 | M77: =VLOOKUP(Table13[[#This Row],[ASIN]],'[1]2024'!$A:$AB,28,0) -> No Supplies | N77: =VLOOKUP(Table13[[#This Row],[SKU]],Data1!A:C,3,0) -> 1 | O77: =VLOOKUP(Table13[[#This Row],[Item '#]],Data2!A:D,4,0) -> 0 | P77: =VLOOKUP(Table13[[#This Row],[Item '#]],Data2!A:D,3,0) -> 48 | Q77: 432 | R77: =VLOOKUP(Table13[[#This Row],[Item '#]],[2]Sheet1!$B:$D,3,0) -> 80962
A78: 4003-EACH-1 | B78: B07TGDNG2G | C78: X0040LGDTX | D78: =VLOOKUP(Table13[[#This Row],[SKU]],Data1!A:B,2,0) -> 4003 | E78: =Table13[[#This Row],[UoM]]*Table13[[#This Row],[Recommended Replenishment Qty]] -> 72 | F78: =Table13[[#This Row],[Total EA (Transfer to WH06)]]/Table13[[#This Row],[UoM]] -> 72 | G78: =Table13[[#This Row],[Total EA (Transfer to WH06)]]/Table13[[#This Row],[BOX]] -> 3 | I78: =Table13[[#This Row],[Sellable Unit/Set/box to ship]]/Table13[[#This Row],[Box to pull]] -> 24 | J78: =IF(ISNUMBER(SEARCH("FNSKU",K78)),"Labeling","") -> Labeling | K78: =VLOOKUP(Table13[[#This Row],[SKU]],Instruction!A:F,6,0) -> • Use FNSKU to label each item (cover barcode). Apply outer box/case label accordingly to match item# (Cover all existing barcodes on the box/case) | L78: =VLOOKUP(Table13[[#This Row],[SKU]],Instruction!A:G,7,0) -> 0 | M78: =VLOOKUP(Table13[[#This Row],[ASIN]],'[1]2024'!$A:$AB,28,0) -> No Supplies | N78: =VLOOKUP(Table13[[#This Row],[SKU]],Data1!A:C,3,0) -> 1 | O78: =VLOOKUP(Table13[[#This Row],[Item '#]],Data2!A:D,4,0) -> 24 | P78: =VLOOKUP(Table13[[#This Row],[Item '#]],Data2!A:D,3,0) -> 144 | Q78: 72 | R78: =VLOOKUP(Table13[[#This Row],[Item '#]],[2]Sheet1!$B:$D,3,0) -> 23165
A79: 338-EACH | B79: B07S4BSLL5 | C79: B07S4BSLL5 | D79: =VLOOKUP(Table13[[#This Row],[SKU]],Data1!A:B,2,0) -> 338 | E79: =Table13[[#This Row],[UoM]]*Table13[[#This Row],[Recommended Replenishment Qty]] -> 576 | F79: =Table13[[#This Row],[Total EA (Transfer to WH06)]]/Table13[[#This Row],[UoM]] -> 576 | H79: =Table13[[#This Row],[Total EA (Transfer to WH06)]]/Table13[[#This Row],[CASE]] -> 2 | I79: =Table13[[#This Row],[Sellable Unit/Set/box to ship]]/Table13[[#This Row],[Case to pull]] -> 288 | J79: =IF(ISNUMBER(SEARCH("FNSKU",K79)),"Labeling","") | K79: =VLOOKUP(Table13[[#This Row],[SKU]],Instruction!A:F,6,0) -> Apply outer box/case label accordingly to match item# (Cover all existing barcodes on the box/case) | L79: =VLOOKUP(Table13[[#This Row],[SKU]],Instruction!A:G,7,0) -> 0 | M79: =VLOOKUP(Table13[[#This Row],[ASIN]],'[1]2024'!$A:$AB,28,0) -> No Supplies | N79: =VLOOKUP(Table13[[#This Row],[SKU]],Data1!A:C,3,0) -> 1 | O79: =VLOOKUP(Table13[[#This Row],[Item '#]],Data2!A:D,4,0) -> 24 | P79: =VLOOKUP(Table13[[#This Row],[Item '#]],Data2!A:D,3,0) -> 288 | Q79: 576 | R79: =VLOOKUP(Table13[[#This Row],[Item '#]],[2]Sheet1!$B:$D,3,0) -> 20001
A80: 2207-EACH | B80: B001BO3JHA | C80: B001BO3JHA | D80: =VLOOKUP(Table13[[#This Row],[SKU]],Data1!A:B,2,0) -> 2207 | E80: =Table13[[#This Row],[UoM]]*Table13[[#This Row],[Recommended Replenishment Qty]] -> 288 | F80: =Table13[[#This Row],[Total EA (Transfer to WH06)]]/Table13[[#This Row],[UoM]] -> 288 | H80: =Table13[[#This Row],[Total EA (Transfer to WH06)]]/Table13[[#This Row],[CASE]] -> 4 | I80: =Table13[[#This Row],[Sellable Unit/Set/box to ship]]/Table13[[#This Row],[Case to pull]] -> 72 | J80: =IF(ISNUMBER(SEARCH("FNSKU",K80)),"Labeling","") | K80: =VLOOKUP(Table13[[#This Row],[SKU]],Instruction!A:F,6,0) -> Apply outer box/case label accordingly to match item# (Cover all existing barcodes on the box/case) | L80: =VLOOKUP(Table13[[#This Row],[SKU]],Instruction!A:G,7,0) -> 0 | M80: =VLOOKUP(Table13[[#This Row],[ASIN]],'[1]2024'!$A:$AB,28,0) -> No Supplies | N80: =VLOOKUP(Table13[[#This Row],[SKU]],Data1!A:C,3,0) -> 1 | O80: =VLOOKUP(Table13[[#This Row],[Item '#]],Data2!A:D,4,0) -> 24 | P80: =VLOOKUP(Table13[[#This Row],[Item '#]],Data2!A:D,3,0) -> 72 | Q80: 288 | R80: =VLOOKUP(Table13[[#This Row],[Item '#]],[2]Sheet1!$B:$D,3,0) -> 28912
A81: 3467-EACH-1 | B81: B01HTYG3LE | C81: B01HTYG3LE | D81: =VLOOKUP(Table13[[#This Row],[SKU]],Data1!A:B,2,0) -> 3467 | E81: =Table13[[#This Row],[UoM]]*Table13[[#This Row],[Recommended Replenishment Qty]] -> 1512 | F81: =Table13[[#This Row],[Total EA (Transfer to WH06)]]/Table13[[#This Row],[UoM]] -> 1512 | H81: =Table13[[#This Row],[Total EA (Transfer to WH06)]]/Table13[[#This Row],[CASE]] -> 21 | I81: =Table13[[#This Row],[Sellable Unit/Set/box to ship]]/Table13[[#This Row],[Case to pull]] -> 72 | J81: =IF(ISNUMBER(SEARCH("FNSKU",K81)),"Labeling","") -> Labeling | K81: =VLOOKUP(Table13[[#This Row],[SKU]],Instruction!A:F,6,0) -> • Use FNSKU to label each item (cover barcode). Apply outer box/case label accordingly to match item# (Cover all existing barcodes on the box/case) | L81: =VLOOKUP(Table13[[#This Row],[SKU]],Instruction!A:G,7,0) -> 0 | M81: =VLOOKUP(Table13[[#This Row],[ASIN]],'[1]2024'!$A:$AB,28,0) -> No Supplies | N81: =VLOOKUP(Table13[[#This Row],[SKU]],Data1!A:C,3,0) -> 1 | O81: =VLOOKUP(Table13[[#This Row],[Item '#]],Data2!A:D,4,0) -> 24 | P81: =VLOOKUP(Table13[[#This Row],[Item '#]],Data2!A:D,3,0) -> 72 | Q81: 1512 | R81: =VLOOKUP(Table13[[#This Row],[Item '#]],[2]Sheet1!$B:$D,3,0) -> 31672
A82: 851-EACH | B82: B093CPW1HK | C82: B093CPW1HK | D82: =VLOOKUP(Table13[[#This Row],[SKU]],Data1!A:B,2,0) -> 851 | E82: =Table13[[#This Row],[UoM]]*Table13[[#This Row],[Recommended Replenishment Qty]] -> 528 | F82: =Table13[[#This Row],[Total EA (Transfer to WH06)]]/Table13[[#This Row],[UoM]] -> 528 | H82: =Table13[[#This Row],[Total EA (Transfer to WH06)]]/Table13[[#This Row],[CASE]] -> 44 | I82: =Table13[[#This Row],[Sellable Unit/Set/box to ship]]/Table13[[#This Row],[Case to pull]] -> 12 | J82: =IF(ISNUMBER(SEARCH("FNSKU",K82)),"Labeling","") | K82: =VLOOKUP(Table13[[#This Row],[SKU]],Instruction!A:F,6,0) -> Apply outer case label accordingly to match item# (Cover all existing barcodes on the case) | L82: =VLOOKUP(Table13[[#This Row],[SKU]],Instruction!A:G,7,0) -> 0 | M82: =VLOOKUP(Table13[[#This Row],[ASIN]],'[1]2024'!$A:$AB,28,0) -> No Supplies | N82: =VLOOKUP(Table13[[#This Row],[SKU]],Data1!A:C,3,0) -> 1 | O82: =VLOOKUP(Table13[[#This Row],[Item '#]],Data2!A:D,4,0) -> 0 | P82: =VLOOKUP(Table13[[#This Row],[Item '#]],Data2!A:D,3,0) -> 12 | Q82: 528 | R82: =VLOOKUP(Table13[[#This Row],[Item '#]],[2]Sheet1!$B:$D,3,0) -> 8391
A83: 4107-EACH | B83: B07Q84RJLP | C83: X003L8W44J | D83: =VLOOKUP(Table13[[#This Row],[SKU]],Data1!A:B,2,0) -> 4107 | E83: =Table13[[#This Row],[UoM]]*Table13[[#This Row],[Recommended Replenishment Qty]] -> 816 | F83: =Table13[[#This Row],[Total EA (Transfer to WH06)]]/Table13[[#This Row],[UoM]] -> 816 | H83: =Table13[[#This Row],[Total EA (Transfer to WH06)]]/Table13[[#This Row],[CASE]] -> 68 | I83: =Table13[[#This Row],[Sellable Unit/Set/box to ship]]/Table13[[#This Row],[Case to pull]] -> 12 | J83: =IF(ISNUMBER(SEARCH("FNSKU",K83)),"Labeling","") -> Labeling | K83: =VLOOKUP(Table13[[#This Row],[SKU]],Instruction!A:F,6,0) -> • Use FNSKU to label each item (cover barcode). Apply outer box/case label accordingly to match item# (Cover all existing barcodes on the box/case) | L83: =VLOOKUP(Table13[[#This Row],[SKU]],Instruction!A:G,7,0) -> 0 | M83: =VLOOKUP(Table13[[#This Row],[ASIN]],'[1]2024'!$A:$AB,28,0) -> No Supplies | N83: =VLOOKUP(Table13[[#This Row],[SKU]],Data1!A:C,3,0) -> 1 | O83: =VLOOKUP(Table13[[#This Row],[Item '#]],Data2!A:D,4,0) -> 0 | P83: =VLOOKUP(Table13[[#This Row],[Item '#]],Data2!A:D,3,0) -> 12 | Q83: 816 | R83: =VLOOKUP(Table13[[#This Row],[Item '#]],[2]Sheet1!$B:$D,3,0) -> 7639
A84: 3192-EACH | B84: B07Q8Y29ZR | C84: X0044RG61X | D84: =VLOOKUP(Table13[[#This Row],[SKU]],Data1!A:B,2,0) -> 3192 | E84: =Table13[[#This Row],[UoM]]*Table13[[#This Row],[Recommended Replenishment Qty]] -> 96 | F84: =Table13[[#This Row],[Total EA (Transfer to WH06)]]/Table13[[#This Row],[UoM]] -> 96 | H84: =Table13[[#This Row],[Total EA (Transfer to WH06)]]/Table13[[#This Row],[CASE]] -> 8 | I84: =Table13[[#This Row],[Sellable Unit/Set/box to ship]]/Table13[[#This Row],[Case to pull]] -> 12 | J84: =IF(ISNUMBER(SEARCH("FNSKU",K84)),"Labeling","") -> Labeling | K84: =VLOOKUP(Table13[[#This Row],[SKU]],Instruction!A:F,6,0) -> • Use FNSKU to label each item (cover barcode). Apply outer box/case label accordingly to match item# (Cover all existing barcodes on the box/case) | L84: =VLOOKUP(Table13[[#This Row],[SKU]],Instruction!A:G,7,0) -> 0 | M84: =VLOOKUP(Table13[[#This Row],[ASIN]],'[1]2024'!$A:$AB,28,0) -> No Supplies | N84: =VLOOKUP(Table13[[#This Row],[SKU]],Data1!A:C,3,0) -> 1 | O84: =VLOOKUP(Table13[[#This Row],[Item '#]],Data2!A:D,4,0) -> 0 | P84: =VLOOKUP(Table13[[#This Row],[Item '#]],Data2!A:D,3,0) -> 12 | Q84: 96 | R84: =VLOOKUP(Table13[[#This Row],[Item '#]],[2]Sheet1!$B:$D,3,0) -> 5701
A85: 6017-EACH | B85: B07SH9KVKW | C85: B07SH9KVKW | D85: =VLOOKUP(Table13[[#This Row],[SKU]],Data1!A:B,2,0) -> 6017 | E85: =Table13[[#This Row],[UoM]]*Table13[[#This Row],[Recommended Replenishment Qty]] -> 336 | F85: =Table13[[#This Row],[Total EA (Transfer to WH06)]]/Table13[[#This Row],[UoM]] -> 336 | H85: =Table13[[#This Row],[Total EA (Transfer to WH06)]]/Table13[[#This Row],[CASE]] -> 14 | I85: =Table13[[#This Row],[Sellable Unit/Set/box to ship]]/Table13[[#This Row],[Case to pull]] -> 24 | J85: =IF(ISNUMBER(SEARCH("FNSKU",K85)),"Labeling","") | K85: =VLOOKUP(Table13[[#This Row],[SKU]],Instruction!A:F,6,0) -> Apply outer box/case label accordingly to match item# (Cover all existing barcodes on the box/case) | L85: =VLOOKUP(Table13[[#This Row],[SKU]],Instruction!A:G,7,0) -> 0 | M85: =VLOOKUP(Table13[[#This Row],[ASIN]],'[1]2024'!$A:$AB,28,0) -> No Supplies | N85: =VLOOKUP(Table13[[#This Row],[SKU]],Data1!A:C,3,0) -> 1 | O85: =VLOOKUP(Table13[[#This Row],[Item '#]],Data2!A:D,4,0) -> 0 | P85: =VLOOKUP(Table13[[#This Row],[Item '#]],Data2!A:D,3,0) -> 24 | Q85: 336 | R85: =VLOOKUP(Table13[[#This Row],[Item '#]],[2]Sheet1!$B:$D,3,0) -> 18829
