Workbook

Sheet Inventory to Send
A1: Country | B1: Product Name | C1: FNSKU | D1: Merchant SKU | E1: ASIN | F1: Available | G1: Last 12 Month (30 day pace) | H1: Last 45 (30 day pacing) | I1: Last 14 (30 day pacing) | J1: Estimated 60 Day | K1: AWD Units Available | L1: New Inventory Required to Send | M1: Inventory to Send | N1: Inventory to Send from AWD | O1: FBA Days Remaining | P1: Do Not Send
A2: US | B2: BAZIC Products Date Stamper with Black Ink Pads for Stamping, 12 Years of Adjustable Dates, Ideal for Office, Shipping, Receiving, Accounting, Expiration Date Stamp, Due Dates - 1 Pack | C2: B08P3W6YN6 | D2: FBA_6301-EACH | E2: B08P3W6YN6 | F2: 6 | G2: 306.16776 | H2: 376.66685 | I2: 81.32 | J2: 753.33371 | K2: 0 | L2: 747.33371 | M2: 747.33371 | N2: 0 | O2: 0.31858391 | P2: =IFERROR(VLOOKUP(E2,'Do Not Send'!A:B,2,FALSE),"-") -> -
A3: US | B3: BAZIC Colored (12 Pcs) + White (12 Pcs) Chalk + Premium Chalkboard Eraser Bundle, Non-Toxic Kids Art Office Classroom Store Home, 1-Pack | C3: B003BUI01W | D3: FBA_2402-EACH | E3: B003BUI01W | F3: 213 | G3: 69.983553 | H3: 374.66685 | I3: 243.96 | J3: 749.33371 | K3: 0 | L3: 536.33371 | M3: 536.33371 | N3: 0 | O3: 11.370101 | P3: =IFERROR(VLOOKUP(E3,'Do Not Send'!A:B,2,FALSE),"-") -> -
A4: US | B4: BAZIC Ballpoint Pen Spencer Red Retractable Pen Soft Barrel Grip Pens, 1.0 mm Bold Point Smooth Writing, for Office School Teacher (5/Pack), 1-Pack | C4: B00FBOMTA4 | D4: FBA_17049-EACH | E4: B00FBOMTA4 | F4: 43 | G4: 100.65789 | H4: 234.00012 | I4: 391.62 | J4: 468.00023 | K4: 0 | L4: 425.00023 | M4: 425.00023 | N4: 0 | O4: 3.6752118 | P4: =IFERROR(VLOOKUP(E4,'Do Not Send'!A:B,2,FALSE),"-") -> -
A5: US | B5: BAZIC Mechanical Pencil Lead Refills HB 0.7mm (160 Count/Pack), Pencil Lead Refill, 1-Pack | C5: B00FBOIJMG | D5: FBA_781-EACH | E5: B00FBOIJMG | F5: 14 | G5: 53.865132 | H5: 212.66677 | I5: 250.38 | J5: 425.33355 | K5: 0 | L5: 411.33355 | M5: 411.33355 | N5: 0 | O5: 1.3166138 | P5: =IFERROR(VLOOKUP(E5,'Do Not Send'!A:B,2,FALSE),"-") -> -
A6: US | B6: BAZIC Products Plastic Ruler 6" 15 cm, Transparent Assorted Color Measuring Tool with Inches & Centimeters, Durable Plastic Rulers for, School, Office, and Home, 3/Pack, 1-Pack | C6: B07S4BSLL5 | D6: FBA_338-EACH | E6: B07S4BSLL5 | F6: 24 | G6: 66.036184 | H6: 189.33343 | I6: 94.16 | J6: 378.66686 | K6: 0 | L6: 354.66686 | M6: 354.66686 | N6: 0 | O6: 2.53521 | P6: =IFERROR(VLOOKUP(E6,'Do Not Send'!A:B,2,FALSE),"-") -> -
A7: US | B7: BAZIC Products Wooden Ruler 12" (30cm), Singel Metal Edge, Inches Centimeter Metric Measuring Drafting Rulers, for Students School Supplies (3/Pack), 1-Pack | C7: B003BMX6SC | D7: FBA_306-EACH | E7: B003BMX6SC | F7: 49 | G7: 67.105263 | H7: 196.0001 | I7: 147.66 | J7: 392.0002 | K7: 0 | L7: 343.0002 | M7: 343.0002 | N7: 0 | O7: 4.9999975 | P7: =IFERROR(VLOOKUP(E7,'Do Not Send'!A:B,2,FALSE),"-") -> -
A8: US | B8: BAZIC Staples Standard (26/6) Metallic Color 3000/Pack, Stapler Refill Standard Size Staple, Assorted Colors, 1-Pack | C8: B00ESWRD10 | D8: FBA_609-EACH | E8: B00ESWRD10 | F8: 225 | G8: 46.052632 | H8: 266.00013 | I8: 368.08 | J8: 532.00027 | K8: 0 | L8: 307.00027 | M8: 307.00027 | N8: 0 | O8: 16.917285 | P8: =IFERROR(VLOOKUP(E8,'Do Not Send'!A:B,2,FALSE),"-") -> -
A9: US | B9: BAZIC Products Book Wrap - Clear Book Cover Self Adhesive Book Protector for Book Covers for Paperbacks, Plastic Cover for Books, Clear Contact Paper Peel and Stick, 17.5" x 1.7 Yard Roll, 1-Roll | C9: B076F13SG5 | D9: FBA_2901-EACH | E9: B076F13SG5 | F9: 455 | G9: 310.77303 | H9: 380.66686 | I9: 346.68 | J9: 761.33371 | K9: 0 | L9: 306.33371 | M9: 306.33371 | N9: 0 | O9: 23.905417 | P9: =IFERROR(VLOOKUP(E9,'Do Not Send'!A:B,2,FALSE),"-") -> -
A10: US | B10: BAZIC Products Paid Self-Inking Stamp with Red Ink for Office, Business, and Documents, Easy Refillable Pad, Crisp & Clear Impressions, 1-Pack | C10: B08P3WZTXG | D10: FBA_6303-EACH | E10: B08P3WZTXG | F10: 144 | G10: 96.134868 | H10: 189.33343 | I10: 53.5 | J10: 378.66686 | K10: 0 | L10: 234.66686 | M10: 234.66686 | N10: 0 | O10: 15.21126 | P10: =IFERROR(VLOOKUP(E10,'Do Not Send'!A:B,2,FALSE),"-") -> -
A11: US | B11: BAZIC Products Open Closed Signs for Business, Double-sided Vinyl Open Signs for Business Window With Will Return Clock Sign, Be Back Sign With Clock, Ideal for Businesses, Shop, Office & More, 7.5"X9" 1-pack | C11: X003GYE2EX | D11: FBA_4398-EACH | E11: B07SFKBQ7F | F11: 3 | G11: 181.82566 | H11: 100.66672 | I11: 21.4 | J11: 201.33343 | K11: 0 | L11: 198.33343 | M11: 198.33343 | N11: 0 | O11: 0.59602619 | P11: =IFERROR(VLOOKUP(E11,'Do Not Send'!A:B,2,FALSE),"-") -> -
A12: US | B12: BAZIC Invisible Tape w/Dispenser 3/4" X 500", Matte Finish Stationery Tapes Rolls, for Arts Craft Photo Gift Wrapping, (3/Pack), 1-Pack | C12: B0018ML7KG | D12: FBA_903-EACH | E12: B0018ML7KG | F12: 291 | G12: 135.85526 | H12: 240.00012 | I12: 64.2 | J12: 480.00024 | K12: 0 | L12: 189.00024 | M12: 189.00024 | N12: 0 | O12: 24.249988 | P12: =IFERROR(VLOOKUP(E12,'Do Not Send'!A:B,2,FALSE),"-") -> -
A13: US | B13: BAZIC Products Assorted Color Gel Pencil Grip Pen Grip, Finger Grip Pencil Holder, Style May Vary (8/Pack), Pack of 1 | C13: B002WFI620 | D13: FBA_1502-EACH | E13: B002WFI620 | F13: 470 | G13: 49.506579 | H13: 325.3335 | I13: 524.3 | J13: 650.66699 | K13: 0 | L13: 180.66699 | M13: 180.66699 | N13: 0 | O13: 28.893428 | P13: =IFERROR(VLOOKUP(E13,'Do Not Send'!A:B,2,FALSE),"-") -> -
... A162: US | B162: BAZIC Products Chalk Board Eraser, Wood Felt Blackboard and White Board Eraser – Durable Cleaner for Classroom, Office, or Home Use, 4-Packs | C162: X003L8SD9T | D162: FBA_6003-PACK4 | E162: B08JHHM6KN | F162: 11 | G162: 3.125 | H162: 9.333338 | I162: 10.7 | J162: 18.666676 | K162: 36 | L162: 7.666676 | M162: 0 | N162: 7.666676 | O162: 23.571417 | P162: =IFERROR(VLOOKUP(E162,'Do Not Send'!A:B,2,FALSE),"-") -> -

Sheet BoxCase Inventory to Send
A1: Country | B1: Product Name | C1: FNSKU | D1: Merchant SKU | E1: ASIN | F1: Available | G1: Last 12 Month (30 day pace) | H1: Last 45 (30 day pacing) | I1: Last 14 (30 day pacing) | J1: Estimated 60 Day | K1: AWD Units Available | L1: New Inventory Required to Send | M1: Inventory to Send | N1: Inventory to Send from AWD | O1: FBA Days Remaining | P1: Do Not Send
A2: US | B2: BAZIC Products Composition Notebook Wide Ruled - 20 Sheets, Manila Color Composition Notebook with Durable Cover, Non-Spiral and Lined Paper for Journaling, School, Home, or Office, 24-Packs | C2: X003GHJQB9 | D2: FBA_5096-BOX | E2: B07XL4V3N1 | F2: 6 | G2: 42.680921 | H2: 44.000022 | I2: 27.82 | J2: 88.000044 | K2: 0 | L2: 82.000044 | M2: 82.000044 | N2: 0 | O2: 2.7272714 | P2: BOX/CASE PACK - TEMORARY DON'T SEND
A3: US | B3: BAZIC Products Multiplication Flash Cards, Numbers Elementary Math Flashcards Game at School, Problem Solving (36/Pack), 24-Packs | C3: X0044RLX07 | D3: FBA_534-BOX | E3: B07XQKHYRP | F3: 0 | G3: 49.588816 | H3: 38.000019 | I3: 55.64 | J3: 76.000038 | K3: 0 | L3: 76.000038 | M3: 76.000038 | N3: 0 | O3: 0 | P3: BOX/CASE PACK - TEMORARY DON'T SEND
A4: US | B4: BAZIC Products Composition Notebook 100 Sheet 5" x 7" Poly Cover Spiral Notebook, Writing Journal Notebook Mini Pocket Notebooks Assorted Color, 36-Pack | C4: X0040DSASN | D4: FBA_5476-CASE | E4: B0964J2MQ5 | F4: 0 | G4: 17.023026 | H4: 38.000019 | I4: 44.94 | J4: 76.000038 | K4: 0 | L4: 76.000038 | M4: 76.000038 | N4: 0 | O4: 0 | P4: BOX/CASE PACK - TEMORARY DON'T SEND
A5: US | B5: BAZIC Products Subtraction Flash Cards, Numbers Math Flashcards Game at School Home, Problem Solving (36/Pack), 24-Packs | C5: X0044RLXAR | D5: FBA_533-BOX | E5: B07XQLGMSV | F5: 0 | G5: 32.8125 | H5: 33.33335 | I5: 49.22 | J5: 66.6667 | K5: 0 | L5: 66.6667 | M5: 66.6667 | N5: 0 | O5: 0 | P5: BOX/CASE PACK - TEMORARY DON'T SEND
A6: US | B6: BAZIC Products Multiplication Flash Cards, Numbers Elementary Math Flashcards Game at School, Problem Solving (36/Pack), 72-Packs | C6: X0044R3MNN | D6: FBA_534-CASE | E6: B09NMXGBYP | F6: 0 | G6: 21.052632 | H6: 32.000016 | I6: 47.08 | J6: 64.000032 | K6: 0 | L6: 64.000032 | M6: 64.000032 | N6: 0 | O6: 0 | P6: BOX/CASE PACK - TEMORARY DON'T SEND
A7: US | B7: BAZIC Products Composition Notebook Wide Ruled - 20 Sheets, Manila Color Composition Notebook with Durable Cover, Non-Spiral and Lined Paper for Journaling, School, Home, or Office, 24-Packs | C7: B00GKINMJ2 | D7: FBA_5096-BOX-1 | E7: B00GKINMJ2 | F7: 0 | G7: 49.671053 | H7: 29.333348 | I7: 19.26 | J7: 58.666696 | K7: 0 | L7: 58.666696 | M7: 58.666696 | N7: 0 | O7: 0 | P7: BOX/CASE PACK - TEMORARY DON'T SEND
A8: US | B8: BAZIC 1" Matte Color Poly 3-Ring Binder w/ Pocket for School, Home, or Office (Case of 48) (3132-48) | C8: B00275E9XU | D8: FBA_3132-CASE-B | E8: B00275E9XU | F8: 1 | G8: 10.279605 | H8: 20.666677 | I8: 40.66 | J8: 41.333354 | K8: 0 | L8: 40.333354 | M8: 40.333354 | N8: 0 | O8: 0.96774145 | P8: BOX/CASE PACK - TEMORARY DON'T SEND
A9: US | B9: BAZIC Products Trifold Poster Board – White Corrugated Cardboard Display Board for school projects, science fairs, photos, charts, and classroom presentations, 28" x 40", 30-Pack | C9: B07X576XMT | D9: FBA_5086-CASE | E9: B07X576XMT | F9: 0 | G9: 32.894737 | H9: 20.00001 | I9: 53.5 | J9: 40.00002 | K9: 0 | L9: 40.00002 | M9: 40.00002 | N9: 0 | O9: 0 | P9: BOX/CASE PACK - TEMORARY DON'T SEND
A10: US | B10: BAZIC Products Poster Board Green 22" X 28", Colored Poster Board Paper, Bulk Boards for School Craft Project Presentation Drawing Graphic Display, 25-Pack | C10: X003SC1YHV | D10: FBA_5017-CASE | E10: B07X22QHGF | F10: 0 | G10: 13.240132 | H10: 19.333343 | I10: 12.84 | J10: 38.666686 | K10: 0 | L10: 38.666686 | M10: 38.666686 | N10: 0 | O10: 0 | P10: BOX/CASE PACK - TEMORARY DON'T SEND
A11: US | B11: BAZIC Products 3 Ring Binder 1/2" Economy View Binders Organizer - Red, Round Ring, Hold 100 Sheets Paper, for School Office Home, 12-Count | C11: X0044RLTGZ | D11: FBA_4103-CASE | E11: B07QC4VQ8V | F11: 1 | G11: 16.282895 | H11: 17.333342 | I11: 0 | J11: 34.666684 | K11: 0 | L11: 33.666684 | M11: 33.666684 | N11: 0 | O11: 1.1538456 | P11: BOX/CASE PACK - TEMORARY DON'T SEND
A12: US | B12: BAZIC Products Purchase Order Book, 30 Sets 8 3/8" x 10 11/16" 2-Part Carbonless, White & Bound Wraparound Cover (50 Sets/Pack), 12-Packs | C12: X003SBSK29 | D12: FBA_5077-A-CASE | E12: B07XJZDPL5 | F12: 0 | G12: 10.9375 | H12: 16.000008 | I12: 23.54 | J12: 32.000016 | K12: 0 | L12: 32.000016 | M12: 32.000016 | N12: 0 | O12: 0 | P12: BOX/CASE PACK - TEMORARY DON'T SEND
A13: US | B13: BAZIC Products Addition Flash Cards, Numbers Math Flashcards Game at School Home, Problem Solving (36/Pack), 24-Packs | C13: X0044R3MFV | D13: FBA_532-BOX | E13: B07XQGFLTT | F13: 61 | G13: 43.256579 | H13: 44.000022 | I13: 77.04 | J13: 88.000044 | K13: 0 | L13: 27.000044 | M13: 27.000044 | N13: 0 | O13: 27.727259 | P13: BOX/CASE PACK - TEMORARY DON'T SEND
... A80: US | B80: BAZIC Products 3 Ring Binder 1" Economy View Binders Organizer - Purple, Round Ring, Hold 175 Sheets Paper, for School Office Home, 12-Count | C80: X003SC97LB | D80: FBA_4127-CASE | E80: B07QF61WN3 | F80: 2 | G80: 4.9342105 | H80: 1.333334 | I80: 2.14 | J80: 2.666668 | K80: 0 | L80: 0.666668 | M80: 0.666668 | N80: 0 | O80: 29.999985 | P80: BOX/CASE PACK - TEMORARY DON'T SEND

Sheet Do Not Send
A1: Asin | B1: NOTE
A2: B08FK9Z656 | B2: BOX/CASE PACK - TEMORARY DON'T SEND
A3: B07QF4V3CC | B3: BOX/CASE PACK - TEMORARY DON'T SEND
A4: B07XL4V3N1 | B4: BOX/CASE PACK - TEMORARY DON'T SEND
A5: B07XQJFXT3 | B5: BOX/CASE PACK - TEMORARY DON'T SEND
A6: B09NMSV1KG | B6: BOX/CASE PACK - TEMORARY DON'T SEND
A7: B07XQP9HMF | B7: BOX/CASE PACK - TEMORARY DON'T SEND
A8: B07SF72V1F | B8: BOX/CASE PACK - TEMORARY DON'T SEND
A9: B07YL8HJQL | B9: BOX/CASE PACK - TEMORARY DON'T SEND
A10: B07YL8PNHY | B10: BOX/CASE PACK - TEMORARY DON'T SEND
A11: B07SD8LDKN | B11: BOX/CASE PACK - TEMORARY DON'T SEND
A12: B07YL75NTZ | B12: BOX/CASE PACK - TEMORARY DON'T SEND
... A360: FBA_1263-EACH | B360: Dangerous Goods

Sheet Proposed FBA Skus
A1: (Child) ASIN | B1: FBA Sku Exists? | C1: Monthly Units Last 45 days | D1: AWD Inventory | E1: Total Inventory to Send | F1: Inventory to Send | G1: Inventory to Send from AWD | H1: Do Not Send
A2: B01HTYG3LE | B2: =IF(COUNTIF('FBA Inventory'!E:E, A2)>0,"Yes","No") -> Yes | C2: =IFERROR(VLOOKUP(A2,'2025 Pivot'!A:B,2,FALSE),0)*0.666667 -> 187.33343 | D2: =IFERROR(VLOOKUP(A2,AWD!D:G,4,FALSE),0) -> 0 | E2: =IF(H2="-", IF(B2="yes", "-", (IF(C2>4.99999,C2*2,"-"))), "-") -> - | F2: =IF(E2="-","-",E2-G2) -> - | G2: =IF(E2="-","-", IF(E2>D2,D2,E2)) -> - | H2: =IFERROR(VLOOKUP(A2,'Do Not Send'!A:B,2,FALSE),"-") -> -
A3: B0BG14KCKZ | B3: =IF(COUNTIF('FBA Inventory'!E:E, A3)>0,"Yes","No") -> Yes | C3: =IFERROR(VLOOKUP(A3,'2025 Pivot'!A:B,2,FALSE),0)*0.666667 -> 3490.0017 | D3: =IFERROR(VLOOKUP(A3,AWD!D:G,4,FALSE),0) -> 0 | E3: =IF(H3="-", IF(B3="yes", "-", (IF(C3>4.99999,C3*2,"-"))), "-") -> - | F3: =IF(E3="-","-",E3-G3) -> - | G3: =IF(E3="-","-", IF(E3>D3,D3,E3)) -> - | H3: =IFERROR(VLOOKUP(A3,'Do Not Send'!A:B,2,FALSE),"-") -> BTS ITEM - DON'T SEND
A4: B08P3W6YN6 | B4: =IF(COUNTIF('FBA Inventory'!E:E, A4)>0,"Yes","No") -> Yes | C4: =IFERROR(VLOOKUP(A4,'2025 Pivot'!A:B,2,FALSE),0)*0.666667 -> 706.66702 | D4: =IFERROR(VLOOKUP(A4,AWD!D:G,4,FALSE),0) -> 0 | E4: =IF(H4="-", IF(B4="yes", "-", (IF(C4>4.99999,C4*2,"-"))), "-") -> - | F4: =IF(E4="-","-",E4-G4) -> - | G4: =IF(E4="-","-", IF(E4>D4,D4,E4)) -> - | H4: =IFERROR(VLOOKUP(A4,'Do Not Send'!A:B,2,FALSE),"-") -> -
A5: B001BNW7QA | B5: =IF(COUNTIF('FBA Inventory'!E:E, A5)>0,"Yes","No") -> Yes | C5: =IFERROR(VLOOKUP(A5,'2025 Pivot'!A:B,2,FALSE),0)*0.666667 -> 2038.6677 | D5: =IFERROR(VLOOKUP(A5,AWD!D:G,4,FALSE),0) -> 0 | E5: =IF(H5="-", IF(B5="yes", "-", (IF(C5>4.99999,C5*2,"-"))), "-") -> - | F5: =IF(E5="-","-",E5-G5) -> - | G5: =IF(E5="-","-", IF(E5>D5,D5,E5)) -> - | H5: =IFERROR(VLOOKUP(A5,'Do Not Send'!A:B,2,FALSE),"-") -> DUPLICATE ASIN - MERGE BEFORE SENDING
A6: B07SFKBQ7F | B6: =IF(COUNTIF('FBA Inventory'!E:E, A6)>0,"Yes","No") -> Yes | C6: =IFERROR(VLOOKUP(A6,'2025 Pivot'!A:B,2,FALSE),0)*0.666667 -> 412.00021 | D6: =IFERROR(VLOOKUP(A6,AWD!D:G,4,FALSE),0) -> 0 | E6: =IF(H6="-", IF(B6="yes", "-", (IF(C6>4.99999,C6*2,"-"))), "-") -> - | F6: =IF(E6="-","-",E6-G6) -> - | G6: =IF(E6="-","-", IF(E6>D6,D6,E6)) -> - | H6: =IFERROR(VLOOKUP(A6,'Do Not Send'!A:B,2,FALSE),"-") -> -
A7: B076F13SG5 | B7: =IF(COUNTIF('FBA Inventory'!E:E, A7)>0,"Yes","No") -> Yes | C7: =IFERROR(VLOOKUP(A7,'2025 Pivot'!A:B,2,FALSE),0)*0.666667 -> 531.3336 | D7: =IFERROR(VLOOKUP(A7,AWD!D:G,4,FALSE),0) -> 0 | E7: =IF(H7="-", IF(B7="yes", "-", (IF(C7>4.99999,C7*2,"-"))), "-") -> - | F7: =IF(E7="-","-",E7-G7) -> - | G7: =IF(E7="-","-", IF(E7>D7,D7,E7)) -> - | H7: =IFERROR(VLOOKUP(A7,'Do Not Send'!A:B,2,FALSE),"-") -> -
A8: B01HDJMKBM | B8: =IF(COUNTIF('FBA Inventory'!E:E, A8)>0,"Yes","No") -> Yes | C8: =IFERROR(VLOOKUP(A8,'2025 Pivot'!A:B,2,FALSE),0)*0.666667 -> 156.00008 | D8: =IFERROR(VLOOKUP(A8,AWD!D:G,4,FALSE),0) -> 0 | E8: =IF(H8="-", IF(B8="yes", "-", (IF(C8>4.99999,C8*2,"-"))), "-") -> - | F8: =IF(E8="-","-",E8-G8) -> - | G8: =IF(E8="-","-", IF(E8>D8,D8,E8)) -> - | H8: =IFERROR(VLOOKUP(A8,'Do Not Send'!A:B,2,FALSE),"-") -> -
A9: B003BMX65A | B9: =IF(COUNTIF('FBA Inventory'!E:E, A9)>0,"Yes","No") -> Yes | C9: =IFERROR(VLOOKUP(A9,'2025 Pivot'!A:B,2,FALSE),0)*0.666667 -> 628.00031 | D9: =IFERROR(VLOOKUP(A9,AWD!D:G,4,FALSE),0) -> 0 | E9: =IF(H9="-", IF(B9="yes", "-", (IF(C9>4.99999,C9*2,"-"))), "-") -> - | F9: =IF(E9="-","-",E9-G9) -> - | G9: =IF(E9="-","-", IF(E9>D9,D9,E9)) -> - | H9: =IFERROR(VLOOKUP(A9,'Do Not Send'!A:B,2,FALSE),"-") -> -
A10: B0018ML7KG | B10: =IF(COUNTIF('FBA Inventory'!E:E, A10)>0,"Yes","No") -> Yes | C10: =IFERROR(VLOOKUP(A10,'2025 Pivot'!A:B,2,FALSE),0)*0.666667 -> 20.666677 | D10: =IFERROR(VLOOKUP(A10,AWD!D:G,4,FALSE),0) -> 0 | E10: =IF(H10="-", IF(B10="yes", "-", (IF(C10>4.99999,C10*2,"-"))), "-") -> - | F10: =IF(E10="-","-",E10-G10) -> - | G10: =IF(E10="-","-", IF(E10>D10,D10,E10)) -> - | H10: =IFERROR(VLOOKUP(A10,'Do Not Send'!A:B,2,FALSE),"-") -> -
A11: B0BCL7XWNT | B11: =IF(COUNTIF('FBA Inventory'!E:E, A11)>0,"Yes","No") -> Yes | C11: =IFERROR(VLOOKUP(A11,'2025 Pivot'!A:B,2,FALSE),0)*0.666667 -> 469.33357 | D11: =IFERROR(VLOOKUP(A11,AWD!D:G,4,FALSE),0) -> 0 | E11: =IF(H11="-", IF(B11="yes", "-", (IF(C11>4.99999,C11*2,"-"))), "-") -> - | F11: =IF(E11="-","-",E11-G11) -> - | G11: =IF(E11="-","-", IF(E11>D11,D11,E11)) -> - | H11: =IFERROR(VLOOKUP(A11,'Do Not Send'!A:B,2,FALSE),"-") -> -
A12: B0BCL6MSMS | B12: =IF(COUNTIF('FBA Inventory'!E:E, A12)>0,"Yes","No") -> Yes | C12: =IFERROR(VLOOKUP(A12,'2025 Pivot'!A:B,2,FALSE),0)*0.666667 -> 357.33351 | D12: =IFERROR(VLOOKUP(A12,AWD!D:G,4,FALSE),0) -> 0 | E12: =IF(H12="-", IF(B12="yes", "-", (IF(C12>4.99999,C12*2,"-"))), "-") -> - | F12: =IF(E12="-","-",E12-G12) -> - | G12: =IF(E12="-","-", IF(E12>D12,D12,E12)) -> - | H12: =IFERROR(VLOOKUP(A12,'Do Not Send'!A:B,2,FALSE),"-") -> -
A13: B00ZPRYV0I | B13: =IF(COUNTIF('FBA Inventory'!E:E, A13)>0,"Yes","No") -> Yes | C13: =IFERROR(VLOOKUP(A13,'2025 Pivot'!A:B,2,FALSE),0)*0.666667 -> 69.333368 | D13: =IFERROR(VLOOKUP(A13,AWD!D:G,4,FALSE),0) -> 0 | E13: =IF(H13="-", IF(B13="yes", "-", (IF(C13>4.99999,C13*2,"-"))), "-") -> - | F13: =IF(E13="-","-",E13-G13) -> - | G13: =IF(E13="-","-", IF(E13>D13,D13,E13)) -> - | H13: =IFERROR(VLOOKUP(A13,'Do Not Send'!A:B,2,FALSE),"-") -> -
... A2205: B0FTKWXTHX | B2205: =IF(COUNTIF('FBA Inventory'!E:E, A2205)>0,"Yes","No") -> Yes | C2205: =IFERROR(VLOOKUP(A2205,'2025 Pivot'!A:B,2,FALSE),0)*0.666667 -> 0 | D2205: =IFERROR(VLOOKUP(A2205,AWD!D:G,4,FALSE),0) -> 0 | E2205: =IF(H2205="-", IF(B2205="yes", "-", (IF(C2205>4.99999,C2205*2,"-"))), "-") -> - | F2205: =IF(E2205="-","-",E2205-G2205) -> - | G2205: =IF(E2205="-","-", IF(E2205>D2205,D2205,E2205)) -> - | H2205: =IFERROR(VLOOKUP(A2205,'Do Not Send'!A:B,2,FALSE),"-") -> -

Sheet Working Sheet
A1: Country | B1: Product Name | C1: Merchant SKU | D1: ASIN | E1: FNSKU | F1: Available | G1: 2024 BTS Units Sold | H1: 2025 BTS Units Sold | I1: Last 2 Months Units Sold | K1: Estimated Units Needed for 2026 BTS | L1: Est Inv on hand at BTS Start | M1: Total Inv to send | N1: AWD Units Available | O1: Inv to Send from AWD | P1: Inv to Send from Warehouse | Q1: 2025 BTS Sales as % of 2024 BTS Unit Sales | R1: New Inventory Required to Send | S1: Inventory to Send to FBA | T1: Inventory to Send from AWD | U1: FBA Days Remaining | V1: Condition | W1: Supplier | X1: Supplier part no. | Y1: Currency code | Z1: Price | AA1: Sales last 30 days | AB1: Units Sold Last 30 Days | AC1: Total Units | AD1: Inbound | AE1: Available | AF1: FC transfer | AG1: FC Processing | AH1: Customer Order | AI1: Unfulfillable | AJ1: Working | AK1: Shipped | AL1: Receiving | AM1: Fulfilled by | AN1: Total Days of Supply (including units from open shipments) | AO1: Days of Supply at Amazon Fulfillment Network | AP1: Alert | AQ1: Recommended replenishment qty | AR1: Recommended ship date | AS1: Recommended action | AT1: Unit storage size | AU1: Last 2 months sales as % of Estimated Need for 2026 BTS
A2: US | B2: BAZIC PRODUCTS Middle & High School Kit Supply Box, 65-Count Student Set for Grades 7–12, Complete School Supply Kit with Middle School Supplies, Organized Supply Box for Highschool, 1-Pack | C2: FBA_8006-CASE | D2: B0BG14KCKZ | E2: X003XE2C7F | F2: 0 | G2: 5151 | H2: 5235 | I2: 6 | J2: 15 | K2: 5235 | L2: 0 | M2: 5235 | N2: 0 | O2: 0 | P2: 5235 | Q2: 1.0163075 | R2: 5235 | S2: 5235 | T2: 0 | U2: 0 | V2: New | W2: BAZIC Products | Y2: USD | Z2: 42.89 | AA2: 0 | AB2: 0 | AC2: 0 | AD2: 0 | AE2: 0 | AF2: 0 | AG2: 0 | AH2: 0 | AI2: 0 | AJ2: 0 | AK2: 0 | AL2: 0 | AM2: Amazon | AN2: 0 | AO2: 0 | AP2: out_of_stock | AQ2: 80 | AR2: 46048 | AS2: Create shipping plan | AT2: 0.2911 ft3
A3: US | B3: BAZIC Products Pink Eraser, Latex Free Bevel Block Erasers, Large Size for Classroom, Office, and Art Use, Smooth Pencil Correction for Writing, Sketching, & Daily Tasks, 4/Pack, 1-Pack | C3: FBA_2227-EACH-UPC | D3: B001BNW7QA | E3: B001BNW7QA | F3: 8 | G3: 2399 | H3: 3058 | I3: 21 | J3: 52.5 | K3: 3058 | L3: 0 | M3: 3058 | N3: 0 | O3: 0 | P3: 3058 | Q3: 1.2746978 | R3: 3050 | S3: 3050 | T3: 0 | U3: 0.10464356 | V3: New | W3: BAZIC Products | Y3: USD | Z3: 3.69 | AA3: 0 | AB3: 0 | AC3: 10 | AD3: 0 | AE3: 10 | AF3: 0 | AG3: 0 | AH3: 0 | AI3: 0 | AJ3: 0 | AK3: 0 | AL3: 0 | AM3: Amazon | AQ3: 0 | AR3: none | AS3: No action required | AT3: 0.006 ft3
A4: US | B4: BAZIC Eraser Top, Latex Free Pencil Tops Erasers (20/Pack), Neon Color Arrowhead Caps Erasers for Kids Student Art Drawing School Supplies, 1-Pack | C4: FBA_2202-EACH | D4: B003BNZVI4 | E4: B003BNZVI4 | F4: 268 | G4: 1697 | H4: 1190 | I4: 66 | J4: 165 | K4: 1697 | L4: 103 | M4: 1594 | N4: 0 | O4: 0 | P4: 1594 | Q4: 0.70123748 | R4: 1429 | S4: 1429 | T4: 0 | U4: 6.3170301 | V4: New | W4: BAZIC Products | Y4: USD | Z4: 4.59 | AA4: 210.74 | AB4: 46 | AC4: 325 | AD4: 0 | AE4: 322 | AF4: 1 | AG4: 2 | AH4: 0 | AI4: 0 | AJ4: 0 | AK4: 0 | AL4: 0 | AM4: Amazon | AN4: 120 | AO4: 119 | AQ4: 0 | AR4: none | AS4: No action required | AT4: 0.009 ft3 | AU4: 0.038892163
A5: US | B5: BAZIC Pencil Pouch 3 Ring Binder Pouch w/Rivet Enforced Rings Hole, Black Mesh Window Zipper Pouches, 1-Count | C5: FBA_808-EACH | D5: B09DP3TR4F | E5: B09DP3TR4F | F5: 505 | G5: 1902 | H5: 1244 | I5: 45 | J5: 112.5 | K5: 1902 | L5: 392.5 | M5: 1509.5 | N5: 0 | O5: 0 | P5: 1509.5 | Q5: 0.65404837 | R5: 1397 | S5: 1397 | T5: 0 | U5: 10.6204 | V5: New | W5: BAZIC Products | Y5: USD | Z5: 4.09 | AA5: 118.61 | AB5: 29 | AC5: 548 | AD5: 0 | AE5: 546 | AF5: 2 | AG5: 0 | AH5: 0 | AI5: 0 | AJ5: 0 | AK5: 0 | AL5: 0 | AM5: Amazon | AN5: 184 | AO5: 184 | AQ5: 0 | AR5: none | AS5: No action required | AT5: 0.0344 ft3 | AU5: 0.023659306
A6: US | B6: BAZIC Products Sketch Pad, Spiral Sketchbook for Artists & Students, Drawing Pad with Thick Paper, Sketching & Drawing for Kids, Teens & Adults, 50 Sheets, 6" x 8", 1-Pack | C6: FBA_5043-EACH | D6: B00H9Z198Q | E6: B00H9Z198Q | F6: 522 | G6: 1650 | H6: 42 | I6: 333 | J6: 832.5 | K6: 1650 | L6: 0 | M6: 1650 | N6: 336 | O6: 336 | P6: 1314 | Q6: 0.025454545 | R6: 1128 | S6: 792 | T6: 336 | U6: 12.654545 | V6: New | W6: BAZIC Products | Y6: USD | Z6: 4.46 | AA6: 1234.8 | AB6: 260 | AC6: 755 | AD6: 480 | AE6: 122 | AF6: 114 | AG6: 3 | AH6: 36 | AI6: 2 | AJ6: 0 | AK6: 480 | AL6: 0 | AM6: Amazon | AN6: 142 | AO6: 134 | AQ6: 0 | AR6: none | AS6: No action required | AT6: 0.0054 ft3 | AU6: 0.20181818
C7: FBA_510-EACH-B | D7: B0018MN4RA | F7: 0 | G7: 3751 | H7: 89 | I7: 1 | J7: 2.5 | K7: 1280.3333 | L7: 0 | M7: 1280.3333 | N7: 0 | O7: 0 | P7: 1280.3333 | Q7: 0.023727006 | R7: 1280.3333 | S7: 1280.3333 | T7: 0 | U7: 0 | AU7: 0.0007810466
B8: BAZIC Products Blank Paper Copy & Multipurpose Paper | C8: FBA_510-EACH-B | D8: B0018MN4RA | F8: 0 | G8: 3751 | H8: 89 | I8: 1 | J8: 1280 | K8: 1280 | L8: 0 | M8: 1280 | N8: 0 | O8: 0 | P8: 1280 | Q8: 0.0237 | R8: 0.0008 | AU8: 0.0008
A9: US | B9: BAZIC Products Binder Dividers, 8.5 x 11 Plastic Index, 11 Hole Punch for 3 Ring Binders, Organizer, Ideal for School, Office, Home Organization, 10 Tab, 10/Pack, 1-Pack | C9: FBA_3107-EACH | D9: B07S4GZW7L | E9: X003BBR0T5 | F9: 27 | G9: 910 | H9: 1277 | I9: 13 | J9: 32.5 | K9: 1277 | L9: 0 | M9: 1277 | N9: 0 | O9: 0 | P9: 1277 | Q9: 1.4032967 | R9: 1250 | S9: 1250 | T9: 0 | U9: 0.84573218 | V9: New | W9: BAZIC Products | Y9: USD | Z9: 5.69 | AA9: 19.12 | AB9: 4 | AC9: 48 | AD9: 48 | AE9: 0 | AF9: 0 | AG9: 0 | AH9: 0 | AI9: 0 | AJ9: 0 | AK9: 48 | AL9: 0 | AM9: Amazon | AN9: 64 | AO9: 64 | AQ9: 0 | AR9: none | AS9: No action required | AT9: 0.0156 ft3
A10: US | B10: BAZIC Manila File Folder 1/3 Cut Letter Size, Left Right Center Tabs Positions, for Organizing Filing Document Storage, Total 12-Count | C10: FBA_3100-EACH | D10: B00ZPRYV0I | E10: B00ZPRYV0I | F10: 969 | G10: 1245 | H10: 104 | I10: 660 | J10: 1650 | K10: 1245 | L10: 0 | M10: 1245 | N10: 0 | O10: 0 | P10: 1245 | Q10: 0.083534137 | R10: 276 | S10: 276 | T10: 0 | U10: 31.13253 | V10: New | W10: BAZIC Products | Y10: USD | Z10: 4.59 | AA10: 1964.52 | AB10: 428 | AC10: 732 | AD10: 48 | AE10: 503 | AF10: 136 | AG10: 19 | AH10: 26 | AI10: 0 | AJ10: 0 | AK10: 48 | AL10: 0 | AM10: Amazon | AN10: 52 | AO10: 49 | AQ10: 48 | AR10: 46055 | AS10: Create shipping plan | AT10: 0.0331 ft3 | AU10: 0.53012048
A11: US | B11: BAZIC PRODUCTS Primary Journal Composition Book Marble, Primary Journal, Writing Journal, Notebooks for Kids, Drawing & Writing Notebook for Kindergarten School Use, Grades K-2, 100 Sheets, 2-Pack | C11: FBA_5053-SET2 | D11: B07S64FRBG | E11: X003AUSTNN | F11: 58 | G11: 1193 | H11: 1041 | I11: 16 | J11: 40 | K11: 1193 | L11: 18 | M11: 1175 | N11: 0 | O11: 0 | P11: 1175 | Q11: 0.87259011 | R11: 1135 | S11: 1135 | T11: 0 | U11: 1.9446773 | V11: New | W11: BAZIC Products | Y11: USD | Z11: 9.59 | AA11: 269.18 | AB11: 28 | AC11: 20 | AD11: 0 | AE11: 19 | AF11: 0 | AG11: 0 | AH11: 1 | AI11: 0 | AJ11: 0 | AK11: 0 | AL11: 0 | AM11: Amazon | AN11: 28 | AO11: 26 | AQ11: 72 | AR11: 46054 | AS11: Create shipping plan | AT11: 0.0354 ft3
A12: US | B12: BAZIC PRODUCTS Elementary School Supply Kit, 86-count Student Set for Elementary Students Grades 3-6, Complete School Supplies With Fully Organized Supply Box, 1-pack | C12: FBA_8005-CASE-B | D12: B0BB8R9HGQ | E12: B0BB8R9HGQ | F12: 80 | G12: 1167 | H12: 946 | I12: 0 | J12: 0 | K12: 1167 | L12: 80 | M12: 1087 | N12: 0 | O12: 0 | P12: 1087 | Q12: 0.81062554 | R12: 1087 | S12: 1087 | T12: 0 | U12: 2.7420737 | V12: New | W12: BAZIC Products | Y12: USD | Z12: 32.89 | AA12: 32.89 | AB12: 1 | AC12: 80 | AD12: 0 | AE12: 73 | AF12: 1 | AG12: 6 | AH12: 0 | AI12: 0 | AJ12: 0 | AK12: 0 | AL12: 0 | AM12: Amazon | AN12: 171 | AO12: 170 | AQ12: 0 | AR12: none | AS12: No action required | AT12: 0.311 ft3
A13: US | B13: BAZIC Products Mini Highlighter Pen Assorted Color, Chisel Tip Broad Fine Line Highlighters Coloring Marker (5/Pack), 1-Pack | C13: FBA_2306-EACH-1 | D13: B008ZHNN68 | E13: B008ZHNN68 | F13: 107 | G13: 1087 | H13: 16 | I13: 513 | J13: 1282.5 | K13: 1087 | L13: 0 | M13: 1087 | N13: 0 | O13: 0 | P13: 1087 | Q13: 0.014719411 | R13: 980 | S13: 980 | T13: 0 | U13: 3.9374425 | V13: New | W13: BAZIC Products | Y13: USD | Z13: 3.99 | AA13: 1125.18 | AB13: 282 | AC13: 490 | AD13: 0 | AE13: 325 | AF13: 126 | AG13: 20 | AH13: 19 | AI13: 1 | AJ13: 0 | AK13: 0 | AL13: 0 | AM13: Amazon | AN13: 26 | AO13: 24 | AQ13: 552 | AR13: 46055 | AS13: Create shipping plan | AT13: 0.0069 ft3 | AU13: 0.47194112
A14: US | B14: BAZIC Products 3 Ring Binder 1/2" Economy View Binders Organizer - Fuchsia, Round Ring, Hold 100 Sheets Paper, for School Office Home, 1-Count | C14: FBA_4106-EACH | D14: B07Q5VPWCP | E14: X003SC97LL | F14: 84 | G14: 1060 | H14: 1068 | I14: 42 | J14: 105 | K14: 1068 | L14: 0 | M14: 1068 | N14: 0 | O14: 0 | P14: 1068 | Q14: 1.0075472 | R14: 984 | S14: 984 | T14: 0 | U14: 3.1460674 | V14: New | W14: BAZIC Products | Y14: USD | Z14: 8.29 | AA14: 190.05 | AB14: 23 | AC14: 23 | AD14: 0 | AE14: 18 | AF14: 3 | AG14: 0 | AH14: 2 | AI14: 0 | AJ14: 0 | AK14: 0 | AL14: 0 | AM14: Amazon | AN14: 18 | AO14: 16 | AQ14: 24 | AR14: 46055 | AS14: Create shipping plan | AT14: 0.0761 ft3
A15: US | B15: BAZIC PRODUCTS Wide Ruled 1-Subject Notebook, Non-Spiral Composition Style, Easy-Tear Wireless Pages, 3-Hole Punched, 80 Sheets, Assorted Colors, for School, Office & Home, 6-Pack | C15: FBA_582-SET6 | D15: B07S964BMT | E15: X003SC1YG7 | F15: 44 | G15: 846 | H15: 1049 | I15: 17 | J15: 42.5 | K15: 1049 | L15: 1.5 | M15: 1047.5 | N15: 0 | O15: 0 | P15: 1047.5 | Q15: 1.2399527 | R15: 1005 | S15: 1005 | T15: 0 | U15: 1.6777884 | V15: New | W15: BAZIC Products | Y15: USD | Z15: 21.76 | AA15: 268.32 | AB15: 13 | AC15: 10 | AD15: 0 | AE15: 7 | AF15: 0 | AG15: 2 | AH15: 1 | AI15: 0 | AJ15: 0 | AK15: 0 | AL15: 0 | AM15: Amazon | AN15: 15 | AO15: 10 | AP15: low_stock | AQ15: 20 | AR15: 46055 | AS15: Create shipping plan | AT15: 0.1415 ft3
A16: US | B16: BAZIC Products Multiplication & Division Flash Cards, Educational Flash Cards for Kids, Math Flash Cards, Ideal for Math Learning Practice at Home or School, 36 Cards, 2-Pack | C16: FBA_534-EA+535-EA | D16: B08DHKDQ7J | E16: X003Z1GPEH | F16: 0 | G16: 453 | H16: 1017 | I16: 0 | J16: 0 | K16: 1017 | L16: 0 | M16: 1017 | N16: 0 | O16: 0 | P16: 1017 | Q16: 2.2450331 | R16: 1017 | S16: 1017 | T16: 0 | U16: 0 | V16: New | W16: BAZIC Products | Y16: USD | Z16: 7.39 | AA16: 0 | AB16: 0 | AC16: 0 | AD16: 0 | AE16: 0 | AF16: 0 | AG16: 0 | AH16: 0 | AI16: 0 | AJ16: 0 | AK16: 0 | AL16: 0 | AM16: Amazon | AP16: out_of_stock | AQ16: 0 | AR16: none | AS16: No action required | AT16: 0.0239 ft3
A17: US | B17: BAZIC Jeweltones Color Plastic Ruler 12" (30cm), Inches Centimeter Metric Measuring Rulers (4/Pack) | C17: FBA_336-EACH | D17: B003BMX65A | E17: X003TIPAXN | F17: 106 | G17: 1000 | H17: 942 | I17: 62 | J17: 155 | K17: 1000 | L17: 0 | M17: 1000 | N17: 0 | O17: 0 | P17: 1000 | Q17: 0.942 | R17: 894 | S17: 894 | T17: 0 | U17: 4.24 | V17: New | W17: BAZIC Products | Y17: USD | Z17: 4.89 | AA17: 156.48 | AB17: 32 | AC17: 170 | AD17: 0 | AE17: 169 | AF17: 1 | AG17: 0 | AH17: 0 | AI17: 0 | AJ17: 0 | AK17: 0 | AL17: 0 | AM17: Amazon | AN17: 151 | AO17: 151 | AQ17: 0 | AR17: none | AS17: No action required | AT17: 0.0158 ft3
A18: US | B18: BAZIC Products 3 Ring Binder 1.5" Economy View Binders Organizer - Fuchsia, Round Ring, Hold 280 Sheets Paper, for School Office Home, 1-Count | C18: FBA_4146-EACH | D18: B07Q97RZJC | E18: X003L8UNND | F18: 83 | G18: 983 | H18: 806 | I18: 181 | J18: 452.5 | K18: 983 | L18: 0 | M18: 983 | N18: 0 | O18: 0 | P18: 983 | Q18: 0.81993896 | R18: 900 | S18: 900 | T18: 0 | U18: 3.3774161 | V18: New | W18: BAZIC Products | Y18: USD | Z18: 11.29 | AA18: 225.76 | AB18: 20 | AC18: 314 | AD18: 0 | AE18: 295 | AF18: 14 | AG18: 1 | AH18: 4 | AI18: 1 | AJ18: 0 | AK18: 0 | AL18: 0 | AM18: Amazon | AN18: 189 | AO18: 189 | AQ18: 0 | AR18: none | AS18: No action required | AT18: 0.1439 ft3
A19: US | B19: BAZIC Products Sketch Pad, Spiral Sketchbook for Artists & Students, Drawing Pad with Thick Paper, Sketching & Drawing for Kids, Teens & Adults, 30 Sheets, 8.5" X 11", 1-Pack | C19: FBA_5045-EACH | D19: B07S94M6P6 | E19: X003DE6G1X | F19: 80 | G19: 928 | H19: 1017 | I19: 8 | J19: 20 | K19: 1017 | L19: 60 | M19: 957 | N19: 0 | O19: 0 | P19: 957 | Q19: 1.0959052 | R19: 937 | S19: 937 | T19: 0 | U19: 3.1465093 | V19: New | W19: BAZIC Products | Y19: USD | Z19: 5.69 | AA19: 181.56 | AB19: 34 | AC19: 97 | AD19: 96 | AE19: 0 | AF19: 0 | AG19: 0 | AH19: 1 | AI19: 1 | AJ19: 48 | AK19: 48 | AL19: 0 | AM19: Amazon | AN19: 94 | AO19: 51 | AQ19: 0 | AR19: none | AS19: No action required | AT19: 0.036 ft3
A20: US | B20: BAZIC Products 3 Ring Binder 1/2" Economy View Binders Organizer - Purple, Round Ring, Hold 100 Sheets Paper, for School Office Home, 1-Count | C20: FBA_4107-EACH | D20: B07Q84RJLP | E20: X003L8W44J | F20: 104 | G20: 791 | H20: 889 | I20: 29 | J20: 72.5 | K20: 889 | L20: 31.5 | M20: 857.5 | N20: 0 | O20: 0 | P20: 857.5 | Q20: 1.1238938 | R20: 785 | S20: 785 | T20: 0 | U20: 4.6794151 | V20: New | W20: BAZIC Products | Y20: USD | Z20: 9.09 | AA20: 74.1 | AB20: 10 | AC20: 159 | AD20: 156 | AE20: 0 | AF20: 0 | AG20: 2 | AH20: 1 | AI20: 0 | AJ20: 60 | AK20: 96 | AL20: 0 | AM20: Amazon | AN20: 63 | AO20: 43 | AQ20: 36 | AR20: 46055 | AS20: Create shipping plan | AT20: 0.049 ft3
A21: US | B21: BAZIC Products 2 Pocket Paper Folder, Letter Size Document Organizer for School, Office, Business Use, Camouflage Design Portfolio Folder for Homework, Reports & Forms, Assorted Colors, 6 Pack | C21: FBA_2170-SET6 | D21: B07S165T2T | E21: X003SBSK1F | F21: 27 | G21: 607 | H21: 812 | I21: 19 | J21: 47.5 | K21: 812 | L21: 0 | M21: 812 | N21: 0 | O21: 0 | P21: 812 | Q21: 1.3377265 | R21: 785 | S21: 785 | T21: 0 | U21: 1.3300493 | V21: New | W21: BAZIC Products | Y21: USD | Z21: 11.39 | AA21: 113.9 | AB21: 10 | AC21: 22 | AD21: 16 | AE21: 3 | AF21: 1 | AG21: 1 | AH21: 1 | AI21: 0 | AJ21: 0 | AK21: 16 | AL21: 0 | AM21: Amazon | AN21: 51 | AO21: 46 | AQ21: 8 | AR21: 46055 | AS21: Create shipping plan | AT21: 0.0737 ft3
A22: US | B22: BAZIC Products Open Closed Signs for Business, Double-sided Vinyl Open Signs for Business Window With Will Return Clock Sign, Be Back Sign With Clock, Ideal for Businesses, Shop, Office & More, 7.5"X9" 1-pack | C22: FBA_4398-EACH | D22: B07SFKBQ7F | E22: X003GYE2EX | F22: 288 | G22: 943 | H22: 618 | I22: 35 | J22: 87.5 | K22: 943 | L22: 200.5 | M22: 742.5 | N22: 0 | O22: 0 | P22: 742.5 | Q22: 0.65535525 | R22: 655 | S22: 655 | T22: 0 | U22: 12.216331 | V22: New | W22: BAZIC Products | Y22: USD | Z22: 4.79 | AA22: 73.73 | AB22: 17 | AC22: 291 | AD22: 291 | AE22: 0 | AF22: 0 | AG22: 0 | AH22: 0 | AI22: 0 | AJ22: 288 | AK22: 0 | AL22: 3 | AM22: Amazon | AN22: 365+ | AO22: 8 | AP22: low_stock | AQ22: 0 | AR22: none | AS22: No action required | AT22: 0.0078 ft3 | AU22: 0.037115589
A23: US | B23: BAZIC Products Blank Paper Copy & Multipurpose Paper 8.5" x 11" – 25 Sheets Pastel Color Printer Paper for Inkjet, Laser, and Fax Machines – Printing Paper for Office, School, and Crafts, 2-Packs | C23: FBA_5190-PACK2 | D23: B0BCL7XWNT | E23: X003SFUYF1 | F23: 22 | G23: 645 | H23: 704 | I23: 26 | J23: 65 | K23: 704 | L23: 0 | M23: 704 | N23: 0 | O23: 0 | P23: 704 | Q23: 1.0914729 | R23: 682 | S23: 682 | T23: 0 | U23: 1.25 | V23: New | W23: BAZIC Products | Y23: USD | Z23: 6.49 | AA23: 58.41 | AB23: 9 | AC23: 70 | AD23: 0 | AE23: 70 | AF23: 0 | AG23: 0 | AH23: 0 | AI23: 1 | AJ23: 0 | AK23: 0 | AL23: 0 | AM23: Amazon | AN23: 161 | AO23: 161 | AQ23: 0 | AR23: none | AS23: No action required | AT23: 0.0416 ft3
A24: US | B24: BAZIC Products Book Wrap - Clear Book Cover Self Adhesive Book Protector for Book Covers for Paperbacks, Plastic Cover for Books, Clear Contact Paper Peel and Stick, 17.5" x 1.7 Yard Roll, 1-Roll | C24: FBA_2901-EACH | D24: B076F13SG5 | E24: B076F13SG5 | F24: 629 | G24: 2487 | H24: 797 | I24: 70 | J24: 175 | K24: 1118 | L24: 454 | M24: 664 | N24: 0 | O24: 0 | P24: 664 | Q24: 0.32046643 | R24: 489 | S24: 489 | T24: 0 | U24: 22.504472 | V24: New | W24: BAZIC Products | Y24: USD | Z24: 5.4 | AA24: 1341.54 | AB24: 286 | AC24: 764 | AD24: 720 | AE24: 0 | AF24: 10 | AG24: 22 | AH24: 12 | AI24: 1 | AJ24: 384 | AK24: 336 | AL24: 0 | AM24: Amazon | AN24: 93 | AO24: 41 | AQ24: 0 | AR24: none | AS24: No action required | AT24: 0.0161 ft3 | AU24: 0.062611807
A25: US | B25: BAZIC Products Black Rubber Bands – Assorted Sizes, Heavy Duty Elastic Bands For Money, Office, School, Home Organization, Crafts, Durable Stretch Rubber Bands, 2 Oz (56.7 g), 1-Pack | C25: FBA_6120-EACH | D25: B09DJVP3DS | E25: B09DJVP3DS | F25: 440 | G25: 679 | H25: 4 | I25: 253 | J25: 632.5 | K25: 679 | L25: 0 | M25: 679 | N25: 36 | O25: 36 | P25: 643 | Q25: 0.0058910162 | R25: 239 | S25: 203 | T25: 36 | U25: 25.920471 | V25: New | W25: BAZIC Products | Y25: USD | Z25: 4.89 | AA25: 1090.47 | AB25: 223 | AC25: 311 | AD25: 72 | AE25: 232 | AF25: 3 | AG25: 2 | AH25: 2 | AI25: 1 | AJ25: 0 | AK25: 72 | AL25: 0 | AM25: Amazon | AN25: 53 | AO25: 52 | AQ25: 36 | AR25: 46055 | AS25: Create shipping plan | AT25: 0.0187 ft3 | AU25: 0.37260677
A26: US | B26: BAZIC Products Pink Eraser Top, Latex-Free Pencil Top Erasers with Arrowhead Caps, Non-Toxic Erasers for Kids, Students, Teachers, Classroom, Art, Homework & School Supplies, 20/Pack, 1-Pack | C26: FBA_2206-EACH | D26: B07RPR34BJ | E26: X002GAOOB9 | F26: 149 | G26: 661 | H26: 472 | I26: 49 | J26: 122.5 | K26: 661 | L26: 26.5 | M26: 634.5 | N26: 0 | O26: 0 | P26: 634.5 | Q26: 0.71406959 | R26: 512 | S26: 512 | T26: 0 | U26: 9.0166415 | V26: New | W26: BAZIC Products | Y26: USD | Z26: 3.89 | AA26: 272.22 | AB26: 70 | AC26: 106 | AD26: 48 | AE26: 51 | AF26: 6 | AG26: 0 | AH26: 1 | AI26: 0 | AJ26: 48 | AK26: 0 | AL26: 0 | AM26: Amazon | AN26: 69 | AO26: 42 | AQ26: 0 | AR26: none | AS26: No action required | AT26: 0.009 ft3 | AU26: 0.074130106
A27: US | B27: BAZIC Products Neon Highlighter – Yellow Pen Style, Chisel Tip Broad Fine Line, Desk Style Highlighter Pen for Office, School, and Study Use, Fluorescent Yellow Ink, Smooth Marking, 5/Pack, 1-Pack | C27: FBA_2300-EACH | D27: B07QXVJFTP | E27: X0044R3N1J | F27: 95 | G27: 458 | H27: 683 | I27: 13 | J27: 32.5 | K27: 683 | L27: 62.5 | M27: 620.5 | N27: 0 | O27: 0 | P27: 620.5 | Q27: 1.4912664 | R27: 588 | S27: 588 | T27: 0 | U27: 5.5636896 | V27: New | W27: BAZIC Products | Y27: USD | Z27: 4.79 | AA27: 219.79 | AB27: 46 | AC27: 53 | AD27: 48 | AE27: 5 | AF27: 0 | AG27: 0 | AH27: 0 | AI27: 0 | AJ27: 48 | AK27: 0 | AL27: 0 | AM27: Amazon | AN27: 45 | AO27: 4 | AP27: low_stock | AQ27: 48 | AR27: 46055 | AS27: Create shipping plan | AT27: 0.0093 ft3
A28: US | B28: BAZIC Products Glitter Glue Tube – 6 Assorted Classic Color, Non-Toxic Washable Glitter Glue for Art, Crafts, Paints, DIY, and Party Projects, 120ml/Pack, 1-Pack | C28: FBA_3467-EACH-1 | D28: B01HTYG3LE | E28: B01HTYG3LE | F28: 1072 | G28: 852 | H28: 281 | I28: 335 | J28: 837.5 | K28: 852 | L28: 234.5 | M28: 617.5 | N28: 0 | O28: 0 | P28: 617.5 | Q28: 0.32981221 | R28: 0 | S28: 0 | T28: 0 | U28: 50.328638 | V28: New | W28: BAZIC Products | Y28: USD | Z28: 6.23 | AA28: 443.89 | AB28: 62 | AC28: 1430 | AD28: 2 | AE28: 1267 | AF28: 35 | AG28: 120 | AH28: 6 | AI28: 2 | AJ28: 0 | AK28: 0 | AL28: 2 | AM28: Amazon | AN28: 308 | AO28: 302 | AQ28: 0 | AR28: none | AS28: No action required | AT28: 0.0131 ft3 | AU28: 0.39319249
A29: US | B29: BAZIC Ballpoint Pen Spencer Red Retractable Pen Soft Barrel Grip Pens, 1.0 mm Bold Point Smooth Writing, for Office School Teacher (5/Pack), 1-Pack | C29: FBA_17049-EACH | D29: B00FBOMTA4 | E29: B00FBOMTA4 | F29: 445 | G29: 774 | H29: 1037 | I29: 7 | J29: 17.5 | K29: 1037 | L29: 427.5 | M29: 609.5 | N29: 0 | O29: 0 | P29: 609.5 | Q29: 1.3397933 | R29: 592 | S29: 592 | T29: 0 | U29: 17.164899 | V29: New | W29: BAZIC Products | Y29: USD | Z29: 5.59 | AA29: 915.66 | AB29: 235 | AC29: 454 | AD29: 432 | AE29: 0 | AF29: 1 | AG29: 14 | AH29: 7 | AI29: 2 | AJ29: 432 | AK29: 0 | AL29: 0 | AM29: Amazon | AN29: 147 | AO29: 0 | AP29: low_stock | AQ29: 0 | AR29: none | AS29: No action required | AT29: 0.0072 ft3
A30: US | B30: BAZIC Products 8 Pocket Folder Portfolio, Double Loop Wire Binding, Letter Size Paper Organizer for Office, School, Business, Presentations, Projects & Document Storage, 1-Pack | C30: FBA_3161-EACH | D30: B08FK78Z2B | E30: X003BXWZTX | F30: 70 | G30: 449 | H30: 609 | I30: 24 | J30: 60 | K30: 609 | L30: 10 | M30: 599 | N30: 0 | O30: 0 | P30: 599 | Q30: 1.3563474 | R30: 539 | S30: 539 | T30: 0 | U30: 4.5977011 | V30: New | W30: BAZIC Products | Y30: USD | Z30: 8.09 | AA30: 244.63 | AB30: 35 | AC30: 28 | AD30: 24 | AE30: 1 | AF30: 0 | AG30: 1 | AH30: 2 | AI30: 1 | AJ30: 24 | AK30: 0 | AL30: 0 | AM30: Amazon | AN30: 23 | AO30: 0 | AP30: low_stock | AQ30: 48 | AR30: 46055 | AS30: Create shipping plan | AT30: 0.0508 ft3
A31: US | B31: BAZIC Products Highlighter – Yellow Color Chisel Tip Highlighter Set, Desk Style Highlighter Pen for Office, School, and Study Use, Fluorescent Yellow Ink, Smooth Marking, 3 Pcs, 1-Pack | C31: FBA_2320-EACH | D31: B075VWXGFL | E31: B075VWXGFL | F31: 29 | G31: 96 | H31: 593 | I31: 3 | J31: 7.5 | K31: 593 | L31: 21.5 | M31: 571.5 | N31: 0 | O31: 0 | P31: 571.5 | Q31: 6.1770833 | R31: 564 | S31: 564 | T31: 0 | U31: 1.9561551 | V31: New | W31: BAZIC Products | Y31: USD | Z31: 4.83 | AA31: 0 | AB31: 0 | AC31: 48 | AD31: 48 | AE31: 0 | AF31: 0 | AG31: 0 | AH31: 0 | AI31: 0 | AJ31: 24 | AK31: 24 | AL31: 0 | AM31: Amazon | AQ31: 0 | AR31: none | AS31: No action required | AT31: 0.0117 ft3
A32: US | B32: BAZIC Products 3 Ring Binder 1/2" Economy View Binders Organizer - Blue, Round Ring, Hold 175 Sheets Paper, for School Office Home, 1-Count | C32: FBA_3190-EACH | D32: B07Q9PJ727 | E32: X003SBSK1P | F32: 34 | G32: 456 | H32: 563 | I32: 17 | J32: 42.5 | K32: 563 | L32: 0 | M32: 563 | N32: 0 | O32: 0 | P32: 563 | Q32: 1.2346491 | R32: 529 | S32: 529 | T32: 0 | U32: 2.4156306 | V32: New | W32: BAZIC Products | Y32: USD | Z32: 8.48 | AA32: 101.76 | AB32: 12 | AC32: 27 | AD32: 12 | AE32: 14 | AF32: 0 | AG32: 0 | AH32: 1 | AI32: 0 | AJ32: 12 | AK32: 0 | AL32: 0 | AM32: Amazon | AN32: 56 | AO32: 33 | AQ32: 12 | AR32: 46054 | AS32: Create shipping plan | AT32: 0.0805 ft3
A33: US | B33: BAZIC Products Washable Clear School Glue 5 Oz. (147 mL), Liquid Clear Glues Adhesive, for Making Slime Art Crafts at School Home Office, 1-Pack | C33: FBA_2044-EACH | D33: B075VXY8MQ | E33: B075VXY8MQ | F33: 72 | G33: 567 | H33: 342 | I33: 23 | J33: 57.5 | K33: 567 | L33: 14.5 | M33: 552.5 | N33: 0 | O33: 0 | P33: 552.5 | Q33: 0.6031746 | R33: 495 | S33: 495 | T33: 0 | U33: 5.0793651 | V33: New | W33: BAZIC Products | Y33: USD | Z33: 6.3 | AA33: 6.37 | AB33: 1 | AC33: 240 | AD33: 240 | AE33: 0 | AF33: 0 | AG33: 0 | AH33: 0 | AI33: 0 | AJ33: 48 | AK33: 192 | AL33: 0 | AM33: Amazon | AN33: 365+ | AO33: 365+ | AQ33: 0 | AR33: none | AS33: No action required | AT33: 0.0109 ft3 | AU33: 0.040564374
A34: US | B34: BAZIC Products Notebook College Ruled 1 Subject 80 Sheets Wireless Notebooks, Lined Composition Book, Assorted Color, 6-Pack | C34: FBA_581-SET6 | D34: B07S97LHGW | E34: X003L8UNOH | F34: 244 | G34: 537 | H34: 464 | I34: 89 | J34: 222.5 | K34: 537 | L34: 21.5 | M34: 515.5 | N34: 0 | O34: 0 | P34: 515.5 | Q34: 0.86405959 | R34: 293 | S34: 293 | T34: 0 | U34: 18.175047 | V34: New | W34: BAZIC Products | Y34: USD | Z34: 16.89 | AA34: 1560.54 | AB34: 93 | AC34: 93 | AD34: 88 | AE34: 0 | AF34: 0 | AG34: 2 | AH34: 3 | AI34: 0 | AJ34: 76 | AK34: 12 | AL34: 0 | AM34: Amazon | AN34: 41 | AO34: 4 | AP34: low_stock | AQ34: 56 | AR34: 46055 | AS34: Create shipping plan | AT34: 0.0866 ft3
A35: US | B35: BAZIC Products 3 Ring Binder 1/2" Economy View Binders Organizer - Green, Round Ring, Hold 100 Sheets Paper, for School Office Home, 1-Count | C35: FBA_4102-EACH | D35: B07Q8WY4R5 | E35: X003L8UNPL | F35: 117 | G35: 449 | H35: 572 | I35: 16 | J35: 40 | K35: 572 | L35: 77 | M35: 495 | N35: 0 | O35: 0 | P35: 495 | Q35: 1.2739421 | R35: 455 | S35: 455 | T35: 0 | U35: 8.1818182 | V35: New | W35: BAZIC Products | Y35: USD | Z35: 6.99 | AA35: 419.4 | AB35: 60 | AC35: 111 | AD35: 108 | AE35: 1 | AF35: 0 | AG35: 0 | AH35: 2 | AI35: 1 | AJ35: 96 | AK35: 12 | AL35: 0 | AM35: Amazon | AN35: 46 | AO35: 5 | AP35: low_stock | AQ35: 84 | AR35: 46055 | AS35: Create shipping plan | AT35: 0.0818 ft3
A36: US | B36: BAZIC Products Blank Paper Copy & Multipurpose Paper 8.5" x 11" – 25 Sheets Pastel Color Printer Paper for Inkjet, Laser, and Fax Machines – Printing Paper for Office, School, and Crafts, 1-Pack | C36: FBA_5190-EACH | D36: B0BCMBR7L9 | E36: B0BCMBR7L9 | F36: 124 | G36: 325 | H36: 514 | I36: 41 | J36: 102.5 | K36: 514 | L36: 21.5 | M36: 492.5 | N36: 0 | O36: 0 | P36: 492.5 | Q36: 1.5815385 | R36: 390 | S36: 390 | T36: 0 | U36: 9.6498054 | V36: New | W36: BAZIC Products | Y36: USD | Z36: 5.15 | AA36: 267.6 | AB36: 61 | AC36: 9 | AD36: 0 | AE36: 0 | AF36: 0 | AG36: 3 | AH36: 6 | AI36: 0 | AJ36: 0 | AK36: 0 | AL36: 0 | AM36: Amazon | AN36: 2 | AO36: 0 | AP36: out_of_stock | AQ36: 168 | AR36: 46048 | AS36: Create shipping plan | AT36: 0.0159 ft3
A37: US | B37: BAZIC Products Blank Paper Copy & Multipurpose Paper - 8.5" x 11" Pastel Color Printer Paper for Inkjet, Laser, and Fax Machines, Ideal for Office, School, and Crafts, 100 Sheets/Pack, 1-Pack | C37: FBA_5191-EACH | D37: B0BCL6MSMS | E37: B0BCL6MSMS | F37: 55 | G37: 309 | H37: 536 | I37: 2 | J37: 5 | K37: 536 | L37: 50 | M37: 486 | N37: 0 | O37: 0 | P37: 486 | Q37: 1.7346278 | R37: 481 | S37: 481 | T37: 0 | U37: 4.1044776 | V37: New | W37: BAZIC Products | Y37: USD | Z37: 8.6 | AA37: 261.56 | AB37: 35 | AC37: 48 | AD37: 48 | AE37: 0 | AF37: 0 | AG37: 0 | AH37: 0 | AI37: 0 | AJ37: 48 | AK37: 0 | AL37: 0 | AM37: Amazon | AN37: 72 | AO37: 0 | AP37: out_of_stock | AQ37: 24 | AR37: 46053 | AS37: Create shipping plan | AT37: 0.0371 ft3
A38: US | B38: BAZIC Products 3 Ring Binder 1" Economy View Binders Organizer - Pastel Color, Round Ring, Hold 175 Sheets Paper, for School Office Home, 4-Count | C38: FBA_3167-SET4 | D38: B08LP2FGJM | E38: X003BVZHKJ | F38: 463 | G38: 926 | H38: 693 | I38: 8 | J38: 20 | K38: 926 | L38: 443 | M38: 483 | N38: 0 | O38: 0 | P38: 483 | Q38: 0.74838013 | R38: 463 | S38: 463 | T38: 0 | U38: 20 | V38: New | W38: BAZIC Products | Y38: USD | Z38: 19.85 | AA38: 119.1 | AB38: 6 | AC38: 476 | AD38: 0 | AE38: 467 | AF38: 0 | AG38: 9 | AH38: 0 | AI38: 0 | AJ38: 0 | AK38: 0 | AL38: 0 | AM38: Amazon | AN38: 205 | AO38: 205 | AQ38: 0 | AR38: none | AS38: No action required | AT38: 0.2279 ft3 | AU38: 0.0086393089
A39: US | B39: BAZIC Products 3 Ring Binder 1" Economy View Binders Organizer - Purple, Round Ring, Hold 175 Sheets Paper, for School Office Home, 1-Count | C39: FBA_4127-EACH | D39: B07Q8XTMXF | E39: X003SC97MF | F39: 29 | G39: 471 | H39: 389 | I39: 31 | J39: 77.5 | K39: 471 | L39: 0 | M39: 471 | N39: 0 | O39: 0 | P39: 471 | Q39: 0.82590234 | R39: 442 | S39: 442 | T39: 0 | U39: 2.462845 | V39: New | W39: BAZIC Products | Y39: USD | Z39: 9.59 | AA39: 190.79 | AB39: 20 | AC39: 74 | AD39: 0 | AE39: 72 | AF39: 1 | AG39: 0 | AH39: 1 | AI39: 0 | AJ39: 0 | AK39: 0 | AL39: 0 | AM39: Amazon | AN39: 131 | AO39: 129 | AQ39: 0 | AR39: none | AS39: No action required | AT39: 0.1021 ft3
A40: US | B40: BAZIC Products Plastic Pencil Case, Ruler Length Large Utility Storage Box, Multi Purpose Organizer & Supply Holder, Clear Box Design, Ideal for School, Office & Craft Use, 1-Pack | C40: FBA_851-EACH | D40: B093CPW1HK | E40: B093CPW1HK | F40: 0 | G40: 478 | H40: 388 | I40: 3 | J40: 7.5 | K40: 478 | L40: 0 | M40: 478 | N40: 12 | O40: 12 | P40: 466 | Q40: 0.81171548 | R40: 478 | S40: 466 | T40: 12 | U40: 0 | V40: New | W40: BAZIC Products | Y40: USD | Z40: 9.89 | AA40: 126.62 | AB40: 14 | AC40: 1 | AD40: 0 | AE40: 0 | AF40: 0 | AG40: 0 | AH40: 1 | AI40: 0 | AJ40: 0 | AK40: 0 | AL40: 0 | AM40: Amazon | AN40: 2 | AO40: 0 | AP40: out_of_stock | AQ40: 24 | AR40: 46048 | AS40: Create shipping plan | AT40: 0.1189 ft3
A41: US | B41: BAZIC Products Pencil Grip – Assorted Color Soft Gel Pen Grip, Comfort Pencil Grip, Ergonomic Pen Grips for Toddler, Kids and Adults, 8/Pack, 1-Packs | C41: FBA_1502-EACH | D41: B002WFI620 | E41: B002WFI620 | F41: 1438 | G41: 650 | H41: 89 | I41: 496 | J41: 1240 | K41: 650 | L41: 198 | M41: 452 | N41: 0 | O41: 0 | P41: 452 | Q41: 0.13692308 | R41: 0 | S41: 0 | T41: 0 | U41: 88.492308 | V41: New | W41: BAZIC Products | Y41: USD | Z41: 3.59 | AA41: 2179.13 | AB41: 607 | AC41: 434 | AD41: 144 | AE41: 74 | AF41: 173 | AG41: 16 | AH41: 27 | AI41: 2 | AJ41: 144 | AK41: 0 | AL41: 0 | AM41: Amazon | AN41: 21 | AO41: 10 | AP41: low_stock | AQ41: 432 | AR41: 46055 | AS41: Create shipping plan | AT41: 0.0061 ft3 | AU41: 0.76307692
A42: US | B42: BAZIC Composition Book Wide Ruled 100 Sheet Black Marble Notebook, Writing Journal Comp Lined Notebooks for School, 1-Pack | C42: FBA_508-EACH | D42: B001E75OY0 | E42: B001E75OY0 | F42: 220 | G42: 646 | H42: 437 | I42: 7 | J42: 17.5 | K42: 646 | L42: 202.5 | M42: 443.5 | N42: 0 | O42: 0 | P42: 443.5 | Q42: 0.67647059 | R42: 426 | S42: 426 | T42: 0 | U42: 13.622291 | V42: New | W42: BAZIC Products | Y42: USD | Z42: 4.59 | AA42: 96.39 | AB42: 21 | AC42: 224 | AD42: 0 | AE42: 221 | AF42: 1 | AG42: 2 | AH42: 0 | AI42: 0 | AJ42: 0 | AK42: 0 | AL42: 0 | AM42: Amazon | AN42: 165 | AO42: 165 | AQ42: 0 | AR42: none | AS42: No action required | AT42: 0.0216 ft3 | AU42: 0.010835913
A43: US | B43: BAZIC PRODUCTS Receipts Book, Money Cash Rent Receipts for Landlords, Business & Offices, 2-Part Carbonless Forms, 50 Sets 7 1/2" x 2 3/4", White with Bound Wraparound Cover (50 Sets/Pack), 1-Pack | C43: FBA_5074-EACH | D43: B00IIN3K5I | E43: B00IIN3K5I | F43: 288 | G43: 284 | H43: 0 | I43: 425 | J43: 1062.5 | K43: 425 | L43: 0 | M43: 425 | N43: 0 | O43: 0 | P43: 425 | Q43: 0 | R43: 137 | S43: 137 | T43: 0 | U43: 27.105882 | V43: New | W43: BAZIC Products | Y43: USD | Z43: 4 | AA43: 424.5 | AB43: 101 | AC43: 502 | AD43: 0 | AE43: 441 | AF43: 41 | AG43: 19 | AH43: 1 | AI43: 0 | AJ43: 0 | AK43: 0 | AL43: 0 | AM43: Amazon | AN43: 108 | AO43: 105 | AQ43: 0 | AR43: none | AS43: No action required | AT43: 0.0046 ft3 | AU43: 1
A44: US | B44: BAZIC PRODUCTS Spiral Notebook, Composition Book, 5" x 7" Poly Cover Spiral Notebook, College Ruled 100 Sheet Notebook for School, Office, & Home Use, Assorted Color, 6-Pack | C44: FBA_5476-SET6 | D44: B0964KDHSP | E44: X003ENT3U9 | F44: 183 | G44: 407 | H44: 112 | I44: 241 | J44: 602.5 | K44: 407 | L44: 0 | M44: 407 | N44: 0 | O44: 0 | P44: 407 | Q44: 0.27518428 | R44: 224 | S44: 224 | T44: 0 | U44: 17.985258 | V44: New | W44: BAZIC Products | Y44: USD | Z44: 15.99 | AA44: 669.57 | AB44: 42 | AC44: 420 | AD44: 413 | AE44: 0 | AF44: 0 | AG44: 7 | AH44: 0 | AI44: 1 | AJ44: 168 | AK44: 240 | AL44: 5 | AM44: Amazon | AN44: 365+ | AO44: 214 | AQ44: 0 | AR44: none | AS44: No action required | AT44: 0.0565 ft3 | AU44: 0.59213759
A45: US | B45: BAZIC PRODUCTS Plastic Pencil Case, Ruler Length Utility Storage Box, Multi Purpose Organizer & Supply Holder, Transparent Box Design, Assorted Color, Ideal for School, Office & Craft Use, 4-Pack | C45: FBA_841-SET4 | D45: B07RBC11NP | E45: X003SC38J3 | F45: 30 | G45: 469 | H45: 295 | I45: 19 | J45: 47.5 | K45: 469 | L45: 0 | M45: 469 | N45: 72 | O45: 72 | P45: 397 | Q45: 0.62899787 | R45: 439 | S45: 367 | T45: 72 | U45: 2.5586354 | V45: New | W45: BAZIC Products | Y45: USD | Z45: 15.89 | AA45: 258.1 | AB45: 17 | AC45: 54 | AD45: 0 | AE45: 41 | AF45: 12 | AG45: 1 | AH45: 0 | AI45: 0 | AJ45: 0 | AK45: 0 | AL45: 0 | AM45: Amazon | AN45: 95 | AO45: 94 | AQ45: 0 | AR45: none | AS45: No action required | AT45: 0.3111 ft3 | AU45: 0.040511727
A46: US | B46: BAZIC Products 3 Ring Binder, Clear View Soft Cover Notebook, Durable Poly Organizer for School & Office Use, 0.5 in Capacity Holds 100 Sheets, Assorted Colors, 6-Pack | C46: FBA_3130-SET6 | D46: B07QC4LBSK | E46: X003L8Z45Z | F46: 258 | G46: 501 | H46: 305 | I46: 59 | J46: 147.5 | K46: 501 | L46: 110.5 | M46: 390.5 | N46: 0 | O46: 0 | P46: 390.5 | Q46: 0.60878244 | R46: 243 | S46: 243 | T46: 0 | U46: 20.598802 | V46: New | W46: BAZIC Products | Y46: USD | Z46: 21.59 | AA46: 2790.22 | AB46: 129 | AC46: 109 | AD46: 72 | AE46: 20 | AF46: 10 | AG46: 3 | AH46: 4 | AI46: 0 | AJ46: 72 | AK46: 0 | AL46: 0 | AM46: Amazon | AN46: 30 | AO46: 8 | AP46: low_stock | AQ46: 112 | AR46: 46055 | AS46: Create shipping plan | AT46: 0.1335 ft3 | AU46: 0.11776447
A47: US | B47: BAZIC Products Letter Stencil Set – Alphabet, Number and Signs Kit, Reusable for Painting, Fabric, and Crafts, Plastic Stencils in Sizes 8, 10, 20, and 30 mm, 4/Pack, 1-Pack | C47: FBA_302-EACH | D47: B00CDB9FSW | E47: B00CDB9FSW | F47: 110 | G47: 382 | H47: 225 | I47: 105 | J47: 262.5 | K47: 382 | L47: 0 | M47: 382 | N47: 0 | O47: 0 | P47: 382 | Q47: 0.58900524 | R47: 272 | S47: 272 | T47: 0 | U47: 11.518325 | V47: New | W47: BAZIC Products | Y47: USD | Z47: 4.89 | AA47: 293.58 | AB47: 60 | AC47: 243 | AD47: 242 | AE47: 0 | AF47: 0 | AG47: 1 | AH47: 0 | AI47: 1 | AJ47: 96 | AK47: 144 | AL47: 2 | AM47: Amazon | AN47: 115 | AO47: 68 | AQ47: 0 | AR47: none | AS47: No action required | AT47: 0.0405 ft3 | AU47: 0.27486911
A48: US | B48: BAZIC Products 3 Ring Binder 1/2" Economy View Binders Organizer - Cyan, Round Ring, Hold 100 Sheets Paper, for School Office Home, 1-Count | C48: FBA_4105-EACH | D48: B07Q712K7L | E48: X003SC97JN | F48: 60 | G48: 301 | H48: 409 | I48: 9 | J48: 22.5 | K48: 409 | L48: 37.5 | M48: 371.5 | N48: 0 | O48: 0 | P48: 371.5 | Q48: 1.358804 | R48: 349 | S48: 349 | T48: 0 | U48: 5.8679707 | V48: New | W48: BAZIC Products | Y48: USD | Z48: 9.09 | AA48: 243.36 | AB48: 31 | AC48: 48 | AD48: 48 | AE48: 0 | AF48: 0 | AG48: 0 | AH48: 0 | AI48: 2 | AJ48: 48 | AK48: 0 | AL48: 0 | AM48: Amazon | AN48: 46 | AO48: 0 | AP48: out_of_stock | AQ48: 36 | AR48: 46053 | AS48: Create shipping plan | AT48: 0.0737 ft3
A49: US | B49: BAZIC Products 3 Ring Binder 1" Economy View Binders Organizer - Fuchsia, Round Ring, Hold 175 Sheets Paper, for School Office Home, 1-Count | C49: FBA_4126-EACH | D49: B07Q4RD2W3 | E49: X003SC1YAX | F49: 43 | G49: 340 | H49: 394 | I49: 6 | J49: 15 | K49: 394 | L49: 28 | M49: 366 | N49: 0 | O49: 0 | P49: 366 | Q49: 1.1588235 | R49: 351 | S49: 351 | T49: 0 | U49: 4.3654822 | V49: New | W49: BAZIC Products | Y49: USD | Z49: 10.49 | AA49: 171.77 | AB49: 19 | AC49: 24 | AD49: 24 | AE49: 0 | AF49: 0 | AG49: 0 | AH49: 0 | AI49: 0 | AJ49: 12 | AK49: 12 | AL49: 0 | AM49: Amazon | AN49: 46 | AO49: 26 | AQ49: 24 | AR49: 46053 | AS49: Create shipping plan | AT49: 0.1005 ft3
A50: US | B50: BAZIC Products Date Stamper with Black Ink Pads for Stamping, 12 Years of Adjustable Dates, Ideal for Office, Shipping, Receiving, Accounting, Expiration Date Stamp, Due Dates - 1 Pack | C50: FBA_6301-EACH | D50: B08P3W6YN6 | E50: B08P3W6YN6 | F50: 867 | G50: 1195 | H50: 1060 | I50: 15 | J50: 37.5 | K50: 1195 | L50: 829.5 | M50: 365.5 | N50: 0 | O50: 0 | P50: 365.5 | Q50: 0.88702929 | R50: 328 | S50: 328 | T50: 0 | U50: 29.020921 | V50: New | W50: BAZIC Products | Y50: USD | Z50: 6.34 | AA50: 698.64 | AB50: 134 | AC50: 869 | AD50: 869 | AE50: 0 | AF50: 0 | AG50: 0 | AH50: 0 | AI50: 0 | AJ50: 864 | AK50: 0 | AL50: 5 | AM50: Amazon | AN50: 365+ | AO50: 2 | AP50: low_stock | AQ50: 0 | AR50: none | AS50: No action required | AT50: 0.0138 ft3
A51: US | B51: BAZIC Products 3 Ring Binder 1/2" Economy View Binders Organizer - Red, Round Ring, Hold 100 Sheets Paper, for School Office Home, 1-Count | C51: FBA_4103-EACH | D51: B07Q8ZFP5P | E51: X003SC97WP | F51: 185 | G51: 716 | H51: 288 | I51: 90 | J51: 225 | K51: 364.66667 | L51: 0 | M51: 364.66667 | N51: 0 | O51: 0 | P51: 364.66667 | Q51: 0.40223464 | R51: 179.66667 | S51: 179.66667 | T51: 0 | U51: 20.292505 | V51: New | W51: BAZIC Products | Y51: USD | Z51: 8.59 | AA51: 449.06 | AB51: 53 | AC51: 278 | AD51: 0 | AE51: 264 | AF51: 0 | AG51: 14 | AH51: 0 | AI51: 0 | AJ51: 0 | AK51: 0 | AL51: 0 | AM51: Amazon | AN51: 183 | AO51: 181 | AQ51: 0 | AR51: none | AS51: No action required | AT51: 0.0828 ft3 | AU51: 0.24680073
A52: US | B52: BAZIC Products Wooden Ruler 12" (30cm), Singel Metal Edge, Inches Centimeter Metric Measuring Drafting Rulers, for Students School Supplies (3/Pack), 2-Packs | C52: FBA_306-PACK2 | D52: B07S9118WX | E52: X0044RLTFB | F52: 86 | G52: 360 | H52: 203 | I52: 58 | J52: 145 | K52: 360 | L52: 0 | M52: 360 | N52: 0 | O52: 0 | P52: 360 | Q52: 0.56388889 | R52: 274 | S52: 274 | T52: 0 | U52: 9.5555556 | V52: New | W52: BAZIC Products | Y52: USD | Z52: 5.69 | AA52: 115.6 | AB52: 20 | AC52: 174 | AD52: 0 | AE52: 170 | AF52: 3 | AG52: 0 | AH52: 1 | AI52: 0 | AJ52: 0 | AK52: 0 | AL52: 0 | AM52: Amazon | AN52: 172 | AO52: 171 | AQ52: 0 | AR52: none | AS52: No action required | AT52: 0.0205 ft3 | AU52: 0.16111111
A53: US | B53: BAZIC Products Eraser Set – Premium Pink Erasers and Cap Erasers for Clean Corrections; Ideal for School, Office, Artists, Writing, Sketching, and Drawing, 15/Pack, 2-Packs | C53: FBA_2233-PACK2 | D53: B09BBRDFT8 | E53: X0042U86B5 | F53: 12 | G53: 915 | H53: 173 | I53: 0 | J53: 0 | K53: 362.66667 | L53: 12 | M53: 350.66667 | N53: 0 | O53: 0 | P53: 350.66667 | Q53: 0.18907104 | R53: 350.66667 | S53: 350.66667 | T53: 0 | U53: 1.3235294 | V53: New | W53: BAZIC Products | Y53: USD | Z53: 6.29 | AA53: 0 | AB53: 0 | AC53: 12 | AD53: 0 | AE53: 12 | AF53: 0 | AG53: 0 | AH53: 0 | AI53: 0 | AJ53: 0 | AK53: 0 | AL53: 0 | AM53: Amazon | AN53: 152 | AO53: 152 | AQ53: 0 | AR53: none | AS53: No action required | AT53: 0.02 ft3 | AU53: 0
A54: US | B54: BAZIC Products Key Tag Label Window, Assorted Color Tags, Plastic Key Holder Key Ring, Identifier Name Number Address Information Label Card (6/Pack), 1-Pack | C54: FBA_4004-EACH | D54: B07S2TFVRK | E54: B07S2TFVRK | F54: 302 | G54: 327 | H54: 5 | I54: 157 | J54: 392.5 | K54: 327 | L54: 0 | M54: 327 | N54: 0 | O54: 0 | P54: 327 | Q54: 0.01529052 | R54: 25 | S54: 25 | T54: 0 | U54: 36.941896 | V54: New | W54: BAZIC Products | Y54: USD | Z54: 3.89 | AA54: 503.09 | AB54: 121 | AC54: 274 | AD54: 0 | AE54: 258 | AF54: 1 | AG54: 8 | AH54: 7 | AI54: 1 | AJ54: 0 | AK54: 0 | AL54: 0 | AM54: Amazon | AN54: 57 | AO54: 54 | AQ54: 72 | AR54: 46055 | AS54: Create shipping plan | AT54: 0.0113 ft3 | AU54: 0.48012232
A55: US | B55: BAZIC Products 3 Ring Binder 1" Economy View Binders Organizer - Grey, Round Ring, Hold 175 Sheets Paper, for School Office Home, 1-Count | C55: FBA_4121-EACH | D55: B07Q713Y6M | E55: X003SBSJAR | F55: 41 | G55: 259 | H55: 307 | I55: 19 | J55: 47.5 | K55: 307 | L55: 0 | M55: 307 | N55: 0 | O55: 0 | P55: 307 | Q55: 1.1853282 | R55: 266 | S55: 266 | T55: 0 | U55: 5.3420195 | V55: New | W55: BAZIC Products | Y55: USD | Z55: 10.49 | AA55: 198.25 | AB55: 19 | AC55: 15 | AD55: 0 | AE55: 15 | AF55: 0 | AG55: 0 | AH55: 0 | AI55: 1 | AJ55: 0 | AK55: 0 | AL55: 0 | AM55: Amazon | AN55: 22 | AO55: 22 | AQ55: 24 | AR55: 46053 | AS55: Create shipping plan | AT55: 0.1078 ft3
A56: US | B56: BAZIC Products Mini Ballpoint Pen, 1.0 mm Bold Point, Black Ink, Smooth Writing Mini Pens with Compact and Key Chain Design, Ideal for Travel, Badge Reel, and Everyday Carry, 5/Pack, 1-Pack | C56: FBA_1753-EACH | D56: B003BLQHFM | E56: B003BLQHFM | F56: 458 | G56: 468 | H56: 296 | I56: 117 | J56: 292.5 | K56: 468 | L56: 165.5 | M56: 302.5 | N56: 0 | O56: 0 | P56: 302.5 | Q56: 0.63247863 | R56: 10 | S56: 10 | T56: 0 | U56: 39.145299 | V56: New | W56: BAZIC Products | Y56: USD | Z56: 4.85 | AA56: 512.89 | AB56: 118 | AC56: 577 | AD56: 577 | AE56: 0 | AF56: 0 | AG56: 0 | AH56: 0 | AI56: 0 | AJ56: 0 | AK56: 576 | AL56: 1 | AM56: Amazon | AN56: 186 | AO56: 186 | AQ56: 0 | AR56: none | AS56: No action required | AT56: 0.0067 ft3 | AU56: 0.25
A57: US | B57: BAZIC Products Two Pockets Paper Portfolio, 3 Metal Fastener Clips Folder, Letter Size Folders for Office Document Papers Organizer, Assorted Color, 10-Count | C57: FBA_3145-SET10 | D57: B0BS2CSG4Q | E57: X003YW88L5 | F57: 22 | G57: 596 | H57: 290 | I57: 12 | J57: 30 | K57: 299.33333 | L57: 0 | M57: 299.33333 | N57: 0 | O57: 0 | P57: 299.33333 | Q57: 0.48657718 | R57: 277.33333 | S57: 277.33333 | T57: 0 | U57: 2.9398664 | V57: New | W57: BAZIC Products | Y57: USD | Z57: 11.14 | AA57: 144.82 | AB57: 13 | AC57: 20 | AD57: 10 | AE57: 9 | AF57: 0 | AG57: 0 | AH57: 1 | AI57: 0 | AJ57: 0 | AK57: 10 | AL57: 0 | AM57: Amazon | AN57: 38 | AO57: 37 | AQ57: 100 | AR57: 46055 | AS57: Create shipping plan | AT57: 0.086 ft3 | AU57: 0.040089087
A58: US | B58: BAZIC Ruled Index Cards 3" X 5" 100 Count, White Flashcards, Ruled Lined Card for Learning Memory Reminder (100/Pack), 1-Pack | C58: FBA_516-EACH | D58: B0019IMFSW | E58: B0019IMFSW | F58: 194 | G58: 523 | H58: 292 | I58: 16 | J58: 40 | K58: 523 | L58: 154 | M58: 369 | N58: 72 | O58: 72 | P58: 297 | Q58: 0.5583174 | R58: 329 | S58: 257 | T58: 72 | U58: 14.837476 | V58: New | W58: BAZIC Products | Y58: USD | Z58: 5.09 | AA58: 0 | AB58: 0 | AC58: 210 | AD58: 0 | AE58: 210 | AF58: 0 | AG58: 0 | AH58: 0 | AI58: 0 | AJ58: 0 | AK58: 0 | AL58: 0 | AM58: Amazon | AQ58: 0 | AR58: none | AS58: No action required | AT58: 0.008 ft3 | AU58: 0.030592734
A59: US | B59: BAZIC Products Composition Book Wide Ruled 100 Sheet, Premium Black Marble Notebook, Writing Journal Comp Lined Notebooks for Office School, 1-Pack | C59: FBA_5090-EACH | D59: B00Z3BPRRW | E59: B00Z3BPRRW | F59: 97 | G59: 60 | H59: 326 | I59: 27 | J59: 67.5 | K59: 326 | L59: 29.5 | M59: 296.5 | N59: 0 | O59: 0 | P59: 296.5 | Q59: 5.4333333 | R59: 229 | S59: 229 | T59: 0 | U59: 11.90184 | V59: New | W59: BAZIC Products | Y59: USD | Z59: 4.79 | AA59: 196.39 | AB59: 41 | AC59: 6 | AD59: 0 | AE59: 5 | AF59: 1 | AG59: 0 | AH59: 0 | AI59: 0 | AJ59: 0 | AK59: 0 | AL59: 0 | AM59: Amazon | AN59: 4 | AO59: 4 | AP59: low_stock | AQ59: 96 | AR59: 46054 | AS59: Create shipping plan | AT59: 0.0162 ft3
A60: US | B60: BAZIC Products Slider Pencil Case, Utility Storage Box Snap Closure, Bright Color Multi Purpose Organizer, 6-Pack | C60: FBA_812-SET6 | D60: B07RCM1LXW | E60: X0042UE50L | F60: 1 | G60: 293 | H60: 229 | I60: 49 | J60: 122.5 | K60: 293 | L60: 0 | M60: 293 | N60: 0 | O60: 0 | P60: 293 | Q60: 0.78156997 | R60: 292 | S60: 292 | T60: 0 | U60: 0.13651877 | V60: New | W60: BAZIC Products | Y60: USD | Z60: 12.99 | AA60: 524.65 | AB60: 41 | AC60: 46 | AD60: 0 | AE60: 46 | AF60: 0 | AG60: 0 | AH60: 0 | AI60: 0 | AJ60: 0 | AK60: 0 | AL60: 0 | AM60: Amazon | AN60: 44 | AO60: 44 | AQ60: 18 | AR60: 46055 | AS60: Create shipping plan | AT60: 0.1343 ft3 | AU60: 0.16723549
A61: US | B61: BAZIC Products Tree Free Copy Paper - 8.5 X 11 Made From Sugarcane Fiber, Smooth Printer Paper for Daily Use, Reliable Copy & Printing Paper Ideal for Home, Office and School, 500/Ream | C61: FBA_41166-EACH-1 | D61: B09MDRGNCP | E61: B09MDRGNCP | F61: 102 | G61: 288 | H61: 99 | I61: 172 | J61: 430 | K61: 288 | L61: 0 | M61: 288 | N61: 0 | O61: 0 | P61: 288 | Q61: 0.34375 | R61: 186 | S61: 186 | T61: 0 | U61: 14.166667 | V61: New | W61: BAZIC Products | Y61: USD | Z61: 14.39 | AA61: 1715.14 | AB61: 118 | AC61: 220 | AD61: 63 | AE61: 119 | AF61: 18 | AG61: 7 | AH61: 13 | AI61: 8 | AJ61: 0 | AK61: 54 | AL61: 9 | AM61: Amazon | AN61: 51 | AO61: 46 | AQ61: 50 | AR61: 46055 | AS61: Create shipping plan | AT61: 0.1404 ft3 | AU61: 0.59722222
A62: US | B62: BAZIC 1/3 Cut Letter Size Color File Folder (6/Pack) | C62: FBA_3109-EACH | D62: B001GE6ACG | E62: B001GE6ACG | F62: 334 | G62: 284 | H62: 34 | I62: 183 | J62: 457.5 | K62: 284 | L62: 0 | M62: 284 | N62: 0 | O62: 0 | P62: 284 | Q62: 0.11971831 | R62: 0 | S62: 0 | T62: 0 | U62: 47.042254 | V62: New | W62: BAZIC Products | Y62: USD | Z62: 4.19 | AA62: 592.92 | AB62: 138 | AC62: 243 | AD62: 0 | AE62: 182 | AF62: 49 | AG62: 6 | AH62: 6 | AI62: 0 | AJ62: 0 | AK62: 0 | AL62: 0 | AM62: Amazon | AN62: 35 | AO62: 33 | AQ62: 192 | AR62: 46055 | AS62: Create shipping plan | AT62: 0.0283 ft3 | AU62: 0.6443662
A63: US | B63: BAZIC Products 2 Pocket Paper Folder, Letter Size Document Organizer for School, Office, Business Use, Paisley Design Portfolio Folder for Homework, Reports & Forms, Assorted Colors, 6-Pack | C63: FBA_2174-SET6 | D63: B07RWLD5MR | E63: X003SC97SJ | F63: 140 | G63: 269 | H63: 329 | I63: 36 | J63: 90 | K63: 329 | L63: 50 | M63: 279 | N63: 0 | O63: 0 | P63: 279 | Q63: 1.2230483 | R63: 189 | S63: 189 | T63: 0 | U63: 17.021277 | V63: New | W63: BAZIC Products | Y63: USD | Z63: 11.68 | AA63: 724.36 | AB63: 72 | AC63: 67 | AD63: 64 | AE63: 3 | AF63: 0 | AG63: 0 | AH63: 0 | AI63: 0 | AJ63: 64 | AK63: 0 | AL63: 0 | AM63: Amazon | AN63: 43 | AO63: 1 | AP63: low_stock | AQ63: 64 | AR63: 46054 | AS63: Create shipping plan | AT63: 0.0632 ft3
A64: US | B64: BAZIC Products Writing Pad 100 Sheets 6" x 9" – Writing Pad With Durable Lined Note Pads, Smooth Writing Paper, and Easy-tear Paper Pads; Compact Note Pads and Writing Pads for Office, School, or Home, 1-pack | C64: FBA_560-BAZIC | D64: B00YAXRY8O | E64: X004GZ0A3X | F64: 51 | G64: 275 | H64: 53 | I64: 55 | J64: 137.5 | K64: 275 | L64: 0 | M64: 275 | N64: 0 | O64: 0 | P64: 275 | Q64: 0.19272727 | R64: 224 | S64: 224 | T64: 0 | U64: 7.4181818 | V64: New | W64: BAZIC Products | Y64: USD | Z64: 4.57 | AA64: 172.39 | AB64: 35 | AC64: 156 | AD64: 144 | AE64: 0 | AF64: 0 | AG64: 5 | AH64: 7 | AI64: 0 | AJ64: 0 | AK64: 144 | AL64: 0 | AM64: Amazon | AN64: 78 | AO64: 72 | AQ64: 0 | AR64: none | AS64: No action required | AT64: 0.0134 ft3 | AU64: 0.2
A65: US | B65: BAZIC Products Date Stamper with Black Ink Pads for Stamping, 12 Years of Adjustable Dates, Ideal for Office, Shipping, Receiving, Accounting, Expiration Date Stamp, Due Dates - 2 Pack | C65: FBA_6301-PACK2 | D65: B08P3T1TWJ | E65: X0042QSBIR | F65: 257 | G65: 274 | H65: 88 | I65: 102 | J65: 255 | K65: 274 | L65: 2 | M65: 272 | N65: 0 | O65: 0 | P65: 272 | Q65: 0.32116788 | R65: 17 | S65: 17 | T65: 0 | U65: 37.518248 | V65: New | W65: BAZIC Products | Y65: USD | Z65: 7.53 | AA65: 1137.03 | AB65: 151 | AC65: 325 | AD65: 288 | AE65: 31 | AF65: 0 | AG65: 0 | AH65: 6 | AI65: 0 | AJ65: 144 | AK65: 144 | AL65: 0 | AM65: Amazon | AN65: 92 | AO65: 48 | AQ65: 0 | AR65: none | AS65: No action required | AT65: 0.026 ft3 | AU65: 0.37226277
A66: US | B66: BAZIC Products Poster Board, Multi Color Fluorescent, 11" X 14", Poster Board Paper, Colored Paper, Vision Board Poster, Ideal for Crafts, Signs, School Projects, Displays, 5/Pack, 1-Pack | C66: FBA_5027-EACH-1 | D66: B00KO8DHVC | E66: X004HP06TF | F66: 216 | G66: 230 | H66: 1 | I66: 271 | J66: 677.5 | K66: 271 | L66: 0 | M66: 271 | N66: 0 | O66: 0 | P66: 271 | Q66: 0.0043478261 | R66: 55 | S66: 55 | T66: 0 | U66: 31.881919 | V66: New | W66: BAZIC Products | Y66: USD | Z66: 3.99 | AA66: 610.47 | AB66: 153 | AC66: 193 | AD66: 0 | AE66: 98 | AF66: 90 | AG66: 5 | AH66: 0 | AI66: 0 | AJ66: 0 | AK66: 0 | AL66: 0 | AM66: Amazon | AN66: 24 | AO66: 23 | AQ66: 144 | AR66: 46055 | AS66: Create shipping plan | AT66: 0.0142 ft3 | AU66: 1
A67: US | B67: BAZIC PRODUCTS Primary School Supply Kit, 57-count Student Set for Kindergarten and Elementary Students Grades K–6, Complete School Supplies With Fully Organized Supply Box, 1-pack | C67: FBA_8004-CASE | D67: B0BG1Q72N8 | E67: X003XE2X7T | F67: 0 | G67: 268 | H67: 244 | I67: 15 | J67: 37.5 | K67: 268 | L67: 0 | M67: 268 | N67: 0 | O67: 0 | P67: 268 | Q67: 0.91044776 | R67: 268 | S67: 268 | T67: 0 | U67: 0 | V67: New | W67: BAZIC Products | Y67: USD | Z67: 29.99 | AA67: 0 | AB67: 0 | AC67: 0 | AD67: 0 | AE67: 0 | AF67: 0 | AG67: 0 | AH67: 0 | AI67: 0 | AJ67: 0 | AK67: 0 | AL67: 0 | AM67: Amazon | AN67: 0 | AO67: 0 | AP67: out_of_stock | AQ67: 9 | AR67: 46048 | AS67: Create shipping plan | AT67: 0.2964 ft3
A68: US | B68: BAZIC Products Composition Notebook Wide Ruled - 20 Sheets, Manila Color Composition Notebook with Durable Cover, Non-Spiral and Lined Paper for Journaling, School, Home, or Office, 24-Packs | C68: FBA_5096-BOX-1 | D68: B00GKINMJ2 | E68: B00GKINMJ2 | F68: 0 | G68: 523 | H68: 181 | I68: 80 | J68: 200 | K68: 261.33333 | L68: 0 | M68: 261.33333 | N68: 0 | O68: 0 | P68: 261.33333 | Q68: 0.34608031 | R68: 261.33333 | S68: 261.33333 | T68: 0 | U68: 0 | V68: New | W68: BAZIC Products | Y68: USD | Z68: 21.09 | AA68: 0 | AB68: 0 | AC68: 0 | AD68: 0 | AE68: 0 | AF68: 0 | AG68: 0 | AH68: 0 | AI68: 0 | AJ68: 0 | AK68: 0 | AL68: 0 | AM68: Amazon | AP68: out_of_stock | AQ68: 0 | AR68: none | AS68: No action required | AT68: 0.1066 ft3 | AU68: 0.30612245
A69: US | B69: BAZIC Dime Coin Wrappers Rolls, Made in USA, Durable Preformed Paper Coins Tubes (36/Pack), 1-Pack | C69: FBA_5013-EACH | D69: B0019IKY5I | E69: B0019IKY5I | F69: 201 | G69: 267 | H69: 49 | I69: 78 | J69: 195 | K69: 267 | L69: 6 | M69: 261 | N69: 0 | O69: 0 | P69: 261 | Q69: 0.1835206 | R69: 66 | S69: 66 | T69: 0 | U69: 30.11236 | V69: New | W69: BAZIC Products | Y69: USD | Z69: 7.39 | AA69: 739 | AB69: 100 | AC69: 185 | AD69: 150 | AE69: 28 | AF69: 2 | AG69: 0 | AH69: 5 | AI69: 0 | AJ69: 100 | AK69: 50 | AL69: 0 | AM69: Amazon | AN69: 79 | AO69: 32 | AQ69: 0 | AR69: none | AS69: No action required | AT69: 0.1498 ft3 | AU69: 0.29213483
A70: US | B70: BAZIC PRODUCTS Plastic Pencil Case, Ruler Length Utility Storage Box, Multi Purpose Organizer & Supply Holder, Transparent Box Design, Assorted Color, Ideal for School, Office & Craft Use, 4-Pack | C70: FBA_850-SET4 | D70: B07RC8TSKL | E70: X003SCCXSP | F70: 0 | G70: 261 | H70: 246 | I70: 14 | J70: 35 | K70: 261 | L70: 0 | M70: 261 | N70: 0 | O70: 0 | P70: 261 | Q70: 0.94252874 | R70: 261 | S70: 261 | T70: 0 | U70: 0 | V70: New | W70: BAZIC Products | Y70: USD | Z70: 17.99 | AA70: 147.71 | AB70: 8 | AC70: 0 | AD70: 0 | AE70: 0 | AF70: 0 | AG70: 0 | AH70: 0 | AI70: 1 | AJ70: 0 | AK70: 0 | AL70: 0 | AM70: Amazon | AN70: 0 | AO70: 0 | AP70: out_of_stock | AQ70: 45 | AR70: 46048 | AS70: Create shipping plan | AT70: 0.4697 ft3
A71: US | B71: BAZIC Products Blank Paper Copy & Multipurpose Paper - 8.5" x 11" White Color Printer Paper for Inkjet, Laser, and Fax Machines, Ideal for Office, School, and Crafts, 50 Sheets/Pack, 2-Packs | C71: FBA_510-PACK2 | D71: B08FBR7YW1 | E71: X003BT4VIF | F71: 50 | G71: 879 | H71: 45 | I71: 1 | J71: 2.5 | K71: 308.33333 | L71: 47.5 | M71: 260.83333 | N71: 0 | O71: 0 | P71: 260.83333 | Q71: 0.051194539 | R71: 258.33333 | S71: 258.33333 | T71: 0 | U71: 6.4864865 | V71: New | W71: BAZIC Products | Y71: USD | Z71: 7.89 | AA71: 192.47 | AB71: 25 | AC71: 25 | AD71: 25 | AE71: 0 | AF71: 0 | AG71: 0 | AH71: 0 | AI71: 0 | AJ71: 25 | AK71: 0 | AL71: 0 | AM71: Amazon | AN71: 24 | AO71: 0 | AP71: out_of_stock | AQ71: 50 | AR71: 46053 | AS71: Create shipping plan | AT71: 0.0294 ft3 | AU71: 0.0032432432
A72: US | B72: BAZIC #2B Premium Wood Pencil, Blue, 12 Per Pack (760-24P) | C72: FBA_760-EACH-1 | D72: B0019ILQ3M | E72: B0019ILQ3M | F72: 47 | G72: 533 | H72: 212 | I72: 35 | J72: 87.5 | K72: 260 | L72: 0 | M72: 260 | N72: 0 | O72: 0 | P72: 260 | Q72: 0.39774859 | R72: 213 | S72: 213 | T72: 0 | U72: 7.2307692 | V72: New | W72: BAZIC Products | Y72: USD | Z72: 5.19 | AA72: 0 | AB72: 0 | AC72: 144 | AD72: 144 | AE72: 0 | AF72: 0 | AG72: 0 | AH72: 0 | AI72: 0 | AJ72: 0 | AK72: 144 | AL72: 0 | AM72: Amazon | AN72: 365+ | AO72: 365+ | AQ72: 0 | AR72: none | AS72: No action required | AT72: 0.0045 ft3 | AU72: 0.13461538
A73: US | B73: BAZIC Products Mini Highlighter Pen Pastel Color, Chisel Tip Broad Fine Line Highlighters Unscented (5/Pack), 1-Pack | C73: FBA_2309-EACH-B | D73: B0C4VY1LR7 | E73: B0C4VY1LR7 | F73: 80 | G73: 247 | H73: 203 | I73: 34 | J73: 85 | K73: 247 | L73: 0 | M73: 247 | N73: 0 | O73: 0 | P73: 247 | Q73: 0.82186235 | R73: 167 | S73: 167 | T73: 0 | U73: 12.955466 | V73: New | W73: BAZIC Products | Y73: USD | Z73: 4.29 | AA73: 5.07 | AB73: 1 | AC73: 168 | AD73: 168 | AE73: 0 | AF73: 0 | AG73: 0 | AH73: 0 | AI73: 0 | AJ73: 24 | AK73: 144 | AL73: 0 | AM73: Amazon | AN73: 365+ | AO73: 365+ | AQ73: 0 | AR73: none | AS73: No action required | AT73: 0.0069 ft3
A74: US | B74: BAZIC Products Sketch Pad, Spiral Sketchbook for Artists & Students, Drawing Pad with Thick Paper, Sketching & Drawing for Kids, Teens & Adults, 30 Sheets, 9" X 12", 2-Pack | C74: FBA_5044-PACK2 | D74: B08DF5N2RF | E74: X0040DT235 | F74: 45 | G74: 206 | H74: 285 | I74: 1 | J74: 2.5 | K74: 285 | L74: 42.5 | M74: 242.5 | N74: 0 | O74: 0 | P74: 242.5 | Q74: 1.3834951 | R74: 240 | S74: 240 | T74: 0 | U74: 6.3157895 | V74: New | W74: BAZIC Products | Y74: USD | Z74: 9.39 | AA74: 0 | AB74: 0 | AC74: 48 | AD74: 0 | AE74: 48 | AF74: 0 | AG74: 0 | AH74: 0 | AI74: 0 | AJ74: 0 | AK74: 0 | AL74: 0 | AM74: Amazon | AQ74: 0 | AR74: none | AS74: No action required | AT74: 0.1029 ft3
A75: US | B75: BAZIC Products Shatterproof Flexible Curve Ruler 12" (30cm), Inches Centimeter Metric Measuring Drafting Rulers, for Students School Supplies, 6-Pack | C75: FBA_315-SET6 | D75: B07SFD3KHB | E75: X004KT3PH3 | F75: 49 | G75: 161 | H75: 242 | I75: 19 | J75: 47.5 | K75: 242 | L75: 1.5 | M75: 240.5 | N75: 0 | O75: 0 | P75: 240.5 | Q75: 1.5031056 | R75: 193 | S75: 193 | T75: 0 | U75: 8.0991736 | V75: New | W75: BAZIC Products | Y75: USD | Z75: 8.99 | AA75: 215.7 | AB75: 24 | AC75: 41 | AD75: 28 | AE75: 7 | AF75: 1 | AG75: 4 | AH75: 1 | AI75: 0 | AJ75: 12 | AK75: 16 | AL75: 0 | AM75: Amazon | AN75: 39 | AO75: 25 | AQ75: 60 | AR75: 46055 | AS75: Create shipping plan | AT75: 0.0053 ft3
A76: US | B76: BAZIC Products Quarter Coin Wrappers – Durable Preformed Paper Tube, Sleeves for Coin Sorter and Holder, 36/Pack, 2 Packs | C76: FBA_5014-PACK2 | D76: B08DF97S7L | E76: X003SC97RP | F76: 154 | G76: 240 | H76: 157 | I76: 63 | J76: 157.5 | K76: 240 | L76: 0 | M76: 240 | N76: 0 | O76: 0 | P76: 240 | Q76: 0.65416667 | R76: 86 | S76: 86 | T76: 0 | U76: 25.666667 | V76: New | W76: BAZIC Products | Y76: USD | Z76: 10.8 | AA76: 515.8 | AB76: 48 | AC76: 37 | AD76: 0 | AE76: 28 | AF76: 2 | AG76: 1 | AH76: 6 | AI76: 0 | AJ76: 0 | AK76: 0 | AL76: 0 | AM76: Amazon | AN76: 8 | AO76: 7 | AP76: low_stock | AQ76: 264 | AR76: 46055 | AS76: Create shipping plan | AT76: 0.189 ft3 | AU76: 0.2625
A77: US | B77: BAZIC PRODUCTS Metallic Colored Pencils – 12 Shimmering Shades & Pre Sharpened Colored Pencils, Ideal for Artists, Adults and Kids for Drawing & Coloring, 12/Pack, 1-Pack | C77: FBA_735-EACH | D77: B0BKRCH9RQ | E77: X0042TSMV5 | F77: 397 | G77: 358 | H77: 147 | I77: 111 | J77: 277.5 | K77: 358 | L77: 119.5 | M77: 238.5 | N77: 0 | O77: 0 | P77: 238.5 | Q77: 0.41061453 | R77: 0 | S77: 0 | T77: 0 | U77: 44.357542 | V77: New | W77: BAZIC Products | Y77: USD | Z77: 5.97 | AA77: 404.24 | AB77: 62 | AC77: 585 | AD77: 576 | AE77: 3 | AF77: 1 | AG77: 0 | AH77: 5 | AI77: 0 | AJ77: 0 | AK77: 576 | AL77: 0 | AM77: Amazon | AN77: 266 | AO77: 263 | AQ77: 0 | AR77: none | AS77: No action required | AT77: 0.0057 ft3 | AU77: 0.31005587
A78: US | B78: BAZIC 3 Ring Binder 1" Economy View Binders Organizer - Pastel Purple Color, Round Ring, Hold 175 Sheets Paper, for School Office Home, 1-Count | C78: FBA_3167-EA-PP | D78: B0CFGGD44R | E78: X003XEDBK7 | F78: 48 | G78: 155 | H78: 253 | I78: 11 | J78: 27.5 | K78: 253 | L78: 20.5 | M78: 232.5 | N78: 0 | O78: 0 | P78: 232.5 | Q78: 1.6322581 | R78: 205 | S78: 205 | T78: 0 | U78: 7.5889328 | V78: New | W78: BAZIC Products | Y78: USD | Z78: 7.99 | AA78: 111.86 | AB78: 14 | AC78: 6 | AD78: 0 | AE78: 5 | AF78: 1 | AG78: 0 | AH78: 0 | AI78: 0 | AJ78: 0 | AK78: 0 | AL78: 0 | AM78: Amazon | AN78: 10 | AO78: 10 | AP78: low_stock | AQ78: 24 | AR78: 46054 | AS78: Create shipping plan | AT78: 0.1022 ft3
A79: US | B79: BAZIC Products Washable Glue Pen 1.7 Oz. (50 mL), Liquid Clear Glues Bond Adhesive for Art Crafts Project at School Home Office (2/Pack), 1-Pack | C79: FBA_2028-EACH | D79: B005OYUL24 | E79: B005OYUL24 | F79: 0 | G79: 98 | H79: 232 | I79: 3 | J79: 7.5 | K79: 232 | L79: 0 | M79: 232 | N79: 0 | O79: 0 | P79: 232 | Q79: 2.3673469 | R79: 232 | S79: 232 | T79: 0 | U79: 0 | V79: New | W79: BAZIC Products | Y79: USD | Z79: 6.89 | AA79: 17.64 | AB79: 3 | AC79: 2 | AD79: 0 | AE79: 0 | AF79: 1 | AG79: 0 | AH79: 1 | AI79: 1 | AJ79: 0 | AK79: 0 | AL79: 0 | AM79: Amazon | AN79: 7 | AO79: 3 | AP79: low_stock | AQ79: 24 | AR79: 46055 | AS79: Create shipping plan | AT79: 0.0167 ft3
A80: US | B80: BAZIC Staples Standard (26/6) Metallic Color 3000/Pack, Stapler Refill Standard Size Staple, Assorted Colors, 1-Pack | C80: FBA_609-EACH | D80: B00ESWRD10 | E80: B00ESWRD10 | F80: 720 | G80: 557 | H80: 10 | I80: 157 | J80: 392.5 | K80: 557 | L80: 327.5 | M80: 229.5 | N80: 0 | O80: 0 | P80: 229.5 | Q80: 0.017953321 | R80: 0 | S80: 0 | T80: 0 | U80: 51.705566 | V80: New | W80: BAZIC Products | Y80: USD | Z80: 4.58 | AA80: 1706.59 | AB80: 421 | AC80: 377 | AD80: 360 | AE80: 0 | AF80: 0 | AG80: 4 | AH80: 13 | AI80: 1 | AJ80: 360 | AK80: 0 | AL80: 0 | AM80: Amazon | AN80: 25 | AO80: 0 | AP80: out_of_stock | AQ80: 504 | AR80: 46055 | AS80: Create shipping plan | AT80: 0.0037 ft3 | AU80: 0.28186715
A81: US | B81: BAZIC Products Dry Erase Lap Board 9"x12" & Marker, Double Sided Primary Ruled & Blank, Small Portable Whiteboards for Teacher Home, 1-Pack | C81: FBA_6017-EACH | D81: B07SH9KVKW | E81: B07SH9KVKW | F81: 105 | G81: 301 | H81: 233 | I81: 13 | J81: 32.5 | K81: 301 | L81: 72.5 | M81: 228.5 | N81: 0 | O81: 0 | P81: 228.5 | Q81: 0.77408638 | R81: 196 | S81: 196 | T81: 0 | U81: 13.953488 | V81: New | W81: BAZIC Products | Y81: USD | Z81: 4.39 | AA81: 48.29 | AB81: 11 | AC81: 120 | AD81: 0 | AE81: 118 | AF81: 1 | AG81: 1 | AH81: 0 | AI81: 0 | AJ81: 0 | AK81: 0 | AL81: 0 | AM81: Amazon | AN81: 175 | AO81: 175 | AQ81: 0 | AR81: none | AS81: No action required | AT81: 0.0368 ft3 | AU81: 0.043189369
A82: US | B82: BAZIC Felt Chalkboard Eraser, Wood Blackboard Eraser Cleaner Dustless, Teacher Kids Office Classroom, 1-Pack | C82: FBA_6003-EACH | D82: B002URU9G6 | E82: B002URU9G6 | F82: 155 | G82: 372 | H82: 28 | I82: 92 | J82: 230 | K82: 372 | L82: 0 | M82: 372 | N82: 144 | O82: 144 | P82: 228 | Q82: 0.075268817 | R82: 217 | S82: 73 | T82: 144 | U82: 16.666667 | V82: New | W82: BAZIC Products | Y82: USD | Z82: 5.49 | AA82: 1312.11 | AB82: 239 | AC82: 235 | AD82: 0 | AE82: 212 | AF82: 17 | AG82: 2 | AH82: 4 | AI82: 3 | AJ82: 0 | AK82: 0 | AL82: 0 | AM82: Amazon | AN82: 90 | AO82: 87 | AQ82: 24 | AR82: 46055 | AS82: Create shipping plan | AT82: 0.0136 ft3 | AU82: 0.24731183
A83: US | B83: BAZIC Products Index Card Case with 5 Tab Dividers – Durable Plastic 3"x5" Flash Card Organizer and Storage Holder, 100-Card Capacity, Ideal for School, Office, and Study Use, 6-Pack | C83: FBA_3182-SET6 | D83: B07S4H1PF7 | E83: X003SBSK5B | F83: 130 | G83: 79 | H83: 231 | I83: 47 | J83: 117.5 | K83: 231 | L83: 12.5 | M83: 218.5 | N83: 0 | O83: 0 | P83: 218.5 | Q83: 2.9240506 | R83: 101 | S83: 101 | T83: 0 | U83: 22.510823 | V83: New | W83: BAZIC Products | Y83: USD | Z83: 12.89 | AA83: 707.83 | AB83: 55 | AC83: 49 | AD83: 18 | AE83: 23 | AF83: 7 | AG83: 0 | AH83: 1 | AI83: 0 | AJ83: 18 | AK83: 0 | AL83: 0 | AM83: Amazon | AN83: 18 | AO83: 11 | AP83: low_stock | AQ83: 66 | AR83: 46055 | AS83: Create shipping plan | AT83: 0.1534 ft3
A84: US | B84: BAZIC Index Card Box 3"x5", Flip Top Utility Plastic Storage Case 250 Cards Capacity, Flash Card Holder Organizer, for Office, 6-Pack | C84: FBA_3125-SET6 | D84: B07RZ3BBSR | E84: X003SC5KIP | F84: 38 | G84: 218 | H84: 158 | I84: 60 | J84: 150 | K84: 218 | L84: 0 | M84: 218 | N84: 0 | O84: 0 | P84: 218 | Q84: 0.72477064 | R84: 180 | S84: 180 | T84: 0 | U84: 6.9724771 | V84: New | W84: BAZIC Products | Y84: USD | Z84: 19.49 | AA84: 331.31 | AB84: 17 | AC84: 81 | AD84: 0 | AE84: 75 | AF84: 5 | AG84: 0 | AH84: 1 | AI84: 0 | AJ84: 0 | AK84: 0 | AL84: 0 | AM84: Amazon | AN84: 85 | AO84: 84 | AQ84: 0 | AR84: none | AS84: No action required | AT84: 0.3179 ft3 | AU84: 0.27522936
A85: US | B85: BAZIC Sketch Book 30 Ct. 8.5" X 11", Spiral Side Bound Sketchbook Drawing Pads, Sketching Paper Coloring Book for Artist Kids School, 1-Pack | C85: FBA_5045-EACH-B | D85: B00FIJTHZW | E85: X003DEKDWV | F85: 144 | G85: 329 | H85: 360 | I85: 0 | J85: 0 | K85: 360 | L85: 144 | M85: 216 | N85: 0 | O85: 0 | P85: 216 | Q85: 1.0942249 | R85: 216 | S85: 216 | T85: 0 | U85: 16 | V85: New | W85: BAZIC Products | Y85: USD | Z85: 5.65 | AA85: 16.57 | AB85: 3 | AC85: 144 | AD85: 144 | AE85: 0 | AF85: 0 | AG85: 0 | AH85: 0 | AI85: 1 | AJ85: 144 | AK85: 0 | AL85: 0 | AM85: Amazon | AN85: 365+ | AO85: 0 | AP85: out_of_stock | AQ85: 0 | AR85: none | AS85: No action required | AT85: 0.0274 ft3
A86: US | B86: BAZIC Products Pink Eraser Top, Latex-Free Pencil Top Erasers with Arrowhead Caps, Non-Toxic Erasers for Kids, Students, Teachers, Classroom, Art, Homework & School Supplies, 50/Pack, 2-Pack | C86: FBA_2205-PACK2 | D86: B09BBLKGY9 | E86: X0044RG65T | F86: 12 | G86: 228 | H86: 179 | I86: 0 | J86: 0 | K86: 228 | L86: 12 | M86: 216 | N86: 0 | O86: 0 | P86: 216 | Q86: 0.78508772 | R86: 216 | S86: 216 | T86: 0 | U86: 2.1052632 | V86: New | W86: BAZIC Products | Y86: USD | Z86: 6.89 | AA86: 0 | AB86: 0 | AC86: 12 | AD86: 0 | AE86: 12 | AF86: 0 | AG86: 0 | AH86: 0 | AI86: 0 | AJ86: 0 | AK86: 0 | AL86: 0 | AM86: Amazon | AQ86: 0 | AR86: none | AS86: No action required | AT86: 0.0367 ft3 | AU86: 0
A87: US | B87: BAZIC Products Pencil Wood Pre-Sharpened #2 HB Jumbo Pencils, Latex Free Eraser, Premium Wood Pre Sharpened Yellow Pencils for School Office (4/Pack), 2-Packs | C87: FBA_716-PACK2 | D87: B08F77T22M | E87: X003WOGAXD | F87: 23 | G87: 95 | H87: 233 | I87: 2 | J87: 5 | K87: 233 | L87: 18 | M87: 215 | N87: 0 | O87: 0 | P87: 215 | Q87: 2.4526316 | R87: 210 | S87: 210 | T87: 0 | U87: 3.9484979 | V87: New | W87: BAZIC Products | Y87: USD | Z87: 6.89 | AA87: 0 | AB87: 0 | AC87: 25 | AD87: 24 | AE87: 1 | AF87: 0 | AG87: 0 | AH87: 0 | AI87: 0 | AJ87: 12 | AK87: 12 | AL87: 0 | AM87: Amazon | AQ87: 0 | AR87: none | AS87: No action required | AT87: 0.0183 ft3
A88: US | B88: BAZIC Products Poster Board Glitter Frame Color - Assorted Glitter Color, Sparkling Frame Colored Poster Board Paper for Crafts, Decorations, & Vision Board Projects, 11” x 14”, 5/Pack, 1-Pack | C88: FBA_5414-EACH | D88: B07TCRK63W | E88: B07TCRK63W | F88: 195 | G88: 142 | H88: 13 | I88: 215 | J88: 537.5 | K88: 215 | L88: 0 | M88: 215 | N88: 0 | O88: 0 | P88: 215 | Q88: 0.091549296 | R88: 20 | S88: 20 | T88: 0 | U88: 36.27907 | V88: New | W88: BAZIC Products | Y88: USD | Z88: 4.82 | AA88: 585.57 | AB88: 125 | AC88: 144 | AD88: 99 | AE88: 32 | AF88: 0 | AG88: 11 | AH88: 2 | AI88: 0 | AJ88: 0 | AK88: 96 | AL88: 3 | AM88: Amazon | AN88: 38 | AO88: 35 | AQ88: 0 | AR88: none | AS88: No action required | AT88: 0.0347 ft3 | AU88: 1
A89: US | B89: BAZIC PRODUCTS Wide Ruled 1-Subject Notebook, Non-Spiral Composition Style, Easy-Tear Wireless Pages, 3-Hole Punched, 80 Sheets, Assorted Colors, for School, Office & Home, 24-Pack | C89: FBA_582-CASE | D89: B07XQL67K5 | E89: X003SC980V | F89: 5 | G89: 139 | H89: 215 | I89: 8 | J89: 20 | K89: 215 | L89: 0 | M89: 215 | N89: 0 | O89: 0 | P89: 215 | Q89: 1.5467626 | R89: 210 | S89: 210 | T89: 0 | U89: 0.93023256 | V89: New | W89: BAZIC Products | Y89: USD | Z89: 49.89 | AA89: 548.79 | AB89: 11 | AC89: 16 | AD89: 0 | AE89: 13 | AF89: 1 | AG89: 2 | AH89: 0 | AI89: 0 | AJ89: 0 | AK89: 0 | AL89: 0 | AM89: Amazon | AN89: 43 | AO89: 39 | AQ89: 8 | AR89: 46055 | AS89: Create shipping plan | AT89: 0.3837 ft3
A90: US | B90: BAZIC PRODUCTS Plastic Pencil Case, Ruler Length Large Utility Storage Box, Multi Purpose Organizer & Supply Holder, Clear Box Design, Ideal for School, Office & Craft Use, 4-Pack | C90: FBA_851-PACK4 | D90: B093CRKPKJ | E90: X003SCA9TF | F90: 0 | G90: 212 | H90: 190 | I90: 39 | J90: 97.5 | K90: 212 | L90: 0 | M90: 212 | N90: 0 | O90: 0 | P90: 212 | Q90: 0.89622642 | R90: 212 | S90: 212 | T90: 0 | U90: 0 | V90: New | W90: BAZIC Products | Y90: USD | Z90: 17.99 | AA90: 18.99 | AB90: 1 | AC90: 0 | AD90: 0 | AE90: 0 | AF90: 0 | AG90: 0 | AH90: 0 | AI90: 1 | AJ90: 0 | AK90: 0 | AL90: 0 | AM90: Amazon | AN90: 0 | AO90: 0 | AP90: out_of_stock | AQ90: 66 | AR90: 46048 | AS90: Create shipping plan | AT90: 0.4489 ft3
A91: US | B91: BAZIC PRODUCTS Manuscript Handwriting Pad – 10.5" X 8", Handwriting Paper, Kids Learning Practice Workbook, Writing Paper with Lines for Kids, Toddler, Kindergarten, 50 Sheets/Pack, 2-Pack | C91: FBA_543-PACK2 | D91: B08DFHV95M | E91: X0040DZIND | F91: 59 | G91: 189 | H91: 240 | I91: 12 | J91: 30 | K91: 240 | L91: 29 | M91: 211 | N91: 0 | O91: 0 | P91: 211 | Q91: 1.2698413 | R91: 181 | S91: 181 | T91: 0 | U91: 9.8333333 | V91: New | W91: BAZIC Products | Y91: USD | Z91: 7.69 | AA91: 0 | AB91: 0 | AC91: 72 | AD91: 72 | AE91: 0 | AF91: 0 | AG91: 0 | AH91: 0 | AI91: 0 | AJ91: 0 | AK91: 72 | AL91: 0 | AM91: Amazon | AN91: 86 | AO91: 86 | AQ91: 0 | AR91: none | AS91: No action required | AT91: 0.0097 ft3
C92: FBA_1621-EACH | D92: B07RFTSF59 | F92: 0 | G92: 209 | H92: 17 | I92: 50 | J92: 209 | K92: 209 | L92: 0 | M92: 209 | N92: 0 | O92: 0 | P92: 209 | Q92: 0.0813 | R92: 0.2392 | AU92: 0.2392
A93: US | B93: BAZIC Products Penny Coin Wrappers – Durable Preformed Paper Tube, Sleeves for Coin Sorter and Holder, 36/Pack, 2 Packs | C93: FBA_5011-PACK2 | D93: B0127E8W0Q | E93: B0127E8W0Q | F93: 33 | G93: 175 | H93: 208 | I93: 56 | J93: 140 | K93: 208 | L93: 0 | M93: 208 | N93: 0 | O93: 0 | P93: 208 | Q93: 1.1885714 | R93: 175 | S93: 175 | T93: 0 | U93: 6.3461538 | V93: New | W93: BAZIC Products | Y93: USD | Z93: 9.89 | AA93: 150.65 | AB93: 15 | AC93: 129 | AD93: 125 | AE93: 0 | AF93: 0 | AG93: 0 | AH93: 4 | AI93: 0 | AJ93: 25 | AK93: 100 | AL93: 0 | AM93: Amazon | AN93: 57 | AO93: 46 | AQ93: 50 | AR93: 46055 | AS93: Create shipping plan | AT93: 0.2418 ft3
A94: US | B94: BAZIC Products 3 Ring Binder 1" Economy View Binders Organizer - Fuchsia, Round Ring, Hold 175 Sheets Paper, for School Office Home, 2-Count | C94: FBA_4126-PACK2 | D94: B08DQHV4BN | E94: X0044R3MG5 | F94: 12 | G94: 36 | H94: 15 | I94: 206 | J94: 515 | K94: 206 | L94: 0 | M94: 206 | N94: 0 | O94: 0 | P94: 206 | Q94: 0.41666667 | R94: 194 | S94: 194 | T94: 0 | U94: 2.3300971 | V94: New | W94: BAZIC Products | Y94: USD | Z94: 17.09 | AA94: 17.09 | AB94: 1 | AC94: 5 | AD94: 0 | AE94: 5 | AF94: 0 | AG94: 0 | AH94: 0 | AI94: 0 | AJ94: 0 | AK94: 0 | AL94: 0 | AM94: Amazon | AN94: 78 | AO94: 78 | AQ94: 0 | AR94: none | AS94: No action required | AT94: 0.1211 ft3 | AU94: 1
A95: US | B95: BAZIC Products Staples Standard (26/6) Metallic Color 3000/Pack, Stapler Refill Standard Size Staple, Assorted Colors, 2-Packs | C95: FBA_609-PACK2 | D95: B09C2RFDFH | E95: X0044R3MO7 | F95: 36 | G95: 115 | H95: 204 | I95: 37 | J95: 92.5 | K95: 204 | L95: 0 | M95: 204 | N95: 0 | O95: 0 | P95: 204 | Q95: 1.773913 | R95: 168 | S95: 168 | T95: 0 | U95: 7.0588235 | V95: New | W95: BAZIC Products | Y95: USD | Z95: 8.69 | AA95: 7.49 | AB95: 1 | AC95: 86 | AD95: 86 | AE95: 0 | AF95: 0 | AG95: 0 | AH95: 0 | AI95: 0 | AJ95: 36 | AK95: 48 | AL95: 2 | AM95: Amazon | AN95: 365+ | AO95: 264 | AQ95: 0 | AR95: none | AS95: No action required | AT95: 0.007 ft3
A96: US | B96: BAZIC Products Expanding File Folder 5 Pockets w/Tab, Letter Size Plastic File Pocket Folders, Office Supplies Paper Documents Organizer, 1-Pack | C96: FBA_3171-EACH | D96: B0BP5Q88DW | E96: X0040DP2BL | F96: 107 | G96: 112 | H96: 203 | I96: 49 | J96: 122.5 | K96: 203 | L96: 0 | M96: 203 | N96: 0 | O96: 0 | P96: 203 | Q96: 1.8125 | R96: 96 | S96: 96 | T96: 0 | U96: 21.083744 | V96: New | W96: BAZIC Products | Y96: USD | Z96: 8.09 | AA96: 339.78 | AB96: 42 | AC96: 40 | AD96: 12 | AE96: 25 | AF96: 1 | AG96: 2 | AH96: 0 | AI96: 0 | AJ96: 12 | AK96: 0 | AL96: 0 | AM96: Amazon | AN96: 30 | AO96: 18 | AQ96: 48 | AR96: 46055 | AS96: Create shipping plan | AT96: 0.0819 ft3
A97: US | B97: BAZIC Products Composition Book 80 Sheet 5" x 7" Poly Cover Notebook, Writing Journal Comp Lined Notebooks for Office School, Assorted Color, 8-Pack | C97: FBA_5472-SET8 | D97: B096BNMBLN | E97: X003EGLP2Z | F97: 58 | G97: 211 | H97: 223 | I97: 15 | J97: 37.5 | K97: 223 | L97: 20.5 | M97: 202.5 | N97: 0 | O97: 0 | P97: 202.5 | Q97: 1.056872 | R97: 165 | S97: 165 | T97: 0 | U97: 10.403587 | V97: New | W97: BAZIC Products | Y97: USD | Z97: 19.75 | AA97: 414.78 | AB97: 22 | AC97: 73 | AD97: 72 | AE97: 0 | AF97: 0 | AG97: 1 | AH97: 0 | AI97: 0 | AJ97: 60 | AK97: 12 | AL97: 0 | AM97: Amazon | AN97: 119 | AO97: 19 | AQ97: 0 | AR97: none | AS97: No action required | AT97: 0.0532 ft3
A98: US | B98: BAZIC Products 3 Ring Binder 1" Economy View Binders Organizer - Green, Round Ring, Hold 175 Sheets Paper, for School Office Home, 1-Count | C98: FBA_4122-EACH | D98: B07Q97RHBH | E98: X003SBSJEN | F98: 1 | G98: 192 | H98: 200 | I98: 6 | J98: 15 | K98: 200 | L98: 0 | M98: 200 | N98: 0 | O98: 0 | P98: 200 | Q98: 1.0416667 | R98: 199 | S98: 199 | T98: 0 | U98: 0.2 | V98: New | W98: BAZIC Products | Y98: USD | Z98: 9.59 | AA98: 28.77 | AB98: 3 | AC98: 25 | AD98: 0 | AE98: 24 | AF98: 1 | AG98: 0 | AH98: 0 | AI98: 1 | AJ98: 0 | AK98: 0 | AL98: 0 | AM98: Amazon | AN98: 91 | AO98: 91 | AQ98: 0 | AR98: none | AS98: No action required | AT98: 0.1124 ft3
A99: US | B99: BAZIC Products Blank Index Cards 3" X 5" 100 Count, White Unruled Flashcards, Flash Card for Learning Memory Reminder (100/Pack), 1-Pack | C99: FBA_520-EACH | D99: B07S962L7Q | E99: X0044RLTFV | F99: 134 | G99: 383 | H99: 152 | I99: 64 | J99: 160 | K99: 199.66667 | L99: 0 | M99: 199.66667 | N99: 0 | O99: 0 | P99: 199.66667 | Q99: 0.39686684 | R99: 65.666667 | S99: 65.666667 | T99: 0 | U99: 26.844741 | V99: New | W99: BAZIC Products | Y99: USD | Z99: 4.5 | AA99: 107 | AB99: 24 | AC99: 150 | AD99: 0 | AE99: 144 | AF99: 2 | AG99: 4 | AH99: 0 | AI99: 0 | AJ99: 0 | AK99: 0 | AL99: 0 | AM99: Amazon | AN99: 175 | AO99: 172 | AQ99: 0 | AR99: none | AS99: No action required | AT99: 0.0067 ft3 | AU99: 0.32053422
A100: US | B100: BAZIC Products Mini Highlighter – Pastel Color Assorted Chisel Tip Highlighter Set, Desk Style Highlighter Pen for Office, School, and Study Use, Smooth Marking, (5/Packs), 1-Pack | C100: FBA_2309-EACH | D100: B0BP5FBZKF | E100: X003TDI6Z7 | F100: 476 | G100: 311 | H100: 133 | I100: 145 | J100: 362.5 | K100: 311 | L100: 113.5 | M100: 197.5 | N100: 0 | O100: 0 | P100: 197.5 | Q100: 0.42765273 | R100: 0 | S100: 0 | T100: 0 | U100: 61.221865 | V100: New | W100: BAZIC Products | Y100: USD | Z100: 4.79 | AA100: 977.14 | AB100: 204 | AC100: 228 | AD100: 147 | AE100: 62 | AF100: 5 | AG100: 6 | AH100: 8 | AI100: 0 | AJ100: 144 | AK100: 0 | AL100: 3 | AM100: Amazon | AN100: 35 | AO100: 9 | AP100: low_stock | AQ100: 120 | AR100: 46055 | AS100: Create shipping plan | AT100: 0.0084 ft3 | AU100: 0.46623794
...

Sheet all asins
A1: (Child) ASIN
A2: B0BG14KCKZ | B2: =VLOOKUP(A2,'FBA Inventory'!E:E,1,FALSE) -> B0BG14KCKZ
A3: B0018MN4RA | B3: =VLOOKUP(A3,'FBA Inventory'!E:E,1,FALSE) -> B0018MN4RA
A4: B003BMWZ48 | B4: =VLOOKUP(A4,'FBA Inventory'!E:E,1,FALSE) -> B003BMWZ48
A5: B09BBP343Q | B5: =VLOOKUP(A5,'FBA Inventory'!E:E,1,FALSE) -> B09BBP343Q
A6: B076F13SG5 | B6: =VLOOKUP(A6,'FBA Inventory'!E:E,1,FALSE) -> B076F13SG5
A7: B09DP3TR4F | B7: =VLOOKUP(A7,'FBA Inventory'!E:E,1,FALSE) -> B09DP3TR4F
A8: B00H9Z198Q | B8: =VLOOKUP(A8,'FBA Inventory'!E:E,1,FALSE) -> B00H9Z198Q
A9: B09GD5961M | B9: =VLOOKUP(A9,'FBA Inventory'!E:E,1,FALSE) -> B09GD5961M
A10: B00ZPRYV0I | B10: =VLOOKUP(A10,'FBA Inventory'!E:E,1,FALSE) -> B00ZPRYV0I
A11: B08P3W6YN6 | B11: =VLOOKUP(A11,'FBA Inventory'!E:E,1,FALSE) -> B08P3W6YN6
A12: B001BNW7QA | B12: =VLOOKUP(A12,'FBA Inventory'!E:E,1,FALSE) -> B001BNW7QA
A13: B07S64FRBG | B13: =VLOOKUP(A13,'FBA Inventory'!E:E,1,FALSE) -> B07S64FRBG
... A4935: B0FCHT1WZ9 | B4935: =VLOOKUP(A4935,'FBA Inventory'!E:E,1,FALSE) -> B0FCHT1WZ9

Sheet InventoryUnits Column Check
A2: Sheet | B2: Actual Header | C2: Correct Header | D2: Column Check
A3: 14 Day SC Report | B3: =VLOOKUP('14 day SC Report'!A1,'14 day SC Report'!A1:O1,10,FALSE) -> Units Ordered | C3: Units Ordered | D3: =IF(B3=C3,"Ok","Error") -> Ok
A4: 45 Day SC Report | B4: =VLOOKUP('2025'!A1,'2025'!A1:O1,10,FALSE) -> Units Ordered | C4: Units Ordered | D4: =IF(B4=C4,"Ok","Error") -> Ok
A5: 12 Month SC Report | B5: =VLOOKUP('2024'!A1,'2024'!A1:O1,10,FALSE) -> Units Ordered | C5: Units Ordered | D5: =IF(B5=C5,"Ok","Error") -> Ok
A6: - | B6: =VLOOKUP('[1]VHC Inventory'!A1,'[1]VHC Inventory'!A1:D1,4,FALSE) -> #REF! | C6: Qty On Hand | D6: =IF(B6=C6,"Ok","Error") -> #REF!
A7: FBA Inventory | B7: =VLOOKUP( 'FBA Inventory'!A1,'FBA Inventory'!A1:Q1,14,FALSE) -> Inbound | C7: Inbound | D7: =IF(B7=C7,"Ok","Error") -> Ok
B8: =VLOOKUP( 'FBA Inventory'!A1,'FBA Inventory'!A1:Q1,15,FALSE) -> Available | C8: Available | D8: =IF(B8=C8,"Ok","Error") -> Ok
B9: =VLOOKUP( 'FBA Inventory'!A1,'FBA Inventory'!A1:Q1,16,FALSE) -> FC transfer | C9: FC transfer | D9: =IF(B9=C9,"Ok","Error") -> Ok
B10: =VLOOKUP( 'FBA Inventory'!A1,'FBA Inventory'!A1:Q1,17,FALSE) -> FC Processing | C10: FC Processing | D10: =IF(B10=C10,"Ok","Error") -> Ok
A11: Duplicate Asins in FBA Inventory | D11: =IF(SUMPRODUCT(--(COUNTIF('FBA Inventory'!E:E,'FBA Inventory'!E:E)>1))>0=FALSE,"OK","Error") -> OK

Sheet AWD
A1: Timestamp | B1: 46079.56
A2: Merchant ID | B2: A2J9CB3QL3LKD1
A4: Product Name | B4: SKU | C4: FNSKU | D4: ASIN | E4: Inbound to AWD (units) | F4: Inbound to AWD (cases) | G4: Available in AWD (units) | H4: Available in AWD (cases) | I4: Available Units in AWD (US) | J4: Available Cartons in AWD (US) | K4: Reserved in AWD (units) | L4: Reserved in AWD (cases) | M4: Outbound Order (units) | N4: Outbound Order (cases) | O4: Researching (units) | P4: Researching (cases) | Q4: Outbound to FBA (units) | R4: Available in FBA (units) | S4: Available in FBA (days) | T4: Reserved in FBA (units) | U4: Customer Order (units) | V4: FC Processing (units) | W4: FC Transfer (units) | X4: Days of Supply (days) | Y4: Auto Replenishment Ratio (percent)
A5: BAZIC 3/4" X 500" Double Sided Permanent Tape w/Dispenser | B5: FBA_930-EACH | C5: B003BMWQYC | D5: B003BMWQYC | E5: 0 | F5: 0 | G5: 48 | H5: 2 | I5: 48 | J5: 2 | K5: 0 | L5: 0 | M5: 0 | N5: 0 | O5: 0 | P5: 0 | Q5: 0 | R5: 41 | S5: 366 | T5: 0 | U5: 0 | V5: 0 | W5: 0 | X5: -- | Y5: 0
A6: BAZIC Products Plastic Pencil Case, Ruler Length Large Utility Storage Box, Multi Purpose Organizer & Supply Holder, Clear Box Design, Ideal for School, Office & Craft Use, 1-Pack | B6: FBA_851-EACH | C6: B093CPW1HK | D6: B093CPW1HK | E6: 0 | F6: 0 | G6: 12 | H6: 1 | I6: 12 | J6: 1 | K6: 0 | L6: 0 | M6: 0 | N6: 0 | O6: 0 | P6: 0 | Q6: 0 | R6: 0 | S6: 0 | T6: 0 | U6: 0 | V6: 0 | W6: 0 | X6: 360.4 | Y6: SC_FBA_GIM_infinite
A7: BAZIC PRODUCTS Plastic Pencil Case, Ruler Length Utility Storage Box, Multi Purpose Organizer & Supply Holder, Transparent Box Design, Assorted Color, Ideal for School, Office & Craft Use, 4-Pack | B7: FBA_841-SET4 | C7: X003SC38J3 | D7: B07RBC11NP | E7: 0 | F7: 0 | G7: 72 | H7: 6 | I7: 72 | J7: 6 | K7: 0 | L7: 0 | M7: 0 | N7: 0 | O7: 0 | P7: 0 | Q7: 0 | R7: 27 | S7: 50 | T7: 4 | U7: 1 | V7: 0 | W7: 3 | X7: 222.9 | Y7: 0
A8: BAZIC Products Plastic Pencil Case Utility Storage Box, Glitter Bright Color, Multi Purpose Organizer for Pens Pencils, 4-Pack | B8: FBA_839-SET4 | C8: B01LZ4HWFD | D8: B01LZ4HWFD | E8: 0 | F8: 0 | G8: 36 | H8: 3 | I8: 36 | J8: 3 | K8: 0 | L8: 0 | M8: 0 | N8: 0 | O8: 0 | P8: 0 | Q8: 0 | R8: 9 | S8: 23 | T8: 3 | U8: 0 | V8: 0 | W8: 3 | X8: 492.1 | Y8: 1
A9: BAZIC Products Pencil Pouch 3 Ring Binder Pouch w/Rivet Enforced Rings Holes, Pastel Color Mesh Window Zipper Pouchesr, 6-Pack | B9: FBA_810-SET6 | C9: X003S83OA5 | D9: B09DPBCNJW | E9: 0 | F9: 0 | G9: 264 | H9: 11 | I9: 264 | J9: 11 | K9: 0 | L9: 0 | M9: 0 | N9: 0 | O9: 0 | P9: 0 | Q9: 0 | R9: 251 | S9: 366 | T9: 0 | U9: 0 | V9: 0 | W9: 0 | X9: -- | Y9: 0
A10: BAZIC Products Pencil Pouch 3 Ring Binder Pouch, Rivet Enforced Ring Hole, Mesh Window Zipper Case, Pastel Purple, 2-Pack | B10: FBA_810-PP-PACK2 | C10: X003KDRU53 | D10: B0BPJTBHZN | E10: 0 | F10: 0 | G10: 72 | H10: 1 | I10: 72 | J10: 1 | K10: 0 | L10: 0 | M10: 0 | N10: 0 | O10: 0 | P10: 0 | Q10: 0 | R10: 75 | S10: 366 | T10: 1 | U10: 0 | V10: 1 | W10: 0 | X10: -- | Y10: 0
A11: BAZIC Products Pencil Pouch 3 Ring Binder Pouch, Rivet Enforced Ring Hole, Mesh Window Zipper Case, Pastel Pink, 2-Pack | B11: FBA_810-PNK-PACK2 | C11: X003KDW1BV | D11: B0BPJPD5QX | E11: 0 | F11: 0 | G11: 72 | H11: 1 | I11: 72 | J11: 1 | K11: 0 | L11: 0 | M11: 0 | N11: 0 | O11: 0 | P11: 0 | Q11: 0 | R11: 104 | S11: 366 | T11: 1 | U11: 0 | V11: 1 | W11: 0 | X11: -- | Y11: 0
A12: BAZIC Products Pencil Pouch 3 Ring Binder Pouch, Rivet Enforced Ring Hole, Mesh Window Zipper Case, Pastel Orange, 2-Pack | B12: FBA_810-OR-PACK2 | C12: X003KDRU5D | D12: B0BPJW18HP | E12: 0 | F12: 0 | G12: 72 | H12: 1 | I12: 72 | J12: 1 | K12: 0 | L12: 0 | M12: 0 | N12: 0 | O12: 0 | P12: 0 | Q12: 0 | R12: 114 | S12: 366 | T12: 0 | U12: 0 | V12: 0 | W12: 0 | X12: -- | Y12: 0
A13: BAZIC Products Pencil Pouch 3 Ring Binder Pouch, Rivet Enforced Ring Hole, Mesh Window Zipper Case, Pastel Grey, 2-Pack | B13: FBA_810-GY-PACK2 | C13: X003KDQIZV | D13: B0BPJLZLLW | E13: 0 | F13: 0 | G13: 72 | H13: 1 | I13: 72 | J13: 1 | K13: 0 | L13: 0 | M13: 0 | N13: 0 | O13: 0 | P13: 0 | Q13: 0 | R13: 60 | S13: 366 | T13: 0 | U13: 0 | V13: 0 | W13: 0 | X13: -- | Y13: 0
A14: BAZIC Products Pencil Pouch 3 Ring Binder Pouch w/Rivet Enforced Rings Holes, Neon Black Color Mesh Window Zipper Pouches, 6-Pack | B14: FBA_809-SETOF6 | C14: X0031MTKF1 | D14: B09HL5JHLT | E14: 0 | F14: 0 | G14: 120 | H14: 5 | I14: 120 | J14: 5 | K14: 0 | L14: 0 | M14: 0 | N14: 0 | O14: 0 | P14: 0 | Q14: 0 | R14: 50 | S14: 151 | T14: 0 | U14: 0 | V14: 0 | W14: 0 | X14: -- | Y14: 0
A15: BAZIC PRODUCTS Pencil Pouch for 3 Ring Binder, Zippered Mesh Window Pencil Case with Reinforced Grommets, Durable Binder Organizer for School Supplies or Office Supplies Storage, 2-Pack | B15: FBA_808-PACK2 | C15: X0039GZAX5 | D15: B09GD5961M | E15: 0 | F15: 0 | G15: 432 | H15: 6 | I15: 432 | J15: 6 | K15: 0 | L15: 0 | M15: 0 | N15: 0 | O15: 0 | P15: 0 | Q15: 0 | R15: 670 | S15: 366 | T15: 20 | U15: 1 | V15: 2 | W15: 17 | X15: 870.1 | Y15: 0
A16: BAZIC PRODUCTS Pencil Pouch 3 Ring Binder Pouch w/Rivet Enforced Rings Holes, Assorted Color Mesh Window, Double Zipper Pouches 6-Pack | B16: FBA_807-SET6 | C16: X003BSZ6JT | D16: B07T9NZN1N | E16: 0 | F16: 0 | G16: 48 | H16: 2 | I16: 48 | J16: 2 | K16: 0 | L16: 0 | M16: 0 | N16: 0 | O16: 0 | P16: 0 | Q16: 0 | R16: 20 | S16: 366 | T16: 0 | U16: 0 | V16: 0 | W16: 0 | X16: -- | Y16: 0
A17: BAZIC Products Pencil Pouch 3 Ring Binder Pouch w/Rivet Enforced Rings Holes, Assorted Color Mesh Window Zipper Pouches, 4-Pack | B17: FBA_803-SET4 | C17: X003SCCWW7 | D17: B07RC79KYS | E17: 0 | F17: 0 | G17: 324 | H17: 9 | I17: 324 | J17: 9 | K17: 0 | L17: 0 | M17: 0 | N17: 0 | O17: 0 | P17: 0 | Q17: 0 | R17: 139 | S17: 136 | T17: 3 | U17: 1 | V17: 2 | W17: 0 | X17: -- | Y17: 0
A18: BAZIC Products School Kit Pack 60 Count, School Supply Box for Elementary Student K-6, Ruler Composition Book Pencil Eraser Crayon, 1-Pack | B18: FBA_8010-EACH | C18: B0B3C4XXJ5 | D18: B0B3C4XXJ5 | E18: 0 | F18: 0 | G18: 420 | H18: 42 | I18: 420 | J18: 42 | K18: 0 | L18: 0 | M18: 0 | N18: 0 | O18: 0 | P18: 0 | Q18: 0 | R18: 65 | S18: 999 | T18: 11 | U18: 1 | V18: 0 | W18: 10 | X18: -- | Y18: 0
A19: BAZIC Products Pencil Wood Pre-Sharpened Pencil #2 HB, Latex Free Eraser Yellow Pre Sharpened Pencils for Exam Sketching School Office (12/Pack), 2-Packs | B19: FBA_761-PACK2 | C19: X003WOIKTF | D19: B08F759LCW | E19: 0 | F19: 0 | G19: 792 | H19: 11 | I19: 792 | J19: 11 | K19: 0 | L19: 0 | M19: 0 | N19: 0 | O19: 0 | P19: 0 | Q19: 0 | R19: 209 | S19: 999 | T19: 0 | U19: 0 | V19: 0 | W19: 0 | X19: -- | Y19: 0
A20: BAZIC Products Black Rubber Bands – Assorted Sizes, Heavy Duty Elastic Bands For Money, Office, School, Home Organization, Crafts, Durable Stretch Rubber Bands, 2 Oz (56.7 g), 1-Pack | B20: FBA_6120-EACH | C20: B09DJVP3DS | D20: B09DJVP3DS | E20: 0 | F20: 0 | G20: 36 | H20: 1 | I20: 36 | J20: 1 | K20: 0 | L20: 0 | M20: 0 | N20: 0 | O20: 0 | P20: 0 | Q20: 37 | R20: 225 | S20: 83 | T20: 69 | U20: 0 | V20: 0 | W20: 69 | X20: 101.4 | Y20: 0.78
A21: BAZIC Products Rubber Bands – Assorted Color & Sizes, Heavy Duty Elastic Bands For Money, Office, School, Home Organization, Crafts, Durable Stretch Rubber Bands, 2 Oz (56.70 g), 1-Pack | B21: FBA_6110-EACH | C21: X002GASSMF | D21: B07SC668W8 | E21: 0 | F21: 0 | G21: 504 | H21: 14 | I21: 504 | J21: 14 | K21: 0 | L21: 0 | M21: 0 | N21: 0 | O21: 0 | P21: 0 | Q21: 1 | R21: 194 | S21: 48 | T21: 11 | U21: 1 | V21: 2 | W21: 8 | X21: 303.7 | Y21: 1
A22: BAZIC Rubber Bands, Assorted Size 2 Oz./ 56.70 g, Made in USA Elastic Stretchable Bands for Bank Paper Bills Money Dollars File Folders, 1-Pack | B22: FBA_6100-EACH | C22: B00GSSDLMM | D22: B00GSSDLMM | E22: 0 | F22: 0 | G22: 936 | H22: 26 | I22: 936 | J22: 26 | K22: 0 | L22: 0 | M22: 0 | N22: 0 | O22: 0 | P22: 0 | Q22: 0 | R22: 354 | S22: 134 | T22: 0 | U22: 0 | V22: 0 | W22: 0 | X22: 511.7 | Y22: 1
A23: BAZIC Staples Standard (26/6) 5000/Pack, Stapler Refill Standard Size Staple, Silver Colors, 1-Pack | B23: FBA_608-EACH | C23: X003EGFQKR | D23: B003BMWZ48 | E23: 0 | F23: 0 | G23: 936 | H23: 13 | I23: 936 | J23: 13 | K23: 72 | L23: 1 | M23: 0 | N23: 0 | O23: 72 | P23: 1 | Q23: 0 | R23: 424 | S23: 30 | T23: 50 | U23: 21 | V23: 16 | W23: 13 | X23: 240.1 | Y23: 1
A24: BAZIC Felt Chalkboard Eraser, Wood Blackboard Eraser Cleaner Dustless, Teacher Kids Office Classroom, 1-Pack | B24: FBA_6003-EACH | C24: B002URU9G6 | D24: B002URU9G6 | E24: 0 | F24: 0 | G24: 144 | H24: 1 | I24: 144 | J24: 1 | K24: 0 | L24: 0 | M24: 0 | N24: 0 | O24: 0 | P24: 0 | Q24: 0 | R24: 149 | S24: 75 | T24: 7 | U24: 1 | V24: 2 | W24: 4 | X24: 124.6 | Y24: 1
A25: BAZIC 100 Ct. 4-1" Quad-Ruled Filler Paper | B25: FBA_569-EACH | C25: B003BLQHZM | D25: B003BLQHZM | E25: 0 | F25: 0 | G25: 432 | H25: 12 | I25: 432 | J25: 12 | K25: 0 | L25: 0 | M25: 0 | N25: 0 | O25: 0 | P25: 0 | Q25: 0 | R25: 84 | S25: 119 | T25: 0 | U25: 0 | V25: 0 | W25: 0 | X25: -- | Y25: 0
A26: BAZIC Products Poster Board Glitter Frame Color - Assorted Glitter Color, Sparkling Frame Colored Poster Board Paper for Crafts, Decorations, & Vision Board Projects, 11” x 14”, 5/Pack, 1-Pack | B26: FBA_5414-EACH | C26: B07TCRK63W | D26: B07TCRK63W | E26: 0 | F26: 0 | G26: 0 | H26: 0 | I26: 0 | J26: 0 | K26: 0 | L26: 0 | M26: 0 | N26: 0 | O26: 0 | P26: 0 | Q26: 48 | R26: 11 | S26: 32 | T26: 88 | U26: 0 | V26: 2 | W26: 86 | X26: 94.3 | Y26: 0.7
A27: BAZIC Products Poster Board Glitter Color 11" X 14", Sparkling Colored Poster Board Paper for Christmas Wedding Birthday Craft Project (3 Color/Pack) COLOR SENT RANDOM | B27: FBA_5413-EACH | C27: B075VXLS9F | D27: B075VXLS9F | E27: 0 | F27: 0 | G27: 48 | H27: 1 | I27: 48 | J27: 1 | K27: 0 | L27: 0 | M27: 0 | N27: 0 | O27: 0 | P27: 0 | Q27: 0 | R27: 23 | S27: 98 | T27: 3 | U27: 0 | V27: 0 | W27: 3 | X27: 267.9 | Y27: 0
A28: BAZIC Division Flash Cards, Numbers Elementary Math Flashcards Game at School, Problem Solving for Ages 8+ 3rd Grade 4th Grade (36/Pack), 1-Pack | B28: FBA_535-EACH | C28: B003BOUX9A | D28: B003BOUX9A | E28: 0 | F28: 0 | G28: 216 | H28: 3 | I28: 216 | J28: 3 | K28: 0 | L28: 0 | M28: 0 | N28: 0 | O28: 0 | P28: 0 | Q28: 0 | R28: 162 | S28: 185 | T28: 8 | U28: 1 | V28: 0 | W28: 7 | X28: 708.3 | Y28: 0
A29: BAZIC Products Poster Board 11" X 14" Assorted Colored Poster Board Paper for School Craft Project Presentation Drawing Graphic Display (5/Pack), 1-Pack | B29: FBA_529-EACH | C29: X003UID51L | D29: B07S9HP4W5 | E29: 0 | F29: 0 | G29: 48 | H29: 1 | I29: 48 | J29: 1 | K29: 0 | L29: 0 | M29: 0 | N29: 0 | O29: 0 | P29: 0 | Q29: 0 | R29: 76 | S29: 31 | T29: 52 | U29: 0 | V29: 48 | W29: 4 | X29: 183.9 | Y29: 1
A30: BAZIC Products Blank Index Cards 3" X 5" 100 Count, White Unruled Flashcards, Flash Card for Learning Memory Reminder (100/Pack), 1-Pack | B30: FBA_520-EACH | C30: X0044RLTFV | D30: B07S962L7Q | E30: 0 | F30: 0 | G30: 0 | H30: 0 | I30: 0 | J30: 0 | K30: 0 | L30: 0 | M30: 0 | N30: 0 | O30: 0 | P30: 0 | Q30: 72 | R30: 54 | S30: 56 | T30: 8 | U30: 0 | V30: 1 | W30: 7 | X30: 171.7 | Y30: 1
A31: BAZIC Products Blank Paper Copy & Multipurpose Paper - 8.5" x 11" Pastel Color Printer Paper for Inkjet, Laser, and Fax Machines, Ideal for Office, School, and Crafts, 100 Sheets/Pack, 2-Packs | B31: FBA_5191-PACK2 | C31: X003WOIMP7 | D31: B0BCLC7Y4R | E31: 0 | F31: 0 | G31: 18 | H31: 1 | I31: 18 | J31: 1 | K31: 0 | L31: 0 | M31: 0 | N31: 0 | O31: 0 | P31: 0 | Q31: 36 | R31: 1 | S31: 50 | T31: 19 | U31: 1 | V31: 18 | W31: 0 | X31: 183.8 | Y31: 0.71
A32: BAZIC Products Neon Page Marker Dispensers – Sticky Notes for Study Materials, Office Use, Sign Here & Notary Supplies, Colored Page Markers for Books and Documents, 50 Flags/Pack, 2-Packs | B32: FBA_5174-PACK2 | C32: X003BTB1G5 | D32: B08JQQCY92 | E32: 0 | F32: 0 | G32: 1008 | H32: 7 | I32: 1008 | J32: 7 | K32: 0 | L32: 0 | M32: 0 | N32: 0 | O32: 0 | P32: 0 | Q32: 0 | R32: 58 | S32: 72 | T32: 1 | U32: 0 | V32: 0 | W32: 1 | X32: -- | Y32: 0
A33: BAZIC Products Neon Page Marker Dispensers, Sticky Notes for Study Materials, Office Use, Sign Here & Neon Colored Page Markers for Books and Documents, 0.5x1.7, 100 Flags/Pack, 2-Packs | B33: FBA_5172-PACK2 | C33: X003BTCGBT | D33: B08JQQ2BML | E33: 0 | F33: 0 | G33: 1008 | H33: 7 | I33: 1008 | J33: 7 | K33: 0 | L33: 0 | M33: 0 | N33: 0 | O33: 0 | P33: 0 | Q33: 0 | R33: 85 | S33: 43 | T33: 26 | U33: 9 | V33: 0 | W33: 17 | X33: 780.9 | Y33: 0
A34: BAZIC Products Neon Page Marker Dispensers, Sticky Notes for Study Materials, Office Use, Sign Here & Neon Colored Page Markers for Books and Documents, 0.5x1.7, 100 Flags/Pack, 1-Pack | B34: FBA_5172-EACH | C34: B07SKBCHNX | D34: B07SKBCHNX | E34: 0 | F34: 0 | G34: 720 | H34: 30 | I34: 720 | J34: 30 | K34: 0 | L34: 0 | M34: 0 | N34: 0 | O34: 0 | P34: 0 | Q34: 0 | R34: 50 | S34: 86 | T34: 24 | U34: 0 | V34: 24 | W34: 0 | X34: -- | Y34: 0
A35: BAZIC Ruled Index Cards 3" X 5" 100 Count, White Flashcards, Ruled Lined Card for Learning Memory Reminder (100/Pack), 1-Pack | B35: FBA_516-EACH | C35: B0019IMFSW | D35: B0019IMFSW | E35: 0 | F35: 0 | G35: 72 | H35: 2 | I35: 72 | J35: 2 | K35: 0 | L35: 0 | M35: 0 | N35: 0 | O35: 0 | P35: 0 | Q35: 0 | R35: 155 | S35: 149 | T35: 39 | U35: 0 | V35: 39 | W35: 0 | X35: -- | Y35: 0
A36: BAZIC PRODUCTS Composition Notebook Wide Ruled - 100 Sheets, Assorted Color Marble Composition Notebook with Durable Cover, Non-Spiral for Journaling, School, Home, or Office, 4-Packs | B36: FBA_509-SET4 | C36: X003SC3FA5 | D36: B07S84C9SY | E36: 0 | F36: 0 | G36: 276 | H36: 23 | I36: 276 | J36: 23 | K36: 0 | L36: 0 | M36: 0 | N36: 0 | O36: 0 | P36: 0 | Q36: 0 | R36: 58 | S36: 161 | T36: 12 | U36: 0 | V36: 12 | W36: 0 | X36: -- | Y36: 0
A37: BAZIC Products Primary Journal Composition Book Blue Marble, 100 Sheet Writing Grades K- 2 Notebook Journal Comp Notebooks for Kindergarten Kids School, 1-Pack | B37: FBA_5087-EACH-1 | C37: X004F8SJVB | D37: B084GC6RYF | E37: 0 | F37: 0 | G37: 480 | H37: 10 | I37: 480 | J37: 10 | K37: 0 | L37: 0 | M37: 0 | N37: 0 | O37: 0 | P37: 0 | Q37: 0 | R37: 53 | S37: 67 | T37: 55 | U37: 0 | V37: 7 | W37: 48 | X37: 845.9 | Y37: 1
A38: BAZIC PRODUCTS Composition Notebook Wide Ruled - 100 Sheets, Black Marble Composition Notebook with Durable Cover, Non-Spiral for Journaling, School, Home, or Office, 6-Pack | B38: FBA_508-PACK6 | C38: X003SC1Y8F | D38: B0B8QRTPL6 | E38: 0 | F38: 0 | G38: 8 | H38: 1 | I38: 8 | J38: 1 | K38: 0 | L38: 0 | M38: 0 | N38: 0 | O38: 0 | P38: 0 | Q38: 0 | R38: 27 | S38: 151 | T38: 0 | U38: 0 | V38: 0 | W38: 0 | X38: 503.7 | Y38: 0
A39: BAZIC PRODUCTS Primary Journal Composition Book Marble, Primary Journal, Writing Journal, Notebooks for Kids, Drawing & Writing Notebook for Kindergarten School Use, Grades K-2, 100 Sheets, 6-Pack | B39: FBA_5053-SET6 | C39: X003UYGOUJ | D39: B0B8TMWY6F | E39: 0 | F39: 0 | G39: 1480 | H39: 185 | I39: 1480 | J39: 185 | K39: 0 | L39: 0 | M39: 0 | N39: 0 | O39: 0 | P39: 0 | Q39: 0 | R39: 143 | S39: 95 | T39: 4 | U39: 0 | V39: 3 | W39: 1 | X39: -- | Y39: 0
A40: BAZIC Products Sketch Pad, Spiral Sketchbook for Artists & Students, Drawing Pad with Thick Paper, Sketching & Drawing for Kids, Teens & Adults, 50 Sheets, 6" x 8", 1-Pack | B40: FBA_5043-EACH | C40: B00H9Z198Q | D40: B00H9Z198Q | E40: 0 | F40: 0 | G40: 336 | H40: 7 | I40: 336 | J40: 7 | K40: 0 | L40: 0 | M40: 0 | N40: 0 | O40: 0 | P40: 0 | Q40: 240 | R40: 160 | S40: 31 | T40: 138 | U40: 16 | V40: 18 | W40: 104 | X40: 130.2 | Y40: 0.71
A41: BAZIC Products Sketch Pad, Spiral Sketchbook for Artists & Students, Drawing Pad with Thick Paper, Sketching & Drawing for Teens & Adults, 50 Sheets, 6" X 8", 48-Pack | B41: FBA_5043-CASE | C41: B07XQML9YS | D41: B07XQML9YS | E41: 0 | F41: 0 | G41: 1 | H41: 1 | I41: 1 | J41: 1 | K41: 0 | L41: 0 | M41: 0 | N41: 0 | O41: 0 | P41: 0 | Q41: 1 | R41: 12 | S41: 113 | T41: 0 | U41: 0 | V41: 0 | W41: 0 | X41: 432.4 | Y41: 1
A42: BAZIC Products Rubber Bands, Assorted Size 1/2 Lbs. Made in USA, Elastic Stretchable Bands for Bank Paper Bills Money Dollars, Colors Sizes May Vary, 1-Pack | B42: FBA_465-EACH-1 | C42: X003T9Y59H | D42: B07T766984 | E42: 0 | F42: 0 | G42: 48 | H42: 1 | I42: 48 | J42: 1 | K42: 0 | L42: 0 | M42: 0 | N42: 0 | O42: 0 | P42: 0 | Q42: 0 | R42: 24 | S42: 53 | T42: 1 | U42: 0 | V42: 0 | W42: 1 | X42: 319 | Y42: 0
A43: BAZIC Products 3 Ring Binder - Purple, Economy View Binder with Clear Overlay Cover and Round Rings, Organizer for School Office Home Use, 1.5-inch Capacity Holds 280 Sheets Paper, 1-Pack | B43: FBA_4147-EACH | C43: X003SBSJBL | D43: B07Q8SQSQF | E43: 0 | F43: 0 | G43: 84 | H43: 7 | I43: 84 | J43: 7 | K43: 0 | L43: 0 | M43: 0 | N43: 0 | O43: 0 | P43: 0 | Q43: 0 | R43: 48 | S43: 84 | T43: 4 | U43: 0 | V43: 2 | W43: 2 | X43: 409.2 | Y43: 0
A44: BAZIC Products Tree Free Copy Paper - 8.5 X 11 Made From Sugarcane Fiber, Smooth Printer Paper for Daily Use, Reliable Copy & Printing Paper Ideal for Home, Office and School, 500/Ream | B44: FBA_41166-EACH-1 | C44: B09MDRGNCP | D44: B09MDRGNCP | E44: 0 | F44: 0 | G44: 0 | H44: 0 | I44: 0 | J44: 0 | K44: 0 | L44: 0 | M44: 0 | N44: 0 | O44: 0 | P44: 0 | Q44: 1 | R44: 83 | S44: 16 | T44: 26 | U44: 9 | V44: 4 | W44: 13 | X44: 94.3 | Y44: 1
A45: BAZIC Products 3 Ring Binder - Grey, Economy View Binder with Clear Overlay Cover and Round Rings, Organizer for School Office Home Use, 0.5 inch Capacity Holds 100 Sheets Paper, 12-Pack | B45: FBA_4101-CASE | C45: X0044RG6IB | D45: B07QF4V3CC | E45: 0 | F45: 0 | G45: 0 | H45: 0 | I45: 0 | J45: 0 | K45: 0 | L45: 0 | M45: 0 | N45: 0 | O45: 0 | P45: 0 | Q45: 1 | R45: 5 | S45: 35 | T45: 0 | U45: 0 | V45: 0 | W45: 0 | X45: 102 | Y45: 1
A46: BAZIC Products Key Tag Label Window, Assorted Color Tags, Plastic Key Holder Key Ring, Identifier Name Number Address Information Label Card (8/Pack), 1-Pack | B46: FBA_4003-EACH-1 | C46: X0040LGDTX | D46: B07TGDNG2G | E46: 0 | F46: 0 | G46: 24 | H46: 1 | I46: 24 | J46: 1 | K46: 0 | L46: 0 | M46: 0 | N46: 0 | O46: 0 | P46: 0 | Q46: 0 | R46: 63 | S46: 366 | T46: 2 | U46: 0 | V46: 0 | W46: 2 | X46: -- | Y46: 1
A47: BAZIC White Round Reinforcement Label (544/Pack) | B47: FBA_3810-EACH | C47: B003BOT5I0 | D47: B003BOT5I0 | E47: 0 | F47: 0 | G47: 576 | H47: 4 | I47: 576 | J47: 4 | K47: 0 | L47: 0 | M47: 0 | N47: 0 | O47: 0 | P47: 0 | Q47: 0 | R47: 230 | S47: 216 | T47: 4 | U47: 0 | V47: 4 | W47: 0 | X47: -- | Y47: 0
A48: BAZIC Manila File Folder 1/3 Cut Letter Size, Left Right Center Tabs Positions, for Organizing Filing Document Storage, Total 6-Count | B48: FBA_3103-EACH | C48: B003BSFCMY | D48: B003BSFCMY | E48: 0 | F48: 0 | G48: 288 | H48: 6 | I48: 288 | J48: 6 | K48: 0 | L48: 0 | M48: 0 | N48: 0 | O48: 0 | P48: 0 | Q48: 1 | R48: 270 | S48: 107 | T48: 54 | U48: 3 | V48: 2 | W48: 49 | X48: 284.8 | Y48: 1
A49: BAZIC PRODUCTS Geometry Set with Pencil Compass – Scale Ruler, HB Wood Pencil, Compass and Protractor Set for Students and Professionals, Ideal Use for Art and Drafting Tools, 24-Packs | B49: FBA_2807-SET4 | C49: X003SCFQOX | D49: B07RJZND6F | E49: 0 | F49: 0 | G49: 108 | H49: 3 | I49: 108 | J49: 3 | K49: 0 | L49: 0 | M49: 0 | N49: 0 | O49: 0 | P49: 0 | Q49: 0 | R49: 32 | S49: 74 | T49: 13 | U49: 12 | V49: 1 | W49: 0 | X49: 773.3 | Y49: 0
A50: BAZIC PRODUCTS White Chalk, Standard Size Blackboard Chalkboard Chalks, Great Game Activity for Kid Teacher School (20/Bucket) | B50: FBA_2403-EACH | C50: X0040DXZ3D | D50: B0BLRQNYFM | E50: 0 | F50: 0 | G50: 24 | H50: 1 | I50: 24 | J50: 1 | K50: 0 | L50: 0 | M50: 0 | N50: 0 | O50: 0 | P50: 0 | Q50: 0 | R50: 44 | S50: 156 | T50: 0 | U50: 0 | V50: 0 | W50: 0 | X50: 575.1 | Y50: 0
A51: BAZIC Products Mini Highlighter Pen Assorted Color, Chisel Tip Broad Fine Line Highlighters Coloring Marker (5/Pack), 1-Pack | B51: FBA_2306-EACH-1 | C51: B008ZHNN68 | D51: B008ZHNN68 | E51: 0 | F51: 0 | G51: 0 | H51: 0 | I51: 0 | J51: 0 | K51: 0 | L51: 0 | M51: 0 | N51: 0 | O51: 0 | P51: 0 | Q51: 6 | R51: 101 | S51: 8 | T51: 9 | U51: 3 | V51: 6 | W51: 0 | X51: 53 | Y51: 1
A52: BAZIC Products Pink Eraser Top, Latex-Free Pencil Top Erasers with Arrowhead Caps, Non-Toxic Erasers for Kids, Students, Teachers, Classroom, Art, Homework & School Supplies, 144/Pack, 1-Pack | B52: FBA_2236-EACH | C52: B08FF6RL8X | D52: B08FF6RL8X | E52: 0 | F52: 0 | G52: 264 | H52: 11 | I52: 264 | J52: 11 | K52: 0 | L52: 0 | M52: 0 | N52: 0 | O52: 0 | P52: 0 | Q52: 0 | R52: 36 | S52: 50 | T52: 14 | U52: 1 | V52: 10 | W52: 3 | X52: 571.5 | Y52: 0
A53: BAZIC Eraser Sets Eraser, Pink (2233) | B53: FBA_2233-EACH | C53: B07C3W3BXS | D53: B07C3W3BXS | E53: 0 | F53: 0 | G53: 216 | H53: 3 | I53: 216 | J53: 3 | K53: 0 | L53: 0 | M53: 0 | N53: 0 | O53: 0 | P53: 0 | Q53: 0 | R53: 232 | S53: 159 | T53: 1 | U53: 0 | V53: 0 | W53: 1 | X53: -- | Y53: 0
A54: BAZIC Products Erasers, Bright Color Oval Eraser (4/Pack) Latex Free, Large Size Block Erasers for Art Drawing School Office Teachers, 1-Pack | B54: FBA_2232-EACH | C54: X0044RLTCJ | D54: B00HZ0A98G | E54: 0 | F54: 0 | G54: 72 | H54: 1 | I54: 72 | J54: 1 | K54: 0 | L54: 0 | M54: 0 | N54: 0 | O54: 0 | P54: 0 | Q54: 0 | R54: 50 | S54: 366 | T54: 0 | U54: 0 | V54: 0 | W54: 0 | X54: -- | Y54: 0
A55: BAZIC Products Pink Eraser, Latex Free Bevel Block Erasers, Large Size for Classroom, Office, and Art Use, Smooth Pencil Correction for Writing, Sketching, & Daily Tasks, 4/Pack, 2-Pack | B55: FBA_2227-PACK2 | C55: X0042QSCSL | D55: B09BBP343Q | E55: 0 | F55: 0 | G55: 1584 | H55: 44 | I55: 1584 | J55: 44 | K55: 0 | L55: 0 | M55: 0 | N55: 0 | O55: 0 | P55: 0 | Q55: 0 | R55: 1000 | S55: 174 | T55: 6 | U55: 0 | V55: 6 | W55: 0 | X55: -- | Y55: 0
A56: BAZIC Products Erasers + Pencil Top Erasers Set (12/Pack), Block Bevel Erasers Neon Color, Arrowhead Caps Tops, Latex Free, for Art Drawing School, 1-Pack | B56: FBA_2225-EACH | C56: B001BO004K | D56: B001BO004K | E56: 0 | F56: 0 | G56: 144 | H56: 2 | I56: 144 | J56: 2 | K56: 0 | L56: 0 | M56: 0 | N56: 0 | O56: 0 | P56: 0 | Q56: 0 | R56: 19 | S56: 149 | T56: 0 | U56: 0 | V56: 0 | W56: 0 | X56: -- | Y56: 0
A57: BAZIC Neon Bevel Eraser (6/Pack) | B57: FBA_2207-EACH | C57: B001BO3JHA | D57: B001BO3JHA | E57: 0 | F57: 0 | G57: 288 | H57: 4 | I57: 288 | J57: 4 | K57: 0 | L57: 0 | M57: 0 | N57: 0 | O57: 0 | P57: 0 | Q57: 0 | R57: 11 | S57: 999 | T57: 0 | U57: 0 | V57: 0 | W57: 0 | X57: -- | Y57: 0
A58: BAZIC Products Pink Eraser Top, Latex-Free Pencil Top Erasers with Arrowhead Caps, Non-Toxic Erasers for Kids, Students, Teachers, Classroom, Art, Homework & School Supplies, 50/Pack, 1-Pack | B58: FBA_2205-EACH | C58: B003BNZVHK | D58: B003BNZVHK | E58: 0 | F58: 0 | G58: 144 | H58: 2 | I58: 144 | J58: 2 | K58: 0 | L58: 0 | M58: 0 | N58: 0 | O58: 0 | P58: 0 | Q58: 0 | R58: 58 | S58: 999 | T58: 1 | U58: 1 | V58: 0 | W58: 0 | X58: -- | Y58: 0
A59: BAZIC Products Neon Eraser Top, Latex-Free Pencil Top Erasers with Arrowhead Caps, Non-Toxic Erasers for Kids, Students, Teachers, Classroom, Art, Homework & School Supplies, 50/Pack, 2-Pack | B59: FBA_2204-PACK2 | C59: X003SBSJAH | D59: B09BBQNGN3 | E59: 0 | F59: 0 | G59: 900 | H59: 25 | I59: 900 | J59: 25 | K59: 0 | L59: 0 | M59: 0 | N59: 0 | O59: 0 | P59: 0 | Q59: 0 | R59: 104 | S59: 152 | T59: 1 | U59: 0 | V59: 0 | W59: 1 | X59: -- | Y59: 0
A60: BAZIC Products Neon Eraser Top, Latex-Free Pencil Top Erasers with Arrowhead Caps, Non-Toxic Erasers for Kids, Students, Teachers, Classroom, Art, Homework & School Supplies, 20/Pack, 2-Pack | B60: FBA_2202-PACK2 | C60: X003SBSJBB | D60: B09BBPZQBV | E60: 0 | F60: 0 | G60: 648 | H60: 9 | I60: 648 | J60: 9 | K60: 0 | L60: 0 | M60: 0 | N60: 0 | O60: 0 | P60: 0 | Q60: 0 | R60: 232 | S60: 153 | T60: 10 | U60: 0 | V60: 9 | W60: 1 | X60: -- | Y60: 0
A61: BAZIC Products 2 Pocket Paper Folder, Letter Size Document Organizer for School, Office, Business Use, Polka Dot Design Portfolio Folder for Homework, Reports & Forms, Assorted Colors, 6-Pack | B61: FBA_2172-SET6 | C61: X003SC97RF | D61: B07RX344Q6 | E61: 0 | F61: 0 | G61: 72 | H61: 9 | I61: 72 | J61: 9 | K61: 0 | L61: 0 | M61: 0 | N61: 0 | O61: 0 | P61: 0 | Q61: 16 | R61: 153 | S61: 111 | T61: 1 | U61: 0 | V61: 0 | W61: 1 | X61: 173.6 | Y61: 0.97
A62: BAZIC Products Loose Leaf Binder Ring 1", Assorted Color Steel Metal Rings for Flash Cards, Index Cards, Study Notes & Craft Organization, Binder Rings, Snap Rings Closure, 10-Count, 1-Pack | B62: FBA_212-EACH | C62: X003TJ1SWJ | D62: B07RLPFK92 | E62: 0 | F62: 0 | G62: 288 | H62: 2 | I62: 288 | J62: 2 | K62: 0 | L62: 0 | M62: 0 | N62: 0 | O62: 0 | P62: 0 | Q62: 0 | R62: 183 | S62: 267 | T62: 13 | U62: 0 | V62: 0 | W62: 13 | X62: -- | Y62: 1
A63: BAZIC Products Super Glue – Small Tube for Crafting, Fabric, Ceramics, Plastic & DIY Repairs, Fast-Drying Clear Glue for Home, School & Office, 6/Pack, 1-Pack | B63: FBA_2007-EACH | C63: B003BSF7ZG | D63: B003BSF7ZG | E63: 0 | F63: 0 | G63: 24 | H63: 1 | I63: 24 | J63: 1 | K63: 0 | L63: 0 | M63: 0 | N63: 0 | O63: 0 | P63: 0 | Q63: 0 | R63: 157 | S63: 160 | T63: 4 | U63: 2 | V63: 0 | W63: 2 | X63: 233.1 | Y63: 1
A64: BAZIC Products Single Use Super Glue – Mini Small Tube for Crafting, Fabric, Ceramics, Plastic & DIY Repairs, Fast-Drying Clear Glue for Home, School & Office, 6/Pack, 2-Packs | B64: FBA_2005-PACK2 | C64: X003TJ1YZ5 | D64: B08GXCMX5Z | E64: 0 | F64: 0 | G64: 72 | H64: 1 | I64: 72 | J64: 1 | K64: 0 | L64: 0 | M64: 0 | N64: 0 | O64: 0 | P64: 0 | Q64: 0 | R64: 20 | S64: 86 | T64: 4 | U64: 0 | V64: 0 | W64: 4 | X64: 341.1 | Y64: 0
A65: BAZIC PRODUCTS Mini Ballpoint Pen, 1.0 mm Bold Point, Black Ink, Smooth Writing Mini Pens with Compact and Key Chain Design, Ideal for Travel, Badge Reel, and Everyday Carry, 5/Pack, 4-Pack | B65: FBA_1753-PACK4 | C65: X0042U5H0N | D65: B09BDGVCHW | E65: 0 | F65: 0 | G65: 36 | H65: 1 | I65: 36 | J65: 1 | K65: 0 | L65: 0 | M65: 0 | N65: 0 | O65: 0 | P65: 0 | Q65: 0 | R65: 36 | S65: 54 | T65: 3 | U65: 0 | V65: 0 | W65: 3 | X65: 140.5 | Y65: 1
A66: BAZIC Products Collorelli Scented Glitter Color Gel Pen, Acid Free Smooth Writing for Drawing Coloring Greeting Card Art Christmas Gift (10/Pack), 1-Pack | B66: FBA_17084-EACH | C66: B094PM76L6 | D66: B094PM76L6 | E66: 0 | F66: 0 | G66: 0 | H66: 0 | I66: 0 | J66: 0 | K66: 0 | L66: 0 | M66: 0 | N66: 0 | O66: 0 | P66: 0 | Q66: 24 | R66: 0 | S66: 999 | T66: 0 | U66: 0 | V66: 0 | W66: 0 | X66: -- | Y66: 1
A67: BAZIC 12 Pastel Color Collorelli Gel Pen | B67: FBA_17083-EACH | C67: B07NDLQMM4 | D67: B07NDLQMM4 | E67: 0 | F67: 0 | G67: 48 | H67: 2 | I67: 48 | J67: 2 | K67: 0 | L67: 0 | M67: 0 | N67: 0 | O67: 0 | P67: 0 | Q67: 24 | R67: 3 | S67: 42 | T67: 3 | U67: 0 | V67: 3 | W67: 0 | X67: 489.6 | Y67: 1
A68: BAZIC PRODUCTS Pencil Grip – Assorted Color Soft Gel Pen Grip, Comfort Pencil Grip, Ergonomic Pen Grips for Toddler, Kids and Adults, 8/Pack, 2-Packs | B68: FBA_1502-SET2 | C68: X003BT3R3Z | D68: B084JMW3MJ | E68: 0 | F68: 0 | G68: 72 | H68: 1 | I68: 72 | J68: 1 | K68: 0 | L68: 0 | M68: 0 | N68: 0 | O68: 0 | P68: 0 | Q68: 72 | R68: 71 | S68: 64 | T68: 4 | U68: 2 | V68: 0 | W68: 2 | X68: 250.1 | Y68: 1
A69: BAZIC 100 Ct. 3" X 3" Yellow Stick On Notes | B69: 5104-EACH | C69: B01GORCP4G | D69: B01GORCP4G | E69: 0 | F69: 0 | G69: 48 | H69: 2 | I69: 48 | J69: 2 | K69: 0 | L69: 0 | M69: 0 | N69: 0 | O69: 0 | P69: 0 | Q69: 0 | R69: unavailable | S69: unavailable | T69: 0 | U69: unavailable | V69: unavailable | W69: unavailable | X69: -- | Y69: 0

Sheet FBA Inventory
A1: Country | B1: Product Name | C1: FNSKU | D1: Merchant SKU | E1: ASIN | F1: Condition | G1: Supplier | H1: Supplier part no. | I1: Currency code | J1: Price | K1: Sales last 30 days | L1: Units Sold Last 30 Days | M1: Total Units | N1: Inbound | O1: Available | P1: FC transfer | Q1: FC Processing | R1: Customer Order | S1: Unfulfillable | T1: Working | U1: Shipped | V1: Receiving | W1: Fulfilled by | X1: Total Days of Supply (including units from open shipments) | Y1: Days of Supply at Amazon Fulfillment Network | Z1: Alert | AA1: Recommended replenishment qty | AB1: Recommended ship date | AC1: Recommended action | AD1: Unit storage size
A2: US | B2: BAZIC PRODUCTS Spiral Notebook, Composition Book, 5" x 7" Poly Cover Spiral Notebook, College Ruled 100 Sheet Notebook for School, Office, & Home Use, Assorted Color, 6-Pack | C2: X003ENT3U9 | D2: FBA_5476-SET6 | E2: B0964KDHSP | F2: New | G2: BAZIC Products | I2: USD | J2: 15.49 | K2: 3739.21 | L2: 217 | M2: =O2+N2+P2+Q2 -> 183 | N2: 0 | O2: 0 | P2: 173 | Q2: 10 | R2: 10 | S2: 0 | T2: 0 | U2: 0 | V2: 0 | W2: Amazon | X2: 22 | Y2: 20 | AA2: 258 | AB2: 46086 | AC2: Create shipping plan | AD2: 0.0805 ft3
A3: US | B3: BAZIC Products Manila File Folders, 1/3-Cut Letter Size with Left, Right, and Center Tab Positions, Ideal for Organizing and Filing Documents, 12/Pack, 1-Pack | C3: B00ZPRYV0I | D3: FBA_3100-EACH | E3: B00ZPRYV0I | F3: New | G3: BAZIC Products | I3: USD | J3: 4.59 | K3: 3029.4 | L3: 660 | M3: =O3+N3+P3+Q3 -> 969 | N3: 864 | O3: 39 | P3: 51 | Q3: 15 | R3: 5 | S3: 1 | T3: 0 | U3: 864 | V3: 0 | W3: Amazon | X3: 48 | Y3: 47 | AA3: 240 | AB3: 46086 | AC3: Create shipping plan | AD3: 0.0331 ft3
A4: US | B4: BAZIC Products Tree Free Copy Paper - 8.5 X 11 Made From Sugarcane Fiber, Smooth Printer Paper for Daily Use, Reliable Copy & Printing Paper Ideal for Home, Office and School, 500/Ream | C4: B09MDRGNCP | D4: FBA_41166-EACH-1 | E4: B09MDRGNCP | F4: New | G4: BAZIC Products | I4: USD | J4: 14.39 | K4: 2129.72 | L4: 148 | M4: =O4+N4+P4+Q4 -> 102 | N4: 1 | O4: 83 | P4: 13 | Q4: 5 | R4: 9 | S4: 4 | T4: 0 | U4: 0 | V4: 1 | W4: Amazon | X4: 19 | Y4: 16 | AA4: 210 | AB4: 46086 | AC4: Create shipping plan | AD4: 0.123 ft3
A5: US | B5: BAZIC Products Glitter Glue Tube – 6 Assorted Classic Color, Non-Toxic Washable Glitter Glue for Art, Crafts, Paints, DIY, and Party Projects, 120ml/Pack, 1-Pack | C5: B01HTYG3LE | D5: FBA_3467-EACH-1 | E5: B01HTYG3LE | F5: New | G5: BAZIC Products | I5: USD | J5: 5.49 | K5: 2003.84 | L5: 350 | M5: =O5+N5+P5+Q5 -> 1072 | N5: 2 | O5: 979 | P5: 90 | Q5: 1 | R5: 8 | S5: 0 | T5: 0 | U5: 0 | V5: 2 | W5: Amazon | X5: 164 | Y5: 162 | AA5: 0 | AB5: none | AC5: No action required | AD5: 0.0131 ft3
A6: US | B6: BAZIC Products Sketch Pad, Spiral Sketchbook for Artists & Students, Drawing Pad with Thick Paper, Sketching & Drawing for Kids, Teens & Adults, 50 Sheets, 6" x 8", 1-Pack | C6: B00H9Z198Q | D6: FBA_5043-EACH | E6: B00H9Z198Q | F6: New | G6: BAZIC Products | I6: USD | J6: 3.89 | K6: 1962.23 | L6: 480 | M6: =O6+N6+P6+Q6 -> 522 | N6: 240 | O6: 160 | P6: 104 | Q6: 18 | R6: 16 | S6: 1 | T6: 0 | U6: 240 | V6: 0 | W6: Amazon | X6: 33 | Y6: 31 | AA6: 192 | AB6: 46086 | AC6: Create shipping plan | AD6: 0.0054 ft3
A7: US | B7: BAZIC PRODUCTS Receipts Book, Money Cash Rent Receipts for Landlords, Business & Offices, 2-Part Carbonless Forms, 50 Sets 7 1/2" x 2 3/4", White with Bound Wraparound Cover (50 Sets/Pack), 1-Pack | C7: B00IIN3K5I | D7: FBA_5074-EACH | E7: B00IIN3K5I | F7: New | G7: BAZIC Products | I7: USD | J7: 4 | K7: 1870.57 | L7: 479 | M7: =O7+N7+P7+Q7 -> 288 | N7: 288 | O7: 0 | P7: 0 | Q7: 0 | R7: 0 | S7: 1 | T7: 0 | U7: 288 | V7: 0 | W7: Amazon | X7: 20 | Y7: 20 | AA7: 768 | AB7: 46086 | AC7: Create shipping plan | AD7: 0.0046 ft3
A8: US | B8: BAZIC PRODUCTS Plastic Pencil Case, Multi Purpose Organizer & Supply Holder, Clear Box Design, Durable Plastic Storage for School, Office, Classroom & Craft Supplies, 24-Pack | C8: X003SCCXUD | D8: FBA_847-CASE | E8: B08QRLYMJ4 | F8: New | G8: BAZIC Products | I8: USD | J8: 54.79 | K8: 1725.75 | L8: 45 | M8: =O8+N8+P8+Q8 -> 22 | N8: 0 | O8: 18 | P8: 0 | Q8: 4 | R8: 8 | S8: 0 | T8: 0 | U8: 0 | V8: 0 | W8: Amazon | X8: 11 | Y8: 6 | Z8: low_stock | AA8: 43 | AB8: 46086 | AC8: Create shipping plan | AD8: 1.4967 ft3
A9: US | B9: BAZIC Products Trifold Poster Board – White Corrugated Cardboard Display Board for School Projects, Science Fairs, Photos, Charts, and Classroom Presentations, 36" X 48", 1-Pack | C9: X003SVW1PV | D9: FBA_5033-EACH | E9: B07SCL3C9Y | F9: New | G9: BAZIC Products | I9: USD | J9: 21.49 | K9: 1709.74 | L9: 97 | M9: =O9+N9+P9+Q9 -> 48 | N9: 48 | O9: 0 | P9: 0 | Q9: 0 | R9: 0 | S9: 2 | T9: 0 | U9: 48 | V9: 0 | W9: Amazon | X9: 32 | Y9: 32 | AA9: 120 | AB9: 46086 | AC9: Create shipping plan | AD9: 0.125 ft3
A10: US | B10: BAZIC Products 3 Ring Binder - Fuchsia, Economy View Binder with Clear Overlay Cover and Round Rings, Organizer for School Office Home Use, 1.5-inch Capacity Holds 280 Sheets Paper, 1-Pack | C10: X003L8UNND | D10: FBA_4146-EACH | E10: B07Q97RZJC | F10: New | G10: BAZIC Products | I10: USD | J10: 11.29 | K10: 1668.13 | L10: 216 | M10: =O10+N10+P10+Q10 -> 83 | N10: 0 | O10: 76 | P10: 3 | Q10: 4 | R10: 1 | S10: 3 | T10: 0 | U10: 0 | V10: 0 | W10: Amazon | X10: 32 | Y10: 28 | AA10: 24 | AB10: 46086 | AC10: Create shipping plan | AD10: 0.1439 ft3
A11: US | B11: BAZIC Staples Standard (26/6) 5000/Pack, Stapler Refill Standard Size Staple, Silver Colors, 1-Pack | C11: X003EGFQKR | D11: FBA_608-EACH | E11: B003BMWZ48 | F11: New | G11: BAZIC Products | I11: USD | J11: 5.29 | K11: 1655.13 | L11: 407 | M11: =O11+N11+P11+Q11 -> 453 | N11: 0 | O11: 424 | P11: 13 | Q11: 16 | R11: 21 | S11: 0 | T11: 0 | U11: 0 | V11: 0 | W11: Amazon | X11: 33 | Y11: 30 | AA11: 216 | AB11: 46086 | AC11: Create shipping plan | AD11: 0.0056 ft3
A12: US | B12: BAZIC Products Addition Flash Cards, Numbers Math Flashcards at School Home, Problem Solving (36/Pack), 24-Packs | C12: X0044R3MFV | D12: FBA_532-BOX | E12: B07XQGFLTT | F12: New | G12: BAZIC Products | I12: USD | J12: 42.59 | K12: 1586.15 | L12: 44 | M12: =O12+N12+P12+Q12 -> 0 | N12: 0 | O12: 0 | P12: 0 | Q12: 0 | R12: 0 | S12: 0 | T12: 0 | U12: 0 | V12: 0 | W12: Amazon | X12: 0 | Y12: 0 | Z12: out_of_stock | AA12: 107 | AB12: 46079 | AC12: Create shipping plan | AD12: 0.1797 ft3
A13: US | B13: BAZIC PRODUCTS Plastic Pencil Case, Ruler Length Large Utility Storage Box, Multi Purpose Organizer & Supply Holder, Clear Box Design, Ideal for School, Office & Craft Use, 12-Pack | C13: B093CS5SYX | D13: FBA_851-CASE | E13: B093CS5SYX | F13: New | G13: BAZIC Products | I13: USD | J13: 41.21 | K13: 1405.21 | L13: 41 | M13: =O13+N13+P13+Q13 -> 28 | N13: 0 | O13: 23 | P13: 0 | Q13: 5 | R13: 1 | S13: 0 | T13: 0 | U13: 0 | V13: 0 | W13: Amazon | X13: 29 | Y13: 22 | AA13: 9 | AB13: 46086 | AC13: Create shipping plan | AD13: 1.4998 ft3
A14: US | B14: BAZIC Products Poster Board, Multi Color Fluorescent, 11" X 14", Poster Board Paper, Colored Paper, Vision Board Poster, Ideal for Crafts, Signs, School Projects, Displays, 5/Pack, 1-Pack | C14: X004HP06TF | D14: FBA_5027-EACH-1 | E14: B00KO8DHVC | F14: New | G14: BAZIC Products | I14: USD | J14: 4.4 | K14: 1392.51 | L14: 349 | M14: =O14+N14+P14+Q14 -> 216 | N14: 0 | O14: 186 | P14: 20 | Q14: 10 | R14: 2 | S14: 0 | T14: 0 | U14: 0 | V14: 0 | W14: Amazon | X14: 14 | Y14: 13 | Z14: low_stock | AA14: 384 | AB14: 46086 | AC14: Create shipping plan | AD14: 0.0142 ft3
A15: US | B15: BAZIC Primary Journal Composition Book Marble, 100 Sheet Drawing & Writing Grades K- 2 Notebook Journal Comp Notebooks for Kindergarten School, 48-Pack | C15: X003SC3FBT | D15: FBA_5053-CASE-B | E15: B00275EBHE | F15: New | G15: BAZIC Products | I15: USD | J15: 84.39 | K15: 1350.24 | L15: 16 | M15: =O15+N15+P15+Q15 -> 99 | N15: 0 | O15: 94 | P15: 0 | Q15: 5 | R15: 12 | S15: 0 | T15: 0 | U15: 0 | V15: 0 | W15: Amazon | X15: 104 | Y15: 89 | AA15: 0 | AB15: none | AC15: No action required | AD15: 0.9092 ft3
A16: US | B16: BAZIC Products 3 Ring Binder - Green, Economy View Binder with Clear Overlay Cover and Round Rings, Organizer for School Office Home Use, 0.5-inch Capacity Holds 100 Sheets Paper, 12-Pack | C16: X003SC97OX | D16: FBA_4102-CASE | E16: B07QC4W9YJ | F16: New | G16: BAZIC Products | I16: USD | J16: 42.17 | K16: 1305.98 | L16: 36 | M16: =O16+N16+P16+Q16 -> 8 | N16: 0 | O16: 4 | P16: 3 | Q16: 1 | R16: 0 | S16: 3 | T16: 0 | U16: 0 | V16: 0 | W16: Amazon | X16: 12 | Y16: 11 | Z16: low_stock | AA16: 29 | AB16: 46086 | AC16: Create shipping plan | AD16: 0.4858 ft3
A17: US | B17: BAZIC Products Folding Lap Desk with Storage, Foldable Desk Collapsible Lap Table Laptop Tray, Portable Plastic Lapdesk for Drawing Writing Studying Eating, Assorted Colors, 3-Pack | C17: X004X833YB | D17: FBA_861-SET3 | E17: B0DJTQ229Z | F17: New | G17: unassigned | I17: USD | J17: 55.19 | K17: 1269.34 | L17: 23 | M17: =O17+N17+P17+Q17 -> 42 | N17: 6 | O17: 29 | P17: 3 | Q17: 4 | R17: 2 | S17: 0 | T17: 0 | U17: 6 | V17: 0 | W17: Amazon | X17: 62 | Y17: 53 | AA17: 0 | AB17: none | AC17: No action required | AD17: 0.2848 ft3
A18: US | B18: BAZIC Products Writing Pad 100 Sheets 6" x 9" – Writing Pad With Durable Lined Note Pads, Smooth Writing Paper, and Easy-tear Paper Pads; Compact Note Pads and Writing Pads for Office, School, or Home, 6-Pack [Unknown Binding] | C18: X003SFDOWB | D18: FBA_560-PACK6 | E18: B08FBQM8VF | F18: New | G18: BAZIC Products | I18: USD | J18: 18.5 | K18: 1119.61 | L18: 61 | M18: =O18+N18+P18+Q18 -> 78 | N18: 24 | O18: 50 | P18: 4 | Q18: 0 | R18: 1 | S18: 0 | T18: 0 | U18: 24 | V18: 0 | W18: Amazon | X18: 36 | Y18: 35 | AA18: 40 | AB18: 46086 | AC18: Create shipping plan | AD18: 0.0689 ft3
A19: US | B19: BAZIC Products Trifold Poster Board – White Corrugated Cardboard Display Board for school projects, science fairs, photos, charts, and classroom presentations, 28" x 40", 1-Pack | C19: X003SVW1MJ | D19: FBA_5086-EACH | E19: B07SBH958C | F19: New | G19: BAZIC Products | I19: USD | J19: 15.99 | K19: 1096.78 | L19: 60 | M19: =O19+N19+P19+Q19 -> 88 | N19: 60 | O19: 0 | P19: 28 | Q19: 0 | R19: 3 | S19: 0 | T19: 0 | U19: 60 | V19: 0 | W19: Amazon | X19: 47 | Y19: 45 | AA19: 0 | AB19: none | AC19: No action required | AD19: 0.162 ft3
A20: US | B20: BAZIC Products Pencil Grip – Assorted Color Soft Gel Pen Grip, Comfort Pencil Grip, Ergonomic Pen Grips for Toddler, Kids and Adults, 8/Pack, 1-Packs | C20: B002WFI620 | D20: FBA_1502-EACH | E20: B002WFI620 | F20: New | G20: BAZIC Products | I20: USD | J20: 4.05 | K20: 1096.68 | L20: 297 | M20: =O20+N20+P20+Q20 -> 1438 | N20: 1296 | O20: 0 | P20: 140 | Q20: 2 | R20: 4 | S20: 3 | T20: 0 | U20: 1296 | V20: 0 | W20: Amazon | X20: 188 | Y20: 187 | AA20: 0 | AB20: none | AC20: No action required | AD20: 0.0061 ft3
A21: US | B21: BAZIC PRODUCTS Metallic Colored Pencils – 12 Shimmering Shades & Pre Sharpened Colored Pencils, Ideal for Artists, Adults and Kids for Drawing & Coloring, 12/Pack, 1-Pack | C21: X0042TSMV5 | D21: FBA_735-EACH | E21: B0BKRCH9RQ | F21: New | G21: BAZIC Products | I21: USD | J21: 6.29 | K21: 1028.56 | L21: 163 | M21: =O21+N21+P21+Q21 -> 397 | N21: 2 | O21: 380 | P21: 3 | Q21: 12 | R21: 9 | S21: 0 | T21: 0 | U21: 0 | V21: 2 | W21: Amazon | X21: 90 | Y21: 84 | AA21: 0 | AB21: none | AC21: No action required | AD21: 0.0057 ft3
A22: US | B22: BAZIC PRODUCTS Mini Ballpoint Pen, 1.0 mm Bold Point, Black Ink, Smooth Writing Mini Pens with Compact and Key Chain Design, Ideal for Travel, Badge Reel, and Everyday Carry, 5/Pack, 1-Pack | C22: B003BLQHFM | D22: FBA_1753-EACH | E22: B003BLQHFM | F22: New | G22: BAZIC Products | I22: USD | J22: 4.79 | K22: 1013.39 | L22: 237 | M22: =O22+N22+P22+Q22 -> 458 | N22: 291 | O22: 19 | P22: 144 | Q22: 4 | R22: 12 | S22: 1 | T22: 0 | U22: 0 | V22: 291 | W22: Amazon | X22: 48 | Y22: 47 | AA22: 0 | AB22: none | AC22: No action required | AD22: 0.0067 ft3
A23: US | B23: BAZIC PRODUCTS Index Card Box 3"x5", Plastic Storage Case Holds 250 Cards, Multipurpose Index Card Holder Organizer for Flash Cards, Notes, Office & School Use, Semi-Clear, Assorted Colors, 6-Pack | C23: X003SC5KIP | D23: FBA_3125-SET6 | E23: B07RZ3BBSR | F23: New | G23: BAZIC Products | I23: USD | J23: 21.39 | K23: 1003.89 | L23: 70 | M23: =O23+N23+P23+Q23 -> 38 | N23: 36 | O23: 0 | P23: 1 | Q23: 1 | R23: 0 | S23: 0 | T23: 0 | U23: 36 | V23: 0 | W23: Amazon | X23: 20 | Y23: 19 | AA23: 84 | AB23: 46086 | AC23: Create shipping plan | AD23: 0.3179 ft3
A24: US | B24: BAZIC Products Glitter Glue Tube – 3 Assorted Metallic Colors, Non-Toxic Washable Glitter Glue for Arts, Crafts, DIY, and Party Projects, 6.76 oz/Pack, 3 Packs | C24: X0044R3MJH | D24: FBA_3459-A-SET3 | E24: B086334ZCX | F24: New | G24: BAZIC Products | I24: USD | J24: 14.79 | K24: 994.72 | L24: 71 | M24: =O24+N24+P24+Q24 -> 185 | N24: 0 | O24: 151 | P24: 9 | Q24: 25 | R24: 1 | S24: 0 | T24: 0 | U24: 0 | V24: 0 | W24: Amazon | X24: 103 | Y24: 87 | AA24: 0 | AB24: none | AC24: No action required | AD24: 0.0571 ft3
A25: US | B25: BAZIC Products Trifold Poster Board – White Corrugated Cardboard Display Board for School Projects, Science Fairs, Photos, Charts, and Classroom Presentations, 36" X 48", 1-pack | C25: X003SVW1N3 | D25: FBA_5034-EACH | E25: B07S6DCY9F | F25: New | G25: BAZIC Products | I25: USD | J25: 21.79 | K25: 988.61 | L25: 48 | M25: =O25+N25+P25+Q25 -> 32 | N25: 24 | O25: 0 | P25: 8 | Q25: 0 | R25: 16 | S25: 0 | T25: 0 | U25: 24 | V25: 0 | W25: Amazon | X25: 31 | Y25: 19 | AA25: 72 | AB25: 46086 | AC25: Create shipping plan | AD25: 0.1248 ft3
A26: US | B26: BAZIC Poster Board Display Rack Stackable 10-Slots, Art Drying Racks, Metal Steel Powder Coated, Assembled Size 29.5"x23"x16" (Boards Not Included) | C26: X0042U0GH7 | D26: FBA_20080-CASE | E26: B07SD8LDKN | F26: New | G26: BAZIC Products | I26: USD | J26: 243.35 | K26: 973.8 | L26: 4 | M26: =O26+N26+P26+Q26 -> 0 | N26: 0 | O26: 0 | P26: 0 | Q26: 0 | R26: 0 | S26: 0 | T26: 0 | U26: 0 | V26: 0 | W26: Amazon | X26: 0 | Y26: 0 | Z26: out_of_stock | AA26: 25 | AB26: 46079 | AC26: Create shipping plan | AD26: 2.6044 ft3
A27: US | B27: BAZIC Products Black Rubber Bands – Assorted Sizes, Heavy Duty Elastic Bands For Money, Office, School, Home Organization, Crafts, Durable Stretch Rubber Bands, 2 Oz (56.7 g), 1-Pack | C27: B09DJVP3DS | D27: FBA_6120-EACH | E27: B09DJVP3DS | F27: New | G27: BAZIC Products | I27: USD | J27: 4.75 | K27: 967.35 | L27: 198 | M27: =O27+N27+P27+Q27 -> 440 | N27: 146 | O27: 225 | P27: 69 | Q27: 0 | R27: 0 | S27: 0 | T27: 0 | U27: 144 | V27: 2 | W27: Amazon | X27: 83 | Y27: 83 | AA27: 0 | AB27: none | AC27: No action required | AD27: 0.0187 ft3
A28: US | B28: BAZIC Products Glitter Glue Tubes – 6 Assorted Neon Colors, Non-Toxic Washable Glitter Glue for Arts, Crafts, DIY, and Party Projects, 6.76 oz/Pack, 6 Packs | C28: X003UI8KTN | D28: FBA_3451-SET6 | E28: B08579RYRM | F28: New | G28: BAZIC Products | I28: USD | J28: 21.79 | K28: 946.79 | L28: 44 | M28: =O28+N28+P28+Q28 -> 57 | N28: 3 | O28: 44 | P28: 10 | Q28: 0 | R28: 7 | S28: 1 | T28: 0 | U28: 0 | V28: 3 | W28: Amazon | X28: 30 | Y28: 27 | AA28: 36 | AB28: 46086 | AC28: Create shipping plan | AD28: 0.1034 ft3
A29: US | B29: BAZIC Products Date Stamper with Black Ink Pads for Stamping, 12 Years of Adjustable Dates, Ideal for Office, Shipping, Receiving, Accounting, Expiration Date Stamp, Due Dates - 2 Pack | C29: X0042QSBIR | D29: FBA_6301-PACK2 | E29: B08P3T1TWJ | F29: New | G29: BAZIC Products | I29: USD | J29: 7.53 | K29: 942.87 | L29: 129 | M29: =O29+N29+P29+Q29 -> 257 | N29: 72 | O29: 39 | P29: 144 | Q29: 2 | R29: 2 | S29: 2 | T29: 0 | U29: 72 | V29: 0 | W29: Amazon | X29: 53 | Y29: 52 | AA29: 0 | AB29: none | AC29: No action required | AD29: 0.026 ft3
A30: US | B30: BAZIC Products Poster Board Glitter Frame Color - Assorted Glitter Color, Sparkling Frame Colored Poster Board Paper for Crafts, Decorations, & Vision Board Projects, 11” x 14”, 5/Pack, 1-Pack | C30: B07TCRK63W | D30: FBA_5414-EACH | E30: B07TCRK63W | F30: New | G30: BAZIC Products | I30: USD | J30: 4.19 | K30: 856.92 | L30: 189 | M30: =O30+N30+P30+Q30 -> 195 | N30: 96 | O30: 11 | P30: 86 | Q30: 2 | R30: 0 | S30: 2 | T30: 0 | U30: 48 | V30: 48 | W30: Amazon | X30: 32 | Y30: 32 | AA30: 192 | AB30: 46086 | AC30: Create shipping plan | AD30: 0.0366 ft3
A31: US | B31: BAZIC Products Mini Highlighter Pen Assorted Color, Chisel Tip Broad Fine Line Highlighters Coloring Marker (5/Pack), 1-Pack | C31: B008ZHNN68 | D31: FBA_2306-EACH-1 | E31: B008ZHNN68 | F31: New | G31: BAZIC Products | I31: USD | J31: 4.38 | K31: 804.5 | L31: 195 | M31: =O31+N31+P31+Q31 -> 107 | N31: 0 | O31: 101 | P31: 0 | Q31: 6 | R31: 3 | S31: 0 | T31: 0 | U31: 0 | V31: 0 | W31: Amazon | X31: 9 | Y31: 8 | Z31: low_stock | AA31: 744 | AB31: 46086 | AC31: Create shipping plan | AD31: 0.0069 ft3
A32: US | B32: BAZIC Products 3 Ring Binder - Green, Economy View Binder with Clear Overlay Cover and Round Rings, Organizer for School Office Home Use, 1-inch Capacity Holds 175 Sheets Paper, 12-Pack | C32: X003SC97NT | D32: FBA_4122-CASE | E32: B07QF46PKK | F32: New | G32: BAZIC Products | I32: USD | J32: 56.39 | K32: 664.9 | L32: 16 | M32: =O32+N32+P32+Q32 -> 1 | N32: 0 | O32: 0 | P32: 0 | Q32: 1 | R32: 2 | S32: 0 | T32: 0 | U32: 0 | V32: 0 | W32: Amazon | X32: 6 | Y32: 0 | Z32: out_of_stock | AA32: 41 | AB32: 46079 | AC32: Create shipping plan | AD32: 0.6052 ft3
A33: US | B33: BAZIC 1/3 Cut Letter Size Color File Folder (6/Pack) | C33: B001GE6ACG | D33: FBA_3109-EACH | E33: B001GE6ACG | F33: New | G33: BAZIC Products | I33: USD | J33: 4.8 | K33: 650.44 | L33: 152 | M33: =O33+N33+P33+Q33 -> 334 | N33: 240 | O33: 92 | P33: 0 | Q33: 2 | R33: 1 | S33: 0 | T33: 0 | U33: 240 | V33: 0 | W33: Amazon | X33: 87 | Y33: 86 | AA33: 48 | AB33: 46086 | AC33: Create shipping plan | AD33: 0.0283 ft3
A34: US | B34: BAZIC Products Washable Clear School Glue 5 Oz. (147 mL), Liquid Clear Glues Adhesive, for Making Slime Art Crafts at School Home Office, 1-Pack | C34: B075VXY8MQ | D34: FBA_2044-EACH | E34: B075VXY8MQ | F34: New | G34: BAZIC Products | I34: USD | J34: 5.59 | K34: 647.35 | L34: 118 | M34: =O34+N34+P34+Q34 -> 72 | N34: 0 | O34: 0 | P34: 68 | Q34: 4 | R34: 5 | S34: 0 | T34: 0 | U34: 0 | V34: 0 | W34: Amazon | X34: 17 | Y34: 15 | AA34: 0 | AB34: none | AC34: No action required | AD34: 0.0109 ft3
A35: US | B35: BAZIC PRODUCTS Primary Journal Composition Book Marble, Primary Journal, Writing Journal, Notebooks for Kids, Drawing & Writing Notebook for Kindergarten School Use, Grades K-2, 100 Sheets, 6-Pack | C35: X003UYGOUJ | D35: FBA_5053-SET6 | E35: B0B8TMWY6F | F35: New | G35: BAZIC Products | I35: USD | J35: 15.99 | K35: 637.8 | L35: 40 | M35: =O35+N35+P35+Q35 -> 147 | N35: 0 | O35: 143 | P35: 1 | Q35: 3 | R35: 0 | S35: 0 | T35: 0 | U35: 0 | V35: 0 | W35: Amazon | X35: 96 | Y35: 95 | AA35: 0 | AB35: none | AC35: No action required | AD35: 0.0929 ft3
A36: US | B36: BAZIC Products 3 Ring Binder - Red, Economy View Binder with Clear Overlay Cover and Round Rings, Organizer for School Office Home Use, 0.5-inch in Capacity Holds 100 Sheets Paper, 1-Pack | C36: X003SC97WP | D36: FBA_4103-EACH | E36: B07Q8ZFP5P | F36: New | G36: BAZIC Products | I36: USD | J36: 8.59 | K36: 633.97 | L36: 93 | M36: =O36+N36+P36+Q36 -> 185 | N36: 0 | O36: 176 | P36: 1 | Q36: 8 | R36: 0 | S36: 1 | T36: 0 | U36: 0 | V36: 0 | W36: Amazon | X36: 117 | Y36: 112 | AA36: 0 | AB36: none | AC36: No action required | AD36: 0.0828 ft3
A37: US | B37: BAZIC Products 2 Pocket Paper Folder, Letter Size Document Organizer for School, Office, Business Use, Polka Dot Design Portfolio Folder for Homework, Reports & Forms, Assorted Colors, 6-Pack | C37: X003SC97RF | D37: FBA_2172-SET6 | E37: B07RX344Q6 | F37: New | G37: BAZIC Products | I37: USD | J37: 9.99 | K37: 629.34 | L37: 64 | M37: =O37+N37+P37+Q37 -> 170 | N37: 16 | O37: 153 | P37: 1 | Q37: 0 | R37: 0 | S37: 0 | T37: 0 | U37: 16 | V37: 0 | W37: Amazon | X37: 111 | Y37: 111 | AA37: 0 | AB37: none | AC37: No action required | AD37: 0.0453 ft3
A38: US | B38: BAZIC Products Letter Stencil Set – Alphabet, Number and Signs Kit, Reusable for Painting, Fabric, and Crafts, Plastic Stencils in Sizes 8, 10, 20, and 30 mm, 4/Pack, 1-Pack | C38: B00CDB9FSW | D38: FBA_302-EACH | E38: B00CDB9FSW | F38: New | G38: BAZIC Products | I38: USD | J38: 4.89 | K38: 621.03 | L38: 127 | M38: =O38+N38+P38+Q38 -> 110 | N38: 1 | O38: 10 | P38: 96 | Q38: 3 | R38: 1 | S38: 0 | T38: 0 | U38: 0 | V38: 1 | W38: Amazon | X38: 24 | Y38: 23 | AA38: 120 | AB38: 46086 | AC38: Create shipping plan | AD38: 0.0405 ft3
A39: US | B39: BAZIC Products Key Tag Label Window, Assorted Color Tags, Plastic Key Holder Key Ring, Identifier Name Number Address Information Label Card (6/Pack), 1-Pack | C39: B07S2TFVRK | D39: FBA_4004-EACH | E39: B07S2TFVRK | F39: New | G39: BAZIC Products | I39: USD | J39: 3.89 | K39: 618.86 | L39: 157 | M39: =O39+N39+P39+Q39 -> 302 | N39: 192 | O39: 105 | P39: 1 | Q39: 4 | R39: 7 | S39: 1 | T39: 0 | U39: 192 | V39: 0 | W39: Amazon | X39: 63 | Y39: 61 | AA39: 192 | AB39: 46086 | AC39: Create shipping plan | AD39: 0.0101 ft3
A40: US | B40: BAZIC Products Writing Pad 100 Sheets 6" X 9", Lined Ruled Memo Writing Notebook, Easy Tear Note Paper for Office School Home, 3-Pack | C40: X003SLYPRN | D40: FBA_560-PACK3-B | E40: B07S96S8LT | F40: New | G40: BAZIC Products | I40: USD | J40: 11.89 | K40: 593.41 | L40: 49 | M40: =O40+N40+P40+Q40 -> 131 | N40: 80 | O40: 43 | P40: 4 | Q40: 4 | R40: 1 | S40: 0 | T40: 0 | U40: 48 | V40: 32 | W40: Amazon | X40: 80 | Y40: 77 | AA40: 0 | AB40: none | AC40: No action required | AD40: 0.0421 ft3
A41: US | B41: BAZIC Dime Coin Wrappers Rolls, Made in USA, Durable Preformed Paper Coins Tubes (36/Pack), 1-Pack | C41: B0019IKY5I | D41: FBA_5013-EACH | E41: B0019IKY5I | F41: New | G41: BAZIC Products | I41: USD | J41: 7.79 | K41: 587.62 | L41: 78 | M41: =O41+N41+P41+Q41 -> 201 | N41: 100 | O41: 2 | P41: 98 | Q41: 1 | R41: 0 | S41: 0 | T41: 0 | U41: 100 | V41: 0 | W41: Amazon | X41: 83 | Y41: 83 | AA41: 0 | AB41: none | AC41: No action required | AD41: 0.1369 ft3
A42: US | B42: BAZIC Products Plastic Envelopes with Zipper – Durable Clear Poly Envelopes, Transparent Folder for Documents, Home, Office or School, Letter Size or A4 Folder, 4-Pack | C42: X003Y722CV | D42: FBA_3187-PACK4 | E42: B08G3XTB2Z | F42: New | G42: BAZIC Products | I42: USD | J42: 7.99 | K42: 562.85 | L42: 71 | M42: =O42+N42+P42+Q42 -> 61 | N42: 0 | O42: 59 | P42: 2 | Q42: 0 | R42: 3 | S42: 0 | T42: 0 | U42: 0 | V42: 0 | W42: Amazon | X42: 23 | Y42: 22 | AA42: 120 | AB42: 46086 | AC42: Create shipping plan | AD42: 0.0546 ft3
A43: US | B43: BAZIC Products 3 Ring Binder, Clear View Soft Cover Notebook, Durable Poly Organizer for School & Office Use, 0.5 in Capacity Holds 100 Sheets, Assorted Colors, 6-Pack | C43: X003L8Z45Z | D43: FBA_3130-SET6 | E43: B07QC4LBSK | F43: New | G43: BAZIC Products | I43: USD | J43: 23.85 | K43: 558.36 | L43: 26 | M43: =O43+N43+P43+Q43 -> 258 | N43: 184 | O43: 0 | P43: 74 | Q43: 0 | R43: 1 | S43: 0 | T43: 0 | U43: 184 | V43: 0 | W43: Amazon | X43: 190 | Y43: 189 | AA43: 0 | AB43: none | AC43: No action required | AD43: 0.1335 ft3
A44: US | B44: BAZIC Products Desktop Stapler Standard (26/6), 20 Sheets Bright Color Desktop Staplers for Home Office School, 6-Pack | C44: X0044RS1QV | D44: FBA_622-SET6 | E44: B07SFZY4T8 | F44: New | G44: BAZIC Products | I44: USD | J44: 18.48 | K44: 554.4 | L44: 30 | M44: =O44+N44+P44+Q44 -> 11 | N44: 8 | O44: 1 | P44: 2 | Q44: 0 | R44: 1 | S44: 0 | T44: 0 | U44: 8 | V44: 0 | W44: Amazon | X44: 16 | Y44: 15 | AA44: 24 | AB44: 46086 | AC44: Create shipping plan | AD44: 0.024 ft3
A45: US | B45: BAZIC Products 3 Ring Binder - Red, Economy View Binder with Clear Overlay Cover and Round Rings, Organizer for School Office Home Use, 1.5-inch Capacity Holds 250 Sheets Paper, 12-Pack | C45: X004KT3ZH3 | D45: FBA_4143-CASE | E45: B07QD3GHFT | F45: New | G45: BAZIC Products | I45: USD | J45: 55.89 | K45: 536.79 | L45: 11 | M45: =O45+N45+P45+Q45 -> 12 | N45: 0 | O45: 11 | P45: 0 | Q45: 1 | R45: 0 | S45: 0 | T45: 0 | U45: 0 | V45: 0 | W45: Amazon | X45: 65 | Y45: 60 | AA45: 0 | AB45: none | AC45: No action required | AD45: 0.625 ft3
A46: US | B46: BAZIC Products Expanding File Folder 13 Pockets, Coupon Size Plastic File Folders w/Color Tabs Pocket, Home Office Supplies, Check Bills Receipts Organizer, 4-Pack | C46: X003Y793Z5 | D46: FBA_3179-SET4 | E46: B08CYC1P9N | F46: New | G46: BAZIC Products | I46: USD | J46: 19.89 | K46: 525.68 | L46: 28 | M46: =O46+N46+P46+Q46 -> 75 | N46: 54 | O46: 1 | P46: 20 | Q46: 0 | R46: 3 | S46: 1 | T46: 0 | U46: 54 | V46: 0 | W46: Amazon | X46: 61 | Y46: 59 | AA46: 0 | AB46: none | AC46: No action required | AD46: 0.2512 ft3
A47: US | B47: BAZIC Loose Leaf Binder Ring 1", Book Rings Binder Rings, Nickel Plated Steel Metal Ring for Flash Cards, Index Card, Keychain (12/Pack), 1-Pack | C47: B0019IOEQ8 | D47: FBA_211-EACH-1 | E47: B0019IOEQ8 | F47: New | G47: BAZIC Products | I47: USD | J47: 5.89 | K47: 517.33 | L47: 107 | M47: =O47+N47+P47+Q47 -> 530 | N47: 432 | O47: 0 | P47: 98 | Q47: 0 | R47: 1 | S47: 1 | T47: 0 | U47: 432 | V47: 0 | W47: Amazon | X47: 216 | Y47: 215 | AA47: 0 | AB47: none | AC47: No action required | AD47: 0.008 ft3
A48: US | B48: BAZIC Products Trifold Poster Board – White Corrugated Cardboard Display Board for School Projects, Science Fairs, Photos, Charts, and Classroom Presentations, 36" X 48", 2-Pack | C48: X003S7ZA5X | D48: FBA_5033-PACK2 | E48: B08DHSRY9P | F48: New | G48: BAZIC Products | I48: USD | J48: 28.19 | K48: 508.75 | L48: 24 | M48: =O48+N48+P48+Q48 -> 11 | N48: 0 | O48: 0 | P48: 11 | Q48: 0 | R48: 1 | S48: 0 | T48: 0 | U48: 0 | V48: 0 | W48: Amazon | X48: 14 | Y48: 13 | Z48: low_stock | AA48: 12 | AB48: 46082 | AC48: Create shipping plan | AD48: 0.3 ft3
A49: US | B49: BAZIC Products Book Wrap - Clear Book Cover Self Adhesive Book Protector for Book Covers for Paperbacks, Plastic Cover for Books, Clear Contact Paper Peel and Stick, 17.5" x 1.5 Yard, 1-Roll | C49: B076F13SG5 | D49: FBA_2901-EACH | E49: B076F13SG5 | F49: New | G49: BAZIC Products | I49: USD | J49: 5.19 | K49: 507.16 | L49: 99 | M49: =O49+N49+P49+Q49 -> 629 | N49: 1 | O49: 260 | P49: 351 | Q49: 17 | R49: 2 | S49: 2 | T49: 0 | U49: 0 | V49: 1 | W49: Amazon | X49: 150 | Y49: 146 | AA49: 0 | AB49: none | AC49: No action required | AD49: 0.0162 ft3
A50: US | B50: BAZIC Products Penny Coin Wrappers – Durable Preformed Paper Tube, Sleeves for Coin Sorter and Holder, 36/Pack, 2 Packs | C50: B0127E8W0Q | D50: FBA_5011-PACK2 | E50: B0127E8W0Q | F50: New | G50: BAZIC Products | I50: USD | J50: 9.89 | K50: 504.39 | L50: 51 | M50: =O50+N50+P50+Q50 -> 33 | N50: 0 | O50: 0 | P50: 32 | Q50: 1 | R50: 8 | S50: 0 | T50: 0 | U50: 0 | V50: 0 | W50: Amazon | X50: 15 | Y50: 12 | Z50: low_stock | AA50: 175 | AB50: 46086 | AC50: Create shipping plan | AD50: 0.2418 ft3
A51: US | B51: BAZIC Products 6.5" Paper Edge Scissor Set – Assorted Color, Decorative Edge Scissors, Ideal Use for Home, School, DIY Projects, Scrapbooking, and Crafts, 6-Pack, 1-Pack | C51: X0040DLEAJ | D51: FBA_4401-SET6 | E51: B07SFT8ZG7 | F51: New | G51: BAZIC Products | I51: USD | J51: 12 | K51: 494.7 | L51: 41 | M51: =O51+N51+P51+Q51 -> 76 | N51: 72 | O51: 4 | P51: 0 | Q51: 0 | R51: 0 | S51: 1 | T51: 0 | U51: 72 | V51: 0 | W51: Amazon | X51: 70 | Y51: 70 | AA51: 0 | AB51: none | AC51: No action required | AD51: 0.0665 ft3
A52: US | B52: BAZIC Products Plastic File Folder Case w/Handle, Letter Size File Folders Wallet, Black Color, Portable Paper Documents Organizer, Office Supplies, 1-Pack | C52: X003ZH1VNB | D52: FBA_3124-EACH | E52: B08CYCJ3B6 | F52: New | G52: BAZIC Products | I52: USD | J52: 9.89 | K52: 494.5 | L52: 50 | M52: =O52+N52+P52+Q52 -> 98 | N52: 96 | O52: 0 | P52: 1 | Q52: 1 | R52: 1 | S52: 0 | T52: 0 | U52: 96 | V52: 0 | W52: Amazon | X52: 59 | Y52: 57 | AA52: 0 | AB52: none | AC52: No action required | AD52: 0.1724 ft3
A53: US | B53: BAZIC Products Plastic Pencil Case Utility Storage Box, Clear Color, Multi Purpose Organizer for Pens Pencils, 24-Pack | C53: X003SCIA3H | D53: FBA_840-CASE | E53: B07XQNRXHD | F53: New | G53: BAZIC Products | I53: USD | J53: 63.59 | K53: 489.61 | L53: 11 | M53: =O53+N53+P53+Q53 -> 54 | N53: 0 | O53: 54 | P53: 0 | Q53: 0 | R53: 0 | S53: 0 | T53: 0 | U53: 0 | V53: 0 | W53: Amazon | X53: 84 | Y53: 84 | AA53: 0 | AB53: none | AC53: No action required | AD53: 1.9166 ft3
A54: US | B54: BAZIC Push Pins, Gold Metallic Flat Head Steel Point Thumb Tacks Pin for Cork Bulletin Board Map Posters Picture Office School (200/pack), 1-Pack | C54: B003BUJXSQ | D54: FBA_229-EACH | E54: B003BUJXSQ | F54: New | G54: BAZIC Products | I54: USD | J54: 4.79 | K54: 483.79 | L54: 101 | M54: =O54+N54+P54+Q54 -> 165 | N54: 2 | O54: 148 | P54: 14 | Q54: 1 | R54: 0 | S54: 0 | T54: 0 | U54: 0 | V54: 2 | W54: Amazon | X54: 52 | Y54: 52 | AA54: 24 | AB54: 46086 | AC54: Create shipping plan | AD54: 0.0044 ft3
A55: US | B55: BAZIC PRODUCTS Plastic Pencil Case, Multi Purpose Organizer & Supply Holder, Clear Box Design, Durable Plastic Storage for School, Office, Classroom & Craft Supplies, 4-Pack | C55: X003SCAA3F | D55: FBA_847-PACK4 | E55: B08QR8VLQ6 | F55: New | G55: BAZIC Products | I55: USD | J55: 14.29 | K55: 481.77 | L55: 42 | M55: =O55+N55+P55+Q55 -> 16 | N55: 0 | O55: 14 | P55: 1 | Q55: 1 | R55: 1 | S55: 1 | T55: 0 | U55: 0 | V55: 0 | W55: Amazon | X55: 13 | Y55: 12 | Z55: low_stock | AA55: 36 | AB55: 46086 | AC55: Create shipping plan | AD55: 0.2078 ft3
A56: US | B56: BAZIC Products Wooden Dowel Rods Wood Sticks, 3/8" x 12" Round Natural Color Hardwood Stick, Unfinished Wood for Crafts Lollipops Cake Support (6/Pack), 1-Pack | C56: B09DK3BKGB | D56: FBA_6810-EACH | E56: B09DK3BKGB | F56: New | G56: BAZIC Products | I56: USD | J56: 4.89 | K56: 469.21 | L56: 102 | M56: =O56+N56+P56+Q56 -> 99 | N56: 97 | O56: 0 | P56: 1 | Q56: 1 | R56: 1 | S56: 0 | T56: 0 | U56: 96 | V56: 1 | W56: Amazon | X56: 28 | Y56: 28 | AA56: 120 | AB56: 46085 | AC56: Create shipping plan | AD56: 0.0067 ft3
A57: US | B57: BAZIC Products Mini Stapler w/500 Staples, Standard (26/6) Built-in Staple Remover, Soft Grip 12 Sheets, Portable Small Staplers for Home Office School, 6-Pack | C57: X0044RJ647 | D57: FBA_601-SET6 | E57: B07SGY8JRM | F57: New | G57: BAZIC Products | I57: USD | J57: 16.79 | K57: 464.93 | L57: 28 | M57: =O57+N57+P57+Q57 -> 37 | N57: 13 | O57: 22 | P57: 1 | Q57: 1 | R57: 3 | S57: 0 | T57: 0 | U57: 12 | V57: 1 | W57: Amazon | X57: 48 | Y57: 42 | AA57: 20 | AB57: 46086 | AC57: Create shipping plan | AD57: 0.017 ft3
A58: US | B58: BAZIC PRODUCTS Wide Ruled 1-Subject Notebook, Non-Spiral Composition Style, Easy-Tear Wireless Pages, 3-Hole Punched, 80 Sheets, Assorted Colors, for School, Office & Home, 24-Pack | C58: X003SC980V | D58: FBA_582-CASE | E58: B07XQL67K5 | F58: New | G58: BAZIC Products | I58: USD | J58: 49.89 | K58: 462.39 | L58: 11 | M58: =O58+N58+P58+Q58 -> 5 | N58: 0 | O58: 2 | P58: 0 | Q58: 3 | R58: 0 | S58: 0 | T58: 0 | U58: 0 | V58: 0 | W58: Amazon | X58: 14 | Y58: 6 | Z58: low_stock | AA58: 23 | AB58: 46086 | AC58: Create shipping plan | AD58: 0.3837 ft3
A59: US | B59: BAZIC Products Rubber Bands – Assorted Color & Sizes, Heavy Duty Elastic Bands For Money, Office, School, Home Organization, Crafts, Durable Stretch Rubber Bands, 2 Oz (56.70 g), 1-Pack | C59: X002GASSMF | D59: FBA_6110-EACH | E59: B07SC668W8 | F59: New | G59: BAZIC Products | I59: USD | J59: 5.29 | K59: 461.79 | L59: 87 | M59: =O59+N59+P59+Q59 -> 205 | N59: 1 | O59: 194 | P59: 8 | Q59: 2 | R59: 1 | S59: 0 | T59: 0 | U59: 0 | V59: 1 | W59: Amazon | X59: 49 | Y59: 48 | AA59: 0 | AB59: none | AC59: No action required | AD59: 0.0215 ft3
A60: US | B60: BAZIC Products Paid Self-Inking Stamp with Red Ink for Office, Business, and Documents, Easy Refillable Pad, Crisp & Clear Impressions, 1-Pack | C60: B08P3WZTXG | D60: FBA_6303-EACH | E60: B08P3WZTXG | F60: New | G60: BAZIC Products | I60: USD | J60: 5.58 | K60: 454.33 | L60: 76 | M60: =O60+N60+P60+Q60 -> 189 | N60: 0 | O60: 43 | P60: 141 | Q60: 5 | R60: 6 | S60: 2 | T60: 0 | U60: 0 | V60: 0 | W60: Amazon | X60: 49 | Y60: 47 | AA60: 0 | AB60: none | AC60: No action required | AD60: 0.0103 ft3
A61: US | B61: BAZIC Colored (12 Pcs) + White (12 Pcs) Chalk + Premium Chalkboard Eraser Bundle, Non-Toxic Kids Art Office Classroom Store Home, 1-Pack | C61: B003BUI01W | D61: FBA_2402-EACH | E61: B003BUI01W | F61: New | G61: BAZIC Products | I61: USD | J61: 5.52 | K61: 445.93 | L61: 82 | M61: =O61+N61+P61+Q61 -> 734 | N61: 0 | O61: 109 | P61: 624 | Q61: 1 | R61: 5 | S61: 0 | T61: 0 | U61: 0 | V61: 0 | W61: Amazon | X61: 246 | Y61: 244 | AA61: 0 | AB61: none | AC61: No action required | AD61: 0.0444 ft3
A62: US | B62: BAZIC Felt Chalkboard Eraser, Wood Blackboard Eraser Cleaner Dustless, Teacher Kids Office Classroom, 1-Pack | C62: B002URU9G6 | D62: FBA_6003-EACH | E62: B002URU9G6 | F62: New | G62: BAZIC Products | I62: USD | J62: 5.49 | K62: 444.69 | L62: 81 | M62: =O62+N62+P62+Q62 -> 155 | N62: 0 | O62: 149 | P62: 4 | Q62: 2 | R62: 1 | S62: 1 | T62: 0 | U62: 0 | V62: 0 | W62: Amazon | X62: 77 | Y62: 75 | AA62: 24 | AB62: 46086 | AC62: Create shipping plan | AD62: 0.0136 ft3
A63: US | B63: BAZIC Products 3 Ring Binder 1/2" Economy View Binders Organizer - Purple, Round Ring, Hold 100 Sheets Paper, for School Office Home, 1-Count | C63: X003L8W44J | D63: FBA_4107-EACH | E63: B07Q84RJLP | F63: New | G63: BAZIC Products | I63: USD | J63: 9.09 | K63: 432.96 | L63: 49 | M63: =O63+N63+P63+Q63 -> 104 | N63: 0 | O63: 39 | P63: 62 | Q63: 3 | R63: 4 | S63: 0 | T63: 0 | U63: 0 | V63: 0 | W63: Amazon | X63: 33 | Y63: 31 | AA63: 72 | AB63: 46086 | AC63: Create shipping plan | AD63: 0.049 ft3
A64: US | B64: BAZIC Products Quarter Coin Wrappers – Durable Preformed Paper Tube, Sleeves for Coin Sorter and Holder, 36/Pack, 4 Packs | C64: X003Y77WNF | D64: FBA_5014-PACK4 | E64: B0BG9KF2MB | F64: New | G64: BAZIC Products | I64: USD | J64: 18.15 | K64: 419.98 | L64: 24 | M64: =O64+N64+P64+Q64 -> 58 | N64: 44 | O64: 13 | P64: 0 | Q64: 1 | R64: 0 | S64: 1 | T64: 0 | U64: 44 | V64: 0 | W64: Amazon | X64: 56 | Y64: 55 | AA64: 11 | AB64: 46085 | AC64: Create shipping plan | AD64: 0.6771 ft3
A65: US | B65: BAZIC Products Slider Pencil Case, Utility Storage Box Snap Closure, Bright Color Multi Purpose Organizer, 6-Pack | C65: X0042UE50L | D65: FBA_812-SET6 | E65: B07RCM1LXW | F65: New | G65: BAZIC Products | I65: USD | J65: 13.99 | K65: 418.89 | L65: 39 | M65: =O65+N65+P65+Q65 -> 1 | N65: 0 | O65: 1 | P65: 0 | Q65: 0 | R65: 6 | S65: 0 | T65: 0 | U65: 0 | V65: 0 | W65: Amazon | X65: 7 | Y65: 0 | Z65: low_stock | AA65: 84 | AB65: 46085 | AC65: Create shipping plan | AD65: 0.1343 ft3
A66: US | B66: BAZIC Products Quarter Coin Wrappers – Durable Preformed Paper Tube, Sleeves for Coin Sorter and Holder, 36/Pack, 2 Packs | C66: X003SC97RP | D66: FBA_5014-PACK2 | E66: B08DF97S7L | F66: New | G66: BAZIC Products | I66: USD | J66: 10.8 | K66: 416.88 | L66: 39 | M66: =O66+N66+P66+Q66 -> 154 | N66: 154 | O66: 0 | P66: 0 | Q66: 0 | R66: 1 | S66: 0 | T66: 0 | U66: 154 | V66: 0 | W66: Amazon | X66: 74 | Y66: 74 | AA66: 22 | AB66: 46084 | AC66: Create shipping plan | AD66: 0.3332 ft3
A67: US | B67: BAZIC Products Wooden Ruler 12" (30cm), Singel Metal Edge, Inches Centimeter Metric Measuring Drafting Rulers, for Students School Supplies (3/Pack), 2-Packs | C67: X0044RLTFB | D67: FBA_306-PACK2 | E67: B07S9118WX | F67: New | G67: BAZIC Products | I67: USD | J67: 5.69 | K67: 412.34 | L67: 86 | M67: =O67+N67+P67+Q67 -> 86 | N67: 0 | O67: 75 | P67: 9 | Q67: 2 | R67: 0 | S67: 1 | T67: 0 | U67: 0 | V67: 0 | W67: Amazon | X67: 39 | Y67: 38 | AA67: 48 | AB67: 46086 | AC67: Create shipping plan | AD67: 0.0205 ft3
A68: US | B68: BAZIC PRODUCTS Pencil Pouch for 3 Ring Binder, Zippered Mesh Window Pencil Case with Reinforced Grommets, Durable Binder Organizer for School Supplies or Office Supplies Storage, 2-Pack | C68: X0039GZAX5 | D68: FBA_808-PACK2 | E68: B09GD5961M | F68: New | G68: BAZIC Products | I68: USD | J68: 6.49 | K68: 401.64 | L68: 102 | M68: =O68+N68+P68+Q68 -> 689 | N68: 0 | O68: 670 | P68: 17 | Q68: 2 | R68: 1 | S68: 0 | T68: 0 | U68: 0 | V68: 0 | W68: Amazon | X68: 365+ | Y68: 365+ | AA68: 0 | AB68: none | AC68: No action required | AD68: 0.0361 ft3
A69: US | B69: BAZIC Products Staples Standard (26/6) Metallic Color 3000/Pack, Stapler Refill Standard Size Staple, Assorted Colors, 2-Packs | C69: X0044R3MO7 | D69: FBA_609-PACK2 | E69: B09C2RFDFH | F69: New | G69: BAZIC Products | I69: USD | J69: 8.69 | K69: 401.17 | L69: 47 | M69: =O69+N69+P69+Q69 -> 36 | N69: 0 | O69: 0 | P69: 34 | Q69: 2 | R69: 1 | S69: 0 | T69: 0 | U69: 0 | V69: 0 | W69: Amazon | X69: 15 | Y69: 14 | AA69: 120 | AB69: 46086 | AC69: Create shipping plan | AD69: 0.007 ft3
A70: US | B70: BAZIC #2B Premium Wood Pencil, Blue, 12 Per Pack (760-24P) | C70: B0019ILQ3M | D70: FBA_760-EACH-1 | E70: B0019ILQ3M | F70: New | G70: BAZIC Products | I70: USD | J70: 4.67 | K70: 400.33 | L70: 88 | M70: =O70+N70+P70+Q70 -> 47 | N70: 4 | O70: 39 | P70: 1 | Q70: 3 | R70: 4 | S70: 0 | T70: 0 | U70: 0 | V70: 4 | W70: Amazon | X70: 13 | Y70: 11 | Z70: low_stock | AA70: 120 | AB70: 46086 | AC70: Create shipping plan | AD70: 0.0045 ft3
A71: US | B71: BAZIC PRODUCTS Mini Highlighter – Pastel Color Assorted Chisel Tip Highlighter Set, Desk Style Highlighter Pen for Office, School, and Study Use, Smooth Marking, (5/Packs), 1-Pack | C71: X003TDI6Z7 | D71: FBA_2309-EACH | E71: B0BP5FBZKF | F71: New | G71: BAZIC Products | I71: USD | J71: 5.15 | K71: 391.02 | L71: 83 | M71: =O71+N71+P71+Q71 -> 476 | N71: 336 | O71: 0 | P71: 139 | Q71: 1 | R71: 4 | S71: 1 | T71: 0 | U71: 336 | V71: 0 | W71: Amazon | X71: 218 | Y71: 216 | AA71: 0 | AB71: none | AC71: No action required | AD71: 0.0084 ft3
A72: US | B72: BAZIC Products Small Notebook Memo Size Pad, 5"x7" Spiral Side Bound, 120 Sheets Wirebound Pocket Personal Notebooks, Assorted Color, 4-Pack | C72: X003X7GJZD | D72: FBA_546-SET4 | E72: B07SB6PGTB | F72: New | G72: BAZIC Products | I72: USD | J72: 12.25 | K72: 388.84 | L72: 31 | M72: =O72+N72+P72+Q72 -> 43 | N72: 18 | O72: 16 | P72: 9 | Q72: 0 | R72: 1 | S72: 0 | T72: 0 | U72: 18 | V72: 0 | W72: Amazon | X72: 53 | Y72: 52 | AA72: 0 | AB72: none | AC72: No action required | AD72: 0.0458 ft3
A73: US | B73: BAZIC Products Writing Pad 100 Sheets 6" x 9" – Writing Pad With Durable Lined Note Pads, Smooth Writing Paper, and Easy-tear Paper Pads; Compact Note Pads and Writing Pads for Office, School, or Home, 1-pack [Unknown Binding] | C73: X004GZ0A3X | D73: FBA_560-BAZIC | E73: B00YAXRY8O | F73: New | G73: BAZIC Products | I73: USD | J73: 4.57 | K73: 385.52 | L73: 84 | M73: =O73+N73+P73+Q73 -> 51 | N73: 0 | O73: 2 | P73: 46 | Q73: 3 | R73: 12 | S73: 0 | T73: 0 | U73: 0 | V73: 0 | W73: Amazon | X73: 16 | Y73: 12 | Z73: low_stock | AA73: 48 | AB73: 46086 | AC73: Create shipping plan | AD73: 0.0121 ft3
A74: US | B74: BAZIC Products 3 Ring Binder - Grey, Economy View Binder with Clear Overlay Cover and Round Rings, Organizer for School Office Home Use, 0.5 inch Capacity Holds 100 Sheets Paper, 12-Pack | C74: X0044RG6IB | D74: FBA_4101-CASE | E74: B07QF4V3CC | F74: New | G74: BAZIC Products | I74: USD | J74: 32.55 | K74: 382.32 | L74: 12 | M74: =O74+N74+P74+Q74 -> 6 | N74: 1 | O74: 5 | P74: 0 | Q74: 0 | R74: 0 | S74: 0 | T74: 0 | U74: 1 | V74: 0 | W74: Amazon | X74: 35 | Y74: 35 | AA74: 9 | AB74: 46086 | AC74: Create shipping plan | AD74: 0.4801 ft3
A75: US | B75: BAZIC Products Primary Journal Composition Book Blue Marble, 100 Sheet Writing Grades K- 2 Notebook Journal Comp Notebooks for Kindergarten Kids School, 48-Pack | C75: X003SC1YAD | D75: FBA_5087-CASE | E75: B084JC2TNZ | F75: New | G75: BAZIC Products | I75: USD | J75: 123.89 | K75: 371.67 | L75: 3 | M75: =O75+N75+P75+Q75 -> 99 | N75: 0 | O75: 99 | P75: 0 | Q75: 0 | R75: 0 | S75: 0 | T75: 0 | U75: 0 | V75: 0 | W75: Amazon | X75: 315 | Y75: 315 | AA75: 0 | AB75: none | AC75: No action required | AD75: 0.9722 ft3
A76: US | B76: BAZIC Products Thumbtacks, Assorted Color Jumbo Plastic Head Push Pins – Durable Steel Tacks for Walls and Cork Boards, Poster Pins, and Pushpins for Home, Office & School, 25/Pack, 1 Pack | C76: X003Y78JBT | D76: FBA_210-EACH | E76: B08VD2K1K6 | F76: New | G76: BAZIC Products | I76: USD | J76: 5.09 | K76: 370.71 | L76: 73 | M76: =O76+N76+P76+Q76 -> 14 | N76: 0 | O76: 10 | P76: 1 | Q76: 3 | R76: 0 | S76: 0 | T76: 0 | U76: 0 | V76: 0 | W76: Amazon | X76: 7 | Y76: 5 | Z76: low_stock | AA76: 144 | AB76: 46086 | AC76: Create shipping plan | AD76: 0.0059 ft3
A77: US | B77: BAZIC Rubber Bands, Assorted Size 2 Oz./ 56.70 g, Made in USA Elastic Stretchable Bands for Bank Paper Bills Money Dollars File Folders, 1-Pack | C77: B00GSSDLMM | D77: FBA_6100-EACH | E77: B00GSSDLMM | F77: New | G77: BAZIC Products | I77: USD | J77: 4.66 | K77: 367.36 | L77: 77 | M77: =O77+N77+P77+Q77 -> 354 | N77: 0 | O77: 354 | P77: 0 | Q77: 0 | R77: 0 | S77: 1 | T77: 0 | U77: 0 | V77: 0 | W77: Amazon | X77: 134 | Y77: 134 | AA77: 0 | AB77: none | AC77: No action required | AD77: 0.0084 ft3
A78: US | B78: BAZIC Manila File Folder 1/3 Cut Letter Size, Left Right Center Tabs Positions, for Organizing Filing Document Storage, Total 6-Count | C78: B003BSFCMY | D78: FBA_3103-EACH | E78: B003BSFCMY | F78: New | G78: BAZIC Products | I78: USD | J78: 4.09 | K78: 364.01 | L78: 89 | M78: =O78+N78+P78+Q78 -> 321 | N78: 0 | O78: 270 | P78: 49 | Q78: 2 | R78: 3 | S78: 0 | T78: 0 | U78: 0 | V78: 0 | W78: Amazon | X78: 109 | Y78: 107 | AA78: 0 | AB78: none | AC78: No action required | AD78: 0.0225 ft3
A79: US | B79: BAZIC Products Washable Fruit Scented Markers Broad Line 10 Color, Chisel Tip Broad Fine Line, Non Toxic Marcadorc Art School Supplies (10/Pack), 1-Pack | C79: B07HY4Z2YL | D79: FBA_1286-EACH | E79: B07HY4Z2YL | F79: New | G79: BAZIC Products | I79: USD | J79: 6.25 | K79: 360.36 | L79: 60 | M79: =O79+N79+P79+Q79 -> 62 | N79: 24 | O79: 16 | P79: 22 | Q79: 0 | R79: 1 | S79: 1 | T79: 0 | U79: 24 | V79: 0 | W79: Amazon | X79: 38 | Y79: 37 | AA79: 48 | AB79: 46086 | AC79: Create shipping plan | AD79: 0.0173 ft3
A80: US | B80: BAZIC Products 3 Ring Binder - Lime Green, Economy View Binder with Clear Overlay Cover and Round Rings, Organizer for School Office Home Use, 0.5 inch Capacity Holds 100 Sheets Paper, 4-Pack | C80: X0044RG64P | D80: FBA_4104-PACK4 | E80: B08DQ29JP6 | F80: New | G80: BAZIC Products | I80: USD | J80: 19.59 | K80: 354.36 | L80: 18 | M80: =O80+N80+P80+Q80 -> 18 | N80: 17 | O80: 0 | P80: 0 | Q80: 1 | R80: 6 | S80: 0 | T80: 0 | U80: 15 | V80: 2 | W80: Amazon | X80: 55 | Y80: 39 | AA80: 12 | AB80: 46086 | AC80: Create shipping plan | AD80: 0.1302 ft3
A81: US | B81: BAZIC Products 3 Ring Binder - Purple, Economy View Binder with Clear Overlay Cover and Round Rings, Organizer for School Office Home Use, 1-inch Capacity Holds 175 Sheets Paper, 1-Pack | C81: X003SC97MF | D81: FBA_4127-EACH | E81: B07Q8XTMXF | F81: New | G81: BAZIC Products | I81: USD | J81: 9.59 | K81: 350.29 | L81: 44 | M81: =O81+N81+P81+Q81 -> 29 | N81: 0 | O81: 27 | P81: 1 | Q81: 1 | R81: 1 | S81: 0 | T81: 0 | U81: 0 | V81: 0 | W81: Amazon | X81: 23 | Y81: 21 | AA81: 24 | AB81: 46086 | AC81: Create shipping plan | AD81: 0.1021 ft3
A82: US | B82: BAZIC Products Trifold Poster Board – White Corrugated Cardboard Display Board for school projects, science fairs, photos, charts, and classroom presentations, 28" x 40", 2-Pack | C82: X003SW56RP | D82: FBA_5086-PACK2 | E82: B08DHTKJXY | F82: New | G82: BAZIC Products | I82: USD | J82: 17.99 | K82: 349.6 | L82: 18 | M82: =O82+N82+P82+Q82 -> 37 | N82: 30 | O82: 0 | P82: 7 | Q82: 0 | R82: 8 | S82: 0 | T82: 0 | U82: 30 | V82: 0 | W82: Amazon | X82: 42 | Y82: 33 | AA82: 0 | AB82: none | AC82: No action required | AD82: 0.3241 ft3
A83: US | B83: BAZIC Products Poster Board 22" X 14" Assorted Colored Poster Board Paper for School Craft Project Presentation (3/Pack), 1-Pack | C83: X003GYFQHF | D83: FBA_540-EACH | E83: B0BCM2D62W | F83: New | G83: BAZIC Products | I83: USD | J83: 13.99 | K83: 341.61 | L83: 25 | M83: =O83+N83+P83+Q83 -> 28 | N83: 0 | O83: 28 | P83: 0 | Q83: 0 | R83: 1 | S83: 0 | T83: 0 | U83: 0 | V83: 0 | W83: Amazon | X83: 61 | Y83: 58 | AA83: 0 | AB83: none | AC83: No action required | AD83: 0.0178 ft3
A84: US | B84: BAZIC PRODUCTS Index Card Case with 5 Tab Dividers – Durable Plastic 3"x5" Flash Card Organizer and Storage Holder, 100-Card Capacity, Ideal for School, Office, and Study Use, 6-Pack | C84: X003SBSK5B | D84: FBA_3182-SET6 | E84: B07S4H1PF7 | F84: New | G84: BAZIC Products | I84: USD | J84: 12.89 | K84: 335.44 | L84: 26 | M84: =O84+N84+P84+Q84 -> 130 | N84: 108 | O84: 4 | P84: 18 | Q84: 0 | R84: 0 | S84: 1 | T84: 0 | U84: 102 | V84: 6 | W84: Amazon | X84: 101 | Y84: 101 | AA84: 0 | AB84: none | AC84: No action required | AD84: 0.1534 ft3
A85: US | B85: BAZIC Products Blank Index Cards 3" X 5" 100 Count, White Unruled Flashcards, Flash Card for Learning Memory Reminder (100/Pack), 1-Pack | C85: X0044RLTFV | D85: FBA_520-EACH | E85: B07S962L7Q | F85: New | G85: BAZIC Products | I85: USD | J85: 4.5 | K85: 332.48 | L85: 85 | M85: =O85+N85+P85+Q85 -> 134 | N85: 72 | O85: 54 | P85: 7 | Q85: 1 | R85: 0 | S85: 0 | T85: 0 | U85: 72 | V85: 0 | W85: Amazon | X85: 57 | Y85: 56 | AA85: 36 | AB85: 46086 | AC85: Create shipping plan | AD85: 0.0067 ft3
A86: US | B86: BAZIC Products Glitter Glue Tubes – 6 Assorted Neon Colors, Non-Toxic Washable Glitter Glue for Arts, Crafts, DIY, and Party Projects, 4 oz/Pack, 6 Packs | C86: X0043UZ3TH | D86: FBA_3450-SET6 | E86: B0856ZGDWW | F86: New | G86: BAZIC Products | I86: USD | J86: 19.99 | K86: 326.86 | L86: 26 | M86: =O86+N86+P86+Q86 -> 21 | N86: 12 | O86: 0 | P86: 9 | Q86: 0 | R86: 3 | S86: 1 | T86: 0 | U86: 12 | V86: 0 | W86: Amazon | X86: 33 | Y86: 28 | AA86: 30 | AB86: 46086 | AC86: Create shipping plan | AD86: 0.0546 ft3
A87: US | B87: BAZIC Products Mini Highlighter Pen Pastel Color, Chisel Tip Broad Fine Line Highlighters Unscented (5/Pack), 1-Pack | C87: B0C4VY1LR7 | D87: FBA_2309-EACH-B | E87: B0C4VY1LR7 | F87: New | G87: BAZIC Products | I87: USD | J87: 3.99 | K87: 323.17 | L87: 69 | M87: =O87+N87+P87+Q87 -> 80 | N87: 2 | O87: 50 | P87: 26 | Q87: 2 | R87: 12 | S87: 0 | T87: 0 | U87: 0 | V87: 2 | W87: Amazon | X87: 32 | Y87: 27 | AA87: 48 | AB87: 46086 | AC87: Create shipping plan | AD87: 0.0088 ft3
A88: US | B88: BAZIC PRODUCTS Plastic Pencil Case, Double Deck Utility Storage Box, Multi Purpose Organizer & Supply Holder, Transparent Box Design, Assorted Color, Ideal for School, Office & Craft Use, 4-Pack | C88: X0043UZ1HB | D88: FBA_837-SET4 | E88: B07RCB9JSP | F88: New | G88: BAZIC Products | I88: USD | J88: 11.89 | K88: 321.03 | L88: 27 | M88: =O88+N88+P88+Q88 -> 11 | N88: 0 | O88: 11 | P88: 0 | Q88: 0 | R88: 0 | S88: 0 | T88: 0 | U88: 0 | V88: 0 | W88: Amazon | X88: 22 | Y88: 22 | AA88: 30 | AB88: 46086 | AC88: Create shipping plan | AD88: 0.1094 ft3
A89: US | B89: BAZIC Products Washable Colored Glue Stick 8g/0.28 Oz, All Purpose Acid Glue Sticks for Kids Photos Paper Kids at School Home Office (4/Pack), 2-Pack | C89: X0044RG66D | D89: FBA_2043-PACK2 | E89: B00ZADK142 | F89: New | G89: BAZIC Products | I89: USD | J89: 6.87 | K89: 316.02 | L89: 46 | M89: =O89+N89+P89+Q89 -> 34 | N89: 12 | O89: 17 | P89: 2 | Q89: 3 | R89: 5 | S89: 0 | T89: 0 | U89: 12 | V89: 0 | W89: Amazon | X89: 30 | Y89: 24 | AA89: 60 | AB89: 46086 | AC89: Create shipping plan | AD89: 0.0304 ft3
A90: US | B90: BAZIC Products Neon Page Marker Dispensers, Sticky Notes for Study Materials, Office Use, Sign Here & Neon Colored Page Markers for Books and Documents, 0.5x1.7, 100 Flags/Pack, 2-Packs | C90: X003BTCGBT | D90: FBA_5172-PACK2 | E90: B08JQQ2BML | F90: New | G90: BAZIC Products | I90: USD | J90: 5.57 | K90: 309.55 | L90: 65 | M90: =O90+N90+P90+Q90 -> 102 | N90: 0 | O90: 85 | P90: 17 | Q90: 0 | R90: 9 | S90: 0 | T90: 0 | U90: 0 | V90: 0 | W90: Amazon | X90: 47 | Y90: 43 | AA90: 12 | AB90: 46086 | AC90: Create shipping plan | AD90: 0.0063 ft3
A91: US | B91: BAZIC Products Nickel Penny Coin Wrappers – Durable Preformed Paper Tube, Ideal Use for Organizing, Storing, Transporting, and Exchanging Coins, 36/Pack, 1 Pack | C91: B002NLIS7G | D91: FBA_5012-EACH | E91: B002NLIS7G | F91: New | G91: BAZIC Products | I91: USD | J91: 6.76 | K91: 308.26 | L91: 46 | M91: =O91+N91+P91+Q91 -> 147 | N91: 0 | O91: 0 | P91: 147 | Q91: 0 | R91: 3 | S91: 0 | T91: 0 | U91: 0 | V91: 0 | W91: Amazon | X91: 71 | Y91: 70 | AA91: 0 | AB91: none | AC91: No action required | AD91: 0.1188 ft3
A92: US | B92: BAZIC PRODUCTS Pencil Pouch 3 Ring Binder Pouch w/Rivet Enforced Rings Holes, Mesh Window, Bright Assorted Color Zipper Pouches Case, 144-Pack | C92: X003SC3AUP | D92: FBA_804-CASE | E92: B005OYUIVS | F92: New | G92: BAZIC Products | I92: USD | J92: 209.69 | K92: 293.84 | L92: 2 | M92: =O92+N92+P92+Q92 -> 0 | N92: 0 | O92: 0 | P92: 0 | Q92: 0 | R92: 0 | S92: 0 | T92: 0 | U92: 0 | V92: 0 | W92: Amazon | X92: 0 | Y92: 0 | Z92: out_of_stock | AA92: 2 | AB92: 46079 | AC92: Create shipping plan | AD92: 1.3291 ft3
A93: US | B93: BAZIC Jeweltones Color Plastic Ruler 12" (30cm), Inches Centimeter Metric Measuring Rulers (4/Pack) | C93: X003TIPAXN | D93: FBA_336-EACH | E93: B003BMX65A | F93: New | G93: BAZIC Products | I93: USD | J93: 4.75 | K93: 290.14 | L93: 62 | M93: =O93+N93+P93+Q93 -> 106 | N93: 0 | O93: 105 | P93: 1 | Q93: 0 | R93: 0 | S93: 0 | T93: 0 | U93: 0 | V93: 0 | W93: Amazon | X93: 40 | Y93: 40 | AA93: 120 | AB93: 46086 | AC93: Create shipping plan | AD93: 0.0167 ft3
A94: US | B94: BAZIC Products 4 + 1 Ballpoint Pen + Mechanical Pencil w/Soft Grip, Bold Point 1.0 mm, 0.7mm Lead, Assorted Colors Inks, Smooth Writing, 4-Pack | C94: B00PYV2454 | D94: FBA_1748-SET4-B | E94: B00PYV2454 | F94: New | G94: BAZIC Products | I94: USD | J94: 9.29 | K94: 288.19 | L94: 31 | M94: =O94+N94+P94+Q94 -> 101 | N94: 72 | O94: 26 | P94: 1 | Q94: 2 | R94: 2 | S94: 0 | T94: 0 | U94: 0 | V94: 72 | W94: Amazon | X94: 98 | Y94: 94 | AA94: 0 | AB94: none | AC94: No action required | AD94: 0.023 ft3
A95: US | B95: BAZIC PRODUCTS Crystal Clear Tape with Dispenser 3/4" X 500" – for Home, Office, and School Use; Transparent Tape with Glossy Finish, Ideal for Crafts, & Gift Wrapping, 3/Pack, 1-Pack | C95: B00GTJD0V2 | D95: FBA_929-EACH | E95: B00GTJD0V2 | F95: New | G95: BAZIC Products | I95: USD | J95: 5.45 | K95: 285.87 | L95: 56 | M95: =O95+N95+P95+Q95 -> 68 | N95: 0 | O95: 2 | P95: 41 | Q95: 25 | R95: 7 | S95: 0 | T95: 0 | U95: 0 | V95: 0 | W95: Amazon | X95: 24 | Y95: 14 | AA95: 24 | AB95: 46086 | AC95: Create shipping plan | AD95: 0.0154 ft3
A96: US | B96: BAZIC Products Scented Erasers, Latex Free, Assorted Fruity Scents, Cute Fun Fruit Eraser Classroom Must Haves for Drawing Art School Office (5/Pack), 1-Pack | C96: X004X6YT1J | D96: FBA_2222-EACH | E96: B0D79X1M7W | F96: New | G96: unassigned | I96: USD | J96: 5.79 | K96: 277.29 | L96: 48 | M96: =O96+N96+P96+Q96 -> 7 | N96: 1 | O96: 5 | P96: 0 | Q96: 1 | R96: 2 | S96: 0 | T96: 0 | U96: 0 | V96: 1 | W96: Amazon | X96: 6 | Y96: 4 | Z96: low_stock | AA96: 0 | AB96: none | AC96: No action required | AD96: 0.0073 ft3
A97: US | B97: BAZIC Products Poster Board 11" X 14" Assorted Colored Poster Board Paper for School Craft Project Presentation Drawing Graphic Display (5/Pack), 1-Pack | C97: X003UID51L | D97: FBA_529-EACH | E97: B07S9HP4W5 | F97: New | G97: BAZIC Products | I97: USD | J97: 4.39 | K97: 276.09 | L97: 63 | M97: =O97+N97+P97+Q97 -> 128 | N97: 0 | O97: 76 | P97: 4 | Q97: 48 | R97: 0 | S97: 0 | T97: 0 | U97: 0 | V97: 0 | W97: Amazon | X97: 51 | Y97: 31 | AA97: 0 | AB97: none | AC97: No action required | AD97: 0.025 ft3
A98: US | B98: BAZIC Products Sketch Pad, Spiral Sketchbook for Artists & Students, Drawing Pad with Thick Paper, Sketching & Drawing for Kids, Teens & Adults, 50 Sheets, 6" x 8", 2-Pack | C98: X0040DSNM1 | D98: FBA_5043-PACK2 | E98: B08DFJW6V4 | F98: New | G98: BAZIC Products | I98: USD | J98: 6.79 | K98: 275.63 | L98: 41 | M98: =O98+N98+P98+Q98 -> 277 | N98: 0 | O98: 96 | P98: 177 | Q98: 4 | R98: 6 | S98: 0 | T98: 0 | U98: 0 | V98: 0 | W98: Amazon | X98: 172 | Y98: 166 | AA98: 0 | AB98: none | AC98: No action required | AD98: 0.0247 ft3
A99: US | B99: BAZIC Eraser Top, Latex Free Pencil Tops Erasers (20/Pack), Neon Color Arrowhead Caps Erasers for Kids Student Art Drawing School Supplies, 1-Pack | C99: B003BNZVI4 | D99: FBA_2202-EACH | E99: B003BNZVI4 | F99: New | G99: BAZIC Products | I99: USD | J99: 4.59 | K99: 264.97 | L99: 59 | M99: =O99+N99+P99+Q99 -> 268 | N99: 0 | O99: 267 | P99: 1 | Q99: 0 | R99: 1 | S99: 0 | T99: 0 | U99: 0 | V99: 0 | W99: Amazon | X99: 78 | Y99: 78 | AA99: 24 | AB99: 46086 | AC99: Create shipping plan | AD99: 0.009 ft3
A100: US | B100: BAZIC Products Poster Board Metallic Silver 22" X 28", Colored Poster Board Paper, Bulk Boards for School Craft Project Presentation Drawing Graphic Display, 25-Pack | C100: X003SC97ON | D100: FBA_5419-CASE | E100: B08FFCWTSJ | F100: New | G100: BAZIC Products | I100: USD | J100: 54.39 | K100: 260.74 | L100: 7 | M100: =O100+N100+P100+Q100 -> 1 | N100: 0 | O100: 1 | P100: 0 | Q100: 0 | R100: 0 | S100: 0 | T100: 0 | U100: 0 | V100: 0 | W100: Amazon | X100: 6 | Y100: 6 | Z100: low_stock | AA100: 12 | AB100: 46084 | AC100: Create shipping plan | AD100: 0.2156 ft3
...

Sheet 2024
A1: (Parent) ASIN | B1: (Child) ASIN | C1: Title | D1: SKU | E1: Sessions - Total | F1: Sessions - Total - B2B | G1: Session Percentage - Total | H1: Page Views - Total | I1: Page Views - Total - B2B | J1: Units Ordered | K1: Ordered Product Sales
A2: B0BFZRFR9V | B2: B0BG14KCKZ | C2: BAZIC PRODUCTS Middle & High School Kit Supply Box, 65-Count Student Set for Grades 7–12, Complete School Supply Kit with Middle School Supplies, Organized Supply Box for Highschool, 1-Pack | D2: FBA_8006-CASE | E2: 80981 | F2: 1969 | G2: 0.0508 | H2: 120899 | I2: 3050 | J2: 4475 | K2: 209799.86
A3: B092C5FM1W | B3: B0018MN4RA | C3: BAZIC Products Blank Paper Copy & Multipurpose Paper - 8.5" x 11" White Color Printer Paper for Inkjet, Laser, and Fax Machines, Ideal for Office, School, and Crafts, 50 Sheets/Pack, 1-Pack | D3: FBA_510-EACH-B | E3: 20737 | F3: 427 | G3: 0.013 | H3: 24332 | I3: 499 | J3: 3750 | K3: 16853.16
A4: B003UBOEJY | B4: B003BMWZ48 | C4: BAZIC Products Staples Standard (26/6) 5000/Pack, Stapler Refill Standard Size Staple, Silver Colors, 1-Pack | D4: FBA_608-EACH | E4: 3977 | F4: 519 | G4: 0.0025 | H4: 4665 | I4: 624 | J4: 2493 | K4: 12602.07
A5: B09234DBZ5 | B5: B09BBP343Q | C5: BAZIC Products Pink Eraser, Latex Free Bevel Block Erasers, Large Size for Classroom, Office, and Art Use, Smooth Pencil Correction for Writing, Sketching, & Daily Tasks, 4/Pack, 2-Packs | D5: FBA_2227-PACK2 | E5: 5922 | F5: 150 | G5: 0.0037 | H5: 7025 | I5: 190 | J5: 2326 | K5: 14605.19
A6: B076F13SG5 | B6: B076F13SG5 | C6: BAZIC Products Book Wrap - Clear Book Cover Self Adhesive Book Protector for Book Covers for Paperbacks, Plastic Cover for Books, Clear Contact Paper Peel and Stick, 17.5" x 1.7 Yard Roll, 1-Roll | D6: FBA_2901-EACH | E6: 13516 | F6: 316 | G6: 0.0085 | H6: 18797 | I6: 476 | J6: 2487 | K6: 13301.86
A7: B09DP2RN9T | B7: B09DP3TR4F | C7: BAZIC Pencil Pouch 3 Ring Binder Pouch w/Rivet Enforced Rings Hole, Black Mesh Window Zipper Pouches, 1-Count | D7: FBA_808-EACH | E7: 8913 | F7: 149 | G7: 0.0056 | H7: 11304 | I7: 202 | J7: 1647 | K7: 6959.65
A8: B0D7GD53RF | B8: B00H9Z198Q | C8: BAZIC Products Sketch Pad, Spiral Sketchbook for Artists & Students, Drawing Pad with Thick Paper, Sketching & Drawing for Kids, Teens & Adults, 50 Sheets, 6" x 8", 1-Pack | D8: FBA_5043-EACH | E8: 8457 | F8: 129 | G8: 0.0053 | H8: 11128 | I8: 179 | J8: 1650 | K8: 6622
A9: B09DP2RN9T | B9: B09GD5961M | C9: BAZIC PRODUCTS Pencil Pouch for 3 Ring Binder, Zippered Mesh Window Pencil Case with Reinforced Grommets, Durable Binder Organizer for School Supplies or Office Supplies Storage, 2-Pack | D9: FBA_808-PACK2 | E9: 5607 | F9: 101 | G9: 0.0035 | H9: 7124 | I9: 123 | J9: 1379 | K9: 7755.16
A10: B09237NMB9 | B10: B00ZPRYV0I | C10: BAZIC Manila File Folder 1/3 Cut Letter Size, Left Right Center Tabs Positions, for Organizing Filing Document Storage, Total 12-Count | D10: FBA_3100-EACH | E10: 6412 | F10: 203 | G10: 0.004 | H10: 8068 | I10: 243 | J10: 1245 | K10: 6197.51
A11: B09252M5G4 | B11: B08P3W6YN6 | C11: BAZIC Products Date Stamper with Black Ink Pads for Stamping, 12 Years of Adjustable Dates, Ideal for Office, Shipping, Receiving, Accounting, Expiration Date Stamp, Due Dates - 1 Pack | D11: FBA_6301-EACH | E11: 7770 | F11: 287 | G11: 0.0049 | H11: 10567 | I11: 370 | J11: 1195 | K11: 6360.84
A12: B09234DBZ5 | B12: B001BNW7QA | C12: BAZIC Products Pink Eraser, Latex Free Bevel Block Erasers, Large Size for Classroom, Office, and Art Use, Smooth Pencil Correction for Writing, Sketching, & Daily Tasks, 4/Pack, 1-Pack | D12: FBA_2227-EACH | E12: 13029 | F12: 359 | G12: 0.0082 | H12: 15641 | I12: 484 | J12: 1108 | K12: 4803.13
A13: B092B7WDSW | B13: B07S64FRBG | C13: BAZIC PRODUCTS Primary Journal Composition Book Marble, Primary Journal, Writing Journal, Notebooks for Kids, Drawing & Writing Notebook for Kindergarten School Use, Grades K-2, 100 Sheets, 2-Pack | D13: FBA_5053-SET2 | E13: 19900 | F13: 538 | G13: 0.0125 | H13: 26857 | I13: 704 | J13: 1150 | K13: 13977.47
... A28: B092C5FM1W | B28: B08FBR7YW1 | C28: BAZIC Products Blank Paper Copy & Multipurpose Paper - 8.5" x 11" White Color Printer Paper for Inkjet, Laser, and Fax Machines, Ideal for Office, School, and Crafts, 50 Sheets/Pack, 2-Packs | D28: FBA_510-PACK2 | E28: 4113 | F28: 91 | G28: 0.0026 | H28: 4749 | I28: 112 | J28: 879 | K28: 6985.58
A29: B0D79QBWJK | B29: B07SW927JM | D29: FBA_2030 | E29: 11687 | F29: 305 | G29: 0.0073 | H29: 15341 | I29: 399 | J29: 756 | K29: 3930.3
A30: B091T49CD3 | B30: B07Q84RJLP | C30: BAZIC Products 3 Ring Binder 1/2" Economy View Binders Organizer - Purple, Round Ring, Hold 100 Sheets Paper, for School Office Home, 1-Count | D30: FBA_4107-EACH | E30: 2902 | F30: 117 | G30: 0.0018 | H30: 3758 | I30: 166 | J30: 787 | K30: 6965.01
A31: B091T49CD3 | B31: B07Q8ZFP5P | C31: BAZIC Products 3 Ring Binder 1/2" Economy View Binders Organizer - Red, Round Ring, Hold 100 Sheets Paper, for School Office Home, 1-Count | D31: FBA_4103-EACH | E31: 1973 | F31: 101 | G31: 0.0012 | H31: 2477 | I31: 129 | J31: 716 | K31: 6456.83
A32: B0D6XX39QD | B32: B09DJVP3DS | C32: BAZIC Products Black Rubber Bands – Assorted Sizes, Heavy Duty Elastic Bands For Money, Office, School, Home Organization, Crafts, Durable Stretch Rubber Bands, 2 Oz (56.7 g), 1-Pack | D32: FBA_6120-EACH | E32: 4533 | F32: 117 | G32: 0.0028 | H32: 5878 | I32: 152 | J32: 679 | K32: 3347.29
A33: B092C5FCT5 | B33: B003BMX6SC | C33: BAZIC Products Wooden Ruler 12" (30cm), Singel Metal Edge, Inches Centimeter Metric Measuring Drafting Rulers, for Students School Supplies (3/Pack), 1-Pack | D33: FBA_306-EACH | E33: 4105 | F33: 177 | G33: 0.0026 | H33: 5528 | I33: 243 | J33: 666 | K33: 2651.62
A34: B0D7GD53RF | B34: B07S94M6P6 | C34: BAZIC Products Sketch Pad, Spiral Sketchbook for Artists & Students, Drawing Pad with Thick Paper, Sketching & Drawing for Kids, Teens & Adults, 30 Sheets, 8.5" X 11", 1-Pack | D34: FBA_5045-EACH | E34: 4593 | F34: 108 | G34: 0.0029 | H34: 5933 | I34: 155 | J34: 927 | K34: 4533.87
A35: B0D79QBWJK | B35: B08GWY7YNX | D35: FBA_2030-PACK2 | E35: 3377 | F35: 121 | G35: 0.0021 | H35: 4261 | I35: 149 | J35: 671 | K35: 5381.56
A36: B003UBTO6W | B36: B002WFI620 | C36: BAZIC Products Pencil Grip – Assorted Color Soft Gel Pen Grip, Comfort Pencil Grip, Ergonomic Pen Grips for Toddler, Kids and Adults, 8/Pack, 1-Packs | D36: FBA_1502-EACH | E36: 5001 | F36: 108 | G36: 0.0031 | H36: 6740 | I36: 155 | J36: 650 | K36: 2641.19
A37: B092B5G6XT | B37: B07S964BMT | C37: BAZIC Products Notebook Wide Ruled 1 Subject 80 Sheets Wireless Notebooks, 3 Punched Holes Lined Composition Book, Assorted Color, 6-Pack | D37: FBA_582-SET6 | E37: 4226 | F37: 127 | G37: 0.0027 | H37: 6120 | I37: 181 | J37: 741 | K37: 15516.75
A38: B00FBOMTA4 | B38: B00FBOMTA4 | C38: BAZIC Ballpoint Pen Spencer Red Retractable Pen Soft Barrel Grip Pens, 1.0 mm Bold Point Smooth Writing, for Office School Teacher (5/Pack), 1-Pack | D38: 17049-EACH | E38: 1539 | F38: 37 | G38: 0.001 | H38: 1860 | I38: 43 | J38: 635 | K38: 4005.98
A39: B09235CHLD | B39: B003BNZVI4 | C39: BAZIC Eraser Top, Latex Free Pencil Tops Erasers (20/Pack), Neon Color Arrowhead Caps Erasers for Kids Student Art Drawing School Supplies, 1-Pack | D39: 2202-EACH | E39: 7613 | F39: 278 | G39: 0.0048 | H39: 8997 | I39: 311 | J39: 693 | K39: 3937.77
A40: B092B8LHYH | B40: B001E75OY0 | C40: BAZIC Composition Book Wide Ruled 100 Sheet Black Marble Notebook, Writing Journal Comp Lined Notebooks for School, 1-Pack | D40: FBA_508-EACH | E40: 5045 | F40: 149 | G40: 0.0032 | H40: 6295 | I40: 196 | J40: 646 | K40: 3463.17
A41: B091T94ZQ2 | B41: B07S4GZW7L | C41: BAZIC Products Binder Dividers, 8.5 x 11 Plastic Index, 11 Hole Punch for 3 Ring Binders, Organizer, Ideal for School, Office, Home Organization, 10 Tab, 10/Pack, 1-Pack | D41: FBA_3107-EACH | E41: 2725 | F41: 109 | G41: 0.0017 | H41: 3768 | I41: 158 | J41: 877 | K41: 5317.13
A42: B0CMCX31KN | B42: B07RC79KYS | C42: BAZIC Products Pencil Pouch 3 Ring Binder Pouch w/Rivet Enforced Rings Holes, Assorted Color Mesh Window Zipper Pouches, 4-Pack | D42: FBA_803-SET4 | E42: 4293 | F42: 79 | G42: 0.0027 | H42: 5495 | I42: 97 | J42: 626 | K42: 5395.14
A43: B0921ZT8GT | B43: B07RLPFK92 | C43: Bazic Products Loose Leaf Binder Ring 1", Assorted Color Steel Metal Rings for Flash Cards, Index Cards, Study Notes & Craft Organization, Binder Rings, Snap Rings Closure, 10-Count, 1-Pack | D43: FBA_212-EACH | E43: 1695 | F43: 65 | G43: 0.0011 | H43: 2119 | I43: 79 | J43: 593 | K43: 2896.63
A44: B09238KM85 | B44: B07S165T2T | C44: BAZIC Products 2 Pocket Paper Folder, Letter Size Document Organizer for School, Office, Business Use, Camouflage Design Portfolio Folder for Homework, Reports & Forms, Assorted Colors, 6 Pack | D44: FBA_2170-SET6 | E44: 3202 | F44: 98 | G44: 0.002 | H44: 4191 | I44: 161 | J44: 595 | K44: 6485.5
A45: B0BVC136NJ | B45: B0BCL7XWNT | C45: BAZIC Products Blank Paper Copy & Multipurpose Paper 8.5" x 11" – 25 Sheets Pastel Color Printer Paper for Inkjet, Laser, and Fax Machines – Printing Paper for Office, School, and Crafts, 2-Packs | D45: FBA_5190-PACK2 | E45: 3530 | F45: 195 | G45: 0.0022 | H45: 4357 | I45: 233 | J45: 645 | K45: 5916.84
A46: B092B7F2TZ | B46: B003BLQHZM | C46: BAZIC 100 Ct. 4-1" Quad-Ruled Filler Paper | D46: FBA_569-EACH | E46: 8438 | F46: 267 | G46: 0.0053 | H46: 10358 | I46: 340 | J46: 660 | K46: 4213.7
A47: B09235X9NL | B47: B09BBRDFT8 | C47: BAZIC Products Eraser Set – Premium Pink Erasers and Cap Erasers for Clean Corrections; Ideal for School, Office, Artists, Writing, Sketching, and Drawing, 15/Pack, 2-Packs | D47: FBA_2233-PACK2 | E47: 2016 | F47: 46 | G47: 0.0013 | H47: 2484 | I47: 59 | J47: 574 | K47: 3038.86
... A205: B003BNZVHU | B205: B003BNZVHU | C205: BAZIC Neon Eraser Top. Chisel Shaped Erasers for Standard Pencils (50/Pack) | D205: 2204-EACH-1 | E205: 3034 | F205: 82 | G205: 0.0019 | H205: 3602 | I205: 95 | J205: 112 | K205: 743.96
A206: B0D79QBWJK | B206: B07YL7V4YB | D206: FBA_2030-BOX | E206: 723 | F206: 46 | G206: 0.0005 | H206: 970 | I206: 61 | J206: 109 | K206: 2525.12
A207: B0921DV2FK | B207: B003BLQHYI | C207: BAZIC Self Seal White Envelope 4 1/8" x 9 1/2" #10, No Window Mailing Envelopes, Peel & Seal Mailer for Business Invoice Check (50/Pack), 1-Pack | D207: FBA_574-EACH | E207: 860 | F207: 34 | G207: 0.0005 | H207: 1088 | I207: 41 | J207: 132 | K207: 790.68
A208: B008ZHNN68 | B208: B008ZHNN68 | C208: BAZIC Products Mini Highlighter Pen Assorted Color, Chisel Tip Broad Fine Line Highlighters Coloring Marker (5/Pack), 1-Pack | D208: FBA_2306-EACH-1 | E208: 1132 | F208: 17 | G208: 0.0007 | H208: 1443 | I208: 21 | J208: 109 | K208: 463.88
A209: B092BNVV3J | B209: B07S9468GC | C209: BAZIC Products Notebook 80 Sheets 5" Quad Graph Ruled Notebooks Reversible 4", Easy Tear 3 Punched Holes, Squares Ruled Drafting Blueprint, 4-Pack | D209: FBA_578-SET4 | E209: 683 | F209: 24 | G209: 0.0004 | H209: 932 | I209: 31 | J209: 107 | K209: 1574.25
A210: B0921RG6MW | B210: B002NLIS7G | C210: BAZIC Products Nickel Penny Coin Wrappers – Durable Preformed Paper Tube, Ideal Use for Organizing, Storing, Transporting, and Exchanging Coins, 36/Pack, 1 Pack | D210: FBA_5012-EACH | E210: 759 | F210: 29 | G210: 0.0005 | H210: 1011 | I210: 36 | J210: 117 | K210: 818.03
A211: B09234DBZ5 | B211: B001BNW7QA | C211: BAZIC Products Pink Eraser, Latex Free Bevel Block Erasers, Large Size for Classroom, Office, and Art Use, Smooth Pencil Correction for Writing, Sketching, & Daily Tasks, 4/Pack, 1-Pack | D211: 2227-EACH-1 | E211: 13029 | F211: 359 | G211: 0.0082 | H211: 15641 | I211: 484 | J211: 105 | K211: 649.95
A212: B092CDQXZN | B212: B07T1JYHZC | C212: BAZIC Products Color Paper Cube with Durable Tray, Assorted Color Mini Memo Papers & Notepad Reminders for Home, School, Office Use, 3" x 3" 300 Count/Pack, 1-Pack | D212: FBA_552-EACH | E212: 2100 | F212: 68 | G212: 0.0013 | H212: 2791 | I212: 82 | J212: 104 | K212: 556.65
A213: B0921NXQTT | B213: B00886FNA0 | D213: FBA_5002-EACH | E213: 538 | F213: 18 | G213: 0.0003 | H213: 673 | I213: 20 | J213: 103 | K213: 616.97
A214: B0921TXN58 | B214: B07S962L7Q | C214: BAZIC Products Blank Index Cards 3" X 5" 100 Count, White Unruled Flashcards, Flash Card for Learning Memory Reminder (100/Pack), 1-Pack | D214: FBA_520-EACH | E214: 635 | F214: 41 | G214: 0.0004 | H214: 773 | I214: 55 | J214: 146 | K214: 1006.31
A215: B091BLJ36Q | B215: B08BQMHJ97 | C215: KAPPA Take Along Large Print Word Finds Puzzle Book - 8" x 5" Digest Size 2 Titles, Word Search Find Words Books for Adults Teens, Training Learning with Game, 2-Pack | D215: FBA_3388-SET3 | E215: 648 | F215: 8 | G215: 0.0004 | H215: 841 | I215: 9 | J215: 97 | K215: 1211.5
A216: B0BFZRFR9V | B216: B0BB8R9HGQ | C216: BAZIC PRODUCTS Elementary School Supply Kit, 86-count Student Set for Elementary Students Grades 3-6, Complete School Supplies With Fully Organized Supply Box, 1-pack | D216: 8005-CASE | E216: 28048 | F216: 774 | G216: 0.0176 | H216: 38017 | I216: 1038 | J216: 111 | K216: 5414.99
A217: B091XMHW6V | B217: B003BOUX9A | C217: BAZIC Division Flash Cards, Numbers Elementary Math Flashcards Game at School, Problem Solving for Ages 8+ 3rd Grade 4th Grade (36/Pack), 1-Pack | D217: FBA_535-EACH | E217: 650 | F217: 27 | G217: 0.0004 | H217: 827 | I217: 31 | J217: 117 | K217: 626.13
A218: B093RB3NPF | B218: B08YPCDFFS | C218: BAZIC PRODUCTS Plastic Pencil Case, Double Deck Utility Storage Box, Multi Purpose Organizer & Supply Holder, Transparent Box Design, Assorted Color, Ideal for School, Office & Craft Use, 4-Pack | D218: FBA_845-SET4 | E218: 1059 | F218: 34 | G218: 0.0007 | H218: 1198 | I218: 42 | J218: 97 | K218: 1551.97
A219: B092B8LHYH | B219: B0B8QRTPL6 | C219: BAZIC Products Composition Notebook Wide Ruled - 100 Sheets, Black Marble Composition Notebook with Durable Cover, Non-Spiral for Journaling, School, Home, or Office, 6-Packs | D219: FBA_508-PACK6 | E219: 868 | F219: 24 | G219: 0.0005 | H219: 1143 | I219: 29 | J219: 100 | K219: 1723
A220: B091BPCXP8 | B220: B08BQZ1TTS | C220: Kappa Pocket Puzzle Large Print - 8" x 5" Digest Size 2 Titles, Word Search Find Books for Adults Teens, Training Learning With Game, 2-Pack | D220: 61400-SET2 | E220: 2959 | F220: 27 | G220: 0.0019 | H220: 3740 | I220: 36 | J220: 94 | K220: 941.53
A221: B08F77T22M | B221: B08F77T22M | C221: BAZIC Products Pencil Wood Pre-Sharpened #2 HB Jumbo Pencils, Latex Free Eraser, Premium Wood Pre Sharpened Yellow Pencils for School Office (4/Pack), 2-Packs | D221: FBA_716-PACK2 | E221: 655 | F221: 10 | G221: 0.0004 | H221: 829 | I221: 15 | J221: 95 | K221: 598.64
A222: B091JGVXQT | B222: B00KDLAYZ2 | C222: BAZIC Products Dime Coin Wrappers – Durable Preformed Paper Tube, Sleeves for Coin Sorter and Holder, 36/Pack, 2 Packs | D222: FBA_5013-PACK2 | E222: 374 | F222: 20 | G222: 0.0002 | H222: 456 | I222: 24 | J222: 98 | K222: 815.8
A223: B0D6X9X9XL | B223: B07T766984 | C223: BAZIC Products Rubber Bands, Assorted Size 1/2 Lbs. Made in USA, Elastic Stretchable Bands for Bank Paper Bills Money Dollars, Colors Sizes May Vary, 1-Pack | D223: FBA_465-EACH-1 | E223: 418 | F223: 35 | G223: 0.0003 | H223: 552 | I223: 42 | J223: 92 | K223: 826.86
A224: B092H6W353 | B224: B09C2QNFTV | C224: BAZIC Products Staples Standard 26/6 Metallic Color 3000/Pack Refill for Stapler, Ideal Office Staples for Home, School & Business, Assorted Colors, 4-Packs | D224: FBA_609-PACK4 | E224: 366 | F224: 29 | G224: 0.0002 | H224: 451 | I224: 41 | J224: 92 | K224: 949.95
A225: B0BFZRFR9V | B225: B0BB8R9HGQ | C225: BAZIC PRODUCTS Elementary School Supply Kit, 86-count Student Set for Elementary Students Grades 3-6, Complete School Supplies With Fully Organized Supply Box, 1-pack | D225: 8005-CASE-1 | E225: 28048 | F225: 774 | G225: 0.0176 | H225: 38017 | I225: 1038 | J225: 100 | K225: 4889
... A375: B00275EBHE | B375: B00275EBHE | C375: BAZIC Primary Journal Composition Book Marble, 100 Sheet Drawing & Writing Grades K- 2 Notebook Journal Comp Notebooks for Kindergarten School, 48-Pack | D375: 5053-CASE-B | E375: 2514 | F375: 397 | G375: 0.0016 | H375: 3355 | I375: 645 | J375: 103 | K375: 11453.59
A376: B092RKXK9S | B376: B01GORCP4G | D376: FBA_5104-EACH | E376: 269 | F376: 17 | G376: 0.0002 | H376: 318 | I376: 22 | J376: 38 | K376: 160.05
A377: B0998CXQ1N | B377: B07XQLG446 | C377: BAZIC PRODUCTS Plastic Pencil Case, Ruler Length Utility Storage Box, Multi Purpose Organizer & Supply Holder, Transparent Box Design, Assorted Color, Ideal for School, Office & Craft Use, 24-Pack | D377: FBA_841-CASE | E377: 366 | F377: 39 | G377: 0.0002 | H377: 460 | I377: 62 | J377: 53 | K377: 3249.93
A378: B092B7WDSW | B378: B07XQN9MYD | C378: BAZIC PRODUCTS Primary Journal Composition Book Marble, Primary Journal, Writing Journal, Notebooks for Kids, Drawing & Writing Notebook for Kindergarten School Use, Grades K-2, 100 Sheets, 48-Pack | D378: 5053-CASE | E378: 3790 | F378: 569 | G378: 0.0024 | H378: 4882 | I378: 856 | J378: 130 | K378: 14885.59
A379: B091BMY745 | B379: B08BQWB7QZ | C379: Kappa Large Print Word Finds 2 Titles, Large Print Easy to Read, Word Search Find Words Books for Adults Teens, Training Learning with Game, 2-Pack | D379: 84200-SET2 | E379: 314 | F379: 4 | G379: 0.0002 | H379: 506 | I379: 4 | J379: 39 | K379: 467.6
A380: B09FFP83D6 | B380: B08QRLYMJ4 | C380: BAZIC PRODUCTS Plastic Pencil Case, Multi Purpose Organizer & Supply Holder, Clear Box Design, Durable Plastic Storage for School, Office, Classroom & Craft Supplies, 24-Pack | D380: 847-CASE | E380: 1778 | F380: 329 | G380: 0.0011 | H380: 2291 | I380: 442 | J380: 120 | K380: 6922.02
A381: B07H9JDNRG | B381: B07H9JDNRG | C381: BAZIC Products Open & Closed Sign 12"x16", Double Sides Plastic Vinyl Signs, Business Store Office Restaurants Bars Shops, Waterproof indoor Sigane, 1-Pack | D381: FBA_L-24-EACH | E381: 1521 | F381: 121 | G381: 0.001 | H381: 2038 | I381: 168 | J381: 47 | K381: 268.05
A382: B091T36TXP | B382: B07Q3T595W | C382: BAZIC Products 3 Ring Binder 1.5" Economy View Binders Organizer - Green, Round Ring, Hold 250 Sheets Paper, for School Office Home, 1-Count | D382: FBA_4142-EACH | E382: 486 | F382: 18 | G382: 0.0003 | H382: 600 | I382: 20 | J382: 36 | K382: 377.64
A383: B091V4ZLM2 | B383: B07XQLT9N7 | C383: BAZIC Products Sales Order Book, 50 Sets 5 9/16" x 8 7/16" 2-Part Carbonless, White & Bound Wraparound Cover (50 Sets/Pack), 24-Packs | D383: FBA_5075-BOX | E383: 160 | F383: 30 | G383: 0.0001 | H383: 273 | I383: 63 | J383: 40 | K383: 1529.19
A384: B091SP52LR | B384: B08DQ44MTT | C384: BAZIC Products 3 Ring Binder 1" Economy View Binders Organizer - Purple, Round Ring, Hold 175 Sheets Paper, for School Office Home, 2-Count | D384: FBA_4127-PACK2 | E384: 140 | F384: 10 | G384: 0.0001 | H384: 172 | I384: 18 | J384: 43 | K384: 587.58
A385: B092B8LHYH | B385: B0B8QRTPL6 | C385: BAZIC Products Composition Notebook Wide Ruled - 100 Sheets, Black Marble Composition Notebook with Durable Cover, Non-Spiral for Journaling, School, Home, or Office, 6-Packs | D385: 508-PACK6 | E385: 868 | F385: 24 | G385: 0.0005 | H385: 1143 | I385: 29 | J385: 36 | K385: 786.24
A386: B0D6XBXVWR | B386: B07SD9P6HS | C386: BAZIC Products Rubber Bands Size #32, 2 Oz./ 56.70g, Made in USA Elastic Stretchable Bands for Bank Paper Bills Money Dollars File Folders, 1-Pack | D386: FBA_6101-EACH | E386: 119 | F386: 7 | G386: 0.0001 | H386: 146 | I386: 8 | J386: 40 | K386: 226.81
A387: B0BFT5KHLK | B387: B07T9PH2FD | C387: BAZIC Products 3 Ring Binder – Assorted Matte Bright Color Cover, Soft Cover School Notebook Binder, Ideal Use for School, Home, or Office, 1 Inch Holds 175 Sheets, 6-Packs | D387: FBA_3126-SET6 | E387: 574 | F387: 19 | G387: 0.0004 | H387: 766 | I387: 29 | J387: 41 | K387: 760.5
A388: B09236132P | B388: B09BC5L9F5 | C388: BAZIC Products Pink Eraser Top, Latex-Free Pencil Top Erasers with Arrowhead Caps, Non-Toxic Erasers for Kids, Students, Teachers, Classroom, Art, Homework & School Supplies, 20/Pack, 2-Pack | D388: FBA_2206-PACK2 | E388: 896 | F388: 19 | G388: 0.0006 | H388: 1039 | I388: 23 | J388: 36 | K388: 216
... A537: B09986M8SX | B537: B0CCBTHXWD | C537: BAZIC Products Plastic Pencil Case 8" Storage Box, Assorted Color, Hard Pencil Case, Translucent Multi Purpose Organizer, 24-Pack | D537: 835-CASE | E537: 775 | F537: 47 | G537: 0.0005 | H537: 1018 | I537: 52 | J537: 19 | K537: 977.39
A538: B0D8981ZZN | B538: B0D88SXRCD | D538: 779-PACK4 | E538: 60 | F538: 2 | G538: 0 | H538: 69 | I538: 2 | J538: 18 | K538: 222.12
A539: B0921GFJLL | B539: B003BLQHXO | C539: BAZIC Security Self Seal Envelope 4 1/8" x 9 1/2" #10, No Window Tint Pattern Mailing Envelopes, Peel & Seal, Office Checks Invoices (40/Pack), 1-Pack | D539: FBA_575-EACH | E539: 260 | F539: 15 | G539: 0.0002 | H539: 324 | I539: 23 | J539: 17 | K539: 91.26
A540: B091SP52LR | B540: B07Q84SJRK | C540: BAZIC Products 3 Ring Binder 1" Economy View Binders Organizer - Cyan, Round Ring, Hold 175 Sheets Paper, for School Office Home, 1-Count | D540: 4125-EACH | E540: 779 | F540: 20 | G540: 0.0005 | H540: 965 | I540: 23 | J540: 17 | K540: 274.38
A541: B0D7FV9GW5 | B541: B07S64FDYZ | C541: BAZIC Products Sketch Pad 20 Sheet 18" X 12", White Sketchbook Drawing Pads, Sketching Paper Coloring Book for Artist Beginner Classroom, 1-Pack | D541: 551-EACH | E541: 241 | F541: 8 | G541: 0.0002 | H541: 286 | I541: 13 | J541: 27 | K541: 373.53
A542: B092G686MF | B542: B07SDL9T22 | C542: BAZIC Products Ballpoint Pen Pure Black Color Stick Pens, 1.0 mm Bold Point Smooth Writing, for Office School Teacher (12/Pack), 1-Pack | D542: FBA_1755-EACH | E542: 265 | F542: 6 | G542: 0.0002 | H542: 349 | I542: 6 | J542: 37 | K542: 184.63
A543: B092RL1SBF | B543: B07XL51NKC | C543: BAZIC Products Neon Page Marker Dispensers, Sticky Notes for Study Materials, Office Use, Sign Here & Neon Colored Page Markers for Books and Documents, 1x1.7, 60 Flags/Pack, 24-Packs | D543: FBA_5173-BOX | E543: 151 | F543: 46 | G543: 0.0001 | H543: 190 | I543: 59 | J543: 21 | K543: 772.59
A544: B091DC1CNJ | B544: B07XQLKXF4 | C544: BAZIC Products Drawing Sketching Pencil Set, HB 2B 4B 6B 7B 8B, Professional Graphite Sketch Kit Pencils, for Artists Adults Beginners (6/Pack), 24-Packs | D544: FBA_744-BOX | E544: 114 | F544: 11 | G544: 0.0001 | H544: 133 | I544: 13 | J544: 21 | K544: 835
A545: B0D7GD53RF | B545: B07XQLVXN5 | C545: BAZIC Products Sketch Pad, Spiral Sketchbook for Artists & Students, Drawing Pad with Thick Paper, Sketching & Drawing for Kids, Teens & Adults, 30 Sheets, 9" X 12", 48-Pack | D545: FBA_5044-CASE | E545: 184 | F545: 29 | G545: 0.0001 | H545: 269 | I545: 68 | J545: 21 | K545: 1528.65
A546: B092C6NXR4 | B546: B07XQQ6T8H | C546: BAZIC Products Shatterproof Flexible Ruler 12" (30cm), Inches Centimeter Metric Measuring Drafting Rulers, for Students School Supplies, 24-Pack | D546: 315-BOX | E546: 137 | F546: 19 | G546: 0.0001 | H546: 178 | I546: 26 | J546: 18 | K546: 478.95
A547: B0D7G62SYM | B547: B083NGQTVP | C547: BAZIC Products Air Dry Clay 6 Color 12 oz, Light Modeling Dough Art Craft Slime, Non Toxic Gift for Artist Kids Toddler Boys Girls, 6-Pack | D547: FBA_3350-SET6 | E547: 146 | F547: 2 | G547: 0.0001 | H547: 193 | I547: 3 | J547: 19 | K547: 200.21
A548: B09235HZC1 | B548: B08CYCJ3B6 | C548: BAZIC Products Plastic File Folder Case w/Handle, Letter Size File Folders Wallet, Black Color, Portable Paper Documents Organizer, Office Supplies, 1-Pack | D548: FBA_3124-EACH | E548: 243 | F548: 9 | G548: 0.0002 | H548: 344 | I548: 9 | J548: 33 | K548: 309.69
A549: B09235W5N6 | B549: B08FF4TJ73 | C549: BAZIC Pink Eraser, Latex Free Bevel Erasers, Large Size Block Erasers for Art Drawing School Office Kids Teachers, Total 24 Count | D549: 2235-BOX | E549: 173 | F549: 9 | G549: 0.0001 | H549: 225 | I549: 12 | J549: 20 | K549: 297.8
A550: B0925G5DW6 | B550: B08FRRVHV5 | C550: BAZIC Products Washable Markers Broad Line 8 Color Triangle Jumbo Coloring Marker, Non Toxic Marcadorc Art School Supplies, Gift (8/Pack), 2-Packs | D550: FBA_1228-PACK2 | E550: 136 | F550: 7 | G550: 0.0001 | H550: 170 | I550: 9 | J550: 22 | K550: 158.18
... A560: B09235XFD3 | B560: B07RZ2X267 | C560: BAZIC Products Expanding File Folder 7 Pockets w/Color Tab, Letter Size Plastic File Pocket Folders, Home Office Supplies, Paper Documents Organizer, 1-Pack | D560: FBA_3164-EACH | E560: 421 | F560: 12 | G560: 0.0003 | H560: 522 | I560: 13 | J560: 17 | K560: 145.83
A561: B092G8DKDJ | B561: B07SDKYVYB | D561: 1723-EACH | E561: 144 | F561: 5 | G561: 0.0001 | H561: 179 | I561: 6 | J561: 19 | K561: 126.95
A562: B0921XXD3V | B562: B07X49ZTWW | C562: BAZIC Self Seal White Envelope 3 5/8" x 6 1/2" #6, No Window Mailing Envelopes, Peel & Seal Mailer for Business Invoice Check (100/Pack), 24-Packs | D562: FBA_572-CASE | E562: 41 | F562: 5 | G562: 0 | H562: 52 | I562: 6 | J562: 20 | K562: 1421.8
A563: B091BLJ36Q | B563: B08BQXSGRP | C563: KAPPA Take Along Large Print Word Finds Puzzle Book - 8" x 5" Digest Size 2 Titles, Word Search Find Words Books for Adults Teens, Training Learning with Game, 24-Pack | D563: FBA_3388-CASE | E563: 194 | F563: 13 | G563: 0.0001 | H563: 242 | I563: 17 | J563: 24 | K563: 863.28
A564: B091BM5FT8 | B564: B08BX4PKB1 | C564: PAW Patrol Coloring Book 2-Title, Fun Game Workbook for Learning Drawing Coloring, Gift for Kids Toddler Activity at Classroom Home, 2-Pack | D564: 4576336-SET2 | E564: 534 | F564: 9 | G564: 0.0003 | H564: 669 | I564: 10 | J564: 19 | K564: 227.81
A565: B092BQK26F | B565: B08DFJD25N | C565: BAZIC Products Composition Notebook Wide Ruled - 20 Sheets, Manila Color Composition Notebook with Durable Cover, Non-Spiral and Lined Paper for Journaling, School, Home, or Office, 2-Packs | D565: 5096-PACK2 | E565: 178 | F565: 11 | G565: 0.0001 | H565: 221 | I565: 13 | J565: 17 | K565: 138.31
A566: B0D7GHTQF4 | B566: B08KJN9SF3 | C566: BAZIC Products Modeling Clay Gray Color 1 LB, Light Dough Art Craft, Non Toxic Gift for Artist Kids Toddler Boys Girls, Bulk for Classroom, 2-Pack | D566: 3335-PACK2 | E566: 60 | F566: 9 | G566: 0 | H566: 78 | I566: 14 | J566: 24 | K566: 415.34
A567: B0BDSQ8PCV | B567: B0BDSR46YY | C567: BAZIC Products White Board 5"x7", Magnet Attached to Locker, Small Plastic Frame Dry Erase Board 1 Dry Erase Marker, 4-Pack | D567: FBA_6023-CASE | E567: 110 | F567: 10 | G567: 0.0001 | H567: 138 | I567: 15 | J567: 18 | K567: 590.34
A568: B0923CG126 | B568: B07QXVJFTP | C568: BAZIC Products Neon Highlighter – Yellow Pen Style, Chisel Tip Broad Fine Line, Desk Style Highlighter Pen for Office, School, and Study Use, Fluorescent Yellow Ink, Smooth Marking, 5/Pack, 1-Pack | D568: 2300-EACH | E568: 988 | F568: 35 | G568: 0.0006 | H568: 1212 | I568: 46 | J568: 15 | K568: 94.35
A569: B0921N2DQ1 | B569: B07R3R6V45 | C569: BAZIC Products Plastic Clipboard Memo Size 9" x 6", Low Profile Clip, Mini Small Clip Board, Translucent Color, for Office School Teacher Student, 4-Pack | D569: FBA_1801-SET4 | E569: 186 | F569: 16 | G569: 0.0001 | H569: 257 | I569: 24 | J569: 16 | K569: 192.98
A570: B091V4K8K5 | B570: B07RGMD182 | C570: BAZIC Products Pocket Size Calculator 8-Digit w/Flip Cover, LCD Display, Small Standard Function Electronics Calculators, for Daily & Office, Black, 1-Pack | D570: 3004-EACH | E570: 209 | F570: 7 | G570: 0.0001 | H570: 285 | I570: 7 | J570: 17 | K570: 121.25
A571: B092H6V1L5 | B571: B07S65NJNN | C571: BAZIC Products Oil Gel Ink Retractable Pen Optima Black Color, 0.7 mm Medium Point Soft Grip Smooth Writing, for Office School (3/Pack), 1-Pack | D571: 1795-EACH | E571: 212 | F571: 5 | G571: 0.0001 | H571: 261 | I571: 7 | J571: 15 | K571: 95.75
A572: B092GBMVGS | B572: B07S65QQ82 | C572: BAZIC Products Ballpoint Pen Ixion Black Ink Color Barrels Retractable Pens, 1.0 mm Bold Point Smooth Writing, for Office School Teacher (5/Pack), 1-Pack | D572: FBA_1770-EACH | E572: 476 | F572: 6 | G572: 0.0003 | H572: 594 | I572: 6 | J572: 15 | K572: 67.45
