Workbook

Sheet For WH
A1: SKU | B1: ASIN | C1: FNSKU | D1: Item # | E1: Total EA (Transfer to WH06) | F1: Sellable Unit/Set/box to ship | G1: Box to pull | H1: Case to pull | I1: Sets per Box/Case | J1: Label | K1: Packing Instructions | L1: Supplies | M1: UoM | N1: BOX | O1: CASE | P1: Recommended Replenishment Qty | Q1: Actual Qty Replenished | R1: Current WH Inventory | S1: Pack Unit
A2: 8006-CASE | B2: B0BG14KCKZ | C2: X003XE2C7F | D2: =IFERROR(VLOOKUP(A2,Data1!A:B,2,0),"") -> 8006 | E2: =M2*Q2 -> 5235 | F2: =E2/M2 -> 5235 | G2: =IFERROR(ROUNDUP(E2/N2,0),"") | H2: =IFERROR(ROUNDUP(E2/O2,0),"") -> 1047 | I2: =IFERROR(IF(S2="CASE",F2/H2,F2/G2),"") -> 5 | J2: =IF(ISNUMBER(SEARCH("FNSKU",C2)),"Labeling","") | K2: =IFERROR(VLOOKUP(A2,Instruction!A:F,6,0),"") -> • Prepack. Seal box. Apply FNSKU label on box. • Pack in BX-191313 • Apply outer case label (Cover all existing barcodes on case) | L2: =IFERROR(VLOOKUP(A2,Instruction!A:J,10,0),"No Supplies") -> BX-12123, Seal w/ White sticker. BX191313 | M2: =IFERROR(VLOOKUP(A2,Data1!A:C,3,0),1) -> 1 | N2: =IFERROR(VLOOKUP(D2,Data2!$A:$D,4,0),"") -> 0 | O2: =IFERROR(VLOOKUP(D2,Data2!$A:$C,3,0),"") -> 5 | P2: 5235 | Q2: 5235 | S2: CASE
A3: 2227-EACH-UPC | B3: B001BNW7QA | C3: B001BNW7QA | D3: =IFERROR(VLOOKUP(A3,Data1!A:B,2,0),"") -> 2227 | E3: =M3*Q3 -> 3024 | F3: =E3/M3 -> 3024 | G3: =IFERROR(ROUNDUP(E3/N3,0),"") -> 126 | H3: =IFERROR(ROUNDUP(E3/O3,0),"") -> 42 | I3: =IFERROR(IF(S3="CASE",F3/H3,F3/G3),"") -> 72 | J3: =IF(ISNUMBER(SEARCH("FNSKU",C3)),"Labeling","") | K3: =IFERROR(VLOOKUP(A3,Instruction!A:F,6,0),"") -> Apply outer box/case label accordingly to match item# (Cover all existing barcodes on the box/case) | L3: =IFERROR(VLOOKUP(A3,Instruction!A:J,10,0),"No Supplies") -> No Supplies | M3: =IFERROR(VLOOKUP(A3,Data1!A:C,3,0),1) -> 1 | N3: =IFERROR(VLOOKUP(D3,Data2!$A:$D,4,0),"") -> 24 | O3: =IFERROR(VLOOKUP(D3,Data2!$A:$C,3,0),"") -> 72 | P3: 3058 | Q3: 3024 | S3: CASE
A4: 2202-EACH | B4: B003BNZVI4 | C4: B003BNZVI4 | D4: =IFERROR(VLOOKUP(A4,Data1!A:B,2,0),"") -> 2202 | E4: =M4*Q4 -> 1584 | F4: =E4/M4 -> 1584 | G4: =IFERROR(ROUNDUP(E4/N4,0),"") -> 66 | H4: =IFERROR(ROUNDUP(E4/O4,0),"") -> 11 | I4: =IFERROR(IF(S4="CASE",F4/H4,F4/G4),"") -> 144 | J4: =IF(ISNUMBER(SEARCH("FNSKU",C4)),"Labeling","") | K4: =IFERROR(VLOOKUP(A4,Instruction!A:F,6,0),"") -> Apply outer box/case label accordingly to match item# (Cover all existing barcodes on the box/case) | L4: =IFERROR(VLOOKUP(A4,Instruction!A:J,10,0),"No Supplies") -> No Supplies | M4: =IFERROR(VLOOKUP(A4,Data1!A:C,3,0),1) -> 1 | N4: =IFERROR(VLOOKUP(D4,Data2!$A:$D,4,0),"") -> 24 | O4: =IFERROR(VLOOKUP(D4,Data2!$A:$C,3,0),"") -> 144 | P4: 1594 | Q4: 1584 | S4: CASE
A5: 808-EACH | B5: B09DP3TR4F | C5: B09DP3TR4F | D5: =IFERROR(VLOOKUP(A5,Data1!A:B,2,0),"") -> 808 | E5: =M5*Q5 -> 1440 | F5: =E5/M5 -> 1440 | G5: =IFERROR(ROUNDUP(E5/N5,0),"") -> 60 | H5: =IFERROR(ROUNDUP(E5/O5,0),"") -> 10 | I5: =IFERROR(IF(S5="CASE",F5/H5,F5/G5),"") -> 144 | J5: =IF(ISNUMBER(SEARCH("FNSKU",C5)),"Labeling","") | K5: =IFERROR(VLOOKUP(A5,Instruction!A:F,6,0),"") -> Apply outer box/case label accordingly to match item# (Cover all existing barcodes on the box/case) | L5: =IFERROR(VLOOKUP(A5,Instruction!A:J,10,0),"No Supplies") -> No Supplies | M5: =IFERROR(VLOOKUP(A5,Data1!A:C,3,0),1) -> 1 | N5: =IFERROR(VLOOKUP(D5,Data2!$A:$D,4,0),"") -> 24 | O5: =IFERROR(VLOOKUP(D5,Data2!$A:$C,3,0),"") -> 144 | P5: 1509 | Q5: 1440 | S5: CASE
A6: 5043-EACH | B6: B00H9Z198Q | C6: B00H9Z198Q | D6: =IFERROR(VLOOKUP(A6,Data1!A:B,2,0),"") -> 5043 | E6: =M6*Q6 -> 1296 | F6: =E6/M6 -> 1296 | G6: =IFERROR(ROUNDUP(E6/N6,0),"") | H6: =IFERROR(ROUNDUP(E6/O6,0),"") -> 27 | I6: =IFERROR(IF(S6="CASE",F6/H6,F6/G6),"") -> 48 | J6: =IF(ISNUMBER(SEARCH("FNSKU",C6)),"Labeling","") | K6: =IFERROR(VLOOKUP(A6,Instruction!A:F,6,0),"") -> Apply outer box/case label accordingly to match item# (Cover all existing barcodes on the box/case) | L6: =IFERROR(VLOOKUP(A6,Instruction!A:J,10,0),"No Supplies") -> No Supplies | M6: =IFERROR(VLOOKUP(A6,Data1!A:C,3,0),1) -> 1 | N6: =IFERROR(VLOOKUP(D6,Data2!$A:$D,4,0),"") -> 0 | O6: =IFERROR(VLOOKUP(D6,Data2!$A:$C,3,0),"") -> 48 | P6: 1314 | Q6: 1296 | S6: CASE
A7: 510-EACH-B | B7: B0018MN4RA | D7: =IFERROR(VLOOKUP(A7,Data1!A:B,2,0),"") -> 510 | E7: =M7*Q7 -> 1300 | F7: =E7/M7 -> 1300 | G7: =IFERROR(ROUNDUP(E7/N7,0),"") | H7: =IFERROR(ROUNDUP(E7/O7,0),"") -> 26 | I7: =IFERROR(IF(S7="CASE",F7/H7,F7/G7),"") -> 50 | J7: =IF(ISNUMBER(SEARCH("FNSKU",C7)),"Labeling","") | K7: =IFERROR(VLOOKUP(A7,Instruction!A:F,6,0),"") -> Apply outer case label accordingly to match item# (Cover all existing barcodes on the case) | L7: =IFERROR(VLOOKUP(A7,Instruction!A:J,10,0),"No Supplies") -> No Supplies | M7: =IFERROR(VLOOKUP(A7,Data1!A:C,3,0),1) -> 1 | N7: =IFERROR(VLOOKUP(D7,Data2!$A:$D,4,0),"") -> 0 | O7: =IFERROR(VLOOKUP(D7,Data2!$A:$C,3,0),"") -> 50 | P7: 1280 | Q7: 1300 | S7: CASE
A8: 3107-EACH | B8: B07S4GZW7L | C8: X003BBR0T5 | D8: =IFERROR(VLOOKUP(A8,Data1!A:B,2,0),"") -> 3107 | E8: =M8*Q8 -> 1296 | F8: =E8/M8 -> 1296 | G8: =IFERROR(ROUNDUP(E8/N8,0),"") -> 54 | H8: =IFERROR(ROUNDUP(E8/O8,0),"") -> 9 | I8: =IFERROR(IF(S8="CASE",F8/H8,F8/G8),"") -> 144 | J8: =IF(ISNUMBER(SEARCH("FNSKU",C8)),"Labeling","") | K8: =IFERROR(VLOOKUP(A8,Instruction!A:F,6,0),"") -> • Use FNSKU to label each item (cover barcode). Apply outer box/case label accordingly to match item# (Cover all existing barcodes on the box/case) | L8: =IFERROR(VLOOKUP(A8,Instruction!A:J,10,0),"No Supplies") -> No Supplies | M8: =IFERROR(VLOOKUP(A8,Data1!A:C,3,0),1) -> 1 | N8: =IFERROR(VLOOKUP(D8,Data2!$A:$D,4,0),"") -> 24 | O8: =IFERROR(VLOOKUP(D8,Data2!$A:$C,3,0),"") -> 144 | P8: 1277 | Q8: 1296 | S8: CASE
A9: 3100-EACH | B9: B00ZPRYV0I | C9: B00ZPRYV0I | D9: =IFERROR(VLOOKUP(A9,Data1!A:B,2,0),"") -> 3100 | E9: =M9*Q9 -> 1248 | F9: =E9/M9 -> 1248 | G9: =IFERROR(ROUNDUP(E9/N9,0),"") | H9: =IFERROR(ROUNDUP(E9/O9,0),"") -> 26 | I9: =IFERROR(IF(S9="CASE",F9/H9,F9/G9),"") -> 48 | J9: =IF(ISNUMBER(SEARCH("FNSKU",C9)),"Labeling","") | K9: =IFERROR(VLOOKUP(A9,Instruction!A:F,6,0),"") -> Apply outer box/case label accordingly to match item# (Cover all existing barcodes on the box/case) | L9: =IFERROR(VLOOKUP(A9,Instruction!A:J,10,0),"No Supplies") -> No Supplies | M9: =IFERROR(VLOOKUP(A9,Data1!A:C,3,0),1) -> 1 | N9: =IFERROR(VLOOKUP(D9,Data2!$A:$D,4,0),"") -> 0 | O9: =IFERROR(VLOOKUP(D9,Data2!$A:$C,3,0),"") -> 48 | P9: 1245 | Q9: 1248 | S9: CASE
A10: 5053-SET2 | B10: B07S64FRBG | C10: X003AUSTNN | D10: =IFERROR(VLOOKUP(A10,Data1!A:B,2,0),"") -> 5053 | E10: =M10*Q10 -> 2352 | F10: =E10/M10 -> 1176 | G10: =IFERROR(ROUNDUP(E10/N10,0),"") | H10: =IFERROR(ROUNDUP(E10/O10,0),"") -> 49 | I10: =IFERROR(IF(S10="CASE",F10/H10,F10/G10),"") -> 24 | J10: =IF(ISNUMBER(SEARCH("FNSKU",C10)),"Labeling","") | K10: =IFERROR(VLOOKUP(A10,Instruction!A:F,6,0),"") -> • Insert 2 pcs per poly bag (Blue & Red). Apply FNSKU labels on each of the poly bags. • Insert the poly-bagged sets back to CASE (Cover all existing barcodes on the box/case) | L10: =IFERROR(VLOOKUP(A10,Instruction!A:J,10,0),"No Supplies") -> Poly Bag 9 x 12 | M10: =IFERROR(VLOOKUP(A10,Data1!A:C,3,0),1) -> 2 | N10: =IFERROR(VLOOKUP(D10,Data2!$A:$D,4,0),"") -> 0 | O10: =IFERROR(VLOOKUP(D10,Data2!$A:$C,3,0),"") -> 48 | P10: 1175 | Q10: 1176 | S10: CASE
A11: 8005-CASE-B | B11: B0BB8R9HGQ | C11: B0BB8R9HGQ | D11: =IFERROR(VLOOKUP(A11,Data1!A:B,2,0),"") -> 8005 | E11: =M11*Q11 -> 1085 | F11: =E11/M11 -> 1085 | G11: =IFERROR(ROUNDUP(E11/N11,0),"") | H11: =IFERROR(ROUNDUP(E11/O11,0),"") -> 217 | I11: =IFERROR(IF(S11="CASE",F11/H11,F11/G11),"") -> 5 | J11: =IF(ISNUMBER(SEARCH("FNSKU",C11)),"Labeling","") | K11: =IFERROR(VLOOKUP(A11,Instruction!A:F,6,0),"") -> • Prepack. Seal box. Apply FNSKU label on box. • Pack in BX-191313 • Apply outer case label (Cover all existing barcodes on case) | L11: =IFERROR(VLOOKUP(A11,Instruction!A:J,10,0),"No Supplies") -> 0 | M11: =IFERROR(VLOOKUP(A11,Data1!A:C,3,0),1) -> 1 | N11: =IFERROR(VLOOKUP(D11,Data2!$A:$D,4,0),"") -> 0 | O11: =IFERROR(VLOOKUP(D11,Data2!$A:$C,3,0),"") -> 5 | P11: 1087 | Q11: 1085 | S11: CASE
A12: 2306-EACH-1 | B12: B008ZHNN68 | C12: B008ZHNN68 | D12: =IFERROR(VLOOKUP(A12,Data1!A:B,2,0),"") -> 2306 | E12: =M12*Q12 -> 1152 | F12: =E12/M12 -> 1152 | G12: =IFERROR(ROUNDUP(E12/N12,0),"") -> 48 | H12: =IFERROR(ROUNDUP(E12/O12,0),"") -> 8 | I12: =IFERROR(IF(S12="CASE",F12/H12,F12/G12),"") -> 144 | J12: =IF(ISNUMBER(SEARCH("FNSKU",C12)),"Labeling","") | K12: =IFERROR(VLOOKUP(A12,Instruction!A:F,6,0),"") -> Cover inner box barcode. Apply outer case label accordingly to match item# (Cover barcodes on the case) | L12: =IFERROR(VLOOKUP(A12,Instruction!A:J,10,0),"No Supplies") -> No Supplies | M12: =IFERROR(VLOOKUP(A12,Data1!A:C,3,0),1) -> 1 | N12: =IFERROR(VLOOKUP(D12,Data2!$A:$D,4,0),"") -> 24 | O12: =IFERROR(VLOOKUP(D12,Data2!$A:$C,3,0),"") -> 144 | P12: 1087 | Q12: 1152 | S12: CASE
A13: 4106-EACH | B13: B07Q5VPWCP | C13: X003SC97LL | D13: =IFERROR(VLOOKUP(A13,Data1!A:B,2,0),"") -> 4106 | E13: =M13*Q13 -> 1068 | F13: =E13/M13 -> 1068 | G13: =IFERROR(ROUNDUP(E13/N13,0),"") | H13: =IFERROR(ROUNDUP(E13/O13,0),"") -> 89 | I13: =IFERROR(IF(S13="CASE",F13/H13,F13/G13),"") -> 12 | J13: =IF(ISNUMBER(SEARCH("FNSKU",C13)),"Labeling","") | K13: =IFERROR(VLOOKUP(A13,Instruction!A:F,6,0),"") -> • Use FNSKU to label each item (cover barcode). Apply outer box/case label accordingly to match item# (Cover all existing barcodes on the box/case) | L13: =IFERROR(VLOOKUP(A13,Instruction!A:J,10,0),"No Supplies") -> No Supplies | M13: =IFERROR(VLOOKUP(A13,Data1!A:C,3,0),1) -> 1 | N13: =IFERROR(VLOOKUP(D13,Data2!$A:$D,4,0),"") -> 0 | O13: =IFERROR(VLOOKUP(D13,Data2!$A:$C,3,0),"") -> 12 | P13: 1068 | Q13: 1068 | S13: CASE
A14: 582-SET6 | B14: B07S964BMT | C14: X003SC1YG7 | D14: =IFERROR(VLOOKUP(A14,Data1!A:B,2,0),"") -> 582 | E14: =M14*Q14 -> 6288 | F14: =E14/M14 -> 1048 | G14: =IFERROR(ROUNDUP(E14/N14,0),"") | H14: =IFERROR(ROUNDUP(E14/O14,0),"") -> 262 | I14: =IFERROR(IF(S14="CASE",F14/H14,F14/G14),"") -> 4 | J14: =IF(ISNUMBER(SEARCH("FNSKU",C14)),"Labeling","") | K14: =IFERROR(VLOOKUP(A14,Instruction!A:F,6,0),"") -> • Insert 6 pcs per poly bag (6 different color). Apply FNSKU labels on each of the poly bags. • Insert the poly-bagged sets back to CASE (Cover all existing barcodes on the box/case) • New box size BX- 13.25 x 10.75 x 12.75 | L14: =IFERROR(VLOOKUP(A14,Instruction!A:J,10,0),"No Supplies") -> Poly Bag 12 x 15.5 | M14: =IFERROR(VLOOKUP(A14,Data1!A:C,3,0),1) -> 6 | N14: =IFERROR(VLOOKUP(D14,Data2!$A:$D,4,0),"") -> 0 | O14: =IFERROR(VLOOKUP(D14,Data2!$A:$C,3,0),"") -> 24 | P14: 1047 | Q14: 1048 | S14: CASE
A15: 336-EACH | B15: B003BMX65A | C15: X003TIPAXN | D15: =IFERROR(VLOOKUP(A15,Data1!A:B,2,0),"") -> 336 | E15: =M15*Q15 -> 1008 | F15: =E15/M15 -> 1008 | G15: =IFERROR(ROUNDUP(E15/N15,0),"") -> 42 | H15: =IFERROR(ROUNDUP(E15/O15,0),"") -> 7 | I15: =IFERROR(IF(S15="CASE",F15/H15,F15/G15),"") -> 144 | J15: =IF(ISNUMBER(SEARCH("FNSKU",C15)),"Labeling","") | K15: =IFERROR(VLOOKUP(A15,Instruction!A:F,6,0),"") -> • Use FNSKU to label each item (cover barcode). Apply outer box/case label accordingly to match item# (Cover all existing barcodes on the box/case) | L15: =IFERROR(VLOOKUP(A15,Instruction!A:J,10,0),"No Supplies") -> No Supplies | M15: =IFERROR(VLOOKUP(A15,Data1!A:C,3,0),1) -> 1 | N15: =IFERROR(VLOOKUP(D15,Data2!$A:$D,4,0),"") -> 24 | O15: =IFERROR(VLOOKUP(D15,Data2!$A:$C,3,0),"") -> 144 | P15: 1000 | Q15: 1008 | S15: CASE
A16: 4146-EACH | B16: B07Q97RZJC | C16: X003L8UNND | D16: =IFERROR(VLOOKUP(A16,Data1!A:B,2,0),"") -> 4146 | E16: =M16*Q16 -> 984 | F16: =E16/M16 -> 984 | G16: =IFERROR(ROUNDUP(E16/N16,0),"") | H16: =IFERROR(ROUNDUP(E16/O16,0),"") -> 82 | I16: =IFERROR(IF(S16="CASE",F16/H16,F16/G16),"") -> 12 | J16: =IF(ISNUMBER(SEARCH("FNSKU",C16)),"Labeling","") | K16: =IFERROR(VLOOKUP(A16,Instruction!A:F,6,0),"") -> • Use FNSKU to label each item (cover barcode). Apply outer box/case label accordingly to match item# (Cover all existing barcodes on the box/case) | L16: =IFERROR(VLOOKUP(A16,Instruction!A:J,10,0),"No Supplies") -> No Supplies | M16: =IFERROR(VLOOKUP(A16,Data1!A:C,3,0),1) -> 1 | N16: =IFERROR(VLOOKUP(D16,Data2!$A:$D,4,0),"") -> 0 | O16: =IFERROR(VLOOKUP(D16,Data2!$A:$C,3,0),"") -> 12 | P16: 983 | Q16: 984 | S16: CASE
A17: 5045-EACH | B17: B07S94M6P6 | C17: X003DE6G1X | D17: =IFERROR(VLOOKUP(A17,Data1!A:B,2,0),"") -> 5045 | E17: =M17*Q17 -> 960 | F17: =E17/M17 -> 960 | G17: =IFERROR(ROUNDUP(E17/N17,0),"") | H17: =IFERROR(ROUNDUP(E17/O17,0),"") -> 20 | I17: =IFERROR(IF(S17="CASE",F17/H17,F17/G17),"") -> 48 | J17: =IF(ISNUMBER(SEARCH("FNSKU",C17)),"Labeling","") | K17: =IFERROR(VLOOKUP(A17,Instruction!A:F,6,0),"") -> • Use FNSKU to label each item (cover barcode). Apply outer box/case label accordingly to match item# (Cover all existing barcodes on the box/case) | L17: =IFERROR(VLOOKUP(A17,Instruction!A:J,10,0),"No Supplies") -> No Supplies | M17: =IFERROR(VLOOKUP(A17,Data1!A:C,3,0),1) -> 1 | N17: =IFERROR(VLOOKUP(D17,Data2!$A:$D,4,0),"") -> 0 | O17: =IFERROR(VLOOKUP(D17,Data2!$A:$C,3,0),"") -> 48 | P17: 957 | Q17: 960 | S17: CASE
A18: 4107-EACH | B18: B07Q84RJLP | C18: X003L8W44J | D18: =IFERROR(VLOOKUP(A18,Data1!A:B,2,0),"") -> 4107 | E18: =M18*Q18 -> 852 | F18: =E18/M18 -> 852 | G18: =IFERROR(ROUNDUP(E18/N18,0),"") | H18: =IFERROR(ROUNDUP(E18/O18,0),"") -> 71 | I18: =IFERROR(IF(S18="CASE",F18/H18,F18/G18),"") -> 12 | J18: =IF(ISNUMBER(SEARCH("FNSKU",C18)),"Labeling","") | K18: =IFERROR(VLOOKUP(A18,Instruction!A:F,6,0),"") -> • Use FNSKU to label each item (cover barcode). Apply outer box/case label accordingly to match item# (Cover all existing barcodes on the box/case) | L18: =IFERROR(VLOOKUP(A18,Instruction!A:J,10,0),"No Supplies") -> No Supplies | M18: =IFERROR(VLOOKUP(A18,Data1!A:C,3,0),1) -> 1 | N18: =IFERROR(VLOOKUP(D18,Data2!$A:$D,4,0),"") -> 0 | O18: =IFERROR(VLOOKUP(D18,Data2!$A:$C,3,0),"") -> 12 | P18: 857 | Q18: 852 | S18: CASE
A19: 2170-SET6 | B19: B07S165T2T | C19: X003SBSK1F | D19: =IFERROR(VLOOKUP(A19,Data1!A:B,2,0),"") -> 2170 | E19: =M19*Q19 -> 4896 | F19: =E19/M19 -> 816 | G19: =IFERROR(ROUNDUP(E19/N19,0),"") | H19: =IFERROR(ROUNDUP(E19/O19,0),"") -> 102 | I19: =IFERROR(IF(S19="CASE",F19/H19,F19/G19),"") -> 8 | J19: =IF(ISNUMBER(SEARCH("FNSKU",C19)),"Labeling","") | K19: =IFERROR(VLOOKUP(A19,Instruction!A:F,6,0),"") -> • Insert 6 pcs per poly bag (6 different color). Apply FNSKU labels on each of the poly bags. • Insert the poly-bagged sets back to CASE (Cover all existing barcodes on the box/case) | L19: =IFERROR(VLOOKUP(A19,Instruction!A:J,10,0),"No Supplies") -> Poly Bag 12 x 15.5 | M19: =IFERROR(VLOOKUP(A19,Data1!A:C,3,0),1) -> 6 | N19: =IFERROR(VLOOKUP(D19,Data2!$A:$D,4,0),"") -> 0 | O19: =IFERROR(VLOOKUP(D19,Data2!$A:$C,3,0),"") -> 48 | P19: 812 | Q19: 816 | S19: CASE
... A89: 543-PACK2 | B89: B08DFHV95M | C89: X0040DZIND | D89: =IFERROR(VLOOKUP(A89,Data1!A:B,2,0),"") -> 543 | E89: =M89*Q89 -> 432 | F89: =E89/M89 -> 216 | G89: =IFERROR(ROUNDUP(E89/N89,0),"") | H89: =IFERROR(ROUNDUP(E89/O89,0),"") -> 9 | I89: =IFERROR(IF(S89="CASE",F89/H89,F89/G89),"") -> 24 | J89: =IF(ISNUMBER(SEARCH("FNSKU",C89)),"Labeling","") | K89: =IFERROR(VLOOKUP(A89,Instruction!A:F,6,0),"") -> • Put 2 pcs into poly bag, apply FNSKU label. • Put back to CASE (Cover all existing barcodes on the box/case) | L89: =IFERROR(VLOOKUP(A89,Instruction!A:J,10,0),"No Supplies") -> Poly Bag 9 x 12 | M89: =IFERROR(VLOOKUP(A89,Data1!A:C,3,0),1) -> 2 | N89: =IFERROR(VLOOKUP(D89,Data2!$A:$D,4,0),"") -> 0 | O89: =IFERROR(VLOOKUP(D89,Data2!$A:$C,3,0),"") -> 48 | P89: 211 | Q89: 216 | S89: CASE
A90: 1621-EACH | B90: B07RFTSF59 | D90: =IFERROR(VLOOKUP(A90,Data1!A:B,2,0),"") -> 1621 | E90: =M90*Q90 -> 144 | F90: =E90/M90 -> 144 | G90: =IFERROR(ROUNDUP(E90/N90,0),"") -> 6 | H90: =IFERROR(ROUNDUP(E90/O90,0),"") -> 1 | I90: =IFERROR(IF(S90="CASE",F90/H90,F90/G90),"") -> 144 | J90: =IF(ISNUMBER(SEARCH("FNSKU",C90)),"Labeling","") | K90: • Use FNSKU to label each item (cover barcode). • Put item back to CASE. Discard inner box • Apply outer case label accordingly to match item# (Cover all existing barcodes on the case) | L90: =IFERROR(VLOOKUP(A90,Instruction!A:J,10,0),"No Supplies") -> No Supplies | M90: =IFERROR(VLOOKUP(A90,Data1!A:C,3,0),1) -> 1 | N90: =IFERROR(VLOOKUP(D90,Data2!$A:$D,4,0),"") -> 24 | O90: =IFERROR(VLOOKUP(D90,Data2!$A:$C,3,0),"") -> 144 | P90: 209 | Q90: 144 | S90: CASE
A91: 5011-PACK2 | B91: B0127E8W0Q | C91: B0127E8W0Q | D91: =IFERROR(VLOOKUP(A91,Data1!A:B,2,0),"") -> 5011 | E91: =M91*Q91 -> 400 | F91: =E91/M91 -> 200 | G91: =IFERROR(ROUNDUP(E91/N91,0),"") | H91: =IFERROR(ROUNDUP(E91/O91,0),"") -> 8 | I91: =IFERROR(IF(S91="CASE",F91/H91,F91/G91),"") -> 25 | J91: =IF(ISNUMBER(SEARCH("FNSKU",C91)),"Labeling","") | K91: =IFERROR(VLOOKUP(A91,Instruction!A:F,6,0),"") -> • Insert 2 pcs into poly bag, apply FNSKU label. • Put back to CASE (Cover all existing barcodes on the box/case) | L91: =IFERROR(VLOOKUP(A91,Instruction!A:J,10,0),"No Supplies") -> Poly Bag 12 x 15.5 | M91: =IFERROR(VLOOKUP(A91,Data1!A:C,3,0),1) -> 2 | N91: =IFERROR(VLOOKUP(D91,Data2!$A:$D,4,0),"") -> 0 | O91: =IFERROR(VLOOKUP(D91,Data2!$A:$C,3,0),"") -> 50 | P91: 208 | Q91: 200 | S91: CASE
A92: 4126-PACK2 | B92: B08DQHV4BN | C92: X0044R3MG5 | D92: =IFERROR(VLOOKUP(A92,Data1!A:B,2,0),"") -> 4126 | E92: =M92*Q92 -> 408 | F92: =E92/M92 -> 204 | G92: =IFERROR(ROUNDUP(E92/N92,0),"") | H92: =IFERROR(ROUNDUP(E92/O92,0),"") -> 34 | I92: =IFERROR(IF(S92="CASE",F92/H92,F92/G92),"") -> 6 | J92: =IF(ISNUMBER(SEARCH("FNSKU",C92)),"Labeling","") | K92: =IFERROR(VLOOKUP(A92,Instruction!A:F,6,0),"") -> • Put 2 pcs into polybag and apply FNSKU labels on each of the poly bags. • Insert the poly-bagged sets back to CASE (Cover all existing barcodes on the box/case) | L92: =IFERROR(VLOOKUP(A92,Instruction!A:J,10,0),"No Supplies") -> Poly Bag 14.5 x 19 | M92: =IFERROR(VLOOKUP(A92,Data1!A:C,3,0),1) -> 2 | N92: =IFERROR(VLOOKUP(D92,Data2!$A:$D,4,0),"") -> 0 | O92: =IFERROR(VLOOKUP(D92,Data2!$A:$C,3,0),"") -> 12 | P92: 206 | Q92: 204 | S92: CASE
A93: 609-PACK2 | B93: B09C2RFDFH | C93: X0044R3MO7 | D93: =IFERROR(VLOOKUP(A93,Data1!A:B,2,0),"") -> 609 | E93: =M93*Q93 -> 432 | F93: =E93/M93 -> 216 | G93: =IFERROR(ROUNDUP(E93/N93,0),"") -> 18 | H93: =IFERROR(ROUNDUP(E93/O93,0),"") -> 6 | I93: =IFERROR(IF(S93="CASE",F93/H93,F93/G93),"") -> 36 | J93: =IF(ISNUMBER(SEARCH("FNSKU",C93)),"Labeling","") | K93: =IFERROR(VLOOKUP(A93,Instruction!A:F,6,0),"") -> • Put 2 pcs into polybag and apply FNSKU labels on each of the poly bags. • Insert the poly-bagged sets back to CASE (Cover all existing barcodes on the box/case) | L93: =IFERROR(VLOOKUP(A93,Instruction!A:J,10,0),"No Supplies") -> Poly Bag 6 x 9 | M93: =IFERROR(VLOOKUP(A93,Data1!A:C,3,0),1) -> 2 | N93: =IFERROR(VLOOKUP(D93,Data2!$A:$D,4,0),"") -> 24 | O93: =IFERROR(VLOOKUP(D93,Data2!$A:$C,3,0),"") -> 72 | P93: 204 | Q93: 216 | S93: CASE
A94: 3171-EACH | B94: B0BP5Q88DW | C94: X0040DP2BL | D94: =IFERROR(VLOOKUP(A94,Data1!A:B,2,0),"") -> 3171 | E94: =M94*Q94 -> 204 | F94: =E94/M94 -> 204 | G94: =IFERROR(ROUNDUP(E94/N94,0),"") | H94: =IFERROR(ROUNDUP(E94/O94,0),"") -> 17 | I94: =IFERROR(IF(S94="CASE",F94/H94,F94/G94),"") -> 12 | J94: =IF(ISNUMBER(SEARCH("FNSKU",C94)),"Labeling","") | K94: =IFERROR(VLOOKUP(A94,Instruction!A:F,6,0),"") -> • Use FNSKU to label each item (cover barcode). Apply outer case label accordingly to match item# (Cover all existing barcodes on the case) | L94: =IFERROR(VLOOKUP(A94,Instruction!A:J,10,0),"No Supplies") -> No Supplies | M94: =IFERROR(VLOOKUP(A94,Data1!A:C,3,0),1) -> 1 | N94: =IFERROR(VLOOKUP(D94,Data2!$A:$D,4,0),"") -> 0 | O94: =IFERROR(VLOOKUP(D94,Data2!$A:$C,3,0),"") -> 12 | P94: 203 | Q94: 204 | S94: CASE
A95: 5472-SET8 | B95: B096BNMBLN | C95: X003EGLP2Z | D95: =IFERROR(VLOOKUP(A95,Data1!A:B,2,0),"") -> 5472 | E95: =M95*Q95 -> 1632 | F95: =E95/M95 -> 204 | G95: =IFERROR(ROUNDUP(E95/N95,0),"") | H95: =IFERROR(ROUNDUP(E95/O95,0),"") -> 34 | I95: =IFERROR(IF(S95="CASE",F95/H95,F95/G95),"") -> 6 | J95: =IF(ISNUMBER(SEARCH("FNSKU",C95)),"Labeling","") | K95: =IFERROR(VLOOKUP(A95,Instruction!A:F,6,0),"") -> • Insert 8 pcs per poly bag (8 different color). Apply FNSKU labels on each of the poly bags. • Insert the poly-bagged sets back to CASE (Cover all existing barcodes on the box/case) • New box size BX- 13.25 x 10.75 x 12.75 | L95: =IFERROR(VLOOKUP(A95,Instruction!A:J,10,0),"No Supplies") -> Poly Bag 9 x 12 | M95: =IFERROR(VLOOKUP(A95,Data1!A:C,3,0),1) -> 8 | N95: =IFERROR(VLOOKUP(D95,Data2!$A:$D,4,0),"") -> 0 | O95: =IFERROR(VLOOKUP(D95,Data2!$A:$C,3,0),"") -> 48 | P95: 202 | Q95: 204 | S95: CASE
A96: 4122-EACH | B96: B07Q97RHBH | C96: X003SBSJEN | D96: =IFERROR(VLOOKUP(A96,Data1!A:B,2,0),"") -> 4122 | E96: =M96*Q96 -> 204 | F96: =E96/M96 -> 204 | G96: =IFERROR(ROUNDUP(E96/N96,0),"") | H96: =IFERROR(ROUNDUP(E96/O96,0),"") -> 17 | I96: =IFERROR(IF(S96="CASE",F96/H96,F96/G96),"") -> 12 | J96: =IF(ISNUMBER(SEARCH("FNSKU",C96)),"Labeling","") | K96: =IFERROR(VLOOKUP(A96,Instruction!A:F,6,0),"") -> • Use FNSKU to label each item (cover barcode). Apply outer box/case label accordingly to match item# (Cover all existing barcodes on the box/case) | L96: =IFERROR(VLOOKUP(A96,Instruction!A:J,10,0),"No Supplies") -> No Supplies | M96: =IFERROR(VLOOKUP(A96,Data1!A:C,3,0),1) -> 1 | N96: =IFERROR(VLOOKUP(D96,Data2!$A:$D,4,0),"") -> 0 | O96: =IFERROR(VLOOKUP(D96,Data2!$A:$C,3,0),"") -> 12 | P96: 200 | Q96: 204 | S96: CASE
A97: 520-EACH | B97: B07S962L7Q | C97: X0044RLTFV | D97: =IFERROR(VLOOKUP(A97,Data1!A:B,2,0),"") -> 520 | E97: =M97*Q97 -> 216 | F97: =E97/M97 -> 216 | G97: =IFERROR(ROUNDUP(E97/N97,0),"") | H97: =IFERROR(ROUNDUP(E97/O97,0),"") -> 6 | I97: =IFERROR(IF(S97="CASE",F97/H97,F97/G97),"") -> 36 | J97: =IF(ISNUMBER(SEARCH("FNSKU",C97)),"Labeling","") | K97: =IFERROR(VLOOKUP(A97,Instruction!A:F,6,0),"") -> • Use FNSKU to label each item (cover barcode). Apply outer case label accordingly to match item# (Cover all existing barcodes on the case) | L97: =IFERROR(VLOOKUP(A97,Instruction!A:J,10,0),"No Supplies") -> No Supplies | M97: =IFERROR(VLOOKUP(A97,Data1!A:C,3,0),1) -> 1 | N97: =IFERROR(VLOOKUP(D97,Data2!$A:$D,4,0),"") -> 0 | O97: =IFERROR(VLOOKUP(D97,Data2!$A:$C,3,0),"") -> 36 | P97: 199 | Q97: 216 | S97: CASE
A98: 2309-EACH | B98: B0BP5FBZKF | C98: X003TDI6Z7 | D98: =IFERROR(VLOOKUP(A98,Data1!A:B,2,0),"") -> 2309 | E98: =M98*Q98 -> 144 | F98: =E98/M98 -> 144 | G98: =IFERROR(ROUNDUP(E98/N98,0),"") -> 6 | H98: =IFERROR(ROUNDUP(E98/O98,0),"") -> 1 | I98: =IFERROR(IF(S98="CASE",F98/H98,F98/G98),"") -> 144 | J98: =IF(ISNUMBER(SEARCH("FNSKU",C98)),"Labeling","") | K98: =IFERROR(VLOOKUP(A98,Instruction!A:F,6,0),"") -> • Use FNSKU to label each item (cover barcode). • Put item back to CASE. Discard inner box • Apply outer case label accordingly to match item# (Cover all existing barcodes on the case) | L98: =IFERROR(VLOOKUP(A98,Instruction!A:J,10,0),"No Supplies") -> No Supplies | M98: =IFERROR(VLOOKUP(A98,Data1!A:C,3,0),1) -> 1 | N98: =IFERROR(VLOOKUP(D98,Data2!$A:$D,4,0),"") -> 24 | O98: =IFERROR(VLOOKUP(D98,Data2!$A:$C,3,0),"") -> 144 | P98: 197 | Q98: 144 | S98: CASE
A99: 4104-EACH | B99: B07Q97R8X9 | C99: X003SC1YCL | D99: =IFERROR(VLOOKUP(A99,Data1!A:B,2,0),"") -> 4104 | E99: =M99*Q99 -> 192 | F99: =E99/M99 -> 192 | G99: =IFERROR(ROUNDUP(E99/N99,0),"") | H99: =IFERROR(ROUNDUP(E99/O99,0),"") -> 16 | I99: =IFERROR(IF(S99="CASE",F99/H99,F99/G99),"") -> 12 | J99: =IF(ISNUMBER(SEARCH("FNSKU",C99)),"Labeling","") | K99: =IFERROR(VLOOKUP(A99,Instruction!A:F,6,0),"") -> • Use FNSKU to label each item (cover barcode). Apply outer box/case label accordingly to match item# (Cover all existing barcodes on the box/case) | L99: =IFERROR(VLOOKUP(A99,Instruction!A:J,10,0),"No Supplies") -> No Supplies | M99: =IFERROR(VLOOKUP(A99,Data1!A:C,3,0),1) -> 1 | N99: =IFERROR(VLOOKUP(D99,Data2!$A:$D,4,0),"") -> 0 | O99: =IFERROR(VLOOKUP(D99,Data2!$A:$C,3,0),"") -> 12 | P99: 189 | Q99: 192 | S99: CASE
A100: 2010-EACH | B100: B07RZMG648 | D100: =IFERROR(VLOOKUP(A100,Data1!A:B,2,0),"") -> 2010 | E100: =M100*Q100 -> 144 | F100: =E100/M100 -> 144 | G100: =IFERROR(ROUNDUP(E100/N100,0),"") -> 6 | H100: =IFERROR(ROUNDUP(E100/O100,0),"") -> 1 | I100: =IFERROR(IF(S100="CASE",F100/H100,F100/G100),"") -> 144 | J100: =IF(ISNUMBER(SEARCH("FNSKU",C100)),"Labeling","") | K100: • Use FNSKU to label each item (cover barcode). • Put item back to CASE. Discard inner box • Apply outer case label accordingly to match item# (Cover all existing barcodes on the case) | L100: =IFERROR(VLOOKUP(A100,Instruction!A:J,10,0),"No Supplies") -> No Supplies | M100: =IFERROR(VLOOKUP(A100,Data1!A:C,3,0),1) -> 1 | N100: =IFERROR(VLOOKUP(D100,Data2!$A:$D,4,0),"") -> 24 | O100: =IFERROR(VLOOKUP(D100,Data2!$A:$C,3,0),"") -> 144 | P100: 188 | Q100: 144 | S100: CASE
A101: 847-CASE | B101: B08QRLYMJ4 | C101: X003SCCXUD | D101: =IFERROR(VLOOKUP(A101,Data1!A:B,2,0),"") -> 847 | E101: =M101*Q101 -> 4464 | F101: =E101/M101 -> 186 | G101: =IFERROR(ROUNDUP(E101/N101,0),"") | H101: =IFERROR(ROUNDUP(E101/O101,0),"") -> 186 | I101: =IFERROR(IF(S101="CASE",F101/H101,F101/G101),"") -> 1 | J101: =IF(ISNUMBER(SEARCH("FNSKU",C101)),"Labeling","") | K101: =IFERROR(VLOOKUP(A101,Instruction!A:F,6,0),"") -> • Apply label “THIS IS A SET”. Apply FNSKU to each case. • *Make sure all labels stick securely on the case*. Apply outer case label. Cover all visible barcodes on case | L101: =IFERROR(VLOOKUP(A101,Instruction!A:J,10,0),"No Supplies") -> No Supplies | M101: =IFERROR(VLOOKUP(A101,Data1!A:C,3,0),1) -> 24 | N101: =IFERROR(VLOOKUP(D101,Data2!$A:$D,4,0),"") -> 0 | O101: =IFERROR(VLOOKUP(D101,Data2!$A:$C,3,0),"") -> 24 | P101: 186 | Q101: 186 | S101: CASE
A102: 3451-SET6 | B102: B08579RYRM | C102: X003UI8KTN | D102: =IFERROR(VLOOKUP(A102,Data1!A:B,2,0),"") -> 3451 | E102: =M102*Q102 -> 1128 | F102: =E102/M102 -> 188 | G102: =IFERROR(ROUNDUP(E102/N102,0),"") | H102: =IFERROR(ROUNDUP(E102/O102,0),"") -> 47 | I102: =IFERROR(IF(S102="CASE",F102/H102,F102/G102),"") -> 4 | J102: =IF(ISNUMBER(SEARCH("FNSKU",C102)),"Labeling","") | K102: =IFERROR(VLOOKUP(A102,Instruction!A:F,6,0),"") -> • Insert 6 pcs per poly bag (different color). Apply FNSKU labels on each of the poly bags. • Insert the poly-bagged sets back to BX-191313 • New box size BX- 14 x 13.75 x 16.75 | L102: =IFERROR(VLOOKUP(A102,Instruction!A:J,10,0),"No Supplies") -> Poly Bag 10 x 13 | M102: =IFERROR(VLOOKUP(A102,Data1!A:C,3,0),1) -> 6 | N102: =IFERROR(VLOOKUP(D102,Data2!$A:$D,4,0),"") -> 0 | O102: =IFERROR(VLOOKUP(D102,Data2!$A:$C,3,0),"") -> 24 | P102: 186 | Q102: 188 | S102: CASE
A103: 5096-BOX | B103: B07XL4V3N1 | C103: X003GHJQB9 | D103: =IFERROR(VLOOKUP(A103,Data1!A:B,2,0),"") -> 5096 | E103: =M103*Q103 -> 4608 | F103: =E103/M103 -> 192 | G103: =IFERROR(ROUNDUP(E103/N103,0),"") -> 192 | H103: =IFERROR(ROUNDUP(E103/O103,0),"") -> 16 | I103: =IFERROR(IF(S103="CASE",F103/H103,F103/G103),"") -> 12 | J103: =IF(ISNUMBER(SEARCH("FNSKU",C103)),"Labeling","") | K103: =IFERROR(VLOOKUP(A103,Instruction!A:F,6,0),"") -> • For inner box: apply FNSKU label and “THIS IS A SET” label • Cover all visible barcodes on the box/case • Place all the inner boxes back into the CASE. • Apply outer case label (Cover barcodes on the CASE) | L103: =IFERROR(VLOOKUP(A103,Instruction!A:J,10,0),"No Supplies") -> No Supplies | M103: =IFERROR(VLOOKUP(A103,Data1!A:C,3,0),1) -> 24 | N103: =IFERROR(VLOOKUP(D103,Data2!$A:$D,4,0),"") -> 24 | O103: =IFERROR(VLOOKUP(D103,Data2!$A:$C,3,0),"") -> 288 | P103: 186 | Q103: 192 | S103: CASE
A104: 842-SET4 | B104: B07R95PGYJ | C104: X003SCCWXL | D104: =IFERROR(VLOOKUP(A104,Data1!A:B,2,0),"") -> 842 | E104: =M104*Q104 -> 744 | F104: =E104/M104 -> 186 | G104: =IFERROR(ROUNDUP(E104/N104,0),"") | H104: =IFERROR(ROUNDUP(E104/O104,0),"") -> 31 | I104: =IFERROR(IF(S104="CASE",F104/H104,F104/G104),"") -> 6 | J104: =IF(ISNUMBER(SEARCH("FNSKU",C104)),"Labeling","") | K104: =IFERROR(VLOOKUP(A104,Instruction!A:F,6,0),"") -> • Insert 4 pcs per poly bag (different color). Apply FNSKU on the poly bags. • Insert the poly-bagged sets back to CASE (Cover all existing barcodes on the box/case) • Buddle box size BX- 17 x 16.5 x 22 | L104: =IFERROR(VLOOKUP(A104,Instruction!A:J,10,0),"No Supplies") -> Poly Bag 14.5 x 19 | M104: =IFERROR(VLOOKUP(A104,Data1!A:C,3,0),1) -> 4 | N104: =IFERROR(VLOOKUP(D104,Data2!$A:$D,4,0),"") -> 0 | O104: =IFERROR(VLOOKUP(D104,Data2!$A:$C,3,0),"") -> 24 | P104: 183 | Q104: 186 | S104: CASE
A105: 835-SET4-b | B105: B0D98ZL8R2 | C105: X004HPCH5V | D105: =IFERROR(VLOOKUP(A105,Data1!A:B,2,0),"") -> 835 | E105: =M105*Q105 -> 720 | F105: =E105/M105 -> 180 | G105: =IFERROR(ROUNDUP(E105/N105,0),"") | H105: =IFERROR(ROUNDUP(E105/O105,0),"") -> 30 | I105: =IFERROR(IF(S105="CASE",F105/H105,F105/G105),"") -> 6 | J105: =IF(ISNUMBER(SEARCH("FNSKU",C105)),"Labeling","") | K105: =IFERROR(VLOOKUP(A105,Instruction!A:F,6,0),"") -> • Insert 4 pcs (different color) per poly bag. Apply FNSKU labels on each of the poly bags. Cover all existing barcode. • Insert the poly-bagged sets back to CASE. (Cover all existing barcodes on the box/case) | L105: =IFERROR(VLOOKUP(A105,Instruction!A:J,10,0),"No Supplies") -> 0 | M105: =IFERROR(VLOOKUP(A105,Data1!A:C,3,0),1) -> 4 | N105: =IFERROR(VLOOKUP(D105,Data2!$A:$D,4,0),"") -> 0 | O105: =IFERROR(VLOOKUP(D105,Data2!$A:$C,3,0),"") -> 24 | P105: 182 | Q105: 180 | S105: CASE
A106: 4145-EACH | B106: B07Q8WM9D9 | C106: X003SBSK33 | D106: =IFERROR(VLOOKUP(A106,Data1!A:B,2,0),"") -> 4145 | E106: =M106*Q106 -> 180 | F106: =E106/M106 -> 180 | G106: =IFERROR(ROUNDUP(E106/N106,0),"") | H106: =IFERROR(ROUNDUP(E106/O106,0),"") -> 15 | I106: =IFERROR(IF(S106="CASE",F106/H106,F106/G106),"") -> 12 | J106: =IF(ISNUMBER(SEARCH("FNSKU",C106)),"Labeling","") | K106: =IFERROR(VLOOKUP(A106,Instruction!A:F,6,0),"") -> • Use FNSKU to label each item (cover barcode). Apply outer box/case label accordingly to match item# (Cover all existing barcodes on the box/case) | L106: =IFERROR(VLOOKUP(A106,Instruction!A:J,10,0),"No Supplies") -> No Supplies | M106: =IFERROR(VLOOKUP(A106,Data1!A:C,3,0),1) -> 1 | N106: =IFERROR(VLOOKUP(D106,Data2!$A:$D,4,0),"") -> 0 | O106: =IFERROR(VLOOKUP(D106,Data2!$A:$C,3,0),"") -> 12 | P106: 177 | Q106: 180 | S106: CASE
A107: 608-EACH | B107: B003BMWZ48 | C107: X003EGFQKR | D107: =IFERROR(VLOOKUP(A107,Data1!A:B,2,0),"") -> 608 | E107: =M107*Q107 -> 144 | F107: =E107/M107 -> 144 | G107: =IFERROR(ROUNDUP(E107/N107,0),"") -> 6 | H107: =IFERROR(ROUNDUP(E107/O107,0),"") -> 2 | I107: =IFERROR(IF(S107="CASE",F107/H107,F107/G107),"") -> 72 | J107: =IF(ISNUMBER(SEARCH("FNSKU",C107)),"Labeling","") | K107: =IFERROR(VLOOKUP(A107,Instruction!A:F,6,0),"") -> • Use FNSKU to label each item (cover barcode). Apply outer box/case label accordingly to match item# (Cover all existing barcodes on the box/case) | L107: =IFERROR(VLOOKUP(A107,Instruction!A:J,10,0),"No Supplies") -> No Supplies | M107: =IFERROR(VLOOKUP(A107,Data1!A:C,3,0),1) -> 1 | N107: =IFERROR(VLOOKUP(D107,Data2!$A:$D,4,0),"") -> 24 | O107: =IFERROR(VLOOKUP(D107,Data2!$A:$C,3,0),"") -> 72 | P107: 176 | Q107: 144 | S107: CASE
A108: 804-SET6 | B108: B07R81PNF1 | C108: X003SCIA87 | D108: =IFERROR(VLOOKUP(A108,Data1!A:B,2,0),"") -> 804 | E108: =M108*Q108 -> 1008 | F108: =E108/M108 -> 168 | G108: =IFERROR(ROUNDUP(E108/N108,0),"") -> 42 | H108: =IFERROR(ROUNDUP(E108/O108,0),"") -> 7 | I108: =IFERROR(IF(S108="CASE",F108/H108,F108/G108),"") -> 24 | J108: =IF(ISNUMBER(SEARCH("FNSKU",C108)),"Labeling","") | K108: =IFERROR(VLOOKUP(A108,Instruction!A:F,6,0),"") -> • Put 6 pcs per poly bag (6 different color). Apply FNSKU labels on each of the poly bags. • Put the poly-bagged sets back to CASE (discard inner box) (Cover all existing barcodes on the box/case) | L108: =IFERROR(VLOOKUP(A108,Instruction!A:J,10,0),"No Supplies") -> Poly Bag 9 x 12 | M108: =IFERROR(VLOOKUP(A108,Data1!A:C,3,0),1) -> 6 | N108: =IFERROR(VLOOKUP(D108,Data2!$A:$D,4,0),"") -> 24 | O108: =IFERROR(VLOOKUP(D108,Data2!$A:$C,3,0),"") -> 144 | P108: 173 | Q108: 168 | S108: CASE
A109: 2022-PACK2 | B109: B08GWYQ4S5 | C109: X0044R3MPB | D109: =IFERROR(VLOOKUP(A109,Data1!A:B,2,0),"") -> 2022 | E109: =M109*Q109 -> 288 | F109: =E109/M109 -> 144 | G109: =IFERROR(ROUNDUP(E109/N109,0),"") -> 12 | H109: =IFERROR(ROUNDUP(E109/O109,0),"") -> 2 | I109: =IFERROR(IF(S109="CASE",F109/H109,F109/G109),"") -> 72 | J109: =IF(ISNUMBER(SEARCH("FNSKU",C109)),"Labeling","") | K109: =IFERROR(VLOOKUP(A109,Instruction!A:F,6,0),"") -> • Put 2 pcs into polybag and apply FNSKU labels on each of the poly bags. • Insert the poly-bagged sets back to BOX (Cover all existing barcodes on the box/case) | L109: =IFERROR(VLOOKUP(A109,Instruction!A:J,10,0),"No Supplies") -> Poly Bag 6 x 9 | M109: =IFERROR(VLOOKUP(A109,Data1!A:C,3,0),1) -> 2 | N109: =IFERROR(VLOOKUP(D109,Data2!$A:$D,4,0),"") -> 24 | O109: =IFERROR(VLOOKUP(D109,Data2!$A:$C,3,0),"") -> 144 | P109: 165 | Q109: 144 | S109: CASE
A110: 3144-SET10 | B110: B0BS2CW31B | C110: X003YW3OSR | D110: =IFERROR(VLOOKUP(A110,Data1!A:B,2,0),"") -> 3144 | E110: =M110*Q110 -> 1600 | F110: =E110/M110 -> 160 | G110: =IFERROR(ROUNDUP(E110/N110,0),"") | H110: =IFERROR(ROUNDUP(E110/O110,0),"") -> 16 | I110: =IFERROR(IF(S110="CASE",F110/H110,F110/G110),"") -> 10 | J110: =IF(ISNUMBER(SEARCH("FNSKU",C110)),"Labeling","") | K110: =IFERROR(VLOOKUP(A110,Instruction!A:F,6,0),"") -> • Insert 10 pcs per poly bag (X2 pc - red, yellow, blue, green. X1 pc - purple, orange). Apply FNSKU labels on each of the poly bags. • Insert the poly-bagged sets back to CASE. (Cover all existing barcodes on the box/case) | L110: =IFERROR(VLOOKUP(A110,Instruction!A:J,10,0),"No Supplies") -> Poly Bag 12 x 15.5 | M110: =IFERROR(VLOOKUP(A110,Data1!A:C,3,0),1) -> 10 | N110: =IFERROR(VLOOKUP(D110,Data2!$A:$D,4,0),"") -> 0 | O110: =IFERROR(VLOOKUP(D110,Data2!$A:$C,3,0),"") -> 100 | P110: 164 | Q110: 160 | S110: CASE
A111: 321-EACH | B111: B00914XF5S | C111: B00914XF5S | D111: =IFERROR(VLOOKUP(A111,Data1!A:B,2,0),"") -> 321 | E111: =M111*Q111 -> 168 | F111: =E111/M111 -> 168 | G111: =IFERROR(ROUNDUP(E111/N111,0),"") -> 7 | H111: =IFERROR(ROUNDUP(E111/O111,0),"") -> 1 | I111: =IFERROR(IF(S111="CASE",F111/H111,F111/G111),"") -> 24 | J111: =IF(ISNUMBER(SEARCH("FNSKU",C111)),"Labeling","") | K111: =IFERROR(VLOOKUP(A111,Instruction!A:F,6,0),"") -> Apply outer box/case label accordingly to match item# (Cover all existing barcodes on the box/case) | L111: =IFERROR(VLOOKUP(A111,Instruction!A:J,10,0),"No Supplies") -> No Supplies | M111: =IFERROR(VLOOKUP(A111,Data1!A:C,3,0),1) -> 1 | N111: =IFERROR(VLOOKUP(D111,Data2!$A:$D,4,0),"") -> 24 | O111: =IFERROR(VLOOKUP(D111,Data2!$A:$C,3,0),"") -> 288 | P111: 161 | Q111: 168 | S111: BOX
A112: 840-PACK4 | B112: B08CYBRWPF | C112: X003X0BFG3 | D112: =IFERROR(VLOOKUP(A112,Data1!A:B,2,0),"") -> 840 | E112: =M112*Q112 -> 648 | F112: =E112/M112 -> 162 | G112: =IFERROR(ROUNDUP(E112/N112,0),"") | H112: =IFERROR(ROUNDUP(E112/O112,0),"") -> 27 | I112: =IFERROR(IF(S112="CASE",F112/H112,F112/G112),"") -> 6 | J112: =IF(ISNUMBER(SEARCH("FNSKU",C112)),"Labeling","") | K112: =IFERROR(VLOOKUP(A112,Instruction!A:F,6,0),"") -> • Insert 4 pcs per poly bag. Apply FNSKU on the poly bags. • Insert the poly-bagged sets back to CASE (Cover all existing barcodes on the box/case) • Buddle box size BX- 17 x 16.5 x 22 | L112: =IFERROR(VLOOKUP(A112,Instruction!A:J,10,0),"No Supplies") -> Poly Bag 14.5 x 19 | M112: =IFERROR(VLOOKUP(A112,Data1!A:C,3,0),1) -> 4 | N112: =IFERROR(VLOOKUP(D112,Data2!$A:$D,4,0),"") -> 0 | O112: =IFERROR(VLOOKUP(D112,Data2!$A:$C,3,0),"") -> 24 | P112: 160 | Q112: 162 | S112: CASE
... A129: 851-CASE | B129: B093CS5SYX | C129: B093CS5SYX | D129: =IFERROR(VLOOKUP(A129,Data1!A:B,2,0),"") -> 851 | E129: =M129*Q129 -> 1656 | F129: =E129/M129 -> 138 | G129: =IFERROR(ROUNDUP(E129/N129,0),"") | H129: =IFERROR(ROUNDUP(E129/O129,0),"") -> 138 | I129: =IFERROR(IF(S129="CASE",F129/H129,F129/G129),"") -> 1 | J129: =IF(ISNUMBER(SEARCH("FNSKU",C129)),"Labeling","") | K129: =IFERROR(VLOOKUP(A129,Instruction!A:F,6,0),"") -> • Apply label “THIS IS A SET” **DO NOT COVER CASE BARCODE** • Apply outer case label accordingly to match item# | L129: =IFERROR(VLOOKUP(A129,Instruction!A:J,10,0),"No Supplies") -> No Supplies | M129: =IFERROR(VLOOKUP(A129,Data1!A:C,3,0),1) -> 12 | N129: =IFERROR(VLOOKUP(D129,Data2!$A:$D,4,0),"") -> 0 | O129: =IFERROR(VLOOKUP(D129,Data2!$A:$C,3,0),"") -> 12 | P129: 138 | Q129: 138 | S129: CASE
A130: 8204-EACH | B130: B07RP467JB | D130: =IFERROR(VLOOKUP(A130,Data1!A:B,2,0),"") -> 8204 | E130: =M130*Q130 -> 144 | F130: =E130/M130 -> 144 | G130: =IFERROR(ROUNDUP(E130/N130,0),"") | H130: =IFERROR(ROUNDUP(E130/O130,0),"") -> 6 | I130: =IFERROR(IF(S130="CASE",F130/H130,F130/G130),"") -> 24 | J130: =IF(ISNUMBER(SEARCH("FNSKU",C130)),"Labeling","") | K130: =IFERROR(VLOOKUP(A130,Instruction!A:F,6,0),"") -> • Use FNSKU to label each item (cover barcode). • Put item back to CASE. Discard inner box • Apply outer case label accordingly to match item# (Cover all existing barcodes on the case) | L130: =IFERROR(VLOOKUP(A130,Instruction!A:J,10,0),"No Supplies") -> 0 | M130: =IFERROR(VLOOKUP(A130,Data1!A:C,3,0),1) -> 1 | N130: =IFERROR(VLOOKUP(D130,Data2!$A:$D,4,0),"") -> 0 | O130: =IFERROR(VLOOKUP(D130,Data2!$A:$C,3,0),"") -> 24 | P130: 138 | Q130: 144 | S130: CASE
A131: 3169-SET6 | B131: B07RX2FHFP | C131: X003SC97JX | D131: =IFERROR(VLOOKUP(A131,Data1!A:B,2,0),"") -> 3169 | E131: =M131*Q131 -> 816 | F131: =E131/M131 -> 136 | G131: =IFERROR(ROUNDUP(E131/N131,0),"") | H131: =IFERROR(ROUNDUP(E131/O131,0),"") -> 17 | I131: =IFERROR(IF(S131="CASE",F131/H131,F131/G131),"") -> 8 | J131: =IF(ISNUMBER(SEARCH("FNSKU",C131)),"Labeling","") | K131: =IFERROR(VLOOKUP(A131,Instruction!A:F,6,0),"") -> • Insert 6 pcs per poly bag (6 different color). Apply FNSKU labels on each of the poly bags. • Insert the poly-bagged sets back to CASE (Cover all existing barcodes on the box/case) | L131: =IFERROR(VLOOKUP(A131,Instruction!A:J,10,0),"No Supplies") -> Poly Bag 12 x 15.5 | M131: =IFERROR(VLOOKUP(A131,Data1!A:C,3,0),1) -> 6 | N131: =IFERROR(VLOOKUP(D131,Data2!$A:$D,4,0),"") -> 0 | O131: =IFERROR(VLOOKUP(D131,Data2!$A:$C,3,0),"") -> 48 | P131: 137 | Q131: 136 | S131: CASE
A132: 2204-EACH-1 | B132: B003BNZVHU | C132: B003BNZVHU | D132: =IFERROR(VLOOKUP(A132,Data1!A:B,2,0),"") -> 2204 | E132: =M132*Q132 -> 144 | F132: =E132/M132 -> 144 | G132: =IFERROR(ROUNDUP(E132/N132,0),"") -> 6 | H132: =IFERROR(ROUNDUP(E132/O132,0),"") -> 2 | I132: =IFERROR(IF(S132="CASE",F132/H132,F132/G132),"") -> 72 | J132: =IF(ISNUMBER(SEARCH("FNSKU",C132)),"Labeling","") | K132: =IFERROR(VLOOKUP(A132,Instruction!A:F,6,0),"") -> Apply outer box/case label accordingly to match item# (Cover all existing barcodes on the box/case) | L132: =IFERROR(VLOOKUP(A132,Instruction!A:J,10,0),"No Supplies") -> No Supplies | M132: =IFERROR(VLOOKUP(A132,Data1!A:C,3,0),1) -> 1 | N132: =IFERROR(VLOOKUP(D132,Data2!$A:$D,4,0),"") -> 24 | O132: =IFERROR(VLOOKUP(D132,Data2!$A:$C,3,0),"") -> 72 | P132: 132 | Q132: 144 | S132: CASE
A133: 534-BOX | B133: B07XQKHYRP | C133: X0044RLX07 | D133: =IFERROR(VLOOKUP(A133,Data1!A:B,2,0),"") -> 534 | E133: =M133*Q133 -> 3168 | F133: =E133/M133 -> 132 | G133: =IFERROR(ROUNDUP(E133/N133,0),"") -> 132 | H133: =IFERROR(ROUNDUP(E133/O133,0),"") -> 44 | I133: =IFERROR(IF(S133="CASE",F133/H133,F133/G133),"") -> 3 | J133: =IF(ISNUMBER(SEARCH("FNSKU",C133)),"Labeling","") | K133: =IFERROR(VLOOKUP(A133,Instruction!A:F,6,0),"") -> • For inner box: apply FNSKU label and “THIS IS A SET” label • Cover all visible barcodes on the box/case • Place all the inner boxes back into the CASE. • Apply outer case label (Cover barcodes on the CASE) | L133: =IFERROR(VLOOKUP(A133,Instruction!A:J,10,0),"No Supplies") -> No Supplies | M133: =IFERROR(VLOOKUP(A133,Data1!A:C,3,0),1) -> 24 | N133: =IFERROR(VLOOKUP(D133,Data2!$A:$D,4,0),"") -> 24 | O133: =IFERROR(VLOOKUP(D133,Data2!$A:$C,3,0),"") -> 72 | P133: 131 | Q133: 132 | S133: CASE
A134: 3187-PACK4 | B134: B08G3XTB2Z | C134: X003Y722CV | D134: =IFERROR(VLOOKUP(A134,Data1!A:B,2,0),"") -> 3187 | E134: =M134*Q134 -> 576 | F134: =E134/M134 -> 144 | G134: =IFERROR(ROUNDUP(E134/N134,0),"") -> 24 | H134: =IFERROR(ROUNDUP(E134/O134,0),"") -> 4 | I134: =IFERROR(IF(S134="CASE",F134/H134,F134/G134),"") -> 36 | J134: =IF(ISNUMBER(SEARCH("FNSKU",C134)),"Labeling","") | K134: =IFERROR(VLOOKUP(A134,Instruction!A:F,6,0),"") -> • Put 4 pcs per poly bag. Apply FNSKU labels on each of the poly bags. • Put the poly-bagged sets back to CASE. Discard inner box. (Cover all existing barcodes on the box/case) | L134: =IFERROR(VLOOKUP(A134,Instruction!A:J,10,0),"No Supplies") -> Poly Bag 12 x 15.5 | M134: =IFERROR(VLOOKUP(A134,Data1!A:C,3,0),1) -> 4 | N134: =IFERROR(VLOOKUP(D134,Data2!$A:$D,4,0),"") -> 24 | O134: =IFERROR(VLOOKUP(D134,Data2!$A:$C,3,0),"") -> 144 | P134: 131 | Q134: 144 | S134: CASE
A135: 2024-EACH | B135: B003BS9A54 | C135: B003BS9A54 | D135: =IFERROR(VLOOKUP(A135,Data1!A:B,2,0),"") -> 2024 | E135: =M135*Q135 -> 144 | F135: =E135/M135 -> 144 | G135: =IFERROR(ROUNDUP(E135/N135,0),"") -> 6 | H135: =IFERROR(ROUNDUP(E135/O135,0),"") -> 1 | I135: =IFERROR(IF(S135="CASE",F135/H135,F135/G135),"") -> 144 | J135: =IF(ISNUMBER(SEARCH("FNSKU",C135)),"Labeling","") | K135: =IFERROR(VLOOKUP(A135,Instruction!A:F,6,0),"") -> Apply outer box/case label accordingly to match item# (Cover all existing barcodes on the box/case) | L135: =IFERROR(VLOOKUP(A135,Instruction!A:J,10,0),"No Supplies") -> No Supplies | M135: =IFERROR(VLOOKUP(A135,Data1!A:C,3,0),1) -> 1 | N135: =IFERROR(VLOOKUP(D135,Data2!$A:$D,4,0),"") -> 24 | O135: =IFERROR(VLOOKUP(D135,Data2!$A:$C,3,0),"") -> 144 | P135: 130 | Q135: 144 | S135: CASE
A136: 4120-EACH | B136: B07Q713R9G | C136: X003SC97MP | D136: =IFERROR(VLOOKUP(A136,Data1!A:B,2,0),"") -> 4120 | E136: =M136*Q136 -> 132 | F136: =E136/M136 -> 132 | G136: =IFERROR(ROUNDUP(E136/N136,0),"") | H136: =IFERROR(ROUNDUP(E136/O136,0),"") -> 11 | I136: =IFERROR(IF(S136="CASE",F136/H136,F136/G136),"") -> 12 | J136: =IF(ISNUMBER(SEARCH("FNSKU",C136)),"Labeling","") | K136: =IFERROR(VLOOKUP(A136,Instruction!A:F,6,0),"") -> • Use FNSKU to label each item (cover barcode). Apply outer box/case label accordingly to match item# (Cover all existing barcodes on the box/case) | L136: =IFERROR(VLOOKUP(A136,Instruction!A:J,10,0),"No Supplies") -> No Supplies | M136: =IFERROR(VLOOKUP(A136,Data1!A:C,3,0),1) -> 1 | N136: =IFERROR(VLOOKUP(D136,Data2!$A:$D,4,0),"") -> 0 | O136: =IFERROR(VLOOKUP(D136,Data2!$A:$C,3,0),"") -> 12 | P136: 129 | Q136: 132 | S136: CASE
A137: 560-PACK6 | B137: B08FBQM8VF | C137: X003SFDOWB | D137: =IFERROR(VLOOKUP(A137,Data1!A:B,2,0),"") -> 560 | E137: =M137*Q137 -> 768 | F137: =E137/M137 -> 128 | G137: =IFERROR(ROUNDUP(E137/N137,0),"") | H137: =IFERROR(ROUNDUP(E137/O137,0),"") -> 16 | I137: =IFERROR(IF(S137="CASE",F137/H137,F137/G137),"") -> 8 | J137: =IF(ISNUMBER(SEARCH("FNSKU",C137)),"Labeling","") | K137: =IFERROR(VLOOKUP(A137,Instruction!A:F,6,0),"") -> • Put 6 pcs into polybag and apply FNSKU labels on each of the poly bags. • Insert the poly-bagged sets back to CASE (Cover all existing barcodes on the box/case) | L137: =IFERROR(VLOOKUP(A137,Instruction!A:J,10,0),"No Supplies") -> Poly Bag 9 x 12 | M137: =IFERROR(VLOOKUP(A137,Data1!A:C,3,0),1) -> 6 | N137: =IFERROR(VLOOKUP(D137,Data2!$A:$D,4,0),"") -> 0 | O137: =IFERROR(VLOOKUP(D137,Data2!$A:$C,3,0),"") -> 48 | P137: 127 | Q137: 128 | S137: CASE
A138: 3167-EA-PK | B138: B0CFGH34FV | C138: X003XEHNGP | D138: =IFERROR(VLOOKUP(A138,Data1!A:B,2,0),"") -> 3167 | E138: =M138*Q138 -> 120 | F138: =E138/M138 -> 120 | G138: =IFERROR(ROUNDUP(E138/N138,0),"") | H138: =IFERROR(ROUNDUP(E138/O138,0),"") -> 5 | I138: =IFERROR(IF(S138="CASE",F138/H138,F138/G138),"") -> 24 | J138: =IF(ISNUMBER(SEARCH("FNSKU",C138)),"Labeling","") | K138: =IFERROR(VLOOKUP(A138,Instruction!A:F,6,0),"") -> • Use FNSKU to label each item (cover barcode). • Put 24 units Same color back to original CASE • Apply outer case label accordingly to match item# (Cover all existing barcodes on the case) | L138: =IFERROR(VLOOKUP(A138,Instruction!A:J,10,0),"No Supplies") -> No Supplies | M138: =IFERROR(VLOOKUP(A138,Data1!A:C,3,0),1) -> 1 | N138: =IFERROR(VLOOKUP(D138,Data2!$A:$D,4,0),"") -> 0 | O138: =IFERROR(VLOOKUP(D138,Data2!$A:$C,3,0),"") -> 24 | P138: 124 | Q138: 120 | S138: CASE
A139: 560-PACK3-B | B139: B07S96S8LT | C139: X003SLYPRN | D139: =IFERROR(VLOOKUP(A139,Data1!A:B,2,0),"") -> 560 | E139: =M139*Q139 -> 384 | F139: =E139/M139 -> 128 | G139: =IFERROR(ROUNDUP(E139/N139,0),"") | H139: =IFERROR(ROUNDUP(E139/O139,0),"") -> 8 | I139: =IFERROR(IF(S139="CASE",F139/H139,F139/G139),"") -> 16 | J139: =IF(ISNUMBER(SEARCH("FNSKU",C139)),"Labeling","") | K139: =IFERROR(VLOOKUP(A139,Instruction!A:F,6,0),"") -> • Put 3 pcs into polybag and apply FNSKU labels on each of the poly bags. • Insert the poly-bagged sets back to CASE (Cover all existing barcodes on the box/case) | L139: =IFERROR(VLOOKUP(A139,Instruction!A:J,10,0),"No Supplies") -> Poly Bag 7.5 x 10.5 | M139: =IFERROR(VLOOKUP(A139,Data1!A:C,3,0),1) -> 3 | N139: =IFERROR(VLOOKUP(D139,Data2!$A:$D,4,0),"") -> 0 | O139: =IFERROR(VLOOKUP(D139,Data2!$A:$C,3,0),"") -> 48 | P139: 124 | Q139: 128 | S139: CASE
A140: 744-PACK2 | B140: B08F6W23QR | C140: X004JMREUF | D140: =IFERROR(VLOOKUP(A140,Data1!A:B,2,0),"") -> 744 | E140: =M140*Q140 -> 288 | F140: =E140/M140 -> 144 | G140: =IFERROR(ROUNDUP(E140/N140,0),"") -> 12 | H140: =IFERROR(ROUNDUP(E140/O140,0),"") -> 2 | I140: =IFERROR(IF(S140="CASE",F140/H140,F140/G140),"") -> 72 | J140: =IF(ISNUMBER(SEARCH("FNSKU",C140)),"Labeling","") | K140: =IFERROR(VLOOKUP(A140,Instruction!A:F,6,0),"") -> • Put 2 pcs per poly bag. Apply FNSKU on the poly bags. • Put the poly-bagged sets back to BOX/CASE. Discard inner box (Cover all existing barcodes on the box/case) | L140: =IFERROR(VLOOKUP(A140,Instruction!A:J,10,0),"No Supplies") -> 0 | M140: =IFERROR(VLOOKUP(A140,Data1!A:C,3,0),1) -> 2 | N140: =IFERROR(VLOOKUP(D140,Data2!$A:$D,4,0),"") -> 24 | O140: =IFERROR(VLOOKUP(D140,Data2!$A:$C,3,0),"") -> 144 | P140: 122 | Q140: 144 | S140: CASE
A141: 4398-PACK2 | B141: B08DDHRDDF | C141: X0042UB9EB | D141: =IFERROR(VLOOKUP(A141,Data1!A:B,2,0),"") -> 4398 | E141: =M141*Q141 -> 288 | F141: =E141/M141 -> 144 | G141: =IFERROR(ROUNDUP(E141/N141,0),"") -> 12 | H141: =IFERROR(ROUNDUP(E141/O141,0),"") -> 2 | I141: =IFERROR(IF(S141="CASE",F141/H141,F141/G141),"") -> 72 | J141: =IF(ISNUMBER(SEARCH("FNSKU",C141)),"Labeling","") | K141: =IFERROR(VLOOKUP(A141,Instruction!A:F,6,0),"") -> • Put 2 pcs into polybag and apply FNSKU labels on each of the poly bags. • Insert the poly-bagged sets back to CASE. Discard inner box (Cover all existing barcodes on the box/case) | L141: =IFERROR(VLOOKUP(A141,Instruction!A:J,10,0),"No Supplies") -> Poly Bag 9 x 12 | M141: =IFERROR(VLOOKUP(A141,Data1!A:C,3,0),1) -> 2 | N141: =IFERROR(VLOOKUP(D141,Data2!$A:$D,4,0),"") -> 24 | O141: =IFERROR(VLOOKUP(D141,Data2!$A:$C,3,0),"") -> 144 | P141: 120 | Q141: 144 | S141: CASE
A142: 543-EACH | B142: B0019IOFNA | C142: B0019IOFNA | D142: =IFERROR(VLOOKUP(A142,Data1!A:B,2,0),"") -> 543 | E142: =M142*Q142 -> 96 | F142: =E142/M142 -> 96 | G142: =IFERROR(ROUNDUP(E142/N142,0),"") | H142: =IFERROR(ROUNDUP(E142/O142,0),"") -> 2 | I142: =IFERROR(IF(S142="CASE",F142/H142,F142/G142),"") -> 48 | J142: =IF(ISNUMBER(SEARCH("FNSKU",C142)),"Labeling","") | K142: =IFERROR(VLOOKUP(A142,Instruction!A:F,6,0),"") -> Apply outer box/case label accordingly to match item# (Cover all existing barcodes on the box/case) | L142: =IFERROR(VLOOKUP(A142,Instruction!A:J,10,0),"No Supplies") -> No Supplies | M142: =IFERROR(VLOOKUP(A142,Data1!A:C,3,0),1) -> 1 | N142: =IFERROR(VLOOKUP(D142,Data2!$A:$D,4,0),"") -> 0 | O142: =IFERROR(VLOOKUP(D142,Data2!$A:$C,3,0),"") -> 48 | P142: 119 | Q142: 96 | S142: CASE
... A150: 2345-EACH | B150: B08L41SRH8 | C150: X004KT5ZE9 | D150: =IFERROR(VLOOKUP(A150,Data1!A:B,2,0),"") -> 2345 | E150: =M150*Q150 -> 144 | F150: =E150/M150 -> 144 | G150: =IFERROR(ROUNDUP(E150/N150,0),"") -> 6 | H150: =IFERROR(ROUNDUP(E150/O150,0),"") -> 1 | I150: =IFERROR(IF(S150="CASE",F150/H150,F150/G150),"") -> 144 | J150: =IF(ISNUMBER(SEARCH("FNSKU",C150)),"Labeling","") | K150: =IFERROR(VLOOKUP(A150,Instruction!A:F,6,0),"") -> • Use FNSKU to label each item (cover barcode). Apply outer box/case label accordingly to match item# (Cover all existing barcodes on the box/case) | L150: =IFERROR(VLOOKUP(A150,Instruction!A:J,10,0),"No Supplies") -> No Supplies | M150: =IFERROR(VLOOKUP(A150,Data1!A:C,3,0),1) -> 1 | N150: =IFERROR(VLOOKUP(D150,Data2!$A:$D,4,0),"") -> 24 | O150: =IFERROR(VLOOKUP(D150,Data2!$A:$C,3,0),"") -> 144 | P150: 108 | Q150: 144 | S150: CASE
A151: 3930-EACH | B151: B08NSJ1SFC | D151: =IFERROR(VLOOKUP(A151,Data1!A:B,2,0),"") -> 3930 | E151: =M151*Q151 -> 144 | F151: =E151/M151 -> 144 | G151: =IFERROR(ROUNDUP(E151/N151,0),"") -> 6 | H151: =IFERROR(ROUNDUP(E151/O151,0),"") -> 2 | I151: =IFERROR(IF(S151="CASE",F151/H151,F151/G151),"") -> 72 | J151: =IF(ISNUMBER(SEARCH("FNSKU",C151)),"Labeling","") | K151: =IFERROR(VLOOKUP(A151,Instruction!A:F,6,0),"") -> • Use FNSKU to label each item (cover barcode). • Put item back to CASE. Discard inner box • Apply outer case label accordingly to match item# (Cover all existing barcodes on the case) | L151: =IFERROR(VLOOKUP(A151,Instruction!A:J,10,0),"No Supplies") -> 0 | M151: =IFERROR(VLOOKUP(A151,Data1!A:C,3,0),1) -> 1 | N151: =IFERROR(VLOOKUP(D151,Data2!$A:$D,4,0),"") -> 24 | O151: =IFERROR(VLOOKUP(D151,Data2!$A:$C,3,0),"") -> 72 | P151: 125 | Q151: 144 | S151: CASE
A152: 847-PACK4 | B152: B08QR8VLQ6 | C152: X003SCAA3F | D152: =IFERROR(VLOOKUP(A152,Data1!A:B,2,0),"") -> 847 | E152: =M152*Q152 -> 432 | F152: =E152/M152 -> 108 | G152: =IFERROR(ROUNDUP(E152/N152,0),"") | H152: =IFERROR(ROUNDUP(E152/O152,0),"") -> 18 | I152: =IFERROR(IF(S152="CASE",F152/H152,F152/G152),"") -> 6 | J152: =IF(ISNUMBER(SEARCH("FNSKU",C152)),"Labeling","") | K152: =IFERROR(VLOOKUP(A152,Instruction!A:F,6,0),"") -> • Insert 4 pcs per poly bag. Apply FNSKU on the poly bags. • Insert the poly-bagged sets back to CASE (Cover all existing barcodes on the box/case) • New box size BX- 21 x 11.5 x 18.5 | L152: =IFERROR(VLOOKUP(A152,Instruction!A:J,10,0),"No Supplies") -> Poly Bag 14.5 x 19 | M152: =IFERROR(VLOOKUP(A152,Data1!A:C,3,0),1) -> 4 | N152: =IFERROR(VLOOKUP(D152,Data2!$A:$D,4,0),"") -> 0 | O152: =IFERROR(VLOOKUP(D152,Data2!$A:$C,3,0),"") -> 24 | P152: 108 | Q152: 108 | S152: CASE
A153: 744-EACH | B153: B00IIN3U1M | C153: B00IIN3U1M | D153: =IFERROR(VLOOKUP(A153,Data1!A:B,2,0),"") -> 744 | E153: =M153*Q153 -> 96 | F153: =E153/M153 -> 96 | G153: =IFERROR(ROUNDUP(E153/N153,0),"") -> 4 | H153: =IFERROR(ROUNDUP(E153/O153,0),"") -> 1 | I153: =IFERROR(IF(S153="CASE",F153/H153,F153/G153),"") -> 24 | J153: =IF(ISNUMBER(SEARCH("FNSKU",C153)),"Labeling","") | K153: =IFERROR(VLOOKUP(A153,Instruction!A:F,6,0),"") -> Apply outer box/case label accordingly to match item# (Cover all existing barcodes on the box/case) | L153: =IFERROR(VLOOKUP(A153,Instruction!A:J,10,0),"No Supplies") -> No Supplies | M153: =IFERROR(VLOOKUP(A153,Data1!A:C,3,0),1) -> 1 | N153: =IFERROR(VLOOKUP(D153,Data2!$A:$D,4,0),"") -> 24 | O153: =IFERROR(VLOOKUP(D153,Data2!$A:$C,3,0),"") -> 144 | P153: 107 | Q153: 96 | S153: BOX
A154: 5087-PACK4 | B154: B08FBN6YKB | C154: X0044RLTSN | D154: =IFERROR(VLOOKUP(A154,Data1!A:B,2,0),"") -> 5087 | E154: =M154*Q154 -> 432 | F154: =E154/M154 -> 108 | G154: =IFERROR(ROUNDUP(E154/N154,0),"") | H154: =IFERROR(ROUNDUP(E154/O154,0),"") -> 9 | I154: =IFERROR(IF(S154="CASE",F154/H154,F154/G154),"") -> 12 | J154: =IF(ISNUMBER(SEARCH("FNSKU",C154)),"Labeling","") | K154: =IFERROR(VLOOKUP(A154,Instruction!A:F,6,0),"") -> • Put 4 pcs into polybag and apply FNSKU labels on each of the poly bags. • Insert the poly-bagged sets back to CASE (Cover all existing barcodes on the box/case) | L154: =IFERROR(VLOOKUP(A154,Instruction!A:J,10,0),"No Supplies") -> Poly Bag 10 x 13 | M154: =IFERROR(VLOOKUP(A154,Data1!A:C,3,0),1) -> 4 | N154: =IFERROR(VLOOKUP(D154,Data2!$A:$D,4,0),"") -> 0 | O154: =IFERROR(VLOOKUP(D154,Data2!$A:$C,3,0),"") -> 48 | P154: 105 | Q154: 108 | S154: CASE
A155: 1286-EACH | B155: B07HY4Z2YL | C155: B07HY4Z2YL | D155: =IFERROR(VLOOKUP(A155,Data1!A:B,2,0),"") -> 1286 | E155: =M155*Q155 -> 96 | F155: =E155/M155 -> 96 | G155: =IFERROR(ROUNDUP(E155/N155,0),"") -> 4 | H155: =IFERROR(ROUNDUP(E155/O155,0),"") -> 1 | I155: =IFERROR(IF(S155="CASE",F155/H155,F155/G155),"") -> 24 | J155: =IF(ISNUMBER(SEARCH("FNSKU",C155)),"Labeling","") | K155: =IFERROR(VLOOKUP(A155,Instruction!A:F,6,0),"") -> Apply outer box/case label accordingly to match item# (Cover all existing barcodes on the box/case) | L155: =IFERROR(VLOOKUP(A155,Instruction!A:J,10,0),"No Supplies") -> No Supplies | M155: =IFERROR(VLOOKUP(A155,Data1!A:C,3,0),1) -> 1 | N155: =IFERROR(VLOOKUP(D155,Data2!$A:$D,4,0),"") -> 24 | O155: =IFERROR(VLOOKUP(D155,Data2!$A:$C,3,0),"") -> 144 | P155: 104 | Q155: 96 | S155: BOX
A156: 2901-PACK4 | B156: B09343BG1P | C156: X003EGISIT | D156: =IFERROR(VLOOKUP(A156,Data1!A:B,2,0),"") -> 2901 | E156: =M156*Q156 -> 432 | F156: =E156/M156 -> 108 | G156: =IFERROR(ROUNDUP(E156/N156,0),"") | H156: =IFERROR(ROUNDUP(E156/O156,0),"") -> 9 | I156: =IFERROR(IF(S156="CASE",F156/H156,F156/G156),"") -> 12 | J156: =IF(ISNUMBER(SEARCH("FNSKU",C156)),"Labeling","") | K156: =IFERROR(VLOOKUP(A156,Instruction!A:F,6,0),"") -> • Use masking tape to tape 4 pcs together (top and bottom) and apply FNSKU labels. Cover exist barcode. • Insert the sets back to CASE. (Cover all existing barcodes on the box/case) | L156: =IFERROR(VLOOKUP(A156,Instruction!A:J,10,0),"No Supplies") -> TAPE | M156: =IFERROR(VLOOKUP(A156,Data1!A:C,3,0),1) -> 4 | N156: =IFERROR(VLOOKUP(D156,Data2!$A:$D,4,0),"") -> 0 | O156: =IFERROR(VLOOKUP(D156,Data2!$A:$C,3,0),"") -> 48 | P156: 103 | Q156: 108 | S156: CASE
A157: 2140-SET6 | B157: B07RX2WKJW | C157: X003SC1YMB | D157: =IFERROR(VLOOKUP(A157,Data1!A:B,2,0),"") -> 2140 | E157: =M157*Q157 -> 624 | F157: =E157/M157 -> 104 | G157: =IFERROR(ROUNDUP(E157/N157,0),"") | H157: =IFERROR(ROUNDUP(E157/O157,0),"") -> 13 | I157: =IFERROR(IF(S157="CASE",F157/H157,F157/G157),"") -> 8 | J157: =IF(ISNUMBER(SEARCH("FNSKU",C157)),"Labeling","") | K157: =IFERROR(VLOOKUP(A157,Instruction!A:F,6,0),"") -> • Insert 6 pcs per poly bag (6 different color). Apply FNSKU labels on each of the poly bags. • Insert the poly-bagged sets back to CASE (Cover all existing barcodes on the box/case) | L157: =IFERROR(VLOOKUP(A157,Instruction!A:J,10,0),"No Supplies") -> Poly Bag 12 x 15.5 | M157: =IFERROR(VLOOKUP(A157,Data1!A:C,3,0),1) -> 6 | N157: =IFERROR(VLOOKUP(D157,Data2!$A:$D,4,0),"") -> 0 | O157: =IFERROR(VLOOKUP(D157,Data2!$A:$C,3,0),"") -> 48 | P157: 103 | Q157: 104 | S157: CASE
A158: 609-PACK4 | B158: B09C2QNFTV | C158: X0044RLX89 | D158: =IFERROR(VLOOKUP(A158,Data1!A:B,2,0),"") -> 609 | E158: =M158*Q158 -> 432 | F158: =E158/M158 -> 108 | G158: =IFERROR(ROUNDUP(E158/N158,0),"") -> 18 | H158: =IFERROR(ROUNDUP(E158/O158,0),"") -> 6 | I158: =IFERROR(IF(S158="CASE",F158/H158,F158/G158),"") -> 18 | J158: =IF(ISNUMBER(SEARCH("FNSKU",C158)),"Labeling","") | K158: =IFERROR(VLOOKUP(A158,Instruction!A:F,6,0),"") -> • Put 4 pcs into polybag and apply FNSKU labels on each of the poly bags. • Insert the poly-bagged sets back to CASE (Cover all existing barcodes on the box/case) | L158: =IFERROR(VLOOKUP(A158,Instruction!A:J,10,0),"No Supplies") -> Poly Bag 6 x 9 | M158: =IFERROR(VLOOKUP(A158,Data1!A:C,3,0),1) -> 4 | N158: =IFERROR(VLOOKUP(D158,Data2!$A:$D,4,0),"") -> 24 | O158: =IFERROR(VLOOKUP(D158,Data2!$A:$C,3,0),"") -> 72 | P158: 102 | Q158: 108 | S158: CASE
A159: 3167-EA-BL | B159: B0CFGHTZQ1 | C159: X003XEJBS3 | D159: =IFERROR(VLOOKUP(A159,Data1!A:B,2,0),"") -> 3167 | E159: =M159*Q159 -> 96 | F159: =E159/M159 -> 96 | G159: =IFERROR(ROUNDUP(E159/N159,0),"") | H159: =IFERROR(ROUNDUP(E159/O159,0),"") -> 4 | I159: =IFERROR(IF(S159="CASE",F159/H159,F159/G159),"") -> 24 | J159: =IF(ISNUMBER(SEARCH("FNSKU",C159)),"Labeling","") | K159: =IFERROR(VLOOKUP(A159,Instruction!A:F,6,0),"") -> • Use FNSKU to label each item (cover barcode). • Put 24 units Same color back to original CASE • Apply outer case label accordingly to match item# (Cover all existing barcodes on the case) | L159: =IFERROR(VLOOKUP(A159,Instruction!A:J,10,0),"No Supplies") -> No Supplies | M159: =IFERROR(VLOOKUP(A159,Data1!A:C,3,0),1) -> 1 | N159: =IFERROR(VLOOKUP(D159,Data2!$A:$D,4,0),"") -> 0 | O159: =IFERROR(VLOOKUP(D159,Data2!$A:$C,3,0),"") -> 24 | P159: 100 | Q159: 96 | S159: CASE
A160: 5191-PACK2 | B160: B0BCLC7Y4R | C160: X003WOIMP7 | D160: =IFERROR(VLOOKUP(A160,Data1!A:B,2,0),"") -> 5191 | E160: =M160*Q160 -> 204 | F160: =E160/M160 -> 102 | G160: =IFERROR(ROUNDUP(E160/N160,0),"") | H160: =IFERROR(ROUNDUP(E160/O160,0),"") -> 17 | I160: =IFERROR(IF(S160="CASE",F160/H160,F160/G160),"") -> 6 | J160: =IF(ISNUMBER(SEARCH("FNSKU",C160)),"Labeling","") | K160: =IFERROR(VLOOKUP(A160,Instruction!A:F,6,0),"") -> • Insert 2 pcs into poly bag, apply FNSKU label. • Put back to CASE (Cover all existing barcodes on the box/case) | L160: =IFERROR(VLOOKUP(A160,Instruction!A:J,10,0),"No Supplies") -> Poly Bag 10 x 13 | M160: =IFERROR(VLOOKUP(A160,Data1!A:C,3,0),1) -> 2 | N160: =IFERROR(VLOOKUP(D160,Data2!$A:$D,4,0),"") -> 0 | O160: =IFERROR(VLOOKUP(D160,Data2!$A:$C,3,0),"") -> 12 | P160: 99 | Q160: 102 | S160: CASE
A161: 1706-EACH | B161: B07SCHDND7 | C161: X0044RLX6B | D161: =IFERROR(VLOOKUP(A161,Data1!A:B,2,0),"") -> 1706 | E161: =M161*Q161 -> 96 | F161: =E161/M161 -> 96 | G161: =IFERROR(ROUNDUP(E161/N161,0),"") -> 4 | H161: =IFERROR(ROUNDUP(E161/O161,0),"") -> 1 | I161: =IFERROR(IF(S161="CASE",F161/H161,F161/G161),"") -> 24 | J161: =IF(ISNUMBER(SEARCH("FNSKU",C161)),"Labeling","") | K161: =IFERROR(VLOOKUP(A161,Instruction!A:F,6,0),"") -> • Use FNSKU to label each item (cover barcode). Apply outer box/case label accordingly to match item# (Cover all existing barcodes on the box/case) | L161: =IFERROR(VLOOKUP(A161,Instruction!A:J,10,0),"No Supplies") -> No Supplies | M161: =IFERROR(VLOOKUP(A161,Data1!A:C,3,0),1) -> 1 | N161: =IFERROR(VLOOKUP(D161,Data2!$A:$D,4,0),"") -> 24 | O161: =IFERROR(VLOOKUP(D161,Data2!$A:$C,3,0),"") -> 144 | P161: 99 | Q161: 96 | S161: BOX
A162: 3192-EACH | B162: B07Q8Y29ZR | C162: X0044RG61X | D162: =IFERROR(VLOOKUP(A162,Data1!A:B,2,0),"") -> 3192 | E162: =M162*Q162 -> 96 | F162: =E162/M162 -> 96 | G162: =IFERROR(ROUNDUP(E162/N162,0),"") | H162: =IFERROR(ROUNDUP(E162/O162,0),"") -> 8 | I162: =IFERROR(IF(S162="CASE",F162/H162,F162/G162),"") -> 12 | J162: =IF(ISNUMBER(SEARCH("FNSKU",C162)),"Labeling","") | K162: =IFERROR(VLOOKUP(A162,Instruction!A:F,6,0),"") -> • Use FNSKU to label each item (cover barcode). Apply outer box/case label accordingly to match item# (Cover all existing barcodes on the box/case) | L162: =IFERROR(VLOOKUP(A162,Instruction!A:J,10,0),"No Supplies") -> No Supplies | M162: =IFERROR(VLOOKUP(A162,Data1!A:C,3,0),1) -> 1 | N162: =IFERROR(VLOOKUP(D162,Data2!$A:$D,4,0),"") -> 0 | O162: =IFERROR(VLOOKUP(D162,Data2!$A:$C,3,0),"") -> 12 | P162: 97 | Q162: 96 | S162: CASE
A163: 2043-EACH-1 | B163: B00J8IK3YI | C163: X004DMV5X3 | D163: =IFERROR(VLOOKUP(A163,Data1!A:B,2,0),"") -> 2043 | E163: =M163*Q163 -> 96 | F163: =E163/M163 -> 96 | G163: =IFERROR(ROUNDUP(E163/N163,0),"") -> 4 | H163: =IFERROR(ROUNDUP(E163/O163,0),"") -> 1 | I163: =IFERROR(IF(S163="CASE",F163/H163,F163/G163),"") -> 24 | J163: =IF(ISNUMBER(SEARCH("FNSKU",C163)),"Labeling","") | K163: =IFERROR(VLOOKUP(A163,Instruction!A:F,6,0),"") -> • Use FNSKU to label each item (cover barcode). Apply outer case label accordingly to match item# (Cover all existing barcodes on the case) | L163: =IFERROR(VLOOKUP(A163,Instruction!A:J,10,0),"No Supplies") -> No Supplies | M163: =IFERROR(VLOOKUP(A163,Data1!A:C,3,0),1) -> 1 | N163: =IFERROR(VLOOKUP(D163,Data2!$A:$D,4,0),"") -> 24 | O163: =IFERROR(VLOOKUP(D163,Data2!$A:$C,3,0),"") -> 144 | P163: 93 | Q163: 96 | S163: BOX
A164: 375-SET2 | B164: B08BQJPQ4P | D164: =IFERROR(VLOOKUP(A164,Data1!A:B,2,0),"") -> 375 | E164: =M164*Q164 -> 240 | F164: =E164/M164 -> 120 | G164: =IFERROR(ROUNDUP(E164/N164,0),"") | H164: =IFERROR(ROUNDUP(E164/O164,0),"") -> 10 | I164: =IFERROR(IF(S164="CASE",F164/H164,F164/G164),"") -> 12 | J164: =IF(ISNUMBER(SEARCH("FNSKU",C164)),"Labeling","") | K164: =IFERROR(VLOOKUP(A164,Instruction!A:F,6,0),"") -> • Put 2 pcs (different color) into polybag and apply FNSKU labels on each of the poly bags. • Insert the poly-bagged sets back to CASE (Cover all existing barcodes on the box/case) | L164: =IFERROR(VLOOKUP(A164,Instruction!A:J,10,0),"No Supplies") -> Poly Bag 6 x 9 | M164: =IFERROR(VLOOKUP(A164,Data1!A:C,3,0),1) -> 2 | N164: =IFERROR(VLOOKUP(D164,Data2!$A:$D,4,0),"") -> 0 | O164: =IFERROR(VLOOKUP(D164,Data2!$A:$C,3,0),"") -> 24 | P164: 114 | Q164: 120 | S164: CASE
A165: 1613-EACH | B165: B07RL4KKRS | D165: =IFERROR(VLOOKUP(A165,Data1!A:B,2,0),"") -> 1613 | E165: =M165*Q165 -> 96 | F165: =E165/M165 -> 96 | G165: =IFERROR(ROUNDUP(E165/N165,0),"") -> 4 | H165: =IFERROR(ROUNDUP(E165/O165,0),"") -> 1 | I165: =IFERROR(IF(S165="CASE",F165/H165,F165/G165),"") -> 24 | J165: =IF(ISNUMBER(SEARCH("FNSKU",C165)),"Labeling","") | K165: • Use FNSKU to label each item (cover barcode). • Put item back to CASE. Discard inner box • Apply outer case label accordingly to match item# (Cover all existing barcodes on the case) | L165: =IFERROR(VLOOKUP(A165,Instruction!A:J,10,0),"No Supplies") -> No Supplies | M165: =IFERROR(VLOOKUP(A165,Data1!A:C,3,0),1) -> 1 | N165: =IFERROR(VLOOKUP(D165,Data2!$A:$D,4,0),"") -> 24 | O165: =IFERROR(VLOOKUP(D165,Data2!$A:$C,3,0),"") -> 144 | P165: 93 | Q165: 96 | S165: BOX
A166: 5053-EACH-1 | B166: B003BNYACC | C166: X00484N5OX | D166: =IFERROR(VLOOKUP(A166,Data1!A:B,2,0),"") -> 5053 | E166: =M166*Q166 -> 96 | F166: =E166/M166 -> 96 | G166: =IFERROR(ROUNDUP(E166/N166,0),"") | H166: =IFERROR(ROUNDUP(E166/O166,0),"") -> 2 | I166: =IFERROR(IF(S166="CASE",F166/H166,F166/G166),"") -> 48 | J166: =IF(ISNUMBER(SEARCH("FNSKU",C166)),"Labeling","") | K166: =IFERROR(VLOOKUP(A166,Instruction!A:F,6,0),"") -> • Use FNSKU to label each item (cover barcode). Apply outer box/case label accordingly to match item# (Cover all existing barcodes on the box/case) | L166: =IFERROR(VLOOKUP(A166,Instruction!A:J,10,0),"No Supplies") -> No Supplies | M166: =IFERROR(VLOOKUP(A166,Data1!A:C,3,0),1) -> 1 | N166: =IFERROR(VLOOKUP(D166,Data2!$A:$D,4,0),"") -> 0 | O166: =IFERROR(VLOOKUP(D166,Data2!$A:$C,3,0),"") -> 48 | P166: 92 | Q166: 96 | S166: CASE
A167: 3198-EACH | B167: B07S164JS2 | C167: X003YHO1JX | D167: =IFERROR(VLOOKUP(A167,Data1!A:B,2,0),"") -> 3198 | E167: =M167*Q167 -> 96 | F167: =E167/M167 -> 96 | G167: =IFERROR(ROUNDUP(E167/N167,0),"") -> 4 | H167: =IFERROR(ROUNDUP(E167/O167,0),"") -> 1 | I167: =IFERROR(IF(S167="CASE",F167/H167,F167/G167),"") -> 24 | J167: =IF(ISNUMBER(SEARCH("FNSKU",C167)),"Labeling","") | K167: =IFERROR(VLOOKUP(A167,Instruction!A:F,6,0),"") -> • Use FNSKU to label each item (cover barcode). Apply outer box/case label accordingly to match item# (Cover all existing barcodes on the box/case) | L167: =IFERROR(VLOOKUP(A167,Instruction!A:J,10,0),"No Supplies") -> No Supplies | M167: =IFERROR(VLOOKUP(A167,Data1!A:C,3,0),1) -> 1 | N167: =IFERROR(VLOOKUP(D167,Data2!$A:$D,4,0),"") -> 24 | O167: =IFERROR(VLOOKUP(D167,Data2!$A:$C,3,0),"") -> 144 | P167: 92 | Q167: 96 | S167: BOX
A168: 581-CASE | B168: B07XQM13CX | C168: X003SBSJ93 | D168: =IFERROR(VLOOKUP(A168,Data1!A:B,2,0),"") -> 581 | E168: =M168*Q168 -> 2184 | F168: =E168/M168 -> 91 | G168: =IFERROR(ROUNDUP(E168/N168,0),"") | H168: =IFERROR(ROUNDUP(E168/O168,0),"") -> 91 | I168: =IFERROR(IF(S168="CASE",F168/H168,F168/G168),"") -> 1 | J168: =IF(ISNUMBER(SEARCH("FNSKU",C168)),"Labeling","") | K168: =IFERROR(VLOOKUP(A168,Instruction!A:F,6,0),"") -> • Apply label “THIS IS A SET”. Apply FNSKU to each case. • *Make sure all labels stick securely on the case*. Apply outer case label. Cover all visible barcodes on case | L168: =IFERROR(VLOOKUP(A168,Instruction!A:J,10,0),"No Supplies") -> No Supplies | M168: =IFERROR(VLOOKUP(A168,Data1!A:C,3,0),1) -> 24 | N168: =IFERROR(VLOOKUP(D168,Data2!$A:$D,4,0),"") -> 0 | O168: =IFERROR(VLOOKUP(D168,Data2!$A:$C,3,0),"") -> 24 | P168: 91 | Q168: 91 | S168: CASE
A169: 508-PACK2 | B169: B09C7TDTY1 | C169: X003SC1YD5 | D169: =IFERROR(VLOOKUP(A169,Data1!A:B,2,0),"") -> 508 | E169: =M169*Q169 -> 192 | F169: =E169/M169 -> 96 | G169: =IFERROR(ROUNDUP(E169/N169,0),"") | H169: =IFERROR(ROUNDUP(E169/O169,0),"") -> 4 | I169: =IFERROR(IF(S169="CASE",F169/H169,F169/G169),"") -> 24 | J169: =IF(ISNUMBER(SEARCH("FNSKU",C169)),"Labeling","") | K169: =IFERROR(VLOOKUP(A169,Instruction!A:F,6,0),"") -> • Put 2 pcs into polybag and apply FNSKU labels on each of the poly bags. • Insert the poly-bagged sets back to CASE (Cover all existing barcodes on the box/case) | L169: =IFERROR(VLOOKUP(A169,Instruction!A:J,10,0),"No Supplies") -> Poly Bag 9 x 12 | M169: =IFERROR(VLOOKUP(A169,Data1!A:C,3,0),1) -> 2 | N169: =IFERROR(VLOOKUP(D169,Data2!$A:$D,4,0),"") -> 0 | O169: =IFERROR(VLOOKUP(D169,Data2!$A:$C,3,0),"") -> 48 | P169: 88 | Q169: 96 | S169: CASE
A170: 3161-CASE | B170: B08FK9Z656 | C170: X003SBSJE3 | D170: =IFERROR(VLOOKUP(A170,Data1!A:B,2,0),"") -> 3161 | E170: =M170*Q170 -> 1056 | F170: =E170/M170 -> 88 | G170: =IFERROR(ROUNDUP(E170/N170,0),"") | H170: =IFERROR(ROUNDUP(E170/O170,0),"") -> 88 | I170: =IFERROR(IF(S170="CASE",F170/H170,F170/G170),"") -> 1 | J170: =IF(ISNUMBER(SEARCH("FNSKU",C170)),"Labeling","") | K170: =IFERROR(VLOOKUP(A170,Instruction!A:F,6,0),"") -> • Apply label “THIS IS A SET”. Apply FNSKU to each case. • *Make sure all labels stick securely on the case*. Apply outer case label. Cover all visible barcodes on case | L170: =IFERROR(VLOOKUP(A170,Instruction!A:J,10,0),"No Supplies") -> No Supplies | M170: =IFERROR(VLOOKUP(A170,Data1!A:C,3,0),1) -> 12 | N170: =IFERROR(VLOOKUP(D170,Data2!$A:$D,4,0),"") -> 0 | O170: =IFERROR(VLOOKUP(D170,Data2!$A:$C,3,0),"") -> 12 | P170: 88 | Q170: 88 | S170: CASE
A171: 3167-EA-GN | B171: B0CFGGNJG7 | C171: X003XEGL6N | D171: =IFERROR(VLOOKUP(A171,Data1!A:B,2,0),"") -> 3167 | E171: =M171*Q171 -> 96 | F171: =E171/M171 -> 96 | G171: =IFERROR(ROUNDUP(E171/N171,0),"") | H171: =IFERROR(ROUNDUP(E171/O171,0),"") -> 4 | I171: =IFERROR(IF(S171="CASE",F171/H171,F171/G171),"") -> 24 | J171: =IF(ISNUMBER(SEARCH("FNSKU",C171)),"Labeling","") | K171: =IFERROR(VLOOKUP(A171,Instruction!A:F,6,0),"") -> • Use FNSKU to label each item (cover barcode). • Put 24 units Same color back to original CASE • Apply outer case label accordingly to match item# (Cover all existing barcodes on the case) | L171: =IFERROR(VLOOKUP(A171,Instruction!A:J,10,0),"No Supplies") -> No Supplies | M171: =IFERROR(VLOOKUP(A171,Data1!A:C,3,0),1) -> 1 | N171: =IFERROR(VLOOKUP(D171,Data2!$A:$D,4,0),"") -> 0 | O171: =IFERROR(VLOOKUP(D171,Data2!$A:$C,3,0),"") -> 24 | P171: 87 | Q171: 96 | S171: CASE
A172: 2055-BOX | B172: B08CYZYPRN | C172: X0044RG645 | D172: =IFERROR(VLOOKUP(A172,Data1!A:B,2,0),"") -> 2055 | E172: =M172*Q172 -> 1152 | F172: =E172/M172 -> 96 | G172: =IFERROR(ROUNDUP(E172/N172,0),"") -> 96 | H172: =IFERROR(ROUNDUP(E172/O172,0),"") -> 4 | I172: =IFERROR(IF(S172="CASE",F172/H172,F172/G172),"") -> 24 | J172: =IF(ISNUMBER(SEARCH("FNSKU",C172)),"Labeling","") | K172: =IFERROR(VLOOKUP(A172,Instruction!A:F,6,0),"") -> • For inner box: apply FNSKU label and “THIS IS A SET” label • Cover all visible barcodes on the box/case • Place all the inner boxes back into the CASE. • Apply outer case label (Cover barcodes on the CASE) | L172: =IFERROR(VLOOKUP(A172,Instruction!A:J,10,0),"No Supplies") -> No Supplies | M172: =IFERROR(VLOOKUP(A172,Data1!A:C,3,0),1) -> 12 | N172: =IFERROR(VLOOKUP(D172,Data2!$A:$D,4,0),"") -> 12 | O172: =IFERROR(VLOOKUP(D172,Data2!$A:$C,3,0),"") -> 288 | P172: 87 | Q172: 96 | S172: CASE
A173: 4401-SET6 | B173: B07SFT8ZG7 | C173: X0040DLEAJ | D173: =IFERROR(VLOOKUP(A173,Data1!A:B,2,0),"") -> 4401 | E173: =M173*Q173 -> 576 | F173: =E173/M173 -> 96 | G173: =IFERROR(ROUNDUP(E173/N173,0),"") -> 24 | H173: =IFERROR(ROUNDUP(E173/O173,0),"") -> 4 | I173: =IFERROR(IF(S173="CASE",F173/H173,F173/G173),"") -> 24 | J173: =IF(ISNUMBER(SEARCH("FNSKU",C173)),"Labeling","") | K173: =IFERROR(VLOOKUP(A173,Instruction!A:F,6,0),"") -> • Put 6 pcs into poly bag (Different color), apply FNSKU label. • Insert the poly-bagged sets back to CASE. Discard inner box. (Cover all existing barcodes on the box/case) | L173: =IFERROR(VLOOKUP(A173,Instruction!A:J,10,0),"No Supplies") -> Poly Bag 9 x 12 | M173: =IFERROR(VLOOKUP(A173,Data1!A:C,3,0),1) -> 6 | N173: =IFERROR(VLOOKUP(D173,Data2!$A:$D,4,0),"") -> 24 | O173: =IFERROR(VLOOKUP(D173,Data2!$A:$C,3,0),"") -> 144 | P173: 85 | Q173: 96 | S173: CASE
A174: 5033-EACH | B174: B07SCL3C9Y | C174: X003SVW1PV | D174: =IFERROR(VLOOKUP(A174,Data1!A:B,2,0),"") -> 5033 | E174: =M174*Q174 -> 72 | F174: =E174/M174 -> 72 | G174: =IFERROR(ROUNDUP(E174/N174,0),"") | H174: =IFERROR(ROUNDUP(E174/O174,0),"") -> 3 | I174: =IFERROR(IF(S174="CASE",F174/H174,F174/G174),"") -> 24 | J174: =IF(ISNUMBER(SEARCH("FNSKU",C174)),"Labeling","") | K174: =IFERROR(VLOOKUP(A174,Instruction!A:F,6,0),"") -> • Use FNSKU to label each item (cover barcode). Apply outer box/case label accordingly to match item# (Cover all existing barcodes on the box/case) | L174: =IFERROR(VLOOKUP(A174,Instruction!A:J,10,0),"No Supplies") -> No Supplies | M174: =IFERROR(VLOOKUP(A174,Data1!A:C,3,0),1) -> 1 | N174: =IFERROR(VLOOKUP(D174,Data2!$A:$D,4,0),"") -> 0 | O174: =IFERROR(VLOOKUP(D174,Data2!$A:$C,3,0),"") -> 24 | P174: 83 | Q174: 72 | S174: CASE
A175: 5012-EACH | B175: B002NLIS7G | C175: B002NLIS7G | D175: =IFERROR(VLOOKUP(A175,Data1!A:B,2,0),"") -> 5012 | E175: =M175*Q175 -> 100 | F175: =E175/M175 -> 100 | G175: =IFERROR(ROUNDUP(E175/N175,0),"") | H175: =IFERROR(ROUNDUP(E175/O175,0),"") -> 2 | I175: =IFERROR(IF(S175="CASE",F175/H175,F175/G175),"") -> 50 | J175: =IF(ISNUMBER(SEARCH("FNSKU",C175)),"Labeling","") | K175: =IFERROR(VLOOKUP(A175,Instruction!A:F,6,0),"") -> Apply outer box/case label accordingly to match item# (Cover all existing barcodes on the box/case) | L175: =IFERROR(VLOOKUP(A175,Instruction!A:J,10,0),"No Supplies") -> No Supplies | M175: =IFERROR(VLOOKUP(A175,Data1!A:C,3,0),1) -> 1 | N175: =IFERROR(VLOOKUP(D175,Data2!$A:$D,4,0),"") -> 0 | O175: =IFERROR(VLOOKUP(D175,Data2!$A:$C,3,0),"") -> 50 | P175: 82 | Q175: 100 | S175: CASE
A176: 850-CASE | B176: B07XQLD8PX | C176: B07XQLD8PX | D176: =IFERROR(VLOOKUP(A176,Data1!A:B,2,0),"") -> 850 | E176: =M176*Q176 -> 984 | F176: =E176/M176 -> 82 | G176: =IFERROR(ROUNDUP(E176/N176,0),"") | H176: =IFERROR(ROUNDUP(E176/O176,0),"") -> 82 | I176: =IFERROR(IF(S176="CASE",F176/H176,F176/G176),"") -> 1 | J176: =IF(ISNUMBER(SEARCH("FNSKU",C176)),"Labeling","") | K176: =IFERROR(VLOOKUP(A176,Instruction!A:F,6,0),"") -> • Apply label “THIS IS A SET” **DO NOT COVER CASE BARCODE** • Apply outer case label accordingly to match item# | L176: =IFERROR(VLOOKUP(A176,Instruction!A:J,10,0),"No Supplies") -> No Supplies | M176: =IFERROR(VLOOKUP(A176,Data1!A:C,3,0),1) -> 12 | N176: =IFERROR(VLOOKUP(D176,Data2!$A:$D,4,0),"") -> 0 | O176: =IFERROR(VLOOKUP(D176,Data2!$A:$C,3,0),"") -> 12 | P176: 82 | Q176: 82 | S176: CASE
A177: 565-EACH | B177: B0019IKAES | C177: B0019IKAES | D177: =IFERROR(VLOOKUP(A177,Data1!A:B,2,0),"") -> 565 | E177: =M177*Q177 -> 72 | F177: =E177/M177 -> 72 | G177: =IFERROR(ROUNDUP(E177/N177,0),"") | H177: =IFERROR(ROUNDUP(E177/O177,0),"") -> 2 | I177: =IFERROR(IF(S177="CASE",F177/H177,F177/G177),"") -> 36 | J177: =IF(ISNUMBER(SEARCH("FNSKU",C177)),"Labeling","") | K177: =IFERROR(VLOOKUP(A177,Instruction!A:F,6,0),"") -> Apply outer box/case label accordingly to match item# (Cover all existing barcodes on the box/case) | L177: =IFERROR(VLOOKUP(A177,Instruction!A:J,10,0),"No Supplies") -> No Supplies | M177: =IFERROR(VLOOKUP(A177,Data1!A:C,3,0),1) -> 1 | N177: =IFERROR(VLOOKUP(D177,Data2!$A:$D,4,0),"") -> 0 | O177: =IFERROR(VLOOKUP(D177,Data2!$A:$C,3,0),"") -> 36 | P177: 82 | Q177: 72 | S177: CASE
... A202: 4104-CASE | B202: B07QG6PYDZ | C202: X003SBSK3N | D202: =IFERROR(VLOOKUP(A202,Data1!A:B,2,0),"") -> 4104 | E202: =M202*Q202 -> 804 | F202: =E202/M202 -> 67 | G202: =IFERROR(ROUNDUP(E202/N202,0),"") | H202: =IFERROR(ROUNDUP(E202/O202,0),"") -> 67 | I202: =IFERROR(IF(S202="CASE",F202/H202,F202/G202),"") -> 1 | J202: =IF(ISNUMBER(SEARCH("FNSKU",C202)),"Labeling","") | K202: =IFERROR(VLOOKUP(A202,Instruction!A:F,6,0),"") -> • Apply label “THIS IS A SET”. Apply FNSKU to each case. • *Make sure all labels stick securely on the case*. Apply outer case label. Cover all visible barcodes on case | L202: =IFERROR(VLOOKUP(A202,Instruction!A:J,10,0),"No Supplies") -> No Supplies | M202: =IFERROR(VLOOKUP(A202,Data1!A:C,3,0),1) -> 12 | N202: =IFERROR(VLOOKUP(D202,Data2!$A:$D,4,0),"") -> 0 | O202: =IFERROR(VLOOKUP(D202,Data2!$A:$C,3,0),"") -> 12 | P202: 67 | Q202: 67 | S202: CASE
A203: 1614-PACK2 | B203: B08DL3ZP26 | D203: =IFERROR(VLOOKUP(A203,Data1!A:B,2,0),"") -> 1614 | E203: =M203*Q203 -> 144 | F203: =E203/M203 -> 72 | G203: =IFERROR(ROUNDUP(E203/N203,0),"") -> 6 | H203: =IFERROR(ROUNDUP(E203/O203,0),"") -> 1 | I203: =IFERROR(IF(S203="CASE",F203/H203,F203/G203),"") -> 72 | J203: =IF(ISNUMBER(SEARCH("FNSKU",C203)),"Labeling","") | K203: • Insert 2 pcs into poly bag, apply FNSKU label. • Put back to CASE (Cover all existing barcodes on the box/case) | L203: =IFERROR(VLOOKUP(A203,Instruction!A:J,10,0),"No Supplies") -> 0 | M203: =IFERROR(VLOOKUP(A203,Data1!A:C,3,0),1) -> 2 | N203: =IFERROR(VLOOKUP(D203,Data2!$A:$D,4,0),"") -> 24 | O203: =IFERROR(VLOOKUP(D203,Data2!$A:$C,3,0),"") -> 144 | P203: 67 | Q203: 72 | S203: CASE
A204: 320-SET6 | B204: B07SC5B46P | C204: X0044RLX93 | D204: =IFERROR(VLOOKUP(A204,Data1!A:B,2,0),"") -> 320 | E204: =M204*Q204 -> 288 | F204: =E204/M204 -> 48 | G204: =IFERROR(ROUNDUP(E204/N204,0),"") -> 12 | H204: =IFERROR(ROUNDUP(E204/O204,0),"") -> 1 | I204: =IFERROR(IF(S204="CASE",F204/H204,F204/G204),"") -> 48 | J204: =IF(ISNUMBER(SEARCH("FNSKU",C204)),"Labeling","") | K204: =IFERROR(VLOOKUP(A204,Instruction!A:F,6,0),"") -> • Put 6 pcs (different color) into polybag and apply FNSKU labels on each of the poly bags. • Insert the poly-bagged sets back to CASE (Cover all existing barcodes on the box/case) | L204: =IFERROR(VLOOKUP(A204,Instruction!A:J,10,0),"No Supplies") -> Poly Bag 9 x 12 | M204: =IFERROR(VLOOKUP(A204,Data1!A:C,3,0),1) -> 6 | N204: =IFERROR(VLOOKUP(D204,Data2!$A:$D,4,0),"") -> 24 | O204: =IFERROR(VLOOKUP(D204,Data2!$A:$C,3,0),"") -> 288 | P204: 66 | Q204: 48 | S204: CASE
A205: 846-CASE | B205: B07XQJYFHJ | C205: X003SCCWXB | D205: =IFERROR(VLOOKUP(A205,Data1!A:B,2,0),"") -> 846 | E205: =M205*Q205 -> 1560 | F205: =E205/M205 -> 65 | G205: =IFERROR(ROUNDUP(E205/N205,0),"") | H205: =IFERROR(ROUNDUP(E205/O205,0),"") -> 65 | I205: =IFERROR(IF(S205="CASE",F205/H205,F205/G205),"") -> 1 | J205: =IF(ISNUMBER(SEARCH("FNSKU",C205)),"Labeling","") | K205: =IFERROR(VLOOKUP(A205,Instruction!A:F,6,0),"") -> • Apply label “THIS IS A SET”. Apply FNSKU to each case. • *Make sure all labels stick securely on the case*. Apply outer case label. Cover all visible barcodes on case | L205: =IFERROR(VLOOKUP(A205,Instruction!A:J,10,0),"No Supplies") -> No Supplies | M205: =IFERROR(VLOOKUP(A205,Data1!A:C,3,0),1) -> 24 | N205: =IFERROR(VLOOKUP(D205,Data2!$A:$D,4,0),"") -> 0 | O205: =IFERROR(VLOOKUP(D205,Data2!$A:$C,3,0),"") -> 24 | P205: 65 | Q205: 65 | S205: CASE
A206: 5087-PACK6 | B206: B0B8QH1XGH | C206: X0044R3MFL | D206: =IFERROR(VLOOKUP(A206,Data1!A:B,2,0),"") -> 5087 | E206: =M206*Q206 -> 384 | F206: =E206/M206 -> 64 | G206: =IFERROR(ROUNDUP(E206/N206,0),"") | H206: =IFERROR(ROUNDUP(E206/O206,0),"") -> 8 | I206: =IFERROR(IF(S206="CASE",F206/H206,F206/G206),"") -> 8 | J206: =IF(ISNUMBER(SEARCH("FNSKU",C206)),"Labeling","") | K206: =IFERROR(VLOOKUP(A206,Instruction!A:F,6,0),"") -> • Put 6 pcs into polybag and apply FNSKU labels on each of the poly bags. • Insert the poly-bagged sets back to CASE (Cover all existing barcodes on the box/case) | L206: =IFERROR(VLOOKUP(A206,Instruction!A:J,10,0),"No Supplies") -> Poly Bag 12 x 15.5 | M206: =IFERROR(VLOOKUP(A206,Data1!A:C,3,0),1) -> 6 | N206: =IFERROR(VLOOKUP(D206,Data2!$A:$D,4,0),"") -> 0 | O206: =IFERROR(VLOOKUP(D206,Data2!$A:$C,3,0),"") -> 48 | P206: 64 | Q206: 64 | S206: CASE
A207: 8205-EACH-1 | B207: B003BLQHZ2 | D207: =IFERROR(VLOOKUP(A207,Data1!A:B,2,0),"") -> 8205 | E207: =M207*Q207 -> 72 | F207: =E207/M207 -> 72 | G207: =IFERROR(ROUNDUP(E207/N207,0),"") | H207: =IFERROR(ROUNDUP(E207/O207,0),"") -> 3 | I207: =IFERROR(IF(S207="CASE",F207/H207,F207/G207),"") -> 24 | J207: =IF(ISNUMBER(SEARCH("FNSKU",C207)),"Labeling","") | K207: =IFERROR(VLOOKUP(A207,Instruction!A:F,6,0),"") -> • Use FNSKU to label each item (cover barcode). • Put item back to CASE. Discard inner box • Apply outer case label accordingly to match item# (Cover all existing barcodes on the case) | L207: =IFERROR(VLOOKUP(A207,Instruction!A:J,10,0),"No Supplies") -> 0 | M207: =IFERROR(VLOOKUP(A207,Data1!A:C,3,0),1) -> 1 | N207: =IFERROR(VLOOKUP(D207,Data2!$A:$D,4,0),"") -> 0 | O207: =IFERROR(VLOOKUP(D207,Data2!$A:$C,3,0),"") -> 24 | P207: 72 | Q207: 72 | S207: CASE
A208: 2330-EACH | B208: B00TQ5WT4U | C208: B00TQ5WT4U | D208: =IFERROR(VLOOKUP(A208,Data1!A:B,2,0),"") -> 2330 | E208: =M208*Q208 -> 72 | F208: =E208/M208 -> 72 | G208: =IFERROR(ROUNDUP(E208/N208,0),"") -> 3 | H208: =IFERROR(ROUNDUP(E208/O208,0),"") -> 1 | I208: =IFERROR(IF(S208="CASE",F208/H208,F208/G208),"") -> 24 | J208: =IF(ISNUMBER(SEARCH("FNSKU",C208)),"Labeling","") | K208: =IFERROR(VLOOKUP(A208,Instruction!A:F,6,0),"") -> Apply outer box/case label accordingly to match item# (Cover all existing barcodes on the box/case) | L208: =IFERROR(VLOOKUP(A208,Instruction!A:J,10,0),"No Supplies") -> No Supplies | M208: =IFERROR(VLOOKUP(A208,Data1!A:C,3,0),1) -> 1 | N208: =IFERROR(VLOOKUP(D208,Data2!$A:$D,4,0),"") -> 24 | O208: =IFERROR(VLOOKUP(D208,Data2!$A:$C,3,0),"") -> 144 | P208: 64 | Q208: 72 | S208: BOX
A209: 4150-EACH | B209: B07Q5VSDJZ | C209: X003Y74FUN | D209: =IFERROR(VLOOKUP(A209,Data1!A:B,2,0),"") -> 4150 | E209: =M209*Q209 -> 60 | F209: =E209/M209 -> 60 | G209: =IFERROR(ROUNDUP(E209/N209,0),"") | H209: =IFERROR(ROUNDUP(E209/O209,0),"") -> 5 | I209: =IFERROR(IF(S209="CASE",F209/H209,F209/G209),"") -> 12 | J209: =IF(ISNUMBER(SEARCH("FNSKU",C209)),"Labeling","") | K209: =IFERROR(VLOOKUP(A209,Instruction!A:F,6,0),"") -> • Use FNSKU to label each item (cover barcode). Apply outer box/case label accordingly to match item# (Cover all existing barcodes on the box/case) | L209: =IFERROR(VLOOKUP(A209,Instruction!A:J,10,0),"No Supplies") -> No Supplies | M209: =IFERROR(VLOOKUP(A209,Data1!A:C,3,0),1) -> 1 | N209: =IFERROR(VLOOKUP(D209,Data2!$A:$D,4,0),"") -> 0 | O209: =IFERROR(VLOOKUP(D209,Data2!$A:$C,3,0),"") -> 12 | P209: 64 | Q209: 60 | S209: CASE
A210: 4141-EACH | B210: B07Q84PXRP | C210: X003SBSK2T | D210: =IFERROR(VLOOKUP(A210,Data1!A:B,2,0),"") -> 4141 | E210: =M210*Q210 -> 60 | F210: =E210/M210 -> 60 | G210: =IFERROR(ROUNDUP(E210/N210,0),"") | H210: =IFERROR(ROUNDUP(E210/O210,0),"") -> 5 | I210: =IFERROR(IF(S210="CASE",F210/H210,F210/G210),"") -> 12 | J210: =IF(ISNUMBER(SEARCH("FNSKU",C210)),"Labeling","") | K210: =IFERROR(VLOOKUP(A210,Instruction!A:F,6,0),"") -> • Use FNSKU to label each item (cover barcode). Apply outer box/case label accordingly to match item# (Cover all existing barcodes on the box/case) | L210: =IFERROR(VLOOKUP(A210,Instruction!A:J,10,0),"No Supplies") -> No Supplies | M210: =IFERROR(VLOOKUP(A210,Data1!A:C,3,0),1) -> 1 | N210: =IFERROR(VLOOKUP(D210,Data2!$A:$D,4,0),"") -> 0 | O210: =IFERROR(VLOOKUP(D210,Data2!$A:$C,3,0),"") -> 12 | P210: 64 | Q210: 60 | S210: CASE
A211: 801-SET4 | B211: B07RBBZRBK | C211: X003SC3AO1 | D211: =IFERROR(VLOOKUP(A211,Data1!A:B,2,0),"") -> 801 | E211: =M211*Q211 -> 288 | F211: =E211/M211 -> 72 | G211: =IFERROR(ROUNDUP(E211/N211,0),"") -> 12 | H211: =IFERROR(ROUNDUP(E211/O211,0),"") -> 2 | I211: =IFERROR(IF(S211="CASE",F211/H211,F211/G211),"") -> 36 | J211: =IF(ISNUMBER(SEARCH("FNSKU",C211)),"Labeling","") | K211: =IFERROR(VLOOKUP(A211,Instruction!A:F,6,0),"") -> • Put 4 pcs into polybag (different color) and apply FNSKU labels on each of the poly bags. • Insert the poly-bagged sets back to CASE. Discard inner box (Cover all existing barcodes on the box/case) | L211: =IFERROR(VLOOKUP(A211,Instruction!A:J,10,0),"No Supplies") -> Poly Bag 9 x 12 | M211: =IFERROR(VLOOKUP(A211,Data1!A:C,3,0),1) -> 4 | N211: =IFERROR(VLOOKUP(D211,Data2!$A:$D,4,0),"") -> 24 | O211: =IFERROR(VLOOKUP(D211,Data2!$A:$C,3,0),"") -> 144 | P211: 64 | Q211: 72 | S211: CASE
A212: 530-EACH | B212: B07S7GG12K | C212: X003GYJU0J | D212: =IFERROR(VLOOKUP(A212,Data1!A:B,2,0),"") -> 530 | E212: =M212*Q212 -> 48 | F212: =E212/M212 -> 48 | G212: =IFERROR(ROUNDUP(E212/N212,0),"") | H212: =IFERROR(ROUNDUP(E212/O212,0),"") -> 1 | I212: =IFERROR(IF(S212="CASE",F212/H212,F212/G212),"") -> 48 | J212: =IF(ISNUMBER(SEARCH("FNSKU",C212)),"Labeling","") | K212: =IFERROR(VLOOKUP(A212,Instruction!A:F,6,0),"") -> • Use FNSKU to label each item (cover barcode). Apply outer box/case label accordingly to match item# (Cover all existing barcodes on the box/case) | L212: =IFERROR(VLOOKUP(A212,Instruction!A:J,10,0),"No Supplies") -> No Supplies | M212: =IFERROR(VLOOKUP(A212,Data1!A:C,3,0),1) -> 1 | N212: =IFERROR(VLOOKUP(D212,Data2!$A:$D,4,0),"") -> 0 | O212: =IFERROR(VLOOKUP(D212,Data2!$A:$C,3,0),"") -> 48 | P212: 64 | Q212: 48 | S212: CASE
A213: 3006-SET6 | B213: B07RJTVW1K | C213: B07RJTVW1K | D213: =IFERROR(VLOOKUP(A213,Data1!A:B,2,0),"") -> 3006 | E213: =M213*Q213 -> 432 | F213: =E213/M213 -> 72 | G213: =IFERROR(ROUNDUP(E213/N213,0),"") -> 18 | H213: =IFERROR(ROUNDUP(E213/O213,0),"") -> 3 | I213: =IFERROR(IF(S213="CASE",F213/H213,F213/G213),"") -> 24 | J213: =IF(ISNUMBER(SEARCH("FNSKU",C213)),"Labeling","") | K213: =IFERROR(VLOOKUP(A213,Instruction!A:F,6,0),"") -> • Put 6 pcs into polybag (different color) and apply FNSKU labels on each of the poly bags. • Insert the poly-bagged sets back to CASE (Cover all existing barcodes on the box/case) | L213: =IFERROR(VLOOKUP(A213,Instruction!A:J,10,0),"No Supplies") -> Poly Bag 7.5 x 10.5 | M213: =IFERROR(VLOOKUP(A213,Data1!A:C,3,0),1) -> 6 | N213: =IFERROR(VLOOKUP(D213,Data2!$A:$D,4,0),"") -> 24 | O213: =IFERROR(VLOOKUP(D213,Data2!$A:$C,3,0),"") -> 144 | P213: 64 | Q213: 72 | S213: CASE
A214: 1812-SET6 | B214: B00U9UC766 | C214: B00U9UC766 | D214: =IFERROR(VLOOKUP(A214,Data1!A:B,2,0),"") -> 1812 | E214: =M214*Q214 -> 384 | F214: =E214/M214 -> 64 | G214: =IFERROR(ROUNDUP(E214/N214,0),"") | H214: =IFERROR(ROUNDUP(E214/O214,0),"") -> 8 | I214: =IFERROR(IF(S214="CASE",F214/H214,F214/G214),"") -> 8 | J214: =IF(ISNUMBER(SEARCH("FNSKU",C214)),"Labeling","") | K214: =IFERROR(VLOOKUP(A214,Instruction!A:F,6,0),"") -> • Put 6 pcs into polybag (different color) and apply FNSKU labels on each of the poly bags. • Insert the poly-bagged sets back to CASE. (Cover all existing barcodes on the box/case) | L214: =IFERROR(VLOOKUP(A214,Instruction!A:J,10,0),"No Supplies") -> Poly Bag 12 x 15.5 | M214: =IFERROR(VLOOKUP(A214,Data1!A:C,3,0),1) -> 6 | N214: =IFERROR(VLOOKUP(D214,Data2!$A:$D,4,0),"") -> 0 | O214: =IFERROR(VLOOKUP(D214,Data2!$A:$C,3,0),"") -> 48 | P214: 62 | Q214: 64 | S214: CASE
A215: 3132-CASE-B | B215: B00275E9XU | C215: B00275E9XU | D215: =IFERROR(VLOOKUP(A215,Data1!A:B,2,0),"") -> 3132 | E215: =M215*Q215 -> 2976 | F215: =E215/M215 -> 62 | G215: =IFERROR(ROUNDUP(E215/N215,0),"") | H215: =IFERROR(ROUNDUP(E215/O215,0),"") -> 62 | I215: =IFERROR(IF(S215="CASE",F215/H215,F215/G215),"") -> 1 | J215: =IF(ISNUMBER(SEARCH("FNSKU",C215)),"Labeling","") | K215: =IFERROR(VLOOKUP(A215,Instruction!A:F,6,0),"") -> • Apply label “THIS IS A SET” **DO NOT COVER CASE BARCODE** • Apply outer case label accordingly to match item# | L215: =IFERROR(VLOOKUP(A215,Instruction!A:J,10,0),"No Supplies") -> No Supplies | M215: =IFERROR(VLOOKUP(A215,Data1!A:C,3,0),1) -> 48 | N215: =IFERROR(VLOOKUP(D215,Data2!$A:$D,4,0),"") -> 0 | O215: =IFERROR(VLOOKUP(D215,Data2!$A:$C,3,0),"") -> 48 | P215: 62 | Q215: 62 | S215: CASE
A216: 6303-EACH | B216: B08P3WZTXG | C216: B08P3WZTXG | D216: =IFERROR(VLOOKUP(A216,Data1!A:B,2,0),"") -> 6303 | E216: =M216*Q216 -> 72 | F216: =E216/M216 -> 72 | G216: =IFERROR(ROUNDUP(E216/N216,0),"") -> 3 | H216: =IFERROR(ROUNDUP(E216/O216,0),"") -> 1 | I216: =IFERROR(IF(S216="CASE",F216/H216,F216/G216),"") -> 24 | J216: =IF(ISNUMBER(SEARCH("FNSKU",C216)),"Labeling","") | K216: =IFERROR(VLOOKUP(A216,Instruction!A:F,6,0),"") -> Cover inner box barcode. Apply outer case label accordingly to match item# (Cover barcodes on the case) | L216: =IFERROR(VLOOKUP(A216,Instruction!A:J,10,0),"No Supplies") -> No Supplies | M216: =IFERROR(VLOOKUP(A216,Data1!A:C,3,0),1) -> 1 | N216: =IFERROR(VLOOKUP(D216,Data2!$A:$D,4,0),"") -> 24 | O216: =IFERROR(VLOOKUP(D216,Data2!$A:$C,3,0),"") -> 144 | P216: 61 | Q216: 72 | S216: BOX
...

Sheet SO
F1: ATTENTION: AWD removal | G1: Qty | H1: Used
B2: Item# | C2: BOX | D2: CASE | F2: 5027-CASE | G2: 10 | H2: 1
B3: 203 | C3: 1
B4: 534 | C4: 1
B5: 713 | C5: 1
B6: 2012 | C6: 1
B7: 2225 | C7: 1
B8: 609 | C8: 2
B9: 767 | C9: 2
B10: 1293 | C10: 2
B11: 2204 | C11: 2
B12: 2043 | C12: 3
B13: 5074 | C13: 3
B14: S-2 | C14: 4
B15: 837 | C15: 5
B16: 508 | D16: 1
B17: 530 | D17: 1
B18: 569 | D18: 1
B19: 1286 | D19: 1
B20: 2405 | D20: 1
B21: 4151 | D21: 1
B22: 5053 | D22: 1
B23: 5087 | D23: 1
B24: 5173 | D24: 1
B25: 6303 | D25: 1
B26: 533 | D26: 2
B27: 608 | D27: 2
... B46: 4122 | D46: 4
B47: 942-A | D47: 4
B48: 560 | D48: 5
B49: 609 | D49: 5
B50: 5027 | D50: 5
B51: 5043 | D51: 5
B52: 4576436 | D52: 5
B53: 3459-A | D53: 5
B54: 532 | D54: 6
B55: 39200 | D55: 6
B56: 3451 | D56: 8
B57: 3191 | D57: 9
B58: 3467 | D58: 9
B59: 847 | D59: 10
B60: 5066 | D60: 10
B61: 41166 | D61: 10
B62: 3163 | D62: 12
B63: 3167 | D63: 17
B64: 582 | D64: 20

Sheet Sheet1
A1: Workflow name | B1: wf9547a679-894d-4f41-afc0-a2dbe4aa3f05
A2: Shipment ID | B2: STAR-VKFAPNKKS6S4A
A3: Shipment name | B3: To be assigned
A4: Ship to | B4: NORTH EAST, MD
A5: Boxes | B5: 241
A6: SKUs | B6: 72
A7: Units | B7: 4352
A9: Case packed (241 boxes)
A10: SKU | B10: Title | C10: ASIN | D10: FNSKU | E10: Case pack template name | F10: Condition | G10: Who preps units? | H10: Who labels units? | I10: Prep type | J10: Box weight (lb) | K10: Box length (inch) | L10: Box width (inch) | M10: Box height (inch) | N10: Units per box | O10: Total boxes | P10: Total units | Q10: Box ID
A11: FBA_533-BOX | B11: BAZIC Subtraction Flash Cards, Numbers Math Flashcards Game at School Home, Problem Solving (36/Pack), 24-Packs | C11: B07XQLGMSV | D11: X0044RLXAR | E11: Case (3 boxes) | F11: New | G11: By seller | H11: By seller | I11: No prep needed | J11: 16.4 | K11: 7 | L11: 12 | M11: 11 | N11: 3 | O11: 2 | P11: 6 | Q11: To be assigned
A12: FBA_508-EACH | B12: BAZIC Composition Book Wide Ruled 100 Sheet Black Marble Notebook, Writing Journal Comp Lined Notebooks for School, 1-Pack | C12: B001E75OY0 | D12: B001E75OY0 | E12: ASDN_DEFAULT_CONFIG | F12: New | G12: By seller | H12: - | I12: No prep needed | J12: 31.8 | K12: 15.5 | L12: 10 | M12: 8.5 | N12: 48 | O12: 1 | P12: 48 | Q12: To be assigned
A13: FBA_3107-BOX | B13: BAZIC Binder Dividers w/ 10 Color Tabs 8. 5" x 11", 11 Hole Punch Plastic Index Divider with Tab for 3 Ring Binders, (10/Pack), 24-Packs | C13: B07XQJZL28 | D13: X0045A6VWX | E13: Case (6 boxes) | F13: New | G13: By seller | H13: By seller | I13: No prep needed | J13: 37.6 | K13: 10 | L13: 15 | M13: 13 | N13: 6 | O13: 2 | P13: 12 | Q13: To be assigned
A14: FBA_942-A-EA-BL | B14: BAZIC Desktop Tape Dispenser w/Tape Refill 3/4" x 250", 1" Core Weighted Non-Skid Base, Sharpe Blade Tapes Holder, Blue Color, 1-Pack | C14: B0CV2WM9FJ | D14: X0044KCA65 | E14: Case (12) | F14: New | G14: By seller | H14: By seller | I14: No prep needed | J14: 20 | K14: 8 | L14: 12 | M14: 11 | N14: 12 | O14: 1 | P14: 12 | Q14: To be assigned
A15: FBA_3191-CASE | B15: BAZIC 3 Ring Binder 1" Economy View Binders Organizer - Blue, Round Ring, Hold 175 Sheets Paper, for School Office Home, 12-Count | C15: B07QF5ZS6P | D15: X003SBSJJN | E15: 1 Case | F15: New | G15: By seller | H15: By seller | I15: No prep needed | J15: 8.64 | K15: 6 | L15: 13.25 | M15: 12.25 | N15: 1 | O15: 9 | P15: 9 | Q15: To be assigned
A16: FBA_3467-EACH | B16: BAZIC Glitter Glue Tube Classic Color, Non-Toxic Washable Glitter Glue for Slime Paints DIY Art Crafts Party (120ml/Pack), 1-Pack | C16: B01HDJMKBM | D16: B01HDJMKBM | E16: Case (72) | F16: New | G16: By seller | H16: - | I16: No prep needed | J16: 30.58 | K16: 12 | L16: 13.5 | M16: 13.25 | N16: 72 | O16: 4 | P16: 288 | Q16: To be assigned
A17: FBA_3167-SET4 | B17: BAZIC 3 Ring Binder 1" Economy View Binders Organizer - Pastel Color, Round Ring, Hold 175 Sheets Paper, for School Office Home, 4-Count | C17: B08LP2FGJM | D17: X003BVZHKJ | E17: Case Pack (10 Sets) | F17: New | G17: - | H17: By seller | I17: No prep needed | J17: 28 | K17: 13 | L17: 19 | M17: 13 | N17: 10 | O17: 10 | P17: 100 | Q17: To be assigned
A18: FBA_609-PACK4 | B18: BAZIC Staples Standard (26/6) Metallic Color 3000/Pack, Stapler Refill Standard Size Staple, Assorted Colors, 4-Packs | C18: B09C2QNFTV | D18: X0044RLX89 | E18: Case (18) | F18: New | G18: By seller | H18: By seller | I18: No prep needed | J18: 17.08 | K18: 5 | L18: 14 | M18: 8 | N18: 18 | O18: 3 | P18: 54 | Q18: To be assigned
A19: FBA_5414-PACK3 | B19: BAZIC Poster Board Glitter Color 11" X 14", Sparkling Frame Colored Poster Board Paper for Christmas Wedding Birthday Craft Project (5/Pack), 3-Packs | C19: B08FZR2GLR | D19: X00468H3EJ | E19: ASDN_DEFAULT_CONFIG | F19: New | G19: By seller | H19: By seller | I19: No prep needed | J19: 19 | K19: 16 | L19: 15 | M19: 6 | N19: 16 | O19: 2 | P19: 32 | Q19: To be assigned
A20: FBA_4577036-SET2 | B20: Disney Princess Coloring Book 2 Titles, Fun Game Workbook for Learning Drawing Coloring, Gift for Kids Toddler Activity at Classroom Home, 80 Pages, 2-Pack | C20: B0897CBHTZ | D20: X004BHUY9L | E20: Case (18 Sets) | F20: New | G20: - | H20: By seller | I20: No prep needed | J20: 10.6 | K20: 4 | L20: 16 | M20: 11 | N20: 18 | O20: 2 | P20: 36 | Q20: To be assigned
A21: FBA_5043-PACK2 | B21: BAZIC Sketch Pad 50 Sheet 6" X 8", Top Bound Spiral Sketchbook Drawing Pads, Sketching Paper Coloring Book for Artist School, 2-Pack | C21: B08DFJW6V4 | D21: X0040DSNM1 | E21: Case (24) | F21: New | G21: By seller | H21: By seller | I21: No prep needed | J21: 22 | K21: 9.75 | L21: 12.75 | M21: 10 | N21: 24 | O21: 3 | P21: 72 | Q21: To be assigned
A22: FBA_2405-EACH | B22: BAZIC White Chalk, Standard Size Blackboard Chalkboard Chalks, Great Game Activity for Kids, Art Teacher Office School Home (24/Pack), 1-Pack | C22: B003BUK0UG | D22: B003BUK0UG | E22: ASDN_DEFAULT_CONFIG | F22: New | G22: By seller | H22: - | I22: No prep needed | J22: 15 | K22: 8 | L22: 6 | M22: 4 | N22: 24 | O22: 1 | P22: 24 | Q22: To be assigned
... A82: FBA_560-PACK6 | B82: BAZIC Writing Pad 100 Sheets 6" X 9", Lined Ruled Memo Writing Notebook, Easy Tear Note Paper for Office School Home, 6-Pack [unknown_binding] | C82: B08FBQM8VF | D82: X003SFDOWB | E82: ASDN_DEFAULT_CONFIG | F82: New | G82: By seller | H82: By seller | I82: No prep needed | J82: 30 | K82: 12 | L82: 13 | M82: 16 | N82: 8 | O82: 5 | P82: 40 | Q82: To be assigned

Sheet AWD Return
A1: SKU | B1: Item | C1: Qty (EA)
A2: 5027-EACH | B2: 5027 | C2: 480
A3: 560-EACH | B3: 560 | C3: =263-96 -> 167
A4: 3001-EACH | B4: 3001 | C4: 24

Sheet For WH Single
A1: SKU | B1: ASIN | C1: FNSKU | D1: Item | E1: Total EA (Transfer to WH06) | F1: Sellable Unit/Set/box to ship | G1: Box 1 units | H1: Box 2 units | I1: Label | J1: Packing Instructions | K1: Supplies | L1: UoM | M1: -- | N1: --2 | O1: Recommended Replenishment Qty | P1: Current WH Inventory
A2: 4403-SET6 | B2: B0BRNSWP12 | C2: X0043V3DCZ | D2: =VLOOKUP(A2,Data1!A:B,2,0) -> 4403 | E2: =L2*O2 -> 12 | F2: =O2 -> 2 | G2: 2 | I2: Labeling | J2: =VLOOKUP(A2,Instruction!A:F,7,0) -> #REF! | L2: =VLOOKUP(A2,Data1!A:C,3,0) -> 6 | O2: 2 | P2: =VLOOKUP(D2,[1]Sheet1!$B:$D,3,0) -> 10343
A3: 4400-SET2 | B3: B07SFT7P7X | C3: X0043UN7EF | D3: =VLOOKUP(A3,Data1!A:B,2,0) -> 4400 | E3: =L3*O3 -> 8 | F3: =O3 -> 4 | G3: 4 | I3: Labeling | J3: =VLOOKUP(A3,Instruction!A:F,7,0) -> #REF! | L3: =VLOOKUP(A3,Data1!A:C,3,0) -> 2 | O3: 4 | P3: =VLOOKUP(D3,[1]Sheet1!$B:$D,3,0) -> 28720
A4: 17036-EACH | B4: B0CQ66C7RL | C4: X0043UNGZ5 | D4: =VLOOKUP(A4,Data1!A:B,2,0) -> 17036 | E4: =L4*O4 -> 6 | F4: =O4 -> 6 | G4: 6 | I4: Labeling | J4: =VLOOKUP(A4,Instruction!A:F,7,0) -> #REF! | L4: =VLOOKUP(A4,Data1!A:C,3,0) -> 1 | O4: 6 | P4: =VLOOKUP(D4,[1]Sheet1!$B:$D,3,0) -> 19554
A5: 709-EACH | B5: B0CGW5J3SV | C5: X0043V3OBP | D5: =VLOOKUP(A5,Data1!A:B,2,0) -> 709 | E5: =L5*O5 -> 6 | F5: =O5 -> 6 | G5: 6 | I5: Labeling | J5: =VLOOKUP(A5,Instruction!A:F,7,0) -> #REF! | L5: =VLOOKUP(A5,Data1!A:C,3,0) -> 1 | O5: 6 | P5: =VLOOKUP(D5,[1]Sheet1!$B:$D,3,0) -> 2396
A6: 17035-EACH | B6: B0CQ67CVM7 | C6: X0043UZRXT | D6: =VLOOKUP(A6,Data1!A:B,2,0) -> 17035 | E6: =L6*O6 -> 6 | F6: =O6 -> 6 | G6: 6 | I6: Labeling | J6: =VLOOKUP(A6,Instruction!A:F,7,0) -> #REF! | L6: =VLOOKUP(A6,Data1!A:C,3,0) -> 1 | O6: 6 | P6: =VLOOKUP(D6,[1]Sheet1!$B:$D,3,0) -> 33166
A7: 914-EACH | B7: B07SKF1B25 | C7: X00446K72N | D7: =VLOOKUP(A7,Data1!A:B,2,0) -> 914 | E7: =L7*O7 -> 4 | F7: =O7 -> 4 | H7: 4 | I7: Labeling | J7: =VLOOKUP(A7,Instruction!A:F,7,0) -> #REF! | L7: =VLOOKUP(A7,Data1!A:C,3,0) -> 1 | O7: 4 | P7: =VLOOKUP(D7,[1]Sheet1!$B:$D,3,0) -> 32063
A8: 905-EACH | B8: B07SKD994F | C8: X0043UN5TH | D8: =VLOOKUP(A8,Data1!A:B,2,0) -> 905 | E8: =L8*O8 -> 4 | F8: =O8 -> 4 | H8: 4 | I8: Labeling | J8: =VLOOKUP(A8,Instruction!A:F,7,0) -> #REF! | L8: =VLOOKUP(A8,Data1!A:C,3,0) -> 1 | O8: 4 | P8: =VLOOKUP(D8,[1]Sheet1!$B:$D,3,0) -> 86003
A9: 1215-EACH | B9: B0CJMRSK5J | C9: X0043UN4H5 | D9: =VLOOKUP(A9,Data1!A:B,2,0) -> 1215 | E9: =L9*O9 -> 6 | F9: =O9 -> 6 | H9: 6 | I9: Labeling | J9: =VLOOKUP(A9,Instruction!A:F,7,0) -> #REF! | L9: =VLOOKUP(A9,Data1!A:C,3,0) -> 1 | O9: 6 | P9: =VLOOKUP(D9,[1]Sheet1!$B:$D,3,0) -> 10438
A10: 1227-EACH | B10: B08WPW8T92 | C10: X0043V3IBL | D10: =VLOOKUP(A10,Data1!A:B,2,0) -> 1227 | E10: =L10*O10 -> 6 | F10: =O10 -> 6 | H10: 6 | I10: Labeling | J10: =VLOOKUP(A10,Instruction!A:F,7,0) -> #REF! | L10: =VLOOKUP(A10,Data1!A:C,3,0) -> 1 | O10: 6 | P10: =VLOOKUP(D10,[1]Sheet1!$B:$D,3,0) -> 4391
A11: 992-EACH | B11: B08R6JJP2L | C11: X0043V3CT9 | D11: =VLOOKUP(A11,Data1!A:B,2,0) -> 992 | E11: =L11*O11 -> 4 | F11: =O11 -> 4 | H11: 4 | I11: Labeling | J11: =VLOOKUP(A11,Instruction!A:F,7,0) -> #REF! | L11: =VLOOKUP(A11,Data1!A:C,3,0) -> 1 | O11: 4 | P11: =VLOOKUP(D11,[1]Sheet1!$B:$D,3,0) -> 3003
A12: 6041-EACH | B12: B072LP49MC | C12: B072LP49MC | D12: =VLOOKUP(A12,Data1!A:B,2,0) -> 6041 | E12: =L12*O12 -> 4 | F12: =O12 -> 4 | G12: 4 | J12: =VLOOKUP(A12,Instruction!A:F,7,0) -> #REF! | L12: =VLOOKUP(A12,Data1!A:C,3,0) -> 1 | O12: 4 | P12: =VLOOKUP(D12,[1]Sheet1!$B:$D,3,0) -> 4235
A13: 2561-EACH | B13: B09QD62R6R | C13: B09QD62R6R | D13: =VLOOKUP(A13,Data1!A:B,2,0) -> 2561 | E13: =L13*O13 -> 6 | F13: =O13 -> 6 | G13: 6 | J13: =VLOOKUP(A13,Instruction!A:F,7,0) -> #REF! | L13: =VLOOKUP(A13,Data1!A:C,3,0) -> 1 | O13: 6 | P13: =VLOOKUP(D13,[1]Sheet1!$B:$D,3,0) -> 30774
A14: 768-EACH | B14: B005KQ9316 | C14: B005KQ9316 | D14: =VLOOKUP(A14,Data1!A:B,2,0) -> 768 | E14: =L14*O14 -> 4 | F14: =O14 -> 4 | G14: 4 | J14: =VLOOKUP(A14,Instruction!A:F,7,0) -> #REF! | L14: =VLOOKUP(A14,Data1!A:C,3,0) -> 1 | O14: 4 | P14: =VLOOKUP(D14,[1]Sheet1!$B:$D,3,0) -> 22194
A15: 1277-EACH | B15: B0B9P3TD4K | C15: B0B9P3TD4K | D15: =VLOOKUP(A15,Data1!A:B,2,0) -> 1277 | E15: =L15*O15 -> 6 | F15: =O15 -> 6 | G15: 6 | J15: =VLOOKUP(A15,Instruction!A:F,7,0) -> #REF! | L15: =VLOOKUP(A15,Data1!A:C,3,0) -> 1 | O15: 6 | P15: =VLOOKUP(D15,[1]Sheet1!$B:$D,3,0) -> 10417
A16: 120-EACH | B16: B003BS9G44 | C16: B003BS9G44 | D16: =VLOOKUP(A16,Data1!A:B,2,0) -> 120 | E16: =L16*O16 -> 6 | F16: =O16 -> 6 | H16: 6 | J16: =VLOOKUP(A16,Instruction!A:F,7,0) -> #REF! | L16: =VLOOKUP(A16,Data1!A:C,3,0) -> 1 | O16: 6 | P16: =VLOOKUP(D16,[1]Sheet1!$B:$D,3,0) -> 22529
A17: 3301-EACH | B17: B0CPRBHWH9 | C17: B0CPRBHWH9 | D17: =VLOOKUP(A17,Data1!A:B,2,0) -> 3301 | E17: =L17*O17 -> 4 | F17: =O17 -> 4 | H17: 4 | J17: =VLOOKUP(A17,Instruction!A:F,7,0) -> #REF! | L17: =VLOOKUP(A17,Data1!A:C,3,0) -> 1 | O17: 4 | P17: =VLOOKUP(D17,[1]Sheet1!$B:$D,3,0) -> 281
A18: 715-EACH | B18: B07S6D1VMB | C18: B07S6D1VMB | D18: =VLOOKUP(A18,Data1!A:B,2,0) -> 715 | E18: =L18*O18 -> 3 | F18: =O18 -> 3 | H18: 3 | J18: =VLOOKUP(A18,Instruction!A:F,7,0) -> #REF! | L18: =VLOOKUP(A18,Data1!A:C,3,0) -> 1 | O18: 3 | P18: =VLOOKUP(D18,[1]Sheet1!$B:$D,3,0) -> 1789
A19: 3300-EACH | B19: B0CPRPLLFH | C19: B0CPRPLLFH | D19: =VLOOKUP(A19,Data1!A:B,2,0) -> 3300 | E19: =L19*O19 -> 4 | F19: =O19 -> 4 | H19: 4 | J19: =VLOOKUP(A19,Instruction!A:F,7,0) -> #REF! | L19: =VLOOKUP(A19,Data1!A:C,3,0) -> 1 | O19: 4 | P19: =VLOOKUP(D19,[1]Sheet1!$B:$D,3,0) -> 832

Sheet Bundles
B1: SKU | C1: Sellable Set to ship | D1: Item# | E1: Total EA (Transfer to WH07) | F1: Box | G1: Case | H1: Box Uom | I1: Case Uom | J1: Inventory
B2: 532-EA+533-EA+534-EA+535-EA | C2: 24 | D2: 532 | E2: =$C$2 -> 24 | F2: 1 | H2: =VLOOKUP(D2,[2]Data2!A:D,4,0) -> 24 | I2: =VLOOKUP(D2,[2]Data2!A:D,3,0) -> 72 | J2: =VLOOKUP(Table33[[#This Row],[Item'#]],[3]Sheet1!$B:$D,3,0) -> 14369
D3: 533 | E3: =$C$2 -> 24 | F3: 1 | H3: =VLOOKUP(D3,[2]Data2!A:D,4,0) -> 24 | I3: =VLOOKUP(D3,[2]Data2!A:D,3,0) -> 72 | J3: =VLOOKUP(Table33[[#This Row],[Item'#]],[3]Sheet1!$B:$D,3,0) -> 25958
D4: 534 | E4: =$C$2 -> 24 | F4: 1 | H4: =VLOOKUP(D4,[2]Data2!A:D,4,0) -> 24 | I4: =VLOOKUP(D4,[2]Data2!A:D,3,0) -> 72 | J4: =VLOOKUP(Table33[[#This Row],[Item'#]],[3]Sheet1!$B:$D,3,0) -> 35701
D5: 535 | E5: =$C$2 -> 24 | F5: 1 | H5: =VLOOKUP(D5,[2]Data2!A:D,4,0) -> 24 | I5: =VLOOKUP(D5,[2]Data2!A:D,3,0) -> 72 | J5: =VLOOKUP(Table33[[#This Row],[Item'#]],[3]Sheet1!$B:$D,3,0) -> 3669
B7: SKU | C7: Sellable Set to ship | D7: Item# | E7: Total EA (Transfer to WH07) | F7: Box | G7: Case | H7: Box Uom | I7: Case Uom | J7: Inventory
B8: 544-EA+548-EA+549-EA | C8: 24 | D8: 544 | E8: =$C$8 -> 24 | F8: 1 | H8: =VLOOKUP(D8,[2]Data2!A:D,4,0) -> 24 | I8: =VLOOKUP(D8,[2]Data2!A:D,3,0) -> 72 | J8: =VLOOKUP(Table415[[#This Row],[Item'#]],[3]Sheet1!$B:$D,3,0) -> 24437
D9: 548 | E9: =$C$8 -> 24 | F9: 1 | H9: =VLOOKUP(D9,[2]Data2!A:D,4,0) -> 24 | I9: =VLOOKUP(D9,[2]Data2!A:D,3,0) -> 72 | J9: =VLOOKUP(Table415[[#This Row],[Item'#]],[3]Sheet1!$B:$D,3,0) -> 26224
D10: 549 | E10: =$C$8 -> 24 | F10: 1 | H10: =VLOOKUP(D10,[2]Data2!A:D,4,0) -> 24 | I10: =VLOOKUP(D10,[2]Data2!A:D,3,0) -> 72 | J10: =VLOOKUP(Table415[[#This Row],[Item'#]],[3]Sheet1!$B:$D,3,0) -> 2697
B12: SKU | C12: Sellable Set to ship | D12: Item# | E12: Total EA (Transfer to WH07) | F12: Box | G12: Case | H12: Box Uom | I12: Case Uom | J12: Inventory
B13: 534-EA+535-EA | C13: 48 | D13: 534 | E13: 48 | F13: 2 | H13: =VLOOKUP(D13,[2]Data2!A:D,4,0) -> 24 | I13: =VLOOKUP(D13,[2]Data2!A:D,3,0) -> 72 | J13: =VLOOKUP(Table516[[#This Row],[Item'#]],[3]Sheet1!$B:$D,3,0) -> 35701
D14: 535 | E14: 48 | F14: 2 | H14: =VLOOKUP(D14,[2]Data2!A:D,4,0) -> 24 | I14: =VLOOKUP(D14,[2]Data2!A:D,3,0) -> 72 | J14: =VLOOKUP(Table516[[#This Row],[Item'#]],[3]Sheet1!$B:$D,3,0) -> 3669
B16: SKU | C16: Sellable Set to ship | D16: Item# | E16: Total EA (Transfer to WH07) | F16: Box | G16: Case | H16: Box Uom | I16: Case Uom | J16: Inventory
B17: 5600-EA+5601-EA+5602-EA | C17: 24 | D17: 5600 | E17: =$C$8 -> 24 | F17: 1 | H17: =VLOOKUP(D17,[2]Data2!A:D,4,0) -> #N/A | I17: =VLOOKUP(D17,[2]Data2!A:D,3,0) -> #N/A | J17: =VLOOKUP(Table4159[[#This Row],[Item'#]],[3]Sheet1!$B:$D,3,0) -> 8088
D18: 5601 | E18: =$C$8 -> 24 | F18: 1 | H18: =VLOOKUP(D18,[2]Data2!A:D,4,0) -> #N/A | I18: =VLOOKUP(D18,[2]Data2!A:D,3,0) -> #N/A | J18: =VLOOKUP(Table4159[[#This Row],[Item'#]],[3]Sheet1!$B:$D,3,0) -> 6773
D19: 5602 | E19: =$C$8 -> 24 | F19: 1 | H19: =VLOOKUP(D19,[2]Data2!A:D,4,0) -> #N/A | I19: =VLOOKUP(D19,[2]Data2!A:D,3,0) -> #N/A | J19: =VLOOKUP(Table4159[[#This Row],[Item'#]],[3]Sheet1!$B:$D,3,0) -> 7538
B21: SKU | C21: Sellable Set to ship | D21: Item# | E21: Total EA (Transfer to WH07) | F21: Box | G21: Case | H21: Box Uom | I21: Case Uom | J21: Inventory
B22: 6018-EA+1201-EA | C22: 24 | D22: 6018 | E22: 24 | F22: 1 | H22: =VLOOKUP(D22,[2]Data2!A:D,4,0) -> #REF! | I22: =VLOOKUP(D22,[2]Data2!A:D,3,0) -> 24 | J22: =VLOOKUP(Table5165[[#This Row],[Item'#]],[3]Sheet1!$B:$D,3,0) -> 14836
D23: 1201 | E23: 24 | F23: 1 | H23: =VLOOKUP(D23,[2]Data2!A:D,4,0) -> 24 | I23: =VLOOKUP(D23,[2]Data2!A:D,3,0) -> 144 | J23: =VLOOKUP(Table5165[[#This Row],[Item'#]],[3]Sheet1!$B:$D,3,0) -> 65392
B25: SKU | C25: Sellable Set to ship | D25: Item# | E25: Total EA (Transfer to WH07) | F25: Box | G25: Case | H25: Box Uom | I25: Case Uom | J25: Inventory
B26: 4575936-SET2+765-EA+3860-EA | C26: 36 | D26: 4575936 | E26: 72 | G26: 2 | H26: =VLOOKUP(D26,[2]Data2!A:D,4,0) -> #REF! | I26: =VLOOKUP(D26,[2]Data2!A:D,3,0) -> 36 | J26: =VLOOKUP(Table617[[#This Row],[Item'#]],[3]Sheet1!$B:$D,3,0) -> 3475
D27: 765 | E27: 36 | F27: 1.5 | H27: =VLOOKUP(D27,[2]Data2!A:D,4,0) -> 24 | I27: =VLOOKUP(D27,[2]Data2!A:D,3,0) -> 144 | J27: =VLOOKUP(Table617[[#This Row],[Item'#]],[3]Sheet1!$B:$D,3,0) -> 218604
D28: 3860 | E28: 36 | G28: 1.5 | H28: =VLOOKUP(D28,[2]Data2!A:D,4,0) -> #REF! | I28: =VLOOKUP(D28,[2]Data2!A:D,3,0) -> 24 | J28: =VLOOKUP(Table617[[#This Row],[Item'#]],[3]Sheet1!$B:$D,3,0) -> 1204
B30: SKU | C30: Sellable Set to ship | D30: Item# | E30: Total EA (Transfer to WH07) | F30: Box | G30: Case | H30: Box Uom | I30: Case Uom | J30: Inventory
B31: 4577036-SET2+4881536-EA+765-EA+3863-EA | C31: 36 | D31: 4577036 | E31: 72 | G31: 2 | H31: =VLOOKUP(D31,[2]Data2!A:D,4,0) -> #REF! | I31: =VLOOKUP(D31,[2]Data2!A:D,3,0) -> 36 | J31: =VLOOKUP(Table6176[[#This Row],[Item'#]],[3]Sheet1!$B:$D,3,0) -> 2
D32: 4881536 | E32: 36 | G32: 1 | H32: =VLOOKUP(D32,[2]Data2!A:D,4,0) -> #REF! | I32: =VLOOKUP(D32,[2]Data2!A:D,3,0) -> 36 | J32: =VLOOKUP(Table6176[[#This Row],[Item'#]],[3]Sheet1!$B:$D,3,0) -> 9
D33: 3863 | E33: 36 | F33: 1.5 | H33: =VLOOKUP(D33,[2]Data2!A:D,4,0) -> #REF! | I33: =VLOOKUP(D33,[2]Data2!A:D,3,0) -> 24 | J33: =VLOOKUP(Table6176[[#This Row],[Item'#]],[3]Sheet1!$B:$D,3,0) -> 1450
D34: 765 | E34: 36 | F34: 1.5 | H34: =VLOOKUP(D34,[2]Data2!A:D,4,0) -> 24 | I34: =VLOOKUP(D34,[2]Data2!A:D,3,0) -> 144 | J34: =VLOOKUP(Table6176[[#This Row],[Item'#]],[3]Sheet1!$B:$D,3,0) -> 218604
B36: SKU | C36: Sellable Set to ship | D36: Item# | E36: Total EA (Transfer to WH07) | F36: Box | G36: Case | H36: Box Uom | I36: Case Uom | J36: Inventory
B37: 4569945741-SET2+2520-EA | C37: 72 | D37: 4569945741 | E37: 144 | G37: 4 | H37: =VLOOKUP(D37,[2]Data2!A:D,4,0) -> #N/A | I37: =VLOOKUP(D37,[2]Data2!A:D,3,0) -> #N/A | J37: =VLOOKUP(Table61767[[#This Row],[Item'#]],[3]Sheet1!$B:$D,3,0) -> 420 | K37: On Create Inbound Order template use this SKU:
D38: 2520 | E38: 72 | G38: 1 | H38: =VLOOKUP(D38,[2]Data2!A:D,4,0) -> 24 | I38: =VLOOKUP(D38,[2]Data2!A:D,3,0) -> 72 | J38: =VLOOKUP(Table61767[[#This Row],[Item'#]],[3]Sheet1!$B:$D,3,0) -> 16383 | K38: 4576336-SET2+2520-EA
B40: SKU | C40: Sellable Set to ship | D40: Item# | E40: Total EA (Transfer to WH07) | F40: Box | G40: Case | H40: Box Uom | I40: Case Uom | J40: Inventory
B41: 60756-SET2+1224-EA | C41: 36 | D41: 60756 | E41: 72 | G41: 2 | H41: =VLOOKUP(D41,[2]Data2!A:D,4,0) -> #REF! | I41: =VLOOKUP(D41,[2]Data2!A:D,3,0) -> 36 | J41: =VLOOKUP(Table718[[#This Row],[Item'#]],[3]Sheet1!$B:$D,3,0) -> 2022
D42: 1224 | E42: 36 | F42: 1 | H42: =VLOOKUP(D42,[2]Data2!A:D,4,0) -> 24 | I42: =VLOOKUP(D42,[2]Data2!A:D,3,0) -> 144 | J42: =VLOOKUP(Table718[[#This Row],[Item'#]],[3]Sheet1!$B:$D,3,0) -> 68267
B44: SKU | C44: Sellable Set to ship | D44: Item# | E44: Total EA (Transfer to WH07) | F44: Box | G44: Case | H44: Box Uom | I44: Case Uom | J44: Inventory
B45: 49923-EA+734-SET2+2520-EA | C45: 36 | D45: 49923 | E45: 36 | G45: 1 | H45: =VLOOKUP(D45,[2]Data2!A:D,4,0) -> #REF! | I45: =VLOOKUP(D45,[2]Data2!A:D,3,0) -> 36 | J45: =VLOOKUP(Table1223[[#This Row],[Item'#]],[3]Sheet1!$B:$D,3,0) -> 168
D46: 734 | E46: 72 | G46: 2 | H46: =VLOOKUP(D46,[2]Data2!A:D,4,0) -> #REF! | I46: =VLOOKUP(D46,[2]Data2!A:D,3,0) -> 48 | J46: =VLOOKUP(Table1223[[#This Row],[Item'#]],[3]Sheet1!$B:$D,3,0) -> #N/A
D47: 2520 | E47: 36 | F47: 1.5 | H47: =VLOOKUP(D47,[2]Data2!A:D,4,0) -> 24 | I47: =VLOOKUP(D47,[2]Data2!A:D,3,0) -> 72 | J47: =VLOOKUP(Table1223[[#This Row],[Item'#]],[3]Sheet1!$B:$D,3,0) -> 16383
B49: SKU | C49: Sellable Set to ship | D49: Item# | E49: Total EA (Transfer to WH07) | F49: Box | G49: Case | H49: Box Uom | I49: Case Uom | J49: Inventory
B50: 4577036-EA+4881536-EA+765-EA+3863-EA | C50: 36 | D50: 4577036 | E50: 36 | G50: 1 | H50: =VLOOKUP(D50,[2]Data2!A:D,4,0) -> #REF! | I50: =VLOOKUP(D50,[2]Data2!A:D,3,0) -> 36 | J50: =VLOOKUP(Table1122[[#This Row],[Item'#]],[3]Sheet1!$B:$D,3,0) -> 2
D51: 4881536 | E51: 36 | G51: 1 | H51: =VLOOKUP(D51,[2]Data2!A:D,4,0) -> #REF! | I51: =VLOOKUP(D51,[2]Data2!A:D,3,0) -> 36 | J51: =VLOOKUP(Table1122[[#This Row],[Item'#]],[3]Sheet1!$B:$D,3,0) -> 9
D52: 765 | E52: 36 | F52: 1.5 | H52: =VLOOKUP(D52,[2]Data2!A:D,4,0) -> 24 | I52: =VLOOKUP(D52,[2]Data2!A:D,3,0) -> 144 | J52: =VLOOKUP(Table1122[[#This Row],[Item'#]],[3]Sheet1!$B:$D,3,0) -> 218604
D53: 3863 | E53: 36 | F53: 1.5 | H53: =VLOOKUP(D53,[2]Data2!A:D,4,0) -> #REF! | I53: =VLOOKUP(D53,[2]Data2!A:D,3,0) -> 24 | J53: =VLOOKUP(Table1122[[#This Row],[Item'#]],[3]Sheet1!$B:$D,3,0) -> 1450
B55: SKU | C55: Sellable Set to ship | D55: Item# | E55: Total EA (Transfer to WH07) | F55: Box | G55: Case | H55: Box Uom | I55: Case Uom | J55: Inventory
B56: 80169-EA+765-EA | C56: 48 | D56: 80169 | E56: 48 | G56: 1 | H56: =VLOOKUP(D56,[2]Data2!A:D,4,0) -> #REF! | I56: =VLOOKUP(D56,[2]Data2!A:D,3,0) -> 48 | J56: =VLOOKUP(Table1021[[#This Row],[Item'#]],[3]Sheet1!$B:$D,3,0) -> #N/A
D57: 765 | E57: 48 | F57: 2 | H57: =VLOOKUP(D57,[2]Data2!A:D,4,0) -> 24 | I57: =VLOOKUP(D57,[2]Data2!A:D,3,0) -> 144 | J57: =VLOOKUP(Table1021[[#This Row],[Item'#]],[3]Sheet1!$B:$D,3,0) -> 218604
B59: SKU | C59: Sellable Set to ship | D59: Item# | E59: Total EA (Transfer to WH07) | F59: Box | G59: Case | H59: Box Uom | I59: Case Uom | J59: Inventory
B60: 12627-SET2+2517-EA+3862-EA | C60: 48 | D60: 12627 | E60: 96 | G60: 2 | H60: =VLOOKUP(D60,[2]Data2!A:D,4,0) -> #REF! | I60: =VLOOKUP(D60,[2]Data2!A:D,3,0) -> 48 | J60: =VLOOKUP(Table920[[#This Row],[Item'#]],[3]Sheet1!$B:$D,3,0) -> 4903
D61: 2517 | E61: 48 | F61: 2 | H61: =VLOOKUP(D61,[2]Data2!A:D,4,0) -> 24 | I61: =VLOOKUP(D61,[2]Data2!A:D,3,0) -> 144 | J61: =VLOOKUP(Table920[[#This Row],[Item'#]],[3]Sheet1!$B:$D,3,0) -> 9
D62: 3862 | E62: 48 | G62: 2 | H62: =VLOOKUP(D62,[2]Data2!A:D,4,0) -> #REF! | I62: =VLOOKUP(D62,[2]Data2!A:D,3,0) -> 24 | J62: =VLOOKUP(Table920[[#This Row],[Item'#]],[3]Sheet1!$B:$D,3,0) -> 1152
B64: SKU | C64: Sellable Set to ship | D64: Item# | E64: Total EA (Transfer to WH07) | F64: Box | G64: Case | H64: Box Uom | I64: Case Uom | J64: Inventory
B65: 62133-EA+2520-EA | C65: 36 | D65: 62133 | E65: 36 | G65: 1 | H65: =VLOOKUP(D65,[2]Data2!A:D,4,0) -> #N/A | I65: =VLOOKUP(D65,[2]Data2!A:D,3,0) -> #N/A | J65: =VLOOKUP(Table819[[#This Row],[Item'#]],[3]Sheet1!$B:$D,3,0) -> 6
D66: 2520 | E66: 36 | F66: 1.5 | H66: =VLOOKUP(D66,[2]Data2!A:D,4,0) -> 24 | I66: =VLOOKUP(D66,[2]Data2!A:D,3,0) -> 72 | J66: =VLOOKUP(Table819[[#This Row],[Item'#]],[3]Sheet1!$B:$D,3,0) -> 16383
B68: SKU | C68: Sellable Set to ship | D68: Item# | E68: Total EA (Transfer to WH07) | F68: Box | G68: Case | H68: Box Uom | I68: Case Uom | J68: Inventory
B69: 3167-SET4+810-SET6 | C69: 24 | D69: 3167 | E69: =24*6 -> 144 | G69: 6 | H69: =VLOOKUP(D69,[2]Data2!A:D,4,0) -> #REF! | I69: =VLOOKUP(D69,[2]Data2!A:D,3,0) -> 24 | J69: =VLOOKUP(Table81424[[#This Row],[Item'#]],[3]Sheet1!$B:$D,3,0) -> 32731
D70: 810 | E70: =24*4 -> 96 | F70: 4 | H70: =VLOOKUP(D70,[2]Data2!A:D,4,0) -> 24 | I70: =VLOOKUP(D70,[2]Data2!A:D,3,0) -> 144 | J70: =VLOOKUP(Table81424[[#This Row],[Item'#]],[3]Sheet1!$B:$D,3,0) -> 55191
B72: SKU | C72: Sellable Set to ship | D72: Item# | E72: Total EA (Transfer to WH07) | F72: Box | G72: Case | H72: Box Uom | I72: Case Uom | J72: Inventory
B73: 5044-EA+744-EA+768-EA | C73: 48 | D73: 5044 | E73: 144 | G73: 3 | H73: =VLOOKUP(D73,[2]Data2!A:D,4,0) -> #REF! | I73: =VLOOKUP(D73,[2]Data2!A:D,3,0) -> 48 | J73: =VLOOKUP(Table814244[[#This Row],[Item'#]],[3]Sheet1!$B:$D,3,0) -> 5
D74: 744 | E74: 144 | G74: 1 | H74: =VLOOKUP(D74,[2]Data2!A:D,4,0) -> 24 | I74: =VLOOKUP(D74,[2]Data2!A:D,3,0) -> 144 | J74: =VLOOKUP(Table814244[[#This Row],[Item'#]],[3]Sheet1!$B:$D,3,0) -> 14098
D75: 768 | E75: 144 | G75: 2 | H75: =VLOOKUP(D75,[2]Data2!A:D,4,0) -> 12 | I75: =VLOOKUP(D75,[2]Data2!A:D,3,0) -> 72 | J75: =VLOOKUP(Table814244[[#This Row],[Item'#]],[3]Sheet1!$B:$D,3,0) -> 36125
B77: SKU | C77: Sellable Set to ship | D77: Item# | E77: Total EA (Transfer to WH07) | F77: Box | G77: Case | H77: Box Uom | I77: Case Uom | J77: Inventory
B78: 532-EA+533-EA | C78: 24 | D78: 532 | E78: =$C$2 -> 24 | F78: 1 | H78: =VLOOKUP(D78,[2]Data2!A:D,4,0) -> 24 | I78: =VLOOKUP(D78,[2]Data2!A:D,3,0) -> 72 | J78: =VLOOKUP(Table3312[[#This Row],[Item'#]],[3]Sheet1!$B:$D,3,0) -> 14369
D79: 533 | E79: =$C$2 -> 24 | F79: 1 | H79: =VLOOKUP(D79,[2]Data2!A:D,4,0) -> 24 | I79: =VLOOKUP(D79,[2]Data2!A:D,3,0) -> 72 | J79: =VLOOKUP(Table3312[[#This Row],[Item'#]],[3]Sheet1!$B:$D,3,0) -> 25958

Sheet AWD
A1: SKU | B1: ASIN | C1: FNSKU | D1: Item # | E1: Total EA (Transfer to WH06) | F1: Sellable Unit/Set/box to ship | G1: Box to pull | H1: Case to pull | I1: Sets per Box/Case | J1: Label | K1: Packing Instructions | L1: AWD Special | M1: Supplies | N1: UoM | O1: BOX | P1: CASE | Q1: Recommended Replenishment Qty | R1: Current WH Inventory
A2: 4147-EACH | B2: B07Q8SQSQF | C2: X003SBSJBL | D2: =VLOOKUP(Table13[[#This Row],[SKU]],Data1!A:B,2,0) -> 4147 | E2: =Table13[[#This Row],[UoM]]*Table13[[#This Row],[Recommended Replenishment Qty]] -> 156 | F2: =Table13[[#This Row],[Total EA (Transfer to WH06)]]/Table13[[#This Row],[UoM]] -> 156 | H2: =Table13[[#This Row],[Total EA (Transfer to WH06)]]/Table13[[#This Row],[CASE]] -> 13 | I2: =Table13[[#This Row],[Sellable Unit/Set/box to ship]]/Table13[[#This Row],[Case to pull]] -> 12 | J2: =IF(ISNUMBER(SEARCH("FNSKU",K2)),"Labeling","") -> Labeling | K2: =VLOOKUP(Table13[[#This Row],[SKU]],Instruction!A:F,6,0) -> • Use FNSKU to label each item (cover barcode). Apply outer box/case label accordingly to match item# (Cover all existing barcodes on the box/case) | L2: =VLOOKUP(Table13[[#This Row],[SKU]],Instruction!A:G,7,0) -> 0 | M2: =VLOOKUP(Table13[[#This Row],[ASIN]],'[4]2024'!$A:$AB,28,0) -> No Supplies | N2: =VLOOKUP(Table13[[#This Row],[SKU]],Data1!A:C,3,0) -> 1 | O2: =VLOOKUP(Table13[[#This Row],[Item '#]],Data2!A:D,4,0) -> 0 | P2: =VLOOKUP(Table13[[#This Row],[Item '#]],Data2!A:D,3,0) -> 12 | Q2: 156 | R2: =VLOOKUP(Table13[[#This Row],[Item '#]],[3]Sheet1!$B:$D,3,0) -> 5414
A3: 2306-EACH-1 | B3: B008ZHNN68 | C3: B008ZHNN68 | D3: =VLOOKUP(Table13[[#This Row],[SKU]],Data1!A:B,2,0) -> 2306 | E3: =Table13[[#This Row],[UoM]]*Table13[[#This Row],[Recommended Replenishment Qty]] -> 1440 | F3: =Table13[[#This Row],[Total EA (Transfer to WH06)]]/Table13[[#This Row],[UoM]] -> 1440 | H3: =Table13[[#This Row],[Total EA (Transfer to WH06)]]/Table13[[#This Row],[CASE]] -> 10 | I3: =Table13[[#This Row],[Sellable Unit/Set/box to ship]]/Table13[[#This Row],[Case to pull]] -> 144 | J3: =IF(ISNUMBER(SEARCH("FNSKU",K3)),"Labeling","") | K3: =VLOOKUP(Table13[[#This Row],[SKU]],Instruction!A:F,6,0) -> Cover inner box barcode. Apply outer case label accordingly to match item# (Cover barcodes on the case) | L3: =VLOOKUP(Table13[[#This Row],[SKU]],Instruction!A:G,7,0) -> 0 | M3: =VLOOKUP(Table13[[#This Row],[ASIN]],'[4]2024'!$A:$AB,28,0) -> No Supplies | N3: =VLOOKUP(Table13[[#This Row],[SKU]],Data1!A:C,3,0) -> 1 | O3: =VLOOKUP(Table13[[#This Row],[Item '#]],Data2!A:D,4,0) -> 24 | P3: =VLOOKUP(Table13[[#This Row],[Item '#]],Data2!A:D,3,0) -> 144 | Q3: 1440 | R3: =VLOOKUP(Table13[[#This Row],[Item '#]],[3]Sheet1!$B:$D,3,0) -> 10791
A4: 6810-EACH | B4: B09DK3BKGB | C4: B09DK3BKGB | D4: =VLOOKUP(Table13[[#This Row],[SKU]],Data1!A:B,2,0) -> 6810 | E4: =Table13[[#This Row],[UoM]]*Table13[[#This Row],[Recommended Replenishment Qty]] -> 144 | F4: =Table13[[#This Row],[Total EA (Transfer to WH06)]]/Table13[[#This Row],[UoM]] -> 144 | H4: =Table13[[#This Row],[Total EA (Transfer to WH06)]]/Table13[[#This Row],[CASE]] -> 1 | I4: =Table13[[#This Row],[Sellable Unit/Set/box to ship]]/Table13[[#This Row],[Case to pull]] -> 144 | J4: =IF(ISNUMBER(SEARCH("FNSKU",K4)),"Labeling","") | K4: =VLOOKUP(Table13[[#This Row],[SKU]],Instruction!A:F,6,0) -> Apply outer box/case label accordingly to match item# (Cover all existing barcodes on the box/case) | L4: =VLOOKUP(Table13[[#This Row],[SKU]],Instruction!A:G,7,0) -> 0 | M4: =VLOOKUP(Table13[[#This Row],[ASIN]],'[4]2024'!$A:$AB,28,0) -> No Supplies | N4: =VLOOKUP(Table13[[#This Row],[SKU]],Data1!A:C,3,0) -> 1 | O4: =VLOOKUP(Table13[[#This Row],[Item '#]],Data2!A:D,4,0) -> 24 | P4: =VLOOKUP(Table13[[#This Row],[Item '#]],Data2!A:D,3,0) -> 144 | Q4: 144 | R4: =VLOOKUP(Table13[[#This Row],[Item '#]],[3]Sheet1!$B:$D,3,0) -> 21276
A5: 5027-EACH-1 | B5: B00KO8DHVC | C5: X004HP06TF | D5: =VLOOKUP(Table13[[#This Row],[SKU]],Data1!A:B,2,0) -> 5027 | E5: =Table13[[#This Row],[UoM]]*Table13[[#This Row],[Recommended Replenishment Qty]] -> 480 | F5: =Table13[[#This Row],[Total EA (Transfer to WH06)]]/Table13[[#This Row],[UoM]] -> 480 | H5: =Table13[[#This Row],[Total EA (Transfer to WH06)]]/Table13[[#This Row],[CASE]] -> 10 | I5: =Table13[[#This Row],[Sellable Unit/Set/box to ship]]/Table13[[#This Row],[Case to pull]] -> 48 | J5: =IF(ISNUMBER(SEARCH("FNSKU",K5)),"Labeling","") -> Labeling | K5: =VLOOKUP(Table13[[#This Row],[SKU]],Instruction!A:F,6,0) -> • Use FNSKU to label each item (cover barcode). Apply outer case label accordingly to match item# (Cover all existing barcodes on the case) | L5: =VLOOKUP(Table13[[#This Row],[SKU]],Instruction!A:G,7,0) -> 0 | M5: =VLOOKUP(Table13[[#This Row],[ASIN]],'[4]2024'!$A:$AB,28,0) -> No Supplies | N5: =VLOOKUP(Table13[[#This Row],[SKU]],Data1!A:C,3,0) -> 1 | O5: =VLOOKUP(Table13[[#This Row],[Item '#]],Data2!A:D,4,0) -> 0 | P5: =VLOOKUP(Table13[[#This Row],[Item '#]],Data2!A:D,3,0) -> 48 | Q5: 480 | R5: =VLOOKUP(Table13[[#This Row],[Item '#]],[3]Sheet1!$B:$D,3,0) -> 4137
A6: 2205-EACH | B6: B003BNZVHK | C6: B003BNZVHK | D6: =VLOOKUP(Table13[[#This Row],[SKU]],Data1!A:B,2,0) -> 2205 | E6: =Table13[[#This Row],[UoM]]*Table13[[#This Row],[Recommended Replenishment Qty]] -> 216 | F6: =Table13[[#This Row],[Total EA (Transfer to WH06)]]/Table13[[#This Row],[UoM]] -> 216 | H6: =Table13[[#This Row],[Total EA (Transfer to WH06)]]/Table13[[#This Row],[CASE]] -> 3 | I6: =Table13[[#This Row],[Sellable Unit/Set/box to ship]]/Table13[[#This Row],[Case to pull]] -> 72 | J6: =IF(ISNUMBER(SEARCH("FNSKU",K6)),"Labeling","") | K6: =VLOOKUP(Table13[[#This Row],[SKU]],Instruction!A:F,6,0) -> Apply outer box/case label accordingly to match item# (Cover all existing barcodes on the box/case) | L6: =VLOOKUP(Table13[[#This Row],[SKU]],Instruction!A:G,7,0) -> 0 | M6: =VLOOKUP(Table13[[#This Row],[ASIN]],'[4]2024'!$A:$AB,28,0) -> No Supplies | N6: =VLOOKUP(Table13[[#This Row],[SKU]],Data1!A:C,3,0) -> 1 | O6: =VLOOKUP(Table13[[#This Row],[Item '#]],Data2!A:D,4,0) -> 24 | P6: =VLOOKUP(Table13[[#This Row],[Item '#]],Data2!A:D,3,0) -> 72 | Q6: 216 | R6: =VLOOKUP(Table13[[#This Row],[Item '#]],[3]Sheet1!$B:$D,3,0) -> 15609
A7: 4105-EACH | B7: B07Q712K7L | C7: X003SC97JN | D7: =VLOOKUP(Table13[[#This Row],[SKU]],Data1!A:B,2,0) -> 4105 | E7: =Table13[[#This Row],[UoM]]*Table13[[#This Row],[Recommended Replenishment Qty]] -> 396 | F7: =Table13[[#This Row],[Total EA (Transfer to WH06)]]/Table13[[#This Row],[UoM]] -> 396 | H7: =Table13[[#This Row],[Total EA (Transfer to WH06)]]/Table13[[#This Row],[CASE]] -> 33 | I7: =Table13[[#This Row],[Sellable Unit/Set/box to ship]]/Table13[[#This Row],[Case to pull]] -> 12 | J7: =IF(ISNUMBER(SEARCH("FNSKU",K7)),"Labeling","") -> Labeling | K7: =VLOOKUP(Table13[[#This Row],[SKU]],Instruction!A:F,6,0) -> • Use FNSKU to label each item (cover barcode). Apply outer box/case label accordingly to match item# (Cover all existing barcodes on the box/case) | L7: =VLOOKUP(Table13[[#This Row],[SKU]],Instruction!A:G,7,0) -> 0 | M7: =VLOOKUP(Table13[[#This Row],[ASIN]],'[4]2024'!$A:$AB,28,0) -> No Supplies | N7: =VLOOKUP(Table13[[#This Row],[SKU]],Data1!A:C,3,0) -> 1 | O7: =VLOOKUP(Table13[[#This Row],[Item '#]],Data2!A:D,4,0) -> 0 | P7: =VLOOKUP(Table13[[#This Row],[Item '#]],Data2!A:D,3,0) -> 12 | Q7: 396 | R7: =VLOOKUP(Table13[[#This Row],[Item '#]],[3]Sheet1!$B:$D,3,0) -> 5407
A8: 2007-EACH | B8: B003BSF7ZG | C8: B003BSF7ZG | D8: =VLOOKUP(Table13[[#This Row],[SKU]],Data1!A:B,2,0) -> 2007 | E8: =Table13[[#This Row],[UoM]]*Table13[[#This Row],[Recommended Replenishment Qty]] -> 72 | F8: =Table13[[#This Row],[Total EA (Transfer to WH06)]]/Table13[[#This Row],[UoM]] -> 72 | G8: =Table13[[#This Row],[Total EA (Transfer to WH06)]]/Table13[[#This Row],[BOX]] -> 3 | I8: =Table13[[#This Row],[Sellable Unit/Set/box to ship]]/Table13[[#This Row],[Box to pull]] -> 24 | J8: =IF(ISNUMBER(SEARCH("FNSKU",K8)),"Labeling","") | K8: =VLOOKUP(Table13[[#This Row],[SKU]],Instruction!A:F,6,0) -> Apply outer box/case label accordingly to match item# (Cover all existing barcodes on the box/case) | L8: =VLOOKUP(Table13[[#This Row],[SKU]],Instruction!A:G,7,0) -> 0 | M8: =VLOOKUP(Table13[[#This Row],[ASIN]],'[4]2024'!$A:$AB,28,0) -> No Supplies | N8: =VLOOKUP(Table13[[#This Row],[SKU]],Data1!A:C,3,0) -> 1 | O8: =VLOOKUP(Table13[[#This Row],[Item '#]],Data2!A:D,4,0) -> 24 | P8: =VLOOKUP(Table13[[#This Row],[Item '#]],Data2!A:D,3,0) -> 144 | Q8: 72 | R8: =VLOOKUP(Table13[[#This Row],[Item '#]],[3]Sheet1!$B:$D,3,0) -> 6342
A9: 306-EACH | B9: B003BMX6SC | C9: B003BMX6SC | D9: =VLOOKUP(Table13[[#This Row],[SKU]],Data1!A:B,2,0) -> 306 | E9: =Table13[[#This Row],[UoM]]*Table13[[#This Row],[Recommended Replenishment Qty]] -> 720 | F9: =Table13[[#This Row],[Total EA (Transfer to WH06)]]/Table13[[#This Row],[UoM]] -> 720 | H9: =Table13[[#This Row],[Total EA (Transfer to WH06)]]/Table13[[#This Row],[CASE]] -> 5 | I9: =Table13[[#This Row],[Sellable Unit/Set/box to ship]]/Table13[[#This Row],[Case to pull]] -> 144 | J9: =IF(ISNUMBER(SEARCH("FNSKU",K9)),"Labeling","") | K9: =VLOOKUP(Table13[[#This Row],[SKU]],Instruction!A:F,6,0) -> Apply outer box/case label accordingly to match item# (Cover all existing barcodes on box and case) | L9: =VLOOKUP(Table13[[#This Row],[SKU]],Instruction!A:G,7,0) -> 0 | M9: =VLOOKUP(Table13[[#This Row],[ASIN]],'[4]2024'!$A:$AB,28,0) -> No Supplies | N9: =VLOOKUP(Table13[[#This Row],[SKU]],Data1!A:C,3,0) -> 1 | O9: =VLOOKUP(Table13[[#This Row],[Item '#]],Data2!A:D,4,0) -> 24 | P9: =VLOOKUP(Table13[[#This Row],[Item '#]],Data2!A:D,3,0) -> 144 | Q9: 720 | R9: =VLOOKUP(Table13[[#This Row],[Item '#]],[3]Sheet1!$B:$D,3,0) -> 30269
A10: 713-EACH | B10: B07S6D27NC | C10: X003SFVDQ5 | D10: =VLOOKUP(Table13[[#This Row],[SKU]],Data1!A:B,2,0) -> 713 | E10: =Table13[[#This Row],[UoM]]*Table13[[#This Row],[Recommended Replenishment Qty]] -> 72 | F10: =Table13[[#This Row],[Total EA (Transfer to WH06)]]/Table13[[#This Row],[UoM]] -> 72 | G10: =Table13[[#This Row],[Total EA (Transfer to WH06)]]/Table13[[#This Row],[BOX]] -> 3 | I10: =Table13[[#This Row],[Sellable Unit/Set/box to ship]]/Table13[[#This Row],[Box to pull]] -> 24 | J10: =IF(ISNUMBER(SEARCH("FNSKU",K10)),"Labeling","") -> Labeling | K10: =VLOOKUP(Table13[[#This Row],[SKU]],Instruction!A:F,6,0) -> • Use FNSKU to label each item (cover barcode). Apply outer case label accordingly to match item# (Cover all existing barcodes on the case) | L10: =VLOOKUP(Table13[[#This Row],[SKU]],Instruction!A:G,7,0) -> 0 | M10: =VLOOKUP(Table13[[#This Row],[ASIN]],'[4]2024'!$A:$AB,28,0) -> No Supplies | N10: =VLOOKUP(Table13[[#This Row],[SKU]],Data1!A:C,3,0) -> 1 | O10: =VLOOKUP(Table13[[#This Row],[Item '#]],Data2!A:D,4,0) -> 24 | P10: =VLOOKUP(Table13[[#This Row],[Item '#]],Data2!A:D,3,0) -> 144 | Q10: 72 | R10: =VLOOKUP(Table13[[#This Row],[Item '#]],[3]Sheet1!$B:$D,3,0) -> 20946
A11: 5012-EACH | B11: B002NLIS7G | C11: B002NLIS7G | D11: =VLOOKUP(Table13[[#This Row],[SKU]],Data1!A:B,2,0) -> 5012 | E11: =Table13[[#This Row],[UoM]]*Table13[[#This Row],[Recommended Replenishment Qty]] -> 250 | F11: =Table13[[#This Row],[Total EA (Transfer to WH06)]]/Table13[[#This Row],[UoM]] -> 250 | H11: =Table13[[#This Row],[Total EA (Transfer to WH06)]]/Table13[[#This Row],[CASE]] -> 5 | I11: =Table13[[#This Row],[Sellable Unit/Set/box to ship]]/Table13[[#This Row],[Case to pull]] -> 50 | J11: =IF(ISNUMBER(SEARCH("FNSKU",K11)),"Labeling","") | K11: =VLOOKUP(Table13[[#This Row],[SKU]],Instruction!A:F,6,0) -> Apply outer box/case label accordingly to match item# (Cover all existing barcodes on the box/case) | L11: =VLOOKUP(Table13[[#This Row],[SKU]],Instruction!A:G,7,0) -> 0 | M11: =VLOOKUP(Table13[[#This Row],[ASIN]],'[4]2024'!$A:$AB,28,0) -> No Supplies | N11: =VLOOKUP(Table13[[#This Row],[SKU]],Data1!A:C,3,0) -> 1 | O11: =VLOOKUP(Table13[[#This Row],[Item '#]],Data2!A:D,4,0) -> 0 | P11: =VLOOKUP(Table13[[#This Row],[Item '#]],Data2!A:D,3,0) -> 50 | Q11: 250 | R11: =VLOOKUP(Table13[[#This Row],[Item '#]],[3]Sheet1!$B:$D,3,0) -> 12032
A12: 3107-EACH | B12: B07S4GZW7L | C12: X003BBR0T5 | D12: =VLOOKUP(Table13[[#This Row],[SKU]],Data1!A:B,2,0) -> 3107 | E12: =Table13[[#This Row],[UoM]]*Table13[[#This Row],[Recommended Replenishment Qty]] -> 1008 | F12: =Table13[[#This Row],[Total EA (Transfer to WH06)]]/Table13[[#This Row],[UoM]] -> 1008 | H12: =Table13[[#This Row],[Total EA (Transfer to WH06)]]/Table13[[#This Row],[CASE]] -> 7 | I12: =Table13[[#This Row],[Sellable Unit/Set/box to ship]]/Table13[[#This Row],[Case to pull]] -> 144 | J12: =IF(ISNUMBER(SEARCH("FNSKU",K12)),"Labeling","") -> Labeling | K12: =VLOOKUP(Table13[[#This Row],[SKU]],Instruction!A:F,6,0) -> • Use FNSKU to label each item (cover barcode). Apply outer box/case label accordingly to match item# (Cover all existing barcodes on the box/case) | L12: =VLOOKUP(Table13[[#This Row],[SKU]],Instruction!A:G,7,0) -> 0 | M12: =VLOOKUP(Table13[[#This Row],[ASIN]],'[4]2024'!$A:$AB,28,0) -> No Supplies | N12: =VLOOKUP(Table13[[#This Row],[SKU]],Data1!A:C,3,0) -> 1 | O12: =VLOOKUP(Table13[[#This Row],[Item '#]],Data2!A:D,4,0) -> 24 | P12: =VLOOKUP(Table13[[#This Row],[Item '#]],Data2!A:D,3,0) -> 144 | Q12: 1008 | R12: =VLOOKUP(Table13[[#This Row],[Item '#]],[3]Sheet1!$B:$D,3,0) -> 27595
A13: 716-EACH | B13: B003BLQH7A | C13: B003BLQH7A | D13: =VLOOKUP(Table13[[#This Row],[SKU]],Data1!A:B,2,0) -> 716 | E13: =Table13[[#This Row],[UoM]]*Table13[[#This Row],[Recommended Replenishment Qty]] -> 288 | F13: =Table13[[#This Row],[Total EA (Transfer to WH06)]]/Table13[[#This Row],[UoM]] -> 288 | H13: =Table13[[#This Row],[Total EA (Transfer to WH06)]]/Table13[[#This Row],[CASE]] -> 2 | I13: =Table13[[#This Row],[Sellable Unit/Set/box to ship]]/Table13[[#This Row],[Case to pull]] -> 144 | J13: =IF(ISNUMBER(SEARCH("FNSKU",K13)),"Labeling","") -> Labeling | K13: =VLOOKUP(Table13[[#This Row],[SKU]],Instruction!A:F,6,0) -> • Use FNSKU to label each item (cover barcode). Apply outer box/case label accordingly to match item# (Cover all existing barcodes on the box/case) | L13: =VLOOKUP(Table13[[#This Row],[SKU]],Instruction!A:G,7,0) -> 0 | M13: =VLOOKUP(Table13[[#This Row],[ASIN]],'[4]2024'!$A:$AB,28,0) -> No Supplies | N13: =VLOOKUP(Table13[[#This Row],[SKU]],Data1!A:C,3,0) -> 1 | O13: =VLOOKUP(Table13[[#This Row],[Item '#]],Data2!A:D,4,0) -> 24 | P13: =VLOOKUP(Table13[[#This Row],[Item '#]],Data2!A:D,3,0) -> 144 | Q13: 288 | R13: =VLOOKUP(Table13[[#This Row],[Item '#]],[3]Sheet1!$B:$D,3,0) -> 57945
A14: 4126-EACH | B14: B07Q4RD2W3 | C14: X003SC1YAX | D14: =VLOOKUP(Table13[[#This Row],[SKU]],Data1!A:B,2,0) -> 4126 | E14: =Table13[[#This Row],[UoM]]*Table13[[#This Row],[Recommended Replenishment Qty]] -> 372 | F14: =Table13[[#This Row],[Total EA (Transfer to WH06)]]/Table13[[#This Row],[UoM]] -> 372 | H14: =Table13[[#This Row],[Total EA (Transfer to WH06)]]/Table13[[#This Row],[CASE]] -> 31 | I14: =Table13[[#This Row],[Sellable Unit/Set/box to ship]]/Table13[[#This Row],[Case to pull]] -> 12 | J14: =IF(ISNUMBER(SEARCH("FNSKU",K14)),"Labeling","") -> Labeling | K14: =VLOOKUP(Table13[[#This Row],[SKU]],Instruction!A:F,6,0) -> • Use FNSKU to label each item (cover barcode). Apply outer box/case label accordingly to match item# (Cover all existing barcodes on the box/case) | L14: =VLOOKUP(Table13[[#This Row],[SKU]],Instruction!A:G,7,0) -> 0 | M14: =VLOOKUP(Table13[[#This Row],[ASIN]],'[4]2024'!$A:$AB,28,0) -> No Supplies | N14: =VLOOKUP(Table13[[#This Row],[SKU]],Data1!A:C,3,0) -> 1 | O14: =VLOOKUP(Table13[[#This Row],[Item '#]],Data2!A:D,4,0) -> 0 | P14: =VLOOKUP(Table13[[#This Row],[Item '#]],Data2!A:D,3,0) -> 12 | Q14: 372 | R14: =VLOOKUP(Table13[[#This Row],[Item '#]],[3]Sheet1!$B:$D,3,0) -> 10580
A15: 4140-EACH | B15: B07Q84V32B | C15: X003Y7CZSH | D15: =VLOOKUP(Table13[[#This Row],[SKU]],Data1!A:B,2,0) -> 4140 | E15: =Table13[[#This Row],[UoM]]*Table13[[#This Row],[Recommended Replenishment Qty]] -> 96 | F15: =Table13[[#This Row],[Total EA (Transfer to WH06)]]/Table13[[#This Row],[UoM]] -> 96 | H15: =Table13[[#This Row],[Total EA (Transfer to WH06)]]/Table13[[#This Row],[CASE]] -> 8 | I15: =Table13[[#This Row],[Sellable Unit/Set/box to ship]]/Table13[[#This Row],[Case to pull]] -> 12 | J15: =IF(ISNUMBER(SEARCH("FNSKU",K15)),"Labeling","") -> Labeling | K15: =VLOOKUP(Table13[[#This Row],[SKU]],Instruction!A:F,6,0) -> • Use FNSKU to label each item (cover barcode). Apply outer box/case label accordingly to match item# (Cover all existing barcodes on the box/case) | L15: =VLOOKUP(Table13[[#This Row],[SKU]],Instruction!A:G,7,0) -> 0 | M15: =VLOOKUP(Table13[[#This Row],[ASIN]],'[4]2024'!$A:$AB,28,0) -> No Supplies | N15: =VLOOKUP(Table13[[#This Row],[SKU]],Data1!A:C,3,0) -> 1 | O15: =VLOOKUP(Table13[[#This Row],[Item '#]],Data2!A:D,4,0) -> 0 | P15: =VLOOKUP(Table13[[#This Row],[Item '#]],Data2!A:D,3,0) -> 12 | Q15: 96 | R15: =VLOOKUP(Table13[[#This Row],[Item '#]],[3]Sheet1!$B:$D,3,0) -> 1130
A16: 5076-EACH | B16: B015T84GY8 | C16: B015T84GY8 | D16: =VLOOKUP(Table13[[#This Row],[SKU]],Data1!A:B,2,0) -> 5076 | E16: =Table13[[#This Row],[UoM]]*Table13[[#This Row],[Recommended Replenishment Qty]] -> 144 | F16: =Table13[[#This Row],[Total EA (Transfer to WH06)]]/Table13[[#This Row],[UoM]] -> 144 | H16: =Table13[[#This Row],[Total EA (Transfer to WH06)]]/Table13[[#This Row],[CASE]] -> 2 | I16: =Table13[[#This Row],[Sellable Unit/Set/box to ship]]/Table13[[#This Row],[Case to pull]] -> 72 | J16: =IF(ISNUMBER(SEARCH("FNSKU",K16)),"Labeling","") | K16: =VLOOKUP(Table13[[#This Row],[SKU]],Instruction!A:F,6,0) -> Apply outer box/case label accordingly to match item# (Cover all existing barcodes on the box/case) | L16: =VLOOKUP(Table13[[#This Row],[SKU]],Instruction!A:G,7,0) -> 0 | M16: =VLOOKUP(Table13[[#This Row],[ASIN]],'[4]2024'!$A:$AB,28,0) -> No Supplies | N16: =VLOOKUP(Table13[[#This Row],[SKU]],Data1!A:C,3,0) -> 1 | O16: =VLOOKUP(Table13[[#This Row],[Item '#]],Data2!A:D,4,0) -> 24 | P16: =VLOOKUP(Table13[[#This Row],[Item '#]],Data2!A:D,3,0) -> 72 | Q16: 144 | R16: =VLOOKUP(Table13[[#This Row],[Item '#]],[3]Sheet1!$B:$D,3,0) -> 58280
A17: 2232-EACH | B17: B00HZ0A98G | C17: X0044RLTCJ | D17: =VLOOKUP(Table13[[#This Row],[SKU]],Data1!A:B,2,0) -> 2232 | E17: =Table13[[#This Row],[UoM]]*Table13[[#This Row],[Recommended Replenishment Qty]] -> 144 | F17: =Table13[[#This Row],[Total EA (Transfer to WH06)]]/Table13[[#This Row],[UoM]] -> 144 | H17: =Table13[[#This Row],[Total EA (Transfer to WH06)]]/Table13[[#This Row],[CASE]] -> 2 | I17: =Table13[[#This Row],[Sellable Unit/Set/box to ship]]/Table13[[#This Row],[Case to pull]] -> 72 | J17: =IF(ISNUMBER(SEARCH("FNSKU",K17)),"Labeling","") -> Labeling | K17: =VLOOKUP(Table13[[#This Row],[SKU]],Instruction!A:F,6,0) -> • Use FNSKU to label each item (cover barcode). Apply outer case label accordingly to match item# (Cover all existing barcodes on the case) | L17: =VLOOKUP(Table13[[#This Row],[SKU]],Instruction!A:G,7,0) -> 0 | M17: =VLOOKUP(Table13[[#This Row],[ASIN]],'[4]2024'!$A:$AB,28,0) -> No Supplies | N17: =VLOOKUP(Table13[[#This Row],[SKU]],Data1!A:C,3,0) -> 1 | O17: =VLOOKUP(Table13[[#This Row],[Item '#]],Data2!A:D,4,0) -> 24 | P17: =VLOOKUP(Table13[[#This Row],[Item '#]],Data2!A:D,3,0) -> 72 | Q17: 144 | R17: =VLOOKUP(Table13[[#This Row],[Item '#]],[3]Sheet1!$B:$D,3,0) -> 18189
A18: 3142-EACH | B18: B07Q713CKC | C18: X0042TT2C3 | D18: =VLOOKUP(Table13[[#This Row],[SKU]],Data1!A:B,2,0) -> 3142 | E18: =Table13[[#This Row],[UoM]]*Table13[[#This Row],[Recommended Replenishment Qty]] -> 84 | F18: =Table13[[#This Row],[Total EA (Transfer to WH06)]]/Table13[[#This Row],[UoM]] -> 84 | H18: =Table13[[#This Row],[Total EA (Transfer to WH06)]]/Table13[[#This Row],[CASE]] -> 7 | I18: =Table13[[#This Row],[Sellable Unit/Set/box to ship]]/Table13[[#This Row],[Case to pull]] -> 12 | J18: =IF(ISNUMBER(SEARCH("FNSKU",K18)),"Labeling","") -> Labeling | K18: =VLOOKUP(Table13[[#This Row],[SKU]],Instruction!A:F,6,0) -> • Use FNSKU to label each item (cover barcode). Apply outer box/case label accordingly to match item# (Cover all existing barcodes on the box/case) | L18: =VLOOKUP(Table13[[#This Row],[SKU]],Instruction!A:G,7,0) -> 0 | M18: =VLOOKUP(Table13[[#This Row],[ASIN]],'[4]2024'!$A:$AB,28,0) -> No Supplies | N18: =VLOOKUP(Table13[[#This Row],[SKU]],Data1!A:C,3,0) -> 1 | O18: =VLOOKUP(Table13[[#This Row],[Item '#]],Data2!A:D,4,0) -> 0 | P18: =VLOOKUP(Table13[[#This Row],[Item '#]],Data2!A:D,3,0) -> 12 | Q18: 84 | R18: =VLOOKUP(Table13[[#This Row],[Item '#]],[3]Sheet1!$B:$D,3,0) -> 22860
A19: 2209-EACH | B19: B07RQQ2SFV | C19: X0040DP1QH | D19: =VLOOKUP(Table13[[#This Row],[SKU]],Data1!A:B,2,0) -> 2209 | E19: =Table13[[#This Row],[UoM]]*Table13[[#This Row],[Recommended Replenishment Qty]] -> 144 | F19: =Table13[[#This Row],[Total EA (Transfer to WH06)]]/Table13[[#This Row],[UoM]] -> 144 | H19: =Table13[[#This Row],[Total EA (Transfer to WH06)]]/Table13[[#This Row],[CASE]] -> 2 | I19: =Table13[[#This Row],[Sellable Unit/Set/box to ship]]/Table13[[#This Row],[Case to pull]] -> 72 | J19: =IF(ISNUMBER(SEARCH("FNSKU",K19)),"Labeling","") -> Labeling | K19: =VLOOKUP(Table13[[#This Row],[SKU]],Instruction!A:F,6,0) -> • Use FNSKU to label each item (cover barcode). Apply outer case label accordingly to match item# (Cover all existing barcodes on the case) | L19: =VLOOKUP(Table13[[#This Row],[SKU]],Instruction!A:G,7,0) -> 0 | M19: =VLOOKUP(Table13[[#This Row],[ASIN]],'[4]2024'!$A:$AB,28,0) -> No Supplies | N19: =VLOOKUP(Table13[[#This Row],[SKU]],Data1!A:C,3,0) -> 1 | O19: =VLOOKUP(Table13[[#This Row],[Item '#]],Data2!A:D,4,0) -> 24 | P19: =VLOOKUP(Table13[[#This Row],[Item '#]],Data2!A:D,3,0) -> 72 | Q19: 144 | R19: =VLOOKUP(Table13[[#This Row],[Item '#]],[3]Sheet1!$B:$D,3,0) -> 24264
A20: 1286-EACH | B20: B07HY4Z2YL | C20: B07HY4Z2YL | D20: =VLOOKUP(Table13[[#This Row],[SKU]],Data1!A:B,2,0) -> 1286 | E20: =Table13[[#This Row],[UoM]]*Table13[[#This Row],[Recommended Replenishment Qty]] -> 120 | F20: =Table13[[#This Row],[Total EA (Transfer to WH06)]]/Table13[[#This Row],[UoM]] -> 120 | G20: =Table13[[#This Row],[Total EA (Transfer to WH06)]]/Table13[[#This Row],[BOX]] -> 5 | I20: =Table13[[#This Row],[Sellable Unit/Set/box to ship]]/Table13[[#This Row],[Box to pull]] -> 24 | J20: =IF(ISNUMBER(SEARCH("FNSKU",K20)),"Labeling","") | K20: =VLOOKUP(Table13[[#This Row],[SKU]],Instruction!A:F,6,0) -> Apply outer box/case label accordingly to match item# (Cover all existing barcodes on the box/case) | L20: =VLOOKUP(Table13[[#This Row],[SKU]],Instruction!A:G,7,0) -> 0 | M20: =VLOOKUP(Table13[[#This Row],[ASIN]],'[4]2024'!$A:$AB,28,0) -> No Supplies | N20: =VLOOKUP(Table13[[#This Row],[SKU]],Data1!A:C,3,0) -> 1 | O20: =VLOOKUP(Table13[[#This Row],[Item '#]],Data2!A:D,4,0) -> 24 | P20: =VLOOKUP(Table13[[#This Row],[Item '#]],Data2!A:D,3,0) -> 144 | Q20: 120 | R20: =VLOOKUP(Table13[[#This Row],[Item '#]],[3]Sheet1!$B:$D,3,0) -> 9435
A21: 535-EACH | B21: B003BOUX9A | C21: B003BOUX9A | D21: =VLOOKUP(Table13[[#This Row],[SKU]],Data1!A:B,2,0) -> 535 | E21: =Table13[[#This Row],[UoM]]*Table13[[#This Row],[Recommended Replenishment Qty]] -> 144 | F21: =Table13[[#This Row],[Total EA (Transfer to WH06)]]/Table13[[#This Row],[UoM]] -> 144 | H21: =Table13[[#This Row],[Total EA (Transfer to WH06)]]/Table13[[#This Row],[CASE]] -> 2 | I21: =Table13[[#This Row],[Sellable Unit/Set/box to ship]]/Table13[[#This Row],[Case to pull]] -> 72 | J21: =IF(ISNUMBER(SEARCH("FNSKU",K21)),"Labeling","") | K21: =VLOOKUP(Table13[[#This Row],[SKU]],Instruction!A:F,6,0) -> Apply outer case label accordingly to match item# (Cover all existing barcodes on the case) | L21: =VLOOKUP(Table13[[#This Row],[SKU]],Instruction!A:G,7,0) -> 0 | M21: =VLOOKUP(Table13[[#This Row],[ASIN]],'[4]2024'!$A:$AB,28,0) -> No Supplies | N21: =VLOOKUP(Table13[[#This Row],[SKU]],Data1!A:C,3,0) -> 1 | O21: =VLOOKUP(Table13[[#This Row],[Item '#]],Data2!A:D,4,0) -> 24 | P21: =VLOOKUP(Table13[[#This Row],[Item '#]],Data2!A:D,3,0) -> 72 | Q21: 144 | R21: =VLOOKUP(Table13[[#This Row],[Item '#]],[3]Sheet1!$B:$D,3,0) -> 3669
A22: 2024-EACH | B22: B003BS9A54 | C22: B003BS9A54 | D22: =VLOOKUP(Table13[[#This Row],[SKU]],Data1!A:B,2,0) -> 2024 | E22: =Table13[[#This Row],[UoM]]*Table13[[#This Row],[Recommended Replenishment Qty]] -> 96 | F22: =Table13[[#This Row],[Total EA (Transfer to WH06)]]/Table13[[#This Row],[UoM]] -> 96 | G22: =Table13[[#This Row],[Total EA (Transfer to WH06)]]/Table13[[#This Row],[BOX]] -> 4 | I22: =Table13[[#This Row],[Sellable Unit/Set/box to ship]]/Table13[[#This Row],[Box to pull]] -> 24 | J22: =IF(ISNUMBER(SEARCH("FNSKU",K22)),"Labeling","") | K22: =VLOOKUP(Table13[[#This Row],[SKU]],Instruction!A:F,6,0) -> Apply outer box/case label accordingly to match item# (Cover all existing barcodes on the box/case) | L22: =VLOOKUP(Table13[[#This Row],[SKU]],Instruction!A:G,7,0) -> 0 | M22: =VLOOKUP(Table13[[#This Row],[ASIN]],'[4]2024'!$A:$AB,28,0) -> No Supplies | N22: =VLOOKUP(Table13[[#This Row],[SKU]],Data1!A:C,3,0) -> 1 | O22: =VLOOKUP(Table13[[#This Row],[Item '#]],Data2!A:D,4,0) -> 24 | P22: =VLOOKUP(Table13[[#This Row],[Item '#]],Data2!A:D,3,0) -> 144 | Q22: 96 | R22: =VLOOKUP(Table13[[#This Row],[Item '#]],[3]Sheet1!$B:$D,3,0) -> 31005
A23: 3190-EACH | B23: B07Q9PJ727 | C23: X003SBSK1P | D23: =VLOOKUP(Table13[[#This Row],[SKU]],Data1!A:B,2,0) -> 3190 | E23: =Table13[[#This Row],[UoM]]*Table13[[#This Row],[Recommended Replenishment Qty]] -> 564 | F23: =Table13[[#This Row],[Total EA (Transfer to WH06)]]/Table13[[#This Row],[UoM]] -> 564 | H23: =Table13[[#This Row],[Total EA (Transfer to WH06)]]/Table13[[#This Row],[CASE]] -> 47 | I23: =Table13[[#This Row],[Sellable Unit/Set/box to ship]]/Table13[[#This Row],[Case to pull]] -> 12 | J23: =IF(ISNUMBER(SEARCH("FNSKU",K23)),"Labeling","") -> Labeling | K23: =VLOOKUP(Table13[[#This Row],[SKU]],Instruction!A:F,6,0) -> • Use FNSKU to label each item (cover barcode). Apply outer box/case label accordingly to match item# (Cover all existing barcodes on the box/case) | L23: =VLOOKUP(Table13[[#This Row],[SKU]],Instruction!A:G,7,0) -> 0 | M23: =VLOOKUP(Table13[[#This Row],[ASIN]],'[4]2024'!$A:$AB,28,0) -> No Supplies | N23: =VLOOKUP(Table13[[#This Row],[SKU]],Data1!A:C,3,0) -> 1 | O23: =VLOOKUP(Table13[[#This Row],[Item '#]],Data2!A:D,4,0) -> 0 | P23: =VLOOKUP(Table13[[#This Row],[Item '#]],Data2!A:D,3,0) -> 12 | Q23: 564 | R23: =VLOOKUP(Table13[[#This Row],[Item '#]],[3]Sheet1!$B:$D,3,0) -> 3245
A24: 1263-EACH | B24: B07S2ZVL8K | C24: X003TJ47A9 | D24: =VLOOKUP(Table13[[#This Row],[SKU]],Data1!A:B,2,0) -> 1263 | E24: =Table13[[#This Row],[UoM]]*Table13[[#This Row],[Recommended Replenishment Qty]] -> 96 | F24: =Table13[[#This Row],[Total EA (Transfer to WH06)]]/Table13[[#This Row],[UoM]] -> 96 | G24: =Table13[[#This Row],[Total EA (Transfer to WH06)]]/Table13[[#This Row],[BOX]] -> 4 | I24: =Table13[[#This Row],[Sellable Unit/Set/box to ship]]/Table13[[#This Row],[Box to pull]] -> 24 | J24: =IF(ISNUMBER(SEARCH("FNSKU",K24)),"Labeling","") -> Labeling | K24: =VLOOKUP(Table13[[#This Row],[SKU]],Instruction!A:F,6,0) -> • Use FNSKU to label each item (cover barcode). Apply outer box/case label accordingly to match item# (Cover all existing barcodes on the box/case) | L24: =VLOOKUP(Table13[[#This Row],[SKU]],Instruction!A:G,7,0) -> 0 | M24: =VLOOKUP(Table13[[#This Row],[ASIN]],'[4]2024'!$A:$AB,28,0) -> No Supplies | N24: =VLOOKUP(Table13[[#This Row],[SKU]],Data1!A:C,3,0) -> 1 | O24: =VLOOKUP(Table13[[#This Row],[Item '#]],Data2!A:D,4,0) -> 24 | P24: =VLOOKUP(Table13[[#This Row],[Item '#]],Data2!A:D,3,0) -> 144 | Q24: 96 | R24: =VLOOKUP(Table13[[#This Row],[Item '#]],[3]Sheet1!$B:$D,3,0) -> 5699
A25: 4150-EACH | B25: B07Q5VSDJZ | C25: X003Y74FUN | D25: =VLOOKUP(Table13[[#This Row],[SKU]],Data1!A:B,2,0) -> 4150 | E25: =Table13[[#This Row],[UoM]]*Table13[[#This Row],[Recommended Replenishment Qty]] -> 72 | F25: =Table13[[#This Row],[Total EA (Transfer to WH06)]]/Table13[[#This Row],[UoM]] -> 72 | H25: =Table13[[#This Row],[Total EA (Transfer to WH06)]]/Table13[[#This Row],[CASE]] -> 6 | I25: =Table13[[#This Row],[Sellable Unit/Set/box to ship]]/Table13[[#This Row],[Case to pull]] -> 12 | J25: =IF(ISNUMBER(SEARCH("FNSKU",K25)),"Labeling","") -> Labeling | K25: =VLOOKUP(Table13[[#This Row],[SKU]],Instruction!A:F,6,0) -> • Use FNSKU to label each item (cover barcode). Apply outer box/case label accordingly to match item# (Cover all existing barcodes on the box/case) | L25: =VLOOKUP(Table13[[#This Row],[SKU]],Instruction!A:G,7,0) -> 0 | M25: =VLOOKUP(Table13[[#This Row],[ASIN]],'[4]2024'!$A:$AB,28,0) -> No Supplies | N25: =VLOOKUP(Table13[[#This Row],[SKU]],Data1!A:C,3,0) -> 1 | O25: =VLOOKUP(Table13[[#This Row],[Item '#]],Data2!A:D,4,0) -> 0 | P25: =VLOOKUP(Table13[[#This Row],[Item '#]],Data2!A:D,3,0) -> 12 | Q25: 72 | R25: =VLOOKUP(Table13[[#This Row],[Item '#]],[3]Sheet1!$B:$D,3,0) -> 1282
A26: 2315-EACH | B26: B07R289Y78 | C26: X0044R3MJ7 | D26: =VLOOKUP(Table13[[#This Row],[SKU]],Data1!A:B,2,0) -> 2315 | E26: =Table13[[#This Row],[UoM]]*Table13[[#This Row],[Recommended Replenishment Qty]] -> 144 | F26: =Table13[[#This Row],[Total EA (Transfer to WH06)]]/Table13[[#This Row],[UoM]] -> 144 | H26: =Table13[[#This Row],[Total EA (Transfer to WH06)]]/Table13[[#This Row],[CASE]] -> 1 | I26: =Table13[[#This Row],[Sellable Unit/Set/box to ship]]/Table13[[#This Row],[Case to pull]] -> 144 | J26: =IF(ISNUMBER(SEARCH("FNSKU",K26)),"Labeling","") -> Labeling | K26: =VLOOKUP(Table13[[#This Row],[SKU]],Instruction!A:F,6,0) -> • Use FNSKU to label each item (cover barcode). Apply outer box/case label accordingly to match item# (Cover all existing barcodes on the box/case) | L26: =VLOOKUP(Table13[[#This Row],[SKU]],Instruction!A:G,7,0) -> 0 | M26: =VLOOKUP(Table13[[#This Row],[ASIN]],'[4]2024'!$A:$AB,28,0) -> No Supplies | N26: =VLOOKUP(Table13[[#This Row],[SKU]],Data1!A:C,3,0) -> 1 | O26: =VLOOKUP(Table13[[#This Row],[Item '#]],Data2!A:D,4,0) -> 24 | P26: =VLOOKUP(Table13[[#This Row],[Item '#]],Data2!A:D,3,0) -> 144 | Q26: 144 | R26: =VLOOKUP(Table13[[#This Row],[Item '#]],[3]Sheet1!$B:$D,3,0) -> 41622
A27: 1906-EACH | B27: B003BMX3T4 | C27: B003BMX3T4 | D27: =VLOOKUP(Table13[[#This Row],[SKU]],Data1!A:B,2,0) -> 1906 | E27: =Table13[[#This Row],[UoM]]*Table13[[#This Row],[Recommended Replenishment Qty]] -> 96 | F27: =Table13[[#This Row],[Total EA (Transfer to WH06)]]/Table13[[#This Row],[UoM]] -> 96 | G27: =Table13[[#This Row],[Total EA (Transfer to WH06)]]/Table13[[#This Row],[BOX]] -> 4 | I27: =Table13[[#This Row],[Sellable Unit/Set/box to ship]]/Table13[[#This Row],[Box to pull]] -> 24 | J27: =IF(ISNUMBER(SEARCH("FNSKU",K27)),"Labeling","") | K27: =VLOOKUP(Table13[[#This Row],[SKU]],Instruction!A:F,6,0) -> Apply outer box/case label accordingly to match item# (Cover all existing barcodes on the box/case) | L27: =VLOOKUP(Table13[[#This Row],[SKU]],Instruction!A:G,7,0) -> 0 | M27: =VLOOKUP(Table13[[#This Row],[ASIN]],'[4]2024'!$A:$AB,28,0) -> No Supplies | N27: =VLOOKUP(Table13[[#This Row],[SKU]],Data1!A:C,3,0) -> 1 | O27: =VLOOKUP(Table13[[#This Row],[Item '#]],Data2!A:D,4,0) -> 24 | P27: =VLOOKUP(Table13[[#This Row],[Item '#]],Data2!A:D,3,0) -> 144 | Q27: 96 | R27: =VLOOKUP(Table13[[#This Row],[Item '#]],[3]Sheet1!$B:$D,3,0) -> 13179
A28: 203-EACH | B28: B08VCZ11NP | C28: X003Y7AI45 | D28: =VLOOKUP(Table13[[#This Row],[SKU]],Data1!A:B,2,0) -> 203 | E28: =Table13[[#This Row],[UoM]]*Table13[[#This Row],[Recommended Replenishment Qty]] -> 72 | F28: =Table13[[#This Row],[Total EA (Transfer to WH06)]]/Table13[[#This Row],[UoM]] -> 72 | G28: =Table13[[#This Row],[Total EA (Transfer to WH06)]]/Table13[[#This Row],[BOX]] -> 3 | I28: =Table13[[#This Row],[Sellable Unit/Set/box to ship]]/Table13[[#This Row],[Box to pull]] -> 24 | J28: =IF(ISNUMBER(SEARCH("FNSKU",K28)),"Labeling","") -> Labeling | K28: =VLOOKUP(Table13[[#This Row],[SKU]],Instruction!A:F,6,0) -> • Use FNSKU to label each item (cover barcode). Apply outer case label accordingly to match item# (Cover all existing barcodes on the case) | L28: =VLOOKUP(Table13[[#This Row],[SKU]],Instruction!A:G,7,0) -> 0 | M28: =VLOOKUP(Table13[[#This Row],[ASIN]],'[4]2024'!$A:$AB,28,0) -> No Supplies | N28: =VLOOKUP(Table13[[#This Row],[SKU]],Data1!A:C,3,0) -> 1 | O28: =VLOOKUP(Table13[[#This Row],[Item '#]],Data2!A:D,4,0) -> 24 | P28: =VLOOKUP(Table13[[#This Row],[Item '#]],Data2!A:D,3,0) -> 144 | Q28: 72 | R28: =VLOOKUP(Table13[[#This Row],[Item '#]],[3]Sheet1!$B:$D,3,0) -> 16774
A29: 5074-EACH | B29: B00IIN3K5I | C29: B00IIN3K5I | D29: =VLOOKUP(Table13[[#This Row],[SKU]],Data1!A:B,2,0) -> 5074 | E29: =Table13[[#This Row],[UoM]]*Table13[[#This Row],[Recommended Replenishment Qty]] -> 288 | F29: =Table13[[#This Row],[Total EA (Transfer to WH06)]]/Table13[[#This Row],[UoM]] -> 288 | H29: =Table13[[#This Row],[Total EA (Transfer to WH06)]]/Table13[[#This Row],[CASE]] -> 2 | I29: =Table13[[#This Row],[Sellable Unit/Set/box to ship]]/Table13[[#This Row],[Case to pull]] -> 144 | J29: =IF(ISNUMBER(SEARCH("FNSKU",K29)),"Labeling","") | K29: =VLOOKUP(Table13[[#This Row],[SKU]],Instruction!A:F,6,0) -> Apply outer box/case label accordingly to match item# (Cover all existing barcodes on the box/case) | L29: =VLOOKUP(Table13[[#This Row],[SKU]],Instruction!A:G,7,0) -> 0 | M29: =VLOOKUP(Table13[[#This Row],[ASIN]],'[4]2024'!$A:$AB,28,0) -> No Supplies | N29: =VLOOKUP(Table13[[#This Row],[SKU]],Data1!A:C,3,0) -> 1 | O29: =VLOOKUP(Table13[[#This Row],[Item '#]],Data2!A:D,4,0) -> 24 | P29: =VLOOKUP(Table13[[#This Row],[Item '#]],Data2!A:D,3,0) -> 144 | Q29: 288 | R29: =VLOOKUP(Table13[[#This Row],[Item '#]],[3]Sheet1!$B:$D,3,0) -> 51817
A30: 6120-EACH | B30: B09DJVP3DS | C30: B09DJVP3DS | D30: =VLOOKUP(Table13[[#This Row],[SKU]],Data1!A:B,2,0) -> 6120 | E30: =Table13[[#This Row],[UoM]]*Table13[[#This Row],[Recommended Replenishment Qty]] -> 1044 | F30: =Table13[[#This Row],[Total EA (Transfer to WH06)]]/Table13[[#This Row],[UoM]] -> 1044 | H30: =Table13[[#This Row],[Total EA (Transfer to WH06)]]/Table13[[#This Row],[CASE]] -> 29 | I30: =Table13[[#This Row],[Sellable Unit/Set/box to ship]]/Table13[[#This Row],[Case to pull]] -> 36 | J30: =IF(ISNUMBER(SEARCH("FNSKU",K30)),"Labeling","") | K30: =VLOOKUP(Table13[[#This Row],[SKU]],Instruction!A:F,6,0) -> Apply outer box/case label accordingly to match item# (Cover all existing barcodes on the box/case) | L30: =VLOOKUP(Table13[[#This Row],[SKU]],Instruction!A:G,7,0) -> 0 | M30: =VLOOKUP(Table13[[#This Row],[ASIN]],'[4]2024'!$A:$AB,28,0) -> No Supplies | N30: =VLOOKUP(Table13[[#This Row],[SKU]],Data1!A:C,3,0) -> 1 | O30: =VLOOKUP(Table13[[#This Row],[Item '#]],Data2!A:D,4,0) -> 0 | P30: =VLOOKUP(Table13[[#This Row],[Item '#]],Data2!A:D,3,0) -> 36 | Q30: 1044 | R30: =VLOOKUP(Table13[[#This Row],[Item '#]],[3]Sheet1!$B:$D,3,0) -> 9474
A31: 2202-EACH | B31: B003BNZVI4 | C31: B003BNZVI4 | D31: =VLOOKUP(Table13[[#This Row],[SKU]],Data1!A:B,2,0) -> 2202 | E31: =Table13[[#This Row],[UoM]]*Table13[[#This Row],[Recommended Replenishment Qty]] -> 1872 | F31: =Table13[[#This Row],[Total EA (Transfer to WH06)]]/Table13[[#This Row],[UoM]] -> 1872 | H31: =Table13[[#This Row],[Total EA (Transfer to WH06)]]/Table13[[#This Row],[CASE]] -> 13 | I31: =Table13[[#This Row],[Sellable Unit/Set/box to ship]]/Table13[[#This Row],[Case to pull]] -> 144 | J31: =IF(ISNUMBER(SEARCH("FNSKU",K31)),"Labeling","") | K31: =VLOOKUP(Table13[[#This Row],[SKU]],Instruction!A:F,6,0) -> Apply outer box/case label accordingly to match item# (Cover all existing barcodes on the box/case) | L31: =VLOOKUP(Table13[[#This Row],[SKU]],Instruction!A:G,7,0) -> 0 | M31: =VLOOKUP(Table13[[#This Row],[ASIN]],'[4]2024'!$A:$AB,28,0) -> No Supplies | N31: =VLOOKUP(Table13[[#This Row],[SKU]],Data1!A:C,3,0) -> 1 | O31: =VLOOKUP(Table13[[#This Row],[Item '#]],Data2!A:D,4,0) -> 24 | P31: =VLOOKUP(Table13[[#This Row],[Item '#]],Data2!A:D,3,0) -> 144 | Q31: 1872 | R31: =VLOOKUP(Table13[[#This Row],[Item '#]],[3]Sheet1!$B:$D,3,0) -> 21489
A32: 6003-EACH | B32: B002URU9G6 | C32: B002URU9G6 | D32: =VLOOKUP(Table13[[#This Row],[SKU]],Data1!A:B,2,0) -> 6003 | E32: =Table13[[#This Row],[UoM]]*Table13[[#This Row],[Recommended Replenishment Qty]] -> 576 | F32: =Table13[[#This Row],[Total EA (Transfer to WH06)]]/Table13[[#This Row],[UoM]] -> 576 | H32: =Table13[[#This Row],[Total EA (Transfer to WH06)]]/Table13[[#This Row],[CASE]] -> 4 | I32: =Table13[[#This Row],[Sellable Unit/Set/box to ship]]/Table13[[#This Row],[Case to pull]] -> 144 | J32: =IF(ISNUMBER(SEARCH("FNSKU",K32)),"Labeling","") -> Labeling | K32: =VLOOKUP(Table13[[#This Row],[SKU]],Instruction!A:F,6,0) -> • Use FNSKU to label each item (cover barcode). Apply outer box/case label accordingly to match item# (Cover all existing barcodes on the box/case) | L32: =VLOOKUP(Table13[[#This Row],[SKU]],Instruction!A:G,7,0) -> 0 | M32: =VLOOKUP(Table13[[#This Row],[ASIN]],'[4]2024'!$A:$AB,28,0) -> No Supplies | N32: =VLOOKUP(Table13[[#This Row],[SKU]],Data1!A:C,3,0) -> 1 | O32: =VLOOKUP(Table13[[#This Row],[Item '#]],Data2!A:D,4,0) -> 24 | P32: =VLOOKUP(Table13[[#This Row],[Item '#]],Data2!A:D,3,0) -> 144 | Q32: 576 | R32: =VLOOKUP(Table13[[#This Row],[Item '#]],[3]Sheet1!$B:$D,3,0) -> 12353
A33: 847-EACH | B33: B08QRDCTXN | C33: B08QRDCTXN | D33: =VLOOKUP(Table13[[#This Row],[SKU]],Data1!A:B,2,0) -> 847 | E33: =Table13[[#This Row],[UoM]]*Table13[[#This Row],[Recommended Replenishment Qty]] -> 144 | F33: =Table13[[#This Row],[Total EA (Transfer to WH06)]]/Table13[[#This Row],[UoM]] -> 144 | H33: =Table13[[#This Row],[Total EA (Transfer to WH06)]]/Table13[[#This Row],[CASE]] -> 6 | I33: =Table13[[#This Row],[Sellable Unit/Set/box to ship]]/Table13[[#This Row],[Case to pull]] -> 24 | J33: =IF(ISNUMBER(SEARCH("FNSKU",K33)),"Labeling","") | K33: =VLOOKUP(Table13[[#This Row],[SKU]],Instruction!A:F,6,0) -> Apply outer box/case label accordingly to match item# (Cover all existing barcodes on the box/case) | L33: =VLOOKUP(Table13[[#This Row],[SKU]],Instruction!A:G,7,0) -> 0 | M33: =VLOOKUP(Table13[[#This Row],[ASIN]],'[4]2024'!$A:$AB,28,0) -> No Supplies | N33: =VLOOKUP(Table13[[#This Row],[SKU]],Data1!A:C,3,0) -> 1 | O33: =VLOOKUP(Table13[[#This Row],[Item '#]],Data2!A:D,4,0) -> 0 | P33: =VLOOKUP(Table13[[#This Row],[Item '#]],Data2!A:D,3,0) -> 24 | Q33: 144 | R33: =VLOOKUP(Table13[[#This Row],[Item '#]],[3]Sheet1!$B:$D,3,0) -> 20841
A34: 2309-EACH-B | B34: B0C4VY1LR7 | C34: B0C4VY1LR7 | D34: =VLOOKUP(Table13[[#This Row],[SKU]],Data1!A:B,2,0) -> 2309 | E34: =Table13[[#This Row],[UoM]]*Table13[[#This Row],[Recommended Replenishment Qty]] -> 288 | F34: =Table13[[#This Row],[Total EA (Transfer to WH06)]]/Table13[[#This Row],[UoM]] -> 288 | H34: =Table13[[#This Row],[Total EA (Transfer to WH06)]]/Table13[[#This Row],[CASE]] -> 2 | I34: =Table13[[#This Row],[Sellable Unit/Set/box to ship]]/Table13[[#This Row],[Case to pull]] -> 144 | J34: =IF(ISNUMBER(SEARCH("FNSKU",K34)),"Labeling","") | K34: =VLOOKUP(Table13[[#This Row],[SKU]],Instruction!A:F,6,0) -> Apply outer case label accordingly to match item# (Cover all existing barcodes on the case) | L34: =VLOOKUP(Table13[[#This Row],[SKU]],Instruction!A:G,7,0) -> 0 | M34: =VLOOKUP(Table13[[#This Row],[ASIN]],'[4]2024'!$A:$AB,28,0) -> No Supplies | N34: =VLOOKUP(Table13[[#This Row],[SKU]],Data1!A:C,3,0) -> 1 | O34: =VLOOKUP(Table13[[#This Row],[Item '#]],Data2!A:D,4,0) -> 24 | P34: =VLOOKUP(Table13[[#This Row],[Item '#]],Data2!A:D,3,0) -> 144 | Q34: 288 | R34: =VLOOKUP(Table13[[#This Row],[Item '#]],[3]Sheet1!$B:$D,3,0) -> 6246
A35: 508-EACH | B35: B001E75OY0 | C35: B001E75OY0 | D35: =VLOOKUP(Table13[[#This Row],[SKU]],Data1!A:B,2,0) -> 508 | E35: =Table13[[#This Row],[UoM]]*Table13[[#This Row],[Recommended Replenishment Qty]] -> 672 | F35: =Table13[[#This Row],[Total EA (Transfer to WH06)]]/Table13[[#This Row],[UoM]] -> 672 | H35: =Table13[[#This Row],[Total EA (Transfer to WH06)]]/Table13[[#This Row],[CASE]] -> 14 | I35: =Table13[[#This Row],[Sellable Unit/Set/box to ship]]/Table13[[#This Row],[Case to pull]] -> 48 | J35: =IF(ISNUMBER(SEARCH("FNSKU",K35)),"Labeling","") | K35: =VLOOKUP(Table13[[#This Row],[SKU]],Instruction!A:F,6,0) -> Apply outer box/case label accordingly to match item# (Cover all existing barcodes on the box/case) | L35: =VLOOKUP(Table13[[#This Row],[SKU]],Instruction!A:G,7,0) -> 0 | M35: =VLOOKUP(Table13[[#This Row],[ASIN]],'[4]2024'!$A:$AB,28,0) -> No Supplies | N35: =VLOOKUP(Table13[[#This Row],[SKU]],Data1!A:C,3,0) -> 1 | O35: =VLOOKUP(Table13[[#This Row],[Item '#]],Data2!A:D,4,0) -> 0 | P35: =VLOOKUP(Table13[[#This Row],[Item '#]],Data2!A:D,3,0) -> 48 | Q35: 672 | R35: =VLOOKUP(Table13[[#This Row],[Item '#]],[3]Sheet1!$B:$D,3,0) -> 123928
A36: 6110-EACH | B36: B07SC668W8 | C36: X002GASSMF | D36: =VLOOKUP(Table13[[#This Row],[SKU]],Data1!A:B,2,0) -> 6110 | E36: =Table13[[#This Row],[UoM]]*Table13[[#This Row],[Recommended Replenishment Qty]] -> 972 | F36: =Table13[[#This Row],[Total EA (Transfer to WH06)]]/Table13[[#This Row],[UoM]] -> 972 | H36: =Table13[[#This Row],[Total EA (Transfer to WH06)]]/Table13[[#This Row],[CASE]] -> 27 | I36: =Table13[[#This Row],[Sellable Unit/Set/box to ship]]/Table13[[#This Row],[Case to pull]] -> 36 | J36: =IF(ISNUMBER(SEARCH("FNSKU",K36)),"Labeling","") -> Labeling | K36: =VLOOKUP(Table13[[#This Row],[SKU]],Instruction!A:F,6,0) -> • Use FNSKU to label each item (cover barcode). Apply outer box/case label accordingly to match item# (Cover all existing barcodes on the box/case) | L36: =VLOOKUP(Table13[[#This Row],[SKU]],Instruction!A:G,7,0) -> 0 | M36: =VLOOKUP(Table13[[#This Row],[ASIN]],'[4]2024'!$A:$AB,28,0) -> No Supplies | N36: =VLOOKUP(Table13[[#This Row],[SKU]],Data1!A:C,3,0) -> 1 | O36: =VLOOKUP(Table13[[#This Row],[Item '#]],Data2!A:D,4,0) -> 0 | P36: =VLOOKUP(Table13[[#This Row],[Item '#]],Data2!A:D,3,0) -> 36 | Q36: 972 | R36: =VLOOKUP(Table13[[#This Row],[Item '#]],[3]Sheet1!$B:$D,3,0) -> 15948
A37: 6100-EACH | B37: B00GSSDLMM | C37: B00GSSDLMM | D37: =VLOOKUP(Table13[[#This Row],[SKU]],Data1!A:B,2,0) -> 6100 | E37: =Table13[[#This Row],[UoM]]*Table13[[#This Row],[Recommended Replenishment Qty]] -> 1692 | F37: =Table13[[#This Row],[Total EA (Transfer to WH06)]]/Table13[[#This Row],[UoM]] -> 1692 | H37: =Table13[[#This Row],[Total EA (Transfer to WH06)]]/Table13[[#This Row],[CASE]] -> 47 | I37: =Table13[[#This Row],[Sellable Unit/Set/box to ship]]/Table13[[#This Row],[Case to pull]] -> 36 | J37: =IF(ISNUMBER(SEARCH("FNSKU",K37)),"Labeling","") | K37: =VLOOKUP(Table13[[#This Row],[SKU]],Instruction!A:F,6,0) -> Apply outer box/case label accordingly to match item# (Cover all existing barcodes on box and case) | L37: =VLOOKUP(Table13[[#This Row],[SKU]],Instruction!A:G,7,0) -> 0 | M37: =VLOOKUP(Table13[[#This Row],[ASIN]],'[4]2024'!$A:$AB,28,0) -> No Supplies | N37: =VLOOKUP(Table13[[#This Row],[SKU]],Data1!A:C,3,0) -> 1 | O37: =VLOOKUP(Table13[[#This Row],[Item '#]],Data2!A:D,4,0) -> 0 | P37: =VLOOKUP(Table13[[#This Row],[Item '#]],Data2!A:D,3,0) -> 36 | Q37: 1692 | R37: =VLOOKUP(Table13[[#This Row],[Item '#]],[3]Sheet1!$B:$D,3,0) -> 9563
A38: 336-EACH | B38: B003BMX65A | C38: X003TIPAXN | D38: =VLOOKUP(Table13[[#This Row],[SKU]],Data1!A:B,2,0) -> 336 | E38: =Table13[[#This Row],[UoM]]*Table13[[#This Row],[Recommended Replenishment Qty]] -> 1152 | F38: =Table13[[#This Row],[Total EA (Transfer to WH06)]]/Table13[[#This Row],[UoM]] -> 1152 | H38: =Table13[[#This Row],[Total EA (Transfer to WH06)]]/Table13[[#This Row],[CASE]] -> 8 | I38: =Table13[[#This Row],[Sellable Unit/Set/box to ship]]/Table13[[#This Row],[Case to pull]] -> 144 | J38: =IF(ISNUMBER(SEARCH("FNSKU",K38)),"Labeling","") -> Labeling | K38: =VLOOKUP(Table13[[#This Row],[SKU]],Instruction!A:F,6,0) -> • Use FNSKU to label each item (cover barcode). Apply outer box/case label accordingly to match item# (Cover all existing barcodes on the box/case) | L38: =VLOOKUP(Table13[[#This Row],[SKU]],Instruction!A:G,7,0) -> 0 | M38: =VLOOKUP(Table13[[#This Row],[ASIN]],'[4]2024'!$A:$AB,28,0) -> No Supplies | N38: =VLOOKUP(Table13[[#This Row],[SKU]],Data1!A:C,3,0) -> 1 | O38: =VLOOKUP(Table13[[#This Row],[Item '#]],Data2!A:D,4,0) -> 24 | P38: =VLOOKUP(Table13[[#This Row],[Item '#]],Data2!A:D,3,0) -> 144 | Q38: 1152 | R38: =VLOOKUP(Table13[[#This Row],[Item '#]],[3]Sheet1!$B:$D,3,0) -> 41716
A39: 3103-EACH | B39: B003BSFCMY | C39: B003BSFCMY | D39: =VLOOKUP(Table13[[#This Row],[SKU]],Data1!A:B,2,0) -> 3103 | E39: =Table13[[#This Row],[UoM]]*Table13[[#This Row],[Recommended Replenishment Qty]] -> 240 | F39: =Table13[[#This Row],[Total EA (Transfer to WH06)]]/Table13[[#This Row],[UoM]] -> 240 | H39: =Table13[[#This Row],[Total EA (Transfer to WH06)]]/Table13[[#This Row],[CASE]] -> 5 | I39: =Table13[[#This Row],[Sellable Unit/Set/box to ship]]/Table13[[#This Row],[Case to pull]] -> 48 | J39: =IF(ISNUMBER(SEARCH("FNSKU",K39)),"Labeling","") | K39: =VLOOKUP(Table13[[#This Row],[SKU]],Instruction!A:F,6,0) -> Apply outer box/case label accordingly to match item# (Cover all existing barcodes on the box/case) | L39: =VLOOKUP(Table13[[#This Row],[SKU]],Instruction!A:G,7,0) -> 0 | M39: =VLOOKUP(Table13[[#This Row],[ASIN]],'[4]2024'!$A:$AB,28,0) -> No Supplies | N39: =VLOOKUP(Table13[[#This Row],[SKU]],Data1!A:C,3,0) -> 1 | O39: =VLOOKUP(Table13[[#This Row],[Item '#]],Data2!A:D,4,0) -> 0 | P39: =VLOOKUP(Table13[[#This Row],[Item '#]],Data2!A:D,3,0) -> 48 | Q39: 240 | R39: =VLOOKUP(Table13[[#This Row],[Item '#]],[3]Sheet1!$B:$D,3,0) -> 6337
A40: 4398-EACH | B40: B07SFKBQ7F | C40: X003GYE2EX | D40: =VLOOKUP(Table13[[#This Row],[SKU]],Data1!A:B,2,0) -> 4398 | E40: =Table13[[#This Row],[UoM]]*Table13[[#This Row],[Recommended Replenishment Qty]] -> 1008 | F40: =Table13[[#This Row],[Total EA (Transfer to WH06)]]/Table13[[#This Row],[UoM]] -> 1008 | H40: =Table13[[#This Row],[Total EA (Transfer to WH06)]]/Table13[[#This Row],[CASE]] -> 7 | I40: =Table13[[#This Row],[Sellable Unit/Set/box to ship]]/Table13[[#This Row],[Case to pull]] -> 144 | J40: =IF(ISNUMBER(SEARCH("FNSKU",K40)),"Labeling","") -> Labeling | K40: =VLOOKUP(Table13[[#This Row],[SKU]],Instruction!A:F,6,0) -> • Use FNSKU to label each item (cover barcode). Apply outer box/case label accordingly to match item# (Cover all existing barcodes on the box/case) | L40: =VLOOKUP(Table13[[#This Row],[SKU]],Instruction!A:G,7,0) -> 0 | M40: =VLOOKUP(Table13[[#This Row],[ASIN]],'[4]2024'!$A:$AB,28,0) -> No Supplies | N40: =VLOOKUP(Table13[[#This Row],[SKU]],Data1!A:C,3,0) -> 1 | O40: =VLOOKUP(Table13[[#This Row],[Item '#]],Data2!A:D,4,0) -> 24 | P40: =VLOOKUP(Table13[[#This Row],[Item '#]],Data2!A:D,3,0) -> 144 | Q40: 1008 | R40: =VLOOKUP(Table13[[#This Row],[Item '#]],[3]Sheet1!$B:$D,3,0) -> 18572
A41: 2330-EACH | B41: B00TQ5WT4U | C41: B00TQ5WT4U | D41: =VLOOKUP(Table13[[#This Row],[SKU]],Data1!A:B,2,0) -> 2330 | E41: =Table13[[#This Row],[UoM]]*Table13[[#This Row],[Recommended Replenishment Qty]] -> 120 | F41: =Table13[[#This Row],[Total EA (Transfer to WH06)]]/Table13[[#This Row],[UoM]] -> 120 | G41: =Table13[[#This Row],[Total EA (Transfer to WH06)]]/Table13[[#This Row],[BOX]] -> 5 | I41: =Table13[[#This Row],[Sellable Unit/Set/box to ship]]/Table13[[#This Row],[Box to pull]] -> 24 | J41: =IF(ISNUMBER(SEARCH("FNSKU",K41)),"Labeling","") | K41: =VLOOKUP(Table13[[#This Row],[SKU]],Instruction!A:F,6,0) -> Apply outer box/case label accordingly to match item# (Cover all existing barcodes on the box/case) | L41: =VLOOKUP(Table13[[#This Row],[SKU]],Instruction!A:G,7,0) -> 0 | M41: =VLOOKUP(Table13[[#This Row],[ASIN]],'[4]2024'!$A:$AB,28,0) -> No Supplies | N41: =VLOOKUP(Table13[[#This Row],[SKU]],Data1!A:C,3,0) -> 1 | O41: =VLOOKUP(Table13[[#This Row],[Item '#]],Data2!A:D,4,0) -> 24 | P41: =VLOOKUP(Table13[[#This Row],[Item '#]],Data2!A:D,3,0) -> 144 | Q41: 120 | R41: =VLOOKUP(Table13[[#This Row],[Item '#]],[3]Sheet1!$B:$D,3,0) -> 10800
A42: 929-EACH | B42: B00GTJD0V2 | C42: B00GTJD0V2 | D42: =VLOOKUP(Table13[[#This Row],[SKU]],Data1!A:B,2,0) -> 929 | E42: =Table13[[#This Row],[UoM]]*Table13[[#This Row],[Recommended Replenishment Qty]] -> 576 | F42: =Table13[[#This Row],[Total EA (Transfer to WH06)]]/Table13[[#This Row],[UoM]] -> 576 | H42: =Table13[[#This Row],[Total EA (Transfer to WH06)]]/Table13[[#This Row],[CASE]] -> 4 | I42: =Table13[[#This Row],[Sellable Unit/Set/box to ship]]/Table13[[#This Row],[Case to pull]] -> 144 | J42: =IF(ISNUMBER(SEARCH("FNSKU",K42)),"Labeling","") | K42: =VLOOKUP(Table13[[#This Row],[SKU]],Instruction!A:F,6,0) -> Apply outer case label accordingly to match item# (Cover all existing barcodes on the case) | L42: =VLOOKUP(Table13[[#This Row],[SKU]],Instruction!A:G,7,0) -> 0 | M42: =VLOOKUP(Table13[[#This Row],[ASIN]],'[4]2024'!$A:$AB,28,0) -> No Supplies | N42: =VLOOKUP(Table13[[#This Row],[SKU]],Data1!A:C,3,0) -> 1 | O42: =VLOOKUP(Table13[[#This Row],[Item '#]],Data2!A:D,4,0) -> 24 | P42: =VLOOKUP(Table13[[#This Row],[Item '#]],Data2!A:D,3,0) -> 144 | Q42: 576 | R42: =VLOOKUP(Table13[[#This Row],[Item '#]],[3]Sheet1!$B:$D,3,0) -> 40085
A43: 520-EACH | B43: B07S962L7Q | C43: X0044RLTFV | D43: =VLOOKUP(Table13[[#This Row],[SKU]],Data1!A:B,2,0) -> 520 | E43: =Table13[[#This Row],[UoM]]*Table13[[#This Row],[Recommended Replenishment Qty]] -> 432 | F43: =Table13[[#This Row],[Total EA (Transfer to WH06)]]/Table13[[#This Row],[UoM]] -> 432 | H43: =Table13[[#This Row],[Total EA (Transfer to WH06)]]/Table13[[#This Row],[CASE]] -> 12 | I43: =Table13[[#This Row],[Sellable Unit/Set/box to ship]]/Table13[[#This Row],[Case to pull]] -> 36 | J43: =IF(ISNUMBER(SEARCH("FNSKU",K43)),"Labeling","") -> Labeling | K43: =VLOOKUP(Table13[[#This Row],[SKU]],Instruction!A:F,6,0) -> • Use FNSKU to label each item (cover barcode). Apply outer case label accordingly to match item# (Cover all existing barcodes on the case) | L43: =VLOOKUP(Table13[[#This Row],[SKU]],Instruction!A:G,7,0) -> 0 | M43: =VLOOKUP(Table13[[#This Row],[ASIN]],'[4]2024'!$A:$AB,28,0) -> No Supplies | N43: =VLOOKUP(Table13[[#This Row],[SKU]],Data1!A:C,3,0) -> 1 | O43: =VLOOKUP(Table13[[#This Row],[Item '#]],Data2!A:D,4,0) -> 0 | P43: =VLOOKUP(Table13[[#This Row],[Item '#]],Data2!A:D,3,0) -> 36 | Q43: 432 | R43: =VLOOKUP(Table13[[#This Row],[Item '#]],[3]Sheet1!$B:$D,3,0) -> 13641
A44: 1292-EACH | B44: B0B9Q8LBNN | C44: B0B9Q8LBNN | D44: =VLOOKUP(Table13[[#This Row],[SKU]],Data1!A:B,2,0) -> 1292 | E44: =Table13[[#This Row],[UoM]]*Table13[[#This Row],[Recommended Replenishment Qty]] -> 24 | F44: =Table13[[#This Row],[Total EA (Transfer to WH06)]]/Table13[[#This Row],[UoM]] -> 24 | G44: =Table13[[#This Row],[Total EA (Transfer to WH06)]]/Table13[[#This Row],[BOX]] -> 1 | I44: =Table13[[#This Row],[Sellable Unit/Set/box to ship]]/Table13[[#This Row],[Box to pull]] -> 24 | J44: =IF(ISNUMBER(SEARCH("FNSKU",K44)),"Labeling","") | K44: =VLOOKUP(Table13[[#This Row],[SKU]],Instruction!A:F,6,0) -> Apply outer box/case label accordingly to match item# (Cover all existing barcodes on the box/case) | L44: =VLOOKUP(Table13[[#This Row],[SKU]],Instruction!A:G,7,0) -> 0 | M44: =VLOOKUP(Table13[[#This Row],[ASIN]],'[4]2024'!$A:$AB,28,0) -> No Supplies | N44: =VLOOKUP(Table13[[#This Row],[SKU]],Data1!A:C,3,0) -> 1 | O44: =VLOOKUP(Table13[[#This Row],[Item '#]],Data2!A:D,4,0) -> 24 | P44: =VLOOKUP(Table13[[#This Row],[Item '#]],Data2!A:D,3,0) -> 144 | Q44: 24 | R44: =VLOOKUP(Table13[[#This Row],[Item '#]],[3]Sheet1!$B:$D,3,0) -> 17500
A45: 2206-EACH | B45: B07RPR34BJ | C45: X002GAOOB9 | D45: =VLOOKUP(Table13[[#This Row],[SKU]],Data1!A:B,2,0) -> 2206 | E45: =Table13[[#This Row],[UoM]]*Table13[[#This Row],[Recommended Replenishment Qty]] -> 720 | F45: =Table13[[#This Row],[Total EA (Transfer to WH06)]]/Table13[[#This Row],[UoM]] -> 720 | H45: =Table13[[#This Row],[Total EA (Transfer to WH06)]]/Table13[[#This Row],[CASE]] -> 5 | I45: =Table13[[#This Row],[Sellable Unit/Set/box to ship]]/Table13[[#This Row],[Case to pull]] -> 144 | J45: =IF(ISNUMBER(SEARCH("FNSKU",K45)),"Labeling","") -> Labeling | K45: =VLOOKUP(Table13[[#This Row],[SKU]],Instruction!A:F,6,0) -> • Use FNSKU to label each item (cover barcode). Apply outer box/case label accordingly to match item# (Cover all existing barcodes on the box/case) | L45: =VLOOKUP(Table13[[#This Row],[SKU]],Instruction!A:G,7,0) -> 0 | M45: =VLOOKUP(Table13[[#This Row],[ASIN]],'[4]2024'!$A:$AB,28,0) -> No Supplies | N45: =VLOOKUP(Table13[[#This Row],[SKU]],Data1!A:C,3,0) -> 1 | O45: =VLOOKUP(Table13[[#This Row],[Item '#]],Data2!A:D,4,0) -> 24 | P45: =VLOOKUP(Table13[[#This Row],[Item '#]],Data2!A:D,3,0) -> 144 | Q45: 720 | R45: =VLOOKUP(Table13[[#This Row],[Item '#]],[3]Sheet1!$B:$D,3,0) -> 26109
A46: 4124-EACH | B46: B07Q714JRN | C46: B07Q714JRN | D46: =VLOOKUP(Table13[[#This Row],[SKU]],Data1!A:B,2,0) -> 4124 | E46: =Table13[[#This Row],[UoM]]*Table13[[#This Row],[Recommended Replenishment Qty]] -> 132 | F46: =Table13[[#This Row],[Total EA (Transfer to WH06)]]/Table13[[#This Row],[UoM]] -> 132 | H46: =Table13[[#This Row],[Total EA (Transfer to WH06)]]/Table13[[#This Row],[CASE]] -> 11 | I46: =Table13[[#This Row],[Sellable Unit/Set/box to ship]]/Table13[[#This Row],[Case to pull]] -> 12 | J46: =IF(ISNUMBER(SEARCH("FNSKU",K46)),"Labeling","") | K46: =VLOOKUP(Table13[[#This Row],[SKU]],Instruction!A:F,6,0) -> Apply outer box/case label accordingly to match item# (Cover all existing barcodes on the box/case) | L46: =VLOOKUP(Table13[[#This Row],[SKU]],Instruction!A:G,7,0) -> 0 | M46: =VLOOKUP(Table13[[#This Row],[ASIN]],'[4]2024'!$A:$AB,28,0) -> No Supplies | N46: =VLOOKUP(Table13[[#This Row],[SKU]],Data1!A:C,3,0) -> 1 | O46: =VLOOKUP(Table13[[#This Row],[Item '#]],Data2!A:D,4,0) -> 0 | P46: =VLOOKUP(Table13[[#This Row],[Item '#]],Data2!A:D,3,0) -> 12 | Q46: 132 | R46: =VLOOKUP(Table13[[#This Row],[Item '#]],[3]Sheet1!$B:$D,3,0) -> 17484
A47: 3109-EACH | B47: B001GE6ACG | C47: B001GE6ACG | D47: =VLOOKUP(Table13[[#This Row],[SKU]],Data1!A:B,2,0) -> 3109 | E47: =Table13[[#This Row],[UoM]]*Table13[[#This Row],[Recommended Replenishment Qty]] -> 192 | F47: =Table13[[#This Row],[Total EA (Transfer to WH06)]]/Table13[[#This Row],[UoM]] -> 192 | H47: =Table13[[#This Row],[Total EA (Transfer to WH06)]]/Table13[[#This Row],[CASE]] -> 4 | I47: =Table13[[#This Row],[Sellable Unit/Set/box to ship]]/Table13[[#This Row],[Case to pull]] -> 48 | J47: =IF(ISNUMBER(SEARCH("FNSKU",K47)),"Labeling","") | K47: =VLOOKUP(Table13[[#This Row],[SKU]],Instruction!A:F,6,0) -> Apply outer box/case label accordingly to match item# (Cover all existing barcodes on the box/case) | L47: =VLOOKUP(Table13[[#This Row],[SKU]],Instruction!A:G,7,0) -> 0 | M47: =VLOOKUP(Table13[[#This Row],[ASIN]],'[4]2024'!$A:$AB,28,0) -> No Supplies | N47: =VLOOKUP(Table13[[#This Row],[SKU]],Data1!A:C,3,0) -> 1 | O47: =VLOOKUP(Table13[[#This Row],[Item '#]],Data2!A:D,4,0) -> 0 | P47: =VLOOKUP(Table13[[#This Row],[Item '#]],Data2!A:D,3,0) -> 48 | Q47: 192 | R47: =VLOOKUP(Table13[[#This Row],[Item '#]],[3]Sheet1!$B:$D,3,0) -> 60345
A48: 1502-EACH | B48: B002WFI620 | C48: B002WFI620 | D48: =VLOOKUP(Table13[[#This Row],[SKU]],Data1!A:B,2,0) -> 1502 | E48: =Table13[[#This Row],[UoM]]*Table13[[#This Row],[Recommended Replenishment Qty]] -> 1152 | F48: =Table13[[#This Row],[Total EA (Transfer to WH06)]]/Table13[[#This Row],[UoM]] -> 1152 | H48: =Table13[[#This Row],[Total EA (Transfer to WH06)]]/Table13[[#This Row],[CASE]] -> 8 | I48: =Table13[[#This Row],[Sellable Unit/Set/box to ship]]/Table13[[#This Row],[Case to pull]] -> 144 | J48: =IF(ISNUMBER(SEARCH("FNSKU",K48)),"Labeling","") | K48: =VLOOKUP(Table13[[#This Row],[SKU]],Instruction!A:F,6,0) -> Cover inner box barcode. Apply outer case label accordingly to match item# (Cover barcodes on the case) | L48: =VLOOKUP(Table13[[#This Row],[SKU]],Instruction!A:G,7,0) -> 0 | M48: =VLOOKUP(Table13[[#This Row],[ASIN]],'[4]2024'!$A:$AB,28,0) -> No Supplies | N48: =VLOOKUP(Table13[[#This Row],[SKU]],Data1!A:C,3,0) -> 1 | O48: =VLOOKUP(Table13[[#This Row],[Item '#]],Data2!A:D,4,0) -> 24 | P48: =VLOOKUP(Table13[[#This Row],[Item '#]],Data2!A:D,3,0) -> 144 | Q48: 1152 | R48: =VLOOKUP(Table13[[#This Row],[Item '#]],[3]Sheet1!$B:$D,3,0) -> 5441
A49: 6303-EACH | B49: B08P3WZTXG | C49: B08P3WZTXG | D49: =VLOOKUP(Table13[[#This Row],[SKU]],Data1!A:B,2,0) -> 6303 | E49: =Table13[[#This Row],[UoM]]*Table13[[#This Row],[Recommended Replenishment Qty]] -> 72 | F49: =Table13[[#This Row],[Total EA (Transfer to WH06)]]/Table13[[#This Row],[UoM]] -> 72 | G49: =Table13[[#This Row],[Total EA (Transfer to WH06)]]/Table13[[#This Row],[BOX]] -> 3 | I49: =Table13[[#This Row],[Sellable Unit/Set/box to ship]]/Table13[[#This Row],[Box to pull]] -> 24 | J49: =IF(ISNUMBER(SEARCH("FNSKU",K49)),"Labeling","") | K49: =VLOOKUP(Table13[[#This Row],[SKU]],Instruction!A:F,6,0) -> Cover inner box barcode. Apply outer case label accordingly to match item# (Cover barcodes on the case) | L49: =VLOOKUP(Table13[[#This Row],[SKU]],Instruction!A:G,7,0) -> 0 | M49: =VLOOKUP(Table13[[#This Row],[ASIN]],'[4]2024'!$A:$AB,28,0) -> No Supplies | N49: =VLOOKUP(Table13[[#This Row],[SKU]],Data1!A:C,3,0) -> 1 | O49: =VLOOKUP(Table13[[#This Row],[Item '#]],Data2!A:D,4,0) -> 24 | P49: =VLOOKUP(Table13[[#This Row],[Item '#]],Data2!A:D,3,0) -> 144 | Q49: 72 | R49: =VLOOKUP(Table13[[#This Row],[Item '#]],[3]Sheet1!$B:$D,3,0) -> -131
A50: 304-EACH | B50: B0019IO3VY | C50: B0019IO3VY | D50: =VLOOKUP(Table13[[#This Row],[SKU]],Data1!A:B,2,0) -> 304 | E50: =Table13[[#This Row],[UoM]]*Table13[[#This Row],[Recommended Replenishment Qty]] -> 120 | F50: =Table13[[#This Row],[Total EA (Transfer to WH06)]]/Table13[[#This Row],[UoM]] -> 120 | G50: =Table13[[#This Row],[Total EA (Transfer to WH06)]]/Table13[[#This Row],[BOX]] -> 5 | I50: =Table13[[#This Row],[Sellable Unit/Set/box to ship]]/Table13[[#This Row],[Box to pull]] -> 24 | J50: =IF(ISNUMBER(SEARCH("FNSKU",K50)),"Labeling","") | K50: =VLOOKUP(Table13[[#This Row],[SKU]],Instruction!A:F,6,0) -> Apply outer box/case label accordingly to match item# (Cover all existing barcodes on the box/case) | L50: =VLOOKUP(Table13[[#This Row],[SKU]],Instruction!A:G,7,0) -> 0 | M50: =VLOOKUP(Table13[[#This Row],[ASIN]],'[4]2024'!$A:$AB,28,0) -> No Supplies | N50: =VLOOKUP(Table13[[#This Row],[SKU]],Data1!A:C,3,0) -> 1 | O50: =VLOOKUP(Table13[[#This Row],[Item '#]],Data2!A:D,4,0) -> 24 | P50: =VLOOKUP(Table13[[#This Row],[Item '#]],Data2!A:D,3,0) -> 288 | Q50: 120 | R50: =VLOOKUP(Table13[[#This Row],[Item '#]],[3]Sheet1!$B:$D,3,0) -> 24371
A51: 540-EACH | B51: B0BCM2D62W | C51: X003GYFQHF | D51: =VLOOKUP(Table13[[#This Row],[SKU]],Data1!A:B,2,0) -> 540 | E51: =Table13[[#This Row],[UoM]]*Table13[[#This Row],[Recommended Replenishment Qty]] -> 48 | F51: =Table13[[#This Row],[Total EA (Transfer to WH06)]]/Table13[[#This Row],[UoM]] -> 48 | H51: =Table13[[#This Row],[Total EA (Transfer to WH06)]]/Table13[[#This Row],[CASE]] -> 1 | I51: =Table13[[#This Row],[Sellable Unit/Set/box to ship]]/Table13[[#This Row],[Case to pull]] -> 48 | J51: =IF(ISNUMBER(SEARCH("FNSKU",K51)),"Labeling","") -> Labeling | K51: =VLOOKUP(Table13[[#This Row],[SKU]],Instruction!A:F,6,0) -> • Use FNSKU to label each item (cover barcode). Apply outer box/case label accordingly to match item# (Cover all existing barcodes on the box/case) | L51: =VLOOKUP(Table13[[#This Row],[SKU]],Instruction!A:G,7,0) -> 0 | M51: =VLOOKUP(Table13[[#This Row],[ASIN]],'[4]2024'!$A:$AB,28,0) -> No Supplies | N51: =VLOOKUP(Table13[[#This Row],[SKU]],Data1!A:C,3,0) -> 1 | O51: =VLOOKUP(Table13[[#This Row],[Item '#]],Data2!A:D,4,0) -> 0 | P51: =VLOOKUP(Table13[[#This Row],[Item '#]],Data2!A:D,3,0) -> 48 | Q51: 48 | R51: =VLOOKUP(Table13[[#This Row],[Item '#]],[3]Sheet1!$B:$D,3,0) -> 9965
A52: 229-EACH | B52: B003BUJXSQ | C52: B003BUJXSQ | D52: =VLOOKUP(Table13[[#This Row],[SKU]],Data1!A:B,2,0) -> 229 | E52: =Table13[[#This Row],[UoM]]*Table13[[#This Row],[Recommended Replenishment Qty]] -> 144 | F52: =Table13[[#This Row],[Total EA (Transfer to WH06)]]/Table13[[#This Row],[UoM]] -> 144 | H52: =Table13[[#This Row],[Total EA (Transfer to WH06)]]/Table13[[#This Row],[CASE]] -> 1 | I52: =Table13[[#This Row],[Sellable Unit/Set/box to ship]]/Table13[[#This Row],[Case to pull]] -> 144 | J52: =IF(ISNUMBER(SEARCH("FNSKU",K52)),"Labeling","") | K52: =VLOOKUP(Table13[[#This Row],[SKU]],Instruction!A:F,6,0) -> Apply outer box/case label accordingly to match item# (Cover all existing barcodes on the box/case) | L52: =VLOOKUP(Table13[[#This Row],[SKU]],Instruction!A:G,7,0) -> 0 | M52: =VLOOKUP(Table13[[#This Row],[ASIN]],'[4]2024'!$A:$AB,28,0) -> No Supplies | N52: =VLOOKUP(Table13[[#This Row],[SKU]],Data1!A:C,3,0) -> 1 | O52: =VLOOKUP(Table13[[#This Row],[Item '#]],Data2!A:D,4,0) -> 24 | P52: =VLOOKUP(Table13[[#This Row],[Item '#]],Data2!A:D,3,0) -> 144 | Q52: 144 | R52: =VLOOKUP(Table13[[#This Row],[Item '#]],[3]Sheet1!$B:$D,3,0) -> 24531
A53: 834-EACH | B53: B0D7RN1FV3 | C53: B0D7RN1FV3 | D53: =VLOOKUP(Table13[[#This Row],[SKU]],Data1!A:B,2,0) -> 834 | E53: =Table13[[#This Row],[UoM]]*Table13[[#This Row],[Recommended Replenishment Qty]] -> 72 | F53: =Table13[[#This Row],[Total EA (Transfer to WH06)]]/Table13[[#This Row],[UoM]] -> 72 | H53: =Table13[[#This Row],[Total EA (Transfer to WH06)]]/Table13[[#This Row],[CASE]] -> 3 | I53: =Table13[[#This Row],[Sellable Unit/Set/box to ship]]/Table13[[#This Row],[Case to pull]] -> 24 | J53: =IF(ISNUMBER(SEARCH("FNSKU",K53)),"Labeling","") | K53: =VLOOKUP(Table13[[#This Row],[SKU]],Instruction!A:F,6,0) -> Apply outer box/case label accordingly to match item# (Cover all existing barcodes on the box/case) | L53: =VLOOKUP(Table13[[#This Row],[SKU]],Instruction!A:G,7,0) -> 0 | M53: =VLOOKUP(Table13[[#This Row],[ASIN]],'[4]2024'!$A:$AB,28,0) -> #N/A | N53: =VLOOKUP(Table13[[#This Row],[SKU]],Data1!A:C,3,0) -> 1 | O53: =VLOOKUP(Table13[[#This Row],[Item '#]],Data2!A:D,4,0) -> 0 | P53: =VLOOKUP(Table13[[#This Row],[Item '#]],Data2!A:D,3,0) -> 24 | Q53: 72 | R53: =VLOOKUP(Table13[[#This Row],[Item '#]],[3]Sheet1!$B:$D,3,0) -> 17524
A54: 4121-EACH | B54: B07Q713Y6M | C54: X003SBSJAR | D54: =VLOOKUP(Table13[[#This Row],[SKU]],Data1!A:B,2,0) -> 4121 | E54: =Table13[[#This Row],[UoM]]*Table13[[#This Row],[Recommended Replenishment Qty]] -> 276 | F54: =Table13[[#This Row],[Total EA (Transfer to WH06)]]/Table13[[#This Row],[UoM]] -> 276 | H54: =Table13[[#This Row],[Total EA (Transfer to WH06)]]/Table13[[#This Row],[CASE]] -> 23 | I54: =Table13[[#This Row],[Sellable Unit/Set/box to ship]]/Table13[[#This Row],[Case to pull]] -> 12 | J54: =IF(ISNUMBER(SEARCH("FNSKU",K54)),"Labeling","") -> Labeling | K54: =VLOOKUP(Table13[[#This Row],[SKU]],Instruction!A:F,6,0) -> • Use FNSKU to label each item (cover barcode). Apply outer box/case label accordingly to match item# (Cover all existing barcodes on the box/case) | L54: =VLOOKUP(Table13[[#This Row],[SKU]],Instruction!A:G,7,0) -> 0 | M54: =VLOOKUP(Table13[[#This Row],[ASIN]],'[4]2024'!$A:$AB,28,0) -> No Supplies | N54: =VLOOKUP(Table13[[#This Row],[SKU]],Data1!A:C,3,0) -> 1 | O54: =VLOOKUP(Table13[[#This Row],[Item '#]],Data2!A:D,4,0) -> 0 | P54: =VLOOKUP(Table13[[#This Row],[Item '#]],Data2!A:D,3,0) -> 12 | Q54: 276 | R54: =VLOOKUP(Table13[[#This Row],[Item '#]],[3]Sheet1!$B:$D,3,0) -> 4113
A55: 5011-EACH | B55: B001BO40DC | C55: B001BO40DC | D55: =VLOOKUP(Table13[[#This Row],[SKU]],Data1!A:B,2,0) -> 5011 | E55: =Table13[[#This Row],[UoM]]*Table13[[#This Row],[Recommended Replenishment Qty]] -> 300 | F55: =Table13[[#This Row],[Total EA (Transfer to WH06)]]/Table13[[#This Row],[UoM]] -> 300 | H55: =Table13[[#This Row],[Total EA (Transfer to WH06)]]/Table13[[#This Row],[CASE]] -> 6 | I55: =Table13[[#This Row],[Sellable Unit/Set/box to ship]]/Table13[[#This Row],[Case to pull]] -> 50 | J55: =IF(ISNUMBER(SEARCH("FNSKU",K55)),"Labeling","") -> Labeling | K55: =VLOOKUP(Table13[[#This Row],[SKU]],Instruction!A:F,6,0) -> • Use FNSKU to label each item (cover barcode). Apply outer box/case label accordingly to match item# (Cover all existing barcodes on the box/case) | L55: =VLOOKUP(Table13[[#This Row],[SKU]],Instruction!A:G,7,0) -> 0 | M55: =VLOOKUP(Table13[[#This Row],[ASIN]],'[4]2024'!$A:$AB,28,0) -> No Supplies | N55: =VLOOKUP(Table13[[#This Row],[SKU]],Data1!A:C,3,0) -> 1 | O55: =VLOOKUP(Table13[[#This Row],[Item '#]],Data2!A:D,4,0) -> 0 | P55: =VLOOKUP(Table13[[#This Row],[Item '#]],Data2!A:D,3,0) -> 50 | Q55: 300 | R55: =VLOOKUP(Table13[[#This Row],[Item '#]],[3]Sheet1!$B:$D,3,0) -> 13663
A56: 2236-EACH | B56: B08FF6RL8X | C56: B08FF6RL8X | D56: =VLOOKUP(Table13[[#This Row],[SKU]],Data1!A:B,2,0) -> 2236 | E56: =Table13[[#This Row],[UoM]]*Table13[[#This Row],[Recommended Replenishment Qty]] -> 288 | F56: =Table13[[#This Row],[Total EA (Transfer to WH06)]]/Table13[[#This Row],[UoM]] -> 288 | H56: =Table13[[#This Row],[Total EA (Transfer to WH06)]]/Table13[[#This Row],[CASE]] -> 12 | I56: =Table13[[#This Row],[Sellable Unit/Set/box to ship]]/Table13[[#This Row],[Case to pull]] -> 24 | J56: =IF(ISNUMBER(SEARCH("FNSKU",K56)),"Labeling","") | K56: =VLOOKUP(Table13[[#This Row],[SKU]],Instruction!A:F,6,0) -> Apply outer box/case label accordingly to match item# (Cover all existing barcodes on the box/case) | L56: =VLOOKUP(Table13[[#This Row],[SKU]],Instruction!A:G,7,0) -> 0 | M56: =VLOOKUP(Table13[[#This Row],[ASIN]],'[4]2024'!$A:$AB,28,0) -> No Supplies | N56: =VLOOKUP(Table13[[#This Row],[SKU]],Data1!A:C,3,0) -> 1 | O56: =VLOOKUP(Table13[[#This Row],[Item '#]],Data2!A:D,4,0) -> 0 | P56: =VLOOKUP(Table13[[#This Row],[Item '#]],Data2!A:D,3,0) -> 24 | Q56: 288 | R56: =VLOOKUP(Table13[[#This Row],[Item '#]],[3]Sheet1!$B:$D,3,0) -> 10509
A57: 552-EACH | B57: B07T1JYHZC | C57: B07T1JYHZC | D57: =VLOOKUP(Table13[[#This Row],[SKU]],Data1!A:B,2,0) -> 552 | E57: =Table13[[#This Row],[UoM]]*Table13[[#This Row],[Recommended Replenishment Qty]] -> 180 | F57: =Table13[[#This Row],[Total EA (Transfer to WH06)]]/Table13[[#This Row],[UoM]] -> 180 | H57: =Table13[[#This Row],[Total EA (Transfer to WH06)]]/Table13[[#This Row],[CASE]] -> 5 | I57: =Table13[[#This Row],[Sellable Unit/Set/box to ship]]/Table13[[#This Row],[Case to pull]] -> 36 | J57: =IF(ISNUMBER(SEARCH("FNSKU",K57)),"Labeling","") | K57: =VLOOKUP(Table13[[#This Row],[SKU]],Instruction!A:F,6,0) -> Apply outer box/case label accordingly to match item# (Cover all existing barcodes on the box/case) | L57: =VLOOKUP(Table13[[#This Row],[SKU]],Instruction!A:G,7,0) -> 0 | M57: =VLOOKUP(Table13[[#This Row],[ASIN]],'[4]2024'!$A:$AB,28,0) -> No Supplies | N57: =VLOOKUP(Table13[[#This Row],[SKU]],Data1!A:C,3,0) -> 1 | O57: =VLOOKUP(Table13[[#This Row],[Item '#]],Data2!A:D,4,0) -> 0 | P57: =VLOOKUP(Table13[[#This Row],[Item '#]],Data2!A:D,3,0) -> 36 | Q57: 180 | R57: =VLOOKUP(Table13[[#This Row],[Item '#]],[3]Sheet1!$B:$D,3,0) -> 17493
A58: 41166-EACH-1 | B58: B09MDRGNCP | C58: B09MDRGNCP | D58: =VLOOKUP(Table13[[#This Row],[SKU]],Data1!A:B,2,0) -> 41166 | E58: =Table13[[#This Row],[UoM]]*Table13[[#This Row],[Recommended Replenishment Qty]] -> 513 | F58: =Table13[[#This Row],[Total EA (Transfer to WH06)]]/Table13[[#This Row],[UoM]] -> 513 | H58: =Table13[[#This Row],[Total EA (Transfer to WH06)]]/Table13[[#This Row],[CASE]] -> 57 | I58: =Table13[[#This Row],[Sellable Unit/Set/box to ship]]/Table13[[#This Row],[Case to pull]] -> 9 | J58: =IF(ISNUMBER(SEARCH("FNSKU",K58)),"Labeling","") | K58: =VLOOKUP(Table13[[#This Row],[SKU]],Instruction!A:F,6,0) -> • 9 UNITS PER CASE (take out 1 unit from original case) • Apply outer case label accordingly to match item# (Cover all existing barcodes on the case) | L58: =VLOOKUP(Table13[[#This Row],[SKU]],Instruction!A:G,7,0) -> 0 | M58: =VLOOKUP(Table13[[#This Row],[ASIN]],'[4]2024'!$A:$AB,28,0) -> No Supplies | N58: =VLOOKUP(Table13[[#This Row],[SKU]],Data1!A:C,3,0) -> 1 | O58: =VLOOKUP(Table13[[#This Row],[Item '#]],Data2!A:D,4,0) -> 0 | P58: 9 | Q58: 513 | R58: =VLOOKUP(Table13[[#This Row],[Item '#]],[3]Sheet1!$B:$D,3,0) -> 1441
A59: 465-EACH-B | B59: B000BLJEKU | C59: B000BLJEKU | D59: =VLOOKUP(Table13[[#This Row],[SKU]],Data1!A:B,2,0) -> 465 | E59: =Table13[[#This Row],[UoM]]*Table13[[#This Row],[Recommended Replenishment Qty]] -> 336 | F59: =Table13[[#This Row],[Total EA (Transfer to WH06)]]/Table13[[#This Row],[UoM]] -> 336 | H59: =Table13[[#This Row],[Total EA (Transfer to WH06)]]/Table13[[#This Row],[CASE]] -> 7 | I59: =Table13[[#This Row],[Sellable Unit/Set/box to ship]]/Table13[[#This Row],[Case to pull]] -> 48 | J59: =IF(ISNUMBER(SEARCH("FNSKU",K59)),"Labeling","") | K59: =VLOOKUP(Table13[[#This Row],[SKU]],Instruction!A:F,6,0) -> Apply outer box/case label accordingly to match item# (Cover all existing barcodes on the box/case) | L59: =VLOOKUP(Table13[[#This Row],[SKU]],Instruction!A:G,7,0) -> 0 | M59: =VLOOKUP(Table13[[#This Row],[ASIN]],'[4]2024'!$A:$AB,28,0) -> No Supplies | N59: =VLOOKUP(Table13[[#This Row],[SKU]],Data1!A:C,3,0) -> 1 | O59: =VLOOKUP(Table13[[#This Row],[Item '#]],Data2!A:D,4,0) -> 0 | P59: =VLOOKUP(Table13[[#This Row],[Item '#]],Data2!A:D,3,0) -> 48 | Q59: 336 | R59: =VLOOKUP(Table13[[#This Row],[Item '#]],[3]Sheet1!$B:$D,3,0) -> 99911
A60: 5045-EACH | B60: B07S94M6P6 | C60: X003DE6G1X | D60: =VLOOKUP(Table13[[#This Row],[SKU]],Data1!A:B,2,0) -> 5045 | E60: =Table13[[#This Row],[UoM]]*Table13[[#This Row],[Recommended Replenishment Qty]] -> 1008 | F60: =Table13[[#This Row],[Total EA (Transfer to WH06)]]/Table13[[#This Row],[UoM]] -> 1008 | H60: =Table13[[#This Row],[Total EA (Transfer to WH06)]]/Table13[[#This Row],[CASE]] -> 21 | I60: =Table13[[#This Row],[Sellable Unit/Set/box to ship]]/Table13[[#This Row],[Case to pull]] -> 48 | J60: =IF(ISNUMBER(SEARCH("FNSKU",K60)),"Labeling","") -> Labeling | K60: =VLOOKUP(Table13[[#This Row],[SKU]],Instruction!A:F,6,0) -> • Use FNSKU to label each item (cover barcode). Apply outer box/case label accordingly to match item# (Cover all existing barcodes on the box/case) | L60: =VLOOKUP(Table13[[#This Row],[SKU]],Instruction!A:G,7,0) -> 0 | M60: =VLOOKUP(Table13[[#This Row],[ASIN]],'[4]2024'!$A:$AB,28,0) -> No Supplies | N60: =VLOOKUP(Table13[[#This Row],[SKU]],Data1!A:C,3,0) -> 1 | O60: =VLOOKUP(Table13[[#This Row],[Item '#]],Data2!A:D,4,0) -> 0 | P60: =VLOOKUP(Table13[[#This Row],[Item '#]],Data2!A:D,3,0) -> 48 | Q60: 1008 | R60: =VLOOKUP(Table13[[#This Row],[Item '#]],[3]Sheet1!$B:$D,3,0) -> 27
A61: 4104-EACH | B61: B07Q97R8X9 | C61: X003SC1YCL | D61: =VLOOKUP(Table13[[#This Row],[SKU]],Data1!A:B,2,0) -> 4104 | E61: =Table13[[#This Row],[UoM]]*Table13[[#This Row],[Recommended Replenishment Qty]] -> 204 | F61: =Table13[[#This Row],[Total EA (Transfer to WH06)]]/Table13[[#This Row],[UoM]] -> 204 | H61: =Table13[[#This Row],[Total EA (Transfer to WH06)]]/Table13[[#This Row],[CASE]] -> 17 | I61: =Table13[[#This Row],[Sellable Unit/Set/box to ship]]/Table13[[#This Row],[Case to pull]] -> 12 | J61: =IF(ISNUMBER(SEARCH("FNSKU",K61)),"Labeling","") -> Labeling | K61: =VLOOKUP(Table13[[#This Row],[SKU]],Instruction!A:F,6,0) -> • Use FNSKU to label each item (cover barcode). Apply outer box/case label accordingly to match item# (Cover all existing barcodes on the box/case) | L61: =VLOOKUP(Table13[[#This Row],[SKU]],Instruction!A:G,7,0) -> 0 | M61: =VLOOKUP(Table13[[#This Row],[ASIN]],'[4]2024'!$A:$AB,28,0) -> No Supplies | N61: =VLOOKUP(Table13[[#This Row],[SKU]],Data1!A:C,3,0) -> 1 | O61: =VLOOKUP(Table13[[#This Row],[Item '#]],Data2!A:D,4,0) -> 0 | P61: =VLOOKUP(Table13[[#This Row],[Item '#]],Data2!A:D,3,0) -> 12 | Q61: 204 | R61: =VLOOKUP(Table13[[#This Row],[Item '#]],[3]Sheet1!$B:$D,3,0) -> 7097
A62: 4120-EACH | B62: B07Q713R9G | C62: X003SC97MP | D62: =VLOOKUP(Table13[[#This Row],[SKU]],Data1!A:B,2,0) -> 4120 | E62: =Table13[[#This Row],[UoM]]*Table13[[#This Row],[Recommended Replenishment Qty]] -> 120 | F62: =Table13[[#This Row],[Total EA (Transfer to WH06)]]/Table13[[#This Row],[UoM]] -> 120 | H62: =Table13[[#This Row],[Total EA (Transfer to WH06)]]/Table13[[#This Row],[CASE]] -> 10 | I62: =Table13[[#This Row],[Sellable Unit/Set/box to ship]]/Table13[[#This Row],[Case to pull]] -> 12 | J62: =IF(ISNUMBER(SEARCH("FNSKU",K62)),"Labeling","") -> Labeling | K62: =VLOOKUP(Table13[[#This Row],[SKU]],Instruction!A:F,6,0) -> • Use FNSKU to label each item (cover barcode). Apply outer box/case label accordingly to match item# (Cover all existing barcodes on the box/case) | L62: =VLOOKUP(Table13[[#This Row],[SKU]],Instruction!A:G,7,0) -> 0 | M62: =VLOOKUP(Table13[[#This Row],[ASIN]],'[4]2024'!$A:$AB,28,0) -> No Supplies | N62: =VLOOKUP(Table13[[#This Row],[SKU]],Data1!A:C,3,0) -> 1 | O62: =VLOOKUP(Table13[[#This Row],[Item '#]],Data2!A:D,4,0) -> 0 | P62: =VLOOKUP(Table13[[#This Row],[Item '#]],Data2!A:D,3,0) -> 12 | Q62: 120 | R62: =VLOOKUP(Table13[[#This Row],[Item '#]],[3]Sheet1!$B:$D,3,0) -> 3798
A63: 212-EACH | B63: B07RLPFK92 | C63: X003TJ1SWJ | D63: =VLOOKUP(Table13[[#This Row],[SKU]],Data1!A:B,2,0) -> 212 | E63: =Table13[[#This Row],[UoM]]*Table13[[#This Row],[Recommended Replenishment Qty]] -> 720 | F63: =Table13[[#This Row],[Total EA (Transfer to WH06)]]/Table13[[#This Row],[UoM]] -> 720 | H63: =Table13[[#This Row],[Total EA (Transfer to WH06)]]/Table13[[#This Row],[CASE]] -> 5 | I63: =Table13[[#This Row],[Sellable Unit/Set/box to ship]]/Table13[[#This Row],[Case to pull]] -> 144 | J63: =IF(ISNUMBER(SEARCH("FNSKU",K63)),"Labeling","") -> Labeling | K63: =VLOOKUP(Table13[[#This Row],[SKU]],Instruction!A:F,6,0) -> • Use FNSKU to label each item (cover barcode). Apply outer box/case label accordingly to match item# (Cover all existing barcodes on the box/case) | L63: =VLOOKUP(Table13[[#This Row],[SKU]],Instruction!A:G,7,0) -> 0 | M63: =VLOOKUP(Table13[[#This Row],[ASIN]],'[4]2024'!$A:$AB,28,0) -> No Supplies | N63: =VLOOKUP(Table13[[#This Row],[SKU]],Data1!A:C,3,0) -> 1 | O63: =VLOOKUP(Table13[[#This Row],[Item '#]],Data2!A:D,4,0) -> 24 | P63: =VLOOKUP(Table13[[#This Row],[Item '#]],Data2!A:D,3,0) -> 144 | Q63: 720 | R63: =VLOOKUP(Table13[[#This Row],[Item '#]],[3]Sheet1!$B:$D,3,0) -> 12261
A64: 903-EACH | B64: B0018ML7KG | C64: B0018ML7KG | D64: =VLOOKUP(Table13[[#This Row],[SKU]],Data1!A:B,2,0) -> 903 | E64: =Table13[[#This Row],[UoM]]*Table13[[#This Row],[Recommended Replenishment Qty]] -> 48 | F64: =Table13[[#This Row],[Total EA (Transfer to WH06)]]/Table13[[#This Row],[UoM]] -> 48 | G64: =Table13[[#This Row],[Total EA (Transfer to WH06)]]/Table13[[#This Row],[BOX]] -> 2 | I64: =Table13[[#This Row],[Sellable Unit/Set/box to ship]]/Table13[[#This Row],[Box to pull]] -> 24 | J64: =IF(ISNUMBER(SEARCH("FNSKU",K64)),"Labeling","") | K64: =VLOOKUP(Table13[[#This Row],[SKU]],Instruction!A:F,6,0) -> Apply outer box/case label accordingly to match item# (Cover all existing barcodes on the box/case) | L64: =VLOOKUP(Table13[[#This Row],[SKU]],Instruction!A:G,7,0) -> 0 | M64: =VLOOKUP(Table13[[#This Row],[ASIN]],'[4]2024'!$A:$AB,28,0) -> No Supplies | N64: =VLOOKUP(Table13[[#This Row],[SKU]],Data1!A:C,3,0) -> 1 | O64: =VLOOKUP(Table13[[#This Row],[Item '#]],Data2!A:D,4,0) -> 24 | P64: =VLOOKUP(Table13[[#This Row],[Item '#]],Data2!A:D,3,0) -> 144 | Q64: 48 | R64: =VLOOKUP(Table13[[#This Row],[Item '#]],[3]Sheet1!$B:$D,3,0) -> 27644
A65: 3161-EACH | B65: B08FK78Z2B | C65: X003BXWZTX | D65: =VLOOKUP(Table13[[#This Row],[SKU]],Data1!A:B,2,0) -> 3161 | E65: =Table13[[#This Row],[UoM]]*Table13[[#This Row],[Recommended Replenishment Qty]] -> 108 | F65: =Table13[[#This Row],[Total EA (Transfer to WH06)]]/Table13[[#This Row],[UoM]] -> 108 | H65: =Table13[[#This Row],[Total EA (Transfer to WH06)]]/Table13[[#This Row],[CASE]] -> 9 | I65: =Table13[[#This Row],[Sellable Unit/Set/box to ship]]/Table13[[#This Row],[Case to pull]] -> 12 | J65: =IF(ISNUMBER(SEARCH("FNSKU",K65)),"Labeling","") -> Labeling | K65: =VLOOKUP(Table13[[#This Row],[SKU]],Instruction!A:F,6,0) -> • Use FNSKU to label each item (cover barcode). Apply outer box/case label accordingly to match item# (Cover all existing barcodes on the box/case) | L65: =VLOOKUP(Table13[[#This Row],[SKU]],Instruction!A:G,7,0) -> 0 | M65: =VLOOKUP(Table13[[#This Row],[ASIN]],'[4]2024'!$A:$AB,28,0) -> No Supplies | N65: =VLOOKUP(Table13[[#This Row],[SKU]],Data1!A:C,3,0) -> 1 | O65: =VLOOKUP(Table13[[#This Row],[Item '#]],Data2!A:D,4,0) -> 0 | P65: =VLOOKUP(Table13[[#This Row],[Item '#]],Data2!A:D,3,0) -> 12 | Q65: 108 | R65: =VLOOKUP(Table13[[#This Row],[Item '#]],[3]Sheet1!$B:$D,3,0) -> 20459
A66: 465-EACH-1 | B66: B07T766984 | C66: X003T9Y59H | D66: =VLOOKUP(Table13[[#This Row],[SKU]],Data1!A:B,2,0) -> 465 | E66: =Table13[[#This Row],[UoM]]*Table13[[#This Row],[Recommended Replenishment Qty]] -> 144 | F66: =Table13[[#This Row],[Total EA (Transfer to WH06)]]/Table13[[#This Row],[UoM]] -> 144 | H66: =Table13[[#This Row],[Total EA (Transfer to WH06)]]/Table13[[#This Row],[CASE]] -> 3 | I66: =Table13[[#This Row],[Sellable Unit/Set/box to ship]]/Table13[[#This Row],[Case to pull]] -> 48 | J66: =IF(ISNUMBER(SEARCH("FNSKU",K66)),"Labeling","") -> Labeling | K66: =VLOOKUP(Table13[[#This Row],[SKU]],Instruction!A:F,6,0) -> • Use FNSKU to label each item (cover barcode). Apply outer box/case label accordingly to match item# (Cover all existing barcodes on the box/case) | L66: =VLOOKUP(Table13[[#This Row],[SKU]],Instruction!A:G,7,0) -> 0 | M66: =VLOOKUP(Table13[[#This Row],[ASIN]],'[4]2024'!$A:$AB,28,0) -> No Supplies | N66: =VLOOKUP(Table13[[#This Row],[SKU]],Data1!A:C,3,0) -> 1 | O66: =VLOOKUP(Table13[[#This Row],[Item '#]],Data2!A:D,4,0) -> 0 | P66: =VLOOKUP(Table13[[#This Row],[Item '#]],Data2!A:D,3,0) -> 48 | Q66: 144 | R66: =VLOOKUP(Table13[[#This Row],[Item '#]],[3]Sheet1!$B:$D,3,0) -> 99911
A67: 2043-EACH-1 | B67: B00J8IK3YI | C67: X004DMV5X3 | D67: =VLOOKUP(Table13[[#This Row],[SKU]],Data1!A:B,2,0) -> 2043 | E67: =Table13[[#This Row],[UoM]]*Table13[[#This Row],[Recommended Replenishment Qty]] -> 96 | F67: =Table13[[#This Row],[Total EA (Transfer to WH06)]]/Table13[[#This Row],[UoM]] -> 96 | G67: =Table13[[#This Row],[Total EA (Transfer to WH06)]]/Table13[[#This Row],[BOX]] -> 4 | I67: =Table13[[#This Row],[Sellable Unit/Set/box to ship]]/Table13[[#This Row],[Box to pull]] -> 24 | J67: =IF(ISNUMBER(SEARCH("FNSKU",K67)),"Labeling","") -> Labeling | K67: =VLOOKUP(Table13[[#This Row],[SKU]],Instruction!A:F,6,0) -> • Use FNSKU to label each item (cover barcode). Apply outer case label accordingly to match item# (Cover all existing barcodes on the case) | L67: =VLOOKUP(Table13[[#This Row],[SKU]],Instruction!A:G,7,0) -> 0 | M67: =VLOOKUP(Table13[[#This Row],[ASIN]],'[4]2024'!$A:$AB,28,0) -> No Supplies | N67: =VLOOKUP(Table13[[#This Row],[SKU]],Data1!A:C,3,0) -> 1 | O67: =VLOOKUP(Table13[[#This Row],[Item '#]],Data2!A:D,4,0) -> 24 | P67: =VLOOKUP(Table13[[#This Row],[Item '#]],Data2!A:D,3,0) -> 144 | Q67: 96 | R67: =VLOOKUP(Table13[[#This Row],[Item '#]],[3]Sheet1!$B:$D,3,0) -> 29460
A68: 5081-EACH | B68: B094XLGQL9 | C68: X0043UZ5ZJ | D68: =VLOOKUP(Table13[[#This Row],[SKU]],Data1!A:B,2,0) -> 5081 | E68: =Table13[[#This Row],[UoM]]*Table13[[#This Row],[Recommended Replenishment Qty]] -> 96 | F68: =Table13[[#This Row],[Total EA (Transfer to WH06)]]/Table13[[#This Row],[UoM]] -> 96 | H68: =Table13[[#This Row],[Total EA (Transfer to WH06)]]/Table13[[#This Row],[CASE]] -> 8 | I68: =Table13[[#This Row],[Sellable Unit/Set/box to ship]]/Table13[[#This Row],[Case to pull]] -> 12 | J68: =IF(ISNUMBER(SEARCH("FNSKU",K68)),"Labeling","") -> Labeling | K68: =VLOOKUP(Table13[[#This Row],[SKU]],Instruction!A:F,6,0) -> • Use FNSKU to label each item (cover barcode). Apply outer case label accordingly to match item# (Cover all existing barcodes on the case) | L68: =VLOOKUP(Table13[[#This Row],[SKU]],Instruction!A:G,7,0) -> 0 | M68: =VLOOKUP(Table13[[#This Row],[ASIN]],'[4]2024'!$A:$AB,28,0) -> No Supplies | N68: =VLOOKUP(Table13[[#This Row],[SKU]],Data1!A:C,3,0) -> 1 | O68: =VLOOKUP(Table13[[#This Row],[Item '#]],Data2!A:D,4,0) -> 0 | P68: =VLOOKUP(Table13[[#This Row],[Item '#]],Data2!A:D,3,0) -> 12 | Q68: 96 | R68: =VLOOKUP(Table13[[#This Row],[Item '#]],[3]Sheet1!$B:$D,3,0) -> 1995
A69: 4127-EACH | B69: B07Q8XTMXF | C69: X003SC97MF | D69: =VLOOKUP(Table13[[#This Row],[SKU]],Data1!A:B,2,0) -> 4127 | E69: =Table13[[#This Row],[UoM]]*Table13[[#This Row],[Recommended Replenishment Qty]] -> 504 | F69: =Table13[[#This Row],[Total EA (Transfer to WH06)]]/Table13[[#This Row],[UoM]] -> 504 | H69: =Table13[[#This Row],[Total EA (Transfer to WH06)]]/Table13[[#This Row],[CASE]] -> 42 | I69: =Table13[[#This Row],[Sellable Unit/Set/box to ship]]/Table13[[#This Row],[Case to pull]] -> 12 | J69: =IF(ISNUMBER(SEARCH("FNSKU",K69)),"Labeling","") -> Labeling | K69: =VLOOKUP(Table13[[#This Row],[SKU]],Instruction!A:F,6,0) -> • Use FNSKU to label each item (cover barcode). Apply outer box/case label accordingly to match item# (Cover all existing barcodes on the box/case) | L69: =VLOOKUP(Table13[[#This Row],[SKU]],Instruction!A:G,7,0) -> 0 | M69: =VLOOKUP(Table13[[#This Row],[ASIN]],'[4]2024'!$A:$AB,28,0) -> No Supplies | N69: =VLOOKUP(Table13[[#This Row],[SKU]],Data1!A:C,3,0) -> 1 | O69: =VLOOKUP(Table13[[#This Row],[Item '#]],Data2!A:D,4,0) -> 0 | P69: =VLOOKUP(Table13[[#This Row],[Item '#]],Data2!A:D,3,0) -> 12 | Q69: 504 | R69: =VLOOKUP(Table13[[#This Row],[Item '#]],[3]Sheet1!$B:$D,3,0) -> 9689
A70: 609-EACH | B70: B00ESWRD10 | C70: B00ESWRD10 | D70: =VLOOKUP(Table13[[#This Row],[SKU]],Data1!A:B,2,0) -> 609 | E70: =Table13[[#This Row],[UoM]]*Table13[[#This Row],[Recommended Replenishment Qty]] -> 648 | F70: =Table13[[#This Row],[Total EA (Transfer to WH06)]]/Table13[[#This Row],[UoM]] -> 648 | H70: =Table13[[#This Row],[Total EA (Transfer to WH06)]]/Table13[[#This Row],[CASE]] -> 9 | I70: =Table13[[#This Row],[Sellable Unit/Set/box to ship]]/Table13[[#This Row],[Case to pull]] -> 72 | J70: =IF(ISNUMBER(SEARCH("FNSKU",K70)),"Labeling","") | K70: =VLOOKUP(Table13[[#This Row],[SKU]],Instruction!A:F,6,0) -> Apply outer box/case label accordingly to match item# (Cover all existing barcodes on the box/case) | L70: =VLOOKUP(Table13[[#This Row],[SKU]],Instruction!A:G,7,0) -> 0 | M70: =VLOOKUP(Table13[[#This Row],[ASIN]],'[4]2024'!$A:$AB,28,0) -> No Supplies | N70: =VLOOKUP(Table13[[#This Row],[SKU]],Data1!A:C,3,0) -> 1 | O70: =VLOOKUP(Table13[[#This Row],[Item '#]],Data2!A:D,4,0) -> 24 | P70: =VLOOKUP(Table13[[#This Row],[Item '#]],Data2!A:D,3,0) -> 72 | Q70: 648 | R70: =VLOOKUP(Table13[[#This Row],[Item '#]],[3]Sheet1!$B:$D,3,0) -> 43572
A71: 2044-EACH | B71: B075VXY8MQ | C71: B075VXY8MQ | D71: =VLOOKUP(Table13[[#This Row],[SKU]],Data1!A:B,2,0) -> 2044 | E71: =Table13[[#This Row],[UoM]]*Table13[[#This Row],[Recommended Replenishment Qty]] -> 912 | F71: =Table13[[#This Row],[Total EA (Transfer to WH06)]]/Table13[[#This Row],[UoM]] -> 912 | H71: =Table13[[#This Row],[Total EA (Transfer to WH06)]]/Table13[[#This Row],[CASE]] -> 19 | I71: =Table13[[#This Row],[Sellable Unit/Set/box to ship]]/Table13[[#This Row],[Case to pull]] -> 48 | J71: =IF(ISNUMBER(SEARCH("FNSKU",K71)),"Labeling","") | K71: =VLOOKUP(Table13[[#This Row],[SKU]],Instruction!A:F,6,0) -> Apply outer case label accordingly to match item# (Cover all existing barcodes on the case) | L71: =VLOOKUP(Table13[[#This Row],[SKU]],Instruction!A:G,7,0) -> 0 | M71: =VLOOKUP(Table13[[#This Row],[ASIN]],'[4]2024'!$A:$AB,28,0) -> No Supplies | N71: =VLOOKUP(Table13[[#This Row],[SKU]],Data1!A:C,3,0) -> 1 | O71: =VLOOKUP(Table13[[#This Row],[Item '#]],Data2!A:D,4,0) -> 0 | P71: =VLOOKUP(Table13[[#This Row],[Item '#]],Data2!A:D,3,0) -> 48 | Q71: 912 | R71: =VLOOKUP(Table13[[#This Row],[Item '#]],[3]Sheet1!$B:$D,3,0) -> 6487
A72: 5174-EACH | B72: B07TGB6SPM | C72: B07TGB6SPM | D72: =VLOOKUP(Table13[[#This Row],[SKU]],Data1!A:B,2,0) -> 5174 | E72: =Table13[[#This Row],[UoM]]*Table13[[#This Row],[Recommended Replenishment Qty]] -> 24 | F72: =Table13[[#This Row],[Total EA (Transfer to WH06)]]/Table13[[#This Row],[UoM]] -> 24 | G72: =Table13[[#This Row],[Total EA (Transfer to WH06)]]/Table13[[#This Row],[BOX]] -> 1 | I72: =Table13[[#This Row],[Sellable Unit/Set/box to ship]]/Table13[[#This Row],[Box to pull]] -> 24 | J72: =IF(ISNUMBER(SEARCH("FNSKU",K72)),"Labeling","") | K72: =VLOOKUP(Table13[[#This Row],[SKU]],Instruction!A:F,6,0) -> Apply outer case label accordingly to match item# (Cover all existing barcodes on the case) | L72: =VLOOKUP(Table13[[#This Row],[SKU]],Instruction!A:G,7,0) -> 0 | M72: =VLOOKUP(Table13[[#This Row],[ASIN]],'[4]2024'!$A:$AB,28,0) -> No Supplies | N72: =VLOOKUP(Table13[[#This Row],[SKU]],Data1!A:C,3,0) -> 1 | O72: =VLOOKUP(Table13[[#This Row],[Item '#]],Data2!A:D,4,0) -> 24 | P72: =VLOOKUP(Table13[[#This Row],[Item '#]],Data2!A:D,3,0) -> 288 | Q72: 24 | R72: =VLOOKUP(Table13[[#This Row],[Item '#]],[3]Sheet1!$B:$D,3,0) -> 12339
A73: 930-EACH | B73: B003BMWQYC | C73: B003BMWQYC | D73: =VLOOKUP(Table13[[#This Row],[SKU]],Data1!A:B,2,0) -> 930 | E73: =Table13[[#This Row],[UoM]]*Table13[[#This Row],[Recommended Replenishment Qty]] -> 96 | F73: =Table13[[#This Row],[Total EA (Transfer to WH06)]]/Table13[[#This Row],[UoM]] -> 96 | G73: =Table13[[#This Row],[Total EA (Transfer to WH06)]]/Table13[[#This Row],[BOX]] -> 4 | I73: =Table13[[#This Row],[Sellable Unit/Set/box to ship]]/Table13[[#This Row],[Box to pull]] -> 24 | J73: =IF(ISNUMBER(SEARCH("FNSKU",K73)),"Labeling","") | K73: =VLOOKUP(Table13[[#This Row],[SKU]],Instruction!A:F,6,0) -> Apply outer case label accordingly to match item# (Cover all existing barcodes on the case) | L73: =VLOOKUP(Table13[[#This Row],[SKU]],Instruction!A:G,7,0) -> 0 | M73: =VLOOKUP(Table13[[#This Row],[ASIN]],'[4]2024'!$A:$AB,28,0) -> No Supplies | N73: =VLOOKUP(Table13[[#This Row],[SKU]],Data1!A:C,3,0) -> 1 | O73: =VLOOKUP(Table13[[#This Row],[Item '#]],Data2!A:D,4,0) -> 24 | P73: =VLOOKUP(Table13[[#This Row],[Item '#]],Data2!A:D,3,0) -> 144 | Q73: 96 | R73: =VLOOKUP(Table13[[#This Row],[Item '#]],[3]Sheet1!$B:$D,3,0) -> 70212
A74: 565-EACH | B74: B0019IKAES | C74: B0019IKAES | D74: =VLOOKUP(Table13[[#This Row],[SKU]],Data1!A:B,2,0) -> 565 | E74: =Table13[[#This Row],[UoM]]*Table13[[#This Row],[Recommended Replenishment Qty]] -> 36 | F74: =Table13[[#This Row],[Total EA (Transfer to WH06)]]/Table13[[#This Row],[UoM]] -> 36 | H74: =Table13[[#This Row],[Total EA (Transfer to WH06)]]/Table13[[#This Row],[CASE]] -> 1 | I74: =Table13[[#This Row],[Sellable Unit/Set/box to ship]]/Table13[[#This Row],[Case to pull]] -> 36 | J74: =IF(ISNUMBER(SEARCH("FNSKU",K74)),"Labeling","") | K74: =VLOOKUP(Table13[[#This Row],[SKU]],Instruction!A:F,6,0) -> Apply outer box/case label accordingly to match item# (Cover all existing barcodes on the box/case) | L74: =VLOOKUP(Table13[[#This Row],[SKU]],Instruction!A:G,7,0) -> 0 | M74: =VLOOKUP(Table13[[#This Row],[ASIN]],'[4]2024'!$A:$AB,28,0) -> No Supplies | N74: =VLOOKUP(Table13[[#This Row],[SKU]],Data1!A:C,3,0) -> 1 | O74: =VLOOKUP(Table13[[#This Row],[Item '#]],Data2!A:D,4,0) -> 0 | P74: =VLOOKUP(Table13[[#This Row],[Item '#]],Data2!A:D,3,0) -> 36 | Q74: 36 | R74: =VLOOKUP(Table13[[#This Row],[Item '#]],[3]Sheet1!$B:$D,3,0) -> 87511
A75: 3171-EACH | B75: B0BP5Q88DW | C75: X0040DP2BL | D75: =VLOOKUP(Table13[[#This Row],[SKU]],Data1!A:B,2,0) -> 3171 | E75: =Table13[[#This Row],[UoM]]*Table13[[#This Row],[Recommended Replenishment Qty]] -> 192 | F75: =Table13[[#This Row],[Total EA (Transfer to WH06)]]/Table13[[#This Row],[UoM]] -> 192 | H75: =Table13[[#This Row],[Total EA (Transfer to WH06)]]/Table13[[#This Row],[CASE]] -> 16 | I75: =Table13[[#This Row],[Sellable Unit/Set/box to ship]]/Table13[[#This Row],[Case to pull]] -> 12 | J75: =IF(ISNUMBER(SEARCH("FNSKU",K75)),"Labeling","") -> Labeling | K75: =VLOOKUP(Table13[[#This Row],[SKU]],Instruction!A:F,6,0) -> • Use FNSKU to label each item (cover barcode). Apply outer case label accordingly to match item# (Cover all existing barcodes on the case) | L75: =VLOOKUP(Table13[[#This Row],[SKU]],Instruction!A:G,7,0) -> 0 | M75: =VLOOKUP(Table13[[#This Row],[ASIN]],'[4]2024'!$A:$AB,28,0) -> No Supplies | N75: =VLOOKUP(Table13[[#This Row],[SKU]],Data1!A:C,3,0) -> 1 | O75: =VLOOKUP(Table13[[#This Row],[Item '#]],Data2!A:D,4,0) -> 0 | P75: =VLOOKUP(Table13[[#This Row],[Item '#]],Data2!A:D,3,0) -> 12 | Q75: 192 | R75: =VLOOKUP(Table13[[#This Row],[Item '#]],[3]Sheet1!$B:$D,3,0) -> 7351
A76: 761-EACH | B76: B0019IHJIS | C76: B0019IHJIS | D76: =VLOOKUP(Table13[[#This Row],[SKU]],Data1!A:B,2,0) -> 761 | E76: =Table13[[#This Row],[UoM]]*Table13[[#This Row],[Recommended Replenishment Qty]] -> 96 | F76: =Table13[[#This Row],[Total EA (Transfer to WH06)]]/Table13[[#This Row],[UoM]] -> 96 | G76: =Table13[[#This Row],[Total EA (Transfer to WH06)]]/Table13[[#This Row],[BOX]] -> 4 | I76: =Table13[[#This Row],[Sellable Unit/Set/box to ship]]/Table13[[#This Row],[Box to pull]] -> 24 | J76: =IF(ISNUMBER(SEARCH("FNSKU",K76)),"Labeling","") | K76: =VLOOKUP(Table13[[#This Row],[SKU]],Instruction!A:F,6,0) -> Apply outer box/case label accordingly to match item# (Cover all existing barcodes on the box/case) | L76: =VLOOKUP(Table13[[#This Row],[SKU]],Instruction!A:G,7,0) -> 0 | M76: =VLOOKUP(Table13[[#This Row],[ASIN]],'[4]2024'!$A:$AB,28,0) -> No Supplies | N76: =VLOOKUP(Table13[[#This Row],[SKU]],Data1!A:C,3,0) -> 1 | O76: =VLOOKUP(Table13[[#This Row],[Item '#]],Data2!A:D,4,0) -> 24 | P76: =VLOOKUP(Table13[[#This Row],[Item '#]],Data2!A:D,3,0) -> 144 | Q76: 96 | R76: =VLOOKUP(Table13[[#This Row],[Item '#]],[3]Sheet1!$B:$D,3,0) -> 133780
